Workbook

Sheet Início
A1: Início — Explorando Galáxias v1.1
A2: Legenda: | B2: Entrada (preencha) | C2: Calculada (automático) | D2: Aviso (texto em vermelho) | E2: Título de bloco | F2: Cabeçalho de coluna | G2: Rótulo da linha | H2: Linha alternada (outro tom) | I2: Não se aplica
A3: Comece por aqui: como usar a ficha, importar no Google Planilhas e o painel de avisos.
A5: Ficha de Personagem — Explorando Galáxias v1.1
A6: Sistema de RPG de mesa no universo de Honkai: Star Rail · autoria: MC Filhos · versão v1.1 · níveis 1 a 20. Ficha automatizada para o Google Planilhas: preencha as células amarelas e o resto se calcula sozinho.
A8: Painel de avisos (automático) — uma linha por aba; zero avisos = ficha conferida
A9: Aba | B9: Avisos | C9: Primeiro aviso
A10: Criação | B10: =SUMPRODUCT((LEN('Criação'!$K$8:$K$10)>0)*1)+(LEN('Criação'!$K$22)>0)*1+SUMPRODUCT((LEN('Criação'!$K$25:$K$28)>0)*1)+(LEN('Criação'!$K$33)>0)*1+SUMPRODUCT((LEN('Criação'!$K$44:$K$51)>0)*1)+(LEN('Criação'!$K$54)>0)*1+(LEN('Criação'!$K$60)>0)*1+(LEN('Criação'!$K$67)>0)*1+SUMPRODUCT((LEN('Criação'!$K$69:$K$73)>0)*1)+SUMPRODUCT((LEN('Criação'!$K$75:$K$82)>0)*1)+SUMPRODUCT((LEN('Criação'!$K$84:$K$88)>0)*1)+(LEN('Criação'!$K$91)>0)*1+SUMPRODUCT((LEN('Criação'!$K$97:$K$99)>0)*1)+SUMPRODUCT((LEN('Criação'!$K$108:$K$111)>0)*1) -> #ERROR! | C10: {=IFERROR(INDEX('Criação'!$K$8:$K$10,MATCH("?*",'Criação'!$K$8:$K$10,0)),IFERROR(INDEX('Criação'!$K$22,MATCH("?*",'Criação'!$K$22,0)),IFERROR(INDEX('Criação'!$K$25:$K$28,MATCH("?*",'Criação'!$K$25:$K$28,0)),IFERROR(INDEX('Criação'!$K$33,MATCH("?*",'Criação'!$K$33,0)),IFERROR(INDEX('Criação'!$K$44:$K$51,MATCH("?*",'Criação'!$K$44:$K$51,0)),IFERROR(INDEX('Criação'!$K$54,MATCH("?*",'Criação'!$K$54,0)),IFERROR(INDEX('Criação'!$K$60,MATCH("?*",'Criação'!$K$60,0)),IFERROR(INDEX('Criação'!$K$67,MATCH("?*",'Criação'!$K$67,0)),IFERROR(INDEX('Criação'!$K$69:$K$73,MATCH("?*",'Criação'!$K$69:$K$73,0)),IFERROR(INDEX('Criação'!$K$75:$K$82,MATCH("?*",'Criação'!$K$75:$K$82,0)),IFERROR(INDEX('Criação'!$K$84:$K$88,MATCH("?*",'Criação'!$K$84:$K$88,0)),IFERROR(INDEX('Criação'!$K$91,MATCH("?*",'Criação'!$K$91,0)),IFERROR(INDEX('Criação'!$K$97:$K$99,MATCH("?*",'Criação'!$K$97:$K$99,0)),IFERROR(INDEX('Criação'!$K$108:$K$111,MATCH("?*",'Criação'!$K$108:$K$111,0)),""))))))))))))))}
A11: Em Jogo | B11: =SUMPRODUCT((LEN('Em Jogo'!$N$2:$N$20)>0)*1) -> #ERROR! | C11: {=IFERROR(INDEX('Em Jogo'!$N$2:$N$20,MATCH("?*",'Em Jogo'!$N$2:$N$20,0)),"")}
A12: Testes | B12: =SUMPRODUCT((LEN(Testes!$K$40:$K$45)>0)*1)+SUMPRODUCT((LEN(Testes!$L$16:$L$20)>0)*1)+SUMPRODUCT((LEN(Testes!$L$22:$L$29)>0)*1)+SUMPRODUCT((LEN(Testes!$L$31:$L$35)>0)*1) -> 0 | C12: {=IFERROR(INDEX(Testes!$K$40:$K$45,MATCH("?*",Testes!$K$40:$K$45,0)),IFERROR(INDEX(Testes!$L$16:$L$20,MATCH("?*",Testes!$L$16:$L$20,0)),IFERROR(INDEX(Testes!$L$22:$L$29,MATCH("?*",Testes!$L$22:$L$29,0)),IFERROR(INDEX(Testes!$L$31:$L$35,MATCH("?*",Testes!$L$31:$L$35,0)),""))))}
A13: Habilidades | B13: =SUMPRODUCT((LEN(Habilidades!$I$12:$I$19)>0)*1)+SUMPRODUCT((LEN(Habilidades!$L$7:$L$8)>0)*1)+(LEN(Habilidades!$L$56)>0)*1 -> 0 | C13: {=IFERROR(INDEX(Habilidades!$I$12:$I$19,MATCH("?*",Habilidades!$I$12:$I$19,0)),IFERROR(INDEX(Habilidades!$L$7:$L$8,MATCH("?*",Habilidades!$L$7:$L$8,0)),IFERROR(INDEX(Habilidades!$L$56,MATCH("?*",Habilidades!$L$56,0)),"")))}
A14: Caminho | B14: =SUMPRODUCT((LEN(Caminho!$K$27:$K$36)>0)*1)+(LEN(Caminho!$K$54)>0)*1+SUMPRODUCT((LEN(Caminho!$K$60:$K$66)>0)*1)+SUMPRODUCT((LEN(Caminho!$K$69:$K$71)>0)*1)+SUMPRODUCT((LEN(Caminho!$K$75:$K$77)>0)*1)+SUMPRODUCT((LEN(Caminho!$K$95:$K$96)>0)*1) -> 0 | C14: {=IFERROR(INDEX(Caminho!$K$27:$K$36,MATCH("?*",Caminho!$K$27:$K$36,0)),IFERROR(INDEX(Caminho!$K$54,MATCH("?*",Caminho!$K$54,0)),IFERROR(INDEX(Caminho!$K$60:$K$66,MATCH("?*",Caminho!$K$60:$K$66,0)),IFERROR(INDEX(Caminho!$K$69:$K$71,MATCH("?*",Caminho!$K$69:$K$71,0)),IFERROR(INDEX(Caminho!$K$75:$K$77,MATCH("?*",Caminho!$K$75:$K$77,0)),IFERROR(INDEX(Caminho!$K$95:$K$96,MATCH("?*",Caminho!$K$95:$K$96,0)),""))))))}
A15: Equipamento | B15: =SUMPRODUCT((LEN(Equipamento!$I$45:$I$47)>0)*1)+(LEN(Equipamento!$K$8)>0)*1+(LEN(Equipamento!$K$21)>0)*1+(LEN(Equipamento!$K$58)>0)*1+SUMPRODUCT((LEN(Equipamento!$K$60:$K$69)>0)*1)+SUMPRODUCT((LEN(Equipamento!$K$71:$K$80)>0)*1)+(LEN(Equipamento!$K$84)>0)*1+SUMPRODUCT((LEN(Equipamento!$K$86:$K$96)>0)*1)+SUMPRODUCT((LEN(Equipamento!$L$19:$L$20)>0)*1)+SUMPRODUCT((LEN(Equipamento!$L$22:$L$23)>0)*1)+SUMPRODUCT((LEN(Equipamento!$L$36:$L$41)>0)*1)+(LEN(Equipamento!$L$48)>0)*1 -> #ERROR! | C15: {=IFERROR(INDEX(Equipamento!$I$45:$I$47,MATCH("?*",Equipamento!$I$45:$I$47,0)),IFERROR(INDEX(Equipamento!$K$8,MATCH("?*",Equipamento!$K$8,0)),IFERROR(INDEX(Equipamento!$K$21,MATCH("?*",Equipamento!$K$21,0)),IFERROR(INDEX(Equipamento!$K$58,MATCH("?*",Equipamento!$K$58,0)),IFERROR(INDEX(Equipamento!$K$60:$K$69,MATCH("?*",Equipamento!$K$60:$K$69,0)),IFERROR(INDEX(Equipamento!$K$71:$K$80,MATCH("?*",Equipamento!$K$71:$K$80,0)),IFERROR(INDEX(Equipamento!$K$84,MATCH("?*",Equipamento!$K$84,0)),IFERROR(INDEX(Equipamento!$K$86:$K$96,MATCH("?*",Equipamento!$K$86:$K$96,0)),IFERROR(INDEX(Equipamento!$L$19:$L$20,MATCH("?*",Equipamento!$L$19:$L$20,0)),IFERROR(INDEX(Equipamento!$L$22:$L$23,MATCH("?*",Equipamento!$L$22:$L$23,0)),IFERROR(INDEX(Equipamento!$L$36:$L$41,MATCH("?*",Equipamento!$L$36:$L$41,0)),IFERROR(INDEX(Equipamento!$L$48,MATCH("?*",Equipamento!$L$48,0)),""))))))))))))}
A16: Progressão | B16: =SUMPRODUCT((LEN('Progressão'!$H$57:$H$62)>0)*1)+SUMPRODUCT((LEN('Progressão'!$I$67:$I$70)>0)*1) -> 0 | C16: {=IFERROR(INDEX('Progressão'!$H$57:$H$62,MATCH("?*",'Progressão'!$H$57:$H$62,0)),IFERROR(INDEX('Progressão'!$I$67:$I$70,MATCH("?*",'Progressão'!$I$67:$I$70,0)),""))}
A17: Total | B17: =SUM(B10:B16) -> #ERROR! | C17: =IF(B17=0,"Nenhum aviso: a ficha está conferida.","Abra a aba indicada e leia a coluna Aviso (na Em Jogo, a linha 13).") -> #ERROR!
A19: Como usar em 6 passos
A20: 1. Criação: preencha as células amarelas de cima para baixo — são os 12 passos do capítulo 03.
A21: 2. Caminho: escolha as Bênçãos nos slots liberados (e monte o Memoespírito, se for A Recordação).
A22: 3. Habilidades: escreva as suas Habilidades e a Ultimate; a ficha calcula dados, média, PH e rolagem.
A23: 4. Equipamento: Cone de Luz, Relíquias, Conjuntos, arma secundária, inventário e Créditos.
A24: 5. Progressão: a cada nível, mude o Nível atual na Criação e preencha os aumentos e as Ressonâncias.
A25: 6. Em Jogo: na mesa, use só esta aba — PV, Energia, PH, condições, usos e a calculadora de dano.
A27: Legenda de cores (a cor nunca é o único sinal: o texto diz)
A28: Entrada (preencha) | B28: Fundo amarelo com borda: é você quem preenche. Toda entrada sai vazia no arquivo.
A29: Calculada (automático) | B29: Fundo azul-claro: fórmula. Não edite (veja a proteção abaixo).
A30: Aviso | B30: Texto vermelho em fundo rosa: alguma regra do livro não fechou. O texto diz o quê.
A31: Título de bloco | B31: Faixa azul-escura: começo de um bloco, com o capítulo do livro.
A32: Não se aplica | B32: Cinza: não vale para o seu personagem (ou é coluna auxiliar).
A34: Como importar no Google Planilhas
A35: 1. Envie o arquivo .xlsx para o seu Google Drive.
A36: 2. Clique com o botão direito no arquivo → Abrir com → Planilhas Google.
A37: 3. No Planilhas: Arquivo → Salvar como Planilhas Google. Use essa cópia (a original continua .xlsx).
A38: 4. Confira o Painel de avisos acima: com a ficha em branco ele mostra zero avisos.
A39: 5. Para esconder a aba Dados: clique com o botão direito na aba Dados → Ocultar página. Não apague a aba Dados: as fórmulas leem dela.
A41: Como proteger as fórmulas (proteção nativa do Google, sem senha)
A42: 1. Dados → Proteger páginas e intervalos → Adicionar uma página ou um intervalo.
A43: 2. Escolha a aba (ou os intervalos calculados) e marque Exceto certas células para deixar as amarelas livres.
A44: 3. Definir permissões → Mostrar um aviso ao editar este intervalo → Concluído.
A45: Assim ninguém apaga uma fórmula sem querer: o Google avisa antes de editar.
A47: O que a ficha não faz (de propósito)
... A49: PV atual é entrada direta: use a calculadora de dano da aba Em Jogo e copie o PV novo. A variante de PV rolado não é calculada (veja Regras Rápidas).

Sheet Criação
A1: Criação — Explorando Galáxias v1.1
A2: Legenda: | B2: Entrada (preencha) | C2: Calculada (automático) | E2: Aviso (texto em vermelho) | G2: Título de bloco | H2: Cabeçalho de coluna | I2: Rótulo da linha | J2: Linha alternada (outro tom) | L2: Não se aplica
A3: Os 12 passos do capítulo 03, de cima para baixo.
N4: Listas auxiliares
A5: Personagem
A6: Nome do personagem | B6: BF "Blake Foster"
A7: Jogador | B7: MCFilhos
A8: Nível atual (1 a 20) | C8: ="Usado nas contas: nível "&$A$14 -> Usado nas contas: nível 1 | K8: =IF($B$8="","",IF(ISNUMBER($B$8),IF(OR($B$8<1,$B$8>20),"Nível fora de 1 a 20: a ficha conta com o nível "&$A$14,IF($B$8<>INT($B$8),"Nível precisa ser inteiro: a ficha conta com o nível "&$A$14,"")),"Nível precisa ser um número de 1 a 20: a ficha conta com o nível 1"))
A9: Nº de jogadores na mesa | C9: ="PH do grupo: máximo "&$E$16&", começa o combate com "&$F$16 -> PH do grupo: máximo 5, começa o combate com 3 | K9: =IF($B$9="","",IF(ISNUMBER($B$9),IF(OR($B$9<1,$B$9>6),"Nº de jogadores fora de 1 a 6: a ficha conta com "&$B$17,IF(OR($B$9<3,$B$9>6),"Fora da tabela do livro (3 a 6 jogadores): o PH segue a mesma regra","")),"Nº de jogadores precisa ser um número de 1 a 6"))
A10: Método de atributos (o Mestre escolhe) | B10: Compra de Pontos | C10: =IF($B$10="","Array oficial (15, 14, 13, 12, 10, 8) ou Compra de Pontos (28)",IF($B$10="Array oficial","Distribua 15, 14, 13, 12, 10 e 8, um em cada Atributo","Todos começam em 8; gaste até 28 pontos")) -> Todos começam em 8; gaste até 28 pontos | K10: =IF($B$10="","",IF(COUNTIF(Dados!$AH$6:$AH$7,$B$10)=0,"Método fora da lista",""))
A12: Números do seu nível (automático) — 26.2 a 26.6
A13: Nível usado | B13: Faixa (1 a 5) | C13: Eficiência | D13: Eficácia | E13: Slots de Eficácia em Perícias | F13: Slots de Eficácia em Testes de Resistência | G13: Especialização de Combate | H13: Teto de RD | I13: Teto de PV temporários | J13: Teto de bônus somado | K13: Teto de penalidade somada | L13: Bênçãos possuídas
A14: =IF(ISNUMBER($B$8),MAX(1,MIN(20,INT($B$8))),1) -> 1 | B14: =INT(($A$14-1)/4)+1 -> 1 | C14: =2+INT(($A$14-1)/3) -> 2 | D14: =2*$C$14 -> 4 | E14: {=INDEX(Dados!$C$258:$C$277,$A$14)} -> 0 | F14: {=INDEX(Dados!$D$258:$D$277,$A$14)} -> 0 | G14: {=INDEX(Dados!$K$258:$K$277,$A$14)} -> 0 | H14: {=INDEX(Dados!$L$258:$L$277,$A$14)} -> 6 | I14: =3*$C$14 -> 6 | J14: =IF($A$14<=9,3,IF($A$14<=15,4,5)) -> 3 | K14: =-$J$14 -> -3 | L14: {=INDEX(Dados!$E$258:$E$277,$A$14)} -> 1
A15: Habilidades conhecidas | B15: Nível máx. de Habilidade | C15: Reescreve 1 Habilidade por nível | D15: Dados de Ataque Básico | E15: PH do grupo: máximo | F15: PH do grupo: início | G15: PH por Ataque Básico que acerta | H15: Ultimate: Nível equivalente | I15: Cone de Luz: Nível máximo | J15: Tier de Relíquia (1 a 4) | K15: Pontos do Memoespírito | L15: DT para descobrir Fraqueza
A16: {=INDEX(Dados!$F$258:$F$277,$A$14)} -> 1 | B16: {=INDEX(Dados!$H$258:$H$277,$A$14)} -> 1 | C16: {=INDEX(Dados!$G$258:$G$277,$A$14)} -> Não | D16: {=INDEX(Dados!$J$258:$J$277,$A$14)} -> 1 | E16: =1+$B$17+IF($A$14>=17,2,IF($A$14>=9,1,0)) -> 5 | F16: =$E$16-2 -> 3 | G16: =IF($A$14<=8,1,2) -> 1 | H16: {=INDEX(Dados!$B$326:$B$330,$B$14)} -> 2 | I16: =$B$14 -> 1 | J16: =IF($A$14<=6,1,IF($A$14<=12,2,IF($A$14<=17,3,4))) -> 1 | K16: =12+INT($A$14/2) -> 12 | L16: {=INDEX(Dados!$B$390:$B$394,$B$14)} -> 13
A17: Nº de jogadores usado (vazio = 4) | B17: =IF(ISNUMBER($B$9),MAX(1,MIN(6,INT($B$9))),4) -> 4 | C17: Aumento de Atributo neste nível? | E17: {=INDEX(Dados!$I$258:$I$277,$A$14)} -> Não
A19: Passo 1 — Conceito e Propósito de Vida
A20: Quem é esse sujeito? (conceito em uma frase)
A21: Propósito de Vida (objetivo de longo prazo)
A22: Em que você acredita (recarrega o Esforço; só Humano) | K22: =IF(AND($B$25<>"Humano",LEN($B$22)>0),"O Esforço é traço do Humano: esta linha só vale para Humano","")
A24: Passo 2 — Raça (capítulo 05)
A25: Raça | B25: Humano | C25: =IF($B$25="","Escolha a Raça",IF($B$25="Humano",IF($B$26="+1 em dois","Bônus racial: +1 em "&IF($B$27="","?",$B$27)&" e +1 em "&IF($B$28="","?",$B$28),IF($B$27="","Escolha onde vai o +2 (qualquer Atributo)","Bônus racial: +2 em "&$B$27)),IF($O$25="","Raça fora da lista do capítulo 05",IF($O$27="","Escolha onde vai o +2: "&$O$25&" ou "&$O$26,"Bônus racial: +2 em "&$O$27)))) -> #ERROR! | K25: =IF($B$25="","",IF(COUNTIF(Dados!$O$6:$O$12,$B$25)=0,"Raça fora da lista do capítulo 05","")) | N25: {=IF($B$25="Humano",INDEX(Dados!$Q$6:$Q$11,1),$O$25)} -> Poder | O25: {=IF($B$25="","",IFERROR(""&INDEX(Dados!$D$7:$D$13,MATCH($B$25,Dados!$A$7:$A$13,0)),""))}
A26: Bônus do Humano: +2 em um ou +1 em dois | B26: #ERROR! | C26: Só para Humano. As outras Raças têm +2 fixo ou à escolha entre duas opções. | K26: =IF(AND($B$26<>"",$B$25<>"Humano"),"O bônus livre é só do Humano","") -> #ERROR! | N26: {=IF($B$25="Humano",INDEX(Dados!$Q$6:$Q$11,2),$O$26)} -> Agilidade | O26: {=IF($B$25="","",IFERROR(""&INDEX(Dados!$E$7:$E$13,MATCH($B$25,Dados!$A$7:$A$13,0)),""))}
A27: Atributo do +2 (Humano com +1 em dois: o 1º) | B27: Poder | C27: A lista mostra só as opções da sua Raça. | K27: =IF(AND($B$25="Humano",$B$26="+1 em dois",$B$27<>"",$B$27=$B$28),"+1 em dois exige atributos diferentes: contou só um +1",IF(AND($B$25<>"",$B$25<>"Humano",$O$25<>"",$B$27<>"",$O$27=""),"Bônus fora das opções da Raça: "&$O$25&IF($O$26="",""," ou "&$O$26),"")) -> #ERROR! | N27: {=IF($B$25="Humano",INDEX(Dados!$Q$6:$Q$11,3),"")} -> Vigor | O27: =IF(OR($B$25="",$B$25="Humano"),"",IF($O$26="",IF(OR($B$27="",$B$27=$O$25),$O$25,""),IF(OR($B$27=$O$25,$B$27=$O$26),$B$27,"")))
A28: Atributo 2 (só Humano com +1 em dois) | B28: Agilidade | K28: =IF(AND($B$28<>"",OR($B$25<>"Humano",$B$26<>"+1 em dois")),"Atributo 2 só vale para Humano com +1 em dois","") -> #ERROR! | N28: {=IF($B$25="Humano",INDEX(Dados!$Q$6:$Q$11,4),"")} -> Sincronia
A29: Traços (resumo) | B29: {=IF($B$25="","",IFERROR(INDEX(Dados!$F$7:$F$13,MATCH($B$25,Dados!$A$7:$A$13,0)),""))} -> Força de Vontade (Esforço: 1 ponto, re-rola um dado) | N29: {=IF($B$25="Humano",INDEX(Dados!$Q$6:$Q$11,5),"")} -> Discernimento
A30: Traços (texto inteiro do livro) | B30: {=IF($B$25="","",IFERROR(INDEX(Dados!$G$7:$G$13,MATCH($B$25,Dados!$A$7:$A$13,0)),""))} -> Força de Vontade: Você tem um recurso que ninguém mais no jogo tem: o Esforço. Esforço: gaste 1 ponto de Esforço para rolar de novo qualquer dado que você acabou de rolar, e use o resultado novo. Você pode declarar depois de ver o resultado, mas antes de o Mestre narrar a consequência. • Você carrega no máximo 1 ponto de Esforço. Ganhar um segundo sem ter gasto o primeiro perde o excedente. • Você recupera o ponto de duas formas: em um Descanso Longo (capítulo 23), ou agindo de acordo com o que o seu personagem acredita, uma vez por sessão, com a aprovação do Mestre. • O que você acredita precisa ser concreto. "Eu acredito na verdade" não serve. "Eu não deixo ninguém para trás, nem inimigo" serve, e cobra um preço na cena — que é justamente o ponto. | N30: {=IF($B$25="Humano",INDEX(Dados!$Q$6:$Q$11,6),"")} -> Presença
A32: Passo 3 — Caminho (capítulo 06)
A33: Caminho | C33: {=IF($B$33="","Escolha o Caminho","Aeon: "&IF($B$33="","",IFERROR(INDEX(Dados!$B$84:$B$92,MATCH($B$33,Dados!$A$84:$A$92,0)),"")))} -> Escolha o Caminho | K33: =IF($B$33="","",IF(COUNTIF(Dados!$P$6:$P$14,$B$33)=0,"Caminho fora da lista do capítulo 06",""))
A34: Aeon | B34: {=IF($B$33="","",IFERROR(INDEX(Dados!$B$84:$B$92,MATCH($B$33,Dados!$A$84:$A$92,0)),""))}
A35: A ideia, em uma frase | B35: {=IF($B$33="","",IFERROR(INDEX(Dados!$C$84:$C$92,MATCH($B$33,Dados!$A$84:$A$92,0)),""))}
A36: Índice de vitalidade N (entra no PV) | B36: {=IF($B$33="",0,IFERROR(INDEX(Dados!$J$84:$J$92,MATCH($B$33,Dados!$A$84:$A$92,0)),0))} -> 0
A37: Bônus de Velocidade do Caminho | B37: {=IF($B$33="",0,IFERROR(INDEX(Dados!$K$84:$K$92,MATCH($B$33,Dados!$A$84:$A$92,0)),0))} -> 0
A38: As 3 Perícias do Caminho (Eficiência de graça) | B38: {=IF($B$33="","",IFERROR(INDEX(Dados!$G$84:$G$92,MATCH($B$33,Dados!$A$84:$A$92,0)),""))} | D38: {=IF($B$33="","",IFERROR(INDEX(Dados!$H$84:$H$92,MATCH($B$33,Dados!$A$84:$A$92,0)),""))} | F38: {=IF($B$33="","",IFERROR(INDEX(Dados!$I$84:$I$92,MATCH($B$33,Dados!$A$84:$A$92,0)),""))}
A39: Atributo de Habilidade que o Caminho permite | B39: {=IF($B$33="","",IFERROR(INDEX(Dados!$D$84:$D$92,MATCH($B$33,Dados!$A$84:$A$92,0)),""))}
A40: Recurso próprio (detalhes na aba Caminho) | B40: {=IF($B$33="","",IFERROR(INDEX(Dados!$L$84:$L$92,MATCH($B$33,Dados!$A$84:$A$92,0)),""))}
A42: Passo 4 — Atributos (teto 15 antes da Raça; teto 20 sempre)
A43: Atributo | B43: Distribuído (preencha) | C43: Raça (automático) | D43: Aumentos (aba Progressão) | E43: Valor atual | F43: Bônus atual | G43: Valor na criação (com Raça) | H43: Bônus na criação | I43: Custo na Compra de Pontos | J43: Valor usado (8 a 20) | K43: Aviso
A44: Poder | C44: =IF($B$25="Humano",IF($B$26="+1 em dois",($B$27="Poder")*1+AND($B$28="Poder",$B$28<>$B$27)*1,($B$27="Poder")*2),IF($O$27="Poder",2,0)) -> #ERROR! | D44: =SUMIF('Progressão'!$D$57:$D$62,"Poder",'Progressão'!$F$57:$F$62)+SUMIF('Progressão'!$E$57:$E$62,"Poder",'Progressão'!$G$57:$G$62) -> 0 | E44: =MIN(20,$J$44+$C$44+$D$44) -> #ERROR! | F44: =IF($E$44<15,VLOOKUP($E$44,Dados!$A$27:$B$39,2,FALSE),INT(($E$44-15)/2)+3) -> #ERROR! | G44: =MIN(20,$J$44+$C$44) -> #ERROR! | H44: =IF($G$44<15,VLOOKUP($G$44,Dados!$A$27:$B$39,2,FALSE),INT(($G$44-15)/2)+3) -> #ERROR! | I44: =IF($B$10="Compra de Pontos",VLOOKUP(MAX(8,MIN(15,$J$44)),Dados!$A$43:$B$50,2,FALSE),"") -> 0 | J44: =IF(ISNUMBER($B$44),MAX(8,MIN(20,INT($B$44))),8) -> 8 | K44: =IF($B$44="","",IF(ISNUMBER($B$44),IF(OR($B$44<8,$B$44>20),"Fora de 8 a 20: a ficha conta com "&$J$44&". ","")&IF($B$44>15,"Acima de 15 antes da Raça. ",""),"Precisa ser um número. "))&IF(AND($D$44>0,$J$44+$C$44+$D$44>20),"Aumento desperdiçado: passou do teto 20.","") -> #ERROR!
A45: Agilidade | C45: =IF($B$25="Humano",IF($B$26="+1 em dois",($B$27="Agilidade")*1+AND($B$28="Agilidade",$B$28<>$B$27)*1,($B$27="Agilidade")*2),IF($O$27="Agilidade",2,0)) -> #ERROR! | D45: =SUMIF('Progressão'!$D$57:$D$62,"Agilidade",'Progressão'!$F$57:$F$62)+SUMIF('Progressão'!$E$57:$E$62,"Agilidade",'Progressão'!$G$57:$G$62) -> 0 | E45: =MIN(20,$J$45+$C$45+$D$45) -> #ERROR! | F45: =IF($E$45<15,VLOOKUP($E$45,Dados!$A$27:$B$39,2,FALSE),INT(($E$45-15)/2)+3) -> #ERROR! | G45: =MIN(20,$J$45+$C$45) -> #ERROR! | H45: =IF($G$45<15,VLOOKUP($G$45,Dados!$A$27:$B$39,2,FALSE),INT(($G$45-15)/2)+3) -> #ERROR! | I45: =IF($B$10="Compra de Pontos",VLOOKUP(MAX(8,MIN(15,$J$45)),Dados!$A$43:$B$50,2,FALSE),"") -> 0 | J45: =IF(ISNUMBER($B$45),MAX(8,MIN(20,INT($B$45))),8) -> 8 | K45: =IF($B$45="","",IF(ISNUMBER($B$45),IF(OR($B$45<8,$B$45>20),"Fora de 8 a 20: a ficha conta com "&$J$45&". ","")&IF($B$45>15,"Acima de 15 antes da Raça. ",""),"Precisa ser um número. "))&IF(AND($D$45>0,$J$45+$C$45+$D$45>20),"Aumento desperdiçado: passou do teto 20.","") -> #ERROR!
A46: Vigor | C46: =IF($B$25="Humano",IF($B$26="+1 em dois",($B$27="Vigor")*1+AND($B$28="Vigor",$B$28<>$B$27)*1,($B$27="Vigor")*2),IF($O$27="Vigor",2,0)) -> #ERROR! | D46: =SUMIF('Progressão'!$D$57:$D$62,"Vigor",'Progressão'!$F$57:$F$62)+SUMIF('Progressão'!$E$57:$E$62,"Vigor",'Progressão'!$G$57:$G$62) -> 0 | E46: =MIN(20,$J$46+$C$46+$D$46) -> #ERROR! | F46: =IF($E$46<15,VLOOKUP($E$46,Dados!$A$27:$B$39,2,FALSE),INT(($E$46-15)/2)+3) -> #ERROR! | G46: =MIN(20,$J$46+$C$46) -> #ERROR! | H46: =IF($G$46<15,VLOOKUP($G$46,Dados!$A$27:$B$39,2,FALSE),INT(($G$46-15)/2)+3) -> #ERROR! | I46: =IF($B$10="Compra de Pontos",VLOOKUP(MAX(8,MIN(15,$J$46)),Dados!$A$43:$B$50,2,FALSE),"") -> 0 | J46: =IF(ISNUMBER($B$46),MAX(8,MIN(20,INT($B$46))),8) -> 8 | K46: =IF($B$46="","",IF(ISNUMBER($B$46),IF(OR($B$46<8,$B$46>20),"Fora de 8 a 20: a ficha conta com "&$J$46&". ","")&IF($B$46>15,"Acima de 15 antes da Raça. ",""),"Precisa ser um número. "))&IF(AND($D$46>0,$J$46+$C$46+$D$46>20),"Aumento desperdiçado: passou do teto 20.","") -> #ERROR!
A47: Sincronia | C47: =IF($B$25="Humano",IF($B$26="+1 em dois",($B$27="Sincronia")*1+AND($B$28="Sincronia",$B$28<>$B$27)*1,($B$27="Sincronia")*2),IF($O$27="Sincronia",2,0)) -> #ERROR! | D47: =SUMIF('Progressão'!$D$57:$D$62,"Sincronia",'Progressão'!$F$57:$F$62)+SUMIF('Progressão'!$E$57:$E$62,"Sincronia",'Progressão'!$G$57:$G$62) -> 0 | E47: =MIN(20,$J$47+$C$47+$D$47) -> #ERROR! | F47: =IF($E$47<15,VLOOKUP($E$47,Dados!$A$27:$B$39,2,FALSE),INT(($E$47-15)/2)+3) -> #ERROR! | G47: =MIN(20,$J$47+$C$47) -> #ERROR! | H47: =IF($G$47<15,VLOOKUP($G$47,Dados!$A$27:$B$39,2,FALSE),INT(($G$47-15)/2)+3) -> #ERROR! | I47: =IF($B$10="Compra de Pontos",VLOOKUP(MAX(8,MIN(15,$J$47)),Dados!$A$43:$B$50,2,FALSE),"") -> 0 | J47: =IF(ISNUMBER($B$47),MAX(8,MIN(20,INT($B$47))),8) -> 8 | K47: =IF($B$47="","",IF(ISNUMBER($B$47),IF(OR($B$47<8,$B$47>20),"Fora de 8 a 20: a ficha conta com "&$J$47&". ","")&IF($B$47>15,"Acima de 15 antes da Raça. ",""),"Precisa ser um número. "))&IF(AND($D$47>0,$J$47+$C$47+$D$47>20),"Aumento desperdiçado: passou do teto 20.","") -> #ERROR!
A48: Discernimento | C48: =IF($B$25="Humano",IF($B$26="+1 em dois",($B$27="Discernimento")*1+AND($B$28="Discernimento",$B$28<>$B$27)*1,($B$27="Discernimento")*2),IF($O$27="Discernimento",2,0)) -> #ERROR! | D48: =SUMIF('Progressão'!$D$57:$D$62,"Discernimento",'Progressão'!$F$57:$F$62)+SUMIF('Progressão'!$E$57:$E$62,"Discernimento",'Progressão'!$G$57:$G$62) -> 0 | E48: =MIN(20,$J$48+$C$48+$D$48) -> #ERROR! | F48: =IF($E$48<15,VLOOKUP($E$48,Dados!$A$27:$B$39,2,FALSE),INT(($E$48-15)/2)+3) -> #ERROR! | G48: =MIN(20,$J$48+$C$48) -> #ERROR! | H48: =IF($G$48<15,VLOOKUP($G$48,Dados!$A$27:$B$39,2,FALSE),INT(($G$48-15)/2)+3) -> #ERROR! | I48: =IF($B$10="Compra de Pontos",VLOOKUP(MAX(8,MIN(15,$J$48)),Dados!$A$43:$B$50,2,FALSE),"") -> 0 | J48: =IF(ISNUMBER($B$48),MAX(8,MIN(20,INT($B$48))),8) -> 8 | K48: =IF($B$48="","",IF(ISNUMBER($B$48),IF(OR($B$48<8,$B$48>20),"Fora de 8 a 20: a ficha conta com "&$J$48&". ","")&IF($B$48>15,"Acima de 15 antes da Raça. ",""),"Precisa ser um número. "))&IF(AND($D$48>0,$J$48+$C$48+$D$48>20),"Aumento desperdiçado: passou do teto 20.","") -> #ERROR!
A49: Presença | C49: =IF($B$25="Humano",IF($B$26="+1 em dois",($B$27="Presença")*1+AND($B$28="Presença",$B$28<>$B$27)*1,($B$27="Presença")*2),IF($O$27="Presença",2,0)) -> #ERROR! | D49: =SUMIF('Progressão'!$D$57:$D$62,"Presença",'Progressão'!$F$57:$F$62)+SUMIF('Progressão'!$E$57:$E$62,"Presença",'Progressão'!$G$57:$G$62) -> 0 | E49: =MIN(20,$J$49+$C$49+$D$49) -> #ERROR! | F49: =IF($E$49<15,VLOOKUP($E$49,Dados!$A$27:$B$39,2,FALSE),INT(($E$49-15)/2)+3) -> #ERROR! | G49: =MIN(20,$J$49+$C$49) -> #ERROR! | H49: =IF($G$49<15,VLOOKUP($G$49,Dados!$A$27:$B$39,2,FALSE),INT(($G$49-15)/2)+3) -> #ERROR! | I49: =IF($B$10="Compra de Pontos",VLOOKUP(MAX(8,MIN(15,$J$49)),Dados!$A$43:$B$50,2,FALSE),"") -> 0 | J49: =IF(ISNUMBER($B$49),MAX(8,MIN(20,INT($B$49))),8) -> 8 | K49: =IF($B$49="","",IF(ISNUMBER($B$49),IF(OR($B$49<8,$B$49>20),"Fora de 8 a 20: a ficha conta com "&$J$49&". ","")&IF($B$49>15,"Acima de 15 antes da Raça. ",""),"Precisa ser um número. "))&IF(AND($D$49>0,$J$49+$C$49+$D$49>20),"Aumento desperdiçado: passou do teto 20.","") -> #ERROR!
A50: Conferência do array oficial | B50: =IF($B$10<>"Array oficial","",IF((ISNUMBER($B$44)*1+ISNUMBER($B$45)*1+ISNUMBER($B$46)*1+ISNUMBER($B$47)*1+ISNUMBER($B$48)*1+ISNUMBER($B$49)*1)<6,"Valores que faltam para fechar o array: "&(6-(ISNUMBER($B$44)*1+ISNUMBER($B$45)*1+ISNUMBER($B$46)*1+ISNUMBER($B$47)*1+ISNUMBER($B$48)*1+ISNUMBER($B$49)*1)),IF(AND(COUNTIF($B$44:$B$49,15)=1,COUNTIF($B$44:$B$49,14)=1,COUNTIF($B$44:$B$49,13)=1,COUNTIF($B$44:$B$49,12)=1,COUNTIF($B$44:$B$49,10)=1,COUNTIF($B$44:$B$49,8)=1),"OK: cada valor usado uma vez","Confira o aviso ao lado"))) | K50: =IF(AND($B$10="Array oficial",(ISNUMBER($B$44)*1+ISNUMBER($B$45)*1+ISNUMBER($B$46)*1+ISNUMBER($B$47)*1+ISNUMBER($B$48)*1+ISNUMBER($B$49)*1)=6),IF(AND(COUNTIF($B$44:$B$49,15)=1,COUNTIF($B$44:$B$49,14)=1,COUNTIF($B$44:$B$49,13)=1,COUNTIF($B$44:$B$49,12)=1,COUNTIF($B$44:$B$49,10)=1,COUNTIF($B$44:$B$49,8)=1),"","Array oficial: use 15, 14, 13, 12, 10 e 8 uma vez cada. Falta: "&IF(COUNTIF($B$44:$B$49,15)=0,"15 ","")&IF(COUNTIF($B$44:$B$49,14)=0,"14 ","")&IF(COUNTIF($B$44:$B$49,13)=0,"13 ","")&IF(COUNTIF($B$44:$B$49,12)=0,"12 ","")&IF(COUNTIF($B$44:$B$49,10)=0,"10 ","")&IF(COUNTIF($B$44:$B$49,8)=0,"8 ","")&"· Repetido: "&IF(COUNTIF($B$44:$B$49,15)>1,"15 ","")&IF(COUNTIF($B$44:$B$49,14)>1,"14 ","")&IF(COUNTIF($B$44:$B$49,13)>1,"13 ","")&IF(COUNTIF($B$44:$B$49,12)>1,"12 ","")&IF(COUNTIF($B$44:$B$49,10)>1,"10 ","")&IF(COUNTIF($B$44:$B$49,8)>1,"8 ","")),"")
A51: Compra de Pontos: gastos de 28 | B51: =IF($B$10="Compra de Pontos",SUM($I$44:$I$49),"") -> 0 | C51: Sobram: | D51: =IF($B$10="Compra de Pontos",28-SUM($I$44:$I$49),"") -> 28 | K51: =IF(AND($B$10="Compra de Pontos",SUM($I$44:$I$49)>28),"Compra de Pontos passou de 28 ("&SUM($I$44:$I$49)&" pontos)","")
A53: Passo 5 — Atributo de Habilidade (fixo pela campanha)
A54: Atributo de Habilidade | C54: Usado: | D54: =IF($N$54="","",IF(AND($B$54="",$N$55=""),$N$54,IF(AND($B$54<>"",OR($B$54=$N$54,$B$54=$N$55)),$B$54,""))) | K54: =IF(AND($N$54<>"",$D$54=""),IF($B$54="","Escolha o Atributo de Habilidade: "&$N$54&" ou "&$N$55,"Fora do que o Caminho permite: "&$N$54&IF($N$55="",""," ou "&$N$55)),"") | N54: {=IF($B$33="","",IFERROR(""&INDEX(Dados!$E$84:$E$92,MATCH($B$33,Dados!$A$84:$A$92,0)),""))}
A55: Bônus do Atributo de Habilidade | B55: {=IF($D$54="",0,IFERROR(INDEX($F$44:$F$49,MATCH($D$54,$A$44:$A$49,0)),0))} -> 0 | N55: {=IF($B$33="","",IFERROR(""&INDEX(Dados!$F$84:$F$92,MATCH($B$33,Dados!$A$84:$A$92,0)),""))}
A56: DT das suas Habilidades (8 + Bônus + Eficiência) | B56: =8+$B$55+$C$14 -> 10
A57: Teste de Ataque das Habilidades e da Ultimate | B57: =$B$55+$C$14+$G$14+$B$124 -> #ERROR! | C57: ="d20"&IF($B$57>=0,"+","")&$B$57 -> #ERROR! | D57: Bônus + Eficiência + Especialização + equipamento (aba Equipamento)
A59: Passo 6 — Elemento (capítulo 20)
A60: Elemento | C60: Suas Habilidades e a Ultimate causam dano deste Elemento. | K60: =IF($B$60="","",IF(COUNTIF(Dados!$R$6:$R$12,$B$60)=0,"Elemento fora da lista do capítulo 20",""))
A61: Efeito de Quebra | B61: {=IF($B$60="","",IFERROR(INDEX(Dados!$H$374:$H$380,MATCH($B$60,Dados!$A$374:$A$380,0)),""))}
A62: Dano de Quebra (20.5) | B62: {=IF($B$60="","",IFERROR(IF(INDEX(Dados!$E$374:$E$380,MATCH($B$60,Dados!$A$374:$A$380,0))<=0,""&INDEX(Dados!$G$374:$G$380,MATCH($B$60,Dados!$A$374:$A$380,0))*$C$14,INDEX(Dados!$E$374:$E$380,MATCH($B$60,Dados!$A$374:$A$380,0))&"d"&INDEX(Dados!$F$374:$F$380,MATCH($B$60,Dados!$A$374:$A$380,0))&IF(INDEX(Dados!$G$374:$G$380,MATCH($B$60,Dados!$A$374:$A$380,0))*$C$14>0,"+"&INDEX(Dados!$G$374:$G$380,MATCH($B$60,Dados!$A$374:$A$380,0))*$C$14,IF(INDEX(Dados!$G$374:$G$380,MATCH($B$60,Dados!$A$374:$A$380,0))*$C$14<0,""&INDEX(Dados!$G$374:$G$380,MATCH($B$60,Dados!$A$374:$A$380,0))*$C$14,""))),""))} | C62: média | D62: {=IF($B$60="","",IFERROR(INT(INDEX(Dados!$E$374:$E$380,MATCH($B$60,Dados!$A$374:$A$380,0))*(INDEX(Dados!$F$374:$F$380,MATCH($B$60,Dados!$A$374:$A$380,0))+1)/2)+INDEX(Dados!$G$374:$G$380,MATCH($B$60,Dados!$A$374:$A$380,0))*$C$14,""))}
A64: Passo 7 — Perícias (3 do Caminho + 2 + Bônus de Sincronia escolhidas, mínimo 2)
A65: Sintonia usa (fixo na criação) | C65: Usado: | D65: =IF($B$65="Sincronia","Sincronia","Discernimento") -> Discernimento
A66: Perícias escolhidas permitidas (Sincronia da criação) | B66: =MAX(2,2+$H$47) -> #ERROR!
A67: Escolhidas / com Eficiência no total | B67: =COUNTIF($D$69:$D$88,"Sim") -> 0 | C67: com Eficiência: | D67: =COUNTIF($E$69:$E$88,"Sim") -> 0 | K67: =IF($B$67>$B$66,"Perícias escolhidas acima do permitido ("&$B$66&"): as últimas ficam sem Eficiência","") -> #ERROR!
A68: Perícia (Poder, Agilidade e Vigor) | B68: Atributo | C68: Do Caminho? | D68: Escolhida (preencha Sim) | E68: Eficiência (automático) | F68: Origem | K68: Aviso
A69: Atletismo | B69: {=INDEX(Dados!$B$54:$B$71,1)} -> Poder | C69: =IF(OR($B$38="Atletismo",$D$38="Atletismo",$F$38="Atletismo"),"Sim","Não") -> Não | E69: =IF(OR($C$69="Sim",AND($D$69="Sim",COUNTIF($D$69:D69,"Sim")<=$B$66)),"Sim","Não") -> #ERROR! | F69: =IF($C$69="Sim","Caminho",IF($E$69="Sim","Escolhida","")) -> #ERROR! | K69: =IF($D$69<>"Sim","",IF($C$69="Sim","Já vem do Caminho: escolha outra",IF($E$69="Não","Acima do permitido ("&$B$66&"): esta fica sem Eficiência","")))
A70: Acrobacia | B70: {=INDEX(Dados!$B$54:$B$71,2)} -> Agilidade | C70: =IF(OR($B$38="Acrobacia",$D$38="Acrobacia",$F$38="Acrobacia"),"Sim","Não") -> Não | E70: =IF(OR($C$70="Sim",AND($D$70="Sim",COUNTIF($D$69:D70,"Sim")<=$B$66)),"Sim","Não") -> #ERROR! | F70: =IF($C$70="Sim","Caminho",IF($E$70="Sim","Escolhida","")) -> #ERROR! | K70: =IF($D$70<>"Sim","",IF($C$70="Sim","Já vem do Caminho: escolha outra",IF($E$70="Não","Acima do permitido ("&$B$66&"): esta fica sem Eficiência","")))
A71: Furtividade | B71: {=INDEX(Dados!$B$54:$B$71,3)} -> Agilidade | C71: =IF(OR($B$38="Furtividade",$D$38="Furtividade",$F$38="Furtividade"),"Sim","Não") -> Não | E71: =IF(OR($C$71="Sim",AND($D$71="Sim",COUNTIF($D$69:D71,"Sim")<=$B$66)),"Sim","Não") -> #ERROR! | F71: =IF($C$71="Sim","Caminho",IF($E$71="Sim","Escolhida","")) -> #ERROR! | K71: =IF($D$71<>"Sim","",IF($C$71="Sim","Já vem do Caminho: escolha outra",IF($E$71="Não","Acima do permitido ("&$B$66&"): esta fica sem Eficiência","")))
A72: Pilotagem | B72: {=INDEX(Dados!$B$54:$B$71,4)} -> Agilidade | C72: =IF(OR($B$38="Pilotagem",$D$38="Pilotagem",$F$38="Pilotagem"),"Sim","Não") -> Não | E72: =IF(OR($C$72="Sim",AND($D$72="Sim",COUNTIF($D$69:D72,"Sim")<=$B$66)),"Sim","Não") -> #ERROR! | F72: =IF($C$72="Sim","Caminho",IF($E$72="Sim","Escolhida","")) -> #ERROR! | K72: =IF($D$72<>"Sim","",IF($C$72="Sim","Já vem do Caminho: escolha outra",IF($E$72="Não","Acima do permitido ("&$B$66&"): esta fica sem Eficiência","")))
A73: Resistência | B73: {=INDEX(Dados!$B$54:$B$71,5)} -> Vigor | C73: =IF(OR($B$38="Resistência",$D$38="Resistência",$F$38="Resistência"),"Sim","Não") -> Não | E73: =IF(OR($C$73="Sim",AND($D$73="Sim",COUNTIF($D$69:D73,"Sim")<=$B$66)),"Sim","Não") -> #ERROR! | F73: =IF($C$73="Sim","Caminho",IF($E$73="Sim","Escolhida","")) -> #ERROR! | K73: =IF($D$73<>"Sim","",IF($C$73="Sim","Já vem do Caminho: escolha outra",IF($E$73="Não","Acima do permitido ("&$B$66&"): esta fica sem Eficiência","")))
A74: Perícia (Sincronia e Discernimento) | B74: Atributo | C74: Do Caminho? | D74: Escolhida (preencha Sim) | E74: Eficiência (automático) | F74: Origem | K74: Aviso
A75: Tecnologia | B75: {=INDEX(Dados!$B$54:$B$71,6)} -> Sincronia | C75: =IF(OR($B$38="Tecnologia",$D$38="Tecnologia",$F$38="Tecnologia"),"Sim","Não") -> Não | E75: =IF(OR($C$75="Sim",AND($D$75="Sim",COUNTIF($D$69:D75,"Sim")<=$B$66)),"Sim","Não") -> #ERROR! | F75: =IF($C$75="Sim","Caminho",IF($E$75="Sim","Escolhida","")) -> #ERROR! | K75: =IF($D$75<>"Sim","",IF($C$75="Sim","Já vem do Caminho: escolha outra",IF($E$75="Não","Acima do permitido ("&$B$66&"): esta fica sem Eficiência","")))
A76: Pesquisa | B76: {=INDEX(Dados!$B$54:$B$71,7)} -> Sincronia | C76: =IF(OR($B$38="Pesquisa",$D$38="Pesquisa",$F$38="Pesquisa"),"Sim","Não") -> Não | E76: =IF(OR($C$76="Sim",AND($D$76="Sim",COUNTIF($D$69:D76,"Sim")<=$B$66)),"Sim","Não") -> #ERROR! | F76: =IF($C$76="Sim","Caminho",IF($E$76="Sim","Escolhida","")) -> #ERROR! | K76: =IF($D$76<>"Sim","",IF($C$76="Sim","Já vem do Caminho: escolha outra",IF($E$76="Não","Acima do permitido ("&$B$66&"): esta fica sem Eficiência","")))
A77: Ciência | B77: {=INDEX(Dados!$B$54:$B$71,8)} -> Sincronia | C77: =IF(OR($B$38="Ciência",$D$38="Ciência",$F$38="Ciência"),"Sim","Não") -> Não | E77: =IF(OR($C$77="Sim",AND($D$77="Sim",COUNTIF($D$69:D77,"Sim")<=$B$66)),"Sim","Não") -> #ERROR! | F77: =IF($C$77="Sim","Caminho",IF($E$77="Sim","Escolhida","")) -> #ERROR! | K77: =IF($D$77<>"Sim","",IF($C$77="Sim","Já vem do Caminho: escolha outra",IF($E$77="Não","Acima do permitido ("&$B$66&"): esta fica sem Eficiência","")))
A78: Mecânica | B78: {=INDEX(Dados!$B$54:$B$71,9)} -> Sincronia | C78: =IF(OR($B$38="Mecânica",$D$38="Mecânica",$F$38="Mecânica"),"Sim","Não") -> Não | E78: =IF(OR($C$78="Sim",AND($D$78="Sim",COUNTIF($D$69:D78,"Sim")<=$B$66)),"Sim","Não") -> #ERROR! | F78: =IF($C$78="Sim","Caminho",IF($E$78="Sim","Escolhida","")) -> #ERROR! | K78: =IF($D$78<>"Sim","",IF($C$78="Sim","Já vem do Caminho: escolha outra",IF($E$78="Não","Acima do permitido ("&$B$66&"): esta fica sem Eficiência","")))
A79: Percepção | B79: {=INDEX(Dados!$B$54:$B$71,10)} -> Discernimento | C79: =IF(OR($B$38="Percepção",$D$38="Percepção",$F$38="Percepção"),"Sim","Não") -> Não | E79: =IF(OR($C$79="Sim",AND($D$79="Sim",COUNTIF($D$69:D79,"Sim")<=$B$66)),"Sim","Não") -> #ERROR! | F79: =IF($C$79="Sim","Caminho",IF($E$79="Sim","Escolhida","")) -> #ERROR! | K79: =IF($D$79<>"Sim","",IF($C$79="Sim","Já vem do Caminho: escolha outra",IF($E$79="Não","Acima do permitido ("&$B$66&"): esta fica sem Eficiência","")))
A80: Sobrevivência | B80: {=INDEX(Dados!$B$54:$B$71,11)} -> Discernimento | C80: =IF(OR($B$38="Sobrevivência",$D$38="Sobrevivência",$F$38="Sobrevivência"),"Sim","Não") -> Não | E80: =IF(OR($C$80="Sim",AND($D$80="Sim",COUNTIF($D$69:D80,"Sim")<=$B$66)),"Sim","Não") -> #ERROR! | F80: =IF($C$80="Sim","Caminho",IF($E$80="Sim","Escolhida","")) -> #ERROR! | K80: =IF($D$80<>"Sim","",IF($C$80="Sim","Já vem do Caminho: escolha outra",IF($E$80="Não","Acima do permitido ("&$B$66&"): esta fica sem Eficiência","")))
A81: Intuição | B81: {=INDEX(Dados!$B$54:$B$71,12)} -> Discernimento | C81: =IF(OR($B$38="Intuição",$D$38="Intuição",$F$38="Intuição"),"Sim","Não") -> Não | E81: =IF(OR($C$81="Sim",AND($D$81="Sim",COUNTIF($D$69:D81,"Sim")<=$B$66)),"Sim","Não") -> #ERROR! | F81: =IF($C$81="Sim","Caminho",IF($E$81="Sim","Escolhida","")) -> #ERROR! | K81: =IF($D$81<>"Sim","",IF($C$81="Sim","Já vem do Caminho: escolha outra",IF($E$81="Não","Acima do permitido ("&$B$66&"): esta fica sem Eficiência","")))
A82: Investigação | B82: {=INDEX(Dados!$B$54:$B$71,13)} -> Discernimento | C82: =IF(OR($B$38="Investigação",$D$38="Investigação",$F$38="Investigação"),"Sim","Não") -> Não | E82: =IF(OR($C$82="Sim",AND($D$82="Sim",COUNTIF($D$69:D82,"Sim")<=$B$66)),"Sim","Não") -> #ERROR! | F82: =IF($C$82="Sim","Caminho",IF($E$82="Sim","Escolhida","")) -> #ERROR! | K82: =IF($D$82<>"Sim","",IF($C$82="Sim","Já vem do Caminho: escolha outra",IF($E$82="Não","Acima do permitido ("&$B$66&"): esta fica sem Eficiência","")))
A83: Perícia (Presença e Sintonia) | B83: Atributo | C83: Do Caminho? | D83: Escolhida (preencha Sim) | E83: Eficiência (automático) | F83: Origem | K83: Aviso
A84: Persuasão | B84: {=INDEX(Dados!$B$54:$B$71,14)} -> Presença | C84: =IF(OR($B$38="Persuasão",$D$38="Persuasão",$F$38="Persuasão"),"Sim","Não") -> Não | E84: =IF(OR($C$84="Sim",AND($D$84="Sim",COUNTIF($D$69:D84,"Sim")<=$B$66)),"Sim","Não") -> #ERROR! | F84: =IF($C$84="Sim","Caminho",IF($E$84="Sim","Escolhida","")) -> #ERROR! | K84: =IF($D$84<>"Sim","",IF($C$84="Sim","Já vem do Caminho: escolha outra",IF($E$84="Não","Acima do permitido ("&$B$66&"): esta fica sem Eficiência","")))
A85: Intimidação | B85: {=INDEX(Dados!$B$54:$B$71,15)} -> Presença | C85: =IF(OR($B$38="Intimidação",$D$38="Intimidação",$F$38="Intimidação"),"Sim","Não") -> Não | E85: =IF(OR($C$85="Sim",AND($D$85="Sim",COUNTIF($D$69:D85,"Sim")<=$B$66)),"Sim","Não") -> #ERROR! | F85: =IF($C$85="Sim","Caminho",IF($E$85="Sim","Escolhida","")) -> #ERROR! | K85: =IF($D$85<>"Sim","",IF($C$85="Sim","Já vem do Caminho: escolha outra",IF($E$85="Não","Acima do permitido ("&$B$66&"): esta fica sem Eficiência","")))
A86: Enganação | B86: {=INDEX(Dados!$B$54:$B$71,16)} -> Presença | C86: =IF(OR($B$38="Enganação",$D$38="Enganação",$F$38="Enganação"),"Sim","Não") -> Não | E86: =IF(OR($C$86="Sim",AND($D$86="Sim",COUNTIF($D$69:D86,"Sim")<=$B$66)),"Sim","Não") -> #ERROR! | F86: =IF($C$86="Sim","Caminho",IF($E$86="Sim","Escolhida","")) -> #ERROR! | K86: =IF($D$86<>"Sim","",IF($C$86="Sim","Já vem do Caminho: escolha outra",IF($E$86="Não","Acima do permitido ("&$B$66&"): esta fica sem Eficiência","")))
A87: Liderança | B87: {=INDEX(Dados!$B$54:$B$71,17)} -> Presença | C87: =IF(OR($B$38="Liderança",$D$38="Liderança",$F$38="Liderança"),"Sim","Não") -> Não | E87: =IF(OR($C$87="Sim",AND($D$87="Sim",COUNTIF($D$69:D87,"Sim")<=$B$66)),"Sim","Não") -> #ERROR! | F87: =IF($C$87="Sim","Caminho",IF($E$87="Sim","Escolhida","")) -> #ERROR! | K87: =IF($D$87<>"Sim","",IF($C$87="Sim","Já vem do Caminho: escolha outra",IF($E$87="Não","Acima do permitido ("&$B$66&"): esta fica sem Eficiência","")))
A88: Sintonia | B88: =$D$65 -> Discernimento | C88: =IF(OR($B$38="Sintonia",$D$38="Sintonia",$F$38="Sintonia"),"Sim","Não") -> Não | E88: =IF(OR($C$88="Sim",AND($D$88="Sim",COUNTIF($D$69:D88,"Sim")<=$B$66)),"Sim","Não") -> #ERROR! | F88: =IF($C$88="Sim","Caminho",IF($E$88="Sim","Escolhida","")) -> #ERROR! | K88: =IF($D$88<>"Sim","",IF($C$88="Sim","Já vem do Caminho: escolha outra",IF($E$88="Não","Acima do permitido ("&$B$66&"): esta fica sem Eficiência","")))
A90: Passo 8 — As cinco estatísticas: PV, Defesa, Esquiva, RD e Velocidade
A91: Armadura ou Vestimenta | C91: =IF($B$91="","Sem armadura: Defesa +0",IFERROR("Defesa +"&VLOOKUP($B$91,Dados!$A$474:$I$476,2,FALSE)&" · "&VLOOKUP($B$91,Dados!$A$474:$I$476,3,FALSE),"")) -> Sem armadura: Defesa +0 | K91: =IF($B$91="","",IF(COUNTIF(Dados!$S$6:$S$8,$B$91)=0,"Armadura fora da lista do capítulo 24",""))
A92: Números da armadura | B92: Defesa | C92: Velocidade | D92: RD | E92: Penalidade em Reflexos e Perícias de Agilidade | F92: Esquiva
A93: (automático, 24.1) | B93: =IFERROR(VLOOKUP($B$91,Dados!$A$474:$I$476,2,FALSE),0) -> 0 | C93: =IFERROR(VLOOKUP($B$91,Dados!$A$474:$I$476,7,FALSE),0) -> 0 | D93: =IFERROR(VLOOKUP($B$91,Dados!$A$474:$I$476,8,FALSE),0) -> 0 | E93: =IFERROR(VLOOKUP($B$91,Dados!$A$474:$I$476,9,FALSE),0) -> 0 | F93: =IFERROR(VLOOKUP($B$91,Dados!$A$474:$I$476,4,FALSE),"Permitida") -> Permitida
A94: Estatística | B94: Base | C94: Extra (equipamento e Bênçãos) | D94: Total | E94: Como se calcula | K94: Aviso
A95: PV máximos | B95: =25+5*$B$36+3*$F$46+($A$14-1)*(5+$B$36+$F$46) -> #ERROR! | C95: =$B$120 -> 0 | D95: =$B$95+$B$120 -> #ERROR! | E95: 25 + 5 × N + 3 × Bônus de Vigor + (nível - 1) × (5 + N + Bônus de Vigor) — 06.4
A96: Defesa | B96: =10+$F$45+$B$93 -> #ERROR! | C96: =$B$121 -> 0 | D96: =$B$96+$B$121 -> #ERROR! | E96: 10 + Bônus de Agilidade + armadura — 18.4
A97: Esquiva (Reação) | D97: =IF($F$93="Proibida","Proibida (Armadura Pesada)",$D$96+$C$14) -> #ERROR! | E97: Defesa + Eficiência; proibida com Armadura Pesada | K97: =IF($F$93="Proibida","Armadura Pesada não permite Esquiva","")
A98: RD | B98: =$D$93 -> 0 | C98: =$B$122 -> 0 | D98: =MIN($H$14,$B$98+$B$122) -> 0 | E98: ="Armadura + Bênçãos + equipamento, até o teto de RD ("&$H$14&") — 18.4" -> Armadura + Bênçãos + equipamento, até o teto de RD (6) — 18.4 | K98: =IF($B$98+$B$122>$H$14,"RD limitada ao teto ("&$H$14&")","")
A99: Velocidade (VEL) | B99: =10+$F$45+$B$37+$C$93 -> #ERROR! | C99: =$B$123 -> 0 | D99: =$B$99+$B$123 -> #ERROR! | E99: 10 + Bônus de Agilidade + Bônus do Caminho + armadura — 19.1 | K99: =IF(OR($D$99<7,$D$99>25),"Velocidade fora de 7 a 25 (19.1)","") -> #ERROR!
A101: Passos 9 a 11 — Habilidade, Ultimate e Bênção
A102: Passo 9 — Sua primeira Habilidade | B102: =IF(LEN($B$125)=0,"Preencha a Habilidade 1 na aba Habilidades","OK: "&$B$125) -> Preencha a Habilidade 1 na aba Habilidades
A103: Passo 10 — Sua Ultimate | B103: =IF(LEN($B$126)=0,"Preencha a Ultimate na aba Habilidades","OK: "&$B$126) -> Preencha a Ultimate na aba Habilidades
A104: Passo 11 — Sua primeira Bênção | B104: =IF(LEN(Caminho!$C$27)=0,"Preencha a Bênção do nível 1 na aba Caminho","OK: "&Caminho!$C$27) -> Preencha a Bênção do nível 1 na aba Caminho
A106: Passo 12 — Equipamento, nome e acabamento
A107: Arma: nome e descrição
A108: Categoria da arma (capítulo 18) | C108: =IF($B$108="","",IFERROR(VLOOKUP($B$108,Dados!$A$457:$J$462,2,FALSE)&" · alcance "&VLOOKUP($B$108,Dados!$A$457:$J$462,5,FALSE)&" · "&VLOOKUP($B$108,Dados!$A$457:$J$462,6,FALSE)&IF(VLOOKUP($B$108,Dados!$A$457:$J$462,10,FALSE)="Sim"," · duas mãos",""),"")) | K108: =IF($B$108="","",IF(COUNTIF(Dados!$T$6:$T$11,$B$108)=0,"Categoria fora da lista do capítulo 24",""))
A109: Atributo (só arma Média: Poder ou Agilidade) | C109: Atributo de ataque: | D109: =IF($B$108="","",IF($B$108="Média",IF(OR($B$109="Poder",$B$109="Agilidade"),$B$109,"Poder"),IFERROR(VLOOKUP($B$108,Dados!$A$457:$J$462,6,FALSE),""))) | K109: =IF(AND($B$109<>"",$B$108<>"Média"),"O atributo só se escolhe na arma Média",IF(AND($B$108="Média",$B$109=""),"Arma Média: escolha Poder ou Agilidade (contando Poder)",""))
A110: Elemento próprio da arma (vazio = Físico) | C110: Elemento do Ataque Básico: | D110: =IF($B$110="","Físico",$B$110) -> Físico | K110: =IF($B$110="","",IF(COUNTIF(Dados!$R$6:$R$12,$B$110)=0,"Elemento fora da lista do capítulo 20",""))
A111: Propriedade especial (no máximo 1) | C111: =IF(OR($B$111="",$B$111="Nenhuma"),"",IFERROR(VLOOKUP($B$111,Dados!$A$466:$B$470,2,FALSE),"")) | K111: =IF($B$111="","",IF(COUNTIF(Dados!$V$6:$V$11,$B$111)=0,"Só uma propriedade especial por arma (24.2): escolha uma da lista",""))
...

Sheet Em Jogo
A1: Resumo para o Jogador | E1: Recursos (preencha os amarelos) | I1: Calculadora de dano (23.1 e 23.3) | N1: Avisos desta aba (automático; o resumo aparece na linha 13) | P1: Valores auxiliares (automático) | S1: Usos (auxiliar): nome | T1: frequência | U1: entra? | V1: ordem | W1: Perícias (auxiliar) | AC1: Usos (auxiliar): frequência por linha
A2: Nome | B2: =IF(LEN('Criação'!$B$6)=0,"(sem nome)",""&'Criação'!$B$6) -> BF "Blake Foster" | E2: PV atual | G2: ="de "&'Criação'!$D$95&IF($Q$3="Sim"," · Morrendo"," · vazio = cheio") -> #ERROR! | I2: Dano recebido | K2: depois de dados e bônus | N2: =IF(LEN($F$2)=0,"",IF(ISNUMBER($F$2),IF($F$2>'Criação'!$D$95,"PV atual acima do máximo ("&'Criação'!$D$95&"). ","")&IF($F$2<0,"PV não fica abaixo de 0 (23.4). ",""),"PV atual precisa ser um número.")) | P2: PV atual usado (vazio = cheio) | Q2: =IF(ISNUMBER($F$2),MAX(0,INT($F$2)),'Criação'!$D$95) -> #ERROR! | S2: ="Descanso Curto" -> Descanso Curto | T2: ="2/dia" -> 2/dia | U2: =1 -> 1 | V2: =IF(U2=1,0+1,0) -> 1 | W2: Atletismo | X2: =0+IF('Criação'!$E$69="Sim",1,0) -> #ERROR! | Y2: =IF('Criação'!$E$69="Sim",X2,0) -> #ERROR! | Z2: =Testes!$I$16 -> #ERROR! | AA2: =IF(LEN(Testes!$J$16)>0,"Vantagem","") | AB2: {=IFERROR(INDEX($AA$2:$AA$19,MATCH(1,$Y$2:$Y$19,0)),"")} | AC2: {=IFERROR(INDEX($T$2:$T$16,MATCH(1,$V$2:$V$16,0)),"")} -> 2/dia | AD2: =IF($A$37="","",IF($A$37="Sangramento",IF(ISNUMBER($D$37),MIN(INT('Criação'!$D$95*5/100),3*IF(ISNUMBER($D$37),$D$37,0))&" por turno","5% PV, teto 3×Ef"),IF($A$37="Queimadura","2d6+"&IF(ISNUMBER($D$37),IF(ISNUMBER($D$37),$D$37,0),"Ef"),IF(OR($A$37="Choque",$A$37="Aprisionamento"),"1d6+"&IF(ISNUMBER($D$37),IF(ISNUMBER($D$37),$D$37,0),"Ef"),IF(OR($A$37="Cisalhamento de Vento",$A$37="Embaraço"),"1d6 por acúmulo",IF($A$37="Surpreso","casa pulada no 1º Ciclo","—"))))))
A3: Raça · Caminho | B3: =IF('Criação'!$B$25="","Raça?",'Criação'!$B$25)&" · "&IF('Criação'!$B$33="","Caminho?",'Criação'!$B$33)&" · nível "&'Criação'!$A$14 -> Humano · Caminho? · nível 1 | E3: Temporários | G3: ="ou Barreira · teto "&'Criação'!$I$14&" · não acumulam" -> ou Barreira · teto 6 · não acumulam | I3: Contínuo? | K3: Contínuo ignora a RD | N3: =IF(LEN($F$3)=0,"",IF(ISNUMBER($F$3),IF($F$3>'Criação'!$I$14,"PV temporários acima do teto ("&'Criação'!$I$14&", 23.3): conta o teto.",""),"PV temporários precisa ser um número.")) | P3: Morrendo (PV 0) | Q3: =IF($Q$2=0,"Sim","Não") -> #ERROR! | S3: ="Técnica" -> Técnica | T3: ="2/Desc. Longo" -> 2/Desc. Longo | U3: =1 -> 1 | V3: =IF(U3=1,MAX($V$2:V2)+1,0) -> 2 | W3: Acrobacia | X3: =X2+IF('Criação'!$E$70="Sim",1,0) -> #ERROR! | Y3: =IF('Criação'!$E$70="Sim",X3,0) -> #ERROR! | Z3: =Testes!$I$17 -> #ERROR! | AA3: =IF(LEN(Testes!$J$17)>0,"Vantagem","") | AB3: {=IFERROR(INDEX($AA$2:$AA$19,MATCH(2,$Y$2:$Y$19,0)),"")} | AC3: {=IFERROR(INDEX($T$2:$T$16,MATCH(2,$V$2:$V$16,0)),"")} -> 2/Desc. Longo | AD3: =IF($A$38="","",IF($A$38="Sangramento",IF(ISNUMBER($D$38),MIN(INT('Criação'!$D$95*5/100),3*IF(ISNUMBER($D$38),$D$38,0))&" por turno","5% PV, teto 3×Ef"),IF($A$38="Queimadura","2d6+"&IF(ISNUMBER($D$38),IF(ISNUMBER($D$38),$D$38,0),"Ef"),IF(OR($A$38="Choque",$A$38="Aprisionamento"),"1d6+"&IF(ISNUMBER($D$38),IF(ISNUMBER($D$38),$D$38,0),"Ef"),IF(OR($A$38="Cisalhamento de Vento",$A$38="Embaraço"),"1d6 por acúmulo",IF($A$38="Surpreso","casa pulada no 1º Ciclo","—"))))))
A4: Elemento | B4: =IF('Criação'!$B$60="","—",'Criação'!$B$60)&" (Ataque Básico: "&'Criação'!$D$110&")" -> — (Ataque Básico: Físico) | E4: Energia | G4: ="0 a 100 · Ultimate pronta: "&IF($Q$22="Sim","Sim","Não ("&Habilidades!$G$61&")") -> 0 a 100 · Ultimate pronta: Não (100) | I4: RD aplicada | J4: =IF($J$3="Sim",0,'Criação'!$D$98) -> 0 | N4: =IF(LEN($F$4)=0,"",IF(ISNUMBER($F$4),IF($F$4>100,"Energia acima de 100 é perdida (17.1).","")&IF($F$4<0,"Energia não fica abaixo de 0.",""),"Energia precisa ser um número.")) | P4: PV temporários usados (teto) | Q4: =IF(ISNUMBER($F$3),MAX(0,MIN('Criação'!$I$14,INT($F$3))),0) -> 0 | S4: ="To na sua mente" -> To na sua mente | T4: ="2/dia" -> 2/dia | U4: =IF('Criação'!$B$25="Haloviano",1,0) -> 0 | V4: =IF(U4=1,MAX($V$2:V3)+1,0) -> 0 | W4: Furtividade | X4: =X3+IF('Criação'!$E$71="Sim",1,0) -> #ERROR! | Y4: =IF('Criação'!$E$71="Sim",X4,0) -> #ERROR! | Z4: =Testes!$I$18 -> #ERROR! | AA4: =IF(LEN(Testes!$J$18)>0,"Vantagem","") | AB4: {=IFERROR(INDEX($AA$2:$AA$19,MATCH(3,$Y$2:$Y$19,0)),"")} | AC4: {=IFERROR(INDEX($T$2:$T$16,MATCH(3,$V$2:$V$16,0)),"")} | AD4: =IF($A$39="","",IF($A$39="Sangramento",IF(ISNUMBER($D$39),MIN(INT('Criação'!$D$95*5/100),3*IF(ISNUMBER($D$39),$D$39,0))&" por turno","5% PV, teto 3×Ef"),IF($A$39="Queimadura","2d6+"&IF(ISNUMBER($D$39),IF(ISNUMBER($D$39),$D$39,0),"Ef"),IF(OR($A$39="Choque",$A$39="Aprisionamento"),"1d6+"&IF(ISNUMBER($D$39),IF(ISNUMBER($D$39),$D$39,0),"Ef"),IF(OR($A$39="Cisalhamento de Vento",$A$39="Embaraço"),"1d6 por acúmulo",IF($A$39="Surpreso","casa pulada no 1º Ciclo","—"))))))
A5: PV | B5: =$Q$2&" / "&'Criação'!$D$95&IF($Q$4>0," (+"&$Q$4&" temporários)","")&IF($Q$3="Sim"," · Morrendo","") -> #ERROR! | E5: PH do grupo | G5: ="máx "&'Criação'!$E$16&" · início "&'Criação'!$F$16&" · +"&'Criação'!$G$16&" por acerto" -> máx 5 · início 3 · +1 por acerto | I5: Após a RD | J5: =IF(ISNUMBER($J$2),IF($J$2<=0,0,MAX(1,$J$2-$J$4)),0) -> 0 | K5: mínimo 1 | N5: =IF(LEN($F$5)=0,"",IF(ISNUMBER($F$5),IF($F$5>'Criação'!$E$16,"PH acima do máximo do grupo ("&'Criação'!$E$16&", 16.2).",""),"PH precisa ser um número.")) | P5: Energia usada (0 a 100) | Q5: =IF(ISNUMBER($F$4),MAX(0,MIN(100,INT($F$4))),0) -> 0 | S5: ="Efeito do Cone de Luz" -> Efeito do Cone de Luz | T5: =IF(Equipamento!$P$28=1,"1/combate","1/Ciclo") -> 1/Ciclo | U5: =IF(Equipamento!$P$28>0,1,0) -> 0 | V5: =IF(U5=1,MAX($V$2:V4)+1,0) -> 0 | W5: Pilotagem | X5: =X4+IF('Criação'!$E$72="Sim",1,0) -> #ERROR! | Y5: =IF('Criação'!$E$72="Sim",X5,0) -> #ERROR! | Z5: =Testes!$I$19 -> #ERROR! | AA5: =IF(LEN(Testes!$J$19)>0,"Vantagem","") | AB5: {=IFERROR(INDEX($AA$2:$AA$19,MATCH(4,$Y$2:$Y$19,0)),"")} | AC5: {=IFERROR(INDEX($T$2:$T$16,MATCH(4,$V$2:$V$16,0)),"")} | AD5: =IF($A$40="","",IF($A$40="Sangramento",IF(ISNUMBER($D$40),MIN(INT('Criação'!$D$95*5/100),3*IF(ISNUMBER($D$40),$D$40,0))&" por turno","5% PV, teto 3×Ef"),IF($A$40="Queimadura","2d6+"&IF(ISNUMBER($D$40),IF(ISNUMBER($D$40),$D$40,0),"Ef"),IF(OR($A$40="Choque",$A$40="Aprisionamento"),"1d6+"&IF(ISNUMBER($D$40),IF(ISNUMBER($D$40),$D$40,0),"Ef"),IF(OR($A$40="Cisalhamento de Vento",$A$40="Embaraço"),"1d6 por acúmulo",IF($A$40="Surpreso","casa pulada no 1º Ciclo","—"))))))
A6: Defesa · Esquiva | B6: ='Criação'!$D$96&IF($Q$16>'Criação'!$D$96," ("&$Q$16&" com temporários)","")&" · Esquiva "&IF(ISNUMBER('Criação'!$D$97),'Criação'!$D$97,"proibida") -> #ERROR! | E6: Esforço | G6: =IF('Criação'!$B$25="Humano","máx 1 · volta no Descanso Longo","só para Humano") -> máx 1 · volta no Descanso Longo | I6: Absorvido | J6: =MIN($Q$4,$J$5) -> 0 | K6: pelos temporários | N6: =IF(LEN($F$6)=0,"",IF(ISNUMBER($F$6),IF('Criação'!$B$25<>"Humano","O Esforço é traço do Humano (05). ","")&IF($F$6>1,"Esforço máximo 1 (05).",""),"Esforço precisa ser um número.")) | P6: Memoespírito ativo (só A Recordação) | Q6: =IF(AND($F$7="Sim",'Criação'!$B$33="A Recordação"),"Sim","Não") -> Não | S6: ="Corda de Ligação" -> Corda de Ligação | T6: ="1/combate" -> 1/combate | U6: =IF(Equipamento!$G$41>0,1,0) -> 0 | V6: =IF(U6=1,MAX($V$2:V5)+1,0) -> 0 | W6: Resistência | X6: =X5+IF('Criação'!$E$73="Sim",1,0) -> #ERROR! | Y6: =IF('Criação'!$E$73="Sim",X6,0) -> #ERROR! | Z6: =Testes!$I$20 -> #ERROR! | AA6: =IF(LEN(Testes!$J$20)>0,"Vantagem","") | AB6: {=IFERROR(INDEX($AA$2:$AA$19,MATCH(5,$Y$2:$Y$19,0)),"")} | AC6: {=IFERROR(INDEX($T$2:$T$16,MATCH(5,$V$2:$V$16,0)),"")}
A7: RD · Velocidade | B7: ="RD "&'Criação'!$D$98&" · VEL "&'Criação'!$D$99 -> #ERROR! | E7: Memoespírito | G7: =IF('Criação'!$B$33="A Recordação","PV dele (máx "&Caminho!$B$80&")","só A Recordação") -> só A Recordação | I7: PV perdidos | J7: =$J$5-$J$6 -> 0 | N7: =IF(AND(OR($F$7="Sim",LEN($H$7)>0),'Criação'!$B$33<>"A Recordação"),"Memoespírito só na Recordação: não conta. ","")&IF(LEN($H$7)=0,"",IF(ISNUMBER($H$7),IF(AND('Criação'!$B$33="A Recordação",$H$7>Caminho!$B$80),"PV do Memoespírito acima do máximo ("&Caminho!$B$80&"). ",""),"PV do Memoespírito precisa ser um número.")) | P7: Fúria (Sacrifício Desesperado, máx. 2) | Q7: =IF($G$8="Fúria",MIN(2,IF(ISNUMBER($F$8),MAX(0,INT($F$8)),0)),0) -> 0 | S7: =""&Caminho!$I$27 | T7: =IF(Caminho!$H$27="Uma vez por turno","1/turno",IF(Caminho!$H$27="Uma vez por Ciclo","1/Ciclo",IF(Caminho!$H$27="Uma vez por combate por alvo","1/combate/alvo",IF(Caminho!$H$27="Uma vez por combate","1/combate",IF(Caminho!$H$27="Uma vez por Descanso Longo","1/Desc. Longo",IF(Caminho!$H$27="Uma vez por sessão","1/sessão",IF(Caminho!$H$27="Duas vezes por dia","2/dia",""&Caminho!$H$27))))))) | U7: =IF(AND(LEN(Caminho!$I$27)>0,LEN(Caminho!$H$27)>0,Caminho!$H$27<>"Sem limite declarado"),1,0) -> 0 | V7: =IF(U7=1,MAX($V$2:V6)+1,0) -> 0 | W7: Tecnologia | X7: =X6+IF('Criação'!$E$75="Sim",1,0) -> #ERROR! | Y7: =IF('Criação'!$E$75="Sim",X7,0) -> #ERROR! | Z7: =Testes!$I$22 -> #ERROR! | AA7: =IF(LEN(Testes!$J$22)>0,"Vantagem","") | AB7: {=IFERROR(INDEX($AA$2:$AA$19,MATCH(6,$Y$2:$Y$19,0)),"")} | AC7: {=IFERROR(INDEX($T$2:$T$16,MATCH(6,$V$2:$V$16,0)),"")}
A8: DT das Habilidades | B8: ='Criação'!$B$56&" · ataque de Habilidade "&'Criação'!$C$57 -> #ERROR! | E8: Acúmulos | G8: =IF((COUNTIF(Caminho!$I$27:$I$36,"Sacrifício Desesperado")>0),"Fúria",IF((COUNTIF(Caminho!$I$27:$I$36,"Florescimento da Alma")>0),"Florescimento",IF((COUNTIF(Caminho!$I$27:$I$36,"Memória Devastadora")>0),"Fragmentos de Memória",IF('Criação'!$B$33="A Erudição","Acúmulos de Cálculo","—")))) -> — | H8: =IF($G$8="—","sem acúmulo","máx "&IF($G$8="Fúria",2,IF($G$8="Acúmulos de Cálculo",IF((COUNTIF(Caminho!$I$27:$I$36,"Teto Rompido")>0),7,5),IF($G$8="—",0,5)))) -> sem acúmulo | I8: PV novo | J8: =MAX(0,$Q$2-$J$7) -> #ERROR! | K8: ="PV novo: "&$J$8&" · temp. "&($Q$4-$J$6) -> #ERROR! | N8: =IF(LEN($F$8)=0,"",IF(ISNUMBER($F$8),IF($G$8="—","Nenhuma Bênção sua tem acúmulo neste campo.",IF($F$8>IF($G$8="Fúria",2,IF($G$8="Acúmulos de Cálculo",IF((COUNTIF(Caminho!$I$27:$I$36,"Teto Rompido")>0),7,5),IF($G$8="—",0,5))),"Máximo "&IF($G$8="Fúria",2,IF($G$8="Acúmulos de Cálculo",IF((COUNTIF(Caminho!$I$27:$I$36,"Teto Rompido")>0),7,5),IF($G$8="—",0,5)))&" acúmulos de "&$G$8&".","")),"Acúmulos precisa ser um número.")) | P8: Florescimento (máx. 5) | Q8: =IF($G$8="Florescimento",MIN(5,IF(ISNUMBER($F$8),MAX(0,INT($F$8)),0)),0) -> 0 | S8: =""&Caminho!$I$28 | T8: =IF(Caminho!$H$28="Uma vez por turno","1/turno",IF(Caminho!$H$28="Uma vez por Ciclo","1/Ciclo",IF(Caminho!$H$28="Uma vez por combate por alvo","1/combate/alvo",IF(Caminho!$H$28="Uma vez por combate","1/combate",IF(Caminho!$H$28="Uma vez por Descanso Longo","1/Desc. Longo",IF(Caminho!$H$28="Uma vez por sessão","1/sessão",IF(Caminho!$H$28="Duas vezes por dia","2/dia",""&Caminho!$H$28))))))) | U8: =IF(AND(LEN(Caminho!$I$28)>0,LEN(Caminho!$H$28)>0,Caminho!$H$28<>"Sem limite declarado"),1,0) -> 0 | V8: =IF(U8=1,MAX($V$2:V7)+1,0) -> 0 | W8: Pesquisa | X8: =X7+IF('Criação'!$E$76="Sim",1,0) -> #ERROR! | Y8: =IF('Criação'!$E$76="Sim",X8,0) -> #ERROR! | Z8: =Testes!$I$23 -> #ERROR! | AA8: =IF(LEN(Testes!$J$23)>0,"Vantagem","") | AB8: {=IFERROR(INDEX($AA$2:$AA$19,MATCH(7,$Y$2:$Y$19,0)),"")} | AC8: {=IFERROR(INDEX($T$2:$T$16,MATCH(7,$V$2:$V$16,0)),"")}
A9: Melhor ataque | B9: =IF('Criação'!$B$108="","Habilidades "&'Criação'!$C$57,"Ataque Básico "&Equipamento!$B$13&" · "&Equipamento!$C$13&" (média "&Equipamento!$D$13&")") -> #ERROR! | E9: Marcas | G9: =IF((COUNTIF(Caminho!$I$27:$I$36,"Cicatriz da Destruição")>0),"Marcas da Ruína","—") -> — | H9: =IF($G$9="—","sem acúmulo","máx 5") -> sem acúmulo | I9: =IF($J$5=0,"Preencha o dano para ver o resultado",IF($Q$3="Sim","Já Morrendo: 1 falha (2 se crítico ou Nível 5+)",IF($J$8=0,"Cai a 0 PV: fica Morrendo (23.4)","Continua de pé"))) -> Preencha o dano para ver o resultado | N9: =IF(LEN($F$9)=0,"",IF(ISNUMBER($F$9),IF($G$9="—","Nenhuma Bênção sua tem acúmulo neste campo.",IF($F$9>5,"Máximo 5 Marcas da Ruína.","")),"Acúmulos precisa ser um número.")) | P9: Fragmentos de Memória (máx. 5) | Q9: =IF($G$8="Fragmentos de Memória",MIN(5,IF(ISNUMBER($F$8),MAX(0,INT($F$8)),0)),0) -> 0 | S9: =""&Caminho!$I$29 | T9: =IF(Caminho!$H$29="Uma vez por turno","1/turno",IF(Caminho!$H$29="Uma vez por Ciclo","1/Ciclo",IF(Caminho!$H$29="Uma vez por combate por alvo","1/combate/alvo",IF(Caminho!$H$29="Uma vez por combate","1/combate",IF(Caminho!$H$29="Uma vez por Descanso Longo","1/Desc. Longo",IF(Caminho!$H$29="Uma vez por sessão","1/sessão",IF(Caminho!$H$29="Duas vezes por dia","2/dia",""&Caminho!$H$29))))))) | U9: =IF(AND(LEN(Caminho!$I$29)>0,LEN(Caminho!$H$29)>0,Caminho!$H$29<>"Sem limite declarado"),1,0) -> 0 | V9: =IF(U9=1,MAX($V$2:V8)+1,0) -> 0 | W9: Ciência | X9: =X8+IF('Criação'!$E$77="Sim",1,0) -> #ERROR! | Y9: =IF('Criação'!$E$77="Sim",X9,0) -> #ERROR! | Z9: =Testes!$I$24 -> #ERROR! | AA9: =IF(LEN(Testes!$J$24)>0,"Vantagem","") | AB9: {=IFERROR(INDEX($AA$2:$AA$19,MATCH(8,$Y$2:$Y$19,0)),"")} | AC9: {=IFERROR(INDEX($T$2:$T$16,MATCH(8,$V$2:$V$16,0)),"")}
A10: Vantagens raciais | B10: =IF('Criação'!$B$25="Humano","Esforço (máximo 1 ponto)",IF('Criação'!$B$25="Intellitron","Tecnologia, Mecânica, descobrir Fraqueza",IF('Criação'!$B$25="Avginiano","Resistência e Percepção Mental, Força de Vontade",IF('Criação'!$B$25="Vulpes","Perícias de Presença e Força de Vontade",IF('Criação'!$B$25="Vidyadhara","Resistência Física contra água, frio e afogamento",IF('Criação'!$B$25="Xianzhouíta","todo Teste de Resistência, inclusive Morrendo","—")))))) -> Esforço (máximo 1 ponto) | E10: =IF('Criação'!$B$33="","Recurso do Caminho: escolha o Caminho",IF('Criação'!$B$33="A Destruição","PV como moeda: "&(2*'Criação'!$A$14)&" PV por ativação",IF('Criação'!$B$33="A Preservação","Barreira: teto "&$Q$17,IF('Criação'!$B$33="A Erudição","Acúmulos de Cálculo: máx "&IF((COUNTIF(Caminho!$I$27:$I$36,"Teto Rompido")>0),7,5),IF('Criação'!$B$33="A Caça","Marcação de Presa: 1 alvo · crítico "&IF((COUNTIF(Caminho!$I$27:$I$36,"Olho de Lan")>0),"19-20","20"),IF('Criação'!$B$33="A Euforia","Tabela do Riso: 1d6 (aba Caminho)",IF('Criação'!$B$33="A Recordação","Memoespírito: ficha na aba Caminho",IF('Criação'!$B$33="A Inexistência","Recurso: acúmulos de Marca do Vazio e Corrupção",IF('Criação'!$B$33="A Harmonia","Recurso: acúmulos de Eco da Vitória (máx 3)",IF('Criação'!$B$33="A Abundância","Recurso: acúmulos de Florescimento (máx 5)","Recurso do Caminho: escolha um Caminho da lista")))))))))) -> Recurso do Caminho: escolha o Caminho | I10: Cura recebida | K10: ="PV depois: "&IF(ISNUMBER($J$10),MIN('Criação'!$D$95,$Q$2+MAX(0,$J$10)),$Q$2) -> #ERROR! | N10: =IF(LEN($J$2)=0,"",IF(ISNUMBER($J$2),IF($J$2<0,"Dano não é negativo: use a cura.",""),"Dano recebido precisa ser um número.")) | P10: Acúmulos de Cálculo (máx. 5 ou 7) | Q10: =IF($G$8="Acúmulos de Cálculo",MIN(IF((COUNTIF(Caminho!$I$27:$I$36,"Teto Rompido")>0),7,5),IF(ISNUMBER($F$8),MAX(0,INT($F$8)),0)),0) -> 0 | S10: =""&Caminho!$I$30 | T10: =IF(Caminho!$H$30="Uma vez por turno","1/turno",IF(Caminho!$H$30="Uma vez por Ciclo","1/Ciclo",IF(Caminho!$H$30="Uma vez por combate por alvo","1/combate/alvo",IF(Caminho!$H$30="Uma vez por combate","1/combate",IF(Caminho!$H$30="Uma vez por Descanso Longo","1/Desc. Longo",IF(Caminho!$H$30="Uma vez por sessão","1/sessão",IF(Caminho!$H$30="Duas vezes por dia","2/dia",""&Caminho!$H$30))))))) | U10: =IF(AND(LEN(Caminho!$I$30)>0,LEN(Caminho!$H$30)>0,Caminho!$H$30<>"Sem limite declarado"),1,0) -> 0 | V10: =IF(U10=1,MAX($V$2:V9)+1,0) -> 0 | W10: Mecânica | X10: =X9+IF('Criação'!$E$78="Sim",1,0) -> #ERROR! | Y10: =IF('Criação'!$E$78="Sim",X10,0) -> #ERROR! | Z10: =Testes!$I$25 -> #ERROR! | AA10: =IF(LEN(Testes!$J$25)>0,"Vantagem","") | AB10: {=IFERROR(INDEX($AA$2:$AA$19,MATCH(9,$Y$2:$Y$19,0)),"")}
A11: Condições ativas | B11: =IF($Q$24=0,"Nenhuma",$Q$25&IF($Q$24>1," + "&($Q$24-1)&" (linhas 37-40)","")) -> #ERROR! | E11: ="Energia de equipamento: "&IF(Equipamento!$G$41>0,"Corda +"&Equipamento!$G$41&" ao entrar na Fila","sem Corda")&IF(Equipamento!$P$28>=3," · Cone +5 por Ciclo","") -> Energia de equipamento: sem Corda | I11: Descanso Curto | J11: =2*'Criação'!$A$14+'Criação'!$F$46 -> #ERROR! | K11: ="PV depois: "&MIN('Criação'!$D$95,$Q$2+$J$11) -> #ERROR! | N11: =IF(AND(LEN($J$10)>0,NOT(ISNUMBER($J$10))),"Cura precisa ser um número.","") | P11: Marcas da Ruína (máx. 5) | Q11: =IF($G$9="Marcas da Ruína",MIN(5,IF(ISNUMBER($F$9),MAX(0,INT($F$9)),0)),0) -> 0 | S11: =""&Caminho!$I$31 | T11: =IF(Caminho!$H$31="Uma vez por turno","1/turno",IF(Caminho!$H$31="Uma vez por Ciclo","1/Ciclo",IF(Caminho!$H$31="Uma vez por combate por alvo","1/combate/alvo",IF(Caminho!$H$31="Uma vez por combate","1/combate",IF(Caminho!$H$31="Uma vez por Descanso Longo","1/Desc. Longo",IF(Caminho!$H$31="Uma vez por sessão","1/sessão",IF(Caminho!$H$31="Duas vezes por dia","2/dia",""&Caminho!$H$31))))))) | U11: =IF(AND(LEN(Caminho!$I$31)>0,LEN(Caminho!$H$31)>0,Caminho!$H$31<>"Sem limite declarado"),1,0) -> 0 | V11: =IF(U11=1,MAX($V$2:V10)+1,0) -> 0 | W11: Percepção | X11: =X10+IF('Criação'!$E$79="Sim",1,0) -> #ERROR! | Y11: =IF('Criação'!$E$79="Sim",X11,0) -> #ERROR! | Z11: =Testes!$I$26 -> #ERROR! | AA11: =IF(LEN(Testes!$J$26)>0,"Vantagem","") | AB11: {=IFERROR(INDEX($AA$2:$AA$19,MATCH(10,$Y$2:$Y$19,0)),"")}
A12: Pode ser Executado? | B12: =IF('Criação'!$B$25="Xianzhouíta","Não (Xianzhouíta, 23.5)",IF($Q$3="Sim","Sim: está Morrendo (23.5)","Só se estiver Morrendo (23.5)")) -> #ERROR! | E12: =IF(Equipamento!$B$58="Não consegue se mover","Movimento: não se move (carga)",IF($Q$20=1,"Movimento: Lentidão, só Esforço Total move 1 passo","Movimento: 1 Distância por ação · Esforço Total: 2")) -> #ERROR! | I12: ="Descanso Longo: PV cheios, sem condições, Esforço de volta" -> Descanso Longo: PV cheios, sem condições, Esforço de volta | N12: =IF(OR(AND(LEN($D$33)>0,NOT(ISNUMBER($D$33))),AND(LEN($F$33)>0,NOT(ISNUMBER($F$33)))),"Sucessos e falhas precisam ser números de 0 a 3. ",IF(OR(IF(ISNUMBER($D$33),$D$33,0)>3,IF(ISNUMBER($F$33),$F$33,0)>3),"Sucessos e falhas vão de 0 a 3. ",""))&IF(AND($Q$3="Não",IF(ISNUMBER($D$33),$D$33,0)+IF(ISNUMBER($F$33),$F$33,0)>0),"Contador de Morrendo preenchido com PV acima de 0: a cura zera o contador (23.4).","") -> #ERROR! | P12: Instinto de Sobrevivência ligado (PV ≤ 1/3) | Q12: =IF(AND((COUNTIF(Caminho!$I$27:$I$36,"Instinto de Sobrevivência")>0),ISNUMBER($F$2),$Q$2*3<='Criação'!$D$95),1,0) -> #ERROR! | S12: =""&Caminho!$I$32 | T12: =IF(Caminho!$H$32="Uma vez por turno","1/turno",IF(Caminho!$H$32="Uma vez por Ciclo","1/Ciclo",IF(Caminho!$H$32="Uma vez por combate por alvo","1/combate/alvo",IF(Caminho!$H$32="Uma vez por combate","1/combate",IF(Caminho!$H$32="Uma vez por Descanso Longo","1/Desc. Longo",IF(Caminho!$H$32="Uma vez por sessão","1/sessão",IF(Caminho!$H$32="Duas vezes por dia","2/dia",""&Caminho!$H$32))))))) | U12: =IF(AND(LEN(Caminho!$I$32)>0,LEN(Caminho!$H$32)>0,Caminho!$H$32<>"Sem limite declarado"),1,0) -> 0 | V12: =IF(U12=1,MAX($V$2:V11)+1,0) -> 0 | W12: Sobrevivência | X12: =X11+IF('Criação'!$E$80="Sim",1,0) -> #ERROR! | Y12: =IF('Criação'!$E$80="Sim",X12,0) -> #ERROR! | Z12: =Testes!$I$27 -> #ERROR! | AA12: =IF(LEN(Testes!$J$27)>0,"Vantagem","")
A13: =IF((IF(LEN(N2)>0,1,0)+IF(LEN(N3)>0,1,0)+IF(LEN(N4)>0,1,0)+IF(LEN(N5)>0,1,0)+IF(LEN(N6)>0,1,0)+IF(LEN(N7)>0,1,0)+IF(LEN(N8)>0,1,0)+IF(LEN(N9)>0,1,0)+IF(LEN(N10)>0,1,0)+IF(LEN(N11)>0,1,0)+IF(LEN(N12)>0,1,0)+IF(LEN(N13)>0,1,0)+IF(LEN(N14)>0,1,0)+IF(LEN(N15)>0,1,0)+IF(LEN(N16)>0,1,0)+IF(LEN(N17)>0,1,0)+IF(LEN(N18)>0,1,0)+IF(LEN(N19)>0,1,0)+IF(LEN(N20)>0,1,0))=0,"","Avisos ("&(IF(LEN(N2)>0,1,0)+IF(LEN(N3)>0,1,0)+IF(LEN(N4)>0,1,0)+IF(LEN(N5)>0,1,0)+IF(LEN(N6)>0,1,0)+IF(LEN(N7)>0,1,0)+IF(LEN(N8)>0,1,0)+IF(LEN(N9)>0,1,0)+IF(LEN(N10)>0,1,0)+IF(LEN(N11)>0,1,0)+IF(LEN(N12)>0,1,0)+IF(LEN(N13)>0,1,0)+IF(LEN(N14)>0,1,0)+IF(LEN(N15)>0,1,0)+IF(LEN(N16)>0,1,0)+IF(LEN(N17)>0,1,0)+IF(LEN(N18)>0,1,0)+IF(LEN(N19)>0,1,0)+IF(LEN(N20)>0,1,0))&"): "&IF(LEN(N2)>0,N2,IF(LEN(N3)>0,N3,IF(LEN(N4)>0,N4,IF(LEN(N5)>0,N5,IF(LEN(N6)>0,N6,IF(LEN(N7)>0,N7,IF(LEN(N8)>0,N8,IF(LEN(N9)>0,N9,IF(LEN(N10)>0,N10,IF(LEN(N11)>0,N11,IF(LEN(N12)>0,N12,IF(LEN(N13)>0,N13,IF(LEN(N14)>0,N14,IF(LEN(N15)>0,N15,IF(LEN(N16)>0,N16,IF(LEN(N17)>0,N17,IF(LEN(N18)>0,N18,IF(LEN(N19)>0,N19,IF(LEN(N20)>0,N20,"")))))))))))))))))))&IF((IF(LEN(N2)>0,1,0)+IF(LEN(N3)>0,1,0)+IF(LEN(N4)>0,1,0)+IF(LEN(N5)>0,1,0)+IF(LEN(N6)>0,1,0)+IF(LEN(N7)>0,1,0)+IF(LEN(N8)>0,1,0)+IF(LEN(N9)>0,1,0)+IF(LEN(N10)>0,1,0)+IF(LEN(N11)>0,1,0)+IF(LEN(N12)>0,1,0)+IF(LEN(N13)>0,1,0)+IF(LEN(N14)>0,1,0)+IF(LEN(N15)>0,1,0)+IF(LEN(N16)>0,1,0)+IF(LEN(N17)>0,1,0)+IF(LEN(N18)>0,1,0)+IF(LEN(N19)>0,1,0)+IF(LEN(N20)>0,1,0))>1," · os outros estão na coluna N","")) -> #ERROR! | N13: =IF($A$37="","",IF($A$37="Quebrado","Quebrado é só de inimigos (20.3).",IF($A$37="Morrendo","Morrendo liga sozinho com PV 0.",IF(COUNTIF(Dados!$Y$6:$Y$18,$A$37)=0,"Condição fora da lista de 21.5.","")))) | P13: Bônus temporário no Teste de Ataque (antes do teto) | Q13: =2*$Q$12+IF(AND(($Q$6="Sim"),Caminho!$B$57="Catalisador"),1,0)+IF(AND(($Q$6="Sim"),COUNTIF(Caminho!$C$75:$C$77,"Fusão de Memórias")>0),1,0)+IF(AND(($Q$6="Sim"),(COUNTIF(Caminho!$I$27:$I$36,"Memória Compartilhada")>0)),1,0)+COUNTIF(Equipamento!$P$45:$P$47,"Teste de Ataque") -> #ERROR! | S13: =""&Caminho!$I$33 | T13: =IF(Caminho!$H$33="Uma vez por turno","1/turno",IF(Caminho!$H$33="Uma vez por Ciclo","1/Ciclo",IF(Caminho!$H$33="Uma vez por combate por alvo","1/combate/alvo",IF(Caminho!$H$33="Uma vez por combate","1/combate",IF(Caminho!$H$33="Uma vez por Descanso Longo","1/Desc. Longo",IF(Caminho!$H$33="Uma vez por sessão","1/sessão",IF(Caminho!$H$33="Duas vezes por dia","2/dia",""&Caminho!$H$33))))))) | U13: =IF(AND(LEN(Caminho!$I$33)>0,LEN(Caminho!$H$33)>0,Caminho!$H$33<>"Sem limite declarado"),1,0) -> 0 | V13: =IF(U13=1,MAX($V$2:V12)+1,0) -> 0 | W13: Intuição | X13: =X12+IF('Criação'!$E$81="Sim",1,0) -> #ERROR! | Y13: =IF('Criação'!$E$81="Sim",X13,0) -> #ERROR! | Z13: =Testes!$I$28 -> #ERROR! | AA13: =IF(LEN(Testes!$J$28)>0,"Vantagem","")
A14: Ações — Ataque Básico (18), Habilidades (16) e Ultimate (17) | N14: =IF($A$38="","",IF($A$38="Quebrado","Quebrado é só de inimigos (20.3).",IF($A$38="Morrendo","Morrendo liga sozinho com PV 0.",IF(COUNTIF(Dados!$Y$6:$Y$18,$A$38)=0,"Condição fora da lista de 21.5.","")))) | P14: Bônus temporário no Teste de Ataque (no teto) | Q14: =MIN('Criação'!$J$14,$Q$13) -> #ERROR! | S14: =""&Caminho!$I$34 | T14: =IF(Caminho!$H$34="Uma vez por turno","1/turno",IF(Caminho!$H$34="Uma vez por Ciclo","1/Ciclo",IF(Caminho!$H$34="Uma vez por combate por alvo","1/combate/alvo",IF(Caminho!$H$34="Uma vez por combate","1/combate",IF(Caminho!$H$34="Uma vez por Descanso Longo","1/Desc. Longo",IF(Caminho!$H$34="Uma vez por sessão","1/sessão",IF(Caminho!$H$34="Duas vezes por dia","2/dia",""&Caminho!$H$34))))))) | U14: =IF(AND(LEN(Caminho!$I$34)>0,LEN(Caminho!$H$34)>0,Caminho!$H$34<>"Sem limite declarado"),1,0) -> 0 | V14: =IF(U14=1,MAX($V$2:V13)+1,0) -> 0 | W14: Investigação | X14: =X13+IF('Criação'!$E$82="Sim",1,0) -> #ERROR! | Y14: =IF('Criação'!$E$82="Sim",X14,0) -> #ERROR! | Z14: =Testes!$I$29 -> #ERROR! | AA14: =IF(LEN(Testes!$J$29)>0,"Vantagem","")
A15: Ataque Básico | C15: Ataque | D15: Dano | E15: Média | F15: Do atributo | G15: Equipamento | H15: Contra Fraqueza | I15: Crítico | J15: RT | K15: Alcance · Elemento | N15: =IF($A$39="","",IF($A$39="Quebrado","Quebrado é só de inimigos (20.3).",IF($A$39="Morrendo","Morrendo liga sozinho com PV 0.",IF(COUNTIF(Dados!$Y$6:$Y$18,$A$39)=0,"Condição fora da lista de 21.5.","")))) | P15: Defesa temporária (Florescimento, Memória da Guarda) | Q15: =$Q$8+IF(AND((COUNTIF(Caminho!$I$27:$I$36,"Fragmentos do Eu Perdido")>0),($Q$6="Sim"),Caminho!$B$95="Guarda"),'Criação'!$C$14,0) -> 0 | S15: =""&Caminho!$I$35 | T15: =IF(Caminho!$H$35="Uma vez por turno","1/turno",IF(Caminho!$H$35="Uma vez por Ciclo","1/Ciclo",IF(Caminho!$H$35="Uma vez por combate por alvo","1/combate/alvo",IF(Caminho!$H$35="Uma vez por combate","1/combate",IF(Caminho!$H$35="Uma vez por Descanso Longo","1/Desc. Longo",IF(Caminho!$H$35="Uma vez por sessão","1/sessão",IF(Caminho!$H$35="Duas vezes por dia","2/dia",""&Caminho!$H$35))))))) | U15: =IF(AND(LEN(Caminho!$I$35)>0,LEN(Caminho!$H$35)>0,Caminho!$H$35<>"Sem limite declarado"),1,0) -> 0 | V15: =IF(U15=1,MAX($V$2:V14)+1,0) -> 0 | W15: Persuasão | X15: =X14+IF('Criação'!$E$84="Sim",1,0) -> #ERROR! | Y15: =IF('Criação'!$E$84="Sim",X15,0) -> #ERROR! | Z15: =Testes!$I$31 -> #ERROR! | AA15: =IF(LEN(Testes!$J$31)>0,"Vantagem","")
A16: =IF('Criação'!$B$108="","Arma principal: —",IF(LEN('Criação'!$B$107)=0,"Arma "&'Criação'!$B$108,""&'Criação'!$B$107)) -> Arma principal: — | C16: =Equipamento!$B$13 -> — | D16: =Equipamento!$C$13 | E16: =Equipamento!$D$13 | F16: =Equipamento!$E$13 | G16: =Equipamento!$F$13 | H16: =IF(LEN(Equipamento!$G$13)=0,"",Equipamento!$G$13&" ("&Equipamento!$H$13&")") | I16: =Equipamento!$I$13 | J16: =Equipamento!$J$13 | K16: =IF(LEN(Equipamento!$K$13)=0,"",Equipamento!$K$13&" · "&Equipamento!$L$13) | N16: =IF($A$40="","",IF($A$40="Quebrado","Quebrado é só de inimigos (20.3).",IF($A$40="Morrendo","Morrendo liga sozinho com PV 0.",IF(COUNTIF(Dados!$Y$6:$Y$18,$A$40)=0,"Condição fora da lista de 21.5.","")))) | P16: Defesa com temporários | Q16: ='Criação'!$D$96+MIN('Criação'!$J$14,$Q$15) -> #ERROR! | S16: =""&Caminho!$I$36 | T16: =IF(Caminho!$H$36="Uma vez por turno","1/turno",IF(Caminho!$H$36="Uma vez por Ciclo","1/Ciclo",IF(Caminho!$H$36="Uma vez por combate por alvo","1/combate/alvo",IF(Caminho!$H$36="Uma vez por combate","1/combate",IF(Caminho!$H$36="Uma vez por Descanso Longo","1/Desc. Longo",IF(Caminho!$H$36="Uma vez por sessão","1/sessão",IF(Caminho!$H$36="Duas vezes por dia","2/dia",""&Caminho!$H$36))))))) | U16: =IF(AND(LEN(Caminho!$I$36)>0,LEN(Caminho!$H$36)>0,Caminho!$H$36<>"Sem limite declarado"),1,0) -> 0 | V16: =IF(U16=1,MAX($V$2:V15)+1,0) -> 0 | W16: Intimidação | X16: =X15+IF('Criação'!$E$85="Sim",1,0) -> #ERROR! | Y16: =IF('Criação'!$E$85="Sim",X16,0) -> #ERROR! | Z16: =Testes!$I$32 -> #ERROR! | AA16: =IF(LEN(Testes!$J$32)>0,"Vantagem","")
A17: =IF(Equipamento!$C$8="","Arma secundária: —",IF(LEN(Equipamento!$B$8)=0,"Arma "&Equipamento!$C$8,""&Equipamento!$B$8)) -> Arma secundária: — | C17: =Equipamento!$B$14 -> — | D17: =Equipamento!$C$14 | E17: =Equipamento!$D$14 | F17: =Equipamento!$E$14 | G17: =Equipamento!$F$14 | H17: =IF(LEN(Equipamento!$G$14)=0,"",Equipamento!$G$14&" ("&Equipamento!$H$14&")") | I17: =Equipamento!$I$14 | J17: =Equipamento!$J$14 | K17: =IF(LEN(Equipamento!$K$14)=0,"",Equipamento!$K$14&" · "&Equipamento!$L$14) | N17: =IF(MAX($V$2:$V$16)>8,"Mais usos do que cabem aqui: veja a frequência das Bênçãos na aba Caminho.","") | P17: Teto de Barreira (Preservação) | Q17: =IF('Criação'!$B$33="A Preservação",3*'Criação'!$C$14,"") | W17: Enganação | X17: =X16+IF('Criação'!$E$86="Sim",1,0) -> #ERROR! | Y17: =IF('Criação'!$E$86="Sim",X17,0) -> #ERROR! | Z17: =Testes!$I$33 -> #ERROR! | AA17: =IF(LEN(Testes!$J$33)>0,"Vantagem","")
A18: Habilidade | C18: Rolagem | D18: Dano · média | E18: Nível · PH · RT · alvos | G18: Habilidade | I18: Rolagem | J18: Dano · média | K18: Nível · PH · RT · alvos | N18: =IF(AND(ISNUMBER($J$33),$J$33>2),"Descanso Curto: até 2 por dia (23.6).","") | P18: Silenciado | Q18: =IF(COUNTIF($A$37:$A$40,"Silenciado")>0,1,0) -> 0 | W18: Liderança | X18: =X17+IF('Criação'!$E$87="Sim",1,0) -> #ERROR! | Y18: =IF('Criação'!$E$87="Sim",X18,0) -> #ERROR! | Z18: =Testes!$I$34 -> #ERROR! | AA18: =IF(LEN(Testes!$J$34)>0,"Vantagem","")
A19: =IF(Habilidades!$P$12=0,"—",Habilidades!$B$34) -> — | C19: =IF(Habilidades!$P$12=0,"",IF(LEN(IF($Q$19=1,"BLOQUEADA",IF(AND($Q$18=1,Habilidades!$S$12>=4),"BLOQUEADA","")))>0,IF($Q$19=1,"BLOQUEADA",IF(AND($Q$18=1,Habilidades!$S$12>=4),"BLOQUEADA","")),IF(LEN(Habilidades!$F$34)=0,IF(Habilidades!$C$12="Passiva","Passiva","—"),Habilidades!$F$34))) | D19: =IF(LEN(Habilidades!$D$34)=0,"",Habilidades!$D$34&" ("&Habilidades!$E$34&")") | E19: =IF(Habilidades!$P$12=0,"",Habilidades!$S$12&" · "&Habilidades!$G$34&" PH · RT "&Habilidades!$H$34&" · "&Habilidades!$J$34&IF(Habilidades!$J$34=1," alvo"," alvos")) | G19: =IF(Habilidades!$P$16=0,"—",Habilidades!$B$38) -> — | I19: =IF(Habilidades!$P$16=0,"",IF(LEN(IF($Q$19=1,"BLOQUEADA",IF(AND($Q$18=1,Habilidades!$S$16>=4),"BLOQUEADA","")))>0,IF($Q$19=1,"BLOQUEADA",IF(AND($Q$18=1,Habilidades!$S$16>=4),"BLOQUEADA","")),IF(LEN(Habilidades!$F$38)=0,IF(Habilidades!$C$16="Passiva","Passiva","—"),Habilidades!$F$38))) | J19: =IF(LEN(Habilidades!$D$38)=0,"",Habilidades!$D$38&" ("&Habilidades!$E$38&")") | K19: =IF(Habilidades!$P$16=0,"",Habilidades!$S$16&" · "&Habilidades!$G$38&" PH · RT "&Habilidades!$H$38&" · "&Habilidades!$J$38&IF(Habilidades!$J$38=1," alvo"," alvos")) | N19: =IF($Q$13>'Criação'!$J$14,"Bônus temporário no Teste de Ataque acima do teto (+"&'Criação'!$J$14&"): conta só o teto (26.6). ","")&IF($Q$15>'Criação'!$J$14,"Defesa temporária acima do teto (+"&'Criação'!$J$14&"): conta só o teto (26.6).","") -> #ERROR! | P19: Controlado | Q19: =IF(COUNTIF($A$37:$A$40,"Controlado")>0,1,0) -> 0 | W19: Sintonia | X19: =X18+IF('Criação'!$E$88="Sim",1,0) -> #ERROR! | Y19: =IF('Criação'!$E$88="Sim",X19,0) -> #ERROR! | Z19: =Testes!$I$35 -> #ERROR! | AA19: =IF(LEN(Testes!$J$35)>0,"Vantagem","")
A20: =IF(Habilidades!$P$13=0,"—",Habilidades!$B$35) -> — | C20: =IF(Habilidades!$P$13=0,"",IF(LEN(IF($Q$19=1,"BLOQUEADA",IF(AND($Q$18=1,Habilidades!$S$13>=4),"BLOQUEADA","")))>0,IF($Q$19=1,"BLOQUEADA",IF(AND($Q$18=1,Habilidades!$S$13>=4),"BLOQUEADA","")),IF(LEN(Habilidades!$F$35)=0,IF(Habilidades!$C$13="Passiva","Passiva","—"),Habilidades!$F$35))) | D20: =IF(LEN(Habilidades!$D$35)=0,"",Habilidades!$D$35&" ("&Habilidades!$E$35&")") | E20: =IF(Habilidades!$P$13=0,"",Habilidades!$S$13&" · "&Habilidades!$G$35&" PH · RT "&Habilidades!$H$35&" · "&Habilidades!$J$35&IF(Habilidades!$J$35=1," alvo"," alvos")) | G20: =IF(Habilidades!$P$17=0,"—",Habilidades!$B$39) -> — | I20: =IF(Habilidades!$P$17=0,"",IF(LEN(IF($Q$19=1,"BLOQUEADA",IF(AND($Q$18=1,Habilidades!$S$17>=4),"BLOQUEADA","")))>0,IF($Q$19=1,"BLOQUEADA",IF(AND($Q$18=1,Habilidades!$S$17>=4),"BLOQUEADA","")),IF(LEN(Habilidades!$F$39)=0,IF(Habilidades!$C$17="Passiva","Passiva","—"),Habilidades!$F$39))) | J20: =IF(LEN(Habilidades!$D$39)=0,"",Habilidades!$D$39&" ("&Habilidades!$E$39&")") | K20: =IF(Habilidades!$P$17=0,"",Habilidades!$S$17&" · "&Habilidades!$G$39&" PH · RT "&Habilidades!$H$39&" · "&Habilidades!$J$39&IF(Habilidades!$J$39=1," alvo"," alvos")) | N20: =IF($Q$21=1,"Surpreso: a sua casa é pulada no primeiro Ciclo.","") | P20: Lentidão (condição ou carga) | Q20: =IF(OR(COUNTIF($A$37:$A$40,"Lentidão")>0,Equipamento!$B$58="Lentidão"),1,0) -> #ERROR!
A21: =IF(Habilidades!$P$14=0,"—",Habilidades!$B$36) -> — | C21: =IF(Habilidades!$P$14=0,"",IF(LEN(IF($Q$19=1,"BLOQUEADA",IF(AND($Q$18=1,Habilidades!$S$14>=4),"BLOQUEADA","")))>0,IF($Q$19=1,"BLOQUEADA",IF(AND($Q$18=1,Habilidades!$S$14>=4),"BLOQUEADA","")),IF(LEN(Habilidades!$F$36)=0,IF(Habilidades!$C$14="Passiva","Passiva","—"),Habilidades!$F$36))) | D21: =IF(LEN(Habilidades!$D$36)=0,"",Habilidades!$D$36&" ("&Habilidades!$E$36&")") | E21: =IF(Habilidades!$P$14=0,"",Habilidades!$S$14&" · "&Habilidades!$G$36&" PH · RT "&Habilidades!$H$36&" · "&Habilidades!$J$36&IF(Habilidades!$J$36=1," alvo"," alvos")) | G21: =IF(Habilidades!$P$18=0,"—",Habilidades!$B$40) -> — | I21: =IF(Habilidades!$P$18=0,"",IF(LEN(IF($Q$19=1,"BLOQUEADA",IF(AND($Q$18=1,Habilidades!$S$18>=4),"BLOQUEADA","")))>0,IF($Q$19=1,"BLOQUEADA",IF(AND($Q$18=1,Habilidades!$S$18>=4),"BLOQUEADA","")),IF(LEN(Habilidades!$F$40)=0,IF(Habilidades!$C$18="Passiva","Passiva","—"),Habilidades!$F$40))) | J21: =IF(LEN(Habilidades!$D$40)=0,"",Habilidades!$D$40&" ("&Habilidades!$E$40&")") | K21: =IF(Habilidades!$P$18=0,"",Habilidades!$S$18&" · "&Habilidades!$G$40&" PH · RT "&Habilidades!$H$40&" · "&Habilidades!$J$40&IF(Habilidades!$J$40=1," alvo"," alvos")) | P21: Surpreso | Q21: =IF(COUNTIF($A$37:$A$40,"Surpreso")>0,1,0) -> 0
A22: =IF(Habilidades!$P$15=0,"—",Habilidades!$B$37) -> — | C22: =IF(Habilidades!$P$15=0,"",IF(LEN(IF($Q$19=1,"BLOQUEADA",IF(AND($Q$18=1,Habilidades!$S$15>=4),"BLOQUEADA","")))>0,IF($Q$19=1,"BLOQUEADA",IF(AND($Q$18=1,Habilidades!$S$15>=4),"BLOQUEADA","")),IF(LEN(Habilidades!$F$37)=0,IF(Habilidades!$C$15="Passiva","Passiva","—"),Habilidades!$F$37))) | D22: =IF(LEN(Habilidades!$D$37)=0,"",Habilidades!$D$37&" ("&Habilidades!$E$37&")") | E22: =IF(Habilidades!$P$15=0,"",Habilidades!$S$15&" · "&Habilidades!$G$37&" PH · RT "&Habilidades!$H$37&" · "&Habilidades!$J$37&IF(Habilidades!$J$37=1," alvo"," alvos")) | G22: =IF(Habilidades!$P$19=0,"—",Habilidades!$B$41) -> — | I22: =IF(Habilidades!$P$19=0,"",IF(LEN(IF($Q$19=1,"BLOQUEADA",IF(AND($Q$18=1,Habilidades!$S$19>=4),"BLOQUEADA","")))>0,IF($Q$19=1,"BLOQUEADA",IF(AND($Q$18=1,Habilidades!$S$19>=4),"BLOQUEADA","")),IF(LEN(Habilidades!$F$41)=0,IF(Habilidades!$C$19="Passiva","Passiva","—"),Habilidades!$F$41))) | J22: =IF(LEN(Habilidades!$D$41)=0,"",Habilidades!$D$41&" ("&Habilidades!$E$41&")") | K22: =IF(Habilidades!$P$19=0,"",Habilidades!$S$19&" · "&Habilidades!$G$41&" PH · RT "&Habilidades!$H$41&" · "&Habilidades!$J$41&IF(Habilidades!$J$41=1," alvo"," alvos")) | P22: Ultimate pronta | Q22: =IF($Q$5>=Habilidades!$G$61,"Sim","Não") -> Não
A23: =IF(LEN(Habilidades!$C$54)=0,"Ultimate: —",""&Habilidades!$C$54) -> Ultimate: — | C23: =IF(LEN(IF($Q$19=1,"BLOQUEADA",""))>0,IF($Q$19=1,"BLOQUEADA",""),IF(LEN(Habilidades!$F$61)=0,"—",Habilidades!$F$61)) -> — | D23: =IF(LEN(Habilidades!$D$61)=0,"",Habilidades!$D$61&" ("&Habilidades!$E$61&")") | E23: ="RT "&Habilidades!$H$61&" · "&Habilidades!$I$61&IF(Habilidades!$I$61=1," alvo"," alvos") -> RT 5 · 1 alvo | G23: ="Ultimate ("&$Q$5&"/"&Habilidades!$G$61&" de Energia): "&IF(LEN(IF($Q$19=1,"BLOQUEADA",""))>0,"BLOQUEADA (Controlado)",IF($Q$22="Sim","pronta, diga o nome em voz alta","faltam "&(Habilidades!$G$61-$Q$5))) -> Ultimate (0/100 de Energia): faltam 100 | P23: Condições ativas (texto inteiro) | Q23: =""&A37&IF(LEN(""&A38)>0,IF(LEN(""&A37)>0," · ","")&""&A38,"")&IF(LEN(""&A39)>0,IF(LEN(""&A37&""&A38)>0," · ","")&""&A39,"")&IF(LEN(""&A40)>0,IF(LEN(""&A37&""&A38&""&A39)>0," · ","")&""&A40,"")&IF(LEN(IF($Q$3="Sim","Morrendo",""))>0,IF(LEN(""&A37&""&A38&""&A39&""&A40)>0," · ","")&IF($Q$3="Sim","Morrendo",""),"")&IF(LEN(IF(Equipamento!$B$58<>"Normal","Lentidão (carga)",""))>0,IF(LEN(""&A37&""&A38&""&A39&""&A40&IF($Q$3="Sim","Morrendo",""))>0," · ","")&IF(Equipamento!$B$58<>"Normal","Lentidão (carga)",""),"") -> #ERROR!
A24: ="Neste ataque: "&IF(AND(($Q$6="Sim"),(COUNTIF(Caminho!$I$27:$I$36,"Memória Compartilhada")>0)),"+1d6 (Memória Compartilhada) · ","")&IF(AND(($Q$6="Sim"),(COUNTIF(Caminho!$I$27:$I$36,"Fragmentos do Eu Perdido")>0),Caminho!$B$95="Fúria"),"+1d8 (Memória da Fúria) · ","")&IF($Q$7>0,"+"&$Q$7&"d6 (Fúria) · ","")&IF($Q$11>0,"+"&MIN('Criação'!$J$14,$Q$11)&" de dano (Cicatriz) · ","")&IF($Q$12=1,"+2 no ataque, já somado (Instinto) · ","")&"temporários: no máximo +3 por rolagem, fora a Fraqueza (26.6)" -> #ERROR! | P24: Condições ativas (quantas) | Q24: =IF(LEN(""&A37)>0,1,0)+IF(LEN(""&A38)>0,1,0)+IF(LEN(""&A39)>0,1,0)+IF(LEN(""&A40)>0,1,0)+IF(LEN(IF($Q$3="Sim","Morrendo",""))>0,1,0)+IF(LEN(IF(Equipamento!$B$58<>"Normal","Lentidão (carga)",""))>0,1,0) -> #ERROR!
P25: Condições ativas (a primeira) | Q25: =IF(LEN(""&A37)>0,""&A37,IF(LEN(""&A38)>0,""&A38,IF(LEN(""&A39)>0,""&A39,IF(LEN(""&A40)>0,""&A40,IF(LEN(IF($Q$3="Sim","Morrendo",""))>0,IF($Q$3="Sim","Morrendo",""),IF(LEN(IF(Equipamento!$B$58<>"Normal","Lentidão (carga)",""))>0,IF(Equipamento!$B$58<>"Normal","Lentidão (carga)",""),"")))))) -> #ERROR!
A26: Testes de Resistência (d20 + Bônus + Eficiência) | G26: Perícias com Eficiência (rolagem pronta)
A27: Potência Física | B27: =Testes!$I$40 -> d20+2 | C27: =IF(OR('Criação'!$B$25="Xianzhouíta"),"Vantagem ("&'Criação'!$B$25&")","") | E27: =IF(Testes!$G$40=0,"",IF(Testes!$G$40>=0,"+","")&Testes!$G$40&" de equipamento/Bênção") | G27: {=IFERROR(INDEX($W$2:$W$19,MATCH(1,$Y$2:$Y$19,0))&IF(LEN($AB$2)>0," · Vantagem",""),"")} | I27: {=IFERROR(INDEX($Z$2:$Z$19,MATCH(1,$Y$2:$Y$19,0)),"")} | J27: {=IFERROR(INDEX($W$2:$W$19,MATCH(6,$Y$2:$Y$19,0))&IF(LEN($AB$7)>0," · Vantagem",""),"")} | L27: {=IFERROR(INDEX($Z$2:$Z$19,MATCH(6,$Y$2:$Y$19,0)),"")}
A28: Reflexos | B28: =Testes!$I$41 -> d20+2 | C28: =IF(OR('Criação'!$B$25="Xianzhouíta"),"Vantagem ("&'Criação'!$B$25&")","") | E28: =IF(Testes!$G$41=0,"",IF(Testes!$G$41>=0,"+","")&Testes!$G$41&" de equipamento/Bênção") | G28: {=IFERROR(INDEX($W$2:$W$19,MATCH(2,$Y$2:$Y$19,0))&IF(LEN($AB$3)>0," · Vantagem",""),"")} | I28: {=IFERROR(INDEX($Z$2:$Z$19,MATCH(2,$Y$2:$Y$19,0)),"")} | J28: {=IFERROR(INDEX($W$2:$W$19,MATCH(7,$Y$2:$Y$19,0))&IF(LEN($AB$8)>0," · Vantagem",""),"")} | L28: {=IFERROR(INDEX($Z$2:$Z$19,MATCH(7,$Y$2:$Y$19,0)),"")}
A29: Resistência Física | B29: =Testes!$I$42 -> d20+2 | C29: =IF(OR('Criação'!$B$25="Xianzhouíta"),"Vantagem ("&'Criação'!$B$25&")",IF(OR('Criação'!$B$25="Vidyadhara"),"Vantagem condicional","")) | E29: =IF(Testes!$G$42=0,"",IF(Testes!$G$42>=0,"+","")&Testes!$G$42&" de equipamento/Bênção") | G29: {=IFERROR(INDEX($W$2:$W$19,MATCH(3,$Y$2:$Y$19,0))&IF(LEN($AB$4)>0," · Vantagem",""),"")} | I29: {=IFERROR(INDEX($Z$2:$Z$19,MATCH(3,$Y$2:$Y$19,0)),"")} | J29: {=IFERROR(INDEX($W$2:$W$19,MATCH(8,$Y$2:$Y$19,0))&IF(LEN($AB$9)>0," · Vantagem",""),"")} | L29: {=IFERROR(INDEX($Z$2:$Z$19,MATCH(8,$Y$2:$Y$19,0)),"")}
A30: Resistência Mental | B30: =Testes!$I$43 -> d20+2 | C30: =IF(OR('Criação'!$B$25="Xianzhouíta",'Criação'!$B$25="Avginiano"),"Vantagem ("&'Criação'!$B$25&")","") | E30: =IF(Testes!$G$43=0,"",IF(Testes!$G$43>=0,"+","")&Testes!$G$43&" de equipamento/Bênção") | G30: {=IFERROR(INDEX($W$2:$W$19,MATCH(4,$Y$2:$Y$19,0))&IF(LEN($AB$5)>0," · Vantagem",""),"")} | I30: {=IFERROR(INDEX($Z$2:$Z$19,MATCH(4,$Y$2:$Y$19,0)),"")} | J30: {=IFERROR(INDEX($W$2:$W$19,MATCH(9,$Y$2:$Y$19,0))&IF(LEN($AB$10)>0," · Vantagem",""),"")} | L30: {=IFERROR(INDEX($Z$2:$Z$19,MATCH(9,$Y$2:$Y$19,0)),"")}
A31: Percepção Mental | B31: =Testes!$I$44 -> d20+2 | C31: =IF(OR('Criação'!$B$25="Xianzhouíta",'Criação'!$B$25="Avginiano"),"Vantagem ("&'Criação'!$B$25&")","") | E31: =IF(Testes!$G$44=0,"",IF(Testes!$G$44>=0,"+","")&Testes!$G$44&" de equipamento/Bênção") | G31: {=IFERROR(INDEX($W$2:$W$19,MATCH(5,$Y$2:$Y$19,0))&IF(LEN($AB$6)>0," · Vantagem",""),"")} | I31: {=IFERROR(INDEX($Z$2:$Z$19,MATCH(5,$Y$2:$Y$19,0)),"")} | J31: {=IFERROR(INDEX($W$2:$W$19,MATCH(10,$Y$2:$Y$19,0))&IF(LEN($AB$11)>0," · Vantagem",""),"")} | L31: {=IFERROR(INDEX($Z$2:$Z$19,MATCH(10,$Y$2:$Y$19,0)),"")}
A32: Força de Vontade | B32: =Testes!$I$45 -> d20+2 | C32: =IF(OR('Criação'!$B$25="Xianzhouíta",'Criação'!$B$25="Vulpes",'Criação'!$B$25="Avginiano"),"Vantagem ("&'Criação'!$B$25&")","") | E32: =IF(Testes!$G$45=0,"",IF(Testes!$G$45>=0,"+","")&Testes!$G$45&" de equipamento/Bênção") | G32: Usos por combate e descanso (preencha os usados)
A33: Morrendo (DT 10) | B33: =Testes!$I$46 -> #ERROR! | C33: Sucessos | E33: Falhas | G33: {=IFERROR(INDEX($S$2:$S$16,MATCH(1,$V$2:$V$16,0))&IF(LEN($AC$2)>0," · "&$AC$2,""),"—")} -> Descanso Curto · 2/dia
A34: Morrendo agora | B34: =IF(IF(ISNUMBER($D$33),$D$33,0)>=3,"Estabiliza com 1 PV",IF(IF(ISNUMBER($F$33),$F$33,0)>=3,"Morre",IF($Q$3="Sim",IF(ISNUMBER($D$33),$D$33,0)&" sucesso(s), "&IF(ISNUMBER($F$33),$F$33,0)&" falha(s) (0 a 3 cada)","Não está Morrendo")))&IF(LEN(Testes!$J$46)>0," · Vantagem","") -> #ERROR! | G34: {=IFERROR(INDEX($S$2:$S$16,MATCH(2,$V$2:$V$16,0))&IF(LEN($AC$3)>0," · "&$AC$3,""),"—")} -> Técnica · 2/Desc. Longo
A35: Condições ativas (21.5) — Quebrado é só de inimigos | G35: {=IFERROR(INDEX($S$2:$S$16,MATCH(3,$V$2:$V$16,0))&IF(LEN($AC$4)>0," · "&$AC$4,""),"—")} -> —
A36: Condição (preencha) | C36: Turnos | D36: Ef. aplicador | E36: Efeito (tique por turno) | G36: {=IFERROR(INDEX($S$2:$S$16,MATCH(4,$V$2:$V$16,0))&IF(LEN($AC$5)>0," · "&$AC$5,""),"—")} -> —
E37: =IF($A$37="","",IF(AND(ISNUMBER($D$37),OR($A$37="Sangramento",$A$37="Queimadura",$A$37="Choque",$A$37="Aprisionamento")),IF($A$37="Sangramento",$AD$2,$AD$2&" por turno")&IF($A$37="Aprisionamento"," · Atrasa 2",""),IF($A$37="Sangramento","5% dos PV máx. por turno",IF($A$37="Queimadura","Contínuo 2d6 + Eficiência",IF($A$37="Choque","Contínuo 1d6 + Eficiência",IF($A$37="Cisalhamento de Vento","Contínuo 1d6 por acúmulo",IF($A$37="Embaraço","1d6/acúmulo · Atrasa 1 casa",IF($A$37="Aprisionamento","1d6 + Ef. · Atrasa 2 casas",IF($A$37="Lentidão","só move com Esforço Total",IF($A$37="Marcado","+1 Ataque de quem marcou",IF($A$37="Silenciado","sem Habilidade de Nível 4+",IF($A$37="Vulnerável","+1 dado de dano da fonte",IF($A$37="Controlado","quem aplicou decide ações",IF($A$37="Corrupção","+1 em toda DC do aplicador",IF($A$37="Surpreso","casa pulada no 1º Ciclo","veja Regras Rápidas (21.5)"))))))))))))))) | G37: {=IFERROR(INDEX($S$2:$S$16,MATCH(5,$V$2:$V$16,0))&IF(LEN($AC$6)>0," · "&$AC$6,""),"—")} -> —
E38: =IF($A$38="","",IF(AND(ISNUMBER($D$38),OR($A$38="Sangramento",$A$38="Queimadura",$A$38="Choque",$A$38="Aprisionamento")),IF($A$38="Sangramento",$AD$3,$AD$3&" por turno")&IF($A$38="Aprisionamento"," · Atrasa 2",""),IF($A$38="Sangramento","5% dos PV máx. por turno",IF($A$38="Queimadura","Contínuo 2d6 + Eficiência",IF($A$38="Choque","Contínuo 1d6 + Eficiência",IF($A$38="Cisalhamento de Vento","Contínuo 1d6 por acúmulo",IF($A$38="Embaraço","1d6/acúmulo · Atrasa 1 casa",IF($A$38="Aprisionamento","1d6 + Ef. · Atrasa 2 casas",IF($A$38="Lentidão","só move com Esforço Total",IF($A$38="Marcado","+1 Ataque de quem marcou",IF($A$38="Silenciado","sem Habilidade de Nível 4+",IF($A$38="Vulnerável","+1 dado de dano da fonte",IF($A$38="Controlado","quem aplicou decide ações",IF($A$38="Corrupção","+1 em toda DC do aplicador",IF($A$38="Surpreso","casa pulada no 1º Ciclo","veja Regras Rápidas (21.5)"))))))))))))))) | G38: {=IFERROR(INDEX($S$2:$S$16,MATCH(6,$V$2:$V$16,0))&IF(LEN($AC$7)>0," · "&$AC$7,""),"—")} -> —
E39: =IF($A$39="","",IF(AND(ISNUMBER($D$39),OR($A$39="Sangramento",$A$39="Queimadura",$A$39="Choque",$A$39="Aprisionamento")),IF($A$39="Sangramento",$AD$4,$AD$4&" por turno")&IF($A$39="Aprisionamento"," · Atrasa 2",""),IF($A$39="Sangramento","5% dos PV máx. por turno",IF($A$39="Queimadura","Contínuo 2d6 + Eficiência",IF($A$39="Choque","Contínuo 1d6 + Eficiência",IF($A$39="Cisalhamento de Vento","Contínuo 1d6 por acúmulo",IF($A$39="Embaraço","1d6/acúmulo · Atrasa 1 casa",IF($A$39="Aprisionamento","1d6 + Ef. · Atrasa 2 casas",IF($A$39="Lentidão","só move com Esforço Total",IF($A$39="Marcado","+1 Ataque de quem marcou",IF($A$39="Silenciado","sem Habilidade de Nível 4+",IF($A$39="Vulnerável","+1 dado de dano da fonte",IF($A$39="Controlado","quem aplicou decide ações",IF($A$39="Corrupção","+1 em toda DC do aplicador",IF($A$39="Surpreso","casa pulada no 1º Ciclo","veja Regras Rápidas (21.5)"))))))))))))))) | G39: {=IFERROR(INDEX($S$2:$S$16,MATCH(7,$V$2:$V$16,0))&IF(LEN($AC$8)>0," · "&$AC$8,""),"—")} -> —
E40: =IF($A$40="","",IF(AND(ISNUMBER($D$40),OR($A$40="Sangramento",$A$40="Queimadura",$A$40="Choque",$A$40="Aprisionamento")),IF($A$40="Sangramento",$AD$5,$AD$5&" por turno")&IF($A$40="Aprisionamento"," · Atrasa 2",""),IF($A$40="Sangramento","5% dos PV máx. por turno",IF($A$40="Queimadura","Contínuo 2d6 + Eficiência",IF($A$40="Choque","Contínuo 1d6 + Eficiência",IF($A$40="Cisalhamento de Vento","Contínuo 1d6 por acúmulo",IF($A$40="Embaraço","1d6/acúmulo · Atrasa 1 casa",IF($A$40="Aprisionamento","1d6 + Ef. · Atrasa 2 casas",IF($A$40="Lentidão","só move com Esforço Total",IF($A$40="Marcado","+1 Ataque de quem marcou",IF($A$40="Silenciado","sem Habilidade de Nível 4+",IF($A$40="Vulnerável","+1 dado de dano da fonte",IF($A$40="Controlado","quem aplicou decide ações",IF($A$40="Corrupção","+1 em toda DC do aplicador",IF($A$40="Surpreso","casa pulada no 1º Ciclo","veja Regras Rápidas (21.5)"))))))))))))))) | G40: {=IFERROR(INDEX($S$2:$S$16,MATCH(8,$V$2:$V$16,0))&IF(LEN($AC$9)>0," · "&$AC$9,""),"—")} -> —
A42: Em Jogo — Explorando Galáxias v1.1
A43: Legenda: | B43: Entrada (preencha) | C43: Calculada (automático) | D43: Aviso (texto em vermelho) | E43: Título de bloco | F43: Cabeçalho de coluna | G43: Rótulo da linha | H43: Linha alternada (outro tom) | I43: Não se aplica
A44: Tudo que se usa na mesa, numa tela só.

Sheet Testes
A1: Testes — Explorando Galáxias v1.1
A2: Legenda: | B2: Entrada (preencha) | C2: Calculada (automático) | E2: Aviso (texto em vermelho) | G2: Título de bloco | H2: Cabeçalho de coluna | J2: Rótulo da linha | K2: Linha alternada (outro tom) | L2: Não se aplica
A3: As 18 Perícias e os 6 Testes de Resistência com a rolagem pronta.
A5: DT por faixa — 27.2 (a sua faixa) | F5: DT das suas Habilidades: | I5: ='Criação'!$B$56 -> 10 | J5: Sucesso Automático: bônus total ≥ DT → não rola (só Perícia, 27.2)
A6: Dificuldade | B6: DT
A7: {=INDEX(Dados!$A$417:$A$422,1)} -> Trivial | B7: {=INDEX(Dados!$A$417:$F$422,1,'Criação'!$B$14+1)} -> 8
A8: {=INDEX(Dados!$A$417:$A$422,2)} -> Fácil | B8: {=INDEX(Dados!$A$417:$F$422,2,'Criação'!$B$14+1)} -> 10
A9: {=INDEX(Dados!$A$417:$A$422,3)} -> Média | B9: {=INDEX(Dados!$A$417:$F$422,3,'Criação'!$B$14+1)} -> 13
A10: {=INDEX(Dados!$A$417:$A$422,4)} -> Difícil | B10: {=INDEX(Dados!$A$417:$F$422,4,'Criação'!$B$14+1)} -> 16
A11: {=INDEX(Dados!$A$417:$A$422,5)} -> Muito Difícil | B11: {=INDEX(Dados!$A$417:$F$422,5,'Criação'!$B$14+1)} -> 19
A12: {=INDEX(Dados!$A$417:$A$422,6)} -> Heroica | B12: {=INDEX(Dados!$A$417:$F$422,6,'Criação'!$B$14+1)} -> 22
A14: Perícias — 04.4 (rolagem pronta: d20 + Bônus + Eficiência)
A15: Perícia (Poder, Agilidade e Vigor) | B15: Atributo | C15: Bônus | D15: Eficiência (origem) | E15: Eficácia (preencha Sim) | F15: Penalidade (Armadura Pesada) | G15: Extra (equipamento) | H15: Total | I15: Rolagem | J15: Vantagem racial | K15: Sucesso Automático até | L15: Aviso
A16: Atletismo | B16: ='Criação'!$B$69 -> Poder | C16: {=IFERROR(INDEX('Criação'!$F$44:$F$49,MATCH($B$16,'Criação'!$A$44:$A$49,0)),0)} -> 0 | D16: =IF('Criação'!$E$69="Sim","Sim ("&'Criação'!$F$69&")","Não") -> #ERROR! | F16: =IF($B$16="Agilidade",'Criação'!$E$93,0) -> 0 | G16: =IF(Equipamento!$L$31="Atletismo",Equipamento!$K$31,0)+MIN('Criação'!$J$14,COUNTIF(Equipamento!$P$45:$P$47,"Atletismo")) -> 0 | H16: =$C$16+IF('Criação'!$E$69="Sim",IF(AND($E$16="Sim",'Criação'!$E$69="Sim",COUNTIF($E$16:E16,"Sim")<='Criação'!$E$14),2*'Criação'!$C$14,'Criação'!$C$14),0)+$F$16+$G$16 -> #ERROR! | I16: ="d20"&IF($H$16>=0,"+","")&$H$16 -> #ERROR! | J16: ="" | K16: =IF($H$16>=$B$12,"Heroica ("&$B$12&")",IF($H$16>=$B$11,"Muito Difícil ("&$B$11&")",IF($H$16>=$B$10,"Difícil ("&$B$10&")",IF($H$16>=$B$9,"Média ("&$B$9&")",IF($H$16>=$B$8,"Fácil ("&$B$8&")",IF($H$16>=$B$7,"Trivial ("&$B$7&")","—")))))) -> #ERROR! | L16: =IF($E$16<>"Sim","",IF('Criação'!$E$69<>"Sim","Eficácia exige Eficiência nesta Perícia",IF(COUNTIF($E$16:E16,"Sim")>'Criação'!$E$14,"Acima dos slots de Eficácia em Perícias ("&'Criação'!$E$14&")","")))
A17: Acrobacia | B17: ='Criação'!$B$70 -> Agilidade | C17: {=IFERROR(INDEX('Criação'!$F$44:$F$49,MATCH($B$17,'Criação'!$A$44:$A$49,0)),0)} -> 0 | D17: =IF('Criação'!$E$70="Sim","Sim ("&'Criação'!$F$70&")","Não") -> #ERROR! | F17: =IF($B$17="Agilidade",'Criação'!$E$93,0) -> 0 | G17: =IF(Equipamento!$L$31="Acrobacia",Equipamento!$K$31,0)+MIN('Criação'!$J$14,COUNTIF(Equipamento!$P$45:$P$47,"Acrobacia")) -> 0 | H17: =$C$17+IF('Criação'!$E$70="Sim",IF(AND($E$17="Sim",'Criação'!$E$70="Sim",COUNTIF($E$16:E17,"Sim")<='Criação'!$E$14),2*'Criação'!$C$14,'Criação'!$C$14),0)+$F$17+$G$17 -> #ERROR! | I17: ="d20"&IF($H$17>=0,"+","")&$H$17 -> #ERROR! | J17: ="" | K17: =IF($H$17>=$B$12,"Heroica ("&$B$12&")",IF($H$17>=$B$11,"Muito Difícil ("&$B$11&")",IF($H$17>=$B$10,"Difícil ("&$B$10&")",IF($H$17>=$B$9,"Média ("&$B$9&")",IF($H$17>=$B$8,"Fácil ("&$B$8&")",IF($H$17>=$B$7,"Trivial ("&$B$7&")","—")))))) -> #ERROR! | L17: =IF($E$17<>"Sim","",IF('Criação'!$E$70<>"Sim","Eficácia exige Eficiência nesta Perícia",IF(COUNTIF($E$16:E17,"Sim")>'Criação'!$E$14,"Acima dos slots de Eficácia em Perícias ("&'Criação'!$E$14&")","")))
A18: Furtividade | B18: ='Criação'!$B$71 -> Agilidade | C18: {=IFERROR(INDEX('Criação'!$F$44:$F$49,MATCH($B$18,'Criação'!$A$44:$A$49,0)),0)} -> 0 | D18: =IF('Criação'!$E$71="Sim","Sim ("&'Criação'!$F$71&")","Não") -> #ERROR! | F18: =IF($B$18="Agilidade",'Criação'!$E$93,0) -> 0 | G18: =IF(Equipamento!$L$31="Furtividade",Equipamento!$K$31,0)+MIN('Criação'!$J$14,COUNTIF(Equipamento!$P$45:$P$47,"Furtividade")) -> 0 | H18: =$C$18+IF('Criação'!$E$71="Sim",IF(AND($E$18="Sim",'Criação'!$E$71="Sim",COUNTIF($E$16:E18,"Sim")<='Criação'!$E$14),2*'Criação'!$C$14,'Criação'!$C$14),0)+$F$18+$G$18 -> #ERROR! | I18: ="d20"&IF($H$18>=0,"+","")&$H$18 -> #ERROR! | J18: ="" | K18: =IF($H$18>=$B$12,"Heroica ("&$B$12&")",IF($H$18>=$B$11,"Muito Difícil ("&$B$11&")",IF($H$18>=$B$10,"Difícil ("&$B$10&")",IF($H$18>=$B$9,"Média ("&$B$9&")",IF($H$18>=$B$8,"Fácil ("&$B$8&")",IF($H$18>=$B$7,"Trivial ("&$B$7&")","—")))))) -> #ERROR! | L18: =IF($E$18<>"Sim","",IF('Criação'!$E$71<>"Sim","Eficácia exige Eficiência nesta Perícia",IF(COUNTIF($E$16:E18,"Sim")>'Criação'!$E$14,"Acima dos slots de Eficácia em Perícias ("&'Criação'!$E$14&")","")))
A19: Pilotagem | B19: ='Criação'!$B$72 -> Agilidade | C19: {=IFERROR(INDEX('Criação'!$F$44:$F$49,MATCH($B$19,'Criação'!$A$44:$A$49,0)),0)} -> 0 | D19: =IF('Criação'!$E$72="Sim","Sim ("&'Criação'!$F$72&")","Não") -> #ERROR! | F19: =IF($B$19="Agilidade",'Criação'!$E$93,0) -> 0 | G19: =IF(Equipamento!$L$31="Pilotagem",Equipamento!$K$31,0)+MIN('Criação'!$J$14,COUNTIF(Equipamento!$P$45:$P$47,"Pilotagem")) -> 0 | H19: =$C$19+IF('Criação'!$E$72="Sim",IF(AND($E$19="Sim",'Criação'!$E$72="Sim",COUNTIF($E$16:E19,"Sim")<='Criação'!$E$14),2*'Criação'!$C$14,'Criação'!$C$14),0)+$F$19+$G$19 -> #ERROR! | I19: ="d20"&IF($H$19>=0,"+","")&$H$19 -> #ERROR! | J19: ="" | K19: =IF($H$19>=$B$12,"Heroica ("&$B$12&")",IF($H$19>=$B$11,"Muito Difícil ("&$B$11&")",IF($H$19>=$B$10,"Difícil ("&$B$10&")",IF($H$19>=$B$9,"Média ("&$B$9&")",IF($H$19>=$B$8,"Fácil ("&$B$8&")",IF($H$19>=$B$7,"Trivial ("&$B$7&")","—")))))) -> #ERROR! | L19: =IF($E$19<>"Sim","",IF('Criação'!$E$72<>"Sim","Eficácia exige Eficiência nesta Perícia",IF(COUNTIF($E$16:E19,"Sim")>'Criação'!$E$14,"Acima dos slots de Eficácia em Perícias ("&'Criação'!$E$14&")","")))
A20: Resistência | B20: ='Criação'!$B$73 -> Vigor | C20: {=IFERROR(INDEX('Criação'!$F$44:$F$49,MATCH($B$20,'Criação'!$A$44:$A$49,0)),0)} -> 0 | D20: =IF('Criação'!$E$73="Sim","Sim ("&'Criação'!$F$73&")","Não") -> #ERROR! | F20: =IF($B$20="Agilidade",'Criação'!$E$93,0) -> 0 | G20: =IF(Equipamento!$L$31="Resistência",Equipamento!$K$31,0)+MIN('Criação'!$J$14,COUNTIF(Equipamento!$P$45:$P$47,"Resistência")) -> 0 | H20: =$C$20+IF('Criação'!$E$73="Sim",IF(AND($E$20="Sim",'Criação'!$E$73="Sim",COUNTIF($E$16:E20,"Sim")<='Criação'!$E$14),2*'Criação'!$C$14,'Criação'!$C$14),0)+$F$20+$G$20 -> #ERROR! | I20: ="d20"&IF($H$20>=0,"+","")&$H$20 -> #ERROR! | J20: ="" | K20: =IF($H$20>=$B$12,"Heroica ("&$B$12&")",IF($H$20>=$B$11,"Muito Difícil ("&$B$11&")",IF($H$20>=$B$10,"Difícil ("&$B$10&")",IF($H$20>=$B$9,"Média ("&$B$9&")",IF($H$20>=$B$8,"Fácil ("&$B$8&")",IF($H$20>=$B$7,"Trivial ("&$B$7&")","—")))))) -> #ERROR! | L20: =IF($E$20<>"Sim","",IF('Criação'!$E$73<>"Sim","Eficácia exige Eficiência nesta Perícia",IF(COUNTIF($E$16:E20,"Sim")>'Criação'!$E$14,"Acima dos slots de Eficácia em Perícias ("&'Criação'!$E$14&")","")))
A21: Perícia (Sincronia e Discernimento) | B21: Atributo | C21: Bônus | D21: Eficiência (origem) | E21: Eficácia (preencha Sim) | F21: Penalidade (Armadura Pesada) | G21: Extra (equipamento) | H21: Total | I21: Rolagem | J21: Vantagem racial | K21: Sucesso Automático até | L21: Aviso
A22: Tecnologia | B22: ='Criação'!$B$75 -> Sincronia | C22: {=IFERROR(INDEX('Criação'!$F$44:$F$49,MATCH($B$22,'Criação'!$A$44:$A$49,0)),0)} -> 0 | D22: =IF('Criação'!$E$75="Sim","Sim ("&'Criação'!$F$75&")","Não") -> #ERROR! | F22: =IF($B$22="Agilidade",'Criação'!$E$93,0) -> 0 | G22: =IF(Equipamento!$L$31="Tecnologia",Equipamento!$K$31,0)+MIN('Criação'!$J$14,COUNTIF(Equipamento!$P$45:$P$47,"Tecnologia")) -> 0 | H22: =$C$22+IF('Criação'!$E$75="Sim",IF(AND($E$22="Sim",'Criação'!$E$75="Sim",COUNTIF($E$16:E22,"Sim")<='Criação'!$E$14),2*'Criação'!$C$14,'Criação'!$C$14),0)+$F$22+$G$22 -> #ERROR! | I22: ="d20"&IF($H$22>=0,"+","")&$H$22 -> #ERROR! | J22: =IF(OR('Criação'!$B$25="Intellitron"),"Vantagem ("&'Criação'!$B$25&")","") | K22: =IF($H$22>=$B$12,"Heroica ("&$B$12&")",IF($H$22>=$B$11,"Muito Difícil ("&$B$11&")",IF($H$22>=$B$10,"Difícil ("&$B$10&")",IF($H$22>=$B$9,"Média ("&$B$9&")",IF($H$22>=$B$8,"Fácil ("&$B$8&")",IF($H$22>=$B$7,"Trivial ("&$B$7&")","—")))))) -> #ERROR! | L22: =IF($E$22<>"Sim","",IF('Criação'!$E$75<>"Sim","Eficácia exige Eficiência nesta Perícia",IF(COUNTIF($E$16:E22,"Sim")>'Criação'!$E$14,"Acima dos slots de Eficácia em Perícias ("&'Criação'!$E$14&")","")))
A23: Pesquisa | B23: ='Criação'!$B$76 -> Sincronia | C23: {=IFERROR(INDEX('Criação'!$F$44:$F$49,MATCH($B$23,'Criação'!$A$44:$A$49,0)),0)} -> 0 | D23: =IF('Criação'!$E$76="Sim","Sim ("&'Criação'!$F$76&")","Não") -> #ERROR! | F23: =IF($B$23="Agilidade",'Criação'!$E$93,0) -> 0 | G23: =IF(Equipamento!$L$31="Pesquisa",Equipamento!$K$31,0)+MIN('Criação'!$J$14,COUNTIF(Equipamento!$P$45:$P$47,"Pesquisa")) -> 0 | H23: =$C$23+IF('Criação'!$E$76="Sim",IF(AND($E$23="Sim",'Criação'!$E$76="Sim",COUNTIF($E$16:E23,"Sim")<='Criação'!$E$14),2*'Criação'!$C$14,'Criação'!$C$14),0)+$F$23+$G$23 -> #ERROR! | I23: ="d20"&IF($H$23>=0,"+","")&$H$23 -> #ERROR! | J23: ="" | K23: =IF($H$23>=$B$12,"Heroica ("&$B$12&")",IF($H$23>=$B$11,"Muito Difícil ("&$B$11&")",IF($H$23>=$B$10,"Difícil ("&$B$10&")",IF($H$23>=$B$9,"Média ("&$B$9&")",IF($H$23>=$B$8,"Fácil ("&$B$8&")",IF($H$23>=$B$7,"Trivial ("&$B$7&")","—")))))) -> #ERROR! | L23: =IF($E$23<>"Sim","",IF('Criação'!$E$76<>"Sim","Eficácia exige Eficiência nesta Perícia",IF(COUNTIF($E$16:E23,"Sim")>'Criação'!$E$14,"Acima dos slots de Eficácia em Perícias ("&'Criação'!$E$14&")","")))
A24: Ciência | B24: ='Criação'!$B$77 -> Sincronia | C24: {=IFERROR(INDEX('Criação'!$F$44:$F$49,MATCH($B$24,'Criação'!$A$44:$A$49,0)),0)} -> 0 | D24: =IF('Criação'!$E$77="Sim","Sim ("&'Criação'!$F$77&")","Não") -> #ERROR! | F24: =IF($B$24="Agilidade",'Criação'!$E$93,0) -> 0 | G24: =IF(Equipamento!$L$31="Ciência",Equipamento!$K$31,0)+MIN('Criação'!$J$14,COUNTIF(Equipamento!$P$45:$P$47,"Ciência")) -> 0 | H24: =$C$24+IF('Criação'!$E$77="Sim",IF(AND($E$24="Sim",'Criação'!$E$77="Sim",COUNTIF($E$16:E24,"Sim")<='Criação'!$E$14),2*'Criação'!$C$14,'Criação'!$C$14),0)+$F$24+$G$24 -> #ERROR! | I24: ="d20"&IF($H$24>=0,"+","")&$H$24 -> #ERROR! | J24: ="" | K24: =IF($H$24>=$B$12,"Heroica ("&$B$12&")",IF($H$24>=$B$11,"Muito Difícil ("&$B$11&")",IF($H$24>=$B$10,"Difícil ("&$B$10&")",IF($H$24>=$B$9,"Média ("&$B$9&")",IF($H$24>=$B$8,"Fácil ("&$B$8&")",IF($H$24>=$B$7,"Trivial ("&$B$7&")","—")))))) -> #ERROR! | L24: =IF($E$24<>"Sim","",IF('Criação'!$E$77<>"Sim","Eficácia exige Eficiência nesta Perícia",IF(COUNTIF($E$16:E24,"Sim")>'Criação'!$E$14,"Acima dos slots de Eficácia em Perícias ("&'Criação'!$E$14&")","")))
A25: Mecânica | B25: ='Criação'!$B$78 -> Sincronia | C25: {=IFERROR(INDEX('Criação'!$F$44:$F$49,MATCH($B$25,'Criação'!$A$44:$A$49,0)),0)} -> 0 | D25: =IF('Criação'!$E$78="Sim","Sim ("&'Criação'!$F$78&")","Não") -> #ERROR! | F25: =IF($B$25="Agilidade",'Criação'!$E$93,0) -> 0 | G25: =IF(Equipamento!$L$31="Mecânica",Equipamento!$K$31,0)+MIN('Criação'!$J$14,COUNTIF(Equipamento!$P$45:$P$47,"Mecânica")) -> 0 | H25: =$C$25+IF('Criação'!$E$78="Sim",IF(AND($E$25="Sim",'Criação'!$E$78="Sim",COUNTIF($E$16:E25,"Sim")<='Criação'!$E$14),2*'Criação'!$C$14,'Criação'!$C$14),0)+$F$25+$G$25 -> #ERROR! | I25: ="d20"&IF($H$25>=0,"+","")&$H$25 -> #ERROR! | J25: =IF(OR('Criação'!$B$25="Intellitron"),"Vantagem ("&'Criação'!$B$25&")","") | K25: =IF($H$25>=$B$12,"Heroica ("&$B$12&")",IF($H$25>=$B$11,"Muito Difícil ("&$B$11&")",IF($H$25>=$B$10,"Difícil ("&$B$10&")",IF($H$25>=$B$9,"Média ("&$B$9&")",IF($H$25>=$B$8,"Fácil ("&$B$8&")",IF($H$25>=$B$7,"Trivial ("&$B$7&")","—")))))) -> #ERROR! | L25: =IF($E$25<>"Sim","",IF('Criação'!$E$78<>"Sim","Eficácia exige Eficiência nesta Perícia",IF(COUNTIF($E$16:E25,"Sim")>'Criação'!$E$14,"Acima dos slots de Eficácia em Perícias ("&'Criação'!$E$14&")","")))
A26: Percepção | B26: ='Criação'!$B$79 -> Discernimento | C26: {=IFERROR(INDEX('Criação'!$F$44:$F$49,MATCH($B$26,'Criação'!$A$44:$A$49,0)),0)} -> 0 | D26: =IF('Criação'!$E$79="Sim","Sim ("&'Criação'!$F$79&")","Não") -> #ERROR! | F26: =IF($B$26="Agilidade",'Criação'!$E$93,0) -> 0 | G26: =IF(Equipamento!$L$31="Percepção",Equipamento!$K$31,0)+MIN('Criação'!$J$14,COUNTIF(Equipamento!$P$45:$P$47,"Percepção")) -> 0 | H26: =$C$26+IF('Criação'!$E$79="Sim",IF(AND($E$26="Sim",'Criação'!$E$79="Sim",COUNTIF($E$16:E26,"Sim")<='Criação'!$E$14),2*'Criação'!$C$14,'Criação'!$C$14),0)+$F$26+$G$26 -> #ERROR! | I26: ="d20"&IF($H$26>=0,"+","")&$H$26 -> #ERROR! | J26: ="" | K26: =IF($H$26>=$B$12,"Heroica ("&$B$12&")",IF($H$26>=$B$11,"Muito Difícil ("&$B$11&")",IF($H$26>=$B$10,"Difícil ("&$B$10&")",IF($H$26>=$B$9,"Média ("&$B$9&")",IF($H$26>=$B$8,"Fácil ("&$B$8&")",IF($H$26>=$B$7,"Trivial ("&$B$7&")","—")))))) -> #ERROR! | L26: =IF($E$26<>"Sim","",IF('Criação'!$E$79<>"Sim","Eficácia exige Eficiência nesta Perícia",IF(COUNTIF($E$16:E26,"Sim")>'Criação'!$E$14,"Acima dos slots de Eficácia em Perícias ("&'Criação'!$E$14&")","")))
A27: Sobrevivência | B27: ='Criação'!$B$80 -> Discernimento | C27: {=IFERROR(INDEX('Criação'!$F$44:$F$49,MATCH($B$27,'Criação'!$A$44:$A$49,0)),0)} -> 0 | D27: =IF('Criação'!$E$80="Sim","Sim ("&'Criação'!$F$80&")","Não") -> #ERROR! | F27: =IF($B$27="Agilidade",'Criação'!$E$93,0) -> 0 | G27: =IF(Equipamento!$L$31="Sobrevivência",Equipamento!$K$31,0)+MIN('Criação'!$J$14,COUNTIF(Equipamento!$P$45:$P$47,"Sobrevivência")) -> 0 | H27: =$C$27+IF('Criação'!$E$80="Sim",IF(AND($E$27="Sim",'Criação'!$E$80="Sim",COUNTIF($E$16:E27,"Sim")<='Criação'!$E$14),2*'Criação'!$C$14,'Criação'!$C$14),0)+$F$27+$G$27 -> #ERROR! | I27: ="d20"&IF($H$27>=0,"+","")&$H$27 -> #ERROR! | J27: ="" | K27: =IF($H$27>=$B$12,"Heroica ("&$B$12&")",IF($H$27>=$B$11,"Muito Difícil ("&$B$11&")",IF($H$27>=$B$10,"Difícil ("&$B$10&")",IF($H$27>=$B$9,"Média ("&$B$9&")",IF($H$27>=$B$8,"Fácil ("&$B$8&")",IF($H$27>=$B$7,"Trivial ("&$B$7&")","—")))))) -> #ERROR! | L27: =IF($E$27<>"Sim","",IF('Criação'!$E$80<>"Sim","Eficácia exige Eficiência nesta Perícia",IF(COUNTIF($E$16:E27,"Sim")>'Criação'!$E$14,"Acima dos slots de Eficácia em Perícias ("&'Criação'!$E$14&")","")))
A28: Intuição | B28: ='Criação'!$B$81 -> Discernimento | C28: {=IFERROR(INDEX('Criação'!$F$44:$F$49,MATCH($B$28,'Criação'!$A$44:$A$49,0)),0)} -> 0 | D28: =IF('Criação'!$E$81="Sim","Sim ("&'Criação'!$F$81&")","Não") -> #ERROR! | F28: =IF($B$28="Agilidade",'Criação'!$E$93,0) -> 0 | G28: =IF(Equipamento!$L$31="Intuição",Equipamento!$K$31,0)+MIN('Criação'!$J$14,COUNTIF(Equipamento!$P$45:$P$47,"Intuição")) -> 0 | H28: =$C$28+IF('Criação'!$E$81="Sim",IF(AND($E$28="Sim",'Criação'!$E$81="Sim",COUNTIF($E$16:E28,"Sim")<='Criação'!$E$14),2*'Criação'!$C$14,'Criação'!$C$14),0)+$F$28+$G$28 -> #ERROR! | I28: ="d20"&IF($H$28>=0,"+","")&$H$28 -> #ERROR! | J28: ="" | K28: =IF($H$28>=$B$12,"Heroica ("&$B$12&")",IF($H$28>=$B$11,"Muito Difícil ("&$B$11&")",IF($H$28>=$B$10,"Difícil ("&$B$10&")",IF($H$28>=$B$9,"Média ("&$B$9&")",IF($H$28>=$B$8,"Fácil ("&$B$8&")",IF($H$28>=$B$7,"Trivial ("&$B$7&")","—")))))) -> #ERROR! | L28: =IF($E$28<>"Sim","",IF('Criação'!$E$81<>"Sim","Eficácia exige Eficiência nesta Perícia",IF(COUNTIF($E$16:E28,"Sim")>'Criação'!$E$14,"Acima dos slots de Eficácia em Perícias ("&'Criação'!$E$14&")","")))
A29: Investigação | B29: ='Criação'!$B$82 -> Discernimento | C29: {=IFERROR(INDEX('Criação'!$F$44:$F$49,MATCH($B$29,'Criação'!$A$44:$A$49,0)),0)} -> 0 | D29: =IF('Criação'!$E$82="Sim","Sim ("&'Criação'!$F$82&")","Não") -> #ERROR! | F29: =IF($B$29="Agilidade",'Criação'!$E$93,0) -> 0 | G29: =IF(Equipamento!$L$31="Investigação",Equipamento!$K$31,0)+MIN('Criação'!$J$14,COUNTIF(Equipamento!$P$45:$P$47,"Investigação")) -> 0 | H29: =$C$29+IF('Criação'!$E$82="Sim",IF(AND($E$29="Sim",'Criação'!$E$82="Sim",COUNTIF($E$16:E29,"Sim")<='Criação'!$E$14),2*'Criação'!$C$14,'Criação'!$C$14),0)+$F$29+$G$29 -> #ERROR! | I29: ="d20"&IF($H$29>=0,"+","")&$H$29 -> #ERROR! | J29: ="" | K29: =IF($H$29>=$B$12,"Heroica ("&$B$12&")",IF($H$29>=$B$11,"Muito Difícil ("&$B$11&")",IF($H$29>=$B$10,"Difícil ("&$B$10&")",IF($H$29>=$B$9,"Média ("&$B$9&")",IF($H$29>=$B$8,"Fácil ("&$B$8&")",IF($H$29>=$B$7,"Trivial ("&$B$7&")","—")))))) -> #ERROR! | L29: =IF($E$29<>"Sim","",IF('Criação'!$E$82<>"Sim","Eficácia exige Eficiência nesta Perícia",IF(COUNTIF($E$16:E29,"Sim")>'Criação'!$E$14,"Acima dos slots de Eficácia em Perícias ("&'Criação'!$E$14&")","")))
A30: Perícia (Presença e Sintonia) | B30: Atributo | C30: Bônus | D30: Eficiência (origem) | E30: Eficácia (preencha Sim) | F30: Penalidade (Armadura Pesada) | G30: Extra (equipamento) | H30: Total | I30: Rolagem | J30: Vantagem racial | K30: Sucesso Automático até | L30: Aviso
A31: Persuasão | B31: ='Criação'!$B$84 -> Presença | C31: {=IFERROR(INDEX('Criação'!$F$44:$F$49,MATCH($B$31,'Criação'!$A$44:$A$49,0)),0)} -> 0 | D31: =IF('Criação'!$E$84="Sim","Sim ("&'Criação'!$F$84&")","Não") -> #ERROR! | F31: =IF($B$31="Agilidade",'Criação'!$E$93,0) -> 0 | G31: =IF(Equipamento!$L$31="Persuasão",Equipamento!$K$31,0)+MIN('Criação'!$J$14,COUNTIF(Equipamento!$P$45:$P$47,"Persuasão")) -> 0 | H31: =$C$31+IF('Criação'!$E$84="Sim",IF(AND($E$31="Sim",'Criação'!$E$84="Sim",COUNTIF($E$16:E31,"Sim")<='Criação'!$E$14),2*'Criação'!$C$14,'Criação'!$C$14),0)+$F$31+$G$31 -> #ERROR! | I31: ="d20"&IF($H$31>=0,"+","")&$H$31 -> #ERROR! | J31: =IF(OR('Criação'!$B$25="Vulpes"),"Vantagem ("&'Criação'!$B$25&")","") | K31: =IF($H$31>=$B$12,"Heroica ("&$B$12&")",IF($H$31>=$B$11,"Muito Difícil ("&$B$11&")",IF($H$31>=$B$10,"Difícil ("&$B$10&")",IF($H$31>=$B$9,"Média ("&$B$9&")",IF($H$31>=$B$8,"Fácil ("&$B$8&")",IF($H$31>=$B$7,"Trivial ("&$B$7&")","—")))))) -> #ERROR! | L31: =IF($E$31<>"Sim","",IF('Criação'!$E$84<>"Sim","Eficácia exige Eficiência nesta Perícia",IF(COUNTIF($E$16:E31,"Sim")>'Criação'!$E$14,"Acima dos slots de Eficácia em Perícias ("&'Criação'!$E$14&")","")))
A32: Intimidação | B32: ='Criação'!$B$85 -> Presença | C32: {=IFERROR(INDEX('Criação'!$F$44:$F$49,MATCH($B$32,'Criação'!$A$44:$A$49,0)),0)} -> 0 | D32: =IF('Criação'!$E$85="Sim","Sim ("&'Criação'!$F$85&")","Não") -> #ERROR! | F32: =IF($B$32="Agilidade",'Criação'!$E$93,0) -> 0 | G32: =IF(Equipamento!$L$31="Intimidação",Equipamento!$K$31,0)+MIN('Criação'!$J$14,COUNTIF(Equipamento!$P$45:$P$47,"Intimidação")) -> 0 | H32: =$C$32+IF('Criação'!$E$85="Sim",IF(AND($E$32="Sim",'Criação'!$E$85="Sim",COUNTIF($E$16:E32,"Sim")<='Criação'!$E$14),2*'Criação'!$C$14,'Criação'!$C$14),0)+$F$32+$G$32 -> #ERROR! | I32: ="d20"&IF($H$32>=0,"+","")&$H$32 -> #ERROR! | J32: =IF(OR('Criação'!$B$25="Vulpes"),"Vantagem ("&'Criação'!$B$25&")","") | K32: =IF($H$32>=$B$12,"Heroica ("&$B$12&")",IF($H$32>=$B$11,"Muito Difícil ("&$B$11&")",IF($H$32>=$B$10,"Difícil ("&$B$10&")",IF($H$32>=$B$9,"Média ("&$B$9&")",IF($H$32>=$B$8,"Fácil ("&$B$8&")",IF($H$32>=$B$7,"Trivial ("&$B$7&")","—")))))) -> #ERROR! | L32: =IF($E$32<>"Sim","",IF('Criação'!$E$85<>"Sim","Eficácia exige Eficiência nesta Perícia",IF(COUNTIF($E$16:E32,"Sim")>'Criação'!$E$14,"Acima dos slots de Eficácia em Perícias ("&'Criação'!$E$14&")","")))
A33: Enganação | B33: ='Criação'!$B$86 -> Presença | C33: {=IFERROR(INDEX('Criação'!$F$44:$F$49,MATCH($B$33,'Criação'!$A$44:$A$49,0)),0)} -> 0 | D33: =IF('Criação'!$E$86="Sim","Sim ("&'Criação'!$F$86&")","Não") -> #ERROR! | F33: =IF($B$33="Agilidade",'Criação'!$E$93,0) -> 0 | G33: =IF(Equipamento!$L$31="Enganação",Equipamento!$K$31,0)+MIN('Criação'!$J$14,COUNTIF(Equipamento!$P$45:$P$47,"Enganação")) -> 0 | H33: =$C$33+IF('Criação'!$E$86="Sim",IF(AND($E$33="Sim",'Criação'!$E$86="Sim",COUNTIF($E$16:E33,"Sim")<='Criação'!$E$14),2*'Criação'!$C$14,'Criação'!$C$14),0)+$F$33+$G$33 -> #ERROR! | I33: ="d20"&IF($H$33>=0,"+","")&$H$33 -> #ERROR! | J33: =IF(OR('Criação'!$B$25="Vulpes"),"Vantagem ("&'Criação'!$B$25&")","") | K33: =IF($H$33>=$B$12,"Heroica ("&$B$12&")",IF($H$33>=$B$11,"Muito Difícil ("&$B$11&")",IF($H$33>=$B$10,"Difícil ("&$B$10&")",IF($H$33>=$B$9,"Média ("&$B$9&")",IF($H$33>=$B$8,"Fácil ("&$B$8&")",IF($H$33>=$B$7,"Trivial ("&$B$7&")","—")))))) -> #ERROR! | L33: =IF($E$33<>"Sim","",IF('Criação'!$E$86<>"Sim","Eficácia exige Eficiência nesta Perícia",IF(COUNTIF($E$16:E33,"Sim")>'Criação'!$E$14,"Acima dos slots de Eficácia em Perícias ("&'Criação'!$E$14&")","")))
A34: Liderança | B34: ='Criação'!$B$87 -> Presença | C34: {=IFERROR(INDEX('Criação'!$F$44:$F$49,MATCH($B$34,'Criação'!$A$44:$A$49,0)),0)} -> 0 | D34: =IF('Criação'!$E$87="Sim","Sim ("&'Criação'!$F$87&")","Não") -> #ERROR! | F34: =IF($B$34="Agilidade",'Criação'!$E$93,0) -> 0 | G34: =IF(Equipamento!$L$31="Liderança",Equipamento!$K$31,0)+MIN('Criação'!$J$14,COUNTIF(Equipamento!$P$45:$P$47,"Liderança")) -> 0 | H34: =$C$34+IF('Criação'!$E$87="Sim",IF(AND($E$34="Sim",'Criação'!$E$87="Sim",COUNTIF($E$16:E34,"Sim")<='Criação'!$E$14),2*'Criação'!$C$14,'Criação'!$C$14),0)+$F$34+$G$34 -> #ERROR! | I34: ="d20"&IF($H$34>=0,"+","")&$H$34 -> #ERROR! | J34: =IF(OR('Criação'!$B$25="Vulpes"),"Vantagem ("&'Criação'!$B$25&")","") | K34: =IF($H$34>=$B$12,"Heroica ("&$B$12&")",IF($H$34>=$B$11,"Muito Difícil ("&$B$11&")",IF($H$34>=$B$10,"Difícil ("&$B$10&")",IF($H$34>=$B$9,"Média ("&$B$9&")",IF($H$34>=$B$8,"Fácil ("&$B$8&")",IF($H$34>=$B$7,"Trivial ("&$B$7&")","—")))))) -> #ERROR! | L34: =IF($E$34<>"Sim","",IF('Criação'!$E$87<>"Sim","Eficácia exige Eficiência nesta Perícia",IF(COUNTIF($E$16:E34,"Sim")>'Criação'!$E$14,"Acima dos slots de Eficácia em Perícias ("&'Criação'!$E$14&")","")))
A35: Sintonia | B35: ='Criação'!$B$88 -> Discernimento | C35: {=IFERROR(INDEX('Criação'!$F$44:$F$49,MATCH($B$35,'Criação'!$A$44:$A$49,0)),0)} -> 0 | D35: =IF('Criação'!$E$88="Sim","Sim ("&'Criação'!$F$88&")","Não") -> #ERROR! | F35: =IF($B$35="Agilidade",'Criação'!$E$93,0) -> 0 | G35: =IF(Equipamento!$L$31="Sintonia",Equipamento!$K$31,0)+MIN('Criação'!$J$14,COUNTIF(Equipamento!$P$45:$P$47,"Sintonia")) -> 0 | H35: =$C$35+IF('Criação'!$E$88="Sim",IF(AND($E$35="Sim",'Criação'!$E$88="Sim",COUNTIF($E$16:E35,"Sim")<='Criação'!$E$14),2*'Criação'!$C$14,'Criação'!$C$14),0)+$F$35+$G$35 -> #ERROR! | I35: ="d20"&IF($H$35>=0,"+","")&$H$35 -> #ERROR! | J35: ="" | K35: =IF($H$35>=$B$12,"Heroica ("&$B$12&")",IF($H$35>=$B$11,"Muito Difícil ("&$B$11&")",IF($H$35>=$B$10,"Difícil ("&$B$10&")",IF($H$35>=$B$9,"Média ("&$B$9&")",IF($H$35>=$B$8,"Fácil ("&$B$8&")",IF($H$35>=$B$7,"Trivial ("&$B$7&")","—")))))) -> #ERROR! | L35: =IF($E$35<>"Sim","",IF('Criação'!$E$88<>"Sim","Eficácia exige Eficiência nesta Perícia",IF(COUNTIF($E$16:E35,"Sim")>'Criação'!$E$14,"Acima dos slots de Eficácia em Perícias ("&'Criação'!$E$14&")","")))
A36: Slots de Eficácia em Perícias: marcados / permitidos | B36: =COUNTIF($E$16:$E$35,"Sim") -> 0 | C36: ='Criação'!$E$14 -> 0 | D36: Perícias com Eficiência: | E36: ='Criação'!$D$67 -> 0
A38: Testes de Resistência — 04.6 e 22 (Eficiência em todos desde o nível 1; sem crítico, sempre rolado)
A39: Teste de Resistência | B39: Atributo | C39: Bônus | D39: Eficiência | E39: Eficácia (preencha Sim) | F39: Penalidade (Armadura Pesada) | G39: Extra (Bênçãos) | H39: Total | I39: Rolagem | J39: Vantagem racial | K39: Aviso
A40: Potência Física | B40: {=INDEX(Dados!$B$75:$B$80,1)} -> Poder | C40: {=IFERROR(INDEX('Criação'!$F$44:$F$49,MATCH($B$40,'Criação'!$A$44:$A$49,0)),0)} -> 0 | D40: ="+"&'Criação'!$C$14 -> +2 | F40: =IF($B$40="Agilidade",'Criação'!$E$93,0) -> 0 | G40: =IF(Equipamento!$J$31="Potência Física",Equipamento!$I$31,0)+MIN('Criação'!$J$14,COUNTIF(Equipamento!$P$45:$P$47,"Potência Física")+'Em Jogo'!$Q$8) -> 0 | H40: =$C$40+IF(AND($E$40="Sim",COUNTIF($E$40:E40,"Sim")<='Criação'!$F$14),2*'Criação'!$C$14,'Criação'!$C$14)+$F$40+$G$40 -> 2 | I40: ="d20"&IF($H$40>=0,"+","")&$H$40 -> d20+2 | J40: =IF(OR('Criação'!$B$25="Xianzhouíta"),"Vantagem ("&'Criação'!$B$25&")","") | K40: =IF(AND($E$40="Sim",COUNTIF($E$40:E40,"Sim")>'Criação'!$F$14),"Acima dos slots de Eficácia em Testes de Resistência ("&'Criação'!$F$14&"). ","")&IF((COUNTIF(Equipamento!$P$45:$P$47,"Potência Física")+'Em Jogo'!$Q$8)>'Criação'!$J$14,"Bônus temporário acima do teto (+"&'Criação'!$J$14&"): conta só o teto (26.6).","")
A41: Reflexos | B41: {=INDEX(Dados!$B$75:$B$80,2)} -> Agilidade | C41: {=IFERROR(INDEX('Criação'!$F$44:$F$49,MATCH($B$41,'Criação'!$A$44:$A$49,0)),0)} -> 0 | D41: ="+"&'Criação'!$C$14 -> +2 | F41: =IF($B$41="Agilidade",'Criação'!$E$93,0) -> 0 | G41: =IF(Equipamento!$J$31="Reflexos",Equipamento!$I$31,0)+MIN('Criação'!$J$14,COUNTIF(Equipamento!$P$45:$P$47,"Reflexos")+'Em Jogo'!$Q$8) -> 0 | H41: =$C$41+IF(AND($E$41="Sim",COUNTIF($E$40:E41,"Sim")<='Criação'!$F$14),2*'Criação'!$C$14,'Criação'!$C$14)+$F$41+$G$41 -> 2 | I41: ="d20"&IF($H$41>=0,"+","")&$H$41 -> d20+2 | J41: =IF(OR('Criação'!$B$25="Xianzhouíta"),"Vantagem ("&'Criação'!$B$25&")","") | K41: =IF(AND($E$41="Sim",COUNTIF($E$40:E41,"Sim")>'Criação'!$F$14),"Acima dos slots de Eficácia em Testes de Resistência ("&'Criação'!$F$14&"). ","")&IF((COUNTIF(Equipamento!$P$45:$P$47,"Reflexos")+'Em Jogo'!$Q$8)>'Criação'!$J$14,"Bônus temporário acima do teto (+"&'Criação'!$J$14&"): conta só o teto (26.6).","")
A42: Resistência Física | B42: {=INDEX(Dados!$B$75:$B$80,3)} -> Vigor | C42: {=IFERROR(INDEX('Criação'!$F$44:$F$49,MATCH($B$42,'Criação'!$A$44:$A$49,0)),0)} -> 0 | D42: ="+"&'Criação'!$C$14 -> +2 | F42: =IF($B$42="Agilidade",'Criação'!$E$93,0) -> 0 | G42: =IF(Equipamento!$J$31="Resistência Física",Equipamento!$I$31,0)+MIN('Criação'!$J$14,COUNTIF(Equipamento!$P$45:$P$47,"Resistência Física")+'Em Jogo'!$Q$8) -> 0 | H42: =$C$42+IF(AND($E$42="Sim",COUNTIF($E$40:E42,"Sim")<='Criação'!$F$14),2*'Criação'!$C$14,'Criação'!$C$14)+$F$42+$G$42 -> 2 | I42: ="d20"&IF($H$42>=0,"+","")&$H$42 -> d20+2 | J42: =IF(OR('Criação'!$B$25="Xianzhouíta"),"Vantagem ("&'Criação'!$B$25&")","")&IF(OR('Criação'!$B$25="Vidyadhara"),"Vantagem condicional ("&'Criação'!$B$25&": água, frio e afogamento)","") | K42: =IF(AND($E$42="Sim",COUNTIF($E$40:E42,"Sim")>'Criação'!$F$14),"Acima dos slots de Eficácia em Testes de Resistência ("&'Criação'!$F$14&"). ","")&IF((COUNTIF(Equipamento!$P$45:$P$47,"Resistência Física")+'Em Jogo'!$Q$8)>'Criação'!$J$14,"Bônus temporário acima do teto (+"&'Criação'!$J$14&"): conta só o teto (26.6).","")
A43: Resistência Mental | B43: {=INDEX(Dados!$B$75:$B$80,4)} -> Sincronia | C43: {=IFERROR(INDEX('Criação'!$F$44:$F$49,MATCH($B$43,'Criação'!$A$44:$A$49,0)),0)} -> 0 | D43: ="+"&'Criação'!$C$14 -> +2 | F43: =IF($B$43="Agilidade",'Criação'!$E$93,0) -> 0 | G43: =IF(Equipamento!$J$31="Resistência Mental",Equipamento!$I$31,0)+MIN('Criação'!$J$14,COUNTIF(Equipamento!$P$45:$P$47,"Resistência Mental")+'Em Jogo'!$Q$8+'Em Jogo'!$Q$11) -> 0 | H43: =$C$43+IF(AND($E$43="Sim",COUNTIF($E$40:E43,"Sim")<='Criação'!$F$14),2*'Criação'!$C$14,'Criação'!$C$14)+$F$43+$G$43 -> 2 | I43: ="d20"&IF($H$43>=0,"+","")&$H$43 -> d20+2 | J43: =IF(OR('Criação'!$B$25="Xianzhouíta",'Criação'!$B$25="Avginiano"),"Vantagem ("&'Criação'!$B$25&")","") | K43: =IF(AND($E$43="Sim",COUNTIF($E$40:E43,"Sim")>'Criação'!$F$14),"Acima dos slots de Eficácia em Testes de Resistência ("&'Criação'!$F$14&"). ","")&IF((COUNTIF(Equipamento!$P$45:$P$47,"Resistência Mental")+'Em Jogo'!$Q$8+'Em Jogo'!$Q$11)>'Criação'!$J$14,"Bônus temporário acima do teto (+"&'Criação'!$J$14&"): conta só o teto (26.6).","")
A44: Percepção Mental | B44: {=INDEX(Dados!$B$75:$B$80,5)} -> Discernimento | C44: {=IFERROR(INDEX('Criação'!$F$44:$F$49,MATCH($B$44,'Criação'!$A$44:$A$49,0)),0)} -> 0 | D44: ="+"&'Criação'!$C$14 -> +2 | F44: =IF($B$44="Agilidade",'Criação'!$E$93,0) -> 0 | G44: =IF(Equipamento!$J$31="Percepção Mental",Equipamento!$I$31,0)+MIN('Criação'!$J$14,COUNTIF(Equipamento!$P$45:$P$47,"Percepção Mental")+'Em Jogo'!$Q$8) -> 0 | H44: =$C$44+IF(AND($E$44="Sim",COUNTIF($E$40:E44,"Sim")<='Criação'!$F$14),2*'Criação'!$C$14,'Criação'!$C$14)+$F$44+$G$44 -> 2 | I44: ="d20"&IF($H$44>=0,"+","")&$H$44 -> d20+2 | J44: =IF(OR('Criação'!$B$25="Xianzhouíta",'Criação'!$B$25="Avginiano"),"Vantagem ("&'Criação'!$B$25&")","") | K44: =IF(AND($E$44="Sim",COUNTIF($E$40:E44,"Sim")>'Criação'!$F$14),"Acima dos slots de Eficácia em Testes de Resistência ("&'Criação'!$F$14&"). ","")&IF((COUNTIF(Equipamento!$P$45:$P$47,"Percepção Mental")+'Em Jogo'!$Q$8)>'Criação'!$J$14,"Bônus temporário acima do teto (+"&'Criação'!$J$14&"): conta só o teto (26.6).","")
A45: Força de Vontade | B45: {=INDEX(Dados!$B$75:$B$80,6)} -> Presença | C45: {=IFERROR(INDEX('Criação'!$F$44:$F$49,MATCH($B$45,'Criação'!$A$44:$A$49,0)),0)} -> 0 | D45: ="+"&'Criação'!$C$14 -> +2 | F45: =IF($B$45="Agilidade",'Criação'!$E$93,0) -> 0 | G45: =IF(Equipamento!$J$31="Força de Vontade",Equipamento!$I$31,0)+MIN('Criação'!$J$14,COUNTIF(Equipamento!$P$45:$P$47,"Força de Vontade")+'Em Jogo'!$Q$8+'Em Jogo'!$Q$11) -> 0 | H45: =$C$45+IF(AND($E$45="Sim",COUNTIF($E$40:E45,"Sim")<='Criação'!$F$14),2*'Criação'!$C$14,'Criação'!$C$14)+$F$45+$G$45 -> 2 | I45: ="d20"&IF($H$45>=0,"+","")&$H$45 -> d20+2 | J45: =IF(OR('Criação'!$B$25="Xianzhouíta",'Criação'!$B$25="Vulpes",'Criação'!$B$25="Avginiano"),"Vantagem ("&'Criação'!$B$25&")","") | K45: =IF(AND($E$45="Sim",COUNTIF($E$40:E45,"Sim")>'Criação'!$F$14),"Acima dos slots de Eficácia em Testes de Resistência ("&'Criação'!$F$14&"). ","")&IF((COUNTIF(Equipamento!$P$45:$P$47,"Força de Vontade")+'Em Jogo'!$Q$8+'Em Jogo'!$Q$11)>'Criação'!$J$14,"Bônus temporário acima do teto (+"&'Criação'!$J$14&"): conta só o teto (26.6).","")
A46: Teste de Morrendo (sem Eficiência, DT 10) | B46: Presença | C46: ='Criação'!$F$49 -> #ERROR! | D46: Não usa | H46: =$C$46 -> #ERROR! | I46: ="d20"&IF($H$46>=0,"+","")&$H$46&" ≥ 10" -> #ERROR! | J46: =IF(OR('Criação'!$B$25="Xianzhouíta",'Criação'!$B$25="Vulpes",'Criação'!$B$25="Avginiano"),"Vantagem ("&'Criação'!$B$25&", 23.5)","") | K46: 3 sucessos: 1 PV · 3 falhas: morre (23.4)
A47: Slots de Eficácia em Testes de Resistência: marcados / permitidos | B47: =COUNTIF($E$40:$E$45,"Sim") -> 0 | C47: ='Criação'!$F$14 -> 0

Sheet Habilidades
A1: Habilidades — Explorando Galáxias v1.1
A2: Legenda: | B2: Entrada (preencha) | C2: Calculada (automático) | D2: Aviso (texto em vermelho) | E2: Título de bloco | F2: Cabeçalho de coluna | G2: Rótulo da linha | H2: Linha alternada (outro tom) | I2: Não se aplica
A3: As suas Habilidades (até 8) e a Ultimate.
A5: Seus números de Habilidade (automático) — 16.3, 16.6 e 26.2
A6: Teste de Ataque (Habilidades e Ultimate) | C6: ='Criação'!$C$57 -> #ERROR! | D6: DT das Habilidades | F6: ='Criação'!$B$56 -> 10 | G6: Nível máximo | I6: ='Criação'!$B$16 -> 1
A7: Habilidades preenchidas / conhecidas | C7: =SUM($P$12:$P$19) -> 0 | D7: ="de "&'Criação'!$A$16 -> de 1 | E7: =IF('Criação'!$C$16="Sim","A partir do nível 16: em vez de aprender, reescreva 1 Habilidade conhecida por nível (16.6)","Passivas contam no teto de 8 (16.6)") -> Passivas contam no teto de 8 (16.6) | L7: =IF($C$7>'Criação'!$A$16,"Habilidades acima das conhecidas no seu nível ("&'Criação'!$A$16&"): confira as linhas abaixo.","")
A8: Ressonância III (26.7) | C8: =IF('Progressão'!$R$69="","Ainda não ativa: libera no nível 15 (aba Progressão)","Ativa: marque Sim em uma Habilidade para ela subir 1 Nível de efeito, até o Nível máximo") -> Ainda não ativa: libera no nível 15 (aba Progressão) | L8: =IF(COUNTIF($H$12:$H$19,"Sim")>1,"Ressonância III marcada em mais de uma Habilidade: vale só a primeira.","")
A10: Suas Habilidades (preencha) — até 8; escreva pelos sete passos de 16.7
A11: Nº | B11: Nome (preencha) | C11: Tipo | D11: Nível (1 a 7) | E11: Em área? | F11: Resolução | G11: Alcance | H11: Ressonância III aqui? | I11: Aviso | P11: preenchida | Q11: Nível usado | R11: Ress. III vale | S11: Nível efetivo | T11: dados (tabela) | U11: nº de dados | V11: face | W11: fixo
A12: 1 | I12: =IF($P$12=0,"",IF($C$12="","Escolha o Tipo. ",IF(COUNTIF(Dados!$W$6:$W$10,$C$12)=0,"Tipo fora da lista (16.5). ",""))&IF(LEN($D$12)=0,"",IF(ISNUMBER($D$12),IF(OR($D$12<1,$D$12>7),"O Nível vai de 1 a 7. ","")&IF($D$12>'Criação'!$B$16,"Acima do Nível máximo do seu nível ("&'Criação'!$B$16&"). ",""),"Nível precisa ser um número de 1 a 7. "))&IF(LEN($G$12)=0,"",IF(ISERROR(MATCH($G$12,Dados!$X$6:$X$10,0)),"Alcance fora da lista. ",IF(MATCH($G$12,Dados!$X$6:$X$10,0)>MATCH($I$34,Dados!$X$6:$X$10,0),"Alcance acima do que o Nível "&$S$12&" permite (até "&$I$34&"). ","")))&IF(SUM($P$12:P12)>'Criação'!$A$16,"Acima das "&'Criação'!$A$16&" Habilidades conhecidas do seu nível. ","")&IF($H$12="Sim",IF('Progressão'!$R$69="","Ressonância III ainda não está ativa. ",IF(COUNTIF($H$12:H12,"Sim")>1,"Ressonância III só vale numa Habilidade. ","")),"")) | P12: =IF(OR(LEN($B$12)>0,LEN($C$12)>0,LEN($D$12)>0,LEN($E$12)>0,LEN($F$12)>0,LEN($G$12)>0,LEN($H$12)>0,LEN($C$23)>0),1,0) -> 0 | Q12: =IF(ISNUMBER($D$12),MAX(1,MIN(7,INT($D$12))),1) -> 1 | R12: =IF(AND($H$12="Sim",'Progressão'!$R$69<>"",COUNTIF($H$12:H12,"Sim")=1),1,0) -> 0 | S12: =IF(AND($R$12=1,$Q$12<'Criação'!$B$16),MIN('Criação'!$B$16,$Q$12+1),$Q$12) -> 1 | T12: {=IF($C$12="Dano",INDEX(Dados!$C$296:$C$302,$S$12),IF($C$12="Cura",INDEX(Dados!$G$296:$G$302,$S$12),0))} -> 0 | U12: =IF(AND($E$12="Sim",$T$12>0),MAX(1,INT($T$12/2)),$T$12) -> 0 | V12: {=IF($C$12="Dano",INDEX(Dados!$D$296:$D$302,$S$12),IF($C$12="Cura",INDEX(Dados!$H$296:$H$302,$S$12),0))} -> 0 | W12: =IF(OR($C$12="Dano",$C$12="Cura"),'Criação'!$B$55+IF($C$12="Dano",Equipamento!$P$40+Equipamento!$E$31,0),0) -> 0
A13: 2 | I13: =IF($P$13=0,"",IF($C$13="","Escolha o Tipo. ",IF(COUNTIF(Dados!$W$6:$W$10,$C$13)=0,"Tipo fora da lista (16.5). ",""))&IF(LEN($D$13)=0,"",IF(ISNUMBER($D$13),IF(OR($D$13<1,$D$13>7),"O Nível vai de 1 a 7. ","")&IF($D$13>'Criação'!$B$16,"Acima do Nível máximo do seu nível ("&'Criação'!$B$16&"). ",""),"Nível precisa ser um número de 1 a 7. "))&IF(LEN($G$13)=0,"",IF(ISERROR(MATCH($G$13,Dados!$X$6:$X$10,0)),"Alcance fora da lista. ",IF(MATCH($G$13,Dados!$X$6:$X$10,0)>MATCH($I$35,Dados!$X$6:$X$10,0),"Alcance acima do que o Nível "&$S$13&" permite (até "&$I$35&"). ","")))&IF(SUM($P$12:P13)>'Criação'!$A$16,"Acima das "&'Criação'!$A$16&" Habilidades conhecidas do seu nível. ","")&IF($H$13="Sim",IF('Progressão'!$R$69="","Ressonância III ainda não está ativa. ",IF(COUNTIF($H$12:H13,"Sim")>1,"Ressonância III só vale numa Habilidade. ","")),"")) | P13: =IF(OR(LEN($B$13)>0,LEN($C$13)>0,LEN($D$13)>0,LEN($E$13)>0,LEN($F$13)>0,LEN($G$13)>0,LEN($H$13)>0,LEN($C$24)>0),1,0) -> 0 | Q13: =IF(ISNUMBER($D$13),MAX(1,MIN(7,INT($D$13))),1) -> 1 | R13: =IF(AND($H$13="Sim",'Progressão'!$R$69<>"",COUNTIF($H$12:H13,"Sim")=1),1,0) -> 0 | S13: =IF(AND($R$13=1,$Q$13<'Criação'!$B$16),MIN('Criação'!$B$16,$Q$13+1),$Q$13) -> 1 | T13: {=IF($C$13="Dano",INDEX(Dados!$C$296:$C$302,$S$13),IF($C$13="Cura",INDEX(Dados!$G$296:$G$302,$S$13),0))} -> 0 | U13: =IF(AND($E$13="Sim",$T$13>0),MAX(1,INT($T$13/2)),$T$13) -> 0 | V13: {=IF($C$13="Dano",INDEX(Dados!$D$296:$D$302,$S$13),IF($C$13="Cura",INDEX(Dados!$H$296:$H$302,$S$13),0))} -> 0 | W13: =IF(OR($C$13="Dano",$C$13="Cura"),'Criação'!$B$55+IF($C$13="Dano",Equipamento!$P$40+Equipamento!$E$31,0),0) -> 0
A14: 3 | I14: =IF($P$14=0,"",IF($C$14="","Escolha o Tipo. ",IF(COUNTIF(Dados!$W$6:$W$10,$C$14)=0,"Tipo fora da lista (16.5). ",""))&IF(LEN($D$14)=0,"",IF(ISNUMBER($D$14),IF(OR($D$14<1,$D$14>7),"O Nível vai de 1 a 7. ","")&IF($D$14>'Criação'!$B$16,"Acima do Nível máximo do seu nível ("&'Criação'!$B$16&"). ",""),"Nível precisa ser um número de 1 a 7. "))&IF(LEN($G$14)=0,"",IF(ISERROR(MATCH($G$14,Dados!$X$6:$X$10,0)),"Alcance fora da lista. ",IF(MATCH($G$14,Dados!$X$6:$X$10,0)>MATCH($I$36,Dados!$X$6:$X$10,0),"Alcance acima do que o Nível "&$S$14&" permite (até "&$I$36&"). ","")))&IF(SUM($P$12:P14)>'Criação'!$A$16,"Acima das "&'Criação'!$A$16&" Habilidades conhecidas do seu nível. ","")&IF($H$14="Sim",IF('Progressão'!$R$69="","Ressonância III ainda não está ativa. ",IF(COUNTIF($H$12:H14,"Sim")>1,"Ressonância III só vale numa Habilidade. ","")),"")) | P14: =IF(OR(LEN($B$14)>0,LEN($C$14)>0,LEN($D$14)>0,LEN($E$14)>0,LEN($F$14)>0,LEN($G$14)>0,LEN($H$14)>0,LEN($C$25)>0),1,0) -> 0 | Q14: =IF(ISNUMBER($D$14),MAX(1,MIN(7,INT($D$14))),1) -> 1 | R14: =IF(AND($H$14="Sim",'Progressão'!$R$69<>"",COUNTIF($H$12:H14,"Sim")=1),1,0) -> 0 | S14: =IF(AND($R$14=1,$Q$14<'Criação'!$B$16),MIN('Criação'!$B$16,$Q$14+1),$Q$14) -> 1 | T14: {=IF($C$14="Dano",INDEX(Dados!$C$296:$C$302,$S$14),IF($C$14="Cura",INDEX(Dados!$G$296:$G$302,$S$14),0))} -> 0 | U14: =IF(AND($E$14="Sim",$T$14>0),MAX(1,INT($T$14/2)),$T$14) -> 0 | V14: {=IF($C$14="Dano",INDEX(Dados!$D$296:$D$302,$S$14),IF($C$14="Cura",INDEX(Dados!$H$296:$H$302,$S$14),0))} -> 0 | W14: =IF(OR($C$14="Dano",$C$14="Cura"),'Criação'!$B$55+IF($C$14="Dano",Equipamento!$P$40+Equipamento!$E$31,0),0) -> 0
A15: 4 | I15: =IF($P$15=0,"",IF($C$15="","Escolha o Tipo. ",IF(COUNTIF(Dados!$W$6:$W$10,$C$15)=0,"Tipo fora da lista (16.5). ",""))&IF(LEN($D$15)=0,"",IF(ISNUMBER($D$15),IF(OR($D$15<1,$D$15>7),"O Nível vai de 1 a 7. ","")&IF($D$15>'Criação'!$B$16,"Acima do Nível máximo do seu nível ("&'Criação'!$B$16&"). ",""),"Nível precisa ser um número de 1 a 7. "))&IF(LEN($G$15)=0,"",IF(ISERROR(MATCH($G$15,Dados!$X$6:$X$10,0)),"Alcance fora da lista. ",IF(MATCH($G$15,Dados!$X$6:$X$10,0)>MATCH($I$37,Dados!$X$6:$X$10,0),"Alcance acima do que o Nível "&$S$15&" permite (até "&$I$37&"). ","")))&IF(SUM($P$12:P15)>'Criação'!$A$16,"Acima das "&'Criação'!$A$16&" Habilidades conhecidas do seu nível. ","")&IF($H$15="Sim",IF('Progressão'!$R$69="","Ressonância III ainda não está ativa. ",IF(COUNTIF($H$12:H15,"Sim")>1,"Ressonância III só vale numa Habilidade. ","")),"")) | P15: =IF(OR(LEN($B$15)>0,LEN($C$15)>0,LEN($D$15)>0,LEN($E$15)>0,LEN($F$15)>0,LEN($G$15)>0,LEN($H$15)>0,LEN($C$26)>0),1,0) -> 0 | Q15: =IF(ISNUMBER($D$15),MAX(1,MIN(7,INT($D$15))),1) -> 1 | R15: =IF(AND($H$15="Sim",'Progressão'!$R$69<>"",COUNTIF($H$12:H15,"Sim")=1),1,0) -> 0 | S15: =IF(AND($R$15=1,$Q$15<'Criação'!$B$16),MIN('Criação'!$B$16,$Q$15+1),$Q$15) -> 1 | T15: {=IF($C$15="Dano",INDEX(Dados!$C$296:$C$302,$S$15),IF($C$15="Cura",INDEX(Dados!$G$296:$G$302,$S$15),0))} -> 0 | U15: =IF(AND($E$15="Sim",$T$15>0),MAX(1,INT($T$15/2)),$T$15) -> 0 | V15: {=IF($C$15="Dano",INDEX(Dados!$D$296:$D$302,$S$15),IF($C$15="Cura",INDEX(Dados!$H$296:$H$302,$S$15),0))} -> 0 | W15: =IF(OR($C$15="Dano",$C$15="Cura"),'Criação'!$B$55+IF($C$15="Dano",Equipamento!$P$40+Equipamento!$E$31,0),0) -> 0
A16: 5 | I16: =IF($P$16=0,"",IF($C$16="","Escolha o Tipo. ",IF(COUNTIF(Dados!$W$6:$W$10,$C$16)=0,"Tipo fora da lista (16.5). ",""))&IF(LEN($D$16)=0,"",IF(ISNUMBER($D$16),IF(OR($D$16<1,$D$16>7),"O Nível vai de 1 a 7. ","")&IF($D$16>'Criação'!$B$16,"Acima do Nível máximo do seu nível ("&'Criação'!$B$16&"). ",""),"Nível precisa ser um número de 1 a 7. "))&IF(LEN($G$16)=0,"",IF(ISERROR(MATCH($G$16,Dados!$X$6:$X$10,0)),"Alcance fora da lista. ",IF(MATCH($G$16,Dados!$X$6:$X$10,0)>MATCH($I$38,Dados!$X$6:$X$10,0),"Alcance acima do que o Nível "&$S$16&" permite (até "&$I$38&"). ","")))&IF(SUM($P$12:P16)>'Criação'!$A$16,"Acima das "&'Criação'!$A$16&" Habilidades conhecidas do seu nível. ","")&IF($H$16="Sim",IF('Progressão'!$R$69="","Ressonância III ainda não está ativa. ",IF(COUNTIF($H$12:H16,"Sim")>1,"Ressonância III só vale numa Habilidade. ","")),"")) | P16: =IF(OR(LEN($B$16)>0,LEN($C$16)>0,LEN($D$16)>0,LEN($E$16)>0,LEN($F$16)>0,LEN($G$16)>0,LEN($H$16)>0,LEN($C$27)>0),1,0) -> 0 | Q16: =IF(ISNUMBER($D$16),MAX(1,MIN(7,INT($D$16))),1) -> 1 | R16: =IF(AND($H$16="Sim",'Progressão'!$R$69<>"",COUNTIF($H$12:H16,"Sim")=1),1,0) -> 0 | S16: =IF(AND($R$16=1,$Q$16<'Criação'!$B$16),MIN('Criação'!$B$16,$Q$16+1),$Q$16) -> 1 | T16: {=IF($C$16="Dano",INDEX(Dados!$C$296:$C$302,$S$16),IF($C$16="Cura",INDEX(Dados!$G$296:$G$302,$S$16),0))} -> 0 | U16: =IF(AND($E$16="Sim",$T$16>0),MAX(1,INT($T$16/2)),$T$16) -> 0 | V16: {=IF($C$16="Dano",INDEX(Dados!$D$296:$D$302,$S$16),IF($C$16="Cura",INDEX(Dados!$H$296:$H$302,$S$16),0))} -> 0 | W16: =IF(OR($C$16="Dano",$C$16="Cura"),'Criação'!$B$55+IF($C$16="Dano",Equipamento!$P$40+Equipamento!$E$31,0),0) -> 0
A17: 6 | I17: =IF($P$17=0,"",IF($C$17="","Escolha o Tipo. ",IF(COUNTIF(Dados!$W$6:$W$10,$C$17)=0,"Tipo fora da lista (16.5). ",""))&IF(LEN($D$17)=0,"",IF(ISNUMBER($D$17),IF(OR($D$17<1,$D$17>7),"O Nível vai de 1 a 7. ","")&IF($D$17>'Criação'!$B$16,"Acima do Nível máximo do seu nível ("&'Criação'!$B$16&"). ",""),"Nível precisa ser um número de 1 a 7. "))&IF(LEN($G$17)=0,"",IF(ISERROR(MATCH($G$17,Dados!$X$6:$X$10,0)),"Alcance fora da lista. ",IF(MATCH($G$17,Dados!$X$6:$X$10,0)>MATCH($I$39,Dados!$X$6:$X$10,0),"Alcance acima do que o Nível "&$S$17&" permite (até "&$I$39&"). ","")))&IF(SUM($P$12:P17)>'Criação'!$A$16,"Acima das "&'Criação'!$A$16&" Habilidades conhecidas do seu nível. ","")&IF($H$17="Sim",IF('Progressão'!$R$69="","Ressonância III ainda não está ativa. ",IF(COUNTIF($H$12:H17,"Sim")>1,"Ressonância III só vale numa Habilidade. ","")),"")) | P17: =IF(OR(LEN($B$17)>0,LEN($C$17)>0,LEN($D$17)>0,LEN($E$17)>0,LEN($F$17)>0,LEN($G$17)>0,LEN($H$17)>0,LEN($C$28)>0),1,0) -> 0 | Q17: =IF(ISNUMBER($D$17),MAX(1,MIN(7,INT($D$17))),1) -> 1 | R17: =IF(AND($H$17="Sim",'Progressão'!$R$69<>"",COUNTIF($H$12:H17,"Sim")=1),1,0) -> 0 | S17: =IF(AND($R$17=1,$Q$17<'Criação'!$B$16),MIN('Criação'!$B$16,$Q$17+1),$Q$17) -> 1 | T17: {=IF($C$17="Dano",INDEX(Dados!$C$296:$C$302,$S$17),IF($C$17="Cura",INDEX(Dados!$G$296:$G$302,$S$17),0))} -> 0 | U17: =IF(AND($E$17="Sim",$T$17>0),MAX(1,INT($T$17/2)),$T$17) -> 0 | V17: {=IF($C$17="Dano",INDEX(Dados!$D$296:$D$302,$S$17),IF($C$17="Cura",INDEX(Dados!$H$296:$H$302,$S$17),0))} -> 0 | W17: =IF(OR($C$17="Dano",$C$17="Cura"),'Criação'!$B$55+IF($C$17="Dano",Equipamento!$P$40+Equipamento!$E$31,0),0) -> 0
A18: 7 | I18: =IF($P$18=0,"",IF($C$18="","Escolha o Tipo. ",IF(COUNTIF(Dados!$W$6:$W$10,$C$18)=0,"Tipo fora da lista (16.5). ",""))&IF(LEN($D$18)=0,"",IF(ISNUMBER($D$18),IF(OR($D$18<1,$D$18>7),"O Nível vai de 1 a 7. ","")&IF($D$18>'Criação'!$B$16,"Acima do Nível máximo do seu nível ("&'Criação'!$B$16&"). ",""),"Nível precisa ser um número de 1 a 7. "))&IF(LEN($G$18)=0,"",IF(ISERROR(MATCH($G$18,Dados!$X$6:$X$10,0)),"Alcance fora da lista. ",IF(MATCH($G$18,Dados!$X$6:$X$10,0)>MATCH($I$40,Dados!$X$6:$X$10,0),"Alcance acima do que o Nível "&$S$18&" permite (até "&$I$40&"). ","")))&IF(SUM($P$12:P18)>'Criação'!$A$16,"Acima das "&'Criação'!$A$16&" Habilidades conhecidas do seu nível. ","")&IF($H$18="Sim",IF('Progressão'!$R$69="","Ressonância III ainda não está ativa. ",IF(COUNTIF($H$12:H18,"Sim")>1,"Ressonância III só vale numa Habilidade. ","")),"")) | P18: =IF(OR(LEN($B$18)>0,LEN($C$18)>0,LEN($D$18)>0,LEN($E$18)>0,LEN($F$18)>0,LEN($G$18)>0,LEN($H$18)>0,LEN($C$29)>0),1,0) -> 0 | Q18: =IF(ISNUMBER($D$18),MAX(1,MIN(7,INT($D$18))),1) -> 1 | R18: =IF(AND($H$18="Sim",'Progressão'!$R$69<>"",COUNTIF($H$12:H18,"Sim")=1),1,0) -> 0 | S18: =IF(AND($R$18=1,$Q$18<'Criação'!$B$16),MIN('Criação'!$B$16,$Q$18+1),$Q$18) -> 1 | T18: {=IF($C$18="Dano",INDEX(Dados!$C$296:$C$302,$S$18),IF($C$18="Cura",INDEX(Dados!$G$296:$G$302,$S$18),0))} -> 0 | U18: =IF(AND($E$18="Sim",$T$18>0),MAX(1,INT($T$18/2)),$T$18) -> 0 | V18: {=IF($C$18="Dano",INDEX(Dados!$D$296:$D$302,$S$18),IF($C$18="Cura",INDEX(Dados!$H$296:$H$302,$S$18),0))} -> 0 | W18: =IF(OR($C$18="Dano",$C$18="Cura"),'Criação'!$B$55+IF($C$18="Dano",Equipamento!$P$40+Equipamento!$E$31,0),0) -> 0
A19: 8 | I19: =IF($P$19=0,"",IF($C$19="","Escolha o Tipo. ",IF(COUNTIF(Dados!$W$6:$W$10,$C$19)=0,"Tipo fora da lista (16.5). ",""))&IF(LEN($D$19)=0,"",IF(ISNUMBER($D$19),IF(OR($D$19<1,$D$19>7),"O Nível vai de 1 a 7. ","")&IF($D$19>'Criação'!$B$16,"Acima do Nível máximo do seu nível ("&'Criação'!$B$16&"). ",""),"Nível precisa ser um número de 1 a 7. "))&IF(LEN($G$19)=0,"",IF(ISERROR(MATCH($G$19,Dados!$X$6:$X$10,0)),"Alcance fora da lista. ",IF(MATCH($G$19,Dados!$X$6:$X$10,0)>MATCH($I$41,Dados!$X$6:$X$10,0),"Alcance acima do que o Nível "&$S$19&" permite (até "&$I$41&"). ","")))&IF(SUM($P$12:P19)>'Criação'!$A$16,"Acima das "&'Criação'!$A$16&" Habilidades conhecidas do seu nível. ","")&IF($H$19="Sim",IF('Progressão'!$R$69="","Ressonância III ainda não está ativa. ",IF(COUNTIF($H$12:H19,"Sim")>1,"Ressonância III só vale numa Habilidade. ","")),"")) | P19: =IF(OR(LEN($B$19)>0,LEN($C$19)>0,LEN($D$19)>0,LEN($E$19)>0,LEN($F$19)>0,LEN($G$19)>0,LEN($H$19)>0,LEN($C$30)>0),1,0) -> 0 | Q19: =IF(ISNUMBER($D$19),MAX(1,MIN(7,INT($D$19))),1) -> 1 | R19: =IF(AND($H$19="Sim",'Progressão'!$R$69<>"",COUNTIF($H$12:H19,"Sim")=1),1,0) -> 0 | S19: =IF(AND($R$19=1,$Q$19<'Criação'!$B$16),MIN('Criação'!$B$16,$Q$19+1),$Q$19) -> 1 | T19: {=IF($C$19="Dano",INDEX(Dados!$C$296:$C$302,$S$19),IF($C$19="Cura",INDEX(Dados!$G$296:$G$302,$S$19),0))} -> 0 | U19: =IF(AND($E$19="Sim",$T$19>0),MAX(1,INT($T$19/2)),$T$19) -> 0 | V19: {=IF($C$19="Dano",INDEX(Dados!$D$296:$D$302,$S$19),IF($C$19="Cura",INDEX(Dados!$H$296:$H$302,$S$19),0))} -> 0 | W19: =IF(OR($C$19="Dano",$C$19="Cura"),'Criação'!$B$55+IF($C$19="Dano",Equipamento!$P$40+Equipamento!$E$31,0),0) -> 0
A21: Efeito de cada Habilidade (preencha) — o que ela faz, em uma ou duas frases
A22: Nº | B22: Nome (automático) | C22: Efeito (preencha)
A23: 1 | B23: =IF(LEN($B$12)=0,"Habilidade 1",""&$B$12) -> Habilidade 1
A24: 2 | B24: =IF(LEN($B$13)=0,"Habilidade 2",""&$B$13) -> Habilidade 2
A25: 3 | B25: =IF(LEN($B$14)=0,"Habilidade 3",""&$B$14) -> Habilidade 3
A26: 4 | B26: =IF(LEN($B$15)=0,"Habilidade 4",""&$B$15) -> Habilidade 4
A27: 5 | B27: =IF(LEN($B$16)=0,"Habilidade 5",""&$B$16) -> Habilidade 5
A28: 6 | B28: =IF(LEN($B$17)=0,"Habilidade 6",""&$B$17) -> Habilidade 6
A29: 7 | B29: =IF(LEN($B$18)=0,"Habilidade 7",""&$B$18) -> Habilidade 7
A30: 8 | B30: =IF(LEN($B$19)=0,"Habilidade 8",""&$B$19) -> Habilidade 8
A32: Números das Habilidades (automático) — 16.3, 16.4 e 16.5
A33: Nº | B33: Nome | C33: Nível efetivo | D33: Dano ou cura | E33: Média | F33: Rolagem ou DT | G33: PH | H33: Redução de Tenacidade | I33: Alcance máximo | J33: Alvos | K33: Dados da tabela | L33: Média dos dados
A34: 1 | B34: =IF($P$12=0,"",IF(LEN($B$12)=0,"Habilidade 1",""&$B$12)) | C34: =IF($P$12=0,"",$S$12) | D34: =IF(OR($P$12=0,$U$12=0),"",IF($U$12<=0,""&$W$12,$U$12&"d"&$V$12&IF($W$12>0,"+"&$W$12,IF($W$12<0,""&$W$12,"")))) | E34: =IF(OR($P$12=0,$U$12=0),"",INT($U$12*($V$12+1)/2)+$W$12) | F34: =IF($P$12=0,"",IF($F$12="Teste de Ataque",'Criação'!$C$57,IF($F$12="Teste de Resistência","DT "&'Criação'!$B$56,""))) | G34: {=IF($P$12=0,"",IF($C$12="Passiva",0,INDEX(Dados!$J$296:$J$302,$S$12)))} | H34: {=IF($P$12=0,"",IF($C$12="Dano",INDEX(Dados!$K$296:$K$302,$S$12),0))} | I34: =IF($P$12=0,"",CHOOSE(MIN(4,$S$12),"Curta","Média","Longa","Extrema")) | J34: =IF($P$12=0,"",IF($E$12="Sim",IF($S$12>=6,4,3),1)) | K34: =IF(OR($P$12=0,$U$12=0),"",$U$12&"d"&$V$12) | L34: =IF(OR($P$12=0,$U$12=0),"",INT($U$12*($V$12+1)/2))
A35: 2 | B35: =IF($P$13=0,"",IF(LEN($B$13)=0,"Habilidade 2",""&$B$13)) | C35: =IF($P$13=0,"",$S$13) | D35: =IF(OR($P$13=0,$U$13=0),"",IF($U$13<=0,""&$W$13,$U$13&"d"&$V$13&IF($W$13>0,"+"&$W$13,IF($W$13<0,""&$W$13,"")))) | E35: =IF(OR($P$13=0,$U$13=0),"",INT($U$13*($V$13+1)/2)+$W$13) | F35: =IF($P$13=0,"",IF($F$13="Teste de Ataque",'Criação'!$C$57,IF($F$13="Teste de Resistência","DT "&'Criação'!$B$56,""))) | G35: {=IF($P$13=0,"",IF($C$13="Passiva",0,INDEX(Dados!$J$296:$J$302,$S$13)))} | H35: {=IF($P$13=0,"",IF($C$13="Dano",INDEX(Dados!$K$296:$K$302,$S$13),0))} | I35: =IF($P$13=0,"",CHOOSE(MIN(4,$S$13),"Curta","Média","Longa","Extrema")) | J35: =IF($P$13=0,"",IF($E$13="Sim",IF($S$13>=6,4,3),1)) | K35: =IF(OR($P$13=0,$U$13=0),"",$U$13&"d"&$V$13) | L35: =IF(OR($P$13=0,$U$13=0),"",INT($U$13*($V$13+1)/2))
A36: 3 | B36: =IF($P$14=0,"",IF(LEN($B$14)=0,"Habilidade 3",""&$B$14)) | C36: =IF($P$14=0,"",$S$14) | D36: =IF(OR($P$14=0,$U$14=0),"",IF($U$14<=0,""&$W$14,$U$14&"d"&$V$14&IF($W$14>0,"+"&$W$14,IF($W$14<0,""&$W$14,"")))) | E36: =IF(OR($P$14=0,$U$14=0),"",INT($U$14*($V$14+1)/2)+$W$14) | F36: =IF($P$14=0,"",IF($F$14="Teste de Ataque",'Criação'!$C$57,IF($F$14="Teste de Resistência","DT "&'Criação'!$B$56,""))) | G36: {=IF($P$14=0,"",IF($C$14="Passiva",0,INDEX(Dados!$J$296:$J$302,$S$14)))} | H36: {=IF($P$14=0,"",IF($C$14="Dano",INDEX(Dados!$K$296:$K$302,$S$14),0))} | I36: =IF($P$14=0,"",CHOOSE(MIN(4,$S$14),"Curta","Média","Longa","Extrema")) | J36: =IF($P$14=0,"",IF($E$14="Sim",IF($S$14>=6,4,3),1)) | K36: =IF(OR($P$14=0,$U$14=0),"",$U$14&"d"&$V$14) | L36: =IF(OR($P$14=0,$U$14=0),"",INT($U$14*($V$14+1)/2))
A37: 4 | B37: =IF($P$15=0,"",IF(LEN($B$15)=0,"Habilidade 4",""&$B$15)) | C37: =IF($P$15=0,"",$S$15) | D37: =IF(OR($P$15=0,$U$15=0),"",IF($U$15<=0,""&$W$15,$U$15&"d"&$V$15&IF($W$15>0,"+"&$W$15,IF($W$15<0,""&$W$15,"")))) | E37: =IF(OR($P$15=0,$U$15=0),"",INT($U$15*($V$15+1)/2)+$W$15) | F37: =IF($P$15=0,"",IF($F$15="Teste de Ataque",'Criação'!$C$57,IF($F$15="Teste de Resistência","DT "&'Criação'!$B$56,""))) | G37: {=IF($P$15=0,"",IF($C$15="Passiva",0,INDEX(Dados!$J$296:$J$302,$S$15)))} | H37: {=IF($P$15=0,"",IF($C$15="Dano",INDEX(Dados!$K$296:$K$302,$S$15),0))} | I37: =IF($P$15=0,"",CHOOSE(MIN(4,$S$15),"Curta","Média","Longa","Extrema")) | J37: =IF($P$15=0,"",IF($E$15="Sim",IF($S$15>=6,4,3),1)) | K37: =IF(OR($P$15=0,$U$15=0),"",$U$15&"d"&$V$15) | L37: =IF(OR($P$15=0,$U$15=0),"",INT($U$15*($V$15+1)/2))
A38: 5 | B38: =IF($P$16=0,"",IF(LEN($B$16)=0,"Habilidade 5",""&$B$16)) | C38: =IF($P$16=0,"",$S$16) | D38: =IF(OR($P$16=0,$U$16=0),"",IF($U$16<=0,""&$W$16,$U$16&"d"&$V$16&IF($W$16>0,"+"&$W$16,IF($W$16<0,""&$W$16,"")))) | E38: =IF(OR($P$16=0,$U$16=0),"",INT($U$16*($V$16+1)/2)+$W$16) | F38: =IF($P$16=0,"",IF($F$16="Teste de Ataque",'Criação'!$C$57,IF($F$16="Teste de Resistência","DT "&'Criação'!$B$56,""))) | G38: {=IF($P$16=0,"",IF($C$16="Passiva",0,INDEX(Dados!$J$296:$J$302,$S$16)))} | H38: {=IF($P$16=0,"",IF($C$16="Dano",INDEX(Dados!$K$296:$K$302,$S$16),0))} | I38: =IF($P$16=0,"",CHOOSE(MIN(4,$S$16),"Curta","Média","Longa","Extrema")) | J38: =IF($P$16=0,"",IF($E$16="Sim",IF($S$16>=6,4,3),1)) | K38: =IF(OR($P$16=0,$U$16=0),"",$U$16&"d"&$V$16) | L38: =IF(OR($P$16=0,$U$16=0),"",INT($U$16*($V$16+1)/2))
A39: 6 | B39: =IF($P$17=0,"",IF(LEN($B$17)=0,"Habilidade 6",""&$B$17)) | C39: =IF($P$17=0,"",$S$17) | D39: =IF(OR($P$17=0,$U$17=0),"",IF($U$17<=0,""&$W$17,$U$17&"d"&$V$17&IF($W$17>0,"+"&$W$17,IF($W$17<0,""&$W$17,"")))) | E39: =IF(OR($P$17=0,$U$17=0),"",INT($U$17*($V$17+1)/2)+$W$17) | F39: =IF($P$17=0,"",IF($F$17="Teste de Ataque",'Criação'!$C$57,IF($F$17="Teste de Resistência","DT "&'Criação'!$B$56,""))) | G39: {=IF($P$17=0,"",IF($C$17="Passiva",0,INDEX(Dados!$J$296:$J$302,$S$17)))} | H39: {=IF($P$17=0,"",IF($C$17="Dano",INDEX(Dados!$K$296:$K$302,$S$17),0))} | I39: =IF($P$17=0,"",CHOOSE(MIN(4,$S$17),"Curta","Média","Longa","Extrema")) | J39: =IF($P$17=0,"",IF($E$17="Sim",IF($S$17>=6,4,3),1)) | K39: =IF(OR($P$17=0,$U$17=0),"",$U$17&"d"&$V$17) | L39: =IF(OR($P$17=0,$U$17=0),"",INT($U$17*($V$17+1)/2))
A40: 7 | B40: =IF($P$18=0,"",IF(LEN($B$18)=0,"Habilidade 7",""&$B$18)) | C40: =IF($P$18=0,"",$S$18) | D40: =IF(OR($P$18=0,$U$18=0),"",IF($U$18<=0,""&$W$18,$U$18&"d"&$V$18&IF($W$18>0,"+"&$W$18,IF($W$18<0,""&$W$18,"")))) | E40: =IF(OR($P$18=0,$U$18=0),"",INT($U$18*($V$18+1)/2)+$W$18) | F40: =IF($P$18=0,"",IF($F$18="Teste de Ataque",'Criação'!$C$57,IF($F$18="Teste de Resistência","DT "&'Criação'!$B$56,""))) | G40: {=IF($P$18=0,"",IF($C$18="Passiva",0,INDEX(Dados!$J$296:$J$302,$S$18)))} | H40: {=IF($P$18=0,"",IF($C$18="Dano",INDEX(Dados!$K$296:$K$302,$S$18),0))} | I40: =IF($P$18=0,"",CHOOSE(MIN(4,$S$18),"Curta","Média","Longa","Extrema")) | J40: =IF($P$18=0,"",IF($E$18="Sim",IF($S$18>=6,4,3),1)) | K40: =IF(OR($P$18=0,$U$18=0),"",$U$18&"d"&$V$18) | L40: =IF(OR($P$18=0,$U$18=0),"",INT($U$18*($V$18+1)/2))
A41: 8 | B41: =IF($P$19=0,"",IF(LEN($B$19)=0,"Habilidade 8",""&$B$19)) | C41: =IF($P$19=0,"",$S$19) | D41: =IF(OR($P$19=0,$U$19=0),"",IF($U$19<=0,""&$W$19,$U$19&"d"&$V$19&IF($W$19>0,"+"&$W$19,IF($W$19<0,""&$W$19,"")))) | E41: =IF(OR($P$19=0,$U$19=0),"",INT($U$19*($V$19+1)/2)+$W$19) | F41: =IF($P$19=0,"",IF($F$19="Teste de Ataque",'Criação'!$C$57,IF($F$19="Teste de Resistência","DT "&'Criação'!$B$56,""))) | G41: {=IF($P$19=0,"",IF($C$19="Passiva",0,INDEX(Dados!$J$296:$J$302,$S$19)))} | H41: {=IF($P$19=0,"",IF($C$19="Dano",INDEX(Dados!$K$296:$K$302,$S$19),0))} | I41: =IF($P$19=0,"",CHOOSE(MIN(4,$S$19),"Curta","Média","Longa","Extrema")) | J41: =IF($P$19=0,"",IF($E$19="Sim",IF($S$19>=6,4,3),1)) | K41: =IF(OR($P$19=0,$U$19=0),"",$U$19&"d"&$V$19) | L41: =IF(OR($P$19=0,$U$19=0),"",INT($U$19*($V$19+1)/2))
A43: Nº | B43: Nome | C43: Bônus fixo | D43: Guia de 16.5 (o que o efeito pode fazer)
A44: 1 | B44: =IF($P$12=0,"",IF(LEN($B$12)=0,"Habilidade 1",""&$B$12)) | C44: =IF($P$12=0,"",$W$12) | D44: {=IF($P$12=0,"",IF(OR($C$12="Buff",$C$12="Debuff"),INDEX(Dados!$B$306:$B$312,$S$12)&" · "&INDEX(Dados!$C$306:$C$312,$S$12)&" · alvos: "&INDEX(Dados!$D$306:$D$312,$S$12),IF($C$12="Passiva",INDEX(Dados!$B$316:$B$322,$S$12)&" · não custa PH",IF(OR($C$12="Dano",$C$12="Cura"),"Dados da tabela 16.3 + Bônus do Atributo de Habilidade, uma vez","Escolha o Tipo"))))}
A45: 2 | B45: =IF($P$13=0,"",IF(LEN($B$13)=0,"Habilidade 2",""&$B$13)) | C45: =IF($P$13=0,"",$W$13) | D45: {=IF($P$13=0,"",IF(OR($C$13="Buff",$C$13="Debuff"),INDEX(Dados!$B$306:$B$312,$S$13)&" · "&INDEX(Dados!$C$306:$C$312,$S$13)&" · alvos: "&INDEX(Dados!$D$306:$D$312,$S$13),IF($C$13="Passiva",INDEX(Dados!$B$316:$B$322,$S$13)&" · não custa PH",IF(OR($C$13="Dano",$C$13="Cura"),"Dados da tabela 16.3 + Bônus do Atributo de Habilidade, uma vez","Escolha o Tipo"))))}
A46: 3 | B46: =IF($P$14=0,"",IF(LEN($B$14)=0,"Habilidade 3",""&$B$14)) | C46: =IF($P$14=0,"",$W$14) | D46: {=IF($P$14=0,"",IF(OR($C$14="Buff",$C$14="Debuff"),INDEX(Dados!$B$306:$B$312,$S$14)&" · "&INDEX(Dados!$C$306:$C$312,$S$14)&" · alvos: "&INDEX(Dados!$D$306:$D$312,$S$14),IF($C$14="Passiva",INDEX(Dados!$B$316:$B$322,$S$14)&" · não custa PH",IF(OR($C$14="Dano",$C$14="Cura"),"Dados da tabela 16.3 + Bônus do Atributo de Habilidade, uma vez","Escolha o Tipo"))))}
A47: 4 | B47: =IF($P$15=0,"",IF(LEN($B$15)=0,"Habilidade 4",""&$B$15)) | C47: =IF($P$15=0,"",$W$15) | D47: {=IF($P$15=0,"",IF(OR($C$15="Buff",$C$15="Debuff"),INDEX(Dados!$B$306:$B$312,$S$15)&" · "&INDEX(Dados!$C$306:$C$312,$S$15)&" · alvos: "&INDEX(Dados!$D$306:$D$312,$S$15),IF($C$15="Passiva",INDEX(Dados!$B$316:$B$322,$S$15)&" · não custa PH",IF(OR($C$15="Dano",$C$15="Cura"),"Dados da tabela 16.3 + Bônus do Atributo de Habilidade, uma vez","Escolha o Tipo"))))}
A48: 5 | B48: =IF($P$16=0,"",IF(LEN($B$16)=0,"Habilidade 5",""&$B$16)) | C48: =IF($P$16=0,"",$W$16) | D48: {=IF($P$16=0,"",IF(OR($C$16="Buff",$C$16="Debuff"),INDEX(Dados!$B$306:$B$312,$S$16)&" · "&INDEX(Dados!$C$306:$C$312,$S$16)&" · alvos: "&INDEX(Dados!$D$306:$D$312,$S$16),IF($C$16="Passiva",INDEX(Dados!$B$316:$B$322,$S$16)&" · não custa PH",IF(OR($C$16="Dano",$C$16="Cura"),"Dados da tabela 16.3 + Bônus do Atributo de Habilidade, uma vez","Escolha o Tipo"))))}
A49: 6 | B49: =IF($P$17=0,"",IF(LEN($B$17)=0,"Habilidade 6",""&$B$17)) | C49: =IF($P$17=0,"",$W$17) | D49: {=IF($P$17=0,"",IF(OR($C$17="Buff",$C$17="Debuff"),INDEX(Dados!$B$306:$B$312,$S$17)&" · "&INDEX(Dados!$C$306:$C$312,$S$17)&" · alvos: "&INDEX(Dados!$D$306:$D$312,$S$17),IF($C$17="Passiva",INDEX(Dados!$B$316:$B$322,$S$17)&" · não custa PH",IF(OR($C$17="Dano",$C$17="Cura"),"Dados da tabela 16.3 + Bônus do Atributo de Habilidade, uma vez","Escolha o Tipo"))))}
A50: 7 | B50: =IF($P$18=0,"",IF(LEN($B$18)=0,"Habilidade 7",""&$B$18)) | C50: =IF($P$18=0,"",$W$18) | D50: {=IF($P$18=0,"",IF(OR($C$18="Buff",$C$18="Debuff"),INDEX(Dados!$B$306:$B$312,$S$18)&" · "&INDEX(Dados!$C$306:$C$312,$S$18)&" · alvos: "&INDEX(Dados!$D$306:$D$312,$S$18),IF($C$18="Passiva",INDEX(Dados!$B$316:$B$322,$S$18)&" · não custa PH",IF(OR($C$18="Dano",$C$18="Cura"),"Dados da tabela 16.3 + Bônus do Atributo de Habilidade, uma vez","Escolha o Tipo"))))}
A51: 8 | B51: =IF($P$19=0,"",IF(LEN($B$19)=0,"Habilidade 8",""&$B$19)) | C51: =IF($P$19=0,"",$W$19) | D51: {=IF($P$19=0,"",IF(OR($C$19="Buff",$C$19="Debuff"),INDEX(Dados!$B$306:$B$312,$S$19)&" · "&INDEX(Dados!$C$306:$C$312,$S$19)&" · alvos: "&INDEX(Dados!$D$306:$D$312,$S$19),IF($C$19="Passiva",INDEX(Dados!$B$316:$B$322,$S$19)&" · não custa PH",IF(OR($C$19="Dano",$C$19="Cura"),"Dados da tabela 16.3 + Bônus do Atributo de Habilidade, uma vez","Escolha o Tipo"))))}
A53: Ultimate — 17 (100 de Energia, não gasta ação, 1 por Ciclo; potência pela faixa)
A54: Nome (diga em voz alta)
A55: A frase que você diz
A56: Tipo | L56: =IF($C$56="",IF($P$61=1,"Escolha o Tipo da Ultimate.",""),IF(OR($C$56="Dano",$C$56="Cura",$C$56="Buff",$C$56="Debuff",$C$56="Controle"),"","Tipo fora da lista (17.4)."))&IF(AND(LEN($C$58)>0,COUNTIF(Dados!$AK$6:$AK$7,$C$58)=0)," Resolução fora da lista.","")
A57: Em área?
A58: Resolução
A59: Efeito (o que ela faz)
A60: Ultimate | C60: Nível equivalente | D60: Dano ou cura | E60: Média | F60: Rolagem ou DT | G60: Custo (Energia) | H60: Redução de Tenacidade | I60: Alvos | J60: Dados da tabela | K60: Média dos dados | L60: Bônus fixo | P60: preenchida | Q60: nº tabela | R60: nº de dados | S60: face
A61: Números da Ultimate | C61: ='Criação'!$H$16 -> 2 | D61: =IF($R$61=0,"",IF($R$61<=0,""&$L$61,$R$61&"d"&$S$61&IF($L$61>0,"+"&$L$61,IF($L$61<0,""&$L$61,"")))) | E61: =IF($R$61=0,"",INT($R$61*($S$61+1)/2)+$L$61) | F61: =IF($C$58="Teste de Ataque",'Criação'!$C$57,IF($C$58="Teste de Resistência","DT "&'Criação'!$B$56,"")) | G61: =IF('Progressão'!$R$70="Ultimate com 80 de Energia",80,100) -> 100 | H61: {=INDEX(Dados!$K$326:$K$330,'Criação'!$B$14)} -> 5 | I61: =IF($C$57="Sim",IF($C$61>=6,4,3),1) -> 1 | J61: =IF($R$61=0,"",$R$61&"d"&$S$61) | K61: =IF($R$61=0,"",INT($R$61*($S$61+1)/2)) | L61: =IF(OR($C$56="Dano",$C$56="Cura"),'Criação'!$B$55+IF($C$56="Dano",Equipamento!$P$40+Equipamento!$F$31,0),0) -> 0 | P61: =IF(OR(LEN($C$54)>0,LEN($C$55)>0,LEN($C$56)>0,LEN($C$57)>0,LEN($C$58)>0,LEN($C$59)>0),1,0) -> 0 | Q61: {=IF($C$56="Dano",INDEX(Dados!$D$326:$D$330,'Criação'!$B$14),IF($C$56="Cura",INDEX(Dados!$H$326:$H$330,'Criação'!$B$14),0))} -> 0 | R61: =IF(AND($C$57="Sim",$Q$61>0),MAX(1,INT($Q$61/2)),$Q$61) -> 0 | S61: {=IF($C$56="Dano",INDEX(Dados!$E$326:$E$330,'Criação'!$B$14),IF($C$56="Cura",INDEX(Dados!$I$326:$I$330,'Criação'!$B$14),0))} -> 0
A62: Guia de 16.5 (efeito) | C62: {=IF(OR($C$56="Buff",$C$56="Debuff",$C$56="Controle"),"Nível equivalente "&$C$61&": "&INDEX(Dados!$B$306:$B$312,$C$61)&" · "&INDEX(Dados!$C$306:$C$312,$C$61),IF(OR($C$56="Dano",$C$56="Cura"),"Dados da linha da sua faixa (17.3) + Bônus do Atributo de Habilidade, uma vez","Escolha o Tipo"))} -> Escolha o Tipo
A63: A Ultimate sobe sozinha ao mudar de faixa (níveis 5, 9, 13 e 17). Ressonância II: efeito extra; Ressonância IV: pode custar 80 de Energia (26.7).

Sheet Caminho
A1: Caminho — Explorando Galáxias v1.1
A2: Legenda: | B2: Entrada (preencha) | C2: Calculada (automático) | D2: Aviso (texto em vermelho) | F2: Título de bloco | G2: Cabeçalho de coluna | H2: Rótulo da linha | I2: Linha alternada (outro tom) | J2: Não se aplica
A3: O seu Caminho, as Bênçãos adquiridas e o Memoespírito.
A5: Ficha do Caminho (escolha o Caminho na aba Criação, Passo 3)
A6: Caminho | B6: =IF('Criação'!$B$33="","Escolha na aba Criação",'Criação'!$B$33) -> Escolha na aba Criação | D6: Aeon | E6: ='Criação'!$B$34 | G6: Atributo de Habilidade usado | H6: ='Criação'!$D$54
A7: A ideia | B7: ='Criação'!$B$35
A8: N (PV) | B8: ='Criação'!$B$36 -> 0 | C8: Bônus de Velocidade | D8: ='Criação'!$B$37 -> 0 | E8: Perícias do Caminho | G8: ='Criação'!$B$38&IF('Criação'!$B$33="",""," · ")&'Criação'!$D$38&IF('Criação'!$B$33="",""," · ")&'Criação'!$F$38
A9: Recurso próprio | B9: ='Criação'!$B$40
A11: Recurso próprio do Caminho (capítulos 07 a 15)
A12: =IF('Criação'!$B$33="A Preservação","Teto de Barreira (15.2) = 3 × Eficiência = "&3*'Criação'!$C$14,IF('Criação'!$B$33="A Caça","Marcação de Presa (14.2): Ação Complementar, 1 inimigo por vez, +1 dado base contra ele.",IF('Criação'!$B$33="A Euforia","Tabela do Riso (13.2): role 1d6 quando uma Bênção mandar.",IF('Criação'!$B$33="A Erudição","Acúmulos de Cálculo (12.2): máximo "&IF((COUNTIF($I$27:$I$36,"Teto Rompido")>0),7,5)&" por combate",IF('Criação'!$B$33="A Recordação","Memoespírito (11.3 a 11.5): monte a ficha dele no bloco abaixo.",IF('Criação'!$B$33="A Abundância","Nenhum recurso além dos acúmulos das Bênçãos (10.1): Florescimento (até 5).",IF('Criação'!$B$33="A Harmonia","Nenhum recurso além dos acúmulos das Bênçãos (9.1): Eco da Vitória (até 3).",IF('Criação'!$B$33="A Inexistência","Nenhum recurso além dos acúmulos das Bênçãos (8.1): Marca do Vazio (até 3) e Corrupção (até 5).",IF('Criação'!$B$33="A Destruição","PV como moeda (7.2): ativação ou acúmulo de Bênção de custo = 2 × nível = "&2*'Criação'!$A$14&" PV","Escolha o Caminho na aba Criação (Passo 3)."))))))))) -> Escolha o Caminho na aba Criação (Passo 3).
A13: =IF('Criação'!$B$33="A Preservação","Barreira não acumula com outro PV temporário: fica o maior valor.",IF('Criação'!$B$33="A Caça","A marca dura até o fim do combate e migra de graça quando o alvo é derrotado.",IF('Criação'!$B$33="A Euforia","1: Piada interna — +1 dado base no seu próximo ataque neste Ciclo",IF('Criação'!$B$33="A Erudição","Ganha 1 acúmulo por inimigo atingido por um mesmo ataque, Habilidade ou Ultimate sua.",IF('Criação'!$B$33="A Recordação","Invocar: Ação Complementar + 1 PH. A Energia das ações dele vale metade para você.",IF('Criação'!$B$33="A Abundância","Use a frequência e os acúmulos das Bênçãos adquiridas, nos slots abaixo.",IF('Criação'!$B$33="A Harmonia","Use a frequência e os acúmulos das Bênçãos adquiridas, nos slots abaixo.",IF('Criação'!$B$33="A Inexistência","Use a frequência e os acúmulos das Bênçãos adquiridas, nos slots abaixo.",IF('Criação'!$B$33="A Destruição","Dado base comprado no Avatar = 5 × nível = "&(5*'Criação'!$A$14)&" PV","")))))))))
A14: =IF('Criação'!$B$33="A Preservação","Cura não repõe Barreira. O dano passa pela RD antes da Barreira.",IF('Criação'!$B$33="A Caça","Faixa de crítico: "&IF((COUNTIF($I$27:$I$36,"Olho de Lan")>0),"19-20 (Olho de Lan)","20"),IF('Criação'!$B$33="A Euforia","2: Tropeço cósmico — o inimigo mais próximo é Atrasado em 1 casa (capítulo 19, respeita a Firmeza de Elite e Boss)",IF('Criação'!$B$33="A Erudição","Gastar 1 acúmulo: +1 alvo para a ação em curso. Gastar 2: +1 dado base no dano.",IF('Criação'!$B$33="A Destruição","Você escolhe pagar e não pode pagar se o custo for igual ou maior que os seus PV atuais.","")))))
A15: =IF('Criação'!$B$33="A Euforia","3: Riso contagioso — um aliado a até Distância Média ganha +2 na próxima rolagem dele",IF('Criação'!$B$33="A Erudição","Gastar não consome ação. Os acúmulos zeram no fim do combate.",IF('Criação'!$B$33="A Destruição","PV gastos assim não são dano: não geram Energia, não passam por RD e contam para as Marcas.","")))
A16: =IF('Criação'!$B$33="A Euforia","4: Troca de lugar — você e um aliado trocam de casa na Fila; nenhum dos dois pode já ter agido neste Ciclo","")
A17: =IF('Criação'!$B$33="A Euforia","5: Sorte do tolo — você ganha Vantagem na sua próxima rolagem neste Ciclo","")
A18: =IF('Criação'!$B$33="A Euforia","6: Aha! aprova — o grupo recupera 1 PH (uma vez por Ciclo)","")
A20: Bênçãos com número na ficha
A21: Bênção | C21: Custo em PV | D21: Bônus de dano | E21: Bônus ferido | F21: Ferido com PV até | G21: Como funciona
A22: Pacto da Ruína (7.3, nº 1) | C22: =IF((COUNTIF($I$27:$I$36,"Pacto da Ruína")>0),2*'Criação'!$A$14,"") | D22: =IF((COUNTIF($I$27:$I$36,"Pacto da Ruína")>0),'Criação'!$C$14,"") | E22: =IF((COUNTIF($I$27:$I$36,"Pacto da Ruína")>0),2*'Criação'!$C$14,"") | F22: =IF((COUNTIF($I$27:$I$36,"Pacto da Ruína")>0),INT('Criação'!$D$95/2),"") | G22: =IF((COUNTIF($I$27:$I$36,"Pacto da Ruína")>0),"Uma vez por turno: pague o custo e some o bônus ao dano; dobra com metade dos PV ou menos","Só com a Bênção Pacto da Ruína") -> Só com a Bênção Pacto da Ruína
A24: Bênçãos adquiridas — uma por nível ímpar (06.7); o Tier I cabe em qualquer slot
A25: Possuídas / permitidas no nível | B25: =SUMPRODUCT((LEN($I$27:$I$36)>0)*1) -> 0 | C25: ="de "&'Criação'!$L$14&" permitidas no nível "&'Criação'!$A$14 -> de 1 permitidas no nível 1
A26: Slot | B26: Nível do slot | C26: Bênção (preencha) | D26: Tier | E26: Requisito (nível) | F26: Liberado? | G26: Em uma linha | H26: Frequência | I26: Conta na ficha | K26: Aviso | N26: Lista auxiliar: Bênçãos do Caminho
A27: Slot 1 | B27: 1 | D27: {=IF($C$27="","",IFERROR(INDEX(Dados!$D$119:$D$226,MATCH($C$27,Dados!$C$119:$C$226,0)),"—"))} | E27: {=IF($C$27="","",IFERROR(INDEX(Dados!$E$119:$E$226,MATCH($C$27,Dados!$C$119:$C$226,0)),""))} | F27: =IF('Criação'!$A$14>=1,"Sim","Não (nível 1)") -> Sim | G27: {=IF($C$27="","",IFERROR(INDEX(Dados!$F$119:$F$226,MATCH($C$27,Dados!$C$119:$C$226,0)),"Fora do catálogo dos capítulos 07 a 15"))} | H27: {=IF($C$27="","",IFERROR(INDEX(Dados!$G$119:$G$226,MATCH($C$27,Dados!$C$119:$C$226,0)),""))} | I27: =IF(AND($C$27<>"",'Criação'!$A$14>=1),$C$27,"") | K27: {=IF($C$27="","",IF('Criação'!$A$14<1,"Slot ainda não liberado (nível 1). ","")&IF(ISERROR(MATCH($C$27,Dados!$C$119:$C$226,0)),"Bênção fora do catálogo dos capítulos 07 a 15. ",IF(INDEX(Dados!$A$119:$A$226,MATCH($C$27,Dados!$C$119:$C$226,0))<>'Criação'!$B$33,"Bênção de outro Caminho ("&INDEX(Dados!$A$119:$A$226,MATCH($C$27,Dados!$C$119:$C$226,0))&"). ",IF(INDEX(Dados!$E$119:$E$226,MATCH($C$27,Dados!$C$119:$C$226,0))>1,"Tier "&INDEX(Dados!$D$119:$D$226,MATCH($C$27,Dados!$C$119:$C$226,0))&" exige slot de nível "&INDEX(Dados!$E$119:$E$226,MATCH($C$27,Dados!$C$119:$C$226,0))&" ou mais. ","")))&IF(COUNTIF($C$27:$C$36,$C$27)>1,"Bênção repetida.",""))} | N27: {=IF('Criação'!$B$33="","",IFERROR(INDEX(Dados!$C$119:$C$226,MATCH('Criação'!$B$33,Dados!$A$119:$A$226,0)+0),""))}
A28: Slot 2 | B28: 3 | D28: {=IF($C$28="","",IFERROR(INDEX(Dados!$D$119:$D$226,MATCH($C$28,Dados!$C$119:$C$226,0)),"—"))} | E28: {=IF($C$28="","",IFERROR(INDEX(Dados!$E$119:$E$226,MATCH($C$28,Dados!$C$119:$C$226,0)),""))} | F28: =IF('Criação'!$A$14>=3,"Sim","Não (nível 3)") -> Não (nível 3) | G28: {=IF($C$28="","",IFERROR(INDEX(Dados!$F$119:$F$226,MATCH($C$28,Dados!$C$119:$C$226,0)),"Fora do catálogo dos capítulos 07 a 15"))} | H28: {=IF($C$28="","",IFERROR(INDEX(Dados!$G$119:$G$226,MATCH($C$28,Dados!$C$119:$C$226,0)),""))} | I28: =IF(AND($C$28<>"",'Criação'!$A$14>=3),$C$28,"") | K28: {=IF($C$28="","",IF('Criação'!$A$14<3,"Slot ainda não liberado (nível 3). ","")&IF(ISERROR(MATCH($C$28,Dados!$C$119:$C$226,0)),"Bênção fora do catálogo dos capítulos 07 a 15. ",IF(INDEX(Dados!$A$119:$A$226,MATCH($C$28,Dados!$C$119:$C$226,0))<>'Criação'!$B$33,"Bênção de outro Caminho ("&INDEX(Dados!$A$119:$A$226,MATCH($C$28,Dados!$C$119:$C$226,0))&"). ",IF(INDEX(Dados!$E$119:$E$226,MATCH($C$28,Dados!$C$119:$C$226,0))>3,"Tier "&INDEX(Dados!$D$119:$D$226,MATCH($C$28,Dados!$C$119:$C$226,0))&" exige slot de nível "&INDEX(Dados!$E$119:$E$226,MATCH($C$28,Dados!$C$119:$C$226,0))&" ou mais. ","")))&IF(COUNTIF($C$27:$C$36,$C$28)>1,"Bênção repetida.",""))} | N28: {=IF('Criação'!$B$33="","",IFERROR(INDEX(Dados!$C$119:$C$226,MATCH('Criação'!$B$33,Dados!$A$119:$A$226,0)+1),""))}
A29: Slot 3 | B29: 5 | D29: {=IF($C$29="","",IFERROR(INDEX(Dados!$D$119:$D$226,MATCH($C$29,Dados!$C$119:$C$226,0)),"—"))} | E29: {=IF($C$29="","",IFERROR(INDEX(Dados!$E$119:$E$226,MATCH($C$29,Dados!$C$119:$C$226,0)),""))} | F29: =IF('Criação'!$A$14>=5,"Sim","Não (nível 5)") -> Não (nível 5) | G29: {=IF($C$29="","",IFERROR(INDEX(Dados!$F$119:$F$226,MATCH($C$29,Dados!$C$119:$C$226,0)),"Fora do catálogo dos capítulos 07 a 15"))} | H29: {=IF($C$29="","",IFERROR(INDEX(Dados!$G$119:$G$226,MATCH($C$29,Dados!$C$119:$C$226,0)),""))} | I29: =IF(AND($C$29<>"",'Criação'!$A$14>=5),$C$29,"") | K29: {=IF($C$29="","",IF('Criação'!$A$14<5,"Slot ainda não liberado (nível 5). ","")&IF(ISERROR(MATCH($C$29,Dados!$C$119:$C$226,0)),"Bênção fora do catálogo dos capítulos 07 a 15. ",IF(INDEX(Dados!$A$119:$A$226,MATCH($C$29,Dados!$C$119:$C$226,0))<>'Criação'!$B$33,"Bênção de outro Caminho ("&INDEX(Dados!$A$119:$A$226,MATCH($C$29,Dados!$C$119:$C$226,0))&"). ",IF(INDEX(Dados!$E$119:$E$226,MATCH($C$29,Dados!$C$119:$C$226,0))>5,"Tier "&INDEX(Dados!$D$119:$D$226,MATCH($C$29,Dados!$C$119:$C$226,0))&" exige slot de nível "&INDEX(Dados!$E$119:$E$226,MATCH($C$29,Dados!$C$119:$C$226,0))&" ou mais. ","")))&IF(COUNTIF($C$27:$C$36,$C$29)>1,"Bênção repetida.",""))} | N29: {=IF('Criação'!$B$33="","",IFERROR(INDEX(Dados!$C$119:$C$226,MATCH('Criação'!$B$33,Dados!$A$119:$A$226,0)+2),""))}
A30: Slot 4 | B30: 7 | D30: {=IF($C$30="","",IFERROR(INDEX(Dados!$D$119:$D$226,MATCH($C$30,Dados!$C$119:$C$226,0)),"—"))} | E30: {=IF($C$30="","",IFERROR(INDEX(Dados!$E$119:$E$226,MATCH($C$30,Dados!$C$119:$C$226,0)),""))} | F30: =IF('Criação'!$A$14>=7,"Sim","Não (nível 7)") -> Não (nível 7) | G30: {=IF($C$30="","",IFERROR(INDEX(Dados!$F$119:$F$226,MATCH($C$30,Dados!$C$119:$C$226,0)),"Fora do catálogo dos capítulos 07 a 15"))} | H30: {=IF($C$30="","",IFERROR(INDEX(Dados!$G$119:$G$226,MATCH($C$30,Dados!$C$119:$C$226,0)),""))} | I30: =IF(AND($C$30<>"",'Criação'!$A$14>=7),$C$30,"") | K30: {=IF($C$30="","",IF('Criação'!$A$14<7,"Slot ainda não liberado (nível 7). ","")&IF(ISERROR(MATCH($C$30,Dados!$C$119:$C$226,0)),"Bênção fora do catálogo dos capítulos 07 a 15. ",IF(INDEX(Dados!$A$119:$A$226,MATCH($C$30,Dados!$C$119:$C$226,0))<>'Criação'!$B$33,"Bênção de outro Caminho ("&INDEX(Dados!$A$119:$A$226,MATCH($C$30,Dados!$C$119:$C$226,0))&"). ",IF(INDEX(Dados!$E$119:$E$226,MATCH($C$30,Dados!$C$119:$C$226,0))>7,"Tier "&INDEX(Dados!$D$119:$D$226,MATCH($C$30,Dados!$C$119:$C$226,0))&" exige slot de nível "&INDEX(Dados!$E$119:$E$226,MATCH($C$30,Dados!$C$119:$C$226,0))&" ou mais. ","")))&IF(COUNTIF($C$27:$C$36,$C$30)>1,"Bênção repetida.",""))} | N30: {=IF('Criação'!$B$33="","",IFERROR(INDEX(Dados!$C$119:$C$226,MATCH('Criação'!$B$33,Dados!$A$119:$A$226,0)+3),""))}
A31: Slot 5 | B31: 9 | D31: {=IF($C$31="","",IFERROR(INDEX(Dados!$D$119:$D$226,MATCH($C$31,Dados!$C$119:$C$226,0)),"—"))} | E31: {=IF($C$31="","",IFERROR(INDEX(Dados!$E$119:$E$226,MATCH($C$31,Dados!$C$119:$C$226,0)),""))} | F31: =IF('Criação'!$A$14>=9,"Sim","Não (nível 9)") -> Não (nível 9) | G31: {=IF($C$31="","",IFERROR(INDEX(Dados!$F$119:$F$226,MATCH($C$31,Dados!$C$119:$C$226,0)),"Fora do catálogo dos capítulos 07 a 15"))} | H31: {=IF($C$31="","",IFERROR(INDEX(Dados!$G$119:$G$226,MATCH($C$31,Dados!$C$119:$C$226,0)),""))} | I31: =IF(AND($C$31<>"",'Criação'!$A$14>=9),$C$31,"") | K31: {=IF($C$31="","",IF('Criação'!$A$14<9,"Slot ainda não liberado (nível 9). ","")&IF(ISERROR(MATCH($C$31,Dados!$C$119:$C$226,0)),"Bênção fora do catálogo dos capítulos 07 a 15. ",IF(INDEX(Dados!$A$119:$A$226,MATCH($C$31,Dados!$C$119:$C$226,0))<>'Criação'!$B$33,"Bênção de outro Caminho ("&INDEX(Dados!$A$119:$A$226,MATCH($C$31,Dados!$C$119:$C$226,0))&"). ",IF(INDEX(Dados!$E$119:$E$226,MATCH($C$31,Dados!$C$119:$C$226,0))>9,"Tier "&INDEX(Dados!$D$119:$D$226,MATCH($C$31,Dados!$C$119:$C$226,0))&" exige slot de nível "&INDEX(Dados!$E$119:$E$226,MATCH($C$31,Dados!$C$119:$C$226,0))&" ou mais. ","")))&IF(COUNTIF($C$27:$C$36,$C$31)>1,"Bênção repetida.",""))} | N31: {=IF('Criação'!$B$33="","",IFERROR(INDEX(Dados!$C$119:$C$226,MATCH('Criação'!$B$33,Dados!$A$119:$A$226,0)+4),""))}
A32: Slot 6 | B32: 11 | D32: {=IF($C$32="","",IFERROR(INDEX(Dados!$D$119:$D$226,MATCH($C$32,Dados!$C$119:$C$226,0)),"—"))} | E32: {=IF($C$32="","",IFERROR(INDEX(Dados!$E$119:$E$226,MATCH($C$32,Dados!$C$119:$C$226,0)),""))} | F32: =IF('Criação'!$A$14>=11,"Sim","Não (nível 11)") -> Não (nível 11) | G32: {=IF($C$32="","",IFERROR(INDEX(Dados!$F$119:$F$226,MATCH($C$32,Dados!$C$119:$C$226,0)),"Fora do catálogo dos capítulos 07 a 15"))} | H32: {=IF($C$32="","",IFERROR(INDEX(Dados!$G$119:$G$226,MATCH($C$32,Dados!$C$119:$C$226,0)),""))} | I32: =IF(AND($C$32<>"",'Criação'!$A$14>=11),$C$32,"") | K32: {=IF($C$32="","",IF('Criação'!$A$14<11,"Slot ainda não liberado (nível 11). ","")&IF(ISERROR(MATCH($C$32,Dados!$C$119:$C$226,0)),"Bênção fora do catálogo dos capítulos 07 a 15. ",IF(INDEX(Dados!$A$119:$A$226,MATCH($C$32,Dados!$C$119:$C$226,0))<>'Criação'!$B$33,"Bênção de outro Caminho ("&INDEX(Dados!$A$119:$A$226,MATCH($C$32,Dados!$C$119:$C$226,0))&"). ",IF(INDEX(Dados!$E$119:$E$226,MATCH($C$32,Dados!$C$119:$C$226,0))>11,"Tier "&INDEX(Dados!$D$119:$D$226,MATCH($C$32,Dados!$C$119:$C$226,0))&" exige slot de nível "&INDEX(Dados!$E$119:$E$226,MATCH($C$32,Dados!$C$119:$C$226,0))&" ou mais. ","")))&IF(COUNTIF($C$27:$C$36,$C$32)>1,"Bênção repetida.",""))} | N32: {=IF('Criação'!$B$33="","",IFERROR(INDEX(Dados!$C$119:$C$226,MATCH('Criação'!$B$33,Dados!$A$119:$A$226,0)+5),""))}
A33: Slot 7 | B33: 13 | D33: {=IF($C$33="","",IFERROR(INDEX(Dados!$D$119:$D$226,MATCH($C$33,Dados!$C$119:$C$226,0)),"—"))} | E33: {=IF($C$33="","",IFERROR(INDEX(Dados!$E$119:$E$226,MATCH($C$33,Dados!$C$119:$C$226,0)),""))} | F33: =IF('Criação'!$A$14>=13,"Sim","Não (nível 13)") -> Não (nível 13) | G33: {=IF($C$33="","",IFERROR(INDEX(Dados!$F$119:$F$226,MATCH($C$33,Dados!$C$119:$C$226,0)),"Fora do catálogo dos capítulos 07 a 15"))} | H33: {=IF($C$33="","",IFERROR(INDEX(Dados!$G$119:$G$226,MATCH($C$33,Dados!$C$119:$C$226,0)),""))} | I33: =IF(AND($C$33<>"",'Criação'!$A$14>=13),$C$33,"") | K33: {=IF($C$33="","",IF('Criação'!$A$14<13,"Slot ainda não liberado (nível 13). ","")&IF(ISERROR(MATCH($C$33,Dados!$C$119:$C$226,0)),"Bênção fora do catálogo dos capítulos 07 a 15. ",IF(INDEX(Dados!$A$119:$A$226,MATCH($C$33,Dados!$C$119:$C$226,0))<>'Criação'!$B$33,"Bênção de outro Caminho ("&INDEX(Dados!$A$119:$A$226,MATCH($C$33,Dados!$C$119:$C$226,0))&"). ",IF(INDEX(Dados!$E$119:$E$226,MATCH($C$33,Dados!$C$119:$C$226,0))>13,"Tier "&INDEX(Dados!$D$119:$D$226,MATCH($C$33,Dados!$C$119:$C$226,0))&" exige slot de nível "&INDEX(Dados!$E$119:$E$226,MATCH($C$33,Dados!$C$119:$C$226,0))&" ou mais. ","")))&IF(COUNTIF($C$27:$C$36,$C$33)>1,"Bênção repetida.",""))} | N33: {=IF('Criação'!$B$33="","",IFERROR(INDEX(Dados!$C$119:$C$226,MATCH('Criação'!$B$33,Dados!$A$119:$A$226,0)+6),""))}
A34: Slot 8 | B34: 15 | D34: {=IF($C$34="","",IFERROR(INDEX(Dados!$D$119:$D$226,MATCH($C$34,Dados!$C$119:$C$226,0)),"—"))} | E34: {=IF($C$34="","",IFERROR(INDEX(Dados!$E$119:$E$226,MATCH($C$34,Dados!$C$119:$C$226,0)),""))} | F34: =IF('Criação'!$A$14>=15,"Sim","Não (nível 15)") -> Não (nível 15) | G34: {=IF($C$34="","",IFERROR(INDEX(Dados!$F$119:$F$226,MATCH($C$34,Dados!$C$119:$C$226,0)),"Fora do catálogo dos capítulos 07 a 15"))} | H34: {=IF($C$34="","",IFERROR(INDEX(Dados!$G$119:$G$226,MATCH($C$34,Dados!$C$119:$C$226,0)),""))} | I34: =IF(AND($C$34<>"",'Criação'!$A$14>=15),$C$34,"") | K34: {=IF($C$34="","",IF('Criação'!$A$14<15,"Slot ainda não liberado (nível 15). ","")&IF(ISERROR(MATCH($C$34,Dados!$C$119:$C$226,0)),"Bênção fora do catálogo dos capítulos 07 a 15. ",IF(INDEX(Dados!$A$119:$A$226,MATCH($C$34,Dados!$C$119:$C$226,0))<>'Criação'!$B$33,"Bênção de outro Caminho ("&INDEX(Dados!$A$119:$A$226,MATCH($C$34,Dados!$C$119:$C$226,0))&"). ",IF(INDEX(Dados!$E$119:$E$226,MATCH($C$34,Dados!$C$119:$C$226,0))>15,"Tier "&INDEX(Dados!$D$119:$D$226,MATCH($C$34,Dados!$C$119:$C$226,0))&" exige slot de nível "&INDEX(Dados!$E$119:$E$226,MATCH($C$34,Dados!$C$119:$C$226,0))&" ou mais. ","")))&IF(COUNTIF($C$27:$C$36,$C$34)>1,"Bênção repetida.",""))} | N34: {=IF('Criação'!$B$33="","",IFERROR(INDEX(Dados!$C$119:$C$226,MATCH('Criação'!$B$33,Dados!$A$119:$A$226,0)+7),""))}
A35: Slot 9 | B35: 17 | D35: {=IF($C$35="","",IFERROR(INDEX(Dados!$D$119:$D$226,MATCH($C$35,Dados!$C$119:$C$226,0)),"—"))} | E35: {=IF($C$35="","",IFERROR(INDEX(Dados!$E$119:$E$226,MATCH($C$35,Dados!$C$119:$C$226,0)),""))} | F35: =IF('Criação'!$A$14>=17,"Sim","Não (nível 17)") -> Não (nível 17) | G35: {=IF($C$35="","",IFERROR(INDEX(Dados!$F$119:$F$226,MATCH($C$35,Dados!$C$119:$C$226,0)),"Fora do catálogo dos capítulos 07 a 15"))} | H35: {=IF($C$35="","",IFERROR(INDEX(Dados!$G$119:$G$226,MATCH($C$35,Dados!$C$119:$C$226,0)),""))} | I35: =IF(AND($C$35<>"",'Criação'!$A$14>=17),$C$35,"") | K35: {=IF($C$35="","",IF('Criação'!$A$14<17,"Slot ainda não liberado (nível 17). ","")&IF(ISERROR(MATCH($C$35,Dados!$C$119:$C$226,0)),"Bênção fora do catálogo dos capítulos 07 a 15. ",IF(INDEX(Dados!$A$119:$A$226,MATCH($C$35,Dados!$C$119:$C$226,0))<>'Criação'!$B$33,"Bênção de outro Caminho ("&INDEX(Dados!$A$119:$A$226,MATCH($C$35,Dados!$C$119:$C$226,0))&"). ",IF(INDEX(Dados!$E$119:$E$226,MATCH($C$35,Dados!$C$119:$C$226,0))>17,"Tier "&INDEX(Dados!$D$119:$D$226,MATCH($C$35,Dados!$C$119:$C$226,0))&" exige slot de nível "&INDEX(Dados!$E$119:$E$226,MATCH($C$35,Dados!$C$119:$C$226,0))&" ou mais. ","")))&IF(COUNTIF($C$27:$C$36,$C$35)>1,"Bênção repetida.",""))} | N35: {=IF('Criação'!$B$33="","",IFERROR(INDEX(Dados!$C$119:$C$226,MATCH('Criação'!$B$33,Dados!$A$119:$A$226,0)+8),""))}
A36: Slot 10 | B36: 19 | D36: {=IF($C$36="","",IFERROR(INDEX(Dados!$D$119:$D$226,MATCH($C$36,Dados!$C$119:$C$226,0)),"—"))} | E36: {=IF($C$36="","",IFERROR(INDEX(Dados!$E$119:$E$226,MATCH($C$36,Dados!$C$119:$C$226,0)),""))} | F36: =IF('Criação'!$A$14>=19,"Sim","Não (nível 19)") -> Não (nível 19) | G36: {=IF($C$36="","",IFERROR(INDEX(Dados!$F$119:$F$226,MATCH($C$36,Dados!$C$119:$C$226,0)),"Fora do catálogo dos capítulos 07 a 15"))} | H36: {=IF($C$36="","",IFERROR(INDEX(Dados!$G$119:$G$226,MATCH($C$36,Dados!$C$119:$C$226,0)),""))} | I36: =IF(AND($C$36<>"",'Criação'!$A$14>=19),$C$36,"") | K36: {=IF($C$36="","",IF('Criação'!$A$14<19,"Slot ainda não liberado (nível 19). ","")&IF(ISERROR(MATCH($C$36,Dados!$C$119:$C$226,0)),"Bênção fora do catálogo dos capítulos 07 a 15. ",IF(INDEX(Dados!$A$119:$A$226,MATCH($C$36,Dados!$C$119:$C$226,0))<>'Criação'!$B$33,"Bênção de outro Caminho ("&INDEX(Dados!$A$119:$A$226,MATCH($C$36,Dados!$C$119:$C$226,0))&"). ",IF(INDEX(Dados!$E$119:$E$226,MATCH($C$36,Dados!$C$119:$C$226,0))>19,"Tier "&INDEX(Dados!$D$119:$D$226,MATCH($C$36,Dados!$C$119:$C$226,0))&" exige slot de nível "&INDEX(Dados!$E$119:$E$226,MATCH($C$36,Dados!$C$119:$C$226,0))&" ou mais. ","")))&IF(COUNTIF($C$27:$C$36,$C$36)>1,"Bênção repetida.",""))} | N36: {=IF('Criação'!$B$33="","",IFERROR(INDEX(Dados!$C$119:$C$226,MATCH('Criação'!$B$33,Dados!$A$119:$A$226,0)+9),""))}
N37: {=IF('Criação'!$B$33="","",IFERROR(INDEX(Dados!$C$119:$C$226,MATCH('Criação'!$B$33,Dados!$A$119:$A$226,0)+10),""))}
A38: Catálogo das 12 Bênçãos do seu Caminho | N38: {=IF('Criação'!$B$33="","",IFERROR(INDEX(Dados!$C$119:$C$226,MATCH('Criação'!$B$33,Dados!$A$119:$A$226,0)+11),""))}
A39: Nº | C39: Bênção | D39: Tier | E39: Requisito (nível) | F39: Pode escolher agora? | G39: Em uma linha | H39: Frequência
A40: 1 | C40: =$N$27 | D40: {=IF($N$27="","",IFERROR(INDEX(Dados!$D$119:$D$226,MATCH($N$27,Dados!$C$119:$C$226,0)),""))} | E40: {=IF($N$27="","",IFERROR(INDEX(Dados!$E$119:$E$226,MATCH($N$27,Dados!$C$119:$C$226,0)),""))} | F40: =IF($N$27="","",IF(COUNTIF($C$27:$C$36,$N$27)>0,"Já escolhida",IF('Criação'!$A$14>=$E$40,"Sim","A partir do nível "&$E$40))) | G40: {=IF($N$27="","",IFERROR(INDEX(Dados!$F$119:$F$226,MATCH($N$27,Dados!$C$119:$C$226,0)),""))} | H40: {=IF($N$27="","",IFERROR(INDEX(Dados!$G$119:$G$226,MATCH($N$27,Dados!$C$119:$C$226,0)),""))}
A41: 2 | C41: =$N$28 | D41: {=IF($N$28="","",IFERROR(INDEX(Dados!$D$119:$D$226,MATCH($N$28,Dados!$C$119:$C$226,0)),""))} | E41: {=IF($N$28="","",IFERROR(INDEX(Dados!$E$119:$E$226,MATCH($N$28,Dados!$C$119:$C$226,0)),""))} | F41: =IF($N$28="","",IF(COUNTIF($C$27:$C$36,$N$28)>0,"Já escolhida",IF('Criação'!$A$14>=$E$41,"Sim","A partir do nível "&$E$41))) | G41: {=IF($N$28="","",IFERROR(INDEX(Dados!$F$119:$F$226,MATCH($N$28,Dados!$C$119:$C$226,0)),""))} | H41: {=IF($N$28="","",IFERROR(INDEX(Dados!$G$119:$G$226,MATCH($N$28,Dados!$C$119:$C$226,0)),""))}
A42: 3 | C42: =$N$29 | D42: {=IF($N$29="","",IFERROR(INDEX(Dados!$D$119:$D$226,MATCH($N$29,Dados!$C$119:$C$226,0)),""))} | E42: {=IF($N$29="","",IFERROR(INDEX(Dados!$E$119:$E$226,MATCH($N$29,Dados!$C$119:$C$226,0)),""))} | F42: =IF($N$29="","",IF(COUNTIF($C$27:$C$36,$N$29)>0,"Já escolhida",IF('Criação'!$A$14>=$E$42,"Sim","A partir do nível "&$E$42))) | G42: {=IF($N$29="","",IFERROR(INDEX(Dados!$F$119:$F$226,MATCH($N$29,Dados!$C$119:$C$226,0)),""))} | H42: {=IF($N$29="","",IFERROR(INDEX(Dados!$G$119:$G$226,MATCH($N$29,Dados!$C$119:$C$226,0)),""))}
A43: 4 | C43: =$N$30 | D43: {=IF($N$30="","",IFERROR(INDEX(Dados!$D$119:$D$226,MATCH($N$30,Dados!$C$119:$C$226,0)),""))} | E43: {=IF($N$30="","",IFERROR(INDEX(Dados!$E$119:$E$226,MATCH($N$30,Dados!$C$119:$C$226,0)),""))} | F43: =IF($N$30="","",IF(COUNTIF($C$27:$C$36,$N$30)>0,"Já escolhida",IF('Criação'!$A$14>=$E$43,"Sim","A partir do nível "&$E$43))) | G43: {=IF($N$30="","",IFERROR(INDEX(Dados!$F$119:$F$226,MATCH($N$30,Dados!$C$119:$C$226,0)),""))} | H43: {=IF($N$30="","",IFERROR(INDEX(Dados!$G$119:$G$226,MATCH($N$30,Dados!$C$119:$C$226,0)),""))}
A44: 5 | C44: =$N$31 | D44: {=IF($N$31="","",IFERROR(INDEX(Dados!$D$119:$D$226,MATCH($N$31,Dados!$C$119:$C$226,0)),""))} | E44: {=IF($N$31="","",IFERROR(INDEX(Dados!$E$119:$E$226,MATCH($N$31,Dados!$C$119:$C$226,0)),""))} | F44: =IF($N$31="","",IF(COUNTIF($C$27:$C$36,$N$31)>0,"Já escolhida",IF('Criação'!$A$14>=$E$44,"Sim","A partir do nível "&$E$44))) | G44: {=IF($N$31="","",IFERROR(INDEX(Dados!$F$119:$F$226,MATCH($N$31,Dados!$C$119:$C$226,0)),""))} | H44: {=IF($N$31="","",IFERROR(INDEX(Dados!$G$119:$G$226,MATCH($N$31,Dados!$C$119:$C$226,0)),""))}
A45: 6 | C45: =$N$32 | D45: {=IF($N$32="","",IFERROR(INDEX(Dados!$D$119:$D$226,MATCH($N$32,Dados!$C$119:$C$226,0)),""))} | E45: {=IF($N$32="","",IFERROR(INDEX(Dados!$E$119:$E$226,MATCH($N$32,Dados!$C$119:$C$226,0)),""))} | F45: =IF($N$32="","",IF(COUNTIF($C$27:$C$36,$N$32)>0,"Já escolhida",IF('Criação'!$A$14>=$E$45,"Sim","A partir do nível "&$E$45))) | G45: {=IF($N$32="","",IFERROR(INDEX(Dados!$F$119:$F$226,MATCH($N$32,Dados!$C$119:$C$226,0)),""))} | H45: {=IF($N$32="","",IFERROR(INDEX(Dados!$G$119:$G$226,MATCH($N$32,Dados!$C$119:$C$226,0)),""))}
A46: 7 | C46: =$N$33 | D46: {=IF($N$33="","",IFERROR(INDEX(Dados!$D$119:$D$226,MATCH($N$33,Dados!$C$119:$C$226,0)),""))} | E46: {=IF($N$33="","",IFERROR(INDEX(Dados!$E$119:$E$226,MATCH($N$33,Dados!$C$119:$C$226,0)),""))} | F46: =IF($N$33="","",IF(COUNTIF($C$27:$C$36,$N$33)>0,"Já escolhida",IF('Criação'!$A$14>=$E$46,"Sim","A partir do nível "&$E$46))) | G46: {=IF($N$33="","",IFERROR(INDEX(Dados!$F$119:$F$226,MATCH($N$33,Dados!$C$119:$C$226,0)),""))} | H46: {=IF($N$33="","",IFERROR(INDEX(Dados!$G$119:$G$226,MATCH($N$33,Dados!$C$119:$C$226,0)),""))}
A47: 8 | C47: =$N$34 | D47: {=IF($N$34="","",IFERROR(INDEX(Dados!$D$119:$D$226,MATCH($N$34,Dados!$C$119:$C$226,0)),""))} | E47: {=IF($N$34="","",IFERROR(INDEX(Dados!$E$119:$E$226,MATCH($N$34,Dados!$C$119:$C$226,0)),""))} | F47: =IF($N$34="","",IF(COUNTIF($C$27:$C$36,$N$34)>0,"Já escolhida",IF('Criação'!$A$14>=$E$47,"Sim","A partir do nível "&$E$47))) | G47: {=IF($N$34="","",IFERROR(INDEX(Dados!$F$119:$F$226,MATCH($N$34,Dados!$C$119:$C$226,0)),""))} | H47: {=IF($N$34="","",IFERROR(INDEX(Dados!$G$119:$G$226,MATCH($N$34,Dados!$C$119:$C$226,0)),""))}
A48: 9 | C48: =$N$35 | D48: {=IF($N$35="","",IFERROR(INDEX(Dados!$D$119:$D$226,MATCH($N$35,Dados!$C$119:$C$226,0)),""))} | E48: {=IF($N$35="","",IFERROR(INDEX(Dados!$E$119:$E$226,MATCH($N$35,Dados!$C$119:$C$226,0)),""))} | F48: =IF($N$35="","",IF(COUNTIF($C$27:$C$36,$N$35)>0,"Já escolhida",IF('Criação'!$A$14>=$E$48,"Sim","A partir do nível "&$E$48))) | G48: {=IF($N$35="","",IFERROR(INDEX(Dados!$F$119:$F$226,MATCH($N$35,Dados!$C$119:$C$226,0)),""))} | H48: {=IF($N$35="","",IFERROR(INDEX(Dados!$G$119:$G$226,MATCH($N$35,Dados!$C$119:$C$226,0)),""))}
A49: 10 | C49: =$N$36 | D49: {=IF($N$36="","",IFERROR(INDEX(Dados!$D$119:$D$226,MATCH($N$36,Dados!$C$119:$C$226,0)),""))} | E49: {=IF($N$36="","",IFERROR(INDEX(Dados!$E$119:$E$226,MATCH($N$36,Dados!$C$119:$C$226,0)),""))} | F49: =IF($N$36="","",IF(COUNTIF($C$27:$C$36,$N$36)>0,"Já escolhida",IF('Criação'!$A$14>=$E$49,"Sim","A partir do nível "&$E$49))) | G49: {=IF($N$36="","",IFERROR(INDEX(Dados!$F$119:$F$226,MATCH($N$36,Dados!$C$119:$C$226,0)),""))} | H49: {=IF($N$36="","",IFERROR(INDEX(Dados!$G$119:$G$226,MATCH($N$36,Dados!$C$119:$C$226,0)),""))}
A50: 11 | C50: =$N$37 | D50: {=IF($N$37="","",IFERROR(INDEX(Dados!$D$119:$D$226,MATCH($N$37,Dados!$C$119:$C$226,0)),""))} | E50: {=IF($N$37="","",IFERROR(INDEX(Dados!$E$119:$E$226,MATCH($N$37,Dados!$C$119:$C$226,0)),""))} | F50: =IF($N$37="","",IF(COUNTIF($C$27:$C$36,$N$37)>0,"Já escolhida",IF('Criação'!$A$14>=$E$50,"Sim","A partir do nível "&$E$50))) | G50: {=IF($N$37="","",IFERROR(INDEX(Dados!$F$119:$F$226,MATCH($N$37,Dados!$C$119:$C$226,0)),""))} | H50: {=IF($N$37="","",IFERROR(INDEX(Dados!$G$119:$G$226,MATCH($N$37,Dados!$C$119:$C$226,0)),""))}
A51: 12 | C51: =$N$38 | D51: {=IF($N$38="","",IFERROR(INDEX(Dados!$D$119:$D$226,MATCH($N$38,Dados!$C$119:$C$226,0)),""))} | E51: {=IF($N$38="","",IFERROR(INDEX(Dados!$E$119:$E$226,MATCH($N$38,Dados!$C$119:$C$226,0)),""))} | F51: =IF($N$38="","",IF(COUNTIF($C$27:$C$36,$N$38)>0,"Já escolhida",IF('Criação'!$A$14>=$E$51,"Sim","A partir do nível "&$E$51))) | G51: {=IF($N$38="","",IFERROR(INDEX(Dados!$F$119:$F$226,MATCH($N$38,Dados!$C$119:$C$226,0)),""))} | H51: {=IF($N$38="","",IFERROR(INDEX(Dados!$G$119:$G$226,MATCH($N$38,Dados!$C$119:$C$226,0)),""))}
A53: =IF('Criação'!$B$33="A Recordação","Memoespírito — 11.3 a 11.5","Memoespírito — só para A Recordação") -> Memoespírito — só para A Recordação
A54: Só para A Recordação? | B54: =IF('Criação'!$B$33="A Recordação","Sim","Não") -> Não | D54: Fora da Recordação o bloco fica cinza e as contas ficam vazias. | K54: =IF(AND(NOT(($B$54="Sim")),(LEN($B$55)+LEN($B$56)+LEN($B$57)+LEN($B$58)+LEN($B$60)+LEN($B$61)+LEN($B$62)+LEN($B$63)+LEN($B$64)+LEN($B$65)+LEN($B$67)+LEN($B$69)+LEN($B$70)+LEN($B$71)+LEN($B$72)+LEN($E$72)+LEN($B$73)+LEN($E$73)+LEN($C$75)+LEN($C$76)+LEN($C$77)+LEN($B$78))>0),"Memoespírito só na Recordação: estes campos não contam","")
A55: Nome do Memoespírito
A56: Conceito (11.3 Passo 2) | D56: =IF(OR(NOT(($B$54="Sim")),$B$56=""),"",IFERROR(VLOOKUP($B$56,Dados!$A$544:$B$548,2,FALSE),""))
A57: Função (11.3 Passo 3) | D57: =IF(OR(NOT(($B$54="Sim")),$B$57=""),"",IFERROR(VLOOKUP($B$57,Dados!$A$552:$B$555,2,FALSE),""))
A58: Elemento dele
A59: Atributo | B59: Pontos (preencha, máx. 5) | C59: Pontos usados | D59: Teste de Resistência dele | K59: Aviso
A60: Poder | C60: =IF(ISNUMBER($B$60),MAX(0,MIN(5,INT($B$60))),0) -> 0 | D60: =IF(($B$54="Sim"),"d20"&IF(($C$60+'Criação'!$C$14)>=0,"+","")&($C$60+'Criação'!$C$14),"") | K60: =IF($B$60="","",IF(ISNUMBER($B$60),IF($B$60>5,"Máximo 5 pontos por Atributo","")&IF($B$60<0,"Pontos não podem ser negativos",""),"Precisa ser um número"))
A61: Agilidade | C61: =IF(ISNUMBER($B$61),MAX(0,MIN(5,INT($B$61))),0) -> 0 | D61: =IF(($B$54="Sim"),"d20"&IF(($C$61+'Criação'!$C$14)>=0,"+","")&($C$61+'Criação'!$C$14),"") | K61: =IF($B$61="","",IF(ISNUMBER($B$61),IF($B$61>5,"Máximo 5 pontos por Atributo","")&IF($B$61<0,"Pontos não podem ser negativos",""),"Precisa ser um número"))
A62: Vigor | C62: =IF(ISNUMBER($B$62),MAX(0,MIN(5,INT($B$62))),0) -> 0 | D62: =IF(($B$54="Sim"),"d20"&IF(($C$62+'Criação'!$C$14)>=0,"+","")&($C$62+'Criação'!$C$14),"") | K62: =IF($B$62="","",IF(ISNUMBER($B$62),IF($B$62>5,"Máximo 5 pontos por Atributo","")&IF($B$62<0,"Pontos não podem ser negativos",""),"Precisa ser um número"))
A63: Sincronia | C63: =IF(ISNUMBER($B$63),MAX(0,MIN(5,INT($B$63))),0) -> 0 | D63: =IF(($B$54="Sim"),"d20"&IF(($C$63+'Criação'!$C$14)>=0,"+","")&($C$63+'Criação'!$C$14),"") | K63: =IF($B$63="","",IF(ISNUMBER($B$63),IF($B$63>5,"Máximo 5 pontos por Atributo","")&IF($B$63<0,"Pontos não podem ser negativos",""),"Precisa ser um número"))
A64: Discernimento | C64: =IF(ISNUMBER($B$64),MAX(0,MIN(5,INT($B$64))),0) -> 0 | D64: =IF(($B$54="Sim"),"d20"&IF(($C$64+'Criação'!$C$14)>=0,"+","")&($C$64+'Criação'!$C$14),"") | K64: =IF($B$64="","",IF(ISNUMBER($B$64),IF($B$64>5,"Máximo 5 pontos por Atributo","")&IF($B$64<0,"Pontos não podem ser negativos",""),"Precisa ser um número"))
A65: Presença | C65: =IF(ISNUMBER($B$65),MAX(0,MIN(5,INT($B$65))),0) -> 0 | D65: =IF(($B$54="Sim"),"d20"&IF(($C$65+'Criação'!$C$14)>=0,"+","")&($C$65+'Criação'!$C$14),"") | K65: =IF($B$65="","",IF(ISNUMBER($B$65),IF($B$65>5,"Máximo 5 pontos por Atributo","")&IF($B$65<0,"Pontos não podem ser negativos",""),"Precisa ser um número"))
A66: Pontos totais (12 + metade do nível) / gastos | B66: =IF(($B$54="Sim"),'Criação'!$K$16,"") | C66: =SUM($B$60:$B$65) -> 0 | K66: =IF(AND(($B$54="Sim"),$C$66>'Criação'!$K$16),"Pontos acima do total ("&'Criação'!$K$16&")","")
A67: Atributo de ataque dele (vazio = Poder) | D67: =IF($B$67="","Poder",$B$67) -> Poder
A68: Bônus menor (11.3 Passo 4) | B68: Escolha (preencha) | D68: Efeito
A69: Bônus menor 1 | D69: =IF($B$69="","",IFERROR(VLOOKUP($B$69,Dados!$A$559:$B$564,2,FALSE),"")) | K69: =IF($B$69="","",IF(COUNTIF($B$69:$B$71,$B$69)>1,"Bônus menor repetido: escolha 3 diferentes",IF(COUNTIF(Dados!$AE$6:$AE$11,$B$69)=0,"Fora da lista de 11.3","")))
A70: Bônus menor 2 | D70: =IF($B$70="","",IFERROR(VLOOKUP($B$70,Dados!$A$559:$B$564,2,FALSE),"")) | K70: =IF($B$70="","",IF(COUNTIF($B$69:$B$71,$B$70)>1,"Bônus menor repetido: escolha 3 diferentes",IF(COUNTIF(Dados!$AE$6:$AE$11,$B$70)=0,"Fora da lista de 11.3","")))
A71: Bônus menor 3 | D71: =IF($B$71="","",IFERROR(VLOOKUP($B$71,Dados!$A$559:$B$564,2,FALSE),"")) | K71: =IF($B$71="","",IF(COUNTIF($B$69:$B$71,$B$71)>1,"Bônus menor repetido: escolha 3 diferentes",IF(COUNTIF(Dados!$AE$6:$AE$11,$B$71)=0,"Fora da lista de 11.3","")))
A72: Técnica Principal: nome | D72: o que faz
A73: Técnica Auxiliar: nome | D73: o que faz
A74: Evolução (11.3) | B74: Nível | C74: Escolha (preencha) | D74: Efeito
A75: Evolução 1 | B75: 8 | D75: =IF($C$75="","",IFERROR(VLOOKUP($C$75,Dados!$A$582:$B$584,2,FALSE),"")) | K75: =IF($C$75="","",IF('Criação'!$A$14<8,"Só a partir do nível 8. ","")&IF(COUNTIF($C$75:$C$77,$C$75)>1,"Evolução repetida: cada uma só uma vez.",""))
A76: Evolução 2 | B76: 14 | D76: =IF($C$76="","",IFERROR(VLOOKUP($C$76,Dados!$A$582:$B$584,2,FALSE),"")) | K76: =IF($C$76="","",IF('Criação'!$A$14<14,"Só a partir do nível 14. ","")&IF(COUNTIF($C$75:$C$77,$C$76)>1,"Evolução repetida: cada uma só uma vez.",""))
A77: Evolução 3 | B77: 20 | D77: =IF($C$77="","",IFERROR(VLOOKUP($C$77,Dados!$A$582:$B$584,2,FALSE),"")) | K77: =IF($C$77="","",IF('Criação'!$A$14<20,"Só a partir do nível 20. ","")&IF(COUNTIF($C$75:$C$77,$C$77)>1,"Evolução repetida: cada uma só uma vez.",""))
A78: Memória Desperta: +2 em
A79: Estatísticas do Memoespírito (11.4, com Função, Bônus menores, Evoluções e Bênçãos)
A80: PV | B80: =IF(($B$54="Sim"),8*'Criação'!$A$14+3*$C$62+IF($B$57="Guardião",3*'Criação'!$A$14,0)+IF((COUNTIF($B$69:$B$71,"Resistência Espiritual")>0),2*'Criação'!$A$14,0)+IF((COUNTIF($I$27:$I$36,"Ecos do Passado")>0),4*'Criação'!$A$14,0),"")
A81: Defesa | B81: =IF(($B$54="Sim"),10+$C$61+'Criação'!$C$14+IF(AND((COUNTIF($C$75:$C$77,"Memória Desperta")>0),$B$78<>"Velocidade"),2,0),"")
A82: Velocidade | B82: =IF(($B$54="Sim"),10+$C$61+'Criação'!$B$37+IF((COUNTIF($B$69:$B$71,"Velocidade Espiritual")>0),2,0)+IF(AND((COUNTIF($C$75:$C$77,"Memória Desperta")>0),$B$78="Velocidade"),2,0),"")
A83: Teste de Ataque (número) | B83: {=IF(($B$54="Sim"),'Criação'!$B$55+IFERROR(INDEX($C$60:$C$65,MATCH($D$67,$A$60:$A$65,0)),0)+'Criação'!$C$14,"")}
A84: Teste de Ataque | B84: =IF(($B$54="Sim"),"d20"&IF($B$83>=0,"+","")&$B$83,"")
A85: Dados de dano (d6) | B85: =IF(($B$54="Sim"),'Criação'!$D$16+IF((COUNTIF($C$75:$C$77,"Forma Completa")>0),1,0),"")
A86: Dano fixo | B86: {=IF(($B$54="Sim"),IFERROR(INDEX($C$60:$C$65,MATCH($D$67,$A$60:$A$65,0)),0)+IF((COUNTIF($B$69:$B$71,"Força Espiritual")>0),2,0)+IF((COUNTIF($I$27:$I$36,"Ecos do Passado")>0),'Criação'!$B$55,0),"")}
A87: Dano do ataque | B87: =IF(($B$54="Sim"),IF($B$85<=0,""&$B$86,$B$85&"d"&6&IF($B$86>0,"+"&$B$86,IF($B$86<0,""&$B$86,""))),"")
A88: Média do dano | B88: =IF(($B$54="Sim"),INT($B$85*7/2)+$B$86,"")
A89: Média contra Fraqueza (+2 dados) | B89: =IF(($B$54="Sim"),INT(($B$85+2)*7/2)+$B$86,"")
A90: Redução de Tenacidade | B90: =IF(($B$54="Sim"),IF('Criação'!$A$14>=11,2,1)+IF((COUNTIF($I$27:$I$36,"Eternidade Recordada")>0),1,0),"")
A91: RD | B91: =IF(($B$54="Sim"),IF((COUNTIF($B$69:$B$71,"Resistência Espiritual")>0),1,0),"")
A92: Função Predador | B92: =IF(AND(($B$54="Sim"),$B$57="Predador"),"+1d8 de dano nos ataques dele","")
A94: Escolhas permanentes de Bênção (só vale com a Bênção adquirida)
A95: Fragmentos do Eu Perdido: Memória escolhida | D95: ="Fúria: +1d8 nos ataques dele e nos seus com ele ativo · Guarda: +Eficiência de Defesa com ele ativo · Sabedoria: Eficácia em um Teste de Perícia, 2 vezes por dia" -> Fúria: +1d8 nos ataques dele e nos seus com ele ativo · Guarda: +Eficiência de Defesa com ele ativo · Sabedoria: Eficácia em um Teste de Perícia, 2 vezes por dia | K95: =IF($B$95="","",IF(OR($B$95="Fúria",$B$95="Guarda",$B$95="Sabedoria"),"","Escolha uma opção da lista. ")&IF((COUNTIF($I$27:$I$36,"Fragmentos do Eu Perdido")>0),"","Só vale com a Bênção Fragmentos do Eu Perdido num slot liberado."))
A96: Avatar da Recordação: Forma escolhida | D96: ="Manifestada: o Memoespírito ganha +1 Distância e +2 dados · Sincronizada: você ganha PV +2 × nível, +1 de Defesa e +1 dado base nos seus ataques" -> Manifestada: o Memoespírito ganha +1 Distância e +2 dados · Sincronizada: você ganha PV +2 × nível, +1 de Defesa e +1 dado base nos seus ataques | K96: =IF($B$96="","",IF(OR($B$96="Manifestada",$B$96="Sincronizada"),"","Escolha uma opção da lista. ")&IF((COUNTIF($I$27:$I$36,"Avatar da Recordação")>0),"","Só vale com a Bênção Avatar da Recordação num slot liberado."))

Sheet Equipamento
A1: Equipamento — Explorando Galáxias v1.1
A2: Legenda: | B2: Entrada (preencha) | C2: Calculada (automático) | D2: Aviso (texto em vermelho) | E2: Título de bloco | F2: Cabeçalho de coluna | G2: Rótulo da linha | H2: Linha alternada (outro tom) | J2: Não se aplica
A3: Arma, armadura, Cone de Luz, Relíquias, inventário e Créditos.
A5: Armas e armadura — a arma principal e a armadura vêm da aba Criação (Passos 8 e 12)
A6: Arma | B6: Nome | C6: Categoria | D6: Atributo (só arma Média) | E6: Elemento próprio | F6: Propriedade especial | G6: Espaço | H6: Dados base | I6: Atributo de ataque | J6: Elemento do Ataque Básico | K6: Aviso
A7: Principal (edite na aba Criação) | B7: =IF(LEN('Criação'!$B$107)=0,"—",""&'Criação'!$B$107) -> — | C7: =IF(LEN('Criação'!$B$108)=0,"—",""&'Criação'!$B$108) -> — | D7: =IF(LEN('Criação'!$B$109)=0,"—",""&'Criação'!$B$109) -> — | E7: =IF(LEN('Criação'!$B$110)=0,"—",""&'Criação'!$B$110) -> — | F7: =IF(LEN('Criação'!$B$111)=0,"Nenhuma",""&'Criação'!$B$111) -> Nenhuma | G7: ='Criação'!$B$112 -> 0 | H7: =IF('Criação'!$B$108="","",IFERROR(VLOOKUP('Criação'!$B$108,Dados!$A$457:$J$462,2,FALSE),"")) | I7: ='Criação'!$D$109 | J7: =IF('Criação'!$B$108="","",'Criação'!$D$110)
A8: Secundária (preencha) | G8: =IF($C$8="",0,IF($F$8="Dissimulada",0.5,IFERROR(VLOOKUP($C$8,Dados!$A$457:$J$462,8,FALSE),0))) -> 0 | H8: =IF($C$8="","",IFERROR(VLOOKUP($C$8,Dados!$A$457:$J$462,2,FALSE),"")) | I8: =IF($C$8="","",IF($C$8="Média",IF(OR($D$8="Poder",$D$8="Agilidade"),$D$8,"Poder"),IFERROR(VLOOKUP($C$8,Dados!$A$457:$J$462,6,FALSE),""))) | J8: =IF($C$8="","",IF($E$8="","Físico",$E$8)) | K8: =IF(AND($C$8<>"",COUNTIF(Dados!$T$6:$T$11,$C$8)=0),"Categoria fora da lista do capítulo 24. ","")&IF(AND($D$8<>"",$C$8<>"Média"),"O atributo só se escolhe na arma Média. ","")&IF(AND($C$8="Média",$D$8=""),"Arma Média: escolha Poder ou Agilidade (contando Poder). ","")&IF(AND($E$8<>"",COUNTIF(Dados!$R$6:$R$12,$E$8)=0),"Elemento fora da lista do capítulo 20. ","")&IF(AND($F$8<>"",COUNTIF(Dados!$V$6:$V$11,$F$8)=0),"Só uma propriedade especial por arma (24.2): escolha uma da lista. ","")&IF(AND($C$8="",OR(LEN($B$8)>0,$D$8<>"",$E$8<>"",$F$8<>"")),"Escolha a categoria da arma secundária.","")
A9: Armadura (edite na aba Criação) | B9: =IF(LEN('Criação'!$B$91)=0,"Sem armadura",""&'Criação'!$B$91) -> Sem armadura | C9: ="Defesa +"&'Criação'!$B$93 -> Defesa +0 | D9: ="RD "&'Criação'!$D$93 -> RD 0 | E9: ="Velocidade "&IF('Criação'!$C$93>=0,"+","")&'Criação'!$C$93 -> Velocidade +0 | F9: ="Esquiva: "&'Criação'!$F$93 -> Esquiva: Permitida | G9: =IFERROR(VLOOKUP('Criação'!$B$91,Dados!$A$474:$I$476,5,FALSE),0) -> 0
A11: Ataque Básico — 18.2 e 18.5 (dano = dados + atributo + equipamento: Mãos, Cone e Conjuntos, 25.3)
A12: Arma | B12: Teste de Ataque | C12: Dano | D12: Média | E12: Fixo do atributo | F12: Fixo do equipamento | G12: Contra Fraqueza (+2 dados) | H12: Média | I12: Crítico | J12: Redução de Tenacidade | K12: Alcance | L12: Elemento | P12: nº de dados | Q12: face | R12: dano fixo | S12: equipamento | T12: ataque
A13: Principal | B13: =IF('Criação'!$B$108="","—","d20"&IF($T$13>=0,"+","")&$T$13) -> — | C13: =IF('Criação'!$B$108="","",IF($P$13<=0,""&($R$13+$S$13),$P$13&"d"&$Q$13&IF(($R$13+$S$13)>0,"+"&($R$13+$S$13),IF(($R$13+$S$13)<0,""&($R$13+$S$13),"")))) | D13: =IF('Criação'!$B$108="","",INT($P$13*($Q$13+1)/2)+($R$13+$S$13)) | E13: =IF('Criação'!$B$108="","",$R$13) | F13: =IF('Criação'!$B$108="","",$S$13) | G13: =IF('Criação'!$B$108="","",IF(($P$13+2)<=0,""&($R$13+$S$13),($P$13+2)&"d"&$Q$13&IF(($R$13+$S$13)>0,"+"&($R$13+$S$13),IF(($R$13+$S$13)<0,""&($R$13+$S$13),"")))) | H13: =IF('Criação'!$B$108="","",INT(($P$13+2)*($Q$13+1)/2)+($R$13+$S$13)) | I13: =IF('Criação'!$B$108="","",IF((COUNTIF(Caminho!$I$27:$I$36,"Olho de Lan")>0),"19-20","20")) | J13: =IF('Criação'!$B$108="","",1+IF('Criação'!$B$111="Peso de impacto",1,0)) | K13: {=IF('Criação'!$B$108="","",IFERROR(INDEX(Dados!$X$6:$X$10,MIN(5,MATCH(VLOOKUP('Criação'!$B$108,Dados!$A$457:$J$462,5,FALSE),Dados!$X$6:$X$10,0)+IF('Criação'!$B$111="Alcance estendido",1,0))),""))} | L13: =IF('Criação'!$B$108="","",'Criação'!$D$110) | P13: =IF('Criação'!$B$108="",0,'Criação'!$D$16+IFERROR(VLOOKUP('Criação'!$B$108,Dados!$A$457:$J$462,3,FALSE),1)-1+IF(AND((COUNTIF(Caminho!$I$27:$I$36,"Avatar da Recordação")>0),Caminho!$B$96="Sincronizada"),1,0)) -> 0 | Q13: =IFERROR(VLOOKUP('Criação'!$B$108,Dados!$A$457:$J$462,4,FALSE),0) -> 0 | R13: {=IFERROR(INDEX('Criação'!$F$44:$F$49,MATCH('Criação'!$D$109,'Criação'!$A$44:$A$49,0)),0)} -> 0 | S13: =$G$37+$D$31+$G$48 -> 0 | T13: {=IFERROR(INDEX('Criação'!$F$44:$F$49,MATCH('Criação'!$D$109,'Criação'!$A$44:$A$49,0)),0)+'Criação'!$C$14+'Criação'!$G$14+'Criação'!$B$124} -> #ERROR!
A14: Secundária | B14: =IF($C$8="","—","d20"&IF($T$14>=0,"+","")&$T$14) -> — | C14: =IF($C$8="","",IF($P$14<=0,""&($R$14+$S$14),$P$14&"d"&$Q$14&IF(($R$14+$S$14)>0,"+"&($R$14+$S$14),IF(($R$14+$S$14)<0,""&($R$14+$S$14),"")))) | D14: =IF($C$8="","",INT($P$14*($Q$14+1)/2)+($R$14+$S$14)) | E14: =IF($C$8="","",$R$14) | F14: =IF($C$8="","",$S$14) | G14: =IF($C$8="","",IF(($P$14+2)<=0,""&($R$14+$S$14),($P$14+2)&"d"&$Q$14&IF(($R$14+$S$14)>0,"+"&($R$14+$S$14),IF(($R$14+$S$14)<0,""&($R$14+$S$14),"")))) | H14: =IF($C$8="","",INT(($P$14+2)*($Q$14+1)/2)+($R$14+$S$14)) | I14: =IF($C$8="","",IF((COUNTIF(Caminho!$I$27:$I$36,"Olho de Lan")>0),"19-20","20")) | J14: =IF($C$8="","",1+IF($F$8="Peso de impacto",1,0)) | K14: {=IF($C$8="","",IFERROR(INDEX(Dados!$X$6:$X$10,MIN(5,MATCH(VLOOKUP($C$8,Dados!$A$457:$J$462,5,FALSE),Dados!$X$6:$X$10,0)+IF($F$8="Alcance estendido",1,0))),""))} | L14: =IF($C$8="","",$J$8) | P14: =IF($C$8="",0,'Criação'!$D$16+IFERROR(VLOOKUP($C$8,Dados!$A$457:$J$462,3,FALSE),1)-1+IF(AND((COUNTIF(Caminho!$I$27:$I$36,"Avatar da Recordação")>0),Caminho!$B$96="Sincronizada"),1,0)) -> 0 | Q14: =IFERROR(VLOOKUP($C$8,Dados!$A$457:$J$462,4,FALSE),0) -> 0 | R14: {=IFERROR(INDEX('Criação'!$F$44:$F$49,MATCH($I$8,'Criação'!$A$44:$A$49,0)),0)} -> 0 | S14: =$G$37+$D$31+$G$48 -> 0 | T14: {=IFERROR(INDEX('Criação'!$F$44:$F$49,MATCH($I$8,'Criação'!$A$44:$A$49,0)),0)+'Criação'!$C$14+'Criação'!$G$14+'Criação'!$B$124} -> #ERROR!
A15: Mãos (Relíquia) soma no Ataque Básico; a Esfera Planar nunca (25.3). Fraqueza: +2 dados que não critam; o crítico dobra só os dados base (18.3).
A17: Cone de Luz — 25.2 (Bônus Maior permanente, fora do teto; Efeito Condicional temporário)
A18: Nome do Cone de Luz
A19: Nível do Cone (1 a 5) | C19: {="Máximo na sua faixa: Nível "&'Criação'!$B$14&IF($P$28>0," · Bônus Maior da tabela: "&INDEX(Dados!$C$522:$C$526,$P$28),"")} -> Máximo na sua faixa: Nível 1 | L19: =IF(LEN($B$19)=0,"",IF(ISNUMBER($B$19),IF(OR($B$19<1,$B$19>5),"O Nível do Cone vai de 1 a 5. ","")&IF($P$28>'Criação'!$B$14,"Cone de Nível "&$P$28&" acima do máximo da sua faixa (Nível "&'Criação'!$B$14&").",""),"Nível precisa ser um número de 1 a 5."))
A20: Alvo do Bônus Maior (escolha um) | D20: =IF($B$20="","Sem alvo, o bônus numérico não conta (o +PV dos Níveis 2 e 4 conta sempre)","O bônus vai para: "&$B$20&IF(LEN($B$21)>0," ("&$B$21&")","")) -> Sem alvo, o bônus numérico não conta (o +PV dos Níveis 2 e 4 conta sempre) | L20: =IF($B$20="","",IF(COUNTIF(Dados!$AM$6:$AM$15,$B$20)=0,"Alvo fora da lista de 25.2. ",IF(AND(OR($B$20="Um Teste de Resistência",$B$20="Uma Perícia"),LEN($B$21)=0),"Escolha qual "&IF($B$20="Um Teste de Resistência","Teste de Resistência","Perícia")&" recebe o bônus. ",""))&IF($P$28=0,"Preencha o Nível do Cone para o bônus contar.","")) | Y20: Lista: Teste de Resistência ou Perícia do Cone
A21: Qual Teste de Resistência ou Perícia (se o alvo pedir) | K21: =IF(LEN($B$21)=0,"",IF(AND($B$20<>"Um Teste de Resistência",$B$20<>"Uma Perícia"),"Só vale com o alvo Um Teste de Resistência ou Uma Perícia.",IF(COUNTIF($Y$21:$Y$38,$B$21)=0,"Escolha um nome da lista.",""))) | Y21: {=IF($B$20="Um Teste de Resistência",IFERROR(INDEX(Dados!$AA$6:$AA$11,1),""),IF($B$20="Uma Perícia",IFERROR(INDEX(Dados!$Z$6:$Z$23,1),""),""))}
A22: Numérico ou PV (só nos Níveis 1, 3 e 5) | C22: =IF($P$28=0,"",IF($Q$28="e","No Nível "&$P$28&" o Cone dá os dois: +"&$S$28&" e +"&$T$28&" PV",IF($B$22="PV","Vale o PV: +"&$T$28&" PV","Vale o numérico: +"&$S$28&IF($B$22=""," (vazio = Numérico)","")))) | L22: =IF($B$22="","",IF(COUNTIF(Dados!$AN$6:$AN$7,$B$22)=0,"Escolha Numérico ou PV.",IF($Q$28="e","No Nível "&$P$28&" o Cone dá os dois: a escolha não se aplica.",""))) | Y22: {=IF($B$20="Um Teste de Resistência",IFERROR(INDEX(Dados!$AA$6:$AA$11,2),""),IF($B$20="Uma Perícia",IFERROR(INDEX(Dados!$Z$6:$Z$23,2),""),""))}
A23: Sobreposições (cópias extras do mesmo Cone) | C23: {="Cada uma: +1 e +10 PV, até o numérico chegar a +3 · no máximo 1 por faixa alcançada ("&'Criação'!$B$14&")"&IF($P$28>0," · este Cone aceita até "&(3-INDEX(Dados!$D$522:$D$526,$P$28)),"")&" (25.2)"} -> Cada uma: +1 e +10 PV, até o numérico chegar a +3 · no máximo 1 por faixa alcançada (1) (25.2) | L23: {=IF(LEN($B$23)=0,"",IF(ISNUMBER($B$23),IF($B$23>'Criação'!$B$14,"Sobreposições acima de uma por faixa alcançada (máximo "&'Criação'!$B$14&"). ","")&IF($B$23<0,"Não pode ser negativo. ","")&IF($P$28=0,"Sem Cone: preencha o Nível.",IF($R$28>(3-INDEX(Dados!$D$522:$D$526,$P$28)),"Acima do teto: o Cone de Nível "&$P$28&" aceita no máximo "&(3-INDEX(Dados!$D$522:$D$526,$P$28))&" (o numérico para em +3 e o PV para junto, 25.2).","")),"Precisa ser um número."))} | Y23: {=IF($B$20="Um Teste de Resistência",IFERROR(INDEX(Dados!$AA$6:$AA$11,3),""),IF($B$20="Uma Perícia",IFERROR(INDEX(Dados!$Z$6:$Z$23,3),""),""))}
A24: Efeito Condicional (escreva com o Mestre) | Y24: {=IF($B$20="Um Teste de Resistência",IFERROR(INDEX(Dados!$AA$6:$AA$11,4),""),IF($B$20="Uma Perícia",IFERROR(INDEX(Dados!$Z$6:$Z$23,4),""),""))}
A25: Frequência do Efeito Condicional | B25: =IF($P$28=0,"",IF($P$28=1,"1 vez por combate","1 vez por Ciclo")&" · temporário: entra no teto de bônus somado (25.4)") | Y25: {=IF($B$20="Um Teste de Resistência",IFERROR(INDEX(Dados!$AA$6:$AA$11,5),""),IF($B$20="Uma Perícia",IFERROR(INDEX(Dados!$Z$6:$Z$23,5),""),""))}
A26: Energia do Cone (17.2) | B26: =IF($P$28>=3,"Sim: +5 de Energia, no máximo 1 vez por Ciclo (Efeito Condicional)",IF($P$28=0,"","Não: só no Nível 3 ou maior")) | Y26: {=IF($B$20="Um Teste de Resistência",IFERROR(INDEX(Dados!$AA$6:$AA$11,6),""),IF($B$20="Uma Perícia",IFERROR(INDEX(Dados!$Z$6:$Z$23,6),""),""))}
B27: Numérico que vale | C27: PV que vale | D27: Resumo do Bônus Maior | P27: nível | Q27: e/ou | R27: cópias | S27: numérico | T27: PV | Y27: {=IF($B$20="Um Teste de Resistência",IFERROR(INDEX(Dados!$AA$6:$AA$11,7),""),IF($B$20="Uma Perícia",IFERROR(INDEX(Dados!$Z$6:$Z$23,7),""),""))}
A28: Numérico / PV que valem | B28: =IF($P$28=0,0,IF($B$20="PV máximos",0,IF($Q$28="e",$S$28,IF($B$22="PV",0,$S$28)))) -> 0 | C28: =IF($P$28=0,0,IF(OR($B$20="PV máximos",$Q$28="e",$B$22="PV"),$T$28,0)) -> 0 | D28: =IF($P$28=0,"Sem Cone","+"&$B$28&IF($B$20=""," (sem alvo)"," em "&$B$20)&IF($C$28>0," · +"&$C$28&" PV máximos","")) -> Sem Cone | P28: =IF(ISNUMBER($B$19),IF($B$19<1,0,MIN(5,INT($B$19))),0) -> 0 | Q28: {=IF($P$28=0,"",INDEX(Dados!$E$522:$E$526,$P$28))} | R28: =IF(ISNUMBER($B$23),MAX(0,MIN('Criação'!$B$14,INT($B$23))),0) -> 0 | S28: {=IF($P$28=0,0,INDEX(Dados!$D$522:$D$526,$P$28)+MIN($R$28,(3-INDEX(Dados!$D$522:$D$526,$P$28))))} -> 0 | T28: {=IF($P$28=0,0,INDEX(Dados!$F$522:$F$526,$P$28)+10*MIN($R$28,(3-INDEX(Dados!$D$522:$D$526,$P$28))))} -> 0 | Y28: {=IF($B$20="Um Teste de Resistência",IFERROR(INDEX(Dados!$AA$6:$AA$11,8),""),IF($B$20="Uma Perícia",IFERROR(INDEX(Dados!$Z$6:$Z$23,8),""),""))}
A29: Onde o Bônus Maior entra (automático) | Y29: {=IF($B$20="Um Teste de Resistência",IFERROR(INDEX(Dados!$AA$6:$AA$11,9),""),IF($B$20="Uma Perícia",IFERROR(INDEX(Dados!$Z$6:$Z$23,9),""),""))}
A30: PV máximos | B30: Defesa | C30: Velocidade | D30: Dano de Ataque Básico | E30: Dano de Habilidade | F30: Dano de Ultimate | G30: RD | H30: Teste de Ataque | I30: Teste de Resistência | J30: Qual Teste de Resistência | K30: Perícia | L30: Qual Perícia | Y30: {=IF($B$20="Um Teste de Resistência",IFERROR(INDEX(Dados!$AA$6:$AA$11,10),""),IF($B$20="Uma Perícia",IFERROR(INDEX(Dados!$Z$6:$Z$23,10),""),""))}
A31: =$C$28 -> 0 | B31: =IF($B$20="Defesa",$B$28,0) -> 0 | C31: =IF($B$20="Velocidade",$B$28,0) -> 0 | D31: =IF($B$20="Dano de Ataque Básico",$B$28,0) -> 0 | E31: =IF($B$20="Dano de Habilidade",$B$28,0) -> 0 | F31: =IF($B$20="Dano de Ultimate",$B$28,0) -> 0 | G31: =IF($B$20="RD",$B$28,0) -> 0 | H31: =IF($B$20="Teste de Ataque",$B$28,0) -> 0 | I31: =IF(AND($B$20="Um Teste de Resistência",LEN($B$21)>0),$B$28,0) -> 0 | J31: =IF($B$20="Um Teste de Resistência",""&$B$21,"") | K31: =IF(AND($B$20="Uma Perícia",LEN($B$21)>0),$B$28,0) -> 0 | L31: =IF($B$20="Uma Perícia",""&$B$21,"") | Y31: {=IF($B$20="Um Teste de Resistência",IFERROR(INDEX(Dados!$AA$6:$AA$11,11),""),IF($B$20="Uma Perícia",IFERROR(INDEX(Dados!$Z$6:$Z$23,11),""),""))}
Y32: {=IF($B$20="Um Teste de Resistência",IFERROR(INDEX(Dados!$AA$6:$AA$11,12),""),IF($B$20="Uma Perícia",IFERROR(INDEX(Dados!$Z$6:$Z$23,12),""),""))}
A33: Relíquias — 25.3 (6 slots; o Tier sobe sozinho com o nível; bônus de slot fora do teto) | Y33: {=IF($B$20="Um Teste de Resistência",IFERROR(INDEX(Dados!$AA$6:$AA$11,13),""),IF($B$20="Uma Perícia",IFERROR(INDEX(Dados!$Z$6:$Z$23,13),""),""))}
A34: Tier da sua faixa | B34: =CHOOSE('Criação'!$J$16,"I","II","III","IV") -> I | C34: Tier I (níveis 1-6) · II (7-12) · III (13-17) · IV (18-20) — recompensa de marco (25.1) | Y34: {=IF($B$20="Um Teste de Resistência",IFERROR(INDEX(Dados!$AA$6:$AA$11,14),""),IF($B$20="Uma Perícia",IFERROR(INDEX(Dados!$Z$6:$Z$23,14),""),""))}
A35: Slot | B35: Possui? (Sim) | C35: Nome da peça | E35: Conjunto (A, B, C ou —) | F35: Tier | G35: Bônus | H35: O que dá | J35: Elemento (só Esfera Planar) | K35: Vale no seu dano? | L35: Aviso | Y35: {=IF($B$20="Um Teste de Resistência",IFERROR(INDEX(Dados!$AA$6:$AA$11,15),""),IF($B$20="Uma Perícia",IFERROR(INDEX(Dados!$Z$6:$Z$23,15),""),""))}
A36: Cabeça | F36: =IF($B$36="Sim",$B$34,"—") -> — | G36: {=IF($B$36="Sim",INDEX(Dados!$A$530:$F$535,1,2+'Criação'!$J$16),0)} -> 0 | H36: {=IF($B$36="Sim",INDEX(Dados!$B$530:$B$535,1)&": +"&$G$36,INDEX(Dados!$B$530:$B$535,1))} -> PV máximos | J36: — | K36: — | L36: =IF(AND($E$36<>"",$E$36<>"—",$B$36<>"Sim"),"A peça só conta para o Conjunto com Possui = Sim. ","")&IF(AND($E$36<>"",COUNTIF(Dados!$AO$6:$AO$9,$E$36)=0),"Conjunto: use A, B, C ou —. ","")&IF(AND($B$36<>"",$B$36<>"Sim",$B$36<>"Não"),"Possui: use Sim ou Não. ","") | Y36: {=IF($B$20="Um Teste de Resistência",IFERROR(INDEX(Dados!$AA$6:$AA$11,16),""),IF($B$20="Uma Perícia",IFERROR(INDEX(Dados!$Z$6:$Z$23,16),""),""))}
A37: Mãos | F37: =IF($B$37="Sim",$B$34,"—") -> — | G37: {=IF($B$37="Sim",INDEX(Dados!$A$530:$F$535,2,2+'Criação'!$J$16),0)} -> 0 | H37: {=IF($B$37="Sim",INDEX(Dados!$B$530:$B$535,2)&": +"&$G$37,INDEX(Dados!$B$530:$B$535,2))} -> Dano de Ataque Básico | J37: — | K37: — | L37: =IF(AND($E$37<>"",$E$37<>"—",$B$37<>"Sim"),"A peça só conta para o Conjunto com Possui = Sim. ","")&IF(AND($E$37<>"",COUNTIF(Dados!$AO$6:$AO$9,$E$37)=0),"Conjunto: use A, B, C ou —. ","")&IF(AND($B$37<>"",$B$37<>"Sim",$B$37<>"Não"),"Possui: use Sim ou Não. ","") | Y37: {=IF($B$20="Um Teste de Resistência",IFERROR(INDEX(Dados!$AA$6:$AA$11,17),""),IF($B$20="Uma Perícia",IFERROR(INDEX(Dados!$Z$6:$Z$23,17),""),""))}
A38: Tronco | F38: =IF($B$38="Sim",$B$34,"—") -> — | G38: {=IF($B$38="Sim",INDEX(Dados!$A$530:$F$535,3,2+'Criação'!$J$16),0)} -> 0 | H38: {=IF($B$38="Sim",INDEX(Dados!$B$530:$B$535,3)&": +"&$G$38,INDEX(Dados!$B$530:$B$535,3))} -> Defesa | J38: — | K38: — | L38: =IF(AND($E$38<>"",$E$38<>"—",$B$38<>"Sim"),"A peça só conta para o Conjunto com Possui = Sim. ","")&IF(AND($E$38<>"",COUNTIF(Dados!$AO$6:$AO$9,$E$38)=0),"Conjunto: use A, B, C ou —. ","")&IF(AND($B$38<>"",$B$38<>"Sim",$B$38<>"Não"),"Possui: use Sim ou Não. ","") | Y38: {=IF($B$20="Um Teste de Resistência",IFERROR(INDEX(Dados!$AA$6:$AA$11,18),""),IF($B$20="Uma Perícia",IFERROR(INDEX(Dados!$Z$6:$Z$23,18),""),""))}
A39: Botas | F39: =IF($B$39="Sim",$B$34,"—") -> — | G39: {=IF($B$39="Sim",INDEX(Dados!$A$530:$F$535,4,2+'Criação'!$J$16),0)} -> 0 | H39: {=IF($B$39="Sim",INDEX(Dados!$B$530:$B$535,4)&": +"&$G$39,INDEX(Dados!$B$530:$B$535,4))} -> Velocidade | J39: — | K39: — | L39: =IF(AND($E$39<>"",$E$39<>"—",$B$39<>"Sim"),"A peça só conta para o Conjunto com Possui = Sim. ","")&IF(AND($E$39<>"",COUNTIF(Dados!$AO$6:$AO$9,$E$39)=0),"Conjunto: use A, B, C ou —. ","")&IF(AND($B$39<>"",$B$39<>"Sim",$B$39<>"Não"),"Possui: use Sim ou Não. ","")
A40: Esfera Planar | F40: =IF($B$40="Sim",$B$34,"—") -> — | G40: {=IF($B$40="Sim",INDEX(Dados!$A$530:$F$535,5,2+'Criação'!$J$16),0)} -> 0 | H40: {=IF($B$40="Sim",INDEX(Dados!$B$530:$B$535,5)&": +"&$G$40,INDEX(Dados!$B$530:$B$535,5))} -> Dano de um Elemento escolhido | K40: =IF($B$40<>"Sim","",IF($J$40="","Escolha o Elemento",IF($J$40='Criação'!$B$60,"Sim: +"&$G$40&" nas Habilidades e na Ultimate","Não: o seu Elemento é "&IF(LEN('Criação'!$B$60)=0,"(vazio)",'Criação'!$B$60)))) | L40: =IF(AND($E$40<>"",$E$40<>"—",$B$40<>"Sim"),"A peça só conta para o Conjunto com Possui = Sim. ","")&IF(AND($E$40<>"",COUNTIF(Dados!$AO$6:$AO$9,$E$40)=0),"Conjunto: use A, B, C ou —. ","")&IF(AND($B$40<>"",$B$40<>"Sim",$B$40<>"Não"),"Possui: use Sim ou Não. ","")&IF(AND($J$40<>"",COUNTIF(Dados!$R$6:$R$12,$J$40)=0),"Elemento fora da lista do capítulo 20.","") | P40: =IF(AND($B$40="Sim",$J$40<>"",$J$40='Criação'!$B$60),$G$40,0) -> 0
A41: Corda de Ligação | F41: =IF($B$41="Sim",$B$34,"—") -> — | G41: {=IF($B$41="Sim",INDEX(Dados!$A$530:$F$535,6,2+'Criação'!$J$16),0)} -> 0 | H41: {=IF($B$41="Sim",INDEX(Dados!$B$530:$B$535,6)&": +"&$G$41,INDEX(Dados!$B$530:$B$535,6))} -> Energia, 1 vez por combate | J41: — | K41: =IF($B$41="Sim","+"&$G$41&" de Energia ao entrar na Fila, 1 vez por combate","") | L41: =IF(AND($E$41<>"",$E$41<>"—",$B$41<>"Sim"),"A peça só conta para o Conjunto com Possui = Sim. ","")&IF(AND($E$41<>"",COUNTIF(Dados!$AO$6:$AO$9,$E$41)=0),"Conjunto: use A, B, C ou —. ","")&IF(AND($B$41<>"",$B$41<>"Sim",$B$41<>"Não"),"Possui: use Sim ou Não. ","")
A43: Conjuntos de Relíquias — 25.3 (2 peças: bônus pequeno; 4 peças: efeito por Ciclo; teto +3, dentro do teto global)
A44: Conjunto | B44: Nome do Conjunto (preencha) | C44: Bônus de 2 peças (preencha) | E44: Qual rolagem (só no +1 em um tipo de rolagem) | G44: Peças | H44: Ativo | I44: Aviso | P44: rolagem | Q44: VEL | R44: RD | S44: dano | AA44: Lista: rolagens do Conjunto
A45: A | G45: =COUNTIFS($E$36:$E$41,"A",$B$36:$B$41,"Sim") -> 0 | H45: =IF($G$45>=4,"4 peças",IF($G$45>=2,"2 peças","—")) -> — | I45: =IF(AND($C$45<>"",COUNTIF(Dados!$AP$6:$AP$9,$C$45)=0),"Bônus fora da lista de 25.3. ","")&IF(AND(LEN($E$45)>0,$C$45<>"+1 em um tipo de rolagem"),"Qual rolagem só vale com o bônus +1 em um tipo de rolagem. ","")&IF(AND(LEN($E$45)>0,COUNTIF($AA$45:$AA$69,$E$45)=0),"Rolagem fora da lista. ","")&IF(AND($G$45>=2,$C$45="+1 em um tipo de rolagem",LEN($E$45)=0),"Escolha qual rolagem recebe o +1.","") | P45: =IF(AND($G$45>=2,$C$45="+1 em um tipo de rolagem",LEN($E$45)>0),""&$E$45,"") | Q45: =IF(AND($G$45>=2,$C$45="+1 de Velocidade"),1,0) -> 0 | R45: =IF(AND($G$45>=2,$C$45="+1 RD"),1,0) -> 0 | S45: =IF(AND($G$45>=2,$C$45="+2 de dano"),2,0) -> 0 | AA45: Teste de Ataque
A46: B | G46: =COUNTIFS($E$36:$E$41,"B",$B$36:$B$41,"Sim") -> 0 | H46: =IF($G$46>=4,"4 peças",IF($G$46>=2,"2 peças","—")) -> — | I46: =IF(AND($C$46<>"",COUNTIF(Dados!$AP$6:$AP$9,$C$46)=0),"Bônus fora da lista de 25.3. ","")&IF(AND(LEN($E$46)>0,$C$46<>"+1 em um tipo de rolagem"),"Qual rolagem só vale com o bônus +1 em um tipo de rolagem. ","")&IF(AND(LEN($E$46)>0,COUNTIF($AA$45:$AA$69,$E$46)=0),"Rolagem fora da lista. ","")&IF(AND($G$46>=2,$C$46="+1 em um tipo de rolagem",LEN($E$46)=0),"Escolha qual rolagem recebe o +1.","") | P46: =IF(AND($G$46>=2,$C$46="+1 em um tipo de rolagem",LEN($E$46)>0),""&$E$46,"") | Q46: =IF(AND($G$46>=2,$C$46="+1 de Velocidade"),1,0) -> 0 | R46: =IF(AND($G$46>=2,$C$46="+1 RD"),1,0) -> 0 | S46: =IF(AND($G$46>=2,$C$46="+2 de dano"),2,0) -> 0 | AA46: Potência Física
