Workbook

Sheet Início
A1: Início — Explorando Galáxias v1.2
A2: Legenda: | B2: Entrada (preencha) | C2: Calculada (automático) | D2: Aviso (texto em vermelho) | E2: Título de bloco | F2: Cabeçalho de coluna | G2: Rótulo da linha | H2: Linha alternada (outro tom) | I2: Não se aplica
A3: Comece por aqui: como usar a ficha, importar no Google Planilhas e o painel de avisos.
A5: Ficha de Personagem — Explorando Galáxias v1.2
A6: Sistema de RPG de mesa no universo de Honkai: Star Rail · autoria: MC Filhos · versão v1.2 · níveis 1 a 20. Ficha automatizada para o Google Planilhas: preencha as células amarelas e o resto se calcula sozinho. Ficha V1.2 · revisão 1.
A7: Não comece um texto com +, - ou =: o Google entende como fórmula. Se precisar, digite um apóstrofo (') antes.
A9: Painel de avisos (automático) — uma linha por aba; zero avisos = ficha conferida
A10: Aba | B10: Avisos | C10: Primeiro aviso
A11: Criação | B11: =SUMPRODUCT((LEN('Criação'!$K$6:$K$10)>0)*1)+SUMPRODUCT((LEN('Criação'!$K$20:$K$22)>0)*1)+SUMPRODUCT((LEN('Criação'!$K$25:$K$28)>0)*1)+(LEN('Criação'!$K$33)>0)*1+SUMPRODUCT((LEN('Criação'!$K$44:$K$51)>0)*1)+(LEN('Criação'!$K$54)>0)*1+(LEN('Criação'!$K$60)>0)*1+(LEN('Criação'!$K$65)>0)*1+(LEN('Criação'!$K$67)>0)*1+SUMPRODUCT((LEN('Criação'!$K$69:$K$73)>0)*1)+SUMPRODUCT((LEN('Criação'!$K$75:$K$82)>0)*1)+SUMPRODUCT((LEN('Criação'!$K$84:$K$88)>0)*1)+(LEN('Criação'!$K$91)>0)*1+SUMPRODUCT((LEN('Criação'!$K$97:$K$99)>0)*1)+SUMPRODUCT((LEN('Criação'!$K$107:$K$111)>0)*1)+SUMPRODUCT((LEN('Criação'!$K$114:$K$115)>0)*1)+SUMPRODUCT((LEN('Criação'!$K$117:$K$118)>0)*1) | C11: =IFERROR(INDEX('Criação'!$K$6:$K$10,MATCH("?*",'Criação'!$K$6:$K$10,0)),IFERROR(INDEX('Criação'!$K$20:$K$22,MATCH("?*",'Criação'!$K$20:$K$22,0)),IFERROR(INDEX('Criação'!$K$25:$K$28,MATCH("?*",'Criação'!$K$25:$K$28,0)),IFERROR(INDEX('Criação'!$K$33,MATCH("?*",'Criação'!$K$33,0)),IFERROR(INDEX('Criação'!$K$44:$K$51,MATCH("?*",'Criação'!$K$44:$K$51,0)),IFERROR(INDEX('Criação'!$K$54,MATCH("?*",'Criação'!$K$54,0)),IFERROR(INDEX('Criação'!$K$60,MATCH("?*",'Criação'!$K$60,0)),IFERROR(INDEX('Criação'!$K$65,MATCH("?*",'Criação'!$K$65,0)),IFERROR(INDEX('Criação'!$K$67,MATCH("?*",'Criação'!$K$67,0)),IFERROR(INDEX('Criação'!$K$69:$K$73,MATCH("?*",'Criação'!$K$69:$K$73,0)),IFERROR(INDEX('Criação'!$K$75:$K$82,MATCH("?*",'Criação'!$K$75:$K$82,0)),IFERROR(INDEX('Criação'!$K$84:$K$88,MATCH("?*",'Criação'!$K$84:$K$88,0)),IFERROR(INDEX('Criação'!$K$91,MATCH("?*",'Criação'!$K$91,0)),IFERROR(INDEX('Criação'!$K$97:$K$99,MATCH("?*",'Criação'!$K$97:$K$99,0)),IFERROR(INDEX('Criação'!$K$107:$K$111,MATCH("?*",'Criação'!$K$107:$K$111,0)),IFERROR(INDEX('Criação'!$K$114:$K$115,MATCH("?*",'Criação'!$K$114:$K$115,0)),IFERROR(INDEX('Criação'!$K$117:$K$118,MATCH("?*",'Criação'!$K$117:$K$118,0)),"")))))))))))))))))
A12: Em Jogo | B12: =SUMPRODUCT((LEN('Em Jogo'!$N$2:$N$20)>0)*1)+SUMPRODUCT((LEN('Em Jogo'!$N$33:$N$40)>0)*1) | C12: =IFERROR(INDEX('Em Jogo'!$N$2:$N$20,MATCH("?*",'Em Jogo'!$N$2:$N$20,0)),IFERROR(INDEX('Em Jogo'!$N$33:$N$40,MATCH("?*",'Em Jogo'!$N$33:$N$40,0)),""))
A13: Testes | B13: =SUMPRODUCT((LEN('Testes'!$K$40:$K$45)>0)*1)+SUMPRODUCT((LEN('Testes'!$L$16:$L$20)>0)*1)+SUMPRODUCT((LEN('Testes'!$L$22:$L$29)>0)*1)+SUMPRODUCT((LEN('Testes'!$L$31:$L$35)>0)*1) | C13: =IFERROR(INDEX('Testes'!$K$40:$K$45,MATCH("?*",'Testes'!$K$40:$K$45,0)),IFERROR(INDEX('Testes'!$L$16:$L$20,MATCH("?*",'Testes'!$L$16:$L$20,0)),IFERROR(INDEX('Testes'!$L$22:$L$29,MATCH("?*",'Testes'!$L$22:$L$29,0)),IFERROR(INDEX('Testes'!$L$31:$L$35,MATCH("?*",'Testes'!$L$31:$L$35,0)),""))))
A14: Habilidades | B14: =SUMPRODUCT((LEN('Habilidades'!$I$12:$I$19)>0)*1)+(LEN('Habilidades'!$K$54)>0)*1+SUMPRODUCT((LEN('Habilidades'!$K$57:$K$58)>0)*1)+SUMPRODUCT((LEN('Habilidades'!$L$7:$L$8)>0)*1)+SUMPRODUCT((LEN('Habilidades'!$L$55:$L$56)>0)*1)+(LEN('Habilidades'!$L$59)>0)*1 | C14: =IFERROR(INDEX('Habilidades'!$I$12:$I$19,MATCH("?*",'Habilidades'!$I$12:$I$19,0)),IFERROR(INDEX('Habilidades'!$K$54,MATCH("?*",'Habilidades'!$K$54,0)),IFERROR(INDEX('Habilidades'!$K$57:$K$58,MATCH("?*",'Habilidades'!$K$57:$K$58,0)),IFERROR(INDEX('Habilidades'!$L$7:$L$8,MATCH("?*",'Habilidades'!$L$7:$L$8,0)),IFERROR(INDEX('Habilidades'!$L$55:$L$56,MATCH("?*",'Habilidades'!$L$55:$L$56,0)),IFERROR(INDEX('Habilidades'!$L$59,MATCH("?*",'Habilidades'!$L$59,0)),""))))))
A15: Caminho | B15: =SUMPRODUCT((LEN('Caminho'!$K$27:$K$36)>0)*1)+SUMPRODUCT((LEN('Caminho'!$K$54:$K$58)>0)*1)+SUMPRODUCT((LEN('Caminho'!$K$60:$K$67)>0)*1)+SUMPRODUCT((LEN('Caminho'!$K$69:$K$73)>0)*1)+SUMPRODUCT((LEN('Caminho'!$K$75:$K$78)>0)*1)+SUMPRODUCT((LEN('Caminho'!$K$95:$K$96)>0)*1) | C15: =IFERROR(INDEX('Caminho'!$K$27:$K$36,MATCH("?*",'Caminho'!$K$27:$K$36,0)),IFERROR(INDEX('Caminho'!$K$54:$K$58,MATCH("?*",'Caminho'!$K$54:$K$58,0)),IFERROR(INDEX('Caminho'!$K$60:$K$67,MATCH("?*",'Caminho'!$K$60:$K$67,0)),IFERROR(INDEX('Caminho'!$K$69:$K$73,MATCH("?*",'Caminho'!$K$69:$K$73,0)),IFERROR(INDEX('Caminho'!$K$75:$K$78,MATCH("?*",'Caminho'!$K$75:$K$78,0)),IFERROR(INDEX('Caminho'!$K$95:$K$96,MATCH("?*",'Caminho'!$K$95:$K$96,0)),""))))))
A16: Equipamento | B16: =SUMPRODUCT((LEN('Equipamento'!$I$45:$I$47)>0)*1)+(LEN('Equipamento'!$K$8)>0)*1+(LEN('Equipamento'!$K$18)>0)*1+(LEN('Equipamento'!$K$21)>0)*1+(LEN('Equipamento'!$K$58)>0)*1+SUMPRODUCT((LEN('Equipamento'!$K$60:$K$69)>0)*1)+SUMPRODUCT((LEN('Equipamento'!$K$71:$K$80)>0)*1)+(LEN('Equipamento'!$K$84)>0)*1+SUMPRODUCT((LEN('Equipamento'!$K$86:$K$96)>0)*1)+SUMPRODUCT((LEN('Equipamento'!$L$19:$L$20)>0)*1)+SUMPRODUCT((LEN('Equipamento'!$L$22:$L$24)>0)*1)+SUMPRODUCT((LEN('Equipamento'!$L$36:$L$41)>0)*1)+(LEN('Equipamento'!$L$48)>0)*1 | C16: =IFERROR(INDEX('Equipamento'!$I$45:$I$47,MATCH("?*",'Equipamento'!$I$45:$I$47,0)),IFERROR(INDEX('Equipamento'!$K$8,MATCH("?*",'Equipamento'!$K$8,0)),IFERROR(INDEX('Equipamento'!$K$18,MATCH("?*",'Equipamento'!$K$18,0)),IFERROR(INDEX('Equipamento'!$K$21,MATCH("?*",'Equipamento'!$K$21,0)),IFERROR(INDEX('Equipamento'!$K$58,MATCH("?*",'Equipamento'!$K$58,0)),IFERROR(INDEX('Equipamento'!$K$60:$K$69,MATCH("?*",'Equipamento'!$K$60:$K$69,0)),IFERROR(INDEX('Equipamento'!$K$71:$K$80,MATCH("?*",'Equipamento'!$K$71:$K$80,0)),IFERROR(INDEX('Equipamento'!$K$84,MATCH("?*",'Equipamento'!$K$84,0)),IFERROR(INDEX('Equipamento'!$K$86:$K$96,MATCH("?*",'Equipamento'!$K$86:$K$96,0)),IFERROR(INDEX('Equipamento'!$L$19:$L$20,MATCH("?*",'Equipamento'!$L$19:$L$20,0)),IFERROR(INDEX('Equipamento'!$L$22:$L$24,MATCH("?*",'Equipamento'!$L$22:$L$24,0)),IFERROR(INDEX('Equipamento'!$L$36:$L$41,MATCH("?*",'Equipamento'!$L$36:$L$41,0)),IFERROR(INDEX('Equipamento'!$L$48,MATCH("?*",'Equipamento'!$L$48,0)),"")))))))))))))
A17: Progressão | B17: =SUMPRODUCT((LEN('Progressão'!$H$57:$H$62)>0)*1)+SUMPRODUCT((LEN('Progressão'!$I$67:$I$70)>0)*1) | C17: =IFERROR(INDEX('Progressão'!$H$57:$H$62,MATCH("?*",'Progressão'!$H$57:$H$62,0)),IFERROR(INDEX('Progressão'!$I$67:$I$70,MATCH("?*",'Progressão'!$I$67:$I$70,0)),""))
A18: Total | B18: =SUM(B11:B17) | C18: =IF(B18=0,"Nenhum aviso: a ficha está conferida.","Abra a aba indicada e leia a coluna Aviso (na Em Jogo, a linha 13).")
A19: Células com erro na ficha | B19: =SUM($B$21:$K$21) | C19: =IF($B$19=0,"Nenhuma célula com erro.","O Google leu como fórmula um texto que começa com +, - ou =. Procure a célula com erro na aba indicada abaixo (o aviso da linha diz o que fazer), apague e escreva de novo com um apóstrofo (') na frente, ou escolha de novo na lista.")
A20: Erros por aba | B20: Início | C20: Criação | D20: Em Jogo | E20: Testes | F20: Habilidades | G20: Caminho | H20: Equipamento | I20: Progressão | J20: Regras Rápidas | K20: Dados
A21: Células com erro | B21: =SUMPRODUCT(ISERROR($A$1:$L$18)*1)+SUMPRODUCT(ISERROR($A$22:$L$53)*1) | C21: =SUMPRODUCT(ISERROR('Criação'!$A$1:$T$127)*1) | D21: =SUMPRODUCT(ISERROR('Em Jogo'!$A$1:$AP$44)*1) | E21: =SUMPRODUCT(ISERROR('Testes'!$A$1:$O$47)*1) | F21: =SUMPRODUCT(ISERROR('Habilidades'!$A$1:$AF$63)*1) | G21: =SUMPRODUCT(ISERROR('Caminho'!$A$1:$T$96)*1) | H21: =SUMPRODUCT(ISERROR('Equipamento'!$A$1:$AM$97)*1) | I21: =SUMPRODUCT(ISERROR('Progressão'!$A$1:$W$88)*1) | J21: =SUMPRODUCT(ISERROR('Regras Rápidas'!$A$1:$L$119)*1) | K21: =SUMPRODUCT(ISERROR('Dados'!$A$1:$AT$601)*1)
A23: Como usar em 6 passos
A24: 1. Criação: preencha as células amarelas de cima para baixo — são os 12 passos do capítulo 03.
A25: 2. Caminho: escolha as Bênçãos nos slots liberados (e monte o Memoespírito, se for A Recordação).
A26: 3. Habilidades: escreva as suas Habilidades e a Ultimate; a ficha calcula dados, média, PH e rolagem.
A27: 4. Equipamento: Cone de Luz, Relíquias, Conjuntos, arma secundária, inventário e Créditos.
A28: 5. Progressão: a cada nível, mude o Nível atual na Criação e preencha os aumentos e as Ressonâncias.
A29: 6. Em Jogo: na mesa, use só esta aba — PV, Energia, PH, condições, usos e a calculadora de dano.
A31: Legenda de cores (a cor nunca é o único sinal: o texto diz)
A32: Entrada (preencha) | B32: Fundo amarelo com borda: é você quem preenche. Toda entrada sai vazia no arquivo.
A33: Calculada (automático) | B33: Fundo azul-claro: fórmula. Não edite (veja a proteção abaixo).
A34: Aviso | B34: Texto vermelho em fundo rosa: alguma regra do livro não fechou. O texto diz o quê.
A35: Título de bloco | B35: Faixa azul-escura: começo de um bloco, com o capítulo do livro.
A36: Não se aplica | B36: Cinza: não vale para o seu personagem (ou é coluna auxiliar).
A38: Como importar no Google Planilhas
A39: 1. Envie o arquivo .xlsx para o seu Google Drive.
A40: 2. Clique com o botão direito no arquivo → Abrir com → Planilhas Google.
A41: 3. No Planilhas: Arquivo → Salvar como Planilhas Google. Use essa cópia (a original continua .xlsx).
A42: 4. Confira o Painel de avisos acima: com a ficha em branco ele mostra zero avisos.
A43: 5. Para esconder a aba Dados: clique com o botão direito na aba Dados → Ocultar página. Não apague a aba Dados: as fórmulas leem dela.
A45: Como proteger as fórmulas (proteção nativa do Google, sem senha)
A46: 1. Dados → Proteger páginas e intervalos → Adicionar uma página ou um intervalo.
A47: 2. Escolha a aba (ou os intervalos calculados) e marque Exceto certas células para deixar as amarelas livres.
A48: 3. Definir permissões → Mostrar um aviso ao editar este intervalo → Concluído.
A49: Assim ninguém apaga uma fórmula sem querer: o Google avisa antes de editar.
A51: O que a ficha não faz (de propósito)
... A53: PV atual é entrada direta: use a calculadora de dano da aba Em Jogo e copie o PV novo. A variante de PV rolado não é calculada (veja Regras Rápidas).

Sheet Criação
A1: Criação — Explorando Galáxias v1.2
A2: Legenda: | B2: Entrada (preencha) | C2: Calculada (automático) | E2: Aviso (texto em vermelho) | G2: Título de bloco | H2: Cabeçalho de coluna | I2: Rótulo da linha | J2: Linha alternada (outro tom) | L2: Não se aplica
A3: Os 12 passos do capítulo 03, de cima para baixo.
N4: Listas auxiliares
A5: Personagem
A6: Nome do personagem | K6: =IF(T6>0,"O Google leu como fórmula: digite de novo com ' na frente.","") | Q6: =IF(ISERROR($B$6),"",IF(ISBLANK($B$6),"",$B$6)) | T6: =ISERROR($B$6)*1
A7: Jogador | K7: =IF(T7>0,"O Google leu como fórmula: digite de novo com ' na frente.","") | T7: =ISERROR($B$7)*1
A8: Nível atual (1 a 20) | C8: ="Usado nas contas: nível "&$A$14 | K8: =IF(T8>0,"O Google leu como fórmula: digite de novo com ' na frente.",IF($Q$8="","",IF(ISNUMBER($Q$8),IF(OR($Q$8<1,$Q$8>20),"Nível fora de 1 a 20: a ficha conta com o nível "&$A$14,IF($Q$8<>INT($Q$8),"Nível precisa ser inteiro: a ficha conta com o nível "&$A$14,"")),"Nível precisa ser um número de 1 a 20: a ficha conta com o nível 1"))) | Q8: =IF(ISERROR($B$8),"",IF(ISBLANK($B$8),"",$B$8)) | T8: =ISERROR($B$8)*1
A9: Nº de jogadores na mesa | C9: ="PH do grupo: máximo "&$E$16&", começa o combate com "&$F$16 | K9: =IF(T9>0,"O Google leu como fórmula: digite de novo com ' na frente.",IF($Q$9="","",IF(ISNUMBER($Q$9),IF(OR($Q$9<1,$Q$9>6),"Nº de jogadores fora de 1 a 6: a ficha conta com "&$B$17,IF(OR($Q$9<3,$Q$9>6),"Fora da tabela do livro (3 a 6 jogadores): o PH segue a mesma regra","")),"Nº de jogadores precisa ser um número de 1 a 6"))) | Q9: =IF(ISERROR($B$9),"",IF(ISBLANK($B$9),"",$B$9)) | T9: =ISERROR($B$9)*1
A10: Método de atributos (o Mestre escolhe) | C10: =IF($Q$10="","Array oficial (15, 14, 13, 12, 10, 8) ou Compra de Pontos (28)",IF($Q$10="Array oficial","Distribua 15, 14, 13, 12, 10 e 8, um em cada Atributo","Todos começam em 8; gaste até 28 pontos")) | K10: =IF(T10>0,"O Google leu como fórmula: escolha de novo na lista.",IF($Q$10="","",IF(COUNTIF('Dados'!$AH$6:$AH$7,$Q$10)=0,"Método fora da lista",""))) | Q10: =IF(ISERROR($B$10),"",IF(ISBLANK($B$10),"",$B$10)) | T10: =ISERROR($B$10)*1
A12: Números do seu nível (automático) — 26.2 a 26.6
A13: Nível usado | B13: Faixa (1 a 5) | C13: Eficiência | D13: Eficácia | E13: Slots de Eficácia em Perícias | F13: Slots de Eficácia em Testes de Resistência | G13: Especialização de Combate | H13: Teto de RD | I13: Teto de PV temporários | J13: Teto de bônus somado | K13: Teto de penalidade somada | L13: Bênçãos possuídas
A14: =IF(ISNUMBER($Q$8),MAX(1,MIN(20,INT($Q$8))),1) | B14: =INT(($A$14-1)/4)+1 | C14: =2+INT(($A$14-1)/3) | D14: =2*$C$14 | E14: =INDEX('Dados'!$C$265:$C$284,$A$14) | F14: =INDEX('Dados'!$D$265:$D$284,$A$14) | G14: =INDEX('Dados'!$K$265:$K$284,$A$14) | H14: =INDEX('Dados'!$L$265:$L$284,$A$14) | I14: =3*$C$14 | J14: =IF($A$14<=9,3,IF($A$14<=15,4,5)) | K14: =-$J$14 | L14: =INDEX('Dados'!$E$265:$E$284,$A$14)
A15: Habilidades conhecidas | B15: Nível máx. de Habilidade | C15: Reescreve 1 Habilidade por nível | D15: Dados de Ataque Básico | E15: PH do grupo: máximo | F15: PH do grupo: início | G15: PH por Ataque Básico que acerta | H15: Ultimate: Nível equivalente | I15: Cone de Luz: Nível máximo | J15: Tier de Relíquia (1 a 4) | K15: Pontos do Memoespírito | L15: DT para descobrir Fraqueza
A16: =INDEX('Dados'!$F$265:$F$284,$A$14) | B16: =INDEX('Dados'!$H$265:$H$284,$A$14) | C16: =INDEX('Dados'!$G$265:$G$284,$A$14) | D16: =INDEX('Dados'!$J$265:$J$284,$A$14) | E16: =1+$B$17+IF($A$14>=17,2,IF($A$14>=9,1,0)) | F16: =$E$16-2 | G16: =IF($A$14<=8,1,2) | H16: =INDEX('Dados'!$B$333:$B$337,$B$14) | I16: =$B$14 | J16: =IF($A$14<=6,1,IF($A$14<=12,2,IF($A$14<=17,3,4))) | K16: =12+INT($A$14/2) | L16: =INDEX('Dados'!$B$397:$B$401,$B$14)
A17: Nº de jogadores usado (vazio = 4) | B17: =IF(ISNUMBER($Q$9),MAX(1,MIN(6,INT($Q$9))),4) | C17: Aumento de Atributo neste nível? | E17: =INDEX('Dados'!$I$265:$I$284,$A$14)
A19: Passo 1 — Conceito e Propósito de Vida
A20: Quem é esse sujeito? (conceito em uma frase) | K20: =IF(T20>0,"O Google leu como fórmula: digite de novo com ' na frente.","") | T20: =ISERROR($B$20)*1
A21: Propósito de Vida (objetivo de longo prazo) | K21: =IF(T21>0,"O Google leu como fórmula: digite de novo com ' na frente.","") | T21: =ISERROR($B$21)*1
A22: Em que você acredita (recarrega o Esforço; só Humano) | K22: =IF(T22>0,"O Google leu como fórmula: digite de novo com ' na frente.",IF(AND($Q$25<>"Humano",LEN($Q$22)>0),"O Esforço é traço do Humano: esta linha só vale para Humano","")) | Q22: =IF(ISERROR($B$22),"",IF(ISBLANK($B$22),"",$B$22)) | T22: =ISERROR($B$22)*1
A24: Passo 2 — Raça (capítulo 05)
A25: Raça | C25: =IF($Q$25="","Escolha a Raça",IF($Q$25="Humano",IF($Q$26="Dois Atributos (+1 cada)","Bônus racial: +1 em "&IF($Q$27="","?",$Q$27)&" e +1 em "&IF($Q$28="","?",$Q$28),IF($Q$27="","Escolha onde vai o +2 (qualquer Atributo)","Bônus racial: +2 em "&$Q$27)),IF($O$25="","Raça fora da lista do capítulo 05",IF($Q$26="Dois Atributos (+1 cada)","Bônus racial: +1 em "&$O$25&" e +1 em "&$O$26,IF($O$27="","Escolha onde vai o +2: "&$O$25&" ou "&$O$26,"Bônus racial: +2 em "&$O$27))))) | K25: =IF(T25>0,"O Google leu como fórmula: escolha de novo na lista.",IF($Q$25="","",IF(COUNTIF('Dados'!$O$6:$O$12,$Q$25)=0,"Raça fora da lista do capítulo 05",""))) | N25: =IF($Q$25="Humano",INDEX('Dados'!$Q$6:$Q$11,1),$O$25) | O25: =IF($Q$25="","",IFERROR(""&INDEX('Dados'!$D$7:$D$13,MATCH($Q$25,'Dados'!$A$7:$A$13,0)),"")) | Q25: =IF(ISERROR($B$25),"",IF(ISBLANK($B$25),"",$B$25)) | T25: =ISERROR($B$25)*1
A26: Bônus racial: +2 em um, ou +1 em cada | C26: Vale para todas as Raças. Com +1 em cada, os dois Atributos são os da sua Raça — o Humano escolhe entre os seis. | K26: =IF(T26>0,"O Google leu como fórmula: escolha de novo na lista.",IF(AND($Q$26="Dois Atributos (+1 cada)",$Q$25<>"",$Q$25<>"Humano",OR($Q$27<>"",$Q$28<>"")),"Com +1 em cada, os dois Atributos são os da sua Raça: não precisa escolher","")) | N26: =IF($Q$25="Humano",INDEX('Dados'!$Q$6:$Q$11,2),$O$26) | O26: =IF($Q$25="","",IFERROR(""&INDEX('Dados'!$E$7:$E$13,MATCH($Q$25,'Dados'!$A$7:$A$13,0)),"")) | Q26: =IF(ISERROR($B$26),"",IF(ISBLANK($B$26),"",$B$26)) | T26: =ISERROR($B$26)*1
A27: Atributo do +2 (Humano com Dois Atributos: o 1º) | C27: A lista mostra só as opções da sua Raça. | K27: =IF(T27>0,"O Google leu como fórmula: escolha de novo na lista.",IF(AND($Q$25="Humano",$Q$26="Dois Atributos (+1 cada)",$Q$27<>"",$Q$27=$Q$28),"+1 em dois exige atributos diferentes: contou só um +1",IF(AND($Q$25<>"",$Q$25<>"Humano",$O$25<>"",$Q$27<>"",$O$27=""),"Bônus fora das opções da Raça: "&$O$25&IF($O$26="",""," ou "&$O$26),""))) | N27: =IF($Q$25="Humano",INDEX('Dados'!$Q$6:$Q$11,3),"") | O27: =IF(OR($Q$25="",$Q$25="Humano"),"",IF($O$26="",IF(OR($Q$27="",$Q$27=$O$25),$O$25,""),IF(OR($Q$27=$O$25,$Q$27=$O$26),$Q$27,""))) | Q27: =IF(ISERROR($B$27),"",IF(ISBLANK($B$27),"",$B$27)) | T27: =ISERROR($B$27)*1
A28: Atributo 2 (só Humano com Dois Atributos) | K28: =IF(T28>0,"O Google leu como fórmula: escolha de novo na lista.",IF(AND($Q$28<>"",OR($Q$25<>"Humano",$Q$26<>"Dois Atributos (+1 cada)")),"Atributo 2 só vale para Humano com Dois Atributos (+1 cada)","")) | N28: =IF($Q$25="Humano",INDEX('Dados'!$Q$6:$Q$11,4),"") | Q28: =IF(ISERROR($B$28),"",IF(ISBLANK($B$28),"",$B$28)) | T28: =ISERROR($B$28)*1
A29: Traços (resumo) | B29: =IF($Q$25="","",IFERROR(INDEX('Dados'!$F$7:$F$13,MATCH($Q$25,'Dados'!$A$7:$A$13,0)),"")) | N29: =IF($Q$25="Humano",INDEX('Dados'!$Q$6:$Q$11,5),"")
A30: Traços (texto inteiro do livro) | B30: =IF($Q$25="","",IFERROR(INDEX('Dados'!$G$7:$G$13,MATCH($Q$25,'Dados'!$A$7:$A$13,0)),"")) | N30: =IF($Q$25="Humano",INDEX('Dados'!$Q$6:$Q$11,6),"")
A32: Passo 3 — Caminho (capítulo 06)
A33: Caminho | C33: =IF($Q$33="","Escolha o Caminho","Aeon: "&IF($Q$33="","",IFERROR(INDEX('Dados'!$B$91:$B$99,MATCH($Q$33,'Dados'!$A$91:$A$99,0)),""))) | K33: =IF(T33>0,"O Google leu como fórmula: escolha de novo na lista.",IF($Q$33="","",IF(COUNTIF('Dados'!$P$6:$P$14,$Q$33)=0,"Caminho fora da lista do capítulo 06",""))) | Q33: =IF(ISERROR($B$33),"",IF(ISBLANK($B$33),"",$B$33)) | T33: =ISERROR($B$33)*1
A34: Aeon | B34: =IF($Q$33="","",IFERROR(INDEX('Dados'!$B$91:$B$99,MATCH($Q$33,'Dados'!$A$91:$A$99,0)),""))
A35: A ideia, em uma frase | B35: =IF($Q$33="","",IFERROR(INDEX('Dados'!$C$91:$C$99,MATCH($Q$33,'Dados'!$A$91:$A$99,0)),""))
A36: Índice de vitalidade N (entra no PV) | B36: =IF($Q$33="",0,IFERROR(INDEX('Dados'!$J$91:$J$99,MATCH($Q$33,'Dados'!$A$91:$A$99,0)),0))
A37: Bônus de Velocidade do Caminho | B37: =IF($Q$33="",0,IFERROR(INDEX('Dados'!$K$91:$K$99,MATCH($Q$33,'Dados'!$A$91:$A$99,0)),0))
A38: As 3 Perícias do Caminho (Eficiência de graça) | B38: =IF($Q$33="","",IFERROR(INDEX('Dados'!$G$91:$G$99,MATCH($Q$33,'Dados'!$A$91:$A$99,0)),"")) | D38: =IF($Q$33="","",IFERROR(INDEX('Dados'!$H$91:$H$99,MATCH($Q$33,'Dados'!$A$91:$A$99,0)),"")) | F38: =IF($Q$33="","",IFERROR(INDEX('Dados'!$I$91:$I$99,MATCH($Q$33,'Dados'!$A$91:$A$99,0)),""))
A39: Atributo de Habilidade que o Caminho permite | B39: =IF($Q$33="","",IFERROR(INDEX('Dados'!$D$91:$D$99,MATCH($Q$33,'Dados'!$A$91:$A$99,0)),""))
A40: Recurso próprio (detalhes na aba Caminho) | B40: =IF($Q$33="","",IFERROR(INDEX('Dados'!$L$91:$L$99,MATCH($Q$33,'Dados'!$A$91:$A$99,0)),""))
A42: Passo 4 — Atributos (teto 15 antes da Raça; teto 20 sempre)
A43: Atributo | B43: Distribuído (preencha) | C43: Raça (automático) | D43: Aumentos (aba Progressão) | E43: Valor atual | F43: Bônus atual | G43: Valor na criação (com Raça) | H43: Bônus na criação | I43: Custo na Compra de Pontos | J43: Valor usado (8 a 20) | K43: Aviso
A44: Poder | C44: =IF($Q$25="Humano",IF($Q$26="Dois Atributos (+1 cada)",($Q$27="Poder")*1+AND($Q$28="Poder",$Q$28<>$Q$27)*1,($Q$27="Poder")*2),IF($Q$26="Dois Atributos (+1 cada)",($O$25="Poder")*1+($O$26="Poder")*1,IF($O$27="Poder",2,0))) | D44: =SUMIF('Progressão'!$U$57:$U$62,"Poder",'Progressão'!$F$57:$F$62)+SUMIF('Progressão'!$V$57:$V$62,"Poder",'Progressão'!$G$57:$G$62) | E44: =MIN(20,$J$44+$C$44+$D$44) | F44: =IF($E$44<15,VLOOKUP($E$44,'Dados'!$A$34:$B$46,2,FALSE),INT(($E$44-15)/2)+3) | G44: =MIN(20,$J$44+$C$44) | H44: =IF($G$44<15,VLOOKUP($G$44,'Dados'!$A$34:$B$46,2,FALSE),INT(($G$44-15)/2)+3) | I44: =IF($Q$10="Compra de Pontos",VLOOKUP(MAX(8,MIN(15,$J$44)),'Dados'!$A$50:$B$57,2,FALSE),"") | J44: =IF(ISNUMBER($Q$44),MAX(8,MIN(20,INT($Q$44))),8) | K44: =IF(T44>0,"O Google leu como fórmula: digite de novo com ' na frente.",IF($Q$44="","",IF(ISNUMBER($Q$44),IF(OR($Q$44<8,$Q$44>20),"Fora de 8 a 20: a ficha conta com "&$J$44&". ","")&IF($Q$44>15,"Acima de 15 antes da Raça. ",""),"Precisa ser um número. "))&IF(AND($D$44>0,$J$44+$C$44+$D$44>20),"Aumento desperdiçado: passou do teto 20.","")) | Q44: =IF(ISERROR($B$44),"",IF(ISBLANK($B$44),"",$B$44)) | T44: =ISERROR($B$44)*1
A45: Agilidade | C45: =IF($Q$25="Humano",IF($Q$26="Dois Atributos (+1 cada)",($Q$27="Agilidade")*1+AND($Q$28="Agilidade",$Q$28<>$Q$27)*1,($Q$27="Agilidade")*2),IF($Q$26="Dois Atributos (+1 cada)",($O$25="Agilidade")*1+($O$26="Agilidade")*1,IF($O$27="Agilidade",2,0))) | D45: =SUMIF('Progressão'!$U$57:$U$62,"Agilidade",'Progressão'!$F$57:$F$62)+SUMIF('Progressão'!$V$57:$V$62,"Agilidade",'Progressão'!$G$57:$G$62) | E45: =MIN(20,$J$45+$C$45+$D$45) | F45: =IF($E$45<15,VLOOKUP($E$45,'Dados'!$A$34:$B$46,2,FALSE),INT(($E$45-15)/2)+3) | G45: =MIN(20,$J$45+$C$45) | H45: =IF($G$45<15,VLOOKUP($G$45,'Dados'!$A$34:$B$46,2,FALSE),INT(($G$45-15)/2)+3) | I45: =IF($Q$10="Compra de Pontos",VLOOKUP(MAX(8,MIN(15,$J$45)),'Dados'!$A$50:$B$57,2,FALSE),"") | J45: =IF(ISNUMBER($Q$45),MAX(8,MIN(20,INT($Q$45))),8) | K45: =IF(T45>0,"O Google leu como fórmula: digite de novo com ' na frente.",IF($Q$45="","",IF(ISNUMBER($Q$45),IF(OR($Q$45<8,$Q$45>20),"Fora de 8 a 20: a ficha conta com "&$J$45&". ","")&IF($Q$45>15,"Acima de 15 antes da Raça. ",""),"Precisa ser um número. "))&IF(AND($D$45>0,$J$45+$C$45+$D$45>20),"Aumento desperdiçado: passou do teto 20.","")) | Q45: =IF(ISERROR($B$45),"",IF(ISBLANK($B$45),"",$B$45)) | T45: =ISERROR($B$45)*1
A46: Vigor | C46: =IF($Q$25="Humano",IF($Q$26="Dois Atributos (+1 cada)",($Q$27="Vigor")*1+AND($Q$28="Vigor",$Q$28<>$Q$27)*1,($Q$27="Vigor")*2),IF($Q$26="Dois Atributos (+1 cada)",($O$25="Vigor")*1+($O$26="Vigor")*1,IF($O$27="Vigor",2,0))) | D46: =SUMIF('Progressão'!$U$57:$U$62,"Vigor",'Progressão'!$F$57:$F$62)+SUMIF('Progressão'!$V$57:$V$62,"Vigor",'Progressão'!$G$57:$G$62) | E46: =MIN(20,$J$46+$C$46+$D$46) | F46: =IF($E$46<15,VLOOKUP($E$46,'Dados'!$A$34:$B$46,2,FALSE),INT(($E$46-15)/2)+3) | G46: =MIN(20,$J$46+$C$46) | H46: =IF($G$46<15,VLOOKUP($G$46,'Dados'!$A$34:$B$46,2,FALSE),INT(($G$46-15)/2)+3) | I46: =IF($Q$10="Compra de Pontos",VLOOKUP(MAX(8,MIN(15,$J$46)),'Dados'!$A$50:$B$57,2,FALSE),"") | J46: =IF(ISNUMBER($Q$46),MAX(8,MIN(20,INT($Q$46))),8) | K46: =IF(T46>0,"O Google leu como fórmula: digite de novo com ' na frente.",IF($Q$46="","",IF(ISNUMBER($Q$46),IF(OR($Q$46<8,$Q$46>20),"Fora de 8 a 20: a ficha conta com "&$J$46&". ","")&IF($Q$46>15,"Acima de 15 antes da Raça. ",""),"Precisa ser um número. "))&IF(AND($D$46>0,$J$46+$C$46+$D$46>20),"Aumento desperdiçado: passou do teto 20.","")) | Q46: =IF(ISERROR($B$46),"",IF(ISBLANK($B$46),"",$B$46)) | T46: =ISERROR($B$46)*1
A47: Sincronia | C47: =IF($Q$25="Humano",IF($Q$26="Dois Atributos (+1 cada)",($Q$27="Sincronia")*1+AND($Q$28="Sincronia",$Q$28<>$Q$27)*1,($Q$27="Sincronia")*2),IF($Q$26="Dois Atributos (+1 cada)",($O$25="Sincronia")*1+($O$26="Sincronia")*1,IF($O$27="Sincronia",2,0))) | D47: =SUMIF('Progressão'!$U$57:$U$62,"Sincronia",'Progressão'!$F$57:$F$62)+SUMIF('Progressão'!$V$57:$V$62,"Sincronia",'Progressão'!$G$57:$G$62) | E47: =MIN(20,$J$47+$C$47+$D$47) | F47: =IF($E$47<15,VLOOKUP($E$47,'Dados'!$A$34:$B$46,2,FALSE),INT(($E$47-15)/2)+3) | G47: =MIN(20,$J$47+$C$47) | H47: =IF($G$47<15,VLOOKUP($G$47,'Dados'!$A$34:$B$46,2,FALSE),INT(($G$47-15)/2)+3) | I47: =IF($Q$10="Compra de Pontos",VLOOKUP(MAX(8,MIN(15,$J$47)),'Dados'!$A$50:$B$57,2,FALSE),"") | J47: =IF(ISNUMBER($Q$47),MAX(8,MIN(20,INT($Q$47))),8) | K47: =IF(T47>0,"O Google leu como fórmula: digite de novo com ' na frente.",IF($Q$47="","",IF(ISNUMBER($Q$47),IF(OR($Q$47<8,$Q$47>20),"Fora de 8 a 20: a ficha conta com "&$J$47&". ","")&IF($Q$47>15,"Acima de 15 antes da Raça. ",""),"Precisa ser um número. "))&IF(AND($D$47>0,$J$47+$C$47+$D$47>20),"Aumento desperdiçado: passou do teto 20.","")) | Q47: =IF(ISERROR($B$47),"",IF(ISBLANK($B$47),"",$B$47)) | T47: =ISERROR($B$47)*1
A48: Discernimento | C48: =IF($Q$25="Humano",IF($Q$26="Dois Atributos (+1 cada)",($Q$27="Discernimento")*1+AND($Q$28="Discernimento",$Q$28<>$Q$27)*1,($Q$27="Discernimento")*2),IF($Q$26="Dois Atributos (+1 cada)",($O$25="Discernimento")*1+($O$26="Discernimento")*1,IF($O$27="Discernimento",2,0))) | D48: =SUMIF('Progressão'!$U$57:$U$62,"Discernimento",'Progressão'!$F$57:$F$62)+SUMIF('Progressão'!$V$57:$V$62,"Discernimento",'Progressão'!$G$57:$G$62) | E48: =MIN(20,$J$48+$C$48+$D$48) | F48: =IF($E$48<15,VLOOKUP($E$48,'Dados'!$A$34:$B$46,2,FALSE),INT(($E$48-15)/2)+3) | G48: =MIN(20,$J$48+$C$48) | H48: =IF($G$48<15,VLOOKUP($G$48,'Dados'!$A$34:$B$46,2,FALSE),INT(($G$48-15)/2)+3) | I48: =IF($Q$10="Compra de Pontos",VLOOKUP(MAX(8,MIN(15,$J$48)),'Dados'!$A$50:$B$57,2,FALSE),"") | J48: =IF(ISNUMBER($Q$48),MAX(8,MIN(20,INT($Q$48))),8) | K48: =IF(T48>0,"O Google leu como fórmula: digite de novo com ' na frente.",IF($Q$48="","",IF(ISNUMBER($Q$48),IF(OR($Q$48<8,$Q$48>20),"Fora de 8 a 20: a ficha conta com "&$J$48&". ","")&IF($Q$48>15,"Acima de 15 antes da Raça. ",""),"Precisa ser um número. "))&IF(AND($D$48>0,$J$48+$C$48+$D$48>20),"Aumento desperdiçado: passou do teto 20.","")) | Q48: =IF(ISERROR($B$48),"",IF(ISBLANK($B$48),"",$B$48)) | T48: =ISERROR($B$48)*1
A49: Presença | C49: =IF($Q$25="Humano",IF($Q$26="Dois Atributos (+1 cada)",($Q$27="Presença")*1+AND($Q$28="Presença",$Q$28<>$Q$27)*1,($Q$27="Presença")*2),IF($Q$26="Dois Atributos (+1 cada)",($O$25="Presença")*1+($O$26="Presença")*1,IF($O$27="Presença",2,0))) | D49: =SUMIF('Progressão'!$U$57:$U$62,"Presença",'Progressão'!$F$57:$F$62)+SUMIF('Progressão'!$V$57:$V$62,"Presença",'Progressão'!$G$57:$G$62) | E49: =MIN(20,$J$49+$C$49+$D$49) | F49: =IF($E$49<15,VLOOKUP($E$49,'Dados'!$A$34:$B$46,2,FALSE),INT(($E$49-15)/2)+3) | G49: =MIN(20,$J$49+$C$49) | H49: =IF($G$49<15,VLOOKUP($G$49,'Dados'!$A$34:$B$46,2,FALSE),INT(($G$49-15)/2)+3) | I49: =IF($Q$10="Compra de Pontos",VLOOKUP(MAX(8,MIN(15,$J$49)),'Dados'!$A$50:$B$57,2,FALSE),"") | J49: =IF(ISNUMBER($Q$49),MAX(8,MIN(20,INT($Q$49))),8) | K49: =IF(T49>0,"O Google leu como fórmula: digite de novo com ' na frente.",IF($Q$49="","",IF(ISNUMBER($Q$49),IF(OR($Q$49<8,$Q$49>20),"Fora de 8 a 20: a ficha conta com "&$J$49&". ","")&IF($Q$49>15,"Acima de 15 antes da Raça. ",""),"Precisa ser um número. "))&IF(AND($D$49>0,$J$49+$C$49+$D$49>20),"Aumento desperdiçado: passou do teto 20.","")) | Q49: =IF(ISERROR($B$49),"",IF(ISBLANK($B$49),"",$B$49)) | T49: =ISERROR($B$49)*1
A50: Conferência do array oficial | B50: =IF($Q$10<>"Array oficial","",IF((ISNUMBER($Q$44)*1+ISNUMBER($Q$45)*1+ISNUMBER($Q$46)*1+ISNUMBER($Q$47)*1+ISNUMBER($Q$48)*1+ISNUMBER($Q$49)*1)<6,"Valores que faltam para fechar o array: "&(6-(ISNUMBER($Q$44)*1+ISNUMBER($Q$45)*1+ISNUMBER($Q$46)*1+ISNUMBER($Q$47)*1+ISNUMBER($Q$48)*1+ISNUMBER($Q$49)*1)),IF(AND(COUNTIF($Q$44:$Q$49,15)=1,COUNTIF($Q$44:$Q$49,14)=1,COUNTIF($Q$44:$Q$49,13)=1,COUNTIF($Q$44:$Q$49,12)=1,COUNTIF($Q$44:$Q$49,10)=1,COUNTIF($Q$44:$Q$49,8)=1),"OK: cada valor usado uma vez","Confira o aviso ao lado"))) | K50: =IF(AND($Q$10="Array oficial",(ISNUMBER($Q$44)*1+ISNUMBER($Q$45)*1+ISNUMBER($Q$46)*1+ISNUMBER($Q$47)*1+ISNUMBER($Q$48)*1+ISNUMBER($Q$49)*1)=6),IF(AND(COUNTIF($Q$44:$Q$49,15)=1,COUNTIF($Q$44:$Q$49,14)=1,COUNTIF($Q$44:$Q$49,13)=1,COUNTIF($Q$44:$Q$49,12)=1,COUNTIF($Q$44:$Q$49,10)=1,COUNTIF($Q$44:$Q$49,8)=1),"","Array oficial: use 15, 14, 13, 12, 10 e 8 uma vez cada. Falta: "&IF(COUNTIF($Q$44:$Q$49,15)=0,"15 ","")&IF(COUNTIF($Q$44:$Q$49,14)=0,"14 ","")&IF(COUNTIF($Q$44:$Q$49,13)=0,"13 ","")&IF(COUNTIF($Q$44:$Q$49,12)=0,"12 ","")&IF(COUNTIF($Q$44:$Q$49,10)=0,"10 ","")&IF(COUNTIF($Q$44:$Q$49,8)=0,"8 ","")&"· Repetido: "&IF(COUNTIF($Q$44:$Q$49,15)>1,"15 ","")&IF(COUNTIF($Q$44:$Q$49,14)>1,"14 ","")&IF(COUNTIF($Q$44:$Q$49,13)>1,"13 ","")&IF(COUNTIF($Q$44:$Q$49,12)>1,"12 ","")&IF(COUNTIF($Q$44:$Q$49,10)>1,"10 ","")&IF(COUNTIF($Q$44:$Q$49,8)>1,"8 ","")),"")
A51: Compra de Pontos: gastos de 28 | B51: =IF($Q$10="Compra de Pontos",SUM($I$44:$I$49),"") | C51: Sobram: | D51: =IF($Q$10="Compra de Pontos",28-SUM($I$44:$I$49),"") | K51: =IF(AND($Q$10="Compra de Pontos",SUM($I$44:$I$49)>28),"Compra de Pontos passou de 28 ("&SUM($I$44:$I$49)&" pontos)","")
A53: Passo 5 — Atributo de Habilidade (fixo pela campanha)
A54: Atributo de Habilidade | C54: Usado: | D54: =IF($N$54="","",IF(AND($Q$54="",$N$55=""),$N$54,IF(AND($Q$54<>"",OR($Q$54=$N$54,$Q$54=$N$55)),$Q$54,""))) | K54: =IF(T54>0,"O Google leu como fórmula: escolha de novo na lista.",IF(AND($N$54<>"",$D$54=""),IF($Q$54="","Escolha o Atributo de Habilidade: "&$N$54&" ou "&$N$55,"Fora do que o Caminho permite: "&$N$54&IF($N$55="",""," ou "&$N$55)),"")) | N54: =IF($Q$33="","",IFERROR(""&INDEX('Dados'!$E$91:$E$99,MATCH($Q$33,'Dados'!$A$91:$A$99,0)),"")) | Q54: =IF(ISERROR($B$54),"",IF(ISBLANK($B$54),"",$B$54)) | T54: =ISERROR($B$54)*1
A55: Bônus do Atributo de Habilidade | B55: =IF($D$54="",0,IFERROR(INDEX($F$44:$F$49,MATCH($D$54,$A$44:$A$49,0)),0)) | N55: =IF($Q$33="","",IFERROR(""&INDEX('Dados'!$F$91:$F$99,MATCH($Q$33,'Dados'!$A$91:$A$99,0)),""))
A56: DT das suas Habilidades (8 + Bônus + Eficiência) | B56: =8+$B$55+$C$14
A57: Teste de Ataque das Habilidades e da Ultimate | B57: =$B$55+$C$14+$G$14+$B$125 | C57: ="d20"&IF($B$57>=0,"+","")&$B$57 | D57: Bônus + Eficiência + Especialização + equipamento (aba Equipamento)
A59: Passo 6 — Elemento (capítulo 20)
A60: Elemento | C60: Suas Habilidades e a Ultimate causam dano deste Elemento. | K60: =IF(T60>0,"O Google leu como fórmula: escolha de novo na lista.",IF($Q$60="","",IF(COUNTIF('Dados'!$R$6:$R$12,$Q$60)=0,"Elemento fora da lista do capítulo 20",""))) | Q60: =IF(ISERROR($B$60),"",IF(ISBLANK($B$60),"",$B$60)) | T60: =ISERROR($B$60)*1
A61: Efeito de Quebra | B61: =IF($Q$60="","",IFERROR(INDEX('Dados'!$H$381:$H$387,MATCH($Q$60,'Dados'!$A$381:$A$387,0)),""))
A62: Dano de Quebra (20.5) | B62: =IF($Q$60="","",IFERROR(IF(INDEX('Dados'!$E$381:$E$387,MATCH($Q$60,'Dados'!$A$381:$A$387,0))<=0,""&INDEX('Dados'!$G$381:$G$387,MATCH($Q$60,'Dados'!$A$381:$A$387,0))*$C$14,INDEX('Dados'!$E$381:$E$387,MATCH($Q$60,'Dados'!$A$381:$A$387,0))&"d"&INDEX('Dados'!$F$381:$F$387,MATCH($Q$60,'Dados'!$A$381:$A$387,0))&IF(INDEX('Dados'!$G$381:$G$387,MATCH($Q$60,'Dados'!$A$381:$A$387,0))*$C$14>0,"+"&INDEX('Dados'!$G$381:$G$387,MATCH($Q$60,'Dados'!$A$381:$A$387,0))*$C$14,IF(INDEX('Dados'!$G$381:$G$387,MATCH($Q$60,'Dados'!$A$381:$A$387,0))*$C$14<0,""&INDEX('Dados'!$G$381:$G$387,MATCH($Q$60,'Dados'!$A$381:$A$387,0))*$C$14,""))),"")) | C62: média | D62: =IF($Q$60="","",IFERROR(INT(INDEX('Dados'!$E$381:$E$387,MATCH($Q$60,'Dados'!$A$381:$A$387,0))*(INDEX('Dados'!$F$381:$F$387,MATCH($Q$60,'Dados'!$A$381:$A$387,0))+1)/2)+INDEX('Dados'!$G$381:$G$387,MATCH($Q$60,'Dados'!$A$381:$A$387,0))*$C$14,""))
A64: Passo 7 — Perícias (3 do Caminho + 2 + Bônus de Sincronia escolhidas, mínimo 2)
A65: Sintonia usa (fixo na criação) | C65: Usado: | D65: =IF($Q$65="Sincronia","Sincronia","Discernimento") | K65: =IF(T65>0,"O Google leu como fórmula: escolha de novo na lista.","") | Q65: =IF(ISERROR($B$65),"",IF(ISBLANK($B$65),"",$B$65)) | T65: =ISERROR($B$65)*1
A66: Perícias escolhidas permitidas (Sincronia da criação; Humano +1) | B66: =MAX(2,2+$H$47)+IF($Q$25="Humano",1,0)
A67: Escolhidas / com Eficiência no total | B67: =COUNTIF($S$69:$S$88,"Sim") | C67: com Eficiência: | D67: =COUNTIF($E$69:$E$88,"Sim") | K67: =IF($B$67>$B$66,"Perícias escolhidas acima do permitido ("&$B$66&"): as últimas ficam sem Eficiência","")
A68: Perícia (Poder, Agilidade e Vigor) | B68: Atributo | C68: Do Caminho? | D68: Escolhida (preencha Sim) | E68: Eficiência (automático) | F68: Origem | K68: Aviso
A69: Atletismo | B69: =INDEX('Dados'!$B$61:$B$78,1) | C69: =IF(OR($B$38="Atletismo",$D$38="Atletismo",$F$38="Atletismo"),"Sim","Não") | E69: =IF(OR($C$69="Sim",AND($S$69="Sim",COUNTIF($S$69,"Sim")<=$B$66)),"Sim","Não") | F69: =IF($C$69="Sim","Caminho",IF($E$69="Sim","Escolhida","")) | K69: =IF(T69>0,"O Google leu como fórmula: escolha de novo na lista.",IF($S$69<>"Sim","",IF($C$69="Sim","Já vem do Caminho: escolha outra",IF($E$69="Não","Acima do permitido ("&$B$66&"): esta fica sem Eficiência","")))) | S69: =IF(ISERROR($D$69),"",IF(ISBLANK($D$69),"",$D$69)) | T69: =ISERROR($D$69)*1
A70: Acrobacia | B70: =INDEX('Dados'!$B$61:$B$78,2) | C70: =IF(OR($B$38="Acrobacia",$D$38="Acrobacia",$F$38="Acrobacia"),"Sim","Não") | E70: =IF(OR($C$70="Sim",AND($S$70="Sim",COUNTIF($S$69:$S$70,"Sim")<=$B$66)),"Sim","Não") | F70: =IF($C$70="Sim","Caminho",IF($E$70="Sim","Escolhida","")) | K70: =IF(T70>0,"O Google leu como fórmula: escolha de novo na lista.",IF($S$70<>"Sim","",IF($C$70="Sim","Já vem do Caminho: escolha outra",IF($E$70="Não","Acima do permitido ("&$B$66&"): esta fica sem Eficiência","")))) | S70: =IF(ISERROR($D$70),"",IF(ISBLANK($D$70),"",$D$70)) | T70: =ISERROR($D$70)*1
A71: Furtividade | B71: =INDEX('Dados'!$B$61:$B$78,3) | C71: =IF(OR($B$38="Furtividade",$D$38="Furtividade",$F$38="Furtividade"),"Sim","Não") | E71: =IF(OR($C$71="Sim",AND($S$71="Sim",COUNTIF($S$69:$S$71,"Sim")<=$B$66)),"Sim","Não") | F71: =IF($C$71="Sim","Caminho",IF($E$71="Sim","Escolhida","")) | K71: =IF(T71>0,"O Google leu como fórmula: escolha de novo na lista.",IF($S$71<>"Sim","",IF($C$71="Sim","Já vem do Caminho: escolha outra",IF($E$71="Não","Acima do permitido ("&$B$66&"): esta fica sem Eficiência","")))) | S71: =IF(ISERROR($D$71),"",IF(ISBLANK($D$71),"",$D$71)) | T71: =ISERROR($D$71)*1
A72: Pilotagem | B72: =INDEX('Dados'!$B$61:$B$78,4) | C72: =IF(OR($B$38="Pilotagem",$D$38="Pilotagem",$F$38="Pilotagem"),"Sim","Não") | E72: =IF(OR($C$72="Sim",AND($S$72="Sim",COUNTIF($S$69:$S$72,"Sim")<=$B$66)),"Sim","Não") | F72: =IF($C$72="Sim","Caminho",IF($E$72="Sim","Escolhida","")) | K72: =IF(T72>0,"O Google leu como fórmula: escolha de novo na lista.",IF($S$72<>"Sim","",IF($C$72="Sim","Já vem do Caminho: escolha outra",IF($E$72="Não","Acima do permitido ("&$B$66&"): esta fica sem Eficiência","")))) | S72: =IF(ISERROR($D$72),"",IF(ISBLANK($D$72),"",$D$72)) | T72: =ISERROR($D$72)*1
A73: Resistência | B73: =INDEX('Dados'!$B$61:$B$78,5) | C73: =IF(OR($B$38="Resistência",$D$38="Resistência",$F$38="Resistência"),"Sim","Não") | E73: =IF(OR($C$73="Sim",AND($S$73="Sim",COUNTIF($S$69:$S$73,"Sim")<=$B$66)),"Sim","Não") | F73: =IF($C$73="Sim","Caminho",IF($E$73="Sim","Escolhida","")) | K73: =IF(T73>0,"O Google leu como fórmula: escolha de novo na lista.",IF($S$73<>"Sim","",IF($C$73="Sim","Já vem do Caminho: escolha outra",IF($E$73="Não","Acima do permitido ("&$B$66&"): esta fica sem Eficiência","")))) | S73: =IF(ISERROR($D$73),"",IF(ISBLANK($D$73),"",$D$73)) | T73: =ISERROR($D$73)*1
A74: Perícia (Sincronia e Discernimento) | B74: Atributo | C74: Do Caminho? | D74: Escolhida (preencha Sim) | E74: Eficiência (automático) | F74: Origem | K74: Aviso | S74: =IF(ISERROR($D$74),"",IF(ISBLANK($D$74),"",$D$74))
A75: Tecnologia | B75: =INDEX('Dados'!$B$61:$B$78,6) | C75: =IF(OR($B$38="Tecnologia",$D$38="Tecnologia",$F$38="Tecnologia"),"Sim","Não") | E75: =IF(OR($C$75="Sim",AND($S$75="Sim",COUNTIF($S$69:$S$75,"Sim")<=$B$66)),"Sim","Não") | F75: =IF($C$75="Sim","Caminho",IF($E$75="Sim","Escolhida","")) | K75: =IF(T75>0,"O Google leu como fórmula: escolha de novo na lista.",IF($S$75<>"Sim","",IF($C$75="Sim","Já vem do Caminho: escolha outra",IF($E$75="Não","Acima do permitido ("&$B$66&"): esta fica sem Eficiência","")))) | S75: =IF(ISERROR($D$75),"",IF(ISBLANK($D$75),"",$D$75)) | T75: =ISERROR($D$75)*1
A76: Pesquisa | B76: =INDEX('Dados'!$B$61:$B$78,7) | C76: =IF(OR($B$38="Pesquisa",$D$38="Pesquisa",$F$38="Pesquisa"),"Sim","Não") | E76: =IF(OR($C$76="Sim",AND($S$76="Sim",COUNTIF($S$69:$S$76,"Sim")<=$B$66)),"Sim","Não") | F76: =IF($C$76="Sim","Caminho",IF($E$76="Sim","Escolhida","")) | K76: =IF(T76>0,"O Google leu como fórmula: escolha de novo na lista.",IF($S$76<>"Sim","",IF($C$76="Sim","Já vem do Caminho: escolha outra",IF($E$76="Não","Acima do permitido ("&$B$66&"): esta fica sem Eficiência","")))) | S76: =IF(ISERROR($D$76),"",IF(ISBLANK($D$76),"",$D$76)) | T76: =ISERROR($D$76)*1
A77: Ciência | B77: =INDEX('Dados'!$B$61:$B$78,8) | C77: =IF(OR($B$38="Ciência",$D$38="Ciência",$F$38="Ciência"),"Sim","Não") | E77: =IF(OR($C$77="Sim",AND($S$77="Sim",COUNTIF($S$69:$S$77,"Sim")<=$B$66)),"Sim","Não") | F77: =IF($C$77="Sim","Caminho",IF($E$77="Sim","Escolhida","")) | K77: =IF(T77>0,"O Google leu como fórmula: escolha de novo na lista.",IF($S$77<>"Sim","",IF($C$77="Sim","Já vem do Caminho: escolha outra",IF($E$77="Não","Acima do permitido ("&$B$66&"): esta fica sem Eficiência","")))) | S77: =IF(ISERROR($D$77),"",IF(ISBLANK($D$77),"",$D$77)) | T77: =ISERROR($D$77)*1
A78: Mecânica | B78: =INDEX('Dados'!$B$61:$B$78,9) | C78: =IF(OR($B$38="Mecânica",$D$38="Mecânica",$F$38="Mecânica"),"Sim","Não") | E78: =IF(OR($C$78="Sim",AND($S$78="Sim",COUNTIF($S$69:$S$78,"Sim")<=$B$66)),"Sim","Não") | F78: =IF($C$78="Sim","Caminho",IF($E$78="Sim","Escolhida","")) | K78: =IF(T78>0,"O Google leu como fórmula: escolha de novo na lista.",IF($S$78<>"Sim","",IF($C$78="Sim","Já vem do Caminho: escolha outra",IF($E$78="Não","Acima do permitido ("&$B$66&"): esta fica sem Eficiência","")))) | S78: =IF(ISERROR($D$78),"",IF(ISBLANK($D$78),"",$D$78)) | T78: =ISERROR($D$78)*1
A79: Percepção | B79: =INDEX('Dados'!$B$61:$B$78,10) | C79: =IF(OR($B$38="Percepção",$D$38="Percepção",$F$38="Percepção"),"Sim","Não") | E79: =IF(OR($C$79="Sim",AND($S$79="Sim",COUNTIF($S$69:$S$79,"Sim")<=$B$66)),"Sim","Não") | F79: =IF($C$79="Sim","Caminho",IF($E$79="Sim","Escolhida","")) | K79: =IF(T79>0,"O Google leu como fórmula: escolha de novo na lista.",IF($S$79<>"Sim","",IF($C$79="Sim","Já vem do Caminho: escolha outra",IF($E$79="Não","Acima do permitido ("&$B$66&"): esta fica sem Eficiência","")))) | S79: =IF(ISERROR($D$79),"",IF(ISBLANK($D$79),"",$D$79)) | T79: =ISERROR($D$79)*1
A80: Sobrevivência | B80: =INDEX('Dados'!$B$61:$B$78,11) | C80: =IF(OR($B$38="Sobrevivência",$D$38="Sobrevivência",$F$38="Sobrevivência"),"Sim","Não") | E80: =IF(OR($C$80="Sim",AND($S$80="Sim",COUNTIF($S$69:$S$80,"Sim")<=$B$66)),"Sim","Não") | F80: =IF($C$80="Sim","Caminho",IF($E$80="Sim","Escolhida","")) | K80: =IF(T80>0,"O Google leu como fórmula: escolha de novo na lista.",IF($S$80<>"Sim","",IF($C$80="Sim","Já vem do Caminho: escolha outra",IF($E$80="Não","Acima do permitido ("&$B$66&"): esta fica sem Eficiência","")))) | S80: =IF(ISERROR($D$80),"",IF(ISBLANK($D$80),"",$D$80)) | T80: =ISERROR($D$80)*1
A81: Intuição | B81: =INDEX('Dados'!$B$61:$B$78,12) | C81: =IF(OR($B$38="Intuição",$D$38="Intuição",$F$38="Intuição"),"Sim","Não") | E81: =IF(OR($C$81="Sim",AND($S$81="Sim",COUNTIF($S$69:$S$81,"Sim")<=$B$66)),"Sim","Não") | F81: =IF($C$81="Sim","Caminho",IF($E$81="Sim","Escolhida","")) | K81: =IF(T81>0,"O Google leu como fórmula: escolha de novo na lista.",IF($S$81<>"Sim","",IF($C$81="Sim","Já vem do Caminho: escolha outra",IF($E$81="Não","Acima do permitido ("&$B$66&"): esta fica sem Eficiência","")))) | S81: =IF(ISERROR($D$81),"",IF(ISBLANK($D$81),"",$D$81)) | T81: =ISERROR($D$81)*1
A82: Investigação | B82: =INDEX('Dados'!$B$61:$B$78,13) | C82: =IF(OR($B$38="Investigação",$D$38="Investigação",$F$38="Investigação"),"Sim","Não") | E82: =IF(OR($C$82="Sim",AND($S$82="Sim",COUNTIF($S$69:$S$82,"Sim")<=$B$66)),"Sim","Não") | F82: =IF($C$82="Sim","Caminho",IF($E$82="Sim","Escolhida","")) | K82: =IF(T82>0,"O Google leu como fórmula: escolha de novo na lista.",IF($S$82<>"Sim","",IF($C$82="Sim","Já vem do Caminho: escolha outra",IF($E$82="Não","Acima do permitido ("&$B$66&"): esta fica sem Eficiência","")))) | S82: =IF(ISERROR($D$82),"",IF(ISBLANK($D$82),"",$D$82)) | T82: =ISERROR($D$82)*1
A83: Perícia (Presença e Sintonia) | B83: Atributo | C83: Do Caminho? | D83: Escolhida (preencha Sim) | E83: Eficiência (automático) | F83: Origem | K83: Aviso | S83: =IF(ISERROR($D$83),"",IF(ISBLANK($D$83),"",$D$83))
A84: Persuasão | B84: =INDEX('Dados'!$B$61:$B$78,14) | C84: =IF(OR($B$38="Persuasão",$D$38="Persuasão",$F$38="Persuasão"),"Sim","Não") | E84: =IF(OR($C$84="Sim",AND($S$84="Sim",COUNTIF($S$69:$S$84,"Sim")<=$B$66)),"Sim","Não") | F84: =IF($C$84="Sim","Caminho",IF($E$84="Sim","Escolhida","")) | K84: =IF(T84>0,"O Google leu como fórmula: escolha de novo na lista.",IF($S$84<>"Sim","",IF($C$84="Sim","Já vem do Caminho: escolha outra",IF($E$84="Não","Acima do permitido ("&$B$66&"): esta fica sem Eficiência","")))) | S84: =IF(ISERROR($D$84),"",IF(ISBLANK($D$84),"",$D$84)) | T84: =ISERROR($D$84)*1
A85: Intimidação | B85: =INDEX('Dados'!$B$61:$B$78,15) | C85: =IF(OR($B$38="Intimidação",$D$38="Intimidação",$F$38="Intimidação"),"Sim","Não") | E85: =IF(OR($C$85="Sim",AND($S$85="Sim",COUNTIF($S$69:$S$85,"Sim")<=$B$66)),"Sim","Não") | F85: =IF($C$85="Sim","Caminho",IF($E$85="Sim","Escolhida","")) | K85: =IF(T85>0,"O Google leu como fórmula: escolha de novo na lista.",IF($S$85<>"Sim","",IF($C$85="Sim","Já vem do Caminho: escolha outra",IF($E$85="Não","Acima do permitido ("&$B$66&"): esta fica sem Eficiência","")))) | S85: =IF(ISERROR($D$85),"",IF(ISBLANK($D$85),"",$D$85)) | T85: =ISERROR($D$85)*1
A86: Enganação | B86: =INDEX('Dados'!$B$61:$B$78,16) | C86: =IF(OR($B$38="Enganação",$D$38="Enganação",$F$38="Enganação"),"Sim","Não") | E86: =IF(OR($C$86="Sim",AND($S$86="Sim",COUNTIF($S$69:$S$86,"Sim")<=$B$66)),"Sim","Não") | F86: =IF($C$86="Sim","Caminho",IF($E$86="Sim","Escolhida","")) | K86: =IF(T86>0,"O Google leu como fórmula: escolha de novo na lista.",IF($S$86<>"Sim","",IF($C$86="Sim","Já vem do Caminho: escolha outra",IF($E$86="Não","Acima do permitido ("&$B$66&"): esta fica sem Eficiência","")))) | S86: =IF(ISERROR($D$86),"",IF(ISBLANK($D$86),"",$D$86)) | T86: =ISERROR($D$86)*1
A87: Liderança | B87: =INDEX('Dados'!$B$61:$B$78,17) | C87: =IF(OR($B$38="Liderança",$D$38="Liderança",$F$38="Liderança"),"Sim","Não") | E87: =IF(OR($C$87="Sim",AND($S$87="Sim",COUNTIF($S$69:$S$87,"Sim")<=$B$66)),"Sim","Não") | F87: =IF($C$87="Sim","Caminho",IF($E$87="Sim","Escolhida","")) | K87: =IF(T87>0,"O Google leu como fórmula: escolha de novo na lista.",IF($S$87<>"Sim","",IF($C$87="Sim","Já vem do Caminho: escolha outra",IF($E$87="Não","Acima do permitido ("&$B$66&"): esta fica sem Eficiência","")))) | S87: =IF(ISERROR($D$87),"",IF(ISBLANK($D$87),"",$D$87)) | T87: =ISERROR($D$87)*1
A88: Sintonia | B88: =$D$65 | C88: =IF(OR($B$38="Sintonia",$D$38="Sintonia",$F$38="Sintonia"),"Sim","Não") | E88: =IF(OR($C$88="Sim",AND($S$88="Sim",COUNTIF($S$69:$S$88,"Sim")<=$B$66)),"Sim","Não") | F88: =IF($C$88="Sim","Caminho",IF($E$88="Sim","Escolhida","")) | K88: =IF(T88>0,"O Google leu como fórmula: escolha de novo na lista.",IF($S$88<>"Sim","",IF($C$88="Sim","Já vem do Caminho: escolha outra",IF($E$88="Não","Acima do permitido ("&$B$66&"): esta fica sem Eficiência","")))) | S88: =IF(ISERROR($D$88),"",IF(ISBLANK($D$88),"",$D$88)) | T88: =ISERROR($D$88)*1
A90: Passo 8 — As cinco estatísticas: PV, Defesa, Esquiva, RD e Velocidade
A91: Armadura ou Vestimenta | C91: =IF($Q$91="","Sem armadura: Defesa +0",IFERROR("Defesa +"&VLOOKUP($Q$91,'Dados'!$A$480:$I$482,2,FALSE)&" · "&VLOOKUP($Q$91,'Dados'!$A$480:$I$482,3,FALSE),"")) | K91: =IF(T91>0,"O Google leu como fórmula: escolha de novo na lista.",IF($Q$91="","",IF(COUNTIF('Dados'!$S$6:$S$8,$Q$91)=0,"Armadura fora da lista do capítulo 24",""))) | Q91: =IF(ISERROR($B$91),"",IF(ISBLANK($B$91),"",$B$91)) | T91: =ISERROR($B$91)*1
A92: Números da armadura | B92: Defesa | C92: Velocidade | D92: RD | E92: Penalidade em Reflexos e Perícias de Agilidade | F92: Esquiva
A93: (automático, 24.1) | B93: =IFERROR(VLOOKUP($Q$91,'Dados'!$A$480:$I$482,2,FALSE),0) | C93: =IFERROR(VLOOKUP($Q$91,'Dados'!$A$480:$I$482,7,FALSE),0) | D93: =IFERROR(VLOOKUP($Q$91,'Dados'!$A$480:$I$482,8,FALSE),0) | E93: =IFERROR(VLOOKUP($Q$91,'Dados'!$A$480:$I$482,9,FALSE),0) | F93: =IFERROR(VLOOKUP($Q$91,'Dados'!$A$480:$I$482,4,FALSE),"Permitida")
A94: Estatística | B94: Base | C94: Extra (equipamento e Bênçãos) | D94: Total | E94: Como se calcula | K94: Aviso
A95: PV máximos | B95: =25+5*$B$36+3*$F$46+($A$14-1)*(5+$B$36+$F$46) | C95: =$B$121 | D95: =$B$95+$B$121 | E95: 25 + 5 × N + 3 × Bônus de Vigor + (nível - 1) × (5 + N + Bônus de Vigor) — 06.4
A96: Defesa | B96: =10+$F$45+$B$93 | C96: =$B$122 | D96: =$B$96+$B$122 | E96: 10 + Bônus de Agilidade + armadura — 18.4
A97: Esquiva (Reação) | D97: =IF($F$93="Proibida","Proibida (Armadura Pesada)",$D$96+$C$14) | E97: Defesa + Eficiência; proibida com Armadura Pesada | K97: =IF($F$93="Proibida","Armadura Pesada não permite Esquiva","")
A98: RD | B98: =$D$93 | C98: =$B$123 | D98: =MIN($H$14,$B$98+$B$123) | E98: ="Armadura + Bênçãos + equipamento, até o teto de RD ("&$H$14&") — 18.4" | K98: =IF($B$98+$B$123>$H$14,"RD limitada ao teto ("&$H$14&")","")
A99: Velocidade (VEL) | B99: =10+$F$45+$B$37+$C$93 | C99: =$B$124 | D99: =$B$99+$B$124 | E99: 10 + Bônus de Agilidade + Bônus do Caminho + armadura — 19.1 | K99: =IF(OR($D$99<7,$D$99>25),"Velocidade fora de 7 a 25 (19.1)","")
A101: Passos 9 a 11 — Habilidade, Ultimate e Bênção
A102: Passo 9 — Sua primeira Habilidade | B102: =IF(LEN($B$126)=0,"Preencha a Habilidade 1 na aba Habilidades","OK: "&$B$126)
A103: Passo 10 — Sua Ultimate | B103: =IF(LEN($B$127)=0,"Preencha a Ultimate na aba Habilidades","OK: "&$B$127)
A104: Passo 11 — Sua primeira Bênção | B104: =IF(LEN('Caminho'!$Q$27)=0,"Preencha a Bênção do nível 1 na aba Caminho","OK: "&'Caminho'!$Q$27)
A106: Passo 12 — Equipamento, nome e acabamento
A107: Arma: nome e descrição | K107: =IF(T107>0,"O Google leu como fórmula: digite de novo com ' na frente.","") | Q107: =IF(ISERROR($B$107),"",IF(ISBLANK($B$107),"",$B$107)) | T107: =ISERROR($B$107)*1
A108: Categoria da arma (capítulo 18) | C108: =IF($Q$108="","",IFERROR(VLOOKUP($Q$108,'Dados'!$A$464:$J$469,2,FALSE)&" · alcance "&VLOOKUP($Q$108,'Dados'!$A$464:$J$469,5,FALSE)&" · "&VLOOKUP($Q$108,'Dados'!$A$464:$J$469,6,FALSE)&IF(VLOOKUP($Q$108,'Dados'!$A$464:$J$469,10,FALSE)="Sim"," · duas mãos",""),"")) | K108: =IF(T108>0,"O Google leu como fórmula: escolha de novo na lista.",IF($Q$108="","",IF(COUNTIF('Dados'!$T$6:$T$11,$Q$108)=0,"Categoria fora da lista do capítulo 24",""))) | Q108: =IF(ISERROR($B$108),"",IF(ISBLANK($B$108),"",$B$108)) | T108: =ISERROR($B$108)*1
A109: Atributo (só arma Média: Poder ou Agilidade) | C109: Atributo de ataque: | D109: =IF($Q$108="","",IF($Q$108="Média",IF(OR($Q$109="Poder",$Q$109="Agilidade"),$Q$109,"Poder"),IFERROR(VLOOKUP($Q$108,'Dados'!$A$464:$J$469,6,FALSE),""))) | K109: =IF(T109>0,"O Google leu como fórmula: escolha de novo na lista.",IF(AND($Q$109<>"",$Q$108<>"Média"),"O atributo só se escolhe na arma Média",IF(AND($Q$108="Média",$Q$109=""),"Arma Média: escolha Poder ou Agilidade (contando Poder)",""))) | Q109: =IF(ISERROR($B$109),"",IF(ISBLANK($B$109),"",$B$109)) | T109: =ISERROR($B$109)*1
A110: Elemento próprio da arma (vazio = Físico) | C110: Elemento do Ataque Básico: | D110: =IF($Q$110="","Físico",$Q$110) | K110: =IF(T110>0,"O Google leu como fórmula: escolha de novo na lista.",IF($Q$110="","",IF(COUNTIF('Dados'!$R$6:$R$12,$Q$110)=0,"Elemento fora da lista do capítulo 20",""))) | Q110: =IF(ISERROR($B$110),"",IF(ISBLANK($B$110),"",$B$110)) | T110: =ISERROR($B$110)*1
A111: Propriedade especial (no máximo 1) | C111: =IF(OR($Q$111="",$Q$111="Nenhuma"),"",IFERROR(VLOOKUP($Q$111,'Dados'!$A$473:$B$476,2,FALSE),"")) | K111: =IF(T111>0,"O Google leu como fórmula: escolha de novo na lista.",IF($Q$111="","",IF(COUNTIF('Dados'!$V$6:$V$10,$Q$111)=0,"Só uma propriedade especial por arma (24.2): escolha uma da lista",""))) | Q111: =IF(ISERROR($B$111),"",IF(ISBLANK($B$111),"",$B$111)) | T111: =ISERROR($B$111)*1
...

Sheet Em Jogo
A1: Resumo para o Jogador | E1: Recursos (preencha os amarelos) | I1: Calculadora de dano (23.1 e 23.3) | N1: Avisos desta aba (automático; o resumo aparece na linha 13) | P1: Valores auxiliares (automático) | S1: Usos (auxiliar): nome | T1: frequência | U1: entra? | V1: ordem | W1: Perícias (auxiliar) | AC1: Usos (auxiliar): frequência por linha
A2: Nome | B2: =IF(LEN('Criação'!$Q$6)=0,"(sem nome)",""&'Criação'!$Q$6) | E2: PV atual | G2: ="de "&'Criação'!$D$95&IF($Q$3="Sim"," · Morrendo"," · vazio = cheio") | I2: Dano recebido | K2: depois de dados e bônus | N2: =IF(AP2>0,"O Google leu como fórmula: digite de novo com ' na frente.",IF(LEN($AK$2)=0,"",IF(ISNUMBER($AK$2),IF($AK$2>'Criação'!$D$95,"PV atual acima do máximo ("&'Criação'!$D$95&"). ","")&IF($AK$2<0,"PV não fica abaixo de 0 (23.4). ",""),"PV atual precisa ser um número."))) | P2: PV atual usado (vazio = cheio) | Q2: =IF(ISNUMBER($AK$2),MAX(0,INT($AK$2)),'Criação'!$D$95) | S2: ="Descanso Curto" | T2: ="2/dia" | U2: =1 | V2: =IF(U2=1,0+1,0) | W2: Atletismo | X2: =0+IF('Criação'!$E$69="Sim",1,0) | Y2: =IF('Criação'!$E$69="Sim",X2,0) | Z2: ='Testes'!$I$16 | AA2: =IF(LEN('Testes'!$J$16)>0,"Vantagem","") | AB2: =IFERROR(INDEX($AA$2:$AA$19,MATCH(1,$Y$2:$Y$19,0)),"") | AC2: =IFERROR(INDEX($T$2:$T$16,MATCH(1,$V$2:$V$16,0)),"") | AD2: =IF($AF$37="","",IF($AF$37="Sangramento",IF(ISNUMBER($AI$37),MIN(INT('Criação'!$D$95*5/100),3*IF(ISNUMBER($AI$37),$AI$37,0))&" por turno","5% PV, teto 3×Ef"),IF($AF$37="Queimadura","2d6+"&IF(ISNUMBER($AI$37),IF(ISNUMBER($AI$37),$AI$37,0),"Ef"),IF(OR($AF$37="Choque",$AF$37="Aprisionamento"),"1d6+"&IF(ISNUMBER($AI$37),IF(ISNUMBER($AI$37),$AI$37,0),"Ef"),IF(OR($AF$37="Cisalhamento de Vento",$AF$37="Embaraço"),"1d6 por acúmulo",IF($AF$37="Surpreso","casa pulada no 1º Ciclo","—")))))) | AK2: =IF(ISERROR($F$2),"",IF(ISBLANK($F$2),"",$F$2)) | AO2: =IF(ISERROR($J$2),"",IF(ISBLANK($J$2),"",$J$2)) | AP2: =ISERROR($F$2)*1+ISERROR($J$2)*1
A3: Raça · Caminho | B3: =IF('Criação'!$Q$25="","Raça?",'Criação'!$Q$25)&" · "&IF('Criação'!$Q$33="","Caminho?",'Criação'!$Q$33)&" · nível "&'Criação'!$A$14 | E3: Temporários | G3: ="ou Barreira · teto "&'Criação'!$I$14&" · não acumulam" | I3: Contínuo? | K3: Contínuo ignora a RD | N3: =IF(AP3>0,"O Google leu como fórmula: escolha de novo ou digite com ' na frente.",IF(LEN($AK$3)=0,"",IF(ISNUMBER($AK$3),IF($AK$3>'Criação'!$I$14,"PV temporários acima do teto ("&'Criação'!$I$14&", 23.3): conta o teto.",""),"PV temporários precisa ser um número."))) | P3: Morrendo (PV 0) | Q3: =IF($Q$2=0,"Sim","Não") | S3: ="Técnica" | T3: ="2/Desc. Longo" | U3: =1 | V3: =IF(U3=1,MAX($V$2:V2)+1,0) | W3: Acrobacia | X3: =X2+IF('Criação'!$E$70="Sim",1,0) | Y3: =IF('Criação'!$E$70="Sim",X3,0) | Z3: ='Testes'!$I$17 | AA3: =IF(LEN('Testes'!$J$17)>0,"Vantagem","") | AB3: =IFERROR(INDEX($AA$2:$AA$19,MATCH(2,$Y$2:$Y$19,0)),"") | AC3: =IFERROR(INDEX($T$2:$T$16,MATCH(2,$V$2:$V$16,0)),"") | AD3: =IF($AF$38="","",IF($AF$38="Sangramento",IF(ISNUMBER($AI$38),MIN(INT('Criação'!$D$95*5/100),3*IF(ISNUMBER($AI$38),$AI$38,0))&" por turno","5% PV, teto 3×Ef"),IF($AF$38="Queimadura","2d6+"&IF(ISNUMBER($AI$38),IF(ISNUMBER($AI$38),$AI$38,0),"Ef"),IF(OR($AF$38="Choque",$AF$38="Aprisionamento"),"1d6+"&IF(ISNUMBER($AI$38),IF(ISNUMBER($AI$38),$AI$38,0),"Ef"),IF(OR($AF$38="Cisalhamento de Vento",$AF$38="Embaraço"),"1d6 por acúmulo",IF($AF$38="Surpreso","casa pulada no 1º Ciclo","—")))))) | AK3: =IF(ISERROR($F$3),"",IF(ISBLANK($F$3),"",$F$3)) | AO3: =IF(ISERROR($J$3),"",IF(ISBLANK($J$3),"",$J$3)) | AP3: =ISERROR($F$3)*1+ISERROR($J$3)*1
A4: Elemento | B4: =IF('Criação'!$Q$60="","—",'Criação'!$Q$60)&" (Ataque Básico: "&'Criação'!$D$110&")" | E4: Energia | G4: ="0 a 100 · Ultimate pronta: "&IF($Q$22="Sim","Sim","Não ("&'Habilidades'!$G$61&")") | I4: RD aplicada | J4: =IF($AO$3="Sim",0,'Criação'!$D$98) | N4: =IF(AP4>0,"O Google leu como fórmula: digite de novo com ' na frente.",IF(LEN($AK$4)=0,"",IF(ISNUMBER($AK$4),IF($AK$4>100,"Energia acima de 100 é perdida (17.1).","")&IF($AK$4<0,"Energia não fica abaixo de 0.",""),"Energia precisa ser um número."))) | P4: PV temporários usados (teto) | Q4: =IF(ISNUMBER($AK$3),MAX(0,MIN('Criação'!$I$14,INT($AK$3))),0) | S4: ="To na sua mente" | T4: ="2/dia" | U4: =IF('Criação'!$Q$25="Haloviano",1,0) | V4: =IF(U4=1,MAX($V$2:V3)+1,0) | W4: Furtividade | X4: =X3+IF('Criação'!$E$71="Sim",1,0) | Y4: =IF('Criação'!$E$71="Sim",X4,0) | Z4: ='Testes'!$I$18 | AA4: =IF(LEN('Testes'!$J$18)>0,"Vantagem","") | AB4: =IFERROR(INDEX($AA$2:$AA$19,MATCH(3,$Y$2:$Y$19,0)),"") | AC4: =IFERROR(INDEX($T$2:$T$16,MATCH(3,$V$2:$V$16,0)),"") | AD4: =IF($AF$39="","",IF($AF$39="Sangramento",IF(ISNUMBER($AI$39),MIN(INT('Criação'!$D$95*5/100),3*IF(ISNUMBER($AI$39),$AI$39,0))&" por turno","5% PV, teto 3×Ef"),IF($AF$39="Queimadura","2d6+"&IF(ISNUMBER($AI$39),IF(ISNUMBER($AI$39),$AI$39,0),"Ef"),IF(OR($AF$39="Choque",$AF$39="Aprisionamento"),"1d6+"&IF(ISNUMBER($AI$39),IF(ISNUMBER($AI$39),$AI$39,0),"Ef"),IF(OR($AF$39="Cisalhamento de Vento",$AF$39="Embaraço"),"1d6 por acúmulo",IF($AF$39="Surpreso","casa pulada no 1º Ciclo","—")))))) | AK4: =IF(ISERROR($F$4),"",IF(ISBLANK($F$4),"",$F$4)) | AP4: =ISERROR($F$4)*1
A5: PV | B5: =$Q$2&" / "&'Criação'!$D$95&IF($Q$4>0," (+"&$Q$4&" temporários)","")&IF($Q$3="Sim"," · Morrendo","") | E5: PH do grupo | G5: ="máx "&'Criação'!$E$16&" · início "&'Criação'!$F$16&" · +"&'Criação'!$G$16&" por acerto" | I5: Após a RD | J5: =IF(ISNUMBER($AO$2),IF($AO$2<=0,0,MAX(1,$AO$2-$J$4)),0) | K5: mínimo 1 | N5: =IF(AP5>0,"O Google leu como fórmula: digite de novo com ' na frente.",IF(LEN($AK$5)=0,"",IF(ISNUMBER($AK$5),IF($AK$5>'Criação'!$E$16,"PH acima do máximo do grupo ("&'Criação'!$E$16&", 16.2).",""),"PH precisa ser um número."))) | P5: Energia usada (0 a 100) | Q5: =IF(ISNUMBER($AK$4),MAX(0,MIN(100,INT($AK$4))),0) | S5: ="Efeito do Cone de Luz" | T5: =IF('Equipamento'!$P$28=1,"1/combate","1/Ciclo") | U5: =IF('Equipamento'!$P$28>0,1,0) | V5: =IF(U5=1,MAX($V$2:V4)+1,0) | W5: Pilotagem | X5: =X4+IF('Criação'!$E$72="Sim",1,0) | Y5: =IF('Criação'!$E$72="Sim",X5,0) | Z5: ='Testes'!$I$19 | AA5: =IF(LEN('Testes'!$J$19)>0,"Vantagem","") | AB5: =IFERROR(INDEX($AA$2:$AA$19,MATCH(4,$Y$2:$Y$19,0)),"") | AC5: =IFERROR(INDEX($T$2:$T$16,MATCH(4,$V$2:$V$16,0)),"") | AD5: =IF($AF$40="","",IF($AF$40="Sangramento",IF(ISNUMBER($AI$40),MIN(INT('Criação'!$D$95*5/100),3*IF(ISNUMBER($AI$40),$AI$40,0))&" por turno","5% PV, teto 3×Ef"),IF($AF$40="Queimadura","2d6+"&IF(ISNUMBER($AI$40),IF(ISNUMBER($AI$40),$AI$40,0),"Ef"),IF(OR($AF$40="Choque",$AF$40="Aprisionamento"),"1d6+"&IF(ISNUMBER($AI$40),IF(ISNUMBER($AI$40),$AI$40,0),"Ef"),IF(OR($AF$40="Cisalhamento de Vento",$AF$40="Embaraço"),"1d6 por acúmulo",IF($AF$40="Surpreso","casa pulada no 1º Ciclo","—")))))) | AK5: =IF(ISERROR($F$5),"",IF(ISBLANK($F$5),"",$F$5)) | AP5: =ISERROR($F$5)*1
A6: Defesa · Esquiva | B6: ='Criação'!$D$96&IF($Q$16>'Criação'!$D$96," ("&$Q$16&" com temporários)","")&" · Esquiva "&IF(ISNUMBER('Criação'!$D$97),'Criação'!$D$97,"proibida") | E6: Esforço | G6: =IF('Criação'!$Q$25="Humano","máx 1 · volta no Descanso Longo","só para Humano") | I6: Absorvido | J6: =MIN($Q$4,$J$5) | K6: pelos temporários | N6: =IF(AP6>0,"O Google leu como fórmula: digite de novo com ' na frente.",IF(LEN($AK$6)=0,"",IF(ISNUMBER($AK$6),IF('Criação'!$Q$25<>"Humano","O Esforço é traço do Humano (05). ","")&IF($AK$6>1,"Esforço máximo 1 (05).",""),"Esforço precisa ser um número."))) | P6: Memoespírito ativo (só A Recordação) | Q6: =IF(AND($AK$7="Sim",'Criação'!$Q$33="A Recordação"),"Sim","Não") | S6: ="Corda de Ligação" | T6: ="1/combate" | U6: =IF('Equipamento'!$G$41>0,1,0) | V6: =IF(U6=1,MAX($V$2:V5)+1,0) | W6: Resistência | X6: =X5+IF('Criação'!$E$73="Sim",1,0) | Y6: =IF('Criação'!$E$73="Sim",X6,0) | Z6: ='Testes'!$I$20 | AA6: =IF(LEN('Testes'!$J$20)>0,"Vantagem","") | AB6: =IFERROR(INDEX($AA$2:$AA$19,MATCH(5,$Y$2:$Y$19,0)),"") | AC6: =IFERROR(INDEX($T$2:$T$16,MATCH(5,$V$2:$V$16,0)),"") | AK6: =IF(ISERROR($F$6),"",IF(ISBLANK($F$6),"",$F$6)) | AP6: =ISERROR($F$6)*1
A7: RD · Velocidade | B7: ="RD "&'Criação'!$D$98&" · VEL "&'Criação'!$D$99 | E7: Memoespírito | G7: =IF('Criação'!$Q$33="A Recordação","PV dele (máx "&'Caminho'!$B$80&")","só A Recordação") | I7: PV perdidos | J7: =$J$5-$J$6 | N7: =IF(AP7>0,"O Google leu como fórmula: escolha de novo ou digite com ' na frente.",IF(AND(OR($AK$7="Sim",LEN($AM$7)>0),'Criação'!$Q$33<>"A Recordação"),"Memoespírito só na Recordação: não conta. ","")&IF(LEN($AM$7)=0,"",IF(ISNUMBER($AM$7),IF(AND('Criação'!$Q$33="A Recordação",$AM$7>'Caminho'!$B$80),"PV do Memoespírito acima do máximo ("&'Caminho'!$B$80&"). ",""),"PV do Memoespírito precisa ser um número."))) | P7: Fúria (Sacrifício Desesperado, máx. 2) | Q7: =IF($G$8="Fúria",MIN(2,IF(ISNUMBER($AK$8),MAX(0,INT($AK$8)),0)),0) | S7: =""&'Caminho'!$I$27 | T7: =IF('Caminho'!$H$27="Uma vez por turno","1/turno",IF('Caminho'!$H$27="Uma vez por Ciclo","1/Ciclo",IF('Caminho'!$H$27="Uma vez por combate por alvo","1/combate/alvo",IF('Caminho'!$H$27="Uma vez por combate","1/combate",IF('Caminho'!$H$27="Uma vez por Descanso Longo","1/Desc. Longo",IF('Caminho'!$H$27="Uma vez por sessão","1/sessão",IF('Caminho'!$H$27="Duas vezes por dia","2/dia",""&'Caminho'!$H$27))))))) | U7: =IF(AND(LEN('Caminho'!$I$27)>0,LEN('Caminho'!$H$27)>0,'Caminho'!$H$27<>"Sem limite declarado"),1,0) | V7: =IF(U7=1,MAX($V$2:V6)+1,0) | W7: Tecnologia | X7: =X6+IF('Criação'!$E$75="Sim",1,0) | Y7: =IF('Criação'!$E$75="Sim",X7,0) | Z7: ='Testes'!$I$22 | AA7: =IF(LEN('Testes'!$J$22)>0,"Vantagem","") | AB7: =IFERROR(INDEX($AA$2:$AA$19,MATCH(6,$Y$2:$Y$19,0)),"") | AC7: =IFERROR(INDEX($T$2:$T$16,MATCH(6,$V$2:$V$16,0)),"") | AK7: =IF(ISERROR($F$7),"",IF(ISBLANK($F$7),"",$F$7)) | AM7: =IF(ISERROR($H$7),"",IF(ISBLANK($H$7),"",$H$7)) | AP7: =ISERROR($F$7)*1+ISERROR($H$7)*1
A8: DT das Habilidades | B8: ='Criação'!$B$56&" · ataque de Habilidade "&'Criação'!$C$57 | E8: Acúmulos | G8: =IF((COUNTIF('Caminho'!$I$27:$I$36,"Sacrifício Desesperado")>0),"Fúria",IF((COUNTIF('Caminho'!$I$27:$I$36,"Florescimento da Alma")>0),"Florescimento",IF((COUNTIF('Caminho'!$I$27:$I$36,"Memória Devastadora")>0),"Fragmentos de Memória",IF('Criação'!$Q$33="A Erudição","Acúmulos de Cálculo","—")))) | H8: =IF($G$8="—","sem acúmulo","máx "&IF($G$8="Fúria",2,IF($G$8="Acúmulos de Cálculo",IF((COUNTIF('Caminho'!$I$27:$I$36,"Teto Rompido")>0),7,5),IF($G$8="—",0,5)))) | I8: PV novo | J8: =MAX(0,$Q$2-$J$7) | K8: ="PV novo: "&$J$8&" · temp. "&($Q$4-$J$6) | N8: =IF(AP8>0,"O Google leu como fórmula: digite de novo com ' na frente.",IF(LEN($AK$8)=0,"",IF(ISNUMBER($AK$8),IF($G$8="—","Nenhuma Bênção sua tem acúmulo neste campo.",IF($AK$8>IF($G$8="Fúria",2,IF($G$8="Acúmulos de Cálculo",IF((COUNTIF('Caminho'!$I$27:$I$36,"Teto Rompido")>0),7,5),IF($G$8="—",0,5))),"Máximo "&IF($G$8="Fúria",2,IF($G$8="Acúmulos de Cálculo",IF((COUNTIF('Caminho'!$I$27:$I$36,"Teto Rompido")>0),7,5),IF($G$8="—",0,5)))&" acúmulos de "&$G$8&".","")),"Acúmulos precisa ser um número."))) | P8: Florescimento (máx. 5) | Q8: =IF($G$8="Florescimento",MIN(5,IF(ISNUMBER($AK$8),MAX(0,INT($AK$8)),0)),0) | S8: =""&'Caminho'!$I$28 | T8: =IF('Caminho'!$H$28="Uma vez por turno","1/turno",IF('Caminho'!$H$28="Uma vez por Ciclo","1/Ciclo",IF('Caminho'!$H$28="Uma vez por combate por alvo","1/combate/alvo",IF('Caminho'!$H$28="Uma vez por combate","1/combate",IF('Caminho'!$H$28="Uma vez por Descanso Longo","1/Desc. Longo",IF('Caminho'!$H$28="Uma vez por sessão","1/sessão",IF('Caminho'!$H$28="Duas vezes por dia","2/dia",""&'Caminho'!$H$28))))))) | U8: =IF(AND(LEN('Caminho'!$I$28)>0,LEN('Caminho'!$H$28)>0,'Caminho'!$H$28<>"Sem limite declarado"),1,0) | V8: =IF(U8=1,MAX($V$2:V7)+1,0) | W8: Pesquisa | X8: =X7+IF('Criação'!$E$76="Sim",1,0) | Y8: =IF('Criação'!$E$76="Sim",X8,0) | Z8: ='Testes'!$I$23 | AA8: =IF(LEN('Testes'!$J$23)>0,"Vantagem","") | AB8: =IFERROR(INDEX($AA$2:$AA$19,MATCH(7,$Y$2:$Y$19,0)),"") | AC8: =IFERROR(INDEX($T$2:$T$16,MATCH(7,$V$2:$V$16,0)),"") | AK8: =IF(ISERROR($F$8),"",IF(ISBLANK($F$8),"",$F$8)) | AP8: =ISERROR($F$8)*1
A9: Melhor ataque | B9: =IF('Criação'!$Q$108="","Habilidades "&'Criação'!$C$57,"Ataque Básico "&'Equipamento'!$B$13&" · "&'Equipamento'!$C$13&" (média "&'Equipamento'!$D$13&")") | E9: Marcas | G9: =IF((COUNTIF('Caminho'!$I$27:$I$36,"Cicatriz da Destruição")>0),"Marcas da Ruína","—") | H9: =IF($G$9="—","sem acúmulo","máx 5") | I9: =IF($J$5=0,"Preencha o dano para ver o resultado",IF($Q$3="Sim","Já Morrendo: 1 falha (2 se crítico ou Nível 5+)",IF($J$8=0,"Cai a 0 PV: fica Morrendo (23.4)","Continua de pé"))) | N9: =IF(AP9>0,"O Google leu como fórmula: digite de novo com ' na frente.",IF(LEN($AK$9)=0,"",IF(ISNUMBER($AK$9),IF($G$9="—","Nenhuma Bênção sua tem acúmulo neste campo.",IF($AK$9>5,"Máximo 5 Marcas da Ruína.","")),"Acúmulos precisa ser um número."))) | P9: Fragmentos de Memória (máx. 5) | Q9: =IF($G$8="Fragmentos de Memória",MIN(5,IF(ISNUMBER($AK$8),MAX(0,INT($AK$8)),0)),0) | S9: =""&'Caminho'!$I$29 | T9: =IF('Caminho'!$H$29="Uma vez por turno","1/turno",IF('Caminho'!$H$29="Uma vez por Ciclo","1/Ciclo",IF('Caminho'!$H$29="Uma vez por combate por alvo","1/combate/alvo",IF('Caminho'!$H$29="Uma vez por combate","1/combate",IF('Caminho'!$H$29="Uma vez por Descanso Longo","1/Desc. Longo",IF('Caminho'!$H$29="Uma vez por sessão","1/sessão",IF('Caminho'!$H$29="Duas vezes por dia","2/dia",""&'Caminho'!$H$29))))))) | U9: =IF(AND(LEN('Caminho'!$I$29)>0,LEN('Caminho'!$H$29)>0,'Caminho'!$H$29<>"Sem limite declarado"),1,0) | V9: =IF(U9=1,MAX($V$2:V8)+1,0) | W9: Ciência | X9: =X8+IF('Criação'!$E$77="Sim",1,0) | Y9: =IF('Criação'!$E$77="Sim",X9,0) | Z9: ='Testes'!$I$24 | AA9: =IF(LEN('Testes'!$J$24)>0,"Vantagem","") | AB9: =IFERROR(INDEX($AA$2:$AA$19,MATCH(8,$Y$2:$Y$19,0)),"") | AC9: =IFERROR(INDEX($T$2:$T$16,MATCH(8,$V$2:$V$16,0)),"") | AK9: =IF(ISERROR($F$9),"",IF(ISBLANK($F$9),"",$F$9)) | AP9: =ISERROR($F$9)*1
A10: Vantagens raciais | B10: =IF('Criação'!$Q$25="Humano","Esforço (1 ponto) e +1 Perícia na criação",IF('Criação'!$Q$25="Intellitron","Tecnologia, Mecânica, Fraqueza; imune a doença",IF('Criação'!$Q$25="Avginiano","Testes mentais; metade da duração ao falhar",IF('Criação'!$Q$25="Haloviano","Controlado 2× por dia; sem dano de queda",IF('Criação'!$Q$25="Vulpes","Presença e Força de Vontade; 1 favor por descanso",IF('Criação'!$Q$25="Vidyadhara","recupera PV 1× por descanso; respira na água",IF('Criação'!$Q$25="Xianzhouíta","todo Teste de Resistência; 1 pergunta por cena","—"))))))) | E10: =IF('Criação'!$Q$33="","Recurso do Caminho: escolha o Caminho",IF('Criação'!$Q$33="A Destruição","PV como moeda: "&(2*'Criação'!$A$14)&" PV por ativação",IF('Criação'!$Q$33="A Preservação","Barreira: teto "&$Q$17,IF('Criação'!$Q$33="A Erudição","Acúmulos de Cálculo: máx "&IF((COUNTIF('Caminho'!$I$27:$I$36,"Teto Rompido")>0),7,5),IF('Criação'!$Q$33="A Caça","Marcação de Presa: 1 alvo · crítico "&IF((COUNTIF('Caminho'!$I$27:$I$36,"Olho de Lan")>0),"19-20","20"),IF('Criação'!$Q$33="A Euforia","Tabela do Riso: 1d6 (aba Caminho)",IF('Criação'!$Q$33="A Recordação","Memoespírito: ficha na aba Caminho",IF('Criação'!$Q$33="A Inexistência","Recurso: acúmulos de Marca do Vazio e Corrupção",IF('Criação'!$Q$33="A Harmonia","Recurso: acúmulos de Eco da Vitória (máx 3)",IF('Criação'!$Q$33="A Abundância","Recurso: acúmulos de Florescimento (máx 5)","Recurso do Caminho: escolha um Caminho da lista")))))))))) | I10: Cura recebida | K10: ="PV depois: "&IF(ISNUMBER($AO$10),MIN('Criação'!$D$95,$Q$2+MAX(0,$AO$10)),$Q$2) | N10: =IF(AP10>0,"O Google leu como fórmula: digite de novo com ' na frente.",IF(LEN($AO$2)=0,"",IF(ISNUMBER($AO$2),IF($AO$2<0,"Dano não é negativo: use a cura.",""),"Dano recebido precisa ser um número."))) | P10: Acúmulos de Cálculo (máx. 5 ou 7) | Q10: =IF($G$8="Acúmulos de Cálculo",MIN(IF((COUNTIF('Caminho'!$I$27:$I$36,"Teto Rompido")>0),7,5),IF(ISNUMBER($AK$8),MAX(0,INT($AK$8)),0)),0) | S10: =""&'Caminho'!$I$30 | T10: =IF('Caminho'!$H$30="Uma vez por turno","1/turno",IF('Caminho'!$H$30="Uma vez por Ciclo","1/Ciclo",IF('Caminho'!$H$30="Uma vez por combate por alvo","1/combate/alvo",IF('Caminho'!$H$30="Uma vez por combate","1/combate",IF('Caminho'!$H$30="Uma vez por Descanso Longo","1/Desc. Longo",IF('Caminho'!$H$30="Uma vez por sessão","1/sessão",IF('Caminho'!$H$30="Duas vezes por dia","2/dia",""&'Caminho'!$H$30))))))) | U10: =IF(AND(LEN('Caminho'!$I$30)>0,LEN('Caminho'!$H$30)>0,'Caminho'!$H$30<>"Sem limite declarado"),1,0) | V10: =IF(U10=1,MAX($V$2:V9)+1,0) | W10: Mecânica | X10: =X9+IF('Criação'!$E$78="Sim",1,0) | Y10: =IF('Criação'!$E$78="Sim",X10,0) | Z10: ='Testes'!$I$25 | AA10: =IF(LEN('Testes'!$J$25)>0,"Vantagem","") | AB10: =IFERROR(INDEX($AA$2:$AA$19,MATCH(9,$Y$2:$Y$19,0)),"") | AO10: =IF(ISERROR($J$10),"",IF(ISBLANK($J$10),"",$J$10)) | AP10: =ISERROR($J$10)*1
A11: Condições ativas | B11: =IF($Q$24=0,"Nenhuma",$Q$25&IF($Q$24>1," + "&($Q$24-1)&" (linhas 37-40)","")) | E11: ="Energia de equipamento: "&IF('Equipamento'!$G$41>0,"Corda +"&'Equipamento'!$G$41&" ao entrar na Fila","sem Corda")&IF('Equipamento'!$P$28>=3," · Cone +5 por Ciclo","") | I11: Descanso Curto | J11: =2*'Criação'!$A$14+'Criação'!$F$46 | K11: ="PV depois: "&MIN('Criação'!$D$95,$Q$2+$J$11) | N11: =IF(AND(LEN($AO$10)>0,NOT(ISNUMBER($AO$10))),"Cura precisa ser um número.","") | P11: Marcas da Ruína (máx. 5) | Q11: =IF($G$9="Marcas da Ruína",MIN(5,IF(ISNUMBER($AK$9),MAX(0,INT($AK$9)),0)),0) | S11: =""&'Caminho'!$I$31 | T11: =IF('Caminho'!$H$31="Uma vez por turno","1/turno",IF('Caminho'!$H$31="Uma vez por Ciclo","1/Ciclo",IF('Caminho'!$H$31="Uma vez por combate por alvo","1/combate/alvo",IF('Caminho'!$H$31="Uma vez por combate","1/combate",IF('Caminho'!$H$31="Uma vez por Descanso Longo","1/Desc. Longo",IF('Caminho'!$H$31="Uma vez por sessão","1/sessão",IF('Caminho'!$H$31="Duas vezes por dia","2/dia",""&'Caminho'!$H$31))))))) | U11: =IF(AND(LEN('Caminho'!$I$31)>0,LEN('Caminho'!$H$31)>0,'Caminho'!$H$31<>"Sem limite declarado"),1,0) | V11: =IF(U11=1,MAX($V$2:V10)+1,0) | W11: Percepção | X11: =X10+IF('Criação'!$E$79="Sim",1,0) | Y11: =IF('Criação'!$E$79="Sim",X11,0) | Z11: ='Testes'!$I$26 | AA11: =IF(LEN('Testes'!$J$26)>0,"Vantagem","") | AB11: =IFERROR(INDEX($AA$2:$AA$19,MATCH(10,$Y$2:$Y$19,0)),"")
A12: Pode ser Executado? | B12: =IF('Criação'!$Q$25="Xianzhouíta","Não (Xianzhouíta, 23.5)",IF($Q$3="Sim","Sim: está Morrendo (23.5)","Só se estiver Morrendo (23.5)")) | E12: =IF('Equipamento'!$B$58="Não consegue se mover","Movimento: não se move (carga)",IF($Q$20=1,"Movimento: Lentidão, só Esforço Total move 1 passo","Movimento: 1 Distância por ação · Esforço Total: 2")) | I12: ="Descanso Longo: PV cheios, sem condições, Esforço de volta" | N12: =IF(OR(AND(LEN($AI$33)>0,NOT(ISNUMBER($AI$33))),AND(LEN($AK$33)>0,NOT(ISNUMBER($AK$33)))),"Sucessos e falhas precisam ser números de 0 a 3. ",IF(OR(IF(ISNUMBER($AI$33),$AI$33,0)>3,IF(ISNUMBER($AK$33),$AK$33,0)>3),"Sucessos e falhas vão de 0 a 3. ",""))&IF(AND($Q$3="Não",IF(ISNUMBER($AI$33),$AI$33,0)+IF(ISNUMBER($AK$33),$AK$33,0)>0),"Contador de Morrendo preenchido com PV acima de 0: a cura zera o contador (23.4).","") | P12: Instinto de Sobrevivência ligado (PV ≤ 1/3) | Q12: =IF(AND((COUNTIF('Caminho'!$I$27:$I$36,"Instinto de Sobrevivência")>0),ISNUMBER($AK$2),$Q$2*3<='Criação'!$D$95),1,0) | S12: =""&'Caminho'!$I$32 | T12: =IF('Caminho'!$H$32="Uma vez por turno","1/turno",IF('Caminho'!$H$32="Uma vez por Ciclo","1/Ciclo",IF('Caminho'!$H$32="Uma vez por combate por alvo","1/combate/alvo",IF('Caminho'!$H$32="Uma vez por combate","1/combate",IF('Caminho'!$H$32="Uma vez por Descanso Longo","1/Desc. Longo",IF('Caminho'!$H$32="Uma vez por sessão","1/sessão",IF('Caminho'!$H$32="Duas vezes por dia","2/dia",""&'Caminho'!$H$32))))))) | U12: =IF(AND(LEN('Caminho'!$I$32)>0,LEN('Caminho'!$H$32)>0,'Caminho'!$H$32<>"Sem limite declarado"),1,0) | V12: =IF(U12=1,MAX($V$2:V11)+1,0) | W12: Sobrevivência | X12: =X11+IF('Criação'!$E$80="Sim",1,0) | Y12: =IF('Criação'!$E$80="Sim",X12,0) | Z12: ='Testes'!$I$27 | AA12: =IF(LEN('Testes'!$J$27)>0,"Vantagem","")
A13: =IF((IF(LEN(N2)>0,1,0)+IF(LEN(N3)>0,1,0)+IF(LEN(N4)>0,1,0)+IF(LEN(N5)>0,1,0)+IF(LEN(N6)>0,1,0)+IF(LEN(N7)>0,1,0)+IF(LEN(N8)>0,1,0)+IF(LEN(N9)>0,1,0)+IF(LEN(N10)>0,1,0)+IF(LEN(N11)>0,1,0)+IF(LEN(N12)>0,1,0)+IF(LEN(N13)>0,1,0)+IF(LEN(N14)>0,1,0)+IF(LEN(N15)>0,1,0)+IF(LEN(N16)>0,1,0)+IF(LEN(N17)>0,1,0)+IF(LEN(N18)>0,1,0)+IF(LEN(N19)>0,1,0)+IF(LEN(N20)>0,1,0)+IF(LEN(N33)>0,1,0)+IF(LEN(N34)>0,1,0)+IF(LEN(N35)>0,1,0)+IF(LEN(N36)>0,1,0)+IF(LEN(N37)>0,1,0)+IF(LEN(N38)>0,1,0)+IF(LEN(N39)>0,1,0)+IF(LEN(N40)>0,1,0))=0,"","Avisos ("&(IF(LEN(N2)>0,1,0)+IF(LEN(N3)>0,1,0)+IF(LEN(N4)>0,1,0)+IF(LEN(N5)>0,1,0)+IF(LEN(N6)>0,1,0)+IF(LEN(N7)>0,1,0)+IF(LEN(N8)>0,1,0)+IF(LEN(N9)>0,1,0)+IF(LEN(N10)>0,1,0)+IF(LEN(N11)>0,1,0)+IF(LEN(N12)>0,1,0)+IF(LEN(N13)>0,1,0)+IF(LEN(N14)>0,1,0)+IF(LEN(N15)>0,1,0)+IF(LEN(N16)>0,1,0)+IF(LEN(N17)>0,1,0)+IF(LEN(N18)>0,1,0)+IF(LEN(N19)>0,1,0)+IF(LEN(N20)>0,1,0)+IF(LEN(N33)>0,1,0)+IF(LEN(N34)>0,1,0)+IF(LEN(N35)>0,1,0)+IF(LEN(N36)>0,1,0)+IF(LEN(N37)>0,1,0)+IF(LEN(N38)>0,1,0)+IF(LEN(N39)>0,1,0)+IF(LEN(N40)>0,1,0))&"): "&IF(LEN(N2)>0,N2,IF(LEN(N3)>0,N3,IF(LEN(N4)>0,N4,IF(LEN(N5)>0,N5,IF(LEN(N6)>0,N6,IF(LEN(N7)>0,N7,IF(LEN(N8)>0,N8,IF(LEN(N9)>0,N9,IF(LEN(N10)>0,N10,IF(LEN(N11)>0,N11,IF(LEN(N12)>0,N12,IF(LEN(N13)>0,N13,IF(LEN(N14)>0,N14,IF(LEN(N15)>0,N15,IF(LEN(N16)>0,N16,IF(LEN(N17)>0,N17,IF(LEN(N18)>0,N18,IF(LEN(N19)>0,N19,IF(LEN(N20)>0,N20,IF(LEN(N33)>0,N33,IF(LEN(N34)>0,N34,IF(LEN(N35)>0,N35,IF(LEN(N36)>0,N36,IF(LEN(N37)>0,N37,IF(LEN(N38)>0,N38,IF(LEN(N39)>0,N39,IF(LEN(N40)>0,N40,"")))))))))))))))))))))))))))&IF((IF(LEN(N2)>0,1,0)+IF(LEN(N3)>0,1,0)+IF(LEN(N4)>0,1,0)+IF(LEN(N5)>0,1,0)+IF(LEN(N6)>0,1,0)+IF(LEN(N7)>0,1,0)+IF(LEN(N8)>0,1,0)+IF(LEN(N9)>0,1,0)+IF(LEN(N10)>0,1,0)+IF(LEN(N11)>0,1,0)+IF(LEN(N12)>0,1,0)+IF(LEN(N13)>0,1,0)+IF(LEN(N14)>0,1,0)+IF(LEN(N15)>0,1,0)+IF(LEN(N16)>0,1,0)+IF(LEN(N17)>0,1,0)+IF(LEN(N18)>0,1,0)+IF(LEN(N19)>0,1,0)+IF(LEN(N20)>0,1,0)+IF(LEN(N33)>0,1,0)+IF(LEN(N34)>0,1,0)+IF(LEN(N35)>0,1,0)+IF(LEN(N36)>0,1,0)+IF(LEN(N37)>0,1,0)+IF(LEN(N38)>0,1,0)+IF(LEN(N39)>0,1,0)+IF(LEN(N40)>0,1,0))>1," · os outros estão na coluna N","")) | N13: =IF($AF$37="","",IF($AF$37="Quebrado","Quebrado é só de inimigos (20.3).",IF($AF$37="Morrendo","Morrendo liga sozinho com PV 0.",IF(COUNTIF('Dados'!$Y$6:$Y$18,$AF$37)=0,"Condição fora da lista de 21.5.","")))) | P13: Bônus temporário no Teste de Ataque (antes do teto) | Q13: =2*$Q$12+IF(AND(($Q$6="Sim"),'Caminho'!$P$57="Catalisador"),1,0)+IF(AND(($Q$6="Sim"),COUNTIF('Caminho'!$Q$75:$Q$77,"Fusão de Memórias")>0),1,0)+IF(AND(($Q$6="Sim"),(COUNTIF('Caminho'!$I$27:$I$36,"Memória Compartilhada")>0)),1,0)+COUNTIF('Equipamento'!$P$45:$P$47,"Teste de Ataque") | S13: =""&'Caminho'!$I$33 | T13: =IF('Caminho'!$H$33="Uma vez por turno","1/turno",IF('Caminho'!$H$33="Uma vez por Ciclo","1/Ciclo",IF('Caminho'!$H$33="Uma vez por combate por alvo","1/combate/alvo",IF('Caminho'!$H$33="Uma vez por combate","1/combate",IF('Caminho'!$H$33="Uma vez por Descanso Longo","1/Desc. Longo",IF('Caminho'!$H$33="Uma vez por sessão","1/sessão",IF('Caminho'!$H$33="Duas vezes por dia","2/dia",""&'Caminho'!$H$33))))))) | U13: =IF(AND(LEN('Caminho'!$I$33)>0,LEN('Caminho'!$H$33)>0,'Caminho'!$H$33<>"Sem limite declarado"),1,0) | V13: =IF(U13=1,MAX($V$2:V12)+1,0) | W13: Intuição | X13: =X12+IF('Criação'!$E$81="Sim",1,0) | Y13: =IF('Criação'!$E$81="Sim",X13,0) | Z13: ='Testes'!$I$28 | AA13: =IF(LEN('Testes'!$J$28)>0,"Vantagem","")
A14: Ações — Ataque Básico (18), Habilidades (16) e Ultimate (17) | N14: =IF($AF$38="","",IF($AF$38="Quebrado","Quebrado é só de inimigos (20.3).",IF($AF$38="Morrendo","Morrendo liga sozinho com PV 0.",IF(COUNTIF('Dados'!$Y$6:$Y$18,$AF$38)=0,"Condição fora da lista de 21.5.","")))) | P14: Bônus temporário no Teste de Ataque (no teto) | Q14: =MIN('Criação'!$J$14,$Q$13) | S14: =""&'Caminho'!$I$34 | T14: =IF('Caminho'!$H$34="Uma vez por turno","1/turno",IF('Caminho'!$H$34="Uma vez por Ciclo","1/Ciclo",IF('Caminho'!$H$34="Uma vez por combate por alvo","1/combate/alvo",IF('Caminho'!$H$34="Uma vez por combate","1/combate",IF('Caminho'!$H$34="Uma vez por Descanso Longo","1/Desc. Longo",IF('Caminho'!$H$34="Uma vez por sessão","1/sessão",IF('Caminho'!$H$34="Duas vezes por dia","2/dia",""&'Caminho'!$H$34))))))) | U14: =IF(AND(LEN('Caminho'!$I$34)>0,LEN('Caminho'!$H$34)>0,'Caminho'!$H$34<>"Sem limite declarado"),1,0) | V14: =IF(U14=1,MAX($V$2:V13)+1,0) | W14: Investigação | X14: =X13+IF('Criação'!$E$82="Sim",1,0) | Y14: =IF('Criação'!$E$82="Sim",X14,0) | Z14: ='Testes'!$I$29 | AA14: =IF(LEN('Testes'!$J$29)>0,"Vantagem","")
A15: Ataque Básico | C15: Ataque | D15: Dano | E15: Média | F15: Do atributo | G15: Equipamento | H15: Contra Fraqueza | I15: Crítico | J15: RT | K15: Alcance · Elemento | N15: =IF($AF$39="","",IF($AF$39="Quebrado","Quebrado é só de inimigos (20.3).",IF($AF$39="Morrendo","Morrendo liga sozinho com PV 0.",IF(COUNTIF('Dados'!$Y$6:$Y$18,$AF$39)=0,"Condição fora da lista de 21.5.","")))) | P15: Defesa temporária (Florescimento, Memória da Guarda) | Q15: =$Q$8+IF(AND((COUNTIF('Caminho'!$I$27:$I$36,"Fragmentos do Eu Perdido")>0),($Q$6="Sim"),'Caminho'!$P$95="Guarda"),'Criação'!$C$14,0) | S15: =""&'Caminho'!$I$35 | T15: =IF('Caminho'!$H$35="Uma vez por turno","1/turno",IF('Caminho'!$H$35="Uma vez por Ciclo","1/Ciclo",IF('Caminho'!$H$35="Uma vez por combate por alvo","1/combate/alvo",IF('Caminho'!$H$35="Uma vez por combate","1/combate",IF('Caminho'!$H$35="Uma vez por Descanso Longo","1/Desc. Longo",IF('Caminho'!$H$35="Uma vez por sessão","1/sessão",IF('Caminho'!$H$35="Duas vezes por dia","2/dia",""&'Caminho'!$H$35))))))) | U15: =IF(AND(LEN('Caminho'!$I$35)>0,LEN('Caminho'!$H$35)>0,'Caminho'!$H$35<>"Sem limite declarado"),1,0) | V15: =IF(U15=1,MAX($V$2:V14)+1,0) | W15: Persuasão | X15: =X14+IF('Criação'!$E$84="Sim",1,0) | Y15: =IF('Criação'!$E$84="Sim",X15,0) | Z15: ='Testes'!$I$31 | AA15: =IF(LEN('Testes'!$J$31)>0,"Vantagem","")
A16: =IF('Criação'!$Q$108="","Arma principal: —",IF(LEN('Criação'!$Q$107)=0,"Arma "&'Criação'!$Q$108,""&'Criação'!$Q$107)) | C16: ='Equipamento'!$B$13 | D16: ='Equipamento'!$C$13 | E16: ='Equipamento'!$D$13 | F16: ='Equipamento'!$E$13 | G16: ='Equipamento'!$F$13 | H16: =IF(LEN('Equipamento'!$G$13)=0,"",'Equipamento'!$G$13&" ("&'Equipamento'!$H$13&")") | I16: ='Equipamento'!$I$13 | J16: ='Equipamento'!$J$13 | K16: =IF(LEN('Equipamento'!$K$13)=0,"",'Equipamento'!$K$13&" · "&'Equipamento'!$L$13) | N16: =IF($AF$40="","",IF($AF$40="Quebrado","Quebrado é só de inimigos (20.3).",IF($AF$40="Morrendo","Morrendo liga sozinho com PV 0.",IF(COUNTIF('Dados'!$Y$6:$Y$18,$AF$40)=0,"Condição fora da lista de 21.5.","")))) | P16: Defesa com temporários | Q16: ='Criação'!$D$96+MIN('Criação'!$J$14,$Q$15) | S16: =""&'Caminho'!$I$36 | T16: =IF('Caminho'!$H$36="Uma vez por turno","1/turno",IF('Caminho'!$H$36="Uma vez por Ciclo","1/Ciclo",IF('Caminho'!$H$36="Uma vez por combate por alvo","1/combate/alvo",IF('Caminho'!$H$36="Uma vez por combate","1/combate",IF('Caminho'!$H$36="Uma vez por Descanso Longo","1/Desc. Longo",IF('Caminho'!$H$36="Uma vez por sessão","1/sessão",IF('Caminho'!$H$36="Duas vezes por dia","2/dia",""&'Caminho'!$H$36))))))) | U16: =IF(AND(LEN('Caminho'!$I$36)>0,LEN('Caminho'!$H$36)>0,'Caminho'!$H$36<>"Sem limite declarado"),1,0) | V16: =IF(U16=1,MAX($V$2:V15)+1,0) | W16: Intimidação | X16: =X15+IF('Criação'!$E$85="Sim",1,0) | Y16: =IF('Criação'!$E$85="Sim",X16,0) | Z16: ='Testes'!$I$32 | AA16: =IF(LEN('Testes'!$J$32)>0,"Vantagem","")
A17: =IF('Equipamento'!$AE$8="","Arma secundária: —",IF(LEN('Equipamento'!$AD$8)=0,"Arma "&'Equipamento'!$AE$8,""&'Equipamento'!$AD$8)) | C17: ='Equipamento'!$B$14 | D17: ='Equipamento'!$C$14 | E17: ='Equipamento'!$D$14 | F17: ='Equipamento'!$E$14 | G17: ='Equipamento'!$F$14 | H17: =IF(LEN('Equipamento'!$G$14)=0,"",'Equipamento'!$G$14&" ("&'Equipamento'!$H$14&")") | I17: ='Equipamento'!$I$14 | J17: ='Equipamento'!$J$14 | K17: =IF(LEN('Equipamento'!$K$14)=0,"",'Equipamento'!$K$14&" · "&'Equipamento'!$L$14) | N17: =IF(MAX($V$2:$V$16)>8,"Mais usos do que cabem aqui: veja a frequência das Bênçãos na aba Caminho.","") | P17: Teto de Barreira (Preservação) | Q17: =IF('Criação'!$Q$33="A Preservação",3*'Criação'!$C$14,"") | W17: Enganação | X17: =X16+IF('Criação'!$E$86="Sim",1,0) | Y17: =IF('Criação'!$E$86="Sim",X17,0) | Z17: ='Testes'!$I$33 | AA17: =IF(LEN('Testes'!$J$33)>0,"Vantagem","")
A18: Habilidade | C18: Rolagem | D18: Dano · média | E18: Nível · PH · RT · alvos | G18: Habilidade | I18: Rolagem | J18: Dano · média | K18: Nível · PH · RT · alvos | N18: =IF(AND(ISNUMBER($AO$33),$AO$33>2),"Descanso Curto: até 2 por dia (23.6).","") | P18: Silenciado | Q18: =IF(COUNTIF($AF$37:$AF$40,"Silenciado")>0,1,0) | W18: Liderança | X18: =X17+IF('Criação'!$E$87="Sim",1,0) | Y18: =IF('Criação'!$E$87="Sim",X18,0) | Z18: ='Testes'!$I$34 | AA18: =IF(LEN('Testes'!$J$34)>0,"Vantagem","")
A19: =IF('Habilidades'!$P$12=0,"—",'Habilidades'!$B$34) | C19: =IF('Habilidades'!$P$12=0,"",IF(LEN(IF($Q$19=1,"BLOQUEADA",IF(AND($Q$18=1,'Habilidades'!$S$12>=4),"BLOQUEADA","")))>0,IF($Q$19=1,"BLOQUEADA",IF(AND($Q$18=1,'Habilidades'!$S$12>=4),"BLOQUEADA","")),IF(LEN('Habilidades'!$F$34)=0,IF('Habilidades'!$Z$12="Passiva","Passiva","—"),'Habilidades'!$F$34))) | D19: =IF(LEN('Habilidades'!$D$34)=0,"",'Habilidades'!$D$34&" ("&'Habilidades'!$E$34&")") | E19: =IF('Habilidades'!$P$12=0,"",'Habilidades'!$S$12&" · "&'Habilidades'!$G$34&" PH · RT "&'Habilidades'!$H$34&" · "&'Habilidades'!$J$34&IF('Habilidades'!$J$34=1," alvo"," alvos")) | G19: =IF('Habilidades'!$P$16=0,"—",'Habilidades'!$B$38) | I19: =IF('Habilidades'!$P$16=0,"",IF(LEN(IF($Q$19=1,"BLOQUEADA",IF(AND($Q$18=1,'Habilidades'!$S$16>=4),"BLOQUEADA","")))>0,IF($Q$19=1,"BLOQUEADA",IF(AND($Q$18=1,'Habilidades'!$S$16>=4),"BLOQUEADA","")),IF(LEN('Habilidades'!$F$38)=0,IF('Habilidades'!$Z$16="Passiva","Passiva","—"),'Habilidades'!$F$38))) | J19: =IF(LEN('Habilidades'!$D$38)=0,"",'Habilidades'!$D$38&" ("&'Habilidades'!$E$38&")") | K19: =IF('Habilidades'!$P$16=0,"",'Habilidades'!$S$16&" · "&'Habilidades'!$G$38&" PH · RT "&'Habilidades'!$H$38&" · "&'Habilidades'!$J$38&IF('Habilidades'!$J$38=1," alvo"," alvos")) | N19: =IF($Q$13>'Criação'!$J$14,"Bônus temporário no Teste de Ataque acima do teto (+"&'Criação'!$J$14&"): conta só o teto (26.6). ","")&IF($Q$15>'Criação'!$J$14,"Defesa temporária acima do teto (+"&'Criação'!$J$14&"): conta só o teto (26.6).","") | P19: Controlado | Q19: =IF(COUNTIF($AF$37:$AF$40,"Controlado")>0,1,0) | W19: Sintonia | X19: =X18+IF('Criação'!$E$88="Sim",1,0) | Y19: =IF('Criação'!$E$88="Sim",X19,0) | Z19: ='Testes'!$I$35 | AA19: =IF(LEN('Testes'!$J$35)>0,"Vantagem","")
A20: =IF('Habilidades'!$P$13=0,"—",'Habilidades'!$B$35) | C20: =IF('Habilidades'!$P$13=0,"",IF(LEN(IF($Q$19=1,"BLOQUEADA",IF(AND($Q$18=1,'Habilidades'!$S$13>=4),"BLOQUEADA","")))>0,IF($Q$19=1,"BLOQUEADA",IF(AND($Q$18=1,'Habilidades'!$S$13>=4),"BLOQUEADA","")),IF(LEN('Habilidades'!$F$35)=0,IF('Habilidades'!$Z$13="Passiva","Passiva","—"),'Habilidades'!$F$35))) | D20: =IF(LEN('Habilidades'!$D$35)=0,"",'Habilidades'!$D$35&" ("&'Habilidades'!$E$35&")") | E20: =IF('Habilidades'!$P$13=0,"",'Habilidades'!$S$13&" · "&'Habilidades'!$G$35&" PH · RT "&'Habilidades'!$H$35&" · "&'Habilidades'!$J$35&IF('Habilidades'!$J$35=1," alvo"," alvos")) | G20: =IF('Habilidades'!$P$17=0,"—",'Habilidades'!$B$39) | I20: =IF('Habilidades'!$P$17=0,"",IF(LEN(IF($Q$19=1,"BLOQUEADA",IF(AND($Q$18=1,'Habilidades'!$S$17>=4),"BLOQUEADA","")))>0,IF($Q$19=1,"BLOQUEADA",IF(AND($Q$18=1,'Habilidades'!$S$17>=4),"BLOQUEADA","")),IF(LEN('Habilidades'!$F$39)=0,IF('Habilidades'!$Z$17="Passiva","Passiva","—"),'Habilidades'!$F$39))) | J20: =IF(LEN('Habilidades'!$D$39)=0,"",'Habilidades'!$D$39&" ("&'Habilidades'!$E$39&")") | K20: =IF('Habilidades'!$P$17=0,"",'Habilidades'!$S$17&" · "&'Habilidades'!$G$39&" PH · RT "&'Habilidades'!$H$39&" · "&'Habilidades'!$J$39&IF('Habilidades'!$J$39=1," alvo"," alvos")) | N20: =IF($Q$21=1,"Surpreso: a sua casa é pulada no primeiro Ciclo.","") | P20: Lentidão (condição ou carga) | Q20: =IF(OR(COUNTIF($AF$37:$AF$40,"Lentidão")>0,'Equipamento'!$B$58="Lentidão"),1,0)
A21: =IF('Habilidades'!$P$14=0,"—",'Habilidades'!$B$36) | C21: =IF('Habilidades'!$P$14=0,"",IF(LEN(IF($Q$19=1,"BLOQUEADA",IF(AND($Q$18=1,'Habilidades'!$S$14>=4),"BLOQUEADA","")))>0,IF($Q$19=1,"BLOQUEADA",IF(AND($Q$18=1,'Habilidades'!$S$14>=4),"BLOQUEADA","")),IF(LEN('Habilidades'!$F$36)=0,IF('Habilidades'!$Z$14="Passiva","Passiva","—"),'Habilidades'!$F$36))) | D21: =IF(LEN('Habilidades'!$D$36)=0,"",'Habilidades'!$D$36&" ("&'Habilidades'!$E$36&")") | E21: =IF('Habilidades'!$P$14=0,"",'Habilidades'!$S$14&" · "&'Habilidades'!$G$36&" PH · RT "&'Habilidades'!$H$36&" · "&'Habilidades'!$J$36&IF('Habilidades'!$J$36=1," alvo"," alvos")) | G21: =IF('Habilidades'!$P$18=0,"—",'Habilidades'!$B$40) | I21: =IF('Habilidades'!$P$18=0,"",IF(LEN(IF($Q$19=1,"BLOQUEADA",IF(AND($Q$18=1,'Habilidades'!$S$18>=4),"BLOQUEADA","")))>0,IF($Q$19=1,"BLOQUEADA",IF(AND($Q$18=1,'Habilidades'!$S$18>=4),"BLOQUEADA","")),IF(LEN('Habilidades'!$F$40)=0,IF('Habilidades'!$Z$18="Passiva","Passiva","—"),'Habilidades'!$F$40))) | J21: =IF(LEN('Habilidades'!$D$40)=0,"",'Habilidades'!$D$40&" ("&'Habilidades'!$E$40&")") | K21: =IF('Habilidades'!$P$18=0,"",'Habilidades'!$S$18&" · "&'Habilidades'!$G$40&" PH · RT "&'Habilidades'!$H$40&" · "&'Habilidades'!$J$40&IF('Habilidades'!$J$40=1," alvo"," alvos")) | P21: Surpreso | Q21: =IF(COUNTIF($AF$37:$AF$40,"Surpreso")>0,1,0)
A22: =IF('Habilidades'!$P$15=0,"—",'Habilidades'!$B$37) | C22: =IF('Habilidades'!$P$15=0,"",IF(LEN(IF($Q$19=1,"BLOQUEADA",IF(AND($Q$18=1,'Habilidades'!$S$15>=4),"BLOQUEADA","")))>0,IF($Q$19=1,"BLOQUEADA",IF(AND($Q$18=1,'Habilidades'!$S$15>=4),"BLOQUEADA","")),IF(LEN('Habilidades'!$F$37)=0,IF('Habilidades'!$Z$15="Passiva","Passiva","—"),'Habilidades'!$F$37))) | D22: =IF(LEN('Habilidades'!$D$37)=0,"",'Habilidades'!$D$37&" ("&'Habilidades'!$E$37&")") | E22: =IF('Habilidades'!$P$15=0,"",'Habilidades'!$S$15&" · "&'Habilidades'!$G$37&" PH · RT "&'Habilidades'!$H$37&" · "&'Habilidades'!$J$37&IF('Habilidades'!$J$37=1," alvo"," alvos")) | G22: =IF('Habilidades'!$P$19=0,"—",'Habilidades'!$B$41) | I22: =IF('Habilidades'!$P$19=0,"",IF(LEN(IF($Q$19=1,"BLOQUEADA",IF(AND($Q$18=1,'Habilidades'!$S$19>=4),"BLOQUEADA","")))>0,IF($Q$19=1,"BLOQUEADA",IF(AND($Q$18=1,'Habilidades'!$S$19>=4),"BLOQUEADA","")),IF(LEN('Habilidades'!$F$41)=0,IF('Habilidades'!$Z$19="Passiva","Passiva","—"),'Habilidades'!$F$41))) | J22: =IF(LEN('Habilidades'!$D$41)=0,"",'Habilidades'!$D$41&" ("&'Habilidades'!$E$41&")") | K22: =IF('Habilidades'!$P$19=0,"",'Habilidades'!$S$19&" · "&'Habilidades'!$G$41&" PH · RT "&'Habilidades'!$H$41&" · "&'Habilidades'!$J$41&IF('Habilidades'!$J$41=1," alvo"," alvos")) | P22: Ultimate pronta | Q22: =IF($Q$5>='Habilidades'!$G$61,"Sim","Não")
A23: =IF(LEN('Habilidades'!$Z$54)=0,"Ultimate: —",""&'Habilidades'!$Z$54) | C23: =IF(LEN(IF($Q$19=1,"BLOQUEADA",""))>0,IF($Q$19=1,"BLOQUEADA",""),IF(LEN('Habilidades'!$F$61)=0,"—",'Habilidades'!$F$61)) | D23: =IF(LEN('Habilidades'!$D$61)=0,"",'Habilidades'!$D$61&" ("&'Habilidades'!$E$61&")") | E23: ="RT "&'Habilidades'!$H$61&" · "&'Habilidades'!$I$61&IF('Habilidades'!$I$61=1," alvo"," alvos") | G23: ="Ultimate ("&$Q$5&"/"&'Habilidades'!$G$61&" de Energia): "&IF(LEN(IF($Q$19=1,"BLOQUEADA",""))>0,"BLOQUEADA (Controlado)",IF($Q$22="Sim","pronta, diga o nome em voz alta","faltam "&('Habilidades'!$G$61-$Q$5))) | P23: Condições ativas (texto inteiro) | Q23: =""&$AF$37&IF(LEN(""&$AF$38)>0,IF(LEN(""&$AF$37)>0," · ","")&""&$AF$38,"")&IF(LEN(""&$AF$39)>0,IF(LEN(""&$AF$37&""&$AF$38)>0," · ","")&""&$AF$39,"")&IF(LEN(""&$AF$40)>0,IF(LEN(""&$AF$37&""&$AF$38&""&$AF$39)>0," · ","")&""&$AF$40,"")&IF(LEN(IF($Q$3="Sim","Morrendo",""))>0,IF(LEN(""&$AF$37&""&$AF$38&""&$AF$39&""&$AF$40)>0," · ","")&IF($Q$3="Sim","Morrendo",""),"")&IF(LEN(IF('Equipamento'!$B$58<>"Normal","Lentidão (carga)",""))>0,IF(LEN(""&$AF$37&""&$AF$38&""&$AF$39&""&$AF$40&IF($Q$3="Sim","Morrendo",""))>0," · ","")&IF('Equipamento'!$B$58<>"Normal","Lentidão (carga)",""),"")
A24: ="Neste ataque: "&IF(AND(($Q$6="Sim"),(COUNTIF('Caminho'!$I$27:$I$36,"Memória Compartilhada")>0)),"+1d6 (Memória Compartilhada) · ","")&IF(AND(($Q$6="Sim"),(COUNTIF('Caminho'!$I$27:$I$36,"Fragmentos do Eu Perdido")>0),'Caminho'!$P$95="Fúria"),"+1d8 (Memória da Fúria) · ","")&IF($Q$7>0,"+"&$Q$7&"d6 (Fúria) · ","")&IF($Q$11>0,"+"&MIN('Criação'!$J$14,$Q$11)&" de dano (Cicatriz) · ","")&IF($Q$12=1,"+2 no ataque, já somado (Instinto) · ","")&"temporários: no máximo +3 por rolagem, fora a Fraqueza (26.6)" | P24: Condições ativas (quantas) | Q24: =IF(LEN(""&$AF$37)>0,1,0)+IF(LEN(""&$AF$38)>0,1,0)+IF(LEN(""&$AF$39)>0,1,0)+IF(LEN(""&$AF$40)>0,1,0)+IF(LEN(IF($Q$3="Sim","Morrendo",""))>0,1,0)+IF(LEN(IF('Equipamento'!$B$58<>"Normal","Lentidão (carga)",""))>0,1,0)
P25: Condições ativas (a primeira) | Q25: =IF(LEN(""&$AF$37)>0,""&$AF$37,IF(LEN(""&$AF$38)>0,""&$AF$38,IF(LEN(""&$AF$39)>0,""&$AF$39,IF(LEN(""&$AF$40)>0,""&$AF$40,IF(LEN(IF($Q$3="Sim","Morrendo",""))>0,IF($Q$3="Sim","Morrendo",""),IF(LEN(IF('Equipamento'!$B$58<>"Normal","Lentidão (carga)",""))>0,IF('Equipamento'!$B$58<>"Normal","Lentidão (carga)",""),""))))))
A26: Testes de Resistência (d20 + Bônus + Eficiência) | G26: Perícias com Eficiência (rolagem pronta)
A27: Potência Física | B27: ='Testes'!$I$40 | C27: =IF(OR('Criação'!$Q$25="Xianzhouíta"),"Vantagem ("&'Criação'!$Q$25&")","") | E27: =IF('Testes'!$G$40=0,"",IF('Testes'!$G$40>=0,"+","")&'Testes'!$G$40&" de equipamento/Bênção") | G27: =IFERROR(INDEX($W$2:$W$19,MATCH(1,$Y$2:$Y$19,0))&IF(LEN($AB$2)>0," · Vantagem",""),"") | I27: =IFERROR(INDEX($Z$2:$Z$19,MATCH(1,$Y$2:$Y$19,0)),"") | J27: =IFERROR(INDEX($W$2:$W$19,MATCH(6,$Y$2:$Y$19,0))&IF(LEN($AB$7)>0," · Vantagem",""),"") | L27: =IFERROR(INDEX($Z$2:$Z$19,MATCH(6,$Y$2:$Y$19,0)),"")
A28: Reflexos | B28: ='Testes'!$I$41 | C28: =IF(OR('Criação'!$Q$25="Xianzhouíta"),"Vantagem ("&'Criação'!$Q$25&")","") | E28: =IF('Testes'!$G$41=0,"",IF('Testes'!$G$41>=0,"+","")&'Testes'!$G$41&" de equipamento/Bênção") | G28: =IFERROR(INDEX($W$2:$W$19,MATCH(2,$Y$2:$Y$19,0))&IF(LEN($AB$3)>0," · Vantagem",""),"") | I28: =IFERROR(INDEX($Z$2:$Z$19,MATCH(2,$Y$2:$Y$19,0)),"") | J28: =IFERROR(INDEX($W$2:$W$19,MATCH(7,$Y$2:$Y$19,0))&IF(LEN($AB$8)>0," · Vantagem",""),"") | L28: =IFERROR(INDEX($Z$2:$Z$19,MATCH(7,$Y$2:$Y$19,0)),"")
A29: Resistência Física | B29: ='Testes'!$I$42 | C29: =IF(OR('Criação'!$Q$25="Xianzhouíta"),"Vantagem ("&'Criação'!$Q$25&")","") | E29: =IF('Testes'!$G$42=0,"",IF('Testes'!$G$42>=0,"+","")&'Testes'!$G$42&" de equipamento/Bênção") | G29: =IFERROR(INDEX($W$2:$W$19,MATCH(3,$Y$2:$Y$19,0))&IF(LEN($AB$4)>0," · Vantagem",""),"") | I29: =IFERROR(INDEX($Z$2:$Z$19,MATCH(3,$Y$2:$Y$19,0)),"") | J29: =IFERROR(INDEX($W$2:$W$19,MATCH(8,$Y$2:$Y$19,0))&IF(LEN($AB$9)>0," · Vantagem",""),"") | L29: =IFERROR(INDEX($Z$2:$Z$19,MATCH(8,$Y$2:$Y$19,0)),"")
A30: Resistência Mental | B30: ='Testes'!$I$43 | C30: =IF(OR('Criação'!$Q$25="Xianzhouíta",'Criação'!$Q$25="Avginiano"),"Vantagem ("&'Criação'!$Q$25&")","") | E30: =IF('Testes'!$G$43=0,"",IF('Testes'!$G$43>=0,"+","")&'Testes'!$G$43&" de equipamento/Bênção") | G30: =IFERROR(INDEX($W$2:$W$19,MATCH(4,$Y$2:$Y$19,0))&IF(LEN($AB$5)>0," · Vantagem",""),"") | I30: =IFERROR(INDEX($Z$2:$Z$19,MATCH(4,$Y$2:$Y$19,0)),"") | J30: =IFERROR(INDEX($W$2:$W$19,MATCH(9,$Y$2:$Y$19,0))&IF(LEN($AB$10)>0," · Vantagem",""),"") | L30: =IFERROR(INDEX($Z$2:$Z$19,MATCH(9,$Y$2:$Y$19,0)),"")
A31: Percepção Mental | B31: ='Testes'!$I$44 | C31: =IF(OR('Criação'!$Q$25="Xianzhouíta",'Criação'!$Q$25="Avginiano"),"Vantagem ("&'Criação'!$Q$25&")","") | E31: =IF('Testes'!$G$44=0,"",IF('Testes'!$G$44>=0,"+","")&'Testes'!$G$44&" de equipamento/Bênção") | G31: =IFERROR(INDEX($W$2:$W$19,MATCH(5,$Y$2:$Y$19,0))&IF(LEN($AB$6)>0," · Vantagem",""),"") | I31: =IFERROR(INDEX($Z$2:$Z$19,MATCH(5,$Y$2:$Y$19,0)),"") | J31: =IFERROR(INDEX($W$2:$W$19,MATCH(10,$Y$2:$Y$19,0))&IF(LEN($AB$11)>0," · Vantagem",""),"") | L31: =IFERROR(INDEX($Z$2:$Z$19,MATCH(10,$Y$2:$Y$19,0)),"")
A32: Força de Vontade | B32: ='Testes'!$I$45 | C32: =IF(OR('Criação'!$Q$25="Xianzhouíta",'Criação'!$Q$25="Vulpes",'Criação'!$Q$25="Avginiano"),"Vantagem ("&'Criação'!$Q$25&")","") | E32: =IF('Testes'!$G$45=0,"",IF('Testes'!$G$45>=0,"+","")&'Testes'!$G$45&" de equipamento/Bênção") | G32: Usos por combate e descanso (preencha os usados)
A33: Morrendo (DT 10) | B33: ='Testes'!$I$46 | C33: Sucessos | E33: Falhas | G33: =IFERROR(INDEX($S$2:$S$16,MATCH(1,$V$2:$V$16,0))&IF(LEN($AC$2)>0," · "&$AC$2,""),"—") | N33: =IF(AP33>0,"O Google leu como fórmula: digite de novo com ' na frente.","") | AI33: =IF(ISERROR($D$33),"",IF(ISBLANK($D$33),"",$D$33)) | AK33: =IF(ISERROR($F$33),"",IF(ISBLANK($F$33),"",$F$33)) | AO33: =IF(ISERROR($J$33),"",IF(ISBLANK($J$33),"",$J$33)) | AP33: =ISERROR($D$33)*1+ISERROR($F$33)*1+ISERROR($J$33)*1
A34: Morrendo agora | B34: =IF(IF(ISNUMBER($AI$33),$AI$33,0)>=3,"Estabiliza com 1 PV",IF(IF(ISNUMBER($AK$33),$AK$33,0)>=3,"Morre",IF($Q$3="Sim",IF(ISNUMBER($AI$33),$AI$33,0)&" sucesso(s), "&IF(ISNUMBER($AK$33),$AK$33,0)&" falha(s) (0 a 3 cada)","Não está Morrendo")))&IF(LEN('Testes'!$J$46)>0," · Vantagem","") | G34: =IFERROR(INDEX($S$2:$S$16,MATCH(2,$V$2:$V$16,0))&IF(LEN($AC$3)>0," · "&$AC$3,""),"—") | N34: =IF(AP34>0,"O Google leu como fórmula: digite de novo com ' na frente.","") | AP34: =ISERROR($J$34)*1
A35: Condições ativas (21.5) — Quebrado é só de inimigos | G35: =IFERROR(INDEX($S$2:$S$16,MATCH(3,$V$2:$V$16,0))&IF(LEN($AC$4)>0," · "&$AC$4,""),"—") | N35: =IF(AP35>0,"O Google leu como fórmula: digite de novo com ' na frente.","") | AP35: =ISERROR($J$35)*1
A36: Condição (preencha) | C36: Turnos | D36: Ef. aplicador | E36: Efeito (tique por turno) | G36: =IFERROR(INDEX($S$2:$S$16,MATCH(4,$V$2:$V$16,0))&IF(LEN($AC$5)>0," · "&$AC$5,""),"—") | N36: =IF(AP36>0,"O Google leu como fórmula: digite de novo com ' na frente.","") | AP36: =ISERROR($J$36)*1
E37: =IF($AF$37="","",IF(AND(ISNUMBER($AI$37),OR($AF$37="Sangramento",$AF$37="Queimadura",$AF$37="Choque",$AF$37="Aprisionamento")),IF($AF$37="Sangramento",$AD$2,$AD$2&" por turno")&IF($AF$37="Aprisionamento"," · Atrasa 2",""),IF($AF$37="Sangramento","5% dos PV máx. por turno",IF($AF$37="Queimadura","Contínuo 2d6 + Eficiência",IF($AF$37="Choque","Contínuo 1d6 + Eficiência",IF($AF$37="Cisalhamento de Vento","Contínuo 1d6 por acúmulo",IF($AF$37="Embaraço","1d6/acúmulo · Atrasa 1 casa",IF($AF$37="Aprisionamento","1d6 + Ef. · Atrasa 2 casas",IF($AF$37="Lentidão","só move com Esforço Total",IF($AF$37="Marcado","+1 Ataque de quem marcou",IF($AF$37="Silenciado","sem Habilidade de Nível 4+",IF($AF$37="Vulnerável","+1 dado de dano da fonte",IF($AF$37="Controlado","quem aplicou decide ações",IF($AF$37="Corrupção","+1 em toda DC do aplicador",IF($AF$37="Surpreso","casa pulada no 1º Ciclo","veja Regras Rápidas (21.5)"))))))))))))))) | G37: =IFERROR(INDEX($S$2:$S$16,MATCH(5,$V$2:$V$16,0))&IF(LEN($AC$6)>0," · "&$AC$6,""),"—") | N37: =IF(AP37>0,"O Google leu como fórmula: escolha de novo ou digite com ' na frente.","") | AF37: =IF(ISERROR($A$37),"",IF(ISBLANK($A$37),"",$A$37)) | AI37: =IF(ISERROR($D$37),"",IF(ISBLANK($D$37),"",$D$37)) | AP37: =ISERROR($A$37)*1+ISERROR($C$37)*1+ISERROR($D$37)*1+ISERROR($J$37)*1
E38: =IF($AF$38="","",IF(AND(ISNUMBER($AI$38),OR($AF$38="Sangramento",$AF$38="Queimadura",$AF$38="Choque",$AF$38="Aprisionamento")),IF($AF$38="Sangramento",$AD$3,$AD$3&" por turno")&IF($AF$38="Aprisionamento"," · Atrasa 2",""),IF($AF$38="Sangramento","5% dos PV máx. por turno",IF($AF$38="Queimadura","Contínuo 2d6 + Eficiência",IF($AF$38="Choque","Contínuo 1d6 + Eficiência",IF($AF$38="Cisalhamento de Vento","Contínuo 1d6 por acúmulo",IF($AF$38="Embaraço","1d6/acúmulo · Atrasa 1 casa",IF($AF$38="Aprisionamento","1d6 + Ef. · Atrasa 2 casas",IF($AF$38="Lentidão","só move com Esforço Total",IF($AF$38="Marcado","+1 Ataque de quem marcou",IF($AF$38="Silenciado","sem Habilidade de Nível 4+",IF($AF$38="Vulnerável","+1 dado de dano da fonte",IF($AF$38="Controlado","quem aplicou decide ações",IF($AF$38="Corrupção","+1 em toda DC do aplicador",IF($AF$38="Surpreso","casa pulada no 1º Ciclo","veja Regras Rápidas (21.5)"))))))))))))))) | G38: =IFERROR(INDEX($S$2:$S$16,MATCH(6,$V$2:$V$16,0))&IF(LEN($AC$7)>0," · "&$AC$7,""),"—") | N38: =IF(AP38>0,"O Google leu como fórmula: escolha de novo ou digite com ' na frente.","") | AF38: =IF(ISERROR($A$38),"",IF(ISBLANK($A$38),"",$A$38)) | AI38: =IF(ISERROR($D$38),"",IF(ISBLANK($D$38),"",$D$38)) | AP38: =ISERROR($A$38)*1+ISERROR($C$38)*1+ISERROR($D$38)*1+ISERROR($J$38)*1
E39: =IF($AF$39="","",IF(AND(ISNUMBER($AI$39),OR($AF$39="Sangramento",$AF$39="Queimadura",$AF$39="Choque",$AF$39="Aprisionamento")),IF($AF$39="Sangramento",$AD$4,$AD$4&" por turno")&IF($AF$39="Aprisionamento"," · Atrasa 2",""),IF($AF$39="Sangramento","5% dos PV máx. por turno",IF($AF$39="Queimadura","Contínuo 2d6 + Eficiência",IF($AF$39="Choque","Contínuo 1d6 + Eficiência",IF($AF$39="Cisalhamento de Vento","Contínuo 1d6 por acúmulo",IF($AF$39="Embaraço","1d6/acúmulo · Atrasa 1 casa",IF($AF$39="Aprisionamento","1d6 + Ef. · Atrasa 2 casas",IF($AF$39="Lentidão","só move com Esforço Total",IF($AF$39="Marcado","+1 Ataque de quem marcou",IF($AF$39="Silenciado","sem Habilidade de Nível 4+",IF($AF$39="Vulnerável","+1 dado de dano da fonte",IF($AF$39="Controlado","quem aplicou decide ações",IF($AF$39="Corrupção","+1 em toda DC do aplicador",IF($AF$39="Surpreso","casa pulada no 1º Ciclo","veja Regras Rápidas (21.5)"))))))))))))))) | G39: =IFERROR(INDEX($S$2:$S$16,MATCH(7,$V$2:$V$16,0))&IF(LEN($AC$8)>0," · "&$AC$8,""),"—") | N39: =IF(AP39>0,"O Google leu como fórmula: escolha de novo ou digite com ' na frente.","") | AF39: =IF(ISERROR($A$39),"",IF(ISBLANK($A$39),"",$A$39)) | AI39: =IF(ISERROR($D$39),"",IF(ISBLANK($D$39),"",$D$39)) | AP39: =ISERROR($A$39)*1+ISERROR($C$39)*1+ISERROR($D$39)*1+ISERROR($J$39)*1
E40: =IF($AF$40="","",IF(AND(ISNUMBER($AI$40),OR($AF$40="Sangramento",$AF$40="Queimadura",$AF$40="Choque",$AF$40="Aprisionamento")),IF($AF$40="Sangramento",$AD$5,$AD$5&" por turno")&IF($AF$40="Aprisionamento"," · Atrasa 2",""),IF($AF$40="Sangramento","5% dos PV máx. por turno",IF($AF$40="Queimadura","Contínuo 2d6 + Eficiência",IF($AF$40="Choque","Contínuo 1d6 + Eficiência",IF($AF$40="Cisalhamento de Vento","Contínuo 1d6 por acúmulo",IF($AF$40="Embaraço","1d6/acúmulo · Atrasa 1 casa",IF($AF$40="Aprisionamento","1d6 + Ef. · Atrasa 2 casas",IF($AF$40="Lentidão","só move com Esforço Total",IF($AF$40="Marcado","+1 Ataque de quem marcou",IF($AF$40="Silenciado","sem Habilidade de Nível 4+",IF($AF$40="Vulnerável","+1 dado de dano da fonte",IF($AF$40="Controlado","quem aplicou decide ações",IF($AF$40="Corrupção","+1 em toda DC do aplicador",IF($AF$40="Surpreso","casa pulada no 1º Ciclo","veja Regras Rápidas (21.5)"))))))))))))))) | G40: =IFERROR(INDEX($S$2:$S$16,MATCH(8,$V$2:$V$16,0))&IF(LEN($AC$9)>0," · "&$AC$9,""),"—") | N40: =IF(AP40>0,"O Google leu como fórmula: escolha de novo ou digite com ' na frente.","") | AF40: =IF(ISERROR($A$40),"",IF(ISBLANK($A$40),"",$A$40)) | AI40: =IF(ISERROR($D$40),"",IF(ISBLANK($D$40),"",$D$40)) | AP40: =ISERROR($A$40)*1+ISERROR($C$40)*1+ISERROR($D$40)*1+ISERROR($J$40)*1
A42: Em Jogo — Explorando Galáxias v1.2
A43: Legenda: | B43: Entrada (preencha) | C43: Calculada (automático) | D43: Aviso (texto em vermelho) | E43: Título de bloco | F43: Cabeçalho de coluna | G43: Rótulo da linha | H43: Linha alternada (outro tom) | I43: Não se aplica
A44: Tudo que se usa na mesa, numa tela só.

Sheet Testes
A1: Testes — Explorando Galáxias v1.2
A2: Legenda: | B2: Entrada (preencha) | C2: Calculada (automático) | E2: Aviso (texto em vermelho) | G2: Título de bloco | H2: Cabeçalho de coluna | J2: Rótulo da linha | K2: Linha alternada (outro tom) | L2: Não se aplica
A3: As 18 Perícias e os 6 Testes de Resistência com a rolagem pronta.
A5: DT por faixa — 27.2 (a sua faixa) | F5: DT das suas Habilidades: | I5: ='Criação'!$B$56 | J5: Sucesso Automático: bônus total ≥ DT → não rola (só Perícia, 27.2)
A6: Dificuldade | B6: DT
A7: =INDEX('Dados'!$A$424:$A$429,1) | B7: =INDEX('Dados'!$A$424:$F$429,1,'Criação'!$B$14+1)
A8: =INDEX('Dados'!$A$424:$A$429,2) | B8: =INDEX('Dados'!$A$424:$F$429,2,'Criação'!$B$14+1)
A9: =INDEX('Dados'!$A$424:$A$429,3) | B9: =INDEX('Dados'!$A$424:$F$429,3,'Criação'!$B$14+1)
A10: =INDEX('Dados'!$A$424:$A$429,4) | B10: =INDEX('Dados'!$A$424:$F$429,4,'Criação'!$B$14+1)
A11: =INDEX('Dados'!$A$424:$A$429,5) | B11: =INDEX('Dados'!$A$424:$F$429,5,'Criação'!$B$14+1)
A12: =INDEX('Dados'!$A$424:$A$429,6) | B12: =INDEX('Dados'!$A$424:$F$429,6,'Criação'!$B$14+1)
A14: Perícias — 04.4 (rolagem pronta: d20 + Bônus + Eficiência)
A15: Perícia (Poder, Agilidade e Vigor) | B15: Atributo | C15: Bônus | D15: Eficiência (origem) | E15: Eficácia (preencha Sim) | F15: Penalidade (Armadura Pesada) | G15: Extra (equipamento) | H15: Total | I15: Rolagem | J15: Vantagem racial | K15: Sucesso Automático até | L15: Aviso
A16: Atletismo | B16: ='Criação'!$B$69 | C16: =IFERROR(INDEX('Criação'!$F$44:$F$49,MATCH($B$16,'Criação'!$A$44:$A$49,0)),0) | D16: =IF('Criação'!$E$69="Sim","Sim ("&'Criação'!$F$69&")","Não") | F16: =IF($B$16="Agilidade",'Criação'!$E$93,0) | G16: =IF('Equipamento'!$L$31="Atletismo",'Equipamento'!$K$31,0)+MIN('Criação'!$J$14,COUNTIF('Equipamento'!$P$45:$P$47,"Atletismo")) | H16: =$C$16+IF('Criação'!$E$69="Sim",IF(AND($N$16="Sim",'Criação'!$E$69="Sim",COUNTIF($N$16,"Sim")<='Criação'!$E$14),2*'Criação'!$C$14,'Criação'!$C$14),0)+$F$16+$G$16 | I16: ="d20"&IF($H$16>=0,"+","")&$H$16 | J16: ="" | K16: =IF($H$16>=$B$12,"Heroica ("&$B$12&")",IF($H$16>=$B$11,"Muito Difícil ("&$B$11&")",IF($H$16>=$B$10,"Difícil ("&$B$10&")",IF($H$16>=$B$9,"Média ("&$B$9&")",IF($H$16>=$B$8,"Fácil ("&$B$8&")",IF($H$16>=$B$7,"Trivial ("&$B$7&")","—")))))) | L16: =IF(O16>0,"O Google leu como fórmula: escolha de novo na lista.",IF($N$16<>"Sim","",IF('Criação'!$E$69<>"Sim","Eficácia exige Eficiência nesta Perícia",IF(COUNTIF($N$16,"Sim")>'Criação'!$E$14,"Acima dos slots de Eficácia em Perícias ("&'Criação'!$E$14&")","")))) | N16: =IF(ISERROR($E$16),"",IF(ISBLANK($E$16),"",$E$16)) | O16: =ISERROR($E$16)*1
A17: Acrobacia | B17: ='Criação'!$B$70 | C17: =IFERROR(INDEX('Criação'!$F$44:$F$49,MATCH($B$17,'Criação'!$A$44:$A$49,0)),0) | D17: =IF('Criação'!$E$70="Sim","Sim ("&'Criação'!$F$70&")","Não") | F17: =IF($B$17="Agilidade",'Criação'!$E$93,0) | G17: =IF('Equipamento'!$L$31="Acrobacia",'Equipamento'!$K$31,0)+MIN('Criação'!$J$14,COUNTIF('Equipamento'!$P$45:$P$47,"Acrobacia")) | H17: =$C$17+IF('Criação'!$E$70="Sim",IF(AND($N$17="Sim",'Criação'!$E$70="Sim",COUNTIF($N$16:$N$17,"Sim")<='Criação'!$E$14),2*'Criação'!$C$14,'Criação'!$C$14),0)+$F$17+$G$17 | I17: ="d20"&IF($H$17>=0,"+","")&$H$17 | J17: ="" | K17: =IF($H$17>=$B$12,"Heroica ("&$B$12&")",IF($H$17>=$B$11,"Muito Difícil ("&$B$11&")",IF($H$17>=$B$10,"Difícil ("&$B$10&")",IF($H$17>=$B$9,"Média ("&$B$9&")",IF($H$17>=$B$8,"Fácil ("&$B$8&")",IF($H$17>=$B$7,"Trivial ("&$B$7&")","—")))))) | L17: =IF(O17>0,"O Google leu como fórmula: escolha de novo na lista.",IF($N$17<>"Sim","",IF('Criação'!$E$70<>"Sim","Eficácia exige Eficiência nesta Perícia",IF(COUNTIF($N$16:$N$17,"Sim")>'Criação'!$E$14,"Acima dos slots de Eficácia em Perícias ("&'Criação'!$E$14&")","")))) | N17: =IF(ISERROR($E$17),"",IF(ISBLANK($E$17),"",$E$17)) | O17: =ISERROR($E$17)*1
A18: Furtividade | B18: ='Criação'!$B$71 | C18: =IFERROR(INDEX('Criação'!$F$44:$F$49,MATCH($B$18,'Criação'!$A$44:$A$49,0)),0) | D18: =IF('Criação'!$E$71="Sim","Sim ("&'Criação'!$F$71&")","Não") | F18: =IF($B$18="Agilidade",'Criação'!$E$93,0) | G18: =IF('Equipamento'!$L$31="Furtividade",'Equipamento'!$K$31,0)+MIN('Criação'!$J$14,COUNTIF('Equipamento'!$P$45:$P$47,"Furtividade")) | H18: =$C$18+IF('Criação'!$E$71="Sim",IF(AND($N$18="Sim",'Criação'!$E$71="Sim",COUNTIF($N$16:$N$18,"Sim")<='Criação'!$E$14),2*'Criação'!$C$14,'Criação'!$C$14),0)+$F$18+$G$18 | I18: ="d20"&IF($H$18>=0,"+","")&$H$18 | J18: ="" | K18: =IF($H$18>=$B$12,"Heroica ("&$B$12&")",IF($H$18>=$B$11,"Muito Difícil ("&$B$11&")",IF($H$18>=$B$10,"Difícil ("&$B$10&")",IF($H$18>=$B$9,"Média ("&$B$9&")",IF($H$18>=$B$8,"Fácil ("&$B$8&")",IF($H$18>=$B$7,"Trivial ("&$B$7&")","—")))))) | L18: =IF(O18>0,"O Google leu como fórmula: escolha de novo na lista.",IF($N$18<>"Sim","",IF('Criação'!$E$71<>"Sim","Eficácia exige Eficiência nesta Perícia",IF(COUNTIF($N$16:$N$18,"Sim")>'Criação'!$E$14,"Acima dos slots de Eficácia em Perícias ("&'Criação'!$E$14&")","")))) | N18: =IF(ISERROR($E$18),"",IF(ISBLANK($E$18),"",$E$18)) | O18: =ISERROR($E$18)*1
A19: Pilotagem | B19: ='Criação'!$B$72 | C19: =IFERROR(INDEX('Criação'!$F$44:$F$49,MATCH($B$19,'Criação'!$A$44:$A$49,0)),0) | D19: =IF('Criação'!$E$72="Sim","Sim ("&'Criação'!$F$72&")","Não") | F19: =IF($B$19="Agilidade",'Criação'!$E$93,0) | G19: =IF('Equipamento'!$L$31="Pilotagem",'Equipamento'!$K$31,0)+MIN('Criação'!$J$14,COUNTIF('Equipamento'!$P$45:$P$47,"Pilotagem")) | H19: =$C$19+IF('Criação'!$E$72="Sim",IF(AND($N$19="Sim",'Criação'!$E$72="Sim",COUNTIF($N$16:$N$19,"Sim")<='Criação'!$E$14),2*'Criação'!$C$14,'Criação'!$C$14),0)+$F$19+$G$19 | I19: ="d20"&IF($H$19>=0,"+","")&$H$19 | J19: ="" | K19: =IF($H$19>=$B$12,"Heroica ("&$B$12&")",IF($H$19>=$B$11,"Muito Difícil ("&$B$11&")",IF($H$19>=$B$10,"Difícil ("&$B$10&")",IF($H$19>=$B$9,"Média ("&$B$9&")",IF($H$19>=$B$8,"Fácil ("&$B$8&")",IF($H$19>=$B$7,"Trivial ("&$B$7&")","—")))))) | L19: =IF(O19>0,"O Google leu como fórmula: escolha de novo na lista.",IF($N$19<>"Sim","",IF('Criação'!$E$72<>"Sim","Eficácia exige Eficiência nesta Perícia",IF(COUNTIF($N$16:$N$19,"Sim")>'Criação'!$E$14,"Acima dos slots de Eficácia em Perícias ("&'Criação'!$E$14&")","")))) | N19: =IF(ISERROR($E$19),"",IF(ISBLANK($E$19),"",$E$19)) | O19: =ISERROR($E$19)*1
A20: Resistência | B20: ='Criação'!$B$73 | C20: =IFERROR(INDEX('Criação'!$F$44:$F$49,MATCH($B$20,'Criação'!$A$44:$A$49,0)),0) | D20: =IF('Criação'!$E$73="Sim","Sim ("&'Criação'!$F$73&")","Não") | F20: =IF($B$20="Agilidade",'Criação'!$E$93,0) | G20: =IF('Equipamento'!$L$31="Resistência",'Equipamento'!$K$31,0)+MIN('Criação'!$J$14,COUNTIF('Equipamento'!$P$45:$P$47,"Resistência")) | H20: =$C$20+IF('Criação'!$E$73="Sim",IF(AND($N$20="Sim",'Criação'!$E$73="Sim",COUNTIF($N$16:$N$20,"Sim")<='Criação'!$E$14),2*'Criação'!$C$14,'Criação'!$C$14),0)+$F$20+$G$20 | I20: ="d20"&IF($H$20>=0,"+","")&$H$20 | J20: ="" | K20: =IF($H$20>=$B$12,"Heroica ("&$B$12&")",IF($H$20>=$B$11,"Muito Difícil ("&$B$11&")",IF($H$20>=$B$10,"Difícil ("&$B$10&")",IF($H$20>=$B$9,"Média ("&$B$9&")",IF($H$20>=$B$8,"Fácil ("&$B$8&")",IF($H$20>=$B$7,"Trivial ("&$B$7&")","—")))))) | L20: =IF(O20>0,"O Google leu como fórmula: escolha de novo na lista.",IF($N$20<>"Sim","",IF('Criação'!$E$73<>"Sim","Eficácia exige Eficiência nesta Perícia",IF(COUNTIF($N$16:$N$20,"Sim")>'Criação'!$E$14,"Acima dos slots de Eficácia em Perícias ("&'Criação'!$E$14&")","")))) | N20: =IF(ISERROR($E$20),"",IF(ISBLANK($E$20),"",$E$20)) | O20: =ISERROR($E$20)*1
A21: Perícia (Sincronia e Discernimento) | B21: Atributo | C21: Bônus | D21: Eficiência (origem) | E21: Eficácia (preencha Sim) | F21: Penalidade (Armadura Pesada) | G21: Extra (equipamento) | H21: Total | I21: Rolagem | J21: Vantagem racial | K21: Sucesso Automático até | L21: Aviso | N21: =IF(ISERROR($E$21),"",IF(ISBLANK($E$21),"",$E$21))
A22: Tecnologia | B22: ='Criação'!$B$75 | C22: =IFERROR(INDEX('Criação'!$F$44:$F$49,MATCH($B$22,'Criação'!$A$44:$A$49,0)),0) | D22: =IF('Criação'!$E$75="Sim","Sim ("&'Criação'!$F$75&")","Não") | F22: =IF($B$22="Agilidade",'Criação'!$E$93,0) | G22: =IF('Equipamento'!$L$31="Tecnologia",'Equipamento'!$K$31,0)+MIN('Criação'!$J$14,COUNTIF('Equipamento'!$P$45:$P$47,"Tecnologia")) | H22: =$C$22+IF('Criação'!$E$75="Sim",IF(AND($N$22="Sim",'Criação'!$E$75="Sim",COUNTIF($N$16:$N$22,"Sim")<='Criação'!$E$14),2*'Criação'!$C$14,'Criação'!$C$14),0)+$F$22+$G$22 | I22: ="d20"&IF($H$22>=0,"+","")&$H$22 | J22: =IF(OR('Criação'!$Q$25="Intellitron"),"Vantagem ("&'Criação'!$Q$25&")","") | K22: =IF($H$22>=$B$12,"Heroica ("&$B$12&")",IF($H$22>=$B$11,"Muito Difícil ("&$B$11&")",IF($H$22>=$B$10,"Difícil ("&$B$10&")",IF($H$22>=$B$9,"Média ("&$B$9&")",IF($H$22>=$B$8,"Fácil ("&$B$8&")",IF($H$22>=$B$7,"Trivial ("&$B$7&")","—")))))) | L22: =IF(O22>0,"O Google leu como fórmula: escolha de novo na lista.",IF($N$22<>"Sim","",IF('Criação'!$E$75<>"Sim","Eficácia exige Eficiência nesta Perícia",IF(COUNTIF($N$16:$N$22,"Sim")>'Criação'!$E$14,"Acima dos slots de Eficácia em Perícias ("&'Criação'!$E$14&")","")))) | N22: =IF(ISERROR($E$22),"",IF(ISBLANK($E$22),"",$E$22)) | O22: =ISERROR($E$22)*1
A23: Pesquisa | B23: ='Criação'!$B$76 | C23: =IFERROR(INDEX('Criação'!$F$44:$F$49,MATCH($B$23,'Criação'!$A$44:$A$49,0)),0) | D23: =IF('Criação'!$E$76="Sim","Sim ("&'Criação'!$F$76&")","Não") | F23: =IF($B$23="Agilidade",'Criação'!$E$93,0) | G23: =IF('Equipamento'!$L$31="Pesquisa",'Equipamento'!$K$31,0)+MIN('Criação'!$J$14,COUNTIF('Equipamento'!$P$45:$P$47,"Pesquisa")) | H23: =$C$23+IF('Criação'!$E$76="Sim",IF(AND($N$23="Sim",'Criação'!$E$76="Sim",COUNTIF($N$16:$N$23,"Sim")<='Criação'!$E$14),2*'Criação'!$C$14,'Criação'!$C$14),0)+$F$23+$G$23 | I23: ="d20"&IF($H$23>=0,"+","")&$H$23 | J23: ="" | K23: =IF($H$23>=$B$12,"Heroica ("&$B$12&")",IF($H$23>=$B$11,"Muito Difícil ("&$B$11&")",IF($H$23>=$B$10,"Difícil ("&$B$10&")",IF($H$23>=$B$9,"Média ("&$B$9&")",IF($H$23>=$B$8,"Fácil ("&$B$8&")",IF($H$23>=$B$7,"Trivial ("&$B$7&")","—")))))) | L23: =IF(O23>0,"O Google leu como fórmula: escolha de novo na lista.",IF($N$23<>"Sim","",IF('Criação'!$E$76<>"Sim","Eficácia exige Eficiência nesta Perícia",IF(COUNTIF($N$16:$N$23,"Sim")>'Criação'!$E$14,"Acima dos slots de Eficácia em Perícias ("&'Criação'!$E$14&")","")))) | N23: =IF(ISERROR($E$23),"",IF(ISBLANK($E$23),"",$E$23)) | O23: =ISERROR($E$23)*1
A24: Ciência | B24: ='Criação'!$B$77 | C24: =IFERROR(INDEX('Criação'!$F$44:$F$49,MATCH($B$24,'Criação'!$A$44:$A$49,0)),0) | D24: =IF('Criação'!$E$77="Sim","Sim ("&'Criação'!$F$77&")","Não") | F24: =IF($B$24="Agilidade",'Criação'!$E$93,0) | G24: =IF('Equipamento'!$L$31="Ciência",'Equipamento'!$K$31,0)+MIN('Criação'!$J$14,COUNTIF('Equipamento'!$P$45:$P$47,"Ciência")) | H24: =$C$24+IF('Criação'!$E$77="Sim",IF(AND($N$24="Sim",'Criação'!$E$77="Sim",COUNTIF($N$16:$N$24,"Sim")<='Criação'!$E$14),2*'Criação'!$C$14,'Criação'!$C$14),0)+$F$24+$G$24 | I24: ="d20"&IF($H$24>=0,"+","")&$H$24 | J24: ="" | K24: =IF($H$24>=$B$12,"Heroica ("&$B$12&")",IF($H$24>=$B$11,"Muito Difícil ("&$B$11&")",IF($H$24>=$B$10,"Difícil ("&$B$10&")",IF($H$24>=$B$9,"Média ("&$B$9&")",IF($H$24>=$B$8,"Fácil ("&$B$8&")",IF($H$24>=$B$7,"Trivial ("&$B$7&")","—")))))) | L24: =IF(O24>0,"O Google leu como fórmula: escolha de novo na lista.",IF($N$24<>"Sim","",IF('Criação'!$E$77<>"Sim","Eficácia exige Eficiência nesta Perícia",IF(COUNTIF($N$16:$N$24,"Sim")>'Criação'!$E$14,"Acima dos slots de Eficácia em Perícias ("&'Criação'!$E$14&")","")))) | N24: =IF(ISERROR($E$24),"",IF(ISBLANK($E$24),"",$E$24)) | O24: =ISERROR($E$24)*1
A25: Mecânica | B25: ='Criação'!$B$78 | C25: =IFERROR(INDEX('Criação'!$F$44:$F$49,MATCH($B$25,'Criação'!$A$44:$A$49,0)),0) | D25: =IF('Criação'!$E$78="Sim","Sim ("&'Criação'!$F$78&")","Não") | F25: =IF($B$25="Agilidade",'Criação'!$E$93,0) | G25: =IF('Equipamento'!$L$31="Mecânica",'Equipamento'!$K$31,0)+MIN('Criação'!$J$14,COUNTIF('Equipamento'!$P$45:$P$47,"Mecânica")) | H25: =$C$25+IF('Criação'!$E$78="Sim",IF(AND($N$25="Sim",'Criação'!$E$78="Sim",COUNTIF($N$16:$N$25,"Sim")<='Criação'!$E$14),2*'Criação'!$C$14,'Criação'!$C$14),0)+$F$25+$G$25 | I25: ="d20"&IF($H$25>=0,"+","")&$H$25 | J25: =IF(OR('Criação'!$Q$25="Intellitron"),"Vantagem ("&'Criação'!$Q$25&")","") | K25: =IF($H$25>=$B$12,"Heroica ("&$B$12&")",IF($H$25>=$B$11,"Muito Difícil ("&$B$11&")",IF($H$25>=$B$10,"Difícil ("&$B$10&")",IF($H$25>=$B$9,"Média ("&$B$9&")",IF($H$25>=$B$8,"Fácil ("&$B$8&")",IF($H$25>=$B$7,"Trivial ("&$B$7&")","—")))))) | L25: =IF(O25>0,"O Google leu como fórmula: escolha de novo na lista.",IF($N$25<>"Sim","",IF('Criação'!$E$78<>"Sim","Eficácia exige Eficiência nesta Perícia",IF(COUNTIF($N$16:$N$25,"Sim")>'Criação'!$E$14,"Acima dos slots de Eficácia em Perícias ("&'Criação'!$E$14&")","")))) | N25: =IF(ISERROR($E$25),"",IF(ISBLANK($E$25),"",$E$25)) | O25: =ISERROR($E$25)*1
A26: Percepção | B26: ='Criação'!$B$79 | C26: =IFERROR(INDEX('Criação'!$F$44:$F$49,MATCH($B$26,'Criação'!$A$44:$A$49,0)),0) | D26: =IF('Criação'!$E$79="Sim","Sim ("&'Criação'!$F$79&")","Não") | F26: =IF($B$26="Agilidade",'Criação'!$E$93,0) | G26: =IF('Equipamento'!$L$31="Percepção",'Equipamento'!$K$31,0)+MIN('Criação'!$J$14,COUNTIF('Equipamento'!$P$45:$P$47,"Percepção")) | H26: =$C$26+IF('Criação'!$E$79="Sim",IF(AND($N$26="Sim",'Criação'!$E$79="Sim",COUNTIF($N$16:$N$26,"Sim")<='Criação'!$E$14),2*'Criação'!$C$14,'Criação'!$C$14),0)+$F$26+$G$26 | I26: ="d20"&IF($H$26>=0,"+","")&$H$26 | J26: ="" | K26: =IF($H$26>=$B$12,"Heroica ("&$B$12&")",IF($H$26>=$B$11,"Muito Difícil ("&$B$11&")",IF($H$26>=$B$10,"Difícil ("&$B$10&")",IF($H$26>=$B$9,"Média ("&$B$9&")",IF($H$26>=$B$8,"Fácil ("&$B$8&")",IF($H$26>=$B$7,"Trivial ("&$B$7&")","—")))))) | L26: =IF(O26>0,"O Google leu como fórmula: escolha de novo na lista.",IF($N$26<>"Sim","",IF('Criação'!$E$79<>"Sim","Eficácia exige Eficiência nesta Perícia",IF(COUNTIF($N$16:$N$26,"Sim")>'Criação'!$E$14,"Acima dos slots de Eficácia em Perícias ("&'Criação'!$E$14&")","")))) | N26: =IF(ISERROR($E$26),"",IF(ISBLANK($E$26),"",$E$26)) | O26: =ISERROR($E$26)*1
A27: Sobrevivência | B27: ='Criação'!$B$80 | C27: =IFERROR(INDEX('Criação'!$F$44:$F$49,MATCH($B$27,'Criação'!$A$44:$A$49,0)),0) | D27: =IF('Criação'!$E$80="Sim","Sim ("&'Criação'!$F$80&")","Não") | F27: =IF($B$27="Agilidade",'Criação'!$E$93,0) | G27: =IF('Equipamento'!$L$31="Sobrevivência",'Equipamento'!$K$31,0)+MIN('Criação'!$J$14,COUNTIF('Equipamento'!$P$45:$P$47,"Sobrevivência")) | H27: =$C$27+IF('Criação'!$E$80="Sim",IF(AND($N$27="Sim",'Criação'!$E$80="Sim",COUNTIF($N$16:$N$27,"Sim")<='Criação'!$E$14),2*'Criação'!$C$14,'Criação'!$C$14),0)+$F$27+$G$27 | I27: ="d20"&IF($H$27>=0,"+","")&$H$27 | J27: ="" | K27: =IF($H$27>=$B$12,"Heroica ("&$B$12&")",IF($H$27>=$B$11,"Muito Difícil ("&$B$11&")",IF($H$27>=$B$10,"Difícil ("&$B$10&")",IF($H$27>=$B$9,"Média ("&$B$9&")",IF($H$27>=$B$8,"Fácil ("&$B$8&")",IF($H$27>=$B$7,"Trivial ("&$B$7&")","—")))))) | L27: =IF(O27>0,"O Google leu como fórmula: escolha de novo na lista.",IF($N$27<>"Sim","",IF('Criação'!$E$80<>"Sim","Eficácia exige Eficiência nesta Perícia",IF(COUNTIF($N$16:$N$27,"Sim")>'Criação'!$E$14,"Acima dos slots de Eficácia em Perícias ("&'Criação'!$E$14&")","")))) | N27: =IF(ISERROR($E$27),"",IF(ISBLANK($E$27),"",$E$27)) | O27: =ISERROR($E$27)*1
A28: Intuição | B28: ='Criação'!$B$81 | C28: =IFERROR(INDEX('Criação'!$F$44:$F$49,MATCH($B$28,'Criação'!$A$44:$A$49,0)),0) | D28: =IF('Criação'!$E$81="Sim","Sim ("&'Criação'!$F$81&")","Não") | F28: =IF($B$28="Agilidade",'Criação'!$E$93,0) | G28: =IF('Equipamento'!$L$31="Intuição",'Equipamento'!$K$31,0)+MIN('Criação'!$J$14,COUNTIF('Equipamento'!$P$45:$P$47,"Intuição")) | H28: =$C$28+IF('Criação'!$E$81="Sim",IF(AND($N$28="Sim",'Criação'!$E$81="Sim",COUNTIF($N$16:$N$28,"Sim")<='Criação'!$E$14),2*'Criação'!$C$14,'Criação'!$C$14),0)+$F$28+$G$28 | I28: ="d20"&IF($H$28>=0,"+","")&$H$28 | J28: ="" | K28: =IF($H$28>=$B$12,"Heroica ("&$B$12&")",IF($H$28>=$B$11,"Muito Difícil ("&$B$11&")",IF($H$28>=$B$10,"Difícil ("&$B$10&")",IF($H$28>=$B$9,"Média ("&$B$9&")",IF($H$28>=$B$8,"Fácil ("&$B$8&")",IF($H$28>=$B$7,"Trivial ("&$B$7&")","—")))))) | L28: =IF(O28>0,"O Google leu como fórmula: escolha de novo na lista.",IF($N$28<>"Sim","",IF('Criação'!$E$81<>"Sim","Eficácia exige Eficiência nesta Perícia",IF(COUNTIF($N$16:$N$28,"Sim")>'Criação'!$E$14,"Acima dos slots de Eficácia em Perícias ("&'Criação'!$E$14&")","")))) | N28: =IF(ISERROR($E$28),"",IF(ISBLANK($E$28),"",$E$28)) | O28: =ISERROR($E$28)*1
A29: Investigação | B29: ='Criação'!$B$82 | C29: =IFERROR(INDEX('Criação'!$F$44:$F$49,MATCH($B$29,'Criação'!$A$44:$A$49,0)),0) | D29: =IF('Criação'!$E$82="Sim","Sim ("&'Criação'!$F$82&")","Não") | F29: =IF($B$29="Agilidade",'Criação'!$E$93,0) | G29: =IF('Equipamento'!$L$31="Investigação",'Equipamento'!$K$31,0)+MIN('Criação'!$J$14,COUNTIF('Equipamento'!$P$45:$P$47,"Investigação")) | H29: =$C$29+IF('Criação'!$E$82="Sim",IF(AND($N$29="Sim",'Criação'!$E$82="Sim",COUNTIF($N$16:$N$29,"Sim")<='Criação'!$E$14),2*'Criação'!$C$14,'Criação'!$C$14),0)+$F$29+$G$29 | I29: ="d20"&IF($H$29>=0,"+","")&$H$29 | J29: ="" | K29: =IF($H$29>=$B$12,"Heroica ("&$B$12&")",IF($H$29>=$B$11,"Muito Difícil ("&$B$11&")",IF($H$29>=$B$10,"Difícil ("&$B$10&")",IF($H$29>=$B$9,"Média ("&$B$9&")",IF($H$29>=$B$8,"Fácil ("&$B$8&")",IF($H$29>=$B$7,"Trivial ("&$B$7&")","—")))))) | L29: =IF(O29>0,"O Google leu como fórmula: escolha de novo na lista.",IF($N$29<>"Sim","",IF('Criação'!$E$82<>"Sim","Eficácia exige Eficiência nesta Perícia",IF(COUNTIF($N$16:$N$29,"Sim")>'Criação'!$E$14,"Acima dos slots de Eficácia em Perícias ("&'Criação'!$E$14&")","")))) | N29: =IF(ISERROR($E$29),"",IF(ISBLANK($E$29),"",$E$29)) | O29: =ISERROR($E$29)*1
A30: Perícia (Presença e Sintonia) | B30: Atributo | C30: Bônus | D30: Eficiência (origem) | E30: Eficácia (preencha Sim) | F30: Penalidade (Armadura Pesada) | G30: Extra (equipamento) | H30: Total | I30: Rolagem | J30: Vantagem racial | K30: Sucesso Automático até | L30: Aviso | N30: =IF(ISERROR($E$30),"",IF(ISBLANK($E$30),"",$E$30))
A31: Persuasão | B31: ='Criação'!$B$84 | C31: =IFERROR(INDEX('Criação'!$F$44:$F$49,MATCH($B$31,'Criação'!$A$44:$A$49,0)),0) | D31: =IF('Criação'!$E$84="Sim","Sim ("&'Criação'!$F$84&")","Não") | F31: =IF($B$31="Agilidade",'Criação'!$E$93,0) | G31: =IF('Equipamento'!$L$31="Persuasão",'Equipamento'!$K$31,0)+MIN('Criação'!$J$14,COUNTIF('Equipamento'!$P$45:$P$47,"Persuasão")) | H31: =$C$31+IF('Criação'!$E$84="Sim",IF(AND($N$31="Sim",'Criação'!$E$84="Sim",COUNTIF($N$16:$N$31,"Sim")<='Criação'!$E$14),2*'Criação'!$C$14,'Criação'!$C$14),0)+$F$31+$G$31 | I31: ="d20"&IF($H$31>=0,"+","")&$H$31 | J31: =IF(OR('Criação'!$Q$25="Vulpes"),"Vantagem ("&'Criação'!$Q$25&")","") | K31: =IF($H$31>=$B$12,"Heroica ("&$B$12&")",IF($H$31>=$B$11,"Muito Difícil ("&$B$11&")",IF($H$31>=$B$10,"Difícil ("&$B$10&")",IF($H$31>=$B$9,"Média ("&$B$9&")",IF($H$31>=$B$8,"Fácil ("&$B$8&")",IF($H$31>=$B$7,"Trivial ("&$B$7&")","—")))))) | L31: =IF(O31>0,"O Google leu como fórmula: escolha de novo na lista.",IF($N$31<>"Sim","",IF('Criação'!$E$84<>"Sim","Eficácia exige Eficiência nesta Perícia",IF(COUNTIF($N$16:$N$31,"Sim")>'Criação'!$E$14,"Acima dos slots de Eficácia em Perícias ("&'Criação'!$E$14&")","")))) | N31: =IF(ISERROR($E$31),"",IF(ISBLANK($E$31),"",$E$31)) | O31: =ISERROR($E$31)*1
A32: Intimidação | B32: ='Criação'!$B$85 | C32: =IFERROR(INDEX('Criação'!$F$44:$F$49,MATCH($B$32,'Criação'!$A$44:$A$49,0)),0) | D32: =IF('Criação'!$E$85="Sim","Sim ("&'Criação'!$F$85&")","Não") | F32: =IF($B$32="Agilidade",'Criação'!$E$93,0) | G32: =IF('Equipamento'!$L$31="Intimidação",'Equipamento'!$K$31,0)+MIN('Criação'!$J$14,COUNTIF('Equipamento'!$P$45:$P$47,"Intimidação")) | H32: =$C$32+IF('Criação'!$E$85="Sim",IF(AND($N$32="Sim",'Criação'!$E$85="Sim",COUNTIF($N$16:$N$32,"Sim")<='Criação'!$E$14),2*'Criação'!$C$14,'Criação'!$C$14),0)+$F$32+$G$32 | I32: ="d20"&IF($H$32>=0,"+","")&$H$32 | J32: =IF(OR('Criação'!$Q$25="Vulpes"),"Vantagem ("&'Criação'!$Q$25&")","") | K32: =IF($H$32>=$B$12,"Heroica ("&$B$12&")",IF($H$32>=$B$11,"Muito Difícil ("&$B$11&")",IF($H$32>=$B$10,"Difícil ("&$B$10&")",IF($H$32>=$B$9,"Média ("&$B$9&")",IF($H$32>=$B$8,"Fácil ("&$B$8&")",IF($H$32>=$B$7,"Trivial ("&$B$7&")","—")))))) | L32: =IF(O32>0,"O Google leu como fórmula: escolha de novo na lista.",IF($N$32<>"Sim","",IF('Criação'!$E$85<>"Sim","Eficácia exige Eficiência nesta Perícia",IF(COUNTIF($N$16:$N$32,"Sim")>'Criação'!$E$14,"Acima dos slots de Eficácia em Perícias ("&'Criação'!$E$14&")","")))) | N32: =IF(ISERROR($E$32),"",IF(ISBLANK($E$32),"",$E$32)) | O32: =ISERROR($E$32)*1
A33: Enganação | B33: ='Criação'!$B$86 | C33: =IFERROR(INDEX('Criação'!$F$44:$F$49,MATCH($B$33,'Criação'!$A$44:$A$49,0)),0) | D33: =IF('Criação'!$E$86="Sim","Sim ("&'Criação'!$F$86&")","Não") | F33: =IF($B$33="Agilidade",'Criação'!$E$93,0) | G33: =IF('Equipamento'!$L$31="Enganação",'Equipamento'!$K$31,0)+MIN('Criação'!$J$14,COUNTIF('Equipamento'!$P$45:$P$47,"Enganação")) | H33: =$C$33+IF('Criação'!$E$86="Sim",IF(AND($N$33="Sim",'Criação'!$E$86="Sim",COUNTIF($N$16:$N$33,"Sim")<='Criação'!$E$14),2*'Criação'!$C$14,'Criação'!$C$14),0)+$F$33+$G$33 | I33: ="d20"&IF($H$33>=0,"+","")&$H$33 | J33: =IF(OR('Criação'!$Q$25="Vulpes"),"Vantagem ("&'Criação'!$Q$25&")","") | K33: =IF($H$33>=$B$12,"Heroica ("&$B$12&")",IF($H$33>=$B$11,"Muito Difícil ("&$B$11&")",IF($H$33>=$B$10,"Difícil ("&$B$10&")",IF($H$33>=$B$9,"Média ("&$B$9&")",IF($H$33>=$B$8,"Fácil ("&$B$8&")",IF($H$33>=$B$7,"Trivial ("&$B$7&")","—")))))) | L33: =IF(O33>0,"O Google leu como fórmula: escolha de novo na lista.",IF($N$33<>"Sim","",IF('Criação'!$E$86<>"Sim","Eficácia exige Eficiência nesta Perícia",IF(COUNTIF($N$16:$N$33,"Sim")>'Criação'!$E$14,"Acima dos slots de Eficácia em Perícias ("&'Criação'!$E$14&")","")))) | N33: =IF(ISERROR($E$33),"",IF(ISBLANK($E$33),"",$E$33)) | O33: =ISERROR($E$33)*1
A34: Liderança | B34: ='Criação'!$B$87 | C34: =IFERROR(INDEX('Criação'!$F$44:$F$49,MATCH($B$34,'Criação'!$A$44:$A$49,0)),0) | D34: =IF('Criação'!$E$87="Sim","Sim ("&'Criação'!$F$87&")","Não") | F34: =IF($B$34="Agilidade",'Criação'!$E$93,0) | G34: =IF('Equipamento'!$L$31="Liderança",'Equipamento'!$K$31,0)+MIN('Criação'!$J$14,COUNTIF('Equipamento'!$P$45:$P$47,"Liderança")) | H34: =$C$34+IF('Criação'!$E$87="Sim",IF(AND($N$34="Sim",'Criação'!$E$87="Sim",COUNTIF($N$16:$N$34,"Sim")<='Criação'!$E$14),2*'Criação'!$C$14,'Criação'!$C$14),0)+$F$34+$G$34 | I34: ="d20"&IF($H$34>=0,"+","")&$H$34 | J34: =IF(OR('Criação'!$Q$25="Vulpes"),"Vantagem ("&'Criação'!$Q$25&")","") | K34: =IF($H$34>=$B$12,"Heroica ("&$B$12&")",IF($H$34>=$B$11,"Muito Difícil ("&$B$11&")",IF($H$34>=$B$10,"Difícil ("&$B$10&")",IF($H$34>=$B$9,"Média ("&$B$9&")",IF($H$34>=$B$8,"Fácil ("&$B$8&")",IF($H$34>=$B$7,"Trivial ("&$B$7&")","—")))))) | L34: =IF(O34>0,"O Google leu como fórmula: escolha de novo na lista.",IF($N$34<>"Sim","",IF('Criação'!$E$87<>"Sim","Eficácia exige Eficiência nesta Perícia",IF(COUNTIF($N$16:$N$34,"Sim")>'Criação'!$E$14,"Acima dos slots de Eficácia em Perícias ("&'Criação'!$E$14&")","")))) | N34: =IF(ISERROR($E$34),"",IF(ISBLANK($E$34),"",$E$34)) | O34: =ISERROR($E$34)*1
A35: Sintonia | B35: ='Criação'!$B$88 | C35: =IFERROR(INDEX('Criação'!$F$44:$F$49,MATCH($B$35,'Criação'!$A$44:$A$49,0)),0) | D35: =IF('Criação'!$E$88="Sim","Sim ("&'Criação'!$F$88&")","Não") | F35: =IF($B$35="Agilidade",'Criação'!$E$93,0) | G35: =IF('Equipamento'!$L$31="Sintonia",'Equipamento'!$K$31,0)+MIN('Criação'!$J$14,COUNTIF('Equipamento'!$P$45:$P$47,"Sintonia")) | H35: =$C$35+IF('Criação'!$E$88="Sim",IF(AND($N$35="Sim",'Criação'!$E$88="Sim",COUNTIF($N$16:$N$35,"Sim")<='Criação'!$E$14),2*'Criação'!$C$14,'Criação'!$C$14),0)+$F$35+$G$35 | I35: ="d20"&IF($H$35>=0,"+","")&$H$35 | J35: ="" | K35: =IF($H$35>=$B$12,"Heroica ("&$B$12&")",IF($H$35>=$B$11,"Muito Difícil ("&$B$11&")",IF($H$35>=$B$10,"Difícil ("&$B$10&")",IF($H$35>=$B$9,"Média ("&$B$9&")",IF($H$35>=$B$8,"Fácil ("&$B$8&")",IF($H$35>=$B$7,"Trivial ("&$B$7&")","—")))))) | L35: =IF(O35>0,"O Google leu como fórmula: escolha de novo na lista.",IF($N$35<>"Sim","",IF('Criação'!$E$88<>"Sim","Eficácia exige Eficiência nesta Perícia",IF(COUNTIF($N$16:$N$35,"Sim")>'Criação'!$E$14,"Acima dos slots de Eficácia em Perícias ("&'Criação'!$E$14&")","")))) | N35: =IF(ISERROR($E$35),"",IF(ISBLANK($E$35),"",$E$35)) | O35: =ISERROR($E$35)*1
A36: Slots de Eficácia em Perícias: marcados / permitidos | B36: =COUNTIF($N$16:$N$35,"Sim") | C36: ='Criação'!$E$14 | D36: Perícias com Eficiência: | E36: ='Criação'!$D$67
A38: Testes de Resistência — 04.6 e 22 (Eficiência em todos desde o nível 1; sem crítico, sempre rolado)
A39: Teste de Resistência | B39: Atributo | C39: Bônus | D39: Eficiência | E39: Eficácia (preencha Sim) | F39: Penalidade (Armadura Pesada) | G39: Extra (Bênçãos) | H39: Total | I39: Rolagem | J39: Vantagem racial | K39: Aviso
A40: Potência Física | B40: =INDEX('Dados'!$B$82:$B$87,1) | C40: =IFERROR(INDEX('Criação'!$F$44:$F$49,MATCH($B$40,'Criação'!$A$44:$A$49,0)),0) | D40: ="+"&'Criação'!$C$14 | F40: =IF($B$40="Agilidade",'Criação'!$E$93,0) | G40: =IF('Equipamento'!$J$31="Potência Física",'Equipamento'!$I$31,0)+MIN('Criação'!$J$14,COUNTIF('Equipamento'!$P$45:$P$47,"Potência Física")+'Em Jogo'!$Q$8) | H40: =$C$40+IF(AND($N$40="Sim",COUNTIF($N$40,"Sim")<='Criação'!$F$14),2*'Criação'!$C$14,'Criação'!$C$14)+$F$40+$G$40 | I40: ="d20"&IF($H$40>=0,"+","")&$H$40 | J40: =IF(OR('Criação'!$Q$25="Xianzhouíta"),"Vantagem ("&'Criação'!$Q$25&")","") | K40: =IF(O40>0,"O Google leu como fórmula: escolha de novo na lista.",IF(AND($N$40="Sim",COUNTIF($N$40,"Sim")>'Criação'!$F$14),"Acima dos slots de Eficácia em Testes de Resistência ("&'Criação'!$F$14&"). ","")&IF((COUNTIF('Equipamento'!$P$45:$P$47,"Potência Física")+'Em Jogo'!$Q$8)>'Criação'!$J$14,"Bônus temporário acima do teto (+"&'Criação'!$J$14&"): conta só o teto (26.6).","")) | N40: =IF(ISERROR($E$40),"",IF(ISBLANK($E$40),"",$E$40)) | O40: =ISERROR($E$40)*1
A41: Reflexos | B41: =INDEX('Dados'!$B$82:$B$87,2) | C41: =IFERROR(INDEX('Criação'!$F$44:$F$49,MATCH($B$41,'Criação'!$A$44:$A$49,0)),0) | D41: ="+"&'Criação'!$C$14 | F41: =IF($B$41="Agilidade",'Criação'!$E$93,0) | G41: =IF('Equipamento'!$J$31="Reflexos",'Equipamento'!$I$31,0)+MIN('Criação'!$J$14,COUNTIF('Equipamento'!$P$45:$P$47,"Reflexos")+'Em Jogo'!$Q$8) | H41: =$C$41+IF(AND($N$41="Sim",COUNTIF($N$40:$N$41,"Sim")<='Criação'!$F$14),2*'Criação'!$C$14,'Criação'!$C$14)+$F$41+$G$41 | I41: ="d20"&IF($H$41>=0,"+","")&$H$41 | J41: =IF(OR('Criação'!$Q$25="Xianzhouíta"),"Vantagem ("&'Criação'!$Q$25&")","") | K41: =IF(O41>0,"O Google leu como fórmula: escolha de novo na lista.",IF(AND($N$41="Sim",COUNTIF($N$40:$N$41,"Sim")>'Criação'!$F$14),"Acima dos slots de Eficácia em Testes de Resistência ("&'Criação'!$F$14&"). ","")&IF((COUNTIF('Equipamento'!$P$45:$P$47,"Reflexos")+'Em Jogo'!$Q$8)>'Criação'!$J$14,"Bônus temporário acima do teto (+"&'Criação'!$J$14&"): conta só o teto (26.6).","")) | N41: =IF(ISERROR($E$41),"",IF(ISBLANK($E$41),"",$E$41)) | O41: =ISERROR($E$41)*1
A42: Resistência Física | B42: =INDEX('Dados'!$B$82:$B$87,3) | C42: =IFERROR(INDEX('Criação'!$F$44:$F$49,MATCH($B$42,'Criação'!$A$44:$A$49,0)),0) | D42: ="+"&'Criação'!$C$14 | F42: =IF($B$42="Agilidade",'Criação'!$E$93,0) | G42: =IF('Equipamento'!$J$31="Resistência Física",'Equipamento'!$I$31,0)+MIN('Criação'!$J$14,COUNTIF('Equipamento'!$P$45:$P$47,"Resistência Física")+'Em Jogo'!$Q$8) | H42: =$C$42+IF(AND($N$42="Sim",COUNTIF($N$40:$N$42,"Sim")<='Criação'!$F$14),2*'Criação'!$C$14,'Criação'!$C$14)+$F$42+$G$42 | I42: ="d20"&IF($H$42>=0,"+","")&$H$42 | J42: =IF(OR('Criação'!$Q$25="Xianzhouíta"),"Vantagem ("&'Criação'!$Q$25&")","") | K42: =IF(O42>0,"O Google leu como fórmula: escolha de novo na lista.",IF(AND($N$42="Sim",COUNTIF($N$40:$N$42,"Sim")>'Criação'!$F$14),"Acima dos slots de Eficácia em Testes de Resistência ("&'Criação'!$F$14&"). ","")&IF((COUNTIF('Equipamento'!$P$45:$P$47,"Resistência Física")+'Em Jogo'!$Q$8)>'Criação'!$J$14,"Bônus temporário acima do teto (+"&'Criação'!$J$14&"): conta só o teto (26.6).","")) | N42: =IF(ISERROR($E$42),"",IF(ISBLANK($E$42),"",$E$42)) | O42: =ISERROR($E$42)*1
A43: Resistência Mental | B43: =INDEX('Dados'!$B$82:$B$87,4) | C43: =IFERROR(INDEX('Criação'!$F$44:$F$49,MATCH($B$43,'Criação'!$A$44:$A$49,0)),0) | D43: ="+"&'Criação'!$C$14 | F43: =IF($B$43="Agilidade",'Criação'!$E$93,0) | G43: =IF('Equipamento'!$J$31="Resistência Mental",'Equipamento'!$I$31,0)+MIN('Criação'!$J$14,COUNTIF('Equipamento'!$P$45:$P$47,"Resistência Mental")+'Em Jogo'!$Q$8+'Em Jogo'!$Q$11) | H43: =$C$43+IF(AND($N$43="Sim",COUNTIF($N$40:$N$43,"Sim")<='Criação'!$F$14),2*'Criação'!$C$14,'Criação'!$C$14)+$F$43+$G$43 | I43: ="d20"&IF($H$43>=0,"+","")&$H$43 | J43: =IF(OR('Criação'!$Q$25="Xianzhouíta",'Criação'!$Q$25="Avginiano"),"Vantagem ("&'Criação'!$Q$25&")","") | K43: =IF(O43>0,"O Google leu como fórmula: escolha de novo na lista.",IF(AND($N$43="Sim",COUNTIF($N$40:$N$43,"Sim")>'Criação'!$F$14),"Acima dos slots de Eficácia em Testes de Resistência ("&'Criação'!$F$14&"). ","")&IF((COUNTIF('Equipamento'!$P$45:$P$47,"Resistência Mental")+'Em Jogo'!$Q$8+'Em Jogo'!$Q$11)>'Criação'!$J$14,"Bônus temporário acima do teto (+"&'Criação'!$J$14&"): conta só o teto (26.6).","")) | N43: =IF(ISERROR($E$43),"",IF(ISBLANK($E$43),"",$E$43)) | O43: =ISERROR($E$43)*1
A44: Percepção Mental | B44: =INDEX('Dados'!$B$82:$B$87,5) | C44: =IFERROR(INDEX('Criação'!$F$44:$F$49,MATCH($B$44,'Criação'!$A$44:$A$49,0)),0) | D44: ="+"&'Criação'!$C$14 | F44: =IF($B$44="Agilidade",'Criação'!$E$93,0) | G44: =IF('Equipamento'!$J$31="Percepção Mental",'Equipamento'!$I$31,0)+MIN('Criação'!$J$14,COUNTIF('Equipamento'!$P$45:$P$47,"Percepção Mental")+'Em Jogo'!$Q$8) | H44: =$C$44+IF(AND($N$44="Sim",COUNTIF($N$40:$N$44,"Sim")<='Criação'!$F$14),2*'Criação'!$C$14,'Criação'!$C$14)+$F$44+$G$44 | I44: ="d20"&IF($H$44>=0,"+","")&$H$44 | J44: =IF(OR('Criação'!$Q$25="Xianzhouíta",'Criação'!$Q$25="Avginiano"),"Vantagem ("&'Criação'!$Q$25&")","") | K44: =IF(O44>0,"O Google leu como fórmula: escolha de novo na lista.",IF(AND($N$44="Sim",COUNTIF($N$40:$N$44,"Sim")>'Criação'!$F$14),"Acima dos slots de Eficácia em Testes de Resistência ("&'Criação'!$F$14&"). ","")&IF((COUNTIF('Equipamento'!$P$45:$P$47,"Percepção Mental")+'Em Jogo'!$Q$8)>'Criação'!$J$14,"Bônus temporário acima do teto (+"&'Criação'!$J$14&"): conta só o teto (26.6).","")) | N44: =IF(ISERROR($E$44),"",IF(ISBLANK($E$44),"",$E$44)) | O44: =ISERROR($E$44)*1
A45: Força de Vontade | B45: =INDEX('Dados'!$B$82:$B$87,6) | C45: =IFERROR(INDEX('Criação'!$F$44:$F$49,MATCH($B$45,'Criação'!$A$44:$A$49,0)),0) | D45: ="+"&'Criação'!$C$14 | F45: =IF($B$45="Agilidade",'Criação'!$E$93,0) | G45: =IF('Equipamento'!$J$31="Força de Vontade",'Equipamento'!$I$31,0)+MIN('Criação'!$J$14,COUNTIF('Equipamento'!$P$45:$P$47,"Força de Vontade")+'Em Jogo'!$Q$8+'Em Jogo'!$Q$11) | H45: =$C$45+IF(AND($N$45="Sim",COUNTIF($N$40:$N$45,"Sim")<='Criação'!$F$14),2*'Criação'!$C$14,'Criação'!$C$14)+$F$45+$G$45 | I45: ="d20"&IF($H$45>=0,"+","")&$H$45 | J45: =IF(OR('Criação'!$Q$25="Xianzhouíta",'Criação'!$Q$25="Vulpes",'Criação'!$Q$25="Avginiano"),"Vantagem ("&'Criação'!$Q$25&")","") | K45: =IF(O45>0,"O Google leu como fórmula: escolha de novo na lista.",IF(AND($N$45="Sim",COUNTIF($N$40:$N$45,"Sim")>'Criação'!$F$14),"Acima dos slots de Eficácia em Testes de Resistência ("&'Criação'!$F$14&"). ","")&IF((COUNTIF('Equipamento'!$P$45:$P$47,"Força de Vontade")+'Em Jogo'!$Q$8+'Em Jogo'!$Q$11)>'Criação'!$J$14,"Bônus temporário acima do teto (+"&'Criação'!$J$14&"): conta só o teto (26.6).","")) | N45: =IF(ISERROR($E$45),"",IF(ISBLANK($E$45),"",$E$45)) | O45: =ISERROR($E$45)*1
A46: Teste de Morrendo (sem Eficiência, DT 10) | B46: Presença | C46: ='Criação'!$F$49 | D46: Não usa | H46: =$C$46 | I46: ="d20"&IF($H$46>=0,"+","")&$H$46&" ≥ 10" | J46: =IF(OR('Criação'!$Q$25="Xianzhouíta",'Criação'!$Q$25="Vulpes",'Criação'!$Q$25="Avginiano"),"Vantagem ("&'Criação'!$Q$25&", 23.5)","") | K46: 3 sucessos: 1 PV · 3 falhas: morre (23.4)
A47: Slots de Eficácia em Testes de Resistência: marcados / permitidos | B47: =COUNTIF($N$40:$N$45,"Sim") | C47: ='Criação'!$F$14

Sheet Habilidades
A1: Habilidades — Explorando Galáxias v1.2
A2: Legenda: | B2: Entrada (preencha) | C2: Calculada (automático) | D2: Aviso (texto em vermelho) | E2: Título de bloco | F2: Cabeçalho de coluna | G2: Rótulo da linha | H2: Linha alternada (outro tom) | I2: Não se aplica
A3: As suas Habilidades (até 8) e a Ultimate.
A5: Seus números de Habilidade (automático) — 16.3, 16.6 e 26.2
A6: Teste de Ataque (Habilidades e Ultimate) | C6: ='Criação'!$C$57 | D6: DT das Habilidades | F6: ='Criação'!$B$56 | G6: Nível máximo | I6: ='Criação'!$B$16
A7: Habilidades preenchidas / conhecidas | C7: =SUM($P$12:$P$19) | D7: ="de "&'Criação'!$A$16 | E7: =IF('Criação'!$C$16="Sim","A partir do nível 16: em vez de aprender, reescreva 1 Habilidade conhecida por nível (16.6)","Passivas contam no teto de 8 (16.6)") | L7: =IF($C$7>'Criação'!$A$16,"Habilidades acima das conhecidas no seu nível ("&'Criação'!$A$16&"): confira as linhas abaixo.","")
A8: Ressonância III (26.7) | C8: =IF('Progressão'!$R$69="","Ainda não ativa: libera no nível 15 (aba Progressão)","Ativa: marque Sim em uma Habilidade para ela subir 1 Nível de efeito, até o Nível máximo") | L8: =IF(COUNTIF($AE$12:$AE$19,"Sim")>1,"Ressonância III marcada em mais de uma Habilidade: vale só a primeira.","")
A10: Suas Habilidades (preencha) — até 8; escreva pelos sete passos de 16.7
A11: Nº | B11: Nome (preencha) | C11: Tipo | D11: Nível (1 a 7) | E11: Em área? | F11: Resolução | G11: Alcance | H11: Ressonância III aqui? | I11: Aviso | P11: preenchida | Q11: Nível usado | R11: Ress. III vale | S11: Nível efetivo | T11: dados (tabela) | U11: nº de dados | V11: face | W11: fixo
A12: 1 | I12: =IF(AF12>0,"O Google leu como fórmula: escolha de novo ou digite com ' na frente.",IF(AF23>0,"Linha 23: O Google leu como fórmula: digite de novo com ' na frente.",IF($P$12=0,"",IF($Z$12="","Escolha o Tipo. ",IF(COUNTIF('Dados'!$W$6:$W$10,$Z$12)=0,"Tipo fora da lista (16.5). ",""))&IF(LEN($AA$12)=0,"",IF(ISNUMBER($AA$12),IF(OR($AA$12<1,$AA$12>7),"O Nível vai de 1 a 7. ","")&IF($AA$12>'Criação'!$B$16,"Acima do Nível máximo do seu nível ("&'Criação'!$B$16&"). ",""),"Nível precisa ser um número de 1 a 7. "))&IF(LEN($AD$12)=0,"",IF(ISERROR(MATCH($AD$12,'Dados'!$X$6:$X$10,0)),"Alcance fora da lista. ",IF(MATCH($AD$12,'Dados'!$X$6:$X$10,0)>MATCH($I$34,'Dados'!$X$6:$X$10,0),"Alcance acima do que o Nível "&$S$12&" permite (até "&$I$34&"). ","")))&IF(SUM($P$12:P12)>'Criação'!$A$16,"Acima das "&'Criação'!$A$16&" Habilidades conhecidas do seu nível. ","")&IF($AE$12="Sim",IF('Progressão'!$R$69="","Ressonância III ainda não está ativa. ",IF(COUNTIF($AE$12,"Sim")>1,"Ressonância III só vale numa Habilidade. ","")),"")))) | P12: =IF(OR(LEN($Y$12)>0,LEN($Z$12)>0,LEN($AA$12)>0,LEN($AB$12)>0,LEN($AC$12)>0,LEN($AD$12)>0,LEN($AE$12)>0,LEN($Z$23)>0),1,0) | Q12: =IF(ISNUMBER($AA$12),MAX(1,MIN(7,INT($AA$12))),1) | R12: =IF(AND($AE$12="Sim",'Progressão'!$R$69<>"",COUNTIF($AE$12,"Sim")=1),1,0) | S12: =IF(AND($R$12=1,$Q$12<'Criação'!$B$16),MIN('Criação'!$B$16,$Q$12+1),$Q$12) | T12: =IF($Z$12="Dano",INDEX('Dados'!$C$303:$C$309,$S$12),IF($Z$12="Cura",INDEX('Dados'!$G$303:$G$309,$S$12),0)) | U12: =IF(AND($AB$12="Sim",$T$12>0),MAX(1,INT($T$12/2)),$T$12) | V12: =IF($Z$12="Dano",INDEX('Dados'!$D$303:$D$309,$S$12),IF($Z$12="Cura",INDEX('Dados'!$H$303:$H$309,$S$12),0)) | W12: =IF(OR($Z$12="Dano",$Z$12="Cura"),'Criação'!$B$55+IF($Z$12="Dano",'Equipamento'!$P$40+'Equipamento'!$E$31,0),0) | Y12: =IF(ISERROR($B$12),"",IF(ISBLANK($B$12),"",$B$12)) | Z12: =IF(ISERROR($C$12),"",IF(ISBLANK($C$12),"",$C$12)) | AA12: =IF(ISERROR($D$12),"",IF(ISBLANK($D$12),"",$D$12)) | AB12: =IF(ISERROR($E$12),"",IF(ISBLANK($E$12),"",$E$12)) | AC12: =IF(ISERROR($F$12),"",IF(ISBLANK($F$12),"",$F$12)) | AD12: =IF(ISERROR($G$12),"",IF(ISBLANK($G$12),"",$G$12)) | AE12: =IF(ISERROR($H$12),"",IF(ISBLANK($H$12),"",$H$12)) | AF12: =ISERROR($B$12)*1+ISERROR($C$12)*1+ISERROR($D$12)*1+ISERROR($E$12)*1+ISERROR($F$12)*1+ISERROR($G$12)*1+ISERROR($H$12)*1
A13: 2 | I13: =IF(AF13>0,"O Google leu como fórmula: escolha de novo ou digite com ' na frente.",IF(AF24>0,"Linha 24: O Google leu como fórmula: digite de novo com ' na frente.",IF($P$13=0,"",IF($Z$13="","Escolha o Tipo. ",IF(COUNTIF('Dados'!$W$6:$W$10,$Z$13)=0,"Tipo fora da lista (16.5). ",""))&IF(LEN($AA$13)=0,"",IF(ISNUMBER($AA$13),IF(OR($AA$13<1,$AA$13>7),"O Nível vai de 1 a 7. ","")&IF($AA$13>'Criação'!$B$16,"Acima do Nível máximo do seu nível ("&'Criação'!$B$16&"). ",""),"Nível precisa ser um número de 1 a 7. "))&IF(LEN($AD$13)=0,"",IF(ISERROR(MATCH($AD$13,'Dados'!$X$6:$X$10,0)),"Alcance fora da lista. ",IF(MATCH($AD$13,'Dados'!$X$6:$X$10,0)>MATCH($I$35,'Dados'!$X$6:$X$10,0),"Alcance acima do que o Nível "&$S$13&" permite (até "&$I$35&"). ","")))&IF(SUM($P$12:P13)>'Criação'!$A$16,"Acima das "&'Criação'!$A$16&" Habilidades conhecidas do seu nível. ","")&IF($AE$13="Sim",IF('Progressão'!$R$69="","Ressonância III ainda não está ativa. ",IF(COUNTIF($AE$12:$AE$13,"Sim")>1,"Ressonância III só vale numa Habilidade. ","")),"")))) | P13: =IF(OR(LEN($Y$13)>0,LEN($Z$13)>0,LEN($AA$13)>0,LEN($AB$13)>0,LEN($AC$13)>0,LEN($AD$13)>0,LEN($AE$13)>0,LEN($Z$24)>0),1,0) | Q13: =IF(ISNUMBER($AA$13),MAX(1,MIN(7,INT($AA$13))),1) | R13: =IF(AND($AE$13="Sim",'Progressão'!$R$69<>"",COUNTIF($AE$12:$AE$13,"Sim")=1),1,0) | S13: =IF(AND($R$13=1,$Q$13<'Criação'!$B$16),MIN('Criação'!$B$16,$Q$13+1),$Q$13) | T13: =IF($Z$13="Dano",INDEX('Dados'!$C$303:$C$309,$S$13),IF($Z$13="Cura",INDEX('Dados'!$G$303:$G$309,$S$13),0)) | U13: =IF(AND($AB$13="Sim",$T$13>0),MAX(1,INT($T$13/2)),$T$13) | V13: =IF($Z$13="Dano",INDEX('Dados'!$D$303:$D$309,$S$13),IF($Z$13="Cura",INDEX('Dados'!$H$303:$H$309,$S$13),0)) | W13: =IF(OR($Z$13="Dano",$Z$13="Cura"),'Criação'!$B$55+IF($Z$13="Dano",'Equipamento'!$P$40+'Equipamento'!$E$31,0),0) | Y13: =IF(ISERROR($B$13),"",IF(ISBLANK($B$13),"",$B$13)) | Z13: =IF(ISERROR($C$13),"",IF(ISBLANK($C$13),"",$C$13)) | AA13: =IF(ISERROR($D$13),"",IF(ISBLANK($D$13),"",$D$13)) | AB13: =IF(ISERROR($E$13),"",IF(ISBLANK($E$13),"",$E$13)) | AC13: =IF(ISERROR($F$13),"",IF(ISBLANK($F$13),"",$F$13)) | AD13: =IF(ISERROR($G$13),"",IF(ISBLANK($G$13),"",$G$13)) | AE13: =IF(ISERROR($H$13),"",IF(ISBLANK($H$13),"",$H$13)) | AF13: =ISERROR($B$13)*1+ISERROR($C$13)*1+ISERROR($D$13)*1+ISERROR($E$13)*1+ISERROR($F$13)*1+ISERROR($G$13)*1+ISERROR($H$13)*1
A14: 3 | I14: =IF(AF14>0,"O Google leu como fórmula: escolha de novo ou digite com ' na frente.",IF(AF25>0,"Linha 25: O Google leu como fórmula: digite de novo com ' na frente.",IF($P$14=0,"",IF($Z$14="","Escolha o Tipo. ",IF(COUNTIF('Dados'!$W$6:$W$10,$Z$14)=0,"Tipo fora da lista (16.5). ",""))&IF(LEN($AA$14)=0,"",IF(ISNUMBER($AA$14),IF(OR($AA$14<1,$AA$14>7),"O Nível vai de 1 a 7. ","")&IF($AA$14>'Criação'!$B$16,"Acima do Nível máximo do seu nível ("&'Criação'!$B$16&"). ",""),"Nível precisa ser um número de 1 a 7. "))&IF(LEN($AD$14)=0,"",IF(ISERROR(MATCH($AD$14,'Dados'!$X$6:$X$10,0)),"Alcance fora da lista. ",IF(MATCH($AD$14,'Dados'!$X$6:$X$10,0)>MATCH($I$36,'Dados'!$X$6:$X$10,0),"Alcance acima do que o Nível "&$S$14&" permite (até "&$I$36&"). ","")))&IF(SUM($P$12:P14)>'Criação'!$A$16,"Acima das "&'Criação'!$A$16&" Habilidades conhecidas do seu nível. ","")&IF($AE$14="Sim",IF('Progressão'!$R$69="","Ressonância III ainda não está ativa. ",IF(COUNTIF($AE$12:$AE$14,"Sim")>1,"Ressonância III só vale numa Habilidade. ","")),"")))) | P14: =IF(OR(LEN($Y$14)>0,LEN($Z$14)>0,LEN($AA$14)>0,LEN($AB$14)>0,LEN($AC$14)>0,LEN($AD$14)>0,LEN($AE$14)>0,LEN($Z$25)>0),1,0) | Q14: =IF(ISNUMBER($AA$14),MAX(1,MIN(7,INT($AA$14))),1) | R14: =IF(AND($AE$14="Sim",'Progressão'!$R$69<>"",COUNTIF($AE$12:$AE$14,"Sim")=1),1,0) | S14: =IF(AND($R$14=1,$Q$14<'Criação'!$B$16),MIN('Criação'!$B$16,$Q$14+1),$Q$14) | T14: =IF($Z$14="Dano",INDEX('Dados'!$C$303:$C$309,$S$14),IF($Z$14="Cura",INDEX('Dados'!$G$303:$G$309,$S$14),0)) | U14: =IF(AND($AB$14="Sim",$T$14>0),MAX(1,INT($T$14/2)),$T$14) | V14: =IF($Z$14="Dano",INDEX('Dados'!$D$303:$D$309,$S$14),IF($Z$14="Cura",INDEX('Dados'!$H$303:$H$309,$S$14),0)) | W14: =IF(OR($Z$14="Dano",$Z$14="Cura"),'Criação'!$B$55+IF($Z$14="Dano",'Equipamento'!$P$40+'Equipamento'!$E$31,0),0) | Y14: =IF(ISERROR($B$14),"",IF(ISBLANK($B$14),"",$B$14)) | Z14: =IF(ISERROR($C$14),"",IF(ISBLANK($C$14),"",$C$14)) | AA14: =IF(ISERROR($D$14),"",IF(ISBLANK($D$14),"",$D$14)) | AB14: =IF(ISERROR($E$14),"",IF(ISBLANK($E$14),"",$E$14)) | AC14: =IF(ISERROR($F$14),"",IF(ISBLANK($F$14),"",$F$14)) | AD14: =IF(ISERROR($G$14),"",IF(ISBLANK($G$14),"",$G$14)) | AE14: =IF(ISERROR($H$14),"",IF(ISBLANK($H$14),"",$H$14)) | AF14: =ISERROR($B$14)*1+ISERROR($C$14)*1+ISERROR($D$14)*1+ISERROR($E$14)*1+ISERROR($F$14)*1+ISERROR($G$14)*1+ISERROR($H$14)*1
A15: 4 | I15: =IF(AF15>0,"O Google leu como fórmula: escolha de novo ou digite com ' na frente.",IF(AF26>0,"Linha 26: O Google leu como fórmula: digite de novo com ' na frente.",IF($P$15=0,"",IF($Z$15="","Escolha o Tipo. ",IF(COUNTIF('Dados'!$W$6:$W$10,$Z$15)=0,"Tipo fora da lista (16.5). ",""))&IF(LEN($AA$15)=0,"",IF(ISNUMBER($AA$15),IF(OR($AA$15<1,$AA$15>7),"O Nível vai de 1 a 7. ","")&IF($AA$15>'Criação'!$B$16,"Acima do Nível máximo do seu nível ("&'Criação'!$B$16&"). ",""),"Nível precisa ser um número de 1 a 7. "))&IF(LEN($AD$15)=0,"",IF(ISERROR(MATCH($AD$15,'Dados'!$X$6:$X$10,0)),"Alcance fora da lista. ",IF(MATCH($AD$15,'Dados'!$X$6:$X$10,0)>MATCH($I$37,'Dados'!$X$6:$X$10,0),"Alcance acima do que o Nível "&$S$15&" permite (até "&$I$37&"). ","")))&IF(SUM($P$12:P15)>'Criação'!$A$16,"Acima das "&'Criação'!$A$16&" Habilidades conhecidas do seu nível. ","")&IF($AE$15="Sim",IF('Progressão'!$R$69="","Ressonância III ainda não está ativa. ",IF(COUNTIF($AE$12:$AE$15,"Sim")>1,"Ressonância III só vale numa Habilidade. ","")),"")))) | P15: =IF(OR(LEN($Y$15)>0,LEN($Z$15)>0,LEN($AA$15)>0,LEN($AB$15)>0,LEN($AC$15)>0,LEN($AD$15)>0,LEN($AE$15)>0,LEN($Z$26)>0),1,0) | Q15: =IF(ISNUMBER($AA$15),MAX(1,MIN(7,INT($AA$15))),1) | R15: =IF(AND($AE$15="Sim",'Progressão'!$R$69<>"",COUNTIF($AE$12:$AE$15,"Sim")=1),1,0) | S15: =IF(AND($R$15=1,$Q$15<'Criação'!$B$16),MIN('Criação'!$B$16,$Q$15+1),$Q$15) | T15: =IF($Z$15="Dano",INDEX('Dados'!$C$303:$C$309,$S$15),IF($Z$15="Cura",INDEX('Dados'!$G$303:$G$309,$S$15),0)) | U15: =IF(AND($AB$15="Sim",$T$15>0),MAX(1,INT($T$15/2)),$T$15) | V15: =IF($Z$15="Dano",INDEX('Dados'!$D$303:$D$309,$S$15),IF($Z$15="Cura",INDEX('Dados'!$H$303:$H$309,$S$15),0)) | W15: =IF(OR($Z$15="Dano",$Z$15="Cura"),'Criação'!$B$55+IF($Z$15="Dano",'Equipamento'!$P$40+'Equipamento'!$E$31,0),0) | Y15: =IF(ISERROR($B$15),"",IF(ISBLANK($B$15),"",$B$15)) | Z15: =IF(ISERROR($C$15),"",IF(ISBLANK($C$15),"",$C$15)) | AA15: =IF(ISERROR($D$15),"",IF(ISBLANK($D$15),"",$D$15)) | AB15: =IF(ISERROR($E$15),"",IF(ISBLANK($E$15),"",$E$15)) | AC15: =IF(ISERROR($F$15),"",IF(ISBLANK($F$15),"",$F$15)) | AD15: =IF(ISERROR($G$15),"",IF(ISBLANK($G$15),"",$G$15)) | AE15: =IF(ISERROR($H$15),"",IF(ISBLANK($H$15),"",$H$15)) | AF15: =ISERROR($B$15)*1+ISERROR($C$15)*1+ISERROR($D$15)*1+ISERROR($E$15)*1+ISERROR($F$15)*1+ISERROR($G$15)*1+ISERROR($H$15)*1
A16: 5 | I16: =IF(AF16>0,"O Google leu como fórmula: escolha de novo ou digite com ' na frente.",IF(AF27>0,"Linha 27: O Google leu como fórmula: digite de novo com ' na frente.",IF($P$16=0,"",IF($Z$16="","Escolha o Tipo. ",IF(COUNTIF('Dados'!$W$6:$W$10,$Z$16)=0,"Tipo fora da lista (16.5). ",""))&IF(LEN($AA$16)=0,"",IF(ISNUMBER($AA$16),IF(OR($AA$16<1,$AA$16>7),"O Nível vai de 1 a 7. ","")&IF($AA$16>'Criação'!$B$16,"Acima do Nível máximo do seu nível ("&'Criação'!$B$16&"). ",""),"Nível precisa ser um número de 1 a 7. "))&IF(LEN($AD$16)=0,"",IF(ISERROR(MATCH($AD$16,'Dados'!$X$6:$X$10,0)),"Alcance fora da lista. ",IF(MATCH($AD$16,'Dados'!$X$6:$X$10,0)>MATCH($I$38,'Dados'!$X$6:$X$10,0),"Alcance acima do que o Nível "&$S$16&" permite (até "&$I$38&"). ","")))&IF(SUM($P$12:P16)>'Criação'!$A$16,"Acima das "&'Criação'!$A$16&" Habilidades conhecidas do seu nível. ","")&IF($AE$16="Sim",IF('Progressão'!$R$69="","Ressonância III ainda não está ativa. ",IF(COUNTIF($AE$12:$AE$16,"Sim")>1,"Ressonância III só vale numa Habilidade. ","")),"")))) | P16: =IF(OR(LEN($Y$16)>0,LEN($Z$16)>0,LEN($AA$16)>0,LEN($AB$16)>0,LEN($AC$16)>0,LEN($AD$16)>0,LEN($AE$16)>0,LEN($Z$27)>0),1,0) | Q16: =IF(ISNUMBER($AA$16),MAX(1,MIN(7,INT($AA$16))),1) | R16: =IF(AND($AE$16="Sim",'Progressão'!$R$69<>"",COUNTIF($AE$12:$AE$16,"Sim")=1),1,0) | S16: =IF(AND($R$16=1,$Q$16<'Criação'!$B$16),MIN('Criação'!$B$16,$Q$16+1),$Q$16) | T16: =IF($Z$16="Dano",INDEX('Dados'!$C$303:$C$309,$S$16),IF($Z$16="Cura",INDEX('Dados'!$G$303:$G$309,$S$16),0)) | U16: =IF(AND($AB$16="Sim",$T$16>0),MAX(1,INT($T$16/2)),$T$16) | V16: =IF($Z$16="Dano",INDEX('Dados'!$D$303:$D$309,$S$16),IF($Z$16="Cura",INDEX('Dados'!$H$303:$H$309,$S$16),0)) | W16: =IF(OR($Z$16="Dano",$Z$16="Cura"),'Criação'!$B$55+IF($Z$16="Dano",'Equipamento'!$P$40+'Equipamento'!$E$31,0),0) | Y16: =IF(ISERROR($B$16),"",IF(ISBLANK($B$16),"",$B$16)) | Z16: =IF(ISERROR($C$16),"",IF(ISBLANK($C$16),"",$C$16)) | AA16: =IF(ISERROR($D$16),"",IF(ISBLANK($D$16),"",$D$16)) | AB16: =IF(ISERROR($E$16),"",IF(ISBLANK($E$16),"",$E$16)) | AC16: =IF(ISERROR($F$16),"",IF(ISBLANK($F$16),"",$F$16)) | AD16: =IF(ISERROR($G$16),"",IF(ISBLANK($G$16),"",$G$16)) | AE16: =IF(ISERROR($H$16),"",IF(ISBLANK($H$16),"",$H$16)) | AF16: =ISERROR($B$16)*1+ISERROR($C$16)*1+ISERROR($D$16)*1+ISERROR($E$16)*1+ISERROR($F$16)*1+ISERROR($G$16)*1+ISERROR($H$16)*1
A17: 6 | I17: =IF(AF17>0,"O Google leu como fórmula: escolha de novo ou digite com ' na frente.",IF(AF28>0,"Linha 28: O Google leu como fórmula: digite de novo com ' na frente.",IF($P$17=0,"",IF($Z$17="","Escolha o Tipo. ",IF(COUNTIF('Dados'!$W$6:$W$10,$Z$17)=0,"Tipo fora da lista (16.5). ",""))&IF(LEN($AA$17)=0,"",IF(ISNUMBER($AA$17),IF(OR($AA$17<1,$AA$17>7),"O Nível vai de 1 a 7. ","")&IF($AA$17>'Criação'!$B$16,"Acima do Nível máximo do seu nível ("&'Criação'!$B$16&"). ",""),"Nível precisa ser um número de 1 a 7. "))&IF(LEN($AD$17)=0,"",IF(ISERROR(MATCH($AD$17,'Dados'!$X$6:$X$10,0)),"Alcance fora da lista. ",IF(MATCH($AD$17,'Dados'!$X$6:$X$10,0)>MATCH($I$39,'Dados'!$X$6:$X$10,0),"Alcance acima do que o Nível "&$S$17&" permite (até "&$I$39&"). ","")))&IF(SUM($P$12:P17)>'Criação'!$A$16,"Acima das "&'Criação'!$A$16&" Habilidades conhecidas do seu nível. ","")&IF($AE$17="Sim",IF('Progressão'!$R$69="","Ressonância III ainda não está ativa. ",IF(COUNTIF($AE$12:$AE$17,"Sim")>1,"Ressonância III só vale numa Habilidade. ","")),"")))) | P17: =IF(OR(LEN($Y$17)>0,LEN($Z$17)>0,LEN($AA$17)>0,LEN($AB$17)>0,LEN($AC$17)>0,LEN($AD$17)>0,LEN($AE$17)>0,LEN($Z$28)>0),1,0) | Q17: =IF(ISNUMBER($AA$17),MAX(1,MIN(7,INT($AA$17))),1) | R17: =IF(AND($AE$17="Sim",'Progressão'!$R$69<>"",COUNTIF($AE$12:$AE$17,"Sim")=1),1,0) | S17: =IF(AND($R$17=1,$Q$17<'Criação'!$B$16),MIN('Criação'!$B$16,$Q$17+1),$Q$17) | T17: =IF($Z$17="Dano",INDEX('Dados'!$C$303:$C$309,$S$17),IF($Z$17="Cura",INDEX('Dados'!$G$303:$G$309,$S$17),0)) | U17: =IF(AND($AB$17="Sim",$T$17>0),MAX(1,INT($T$17/2)),$T$17) | V17: =IF($Z$17="Dano",INDEX('Dados'!$D$303:$D$309,$S$17),IF($Z$17="Cura",INDEX('Dados'!$H$303:$H$309,$S$17),0)) | W17: =IF(OR($Z$17="Dano",$Z$17="Cura"),'Criação'!$B$55+IF($Z$17="Dano",'Equipamento'!$P$40+'Equipamento'!$E$31,0),0) | Y17: =IF(ISERROR($B$17),"",IF(ISBLANK($B$17),"",$B$17)) | Z17: =IF(ISERROR($C$17),"",IF(ISBLANK($C$17),"",$C$17)) | AA17: =IF(ISERROR($D$17),"",IF(ISBLANK($D$17),"",$D$17)) | AB17: =IF(ISERROR($E$17),"",IF(ISBLANK($E$17),"",$E$17)) | AC17: =IF(ISERROR($F$17),"",IF(ISBLANK($F$17),"",$F$17)) | AD17: =IF(ISERROR($G$17),"",IF(ISBLANK($G$17),"",$G$17)) | AE17: =IF(ISERROR($H$17),"",IF(ISBLANK($H$17),"",$H$17)) | AF17: =ISERROR($B$17)*1+ISERROR($C$17)*1+ISERROR($D$17)*1+ISERROR($E$17)*1+ISERROR($F$17)*1+ISERROR($G$17)*1+ISERROR($H$17)*1
A18: 7 | I18: =IF(AF18>0,"O Google leu como fórmula: escolha de novo ou digite com ' na frente.",IF(AF29>0,"Linha 29: O Google leu como fórmula: digite de novo com ' na frente.",IF($P$18=0,"",IF($Z$18="","Escolha o Tipo. ",IF(COUNTIF('Dados'!$W$6:$W$10,$Z$18)=0,"Tipo fora da lista (16.5). ",""))&IF(LEN($AA$18)=0,"",IF(ISNUMBER($AA$18),IF(OR($AA$18<1,$AA$18>7),"O Nível vai de 1 a 7. ","")&IF($AA$18>'Criação'!$B$16,"Acima do Nível máximo do seu nível ("&'Criação'!$B$16&"). ",""),"Nível precisa ser um número de 1 a 7. "))&IF(LEN($AD$18)=0,"",IF(ISERROR(MATCH($AD$18,'Dados'!$X$6:$X$10,0)),"Alcance fora da lista. ",IF(MATCH($AD$18,'Dados'!$X$6:$X$10,0)>MATCH($I$40,'Dados'!$X$6:$X$10,0),"Alcance acima do que o Nível "&$S$18&" permite (até "&$I$40&"). ","")))&IF(SUM($P$12:P18)>'Criação'!$A$16,"Acima das "&'Criação'!$A$16&" Habilidades conhecidas do seu nível. ","")&IF($AE$18="Sim",IF('Progressão'!$R$69="","Ressonância III ainda não está ativa. ",IF(COUNTIF($AE$12:$AE$18,"Sim")>1,"Ressonância III só vale numa Habilidade. ","")),"")))) | P18: =IF(OR(LEN($Y$18)>0,LEN($Z$18)>0,LEN($AA$18)>0,LEN($AB$18)>0,LEN($AC$18)>0,LEN($AD$18)>0,LEN($AE$18)>0,LEN($Z$29)>0),1,0) | Q18: =IF(ISNUMBER($AA$18),MAX(1,MIN(7,INT($AA$18))),1) | R18: =IF(AND($AE$18="Sim",'Progressão'!$R$69<>"",COUNTIF($AE$12:$AE$18,"Sim")=1),1,0) | S18: =IF(AND($R$18=1,$Q$18<'Criação'!$B$16),MIN('Criação'!$B$16,$Q$18+1),$Q$18) | T18: =IF($Z$18="Dano",INDEX('Dados'!$C$303:$C$309,$S$18),IF($Z$18="Cura",INDEX('Dados'!$G$303:$G$309,$S$18),0)) | U18: =IF(AND($AB$18="Sim",$T$18>0),MAX(1,INT($T$18/2)),$T$18) | V18: =IF($Z$18="Dano",INDEX('Dados'!$D$303:$D$309,$S$18),IF($Z$18="Cura",INDEX('Dados'!$H$303:$H$309,$S$18),0)) | W18: =IF(OR($Z$18="Dano",$Z$18="Cura"),'Criação'!$B$55+IF($Z$18="Dano",'Equipamento'!$P$40+'Equipamento'!$E$31,0),0) | Y18: =IF(ISERROR($B$18),"",IF(ISBLANK($B$18),"",$B$18)) | Z18: =IF(ISERROR($C$18),"",IF(ISBLANK($C$18),"",$C$18)) | AA18: =IF(ISERROR($D$18),"",IF(ISBLANK($D$18),"",$D$18)) | AB18: =IF(ISERROR($E$18),"",IF(ISBLANK($E$18),"",$E$18)) | AC18: =IF(ISERROR($F$18),"",IF(ISBLANK($F$18),"",$F$18)) | AD18: =IF(ISERROR($G$18),"",IF(ISBLANK($G$18),"",$G$18)) | AE18: =IF(ISERROR($H$18),"",IF(ISBLANK($H$18),"",$H$18)) | AF18: =ISERROR($B$18)*1+ISERROR($C$18)*1+ISERROR($D$18)*1+ISERROR($E$18)*1+ISERROR($F$18)*1+ISERROR($G$18)*1+ISERROR($H$18)*1
A19: 8 | I19: =IF(AF19>0,"O Google leu como fórmula: escolha de novo ou digite com ' na frente.",IF(AF30>0,"Linha 30: O Google leu como fórmula: digite de novo com ' na frente.",IF($P$19=0,"",IF($Z$19="","Escolha o Tipo. ",IF(COUNTIF('Dados'!$W$6:$W$10,$Z$19)=0,"Tipo fora da lista (16.5). ",""))&IF(LEN($AA$19)=0,"",IF(ISNUMBER($AA$19),IF(OR($AA$19<1,$AA$19>7),"O Nível vai de 1 a 7. ","")&IF($AA$19>'Criação'!$B$16,"Acima do Nível máximo do seu nível ("&'Criação'!$B$16&"). ",""),"Nível precisa ser um número de 1 a 7. "))&IF(LEN($AD$19)=0,"",IF(ISERROR(MATCH($AD$19,'Dados'!$X$6:$X$10,0)),"Alcance fora da lista. ",IF(MATCH($AD$19,'Dados'!$X$6:$X$10,0)>MATCH($I$41,'Dados'!$X$6:$X$10,0),"Alcance acima do que o Nível "&$S$19&" permite (até "&$I$41&"). ","")))&IF(SUM($P$12:P19)>'Criação'!$A$16,"Acima das "&'Criação'!$A$16&" Habilidades conhecidas do seu nível. ","")&IF($AE$19="Sim",IF('Progressão'!$R$69="","Ressonância III ainda não está ativa. ",IF(COUNTIF($AE$12:$AE$19,"Sim")>1,"Ressonância III só vale numa Habilidade. ","")),"")))) | P19: =IF(OR(LEN($Y$19)>0,LEN($Z$19)>0,LEN($AA$19)>0,LEN($AB$19)>0,LEN($AC$19)>0,LEN($AD$19)>0,LEN($AE$19)>0,LEN($Z$30)>0),1,0) | Q19: =IF(ISNUMBER($AA$19),MAX(1,MIN(7,INT($AA$19))),1) | R19: =IF(AND($AE$19="Sim",'Progressão'!$R$69<>"",COUNTIF($AE$12:$AE$19,"Sim")=1),1,0) | S19: =IF(AND($R$19=1,$Q$19<'Criação'!$B$16),MIN('Criação'!$B$16,$Q$19+1),$Q$19) | T19: =IF($Z$19="Dano",INDEX('Dados'!$C$303:$C$309,$S$19),IF($Z$19="Cura",INDEX('Dados'!$G$303:$G$309,$S$19),0)) | U19: =IF(AND($AB$19="Sim",$T$19>0),MAX(1,INT($T$19/2)),$T$19) | V19: =IF($Z$19="Dano",INDEX('Dados'!$D$303:$D$309,$S$19),IF($Z$19="Cura",INDEX('Dados'!$H$303:$H$309,$S$19),0)) | W19: =IF(OR($Z$19="Dano",$Z$19="Cura"),'Criação'!$B$55+IF($Z$19="Dano",'Equipamento'!$P$40+'Equipamento'!$E$31,0),0) | Y19: =IF(ISERROR($B$19),"",IF(ISBLANK($B$19),"",$B$19)) | Z19: =IF(ISERROR($C$19),"",IF(ISBLANK($C$19),"",$C$19)) | AA19: =IF(ISERROR($D$19),"",IF(ISBLANK($D$19),"",$D$19)) | AB19: =IF(ISERROR($E$19),"",IF(ISBLANK($E$19),"",$E$19)) | AC19: =IF(ISERROR($F$19),"",IF(ISBLANK($F$19),"",$F$19)) | AD19: =IF(ISERROR($G$19),"",IF(ISBLANK($G$19),"",$G$19)) | AE19: =IF(ISERROR($H$19),"",IF(ISBLANK($H$19),"",$H$19)) | AF19: =ISERROR($B$19)*1+ISERROR($C$19)*1+ISERROR($D$19)*1+ISERROR($E$19)*1+ISERROR($F$19)*1+ISERROR($G$19)*1+ISERROR($H$19)*1
A21: Efeito de cada Habilidade (preencha) — o que ela faz, em uma ou duas frases
A22: Nº | B22: Nome (automático) | C22: Efeito (preencha)
A23: 1 | B23: =IF(LEN($Y$12)=0,"Habilidade 1",""&$Y$12) | Z23: =IF(ISERROR($C$23),"",IF(ISBLANK($C$23),"",$C$23)) | AF23: =ISERROR($C$23)*1
A24: 2 | B24: =IF(LEN($Y$13)=0,"Habilidade 2",""&$Y$13) | Z24: =IF(ISERROR($C$24),"",IF(ISBLANK($C$24),"",$C$24)) | AF24: =ISERROR($C$24)*1
A25: 3 | B25: =IF(LEN($Y$14)=0,"Habilidade 3",""&$Y$14) | Z25: =IF(ISERROR($C$25),"",IF(ISBLANK($C$25),"",$C$25)) | AF25: =ISERROR($C$25)*1
A26: 4 | B26: =IF(LEN($Y$15)=0,"Habilidade 4",""&$Y$15) | Z26: =IF(ISERROR($C$26),"",IF(ISBLANK($C$26),"",$C$26)) | AF26: =ISERROR($C$26)*1
A27: 5 | B27: =IF(LEN($Y$16)=0,"Habilidade 5",""&$Y$16) | Z27: =IF(ISERROR($C$27),"",IF(ISBLANK($C$27),"",$C$27)) | AF27: =ISERROR($C$27)*1
A28: 6 | B28: =IF(LEN($Y$17)=0,"Habilidade 6",""&$Y$17) | Z28: =IF(ISERROR($C$28),"",IF(ISBLANK($C$28),"",$C$28)) | AF28: =ISERROR($C$28)*1
A29: 7 | B29: =IF(LEN($Y$18)=0,"Habilidade 7",""&$Y$18) | Z29: =IF(ISERROR($C$29),"",IF(ISBLANK($C$29),"",$C$29)) | AF29: =ISERROR($C$29)*1
A30: 8 | B30: =IF(LEN($Y$19)=0,"Habilidade 8",""&$Y$19) | Z30: =IF(ISERROR($C$30),"",IF(ISBLANK($C$30),"",$C$30)) | AF30: =ISERROR($C$30)*1
A32: Números das Habilidades (automático) — 16.3, 16.4 e 16.5
A33: Nº | B33: Nome | C33: Nível efetivo | D33: Dano ou cura | E33: Média | F33: Rolagem ou DT | G33: PH | H33: Redução de Tenacidade | I33: Alcance máximo | J33: Alvos | K33: Dados da tabela | L33: Média dos dados
A34: 1 | B34: =IF($P$12=0,"",IF(LEN($Y$12)=0,"Habilidade 1",""&$Y$12)) | C34: =IF($P$12=0,"",$S$12) | D34: =IF(OR($P$12=0,$U$12=0),"",IF($U$12<=0,""&$W$12,$U$12&"d"&$V$12&IF($W$12>0,"+"&$W$12,IF($W$12<0,""&$W$12,"")))) | E34: =IF(OR($P$12=0,$U$12=0),"",INT($U$12*($V$12+1)/2)+$W$12) | F34: =IF($P$12=0,"",IF($AC$12="Teste de Ataque",'Criação'!$C$57,IF($AC$12="Teste de Resistência","DT "&'Criação'!$B$56,""))) | G34: =IF($P$12=0,"",IF($Z$12="Passiva",0,INDEX('Dados'!$J$303:$J$309,$S$12))) | H34: =IF($P$12=0,"",IF($Z$12="Dano",INDEX('Dados'!$K$303:$K$309,$S$12),0)) | I34: =IF($P$12=0,"",CHOOSE(MIN(4,$S$12),"Curta","Média","Longa","Extrema")) | J34: =IF($P$12=0,"",IF($AB$12="Sim",IF($S$12>=6,4,3),1)) | K34: =IF(OR($P$12=0,$U$12=0),"",$U$12&"d"&$V$12) | L34: =IF(OR($P$12=0,$U$12=0),"",INT($U$12*($V$12+1)/2))
A35: 2 | B35: =IF($P$13=0,"",IF(LEN($Y$13)=0,"Habilidade 2",""&$Y$13)) | C35: =IF($P$13=0,"",$S$13) | D35: =IF(OR($P$13=0,$U$13=0),"",IF($U$13<=0,""&$W$13,$U$13&"d"&$V$13&IF($W$13>0,"+"&$W$13,IF($W$13<0,""&$W$13,"")))) | E35: =IF(OR($P$13=0,$U$13=0),"",INT($U$13*($V$13+1)/2)+$W$13) | F35: =IF($P$13=0,"",IF($AC$13="Teste de Ataque",'Criação'!$C$57,IF($AC$13="Teste de Resistência","DT "&'Criação'!$B$56,""))) | G35: =IF($P$13=0,"",IF($Z$13="Passiva",0,INDEX('Dados'!$J$303:$J$309,$S$13))) | H35: =IF($P$13=0,"",IF($Z$13="Dano",INDEX('Dados'!$K$303:$K$309,$S$13),0)) | I35: =IF($P$13=0,"",CHOOSE(MIN(4,$S$13),"Curta","Média","Longa","Extrema")) | J35: =IF($P$13=0,"",IF($AB$13="Sim",IF($S$13>=6,4,3),1)) | K35: =IF(OR($P$13=0,$U$13=0),"",$U$13&"d"&$V$13) | L35: =IF(OR($P$13=0,$U$13=0),"",INT($U$13*($V$13+1)/2))
A36: 3 | B36: =IF($P$14=0,"",IF(LEN($Y$14)=0,"Habilidade 3",""&$Y$14)) | C36: =IF($P$14=0,"",$S$14) | D36: =IF(OR($P$14=0,$U$14=0),"",IF($U$14<=0,""&$W$14,$U$14&"d"&$V$14&IF($W$14>0,"+"&$W$14,IF($W$14<0,""&$W$14,"")))) | E36: =IF(OR($P$14=0,$U$14=0),"",INT($U$14*($V$14+1)/2)+$W$14) | F36: =IF($P$14=0,"",IF($AC$14="Teste de Ataque",'Criação'!$C$57,IF($AC$14="Teste de Resistência","DT "&'Criação'!$B$56,""))) | G36: =IF($P$14=0,"",IF($Z$14="Passiva",0,INDEX('Dados'!$J$303:$J$309,$S$14))) | H36: =IF($P$14=0,"",IF($Z$14="Dano",INDEX('Dados'!$K$303:$K$309,$S$14),0)) | I36: =IF($P$14=0,"",CHOOSE(MIN(4,$S$14),"Curta","Média","Longa","Extrema")) | J36: =IF($P$14=0,"",IF($AB$14="Sim",IF($S$14>=6,4,3),1)) | K36: =IF(OR($P$14=0,$U$14=0),"",$U$14&"d"&$V$14) | L36: =IF(OR($P$14=0,$U$14=0),"",INT($U$14*($V$14+1)/2))
A37: 4 | B37: =IF($P$15=0,"",IF(LEN($Y$15)=0,"Habilidade 4",""&$Y$15)) | C37: =IF($P$15=0,"",$S$15) | D37: =IF(OR($P$15=0,$U$15=0),"",IF($U$15<=0,""&$W$15,$U$15&"d"&$V$15&IF($W$15>0,"+"&$W$15,IF($W$15<0,""&$W$15,"")))) | E37: =IF(OR($P$15=0,$U$15=0),"",INT($U$15*($V$15+1)/2)+$W$15) | F37: =IF($P$15=0,"",IF($AC$15="Teste de Ataque",'Criação'!$C$57,IF($AC$15="Teste de Resistência","DT "&'Criação'!$B$56,""))) | G37: =IF($P$15=0,"",IF($Z$15="Passiva",0,INDEX('Dados'!$J$303:$J$309,$S$15))) | H37: =IF($P$15=0,"",IF($Z$15="Dano",INDEX('Dados'!$K$303:$K$309,$S$15),0)) | I37: =IF($P$15=0,"",CHOOSE(MIN(4,$S$15),"Curta","Média","Longa","Extrema")) | J37: =IF($P$15=0,"",IF($AB$15="Sim",IF($S$15>=6,4,3),1)) | K37: =IF(OR($P$15=0,$U$15=0),"",$U$15&"d"&$V$15) | L37: =IF(OR($P$15=0,$U$15=0),"",INT($U$15*($V$15+1)/2))
A38: 5 | B38: =IF($P$16=0,"",IF(LEN($Y$16)=0,"Habilidade 5",""&$Y$16)) | C38: =IF($P$16=0,"",$S$16) | D38: =IF(OR($P$16=0,$U$16=0),"",IF($U$16<=0,""&$W$16,$U$16&"d"&$V$16&IF($W$16>0,"+"&$W$16,IF($W$16<0,""&$W$16,"")))) | E38: =IF(OR($P$16=0,$U$16=0),"",INT($U$16*($V$16+1)/2)+$W$16) | F38: =IF($P$16=0,"",IF($AC$16="Teste de Ataque",'Criação'!$C$57,IF($AC$16="Teste de Resistência","DT "&'Criação'!$B$56,""))) | G38: =IF($P$16=0,"",IF($Z$16="Passiva",0,INDEX('Dados'!$J$303:$J$309,$S$16))) | H38: =IF($P$16=0,"",IF($Z$16="Dano",INDEX('Dados'!$K$303:$K$309,$S$16),0)) | I38: =IF($P$16=0,"",CHOOSE(MIN(4,$S$16),"Curta","Média","Longa","Extrema")) | J38: =IF($P$16=0,"",IF($AB$16="Sim",IF($S$16>=6,4,3),1)) | K38: =IF(OR($P$16=0,$U$16=0),"",$U$16&"d"&$V$16) | L38: =IF(OR($P$16=0,$U$16=0),"",INT($U$16*($V$16+1)/2))
A39: 6 | B39: =IF($P$17=0,"",IF(LEN($Y$17)=0,"Habilidade 6",""&$Y$17)) | C39: =IF($P$17=0,"",$S$17) | D39: =IF(OR($P$17=0,$U$17=0),"",IF($U$17<=0,""&$W$17,$U$17&"d"&$V$17&IF($W$17>0,"+"&$W$17,IF($W$17<0,""&$W$17,"")))) | E39: =IF(OR($P$17=0,$U$17=0),"",INT($U$17*($V$17+1)/2)+$W$17) | F39: =IF($P$17=0,"",IF($AC$17="Teste de Ataque",'Criação'!$C$57,IF($AC$17="Teste de Resistência","DT "&'Criação'!$B$56,""))) | G39: =IF($P$17=0,"",IF($Z$17="Passiva",0,INDEX('Dados'!$J$303:$J$309,$S$17))) | H39: =IF($P$17=0,"",IF($Z$17="Dano",INDEX('Dados'!$K$303:$K$309,$S$17),0)) | I39: =IF($P$17=0,"",CHOOSE(MIN(4,$S$17),"Curta","Média","Longa","Extrema")) | J39: =IF($P$17=0,"",IF($AB$17="Sim",IF($S$17>=6,4,3),1)) | K39: =IF(OR($P$17=0,$U$17=0),"",$U$17&"d"&$V$17) | L39: =IF(OR($P$17=0,$U$17=0),"",INT($U$17*($V$17+1)/2))
A40: 7 | B40: =IF($P$18=0,"",IF(LEN($Y$18)=0,"Habilidade 7",""&$Y$18)) | C40: =IF($P$18=0,"",$S$18) | D40: =IF(OR($P$18=0,$U$18=0),"",IF($U$18<=0,""&$W$18,$U$18&"d"&$V$18&IF($W$18>0,"+"&$W$18,IF($W$18<0,""&$W$18,"")))) | E40: =IF(OR($P$18=0,$U$18=0),"",INT($U$18*($V$18+1)/2)+$W$18) | F40: =IF($P$18=0,"",IF($AC$18="Teste de Ataque",'Criação'!$C$57,IF($AC$18="Teste de Resistência","DT "&'Criação'!$B$56,""))) | G40: =IF($P$18=0,"",IF($Z$18="Passiva",0,INDEX('Dados'!$J$303:$J$309,$S$18))) | H40: =IF($P$18=0,"",IF($Z$18="Dano",INDEX('Dados'!$K$303:$K$309,$S$18),0)) | I40: =IF($P$18=0,"",CHOOSE(MIN(4,$S$18),"Curta","Média","Longa","Extrema")) | J40: =IF($P$18=0,"",IF($AB$18="Sim",IF($S$18>=6,4,3),1)) | K40: =IF(OR($P$18=0,$U$18=0),"",$U$18&"d"&$V$18) | L40: =IF(OR($P$18=0,$U$18=0),"",INT($U$18*($V$18+1)/2))
A41: 8 | B41: =IF($P$19=0,"",IF(LEN($Y$19)=0,"Habilidade 8",""&$Y$19)) | C41: =IF($P$19=0,"",$S$19) | D41: =IF(OR($P$19=0,$U$19=0),"",IF($U$19<=0,""&$W$19,$U$19&"d"&$V$19&IF($W$19>0,"+"&$W$19,IF($W$19<0,""&$W$19,"")))) | E41: =IF(OR($P$19=0,$U$19=0),"",INT($U$19*($V$19+1)/2)+$W$19) | F41: =IF($P$19=0,"",IF($AC$19="Teste de Ataque",'Criação'!$C$57,IF($AC$19="Teste de Resistência","DT "&'Criação'!$B$56,""))) | G41: =IF($P$19=0,"",IF($Z$19="Passiva",0,INDEX('Dados'!$J$303:$J$309,$S$19))) | H41: =IF($P$19=0,"",IF($Z$19="Dano",INDEX('Dados'!$K$303:$K$309,$S$19),0)) | I41: =IF($P$19=0,"",CHOOSE(MIN(4,$S$19),"Curta","Média","Longa","Extrema")) | J41: =IF($P$19=0,"",IF($AB$19="Sim",IF($S$19>=6,4,3),1)) | K41: =IF(OR($P$19=0,$U$19=0),"",$U$19&"d"&$V$19) | L41: =IF(OR($P$19=0,$U$19=0),"",INT($U$19*($V$19+1)/2))
A43: Nº | B43: Nome | C43: Bônus fixo | D43: Guia de 16.5 (o que o efeito pode fazer)
A44: 1 | B44: =IF($P$12=0,"",IF(LEN($Y$12)=0,"Habilidade 1",""&$Y$12)) | C44: =IF($P$12=0,"",$W$12) | D44: =IF($P$12=0,"",IF(OR($Z$12="Buff",$Z$12="Debuff"),INDEX('Dados'!$B$313:$B$319,$S$12)&" · "&INDEX('Dados'!$C$313:$C$319,$S$12)&" · alvos: "&INDEX('Dados'!$D$313:$D$319,$S$12),IF($Z$12="Passiva",INDEX('Dados'!$B$323:$B$329,$S$12)&" · não custa PH",IF(OR($Z$12="Dano",$Z$12="Cura"),"Dados da tabela 16.3 + Bônus do Atributo de Habilidade, uma vez","Escolha o Tipo"))))
A45: 2 | B45: =IF($P$13=0,"",IF(LEN($Y$13)=0,"Habilidade 2",""&$Y$13)) | C45: =IF($P$13=0,"",$W$13) | D45: =IF($P$13=0,"",IF(OR($Z$13="Buff",$Z$13="Debuff"),INDEX('Dados'!$B$313:$B$319,$S$13)&" · "&INDEX('Dados'!$C$313:$C$319,$S$13)&" · alvos: "&INDEX('Dados'!$D$313:$D$319,$S$13),IF($Z$13="Passiva",INDEX('Dados'!$B$323:$B$329,$S$13)&" · não custa PH",IF(OR($Z$13="Dano",$Z$13="Cura"),"Dados da tabela 16.3 + Bônus do Atributo de Habilidade, uma vez","Escolha o Tipo"))))
A46: 3 | B46: =IF($P$14=0,"",IF(LEN($Y$14)=0,"Habilidade 3",""&$Y$14)) | C46: =IF($P$14=0,"",$W$14) | D46: =IF($P$14=0,"",IF(OR($Z$14="Buff",$Z$14="Debuff"),INDEX('Dados'!$B$313:$B$319,$S$14)&" · "&INDEX('Dados'!$C$313:$C$319,$S$14)&" · alvos: "&INDEX('Dados'!$D$313:$D$319,$S$14),IF($Z$14="Passiva",INDEX('Dados'!$B$323:$B$329,$S$14)&" · não custa PH",IF(OR($Z$14="Dano",$Z$14="Cura"),"Dados da tabela 16.3 + Bônus do Atributo de Habilidade, uma vez","Escolha o Tipo"))))
A47: 4 | B47: =IF($P$15=0,"",IF(LEN($Y$15)=0,"Habilidade 4",""&$Y$15)) | C47: =IF($P$15=0,"",$W$15) | D47: =IF($P$15=0,"",IF(OR($Z$15="Buff",$Z$15="Debuff"),INDEX('Dados'!$B$313:$B$319,$S$15)&" · "&INDEX('Dados'!$C$313:$C$319,$S$15)&" · alvos: "&INDEX('Dados'!$D$313:$D$319,$S$15),IF($Z$15="Passiva",INDEX('Dados'!$B$323:$B$329,$S$15)&" · não custa PH",IF(OR($Z$15="Dano",$Z$15="Cura"),"Dados da tabela 16.3 + Bônus do Atributo de Habilidade, uma vez","Escolha o Tipo"))))
A48: 5 | B48: =IF($P$16=0,"",IF(LEN($Y$16)=0,"Habilidade 5",""&$Y$16)) | C48: =IF($P$16=0,"",$W$16) | D48: =IF($P$16=0,"",IF(OR($Z$16="Buff",$Z$16="Debuff"),INDEX('Dados'!$B$313:$B$319,$S$16)&" · "&INDEX('Dados'!$C$313:$C$319,$S$16)&" · alvos: "&INDEX('Dados'!$D$313:$D$319,$S$16),IF($Z$16="Passiva",INDEX('Dados'!$B$323:$B$329,$S$16)&" · não custa PH",IF(OR($Z$16="Dano",$Z$16="Cura"),"Dados da tabela 16.3 + Bônus do Atributo de Habilidade, uma vez","Escolha o Tipo"))))
A49: 6 | B49: =IF($P$17=0,"",IF(LEN($Y$17)=0,"Habilidade 6",""&$Y$17)) | C49: =IF($P$17=0,"",$W$17) | D49: =IF($P$17=0,"",IF(OR($Z$17="Buff",$Z$17="Debuff"),INDEX('Dados'!$B$313:$B$319,$S$17)&" · "&INDEX('Dados'!$C$313:$C$319,$S$17)&" · alvos: "&INDEX('Dados'!$D$313:$D$319,$S$17),IF($Z$17="Passiva",INDEX('Dados'!$B$323:$B$329,$S$17)&" · não custa PH",IF(OR($Z$17="Dano",$Z$17="Cura"),"Dados da tabela 16.3 + Bônus do Atributo de Habilidade, uma vez","Escolha o Tipo"))))
A50: 7 | B50: =IF($P$18=0,"",IF(LEN($Y$18)=0,"Habilidade 7",""&$Y$18)) | C50: =IF($P$18=0,"",$W$18) | D50: =IF($P$18=0,"",IF(OR($Z$18="Buff",$Z$18="Debuff"),INDEX('Dados'!$B$313:$B$319,$S$18)&" · "&INDEX('Dados'!$C$313:$C$319,$S$18)&" · alvos: "&INDEX('Dados'!$D$313:$D$319,$S$18),IF($Z$18="Passiva",INDEX('Dados'!$B$323:$B$329,$S$18)&" · não custa PH",IF(OR($Z$18="Dano",$Z$18="Cura"),"Dados da tabela 16.3 + Bônus do Atributo de Habilidade, uma vez","Escolha o Tipo"))))
A51: 8 | B51: =IF($P$19=0,"",IF(LEN($Y$19)=0,"Habilidade 8",""&$Y$19)) | C51: =IF($P$19=0,"",$W$19) | D51: =IF($P$19=0,"",IF(OR($Z$19="Buff",$Z$19="Debuff"),INDEX('Dados'!$B$313:$B$319,$S$19)&" · "&INDEX('Dados'!$C$313:$C$319,$S$19)&" · alvos: "&INDEX('Dados'!$D$313:$D$319,$S$19),IF($Z$19="Passiva",INDEX('Dados'!$B$323:$B$329,$S$19)&" · não custa PH",IF(OR($Z$19="Dano",$Z$19="Cura"),"Dados da tabela 16.3 + Bônus do Atributo de Habilidade, uma vez","Escolha o Tipo"))))
A53: Ultimate — 17 (100 de Energia, não gasta ação, 1 por Ciclo; potência pela faixa)
A54: Nome (diga em voz alta) | K54: =IF(AF54>0,"O Google leu como fórmula: digite de novo com ' na frente.","") | Z54: =IF(ISERROR($C$54),"",IF(ISBLANK($C$54),"",$C$54)) | AF54: =ISERROR($C$54)*1
A55: A frase que você diz | L55: =IF(AF55>0,"O Google leu como fórmula: digite de novo com ' na frente.","") | Z55: =IF(ISERROR($C$55),"",IF(ISBLANK($C$55),"",$C$55)) | AF55: =ISERROR($C$55)*1
A56: Tipo | L56: =IF(AF56>0,"O Google leu como fórmula: escolha de novo na lista.",IF($Z$56="",IF($P$61=1,"Escolha o Tipo da Ultimate.",""),IF(OR($Z$56="Dano",$Z$56="Cura",$Z$56="Buff",$Z$56="Debuff",$Z$56="Controle"),"","Tipo fora da lista (17.4)."))&IF(AND(LEN($Z$58)>0,COUNTIF('Dados'!$AK$6:$AK$7,$Z$58)=0)," Resolução fora da lista.","")) | Z56: =IF(ISERROR($C$56),"",IF(ISBLANK($C$56),"",$C$56)) | AF56: =ISERROR($C$56)*1
A57: Em área? | K57: =IF(AF57>0,"O Google leu como fórmula: escolha de novo na lista.","") | Z57: =IF(ISERROR($C$57),"",IF(ISBLANK($C$57),"",$C$57)) | AF57: =ISERROR($C$57)*1
A58: Resolução | K58: =IF(AF58>0,"O Google leu como fórmula: escolha de novo na lista.","") | Z58: =IF(ISERROR($C$58),"",IF(ISBLANK($C$58),"",$C$58)) | AF58: =ISERROR($C$58)*1
A59: Efeito (o que ela faz) | L59: =IF(AF59>0,"O Google leu como fórmula: digite de novo com ' na frente.","") | Z59: =IF(ISERROR($C$59),"",IF(ISBLANK($C$59),"",$C$59)) | AF59: =ISERROR($C$59)*1
A60: Ultimate | C60: Nível equivalente | D60: Dano ou cura | E60: Média | F60: Rolagem ou DT | G60: Custo (Energia) | H60: Redução de Tenacidade | I60: Alvos | J60: Dados da tabela | K60: Média dos dados | L60: Bônus fixo | P60: preenchida | Q60: nº tabela | R60: nº de dados | S60: face
A61: Números da Ultimate | C61: ='Criação'!$H$16 | D61: =IF($R$61=0,"",IF($R$61<=0,""&$L$61,$R$61&"d"&$S$61&IF($L$61>0,"+"&$L$61,IF($L$61<0,""&$L$61,"")))) | E61: =IF($R$61=0,"",INT($R$61*($S$61+1)/2)+$L$61) | F61: =IF($Z$58="Teste de Ataque",'Criação'!$C$57,IF($Z$58="Teste de Resistência","DT "&'Criação'!$B$56,"")) | G61: =IF('Progressão'!$R$70="Ultimate com 80 de Energia",80,100) | H61: =INDEX('Dados'!$K$333:$K$337,'Criação'!$B$14) | I61: =IF($Z$57="Sim",IF($C$61>=6,4,3),1) | J61: =IF($R$61=0,"",$R$61&"d"&$S$61) | K61: =IF($R$61=0,"",INT($R$61*($S$61+1)/2)) | L61: =IF(OR($Z$56="Dano",$Z$56="Cura"),'Criação'!$B$55+IF($Z$56="Dano",'Equipamento'!$P$40+'Equipamento'!$F$31,0),0) | P61: =IF(OR(LEN($Z$54)>0,LEN($Z$55)>0,LEN($Z$56)>0,LEN($Z$57)>0,LEN($Z$58)>0,LEN($Z$59)>0),1,0) | Q61: =IF($Z$56="Dano",INDEX('Dados'!$D$333:$D$337,'Criação'!$B$14),IF($Z$56="Cura",INDEX('Dados'!$H$333:$H$337,'Criação'!$B$14),0)) | R61: =IF(AND($Z$57="Sim",$Q$61>0),MAX(1,INT($Q$61/2)),$Q$61) | S61: =IF($Z$56="Dano",INDEX('Dados'!$E$333:$E$337,'Criação'!$B$14),IF($Z$56="Cura",INDEX('Dados'!$I$333:$I$337,'Criação'!$B$14),0))
A62: Guia de 16.5 (efeito) | C62: =IF(OR($Z$56="Buff",$Z$56="Debuff",$Z$56="Controle"),"Nível equivalente "&$C$61&": "&INDEX('Dados'!$B$313:$B$319,$C$61)&" · "&INDEX('Dados'!$C$313:$C$319,$C$61),IF(OR($Z$56="Dano",$Z$56="Cura"),"Dados da linha da sua faixa (17.3) + Bônus do Atributo de Habilidade, uma vez","Escolha o Tipo"))
A63: A Ultimate sobe sozinha ao mudar de faixa (níveis 5, 9, 13 e 17). Ressonância II: efeito extra; Ressonância IV: pode custar 80 de Energia (26.7).

Sheet Caminho
A1: Caminho — Explorando Galáxias v1.2
A2: Legenda: | B2: Entrada (preencha) | C2: Calculada (automático) | D2: Aviso (texto em vermelho) | F2: Título de bloco | G2: Cabeçalho de coluna | H2: Rótulo da linha | I2: Linha alternada (outro tom) | J2: Não se aplica
A3: O seu Caminho, as Bênçãos adquiridas e o Memoespírito.
A5: Ficha do Caminho (escolha o Caminho na aba Criação, Passo 3)
A6: Caminho | B6: =IF('Criação'!$Q$33="","Escolha na aba Criação",'Criação'!$Q$33) | D6: Aeon | E6: ='Criação'!$B$34 | G6: Atributo de Habilidade usado | H6: ='Criação'!$D$54
A7: A ideia | B7: ='Criação'!$B$35
A8: N (PV) | B8: ='Criação'!$B$36 | C8: Bônus de Velocidade | D8: ='Criação'!$B$37 | E8: Perícias do Caminho | G8: ='Criação'!$B$38&IF('Criação'!$Q$33="",""," · ")&'Criação'!$D$38&IF('Criação'!$Q$33="",""," · ")&'Criação'!$F$38
A9: Recurso próprio | B9: ='Criação'!$B$40
A11: Recurso próprio do Caminho (capítulos 07 a 15)
A12: =IF('Criação'!$Q$33="A Preservação","Teto de Barreira (15.2) = 3 × Eficiência = "&3*'Criação'!$C$14,IF('Criação'!$Q$33="A Caça","Marcação de Presa (14.2): Ação Complementar, 1 inimigo por vez, +1 dado base contra ele.",IF('Criação'!$Q$33="A Euforia","Tabela do Riso (13.2): role 1d6 quando uma Bênção mandar.",IF('Criação'!$Q$33="A Erudição","Acúmulos de Cálculo (12.2): máximo "&IF((COUNTIF($I$27:$I$36,"Teto Rompido")>0),7,5)&" por combate",IF('Criação'!$Q$33="A Recordação","Memoespírito (11.3 a 11.5): monte a ficha dele no bloco abaixo.",IF('Criação'!$Q$33="A Abundância","Nenhum recurso além dos acúmulos das Bênçãos (10.1): Florescimento (até 5).",IF('Criação'!$Q$33="A Harmonia","Nenhum recurso além dos acúmulos das Bênçãos (9.1): Eco da Vitória (até 3).",IF('Criação'!$Q$33="A Inexistência","Nenhum recurso além dos acúmulos das Bênçãos (8.1): Marca do Vazio (até 3) e Corrupção (até 5).",IF('Criação'!$Q$33="A Destruição","PV como moeda (7.2): ativação ou acúmulo de Bênção de custo = 2 × nível = "&2*'Criação'!$A$14&" PV","Escolha o Caminho na aba Criação (Passo 3).")))))))))
A13: =IF('Criação'!$Q$33="A Preservação","Barreira não acumula com outro PV temporário: fica o maior valor.",IF('Criação'!$Q$33="A Caça","A marca dura até o fim do combate e migra de graça quando o alvo é derrotado.",IF('Criação'!$Q$33="A Euforia","1: Piada interna — +1 dado base no seu próximo ataque neste Ciclo",IF('Criação'!$Q$33="A Erudição","Ganha 1 acúmulo por inimigo atingido por um mesmo ataque, Habilidade ou Ultimate sua.",IF('Criação'!$Q$33="A Recordação","Invocar: Ação Complementar + 1 PH. A Energia das ações dele vale metade para você.",IF('Criação'!$Q$33="A Abundância","Use a frequência e os acúmulos das Bênçãos adquiridas, nos slots abaixo.",IF('Criação'!$Q$33="A Harmonia","Use a frequência e os acúmulos das Bênçãos adquiridas, nos slots abaixo.",IF('Criação'!$Q$33="A Inexistência","Use a frequência e os acúmulos das Bênçãos adquiridas, nos slots abaixo.",IF('Criação'!$Q$33="A Destruição","Dado base comprado no Avatar = 5 × nível = "&(5*'Criação'!$A$14)&" PV","")))))))))
A14: =IF('Criação'!$Q$33="A Preservação","Cura não repõe Barreira. O dano passa pela RD antes da Barreira.",IF('Criação'!$Q$33="A Caça","Faixa de crítico: "&IF((COUNTIF($I$27:$I$36,"Olho de Lan")>0),"19-20 (Olho de Lan)","20"),IF('Criação'!$Q$33="A Euforia","2: Tropeço cósmico — o inimigo mais próximo é Atrasado em 1 casa (capítulo 19, respeita a Firmeza de Elite e Boss)",IF('Criação'!$Q$33="A Erudição","Gastar 1 acúmulo: +1 alvo para a ação em curso. Gastar 2: +1 dado base no dano.",IF('Criação'!$Q$33="A Destruição","Você escolhe pagar e não pode pagar se o custo for igual ou maior que os seus PV atuais.","")))))
A15: =IF('Criação'!$Q$33="A Euforia","3: Riso contagioso — um aliado a até Distância Média ganha +2 na próxima rolagem dele",IF('Criação'!$Q$33="A Erudição","Gastar não consome ação. Os acúmulos zeram no fim do combate.",IF('Criação'!$Q$33="A Destruição","PV gastos assim não são dano: não geram Energia, não passam por RD e contam para as Marcas.","")))
A16: =IF('Criação'!$Q$33="A Euforia","4: Troca de lugar — você e um aliado trocam de casa na Fila; nenhum dos dois pode já ter agido neste Ciclo","")
A17: =IF('Criação'!$Q$33="A Euforia","5: Sorte do tolo — você ganha Vantagem na sua próxima rolagem neste Ciclo","")
A18: =IF('Criação'!$Q$33="A Euforia","6: Aha! aprova — o grupo recupera 1 PH (uma vez por Ciclo)","")
A20: Bênçãos com número na ficha
A21: Bênção | C21: Custo em PV | D21: Bônus de dano | E21: Bônus ferido | F21: Ferido com PV até | G21: Como funciona
A22: Pacto da Ruína (7.3, nº 1) | C22: =IF((COUNTIF($I$27:$I$36,"Pacto da Ruína")>0),2*'Criação'!$A$14,"") | D22: =IF((COUNTIF($I$27:$I$36,"Pacto da Ruína")>0),'Criação'!$C$14,"") | E22: =IF((COUNTIF($I$27:$I$36,"Pacto da Ruína")>0),2*'Criação'!$C$14,"") | F22: =IF((COUNTIF($I$27:$I$36,"Pacto da Ruína")>0),INT('Criação'!$D$95/2),"") | G22: =IF((COUNTIF($I$27:$I$36,"Pacto da Ruína")>0),"Uma vez por turno: pague o custo e some o bônus ao dano; dobra com metade dos PV ou menos","Só com a Bênção Pacto da Ruína")
A24: Bênçãos adquiridas — uma por nível ímpar (06.7); o Tier I cabe em qualquer slot
A25: Possuídas / permitidas no nível | B25: =SUMPRODUCT((LEN($I$27:$I$36)>0)*1) | C25: ="de "&'Criação'!$L$14&" permitidas no nível "&'Criação'!$A$14
A26: Slot | B26: Nível do slot | C26: Bênção (preencha) | D26: Tier | E26: Requisito (nível) | F26: Liberado? | G26: Em uma linha | H26: Frequência | I26: Conta na ficha | K26: Aviso | N26: Lista auxiliar: Bênçãos do Caminho
A27: Slot 1 | B27: 1 | D27: =IF($Q$27="","",IFERROR(INDEX('Dados'!$D$126:$D$233,MATCH($Q$27,'Dados'!$C$126:$C$233,0)),"—")) | E27: =IF($Q$27="","",IFERROR(INDEX('Dados'!$E$126:$E$233,MATCH($Q$27,'Dados'!$C$126:$C$233,0)),"")) | F27: =IF('Criação'!$A$14>=1,"Sim","Não (nível 1)") | G27: =IF($Q$27="","",IFERROR(INDEX('Dados'!$F$126:$F$233,MATCH($Q$27,'Dados'!$C$126:$C$233,0)),"Fora do catálogo dos capítulos 07 a 15")) | H27: =IF($Q$27="","",IFERROR(INDEX('Dados'!$G$126:$G$233,MATCH($Q$27,'Dados'!$C$126:$C$233,0)),"")) | I27: =IF(AND($Q$27<>"",'Criação'!$A$14>=1),$Q$27,"") | K27: =IF(T27>0,"O Google leu como fórmula: escolha de novo na lista.",IF($Q$27="","",IF('Criação'!$A$14<1,"Slot ainda não liberado (nível 1). ","")&IF(ISERROR(MATCH($Q$27,'Dados'!$C$126:$C$233,0)),"Bênção fora do catálogo dos capítulos 07 a 15. ",IF(INDEX('Dados'!$A$126:$A$233,MATCH($Q$27,'Dados'!$C$126:$C$233,0))<>'Criação'!$Q$33,"Bênção de outro Caminho ("&INDEX('Dados'!$A$126:$A$233,MATCH($Q$27,'Dados'!$C$126:$C$233,0))&"). ",IF(INDEX('Dados'!$E$126:$E$233,MATCH($Q$27,'Dados'!$C$126:$C$233,0))>1,"Tier "&INDEX('Dados'!$D$126:$D$233,MATCH($Q$27,'Dados'!$C$126:$C$233,0))&" exige slot de nível "&INDEX('Dados'!$E$126:$E$233,MATCH($Q$27,'Dados'!$C$126:$C$233,0))&" ou mais. ","")))&IF(COUNTIF($Q$27:$Q$36,$Q$27)>1,"Bênção repetida.",""))) | N27: =IF('Criação'!$Q$33="","",IFERROR(INDEX('Dados'!$C$126:$C$233,MATCH('Criação'!$Q$33,'Dados'!$A$126:$A$233,0)+0),"")) | Q27: =IF(ISERROR($C$27),"",IF(ISBLANK($C$27),"",$C$27)) | T27: =ISERROR($C$27)*1
A28: Slot 2 | B28: 3 | D28: =IF($Q$28="","",IFERROR(INDEX('Dados'!$D$126:$D$233,MATCH($Q$28,'Dados'!$C$126:$C$233,0)),"—")) | E28: =IF($Q$28="","",IFERROR(INDEX('Dados'!$E$126:$E$233,MATCH($Q$28,'Dados'!$C$126:$C$233,0)),"")) | F28: =IF('Criação'!$A$14>=3,"Sim","Não (nível 3)") | G28: =IF($Q$28="","",IFERROR(INDEX('Dados'!$F$126:$F$233,MATCH($Q$28,'Dados'!$C$126:$C$233,0)),"Fora do catálogo dos capítulos 07 a 15")) | H28: =IF($Q$28="","",IFERROR(INDEX('Dados'!$G$126:$G$233,MATCH($Q$28,'Dados'!$C$126:$C$233,0)),"")) | I28: =IF(AND($Q$28<>"",'Criação'!$A$14>=3),$Q$28,"") | K28: =IF(T28>0,"O Google leu como fórmula: escolha de novo na lista.",IF($Q$28="","",IF('Criação'!$A$14<3,"Slot ainda não liberado (nível 3). ","")&IF(ISERROR(MATCH($Q$28,'Dados'!$C$126:$C$233,0)),"Bênção fora do catálogo dos capítulos 07 a 15. ",IF(INDEX('Dados'!$A$126:$A$233,MATCH($Q$28,'Dados'!$C$126:$C$233,0))<>'Criação'!$Q$33,"Bênção de outro Caminho ("&INDEX('Dados'!$A$126:$A$233,MATCH($Q$28,'Dados'!$C$126:$C$233,0))&"). ",IF(INDEX('Dados'!$E$126:$E$233,MATCH($Q$28,'Dados'!$C$126:$C$233,0))>3,"Tier "&INDEX('Dados'!$D$126:$D$233,MATCH($Q$28,'Dados'!$C$126:$C$233,0))&" exige slot de nível "&INDEX('Dados'!$E$126:$E$233,MATCH($Q$28,'Dados'!$C$126:$C$233,0))&" ou mais. ","")))&IF(COUNTIF($Q$27:$Q$36,$Q$28)>1,"Bênção repetida.",""))) | N28: =IF('Criação'!$Q$33="","",IFERROR(INDEX('Dados'!$C$126:$C$233,MATCH('Criação'!$Q$33,'Dados'!$A$126:$A$233,0)+1),"")) | Q28: =IF(ISERROR($C$28),"",IF(ISBLANK($C$28),"",$C$28)) | T28: =ISERROR($C$28)*1
A29: Slot 3 | B29: 5 | D29: =IF($Q$29="","",IFERROR(INDEX('Dados'!$D$126:$D$233,MATCH($Q$29,'Dados'!$C$126:$C$233,0)),"—")) | E29: =IF($Q$29="","",IFERROR(INDEX('Dados'!$E$126:$E$233,MATCH($Q$29,'Dados'!$C$126:$C$233,0)),"")) | F29: =IF('Criação'!$A$14>=5,"Sim","Não (nível 5)") | G29: =IF($Q$29="","",IFERROR(INDEX('Dados'!$F$126:$F$233,MATCH($Q$29,'Dados'!$C$126:$C$233,0)),"Fora do catálogo dos capítulos 07 a 15")) | H29: =IF($Q$29="","",IFERROR(INDEX('Dados'!$G$126:$G$233,MATCH($Q$29,'Dados'!$C$126:$C$233,0)),"")) | I29: =IF(AND($Q$29<>"",'Criação'!$A$14>=5),$Q$29,"") | K29: =IF(T29>0,"O Google leu como fórmula: escolha de novo na lista.",IF($Q$29="","",IF('Criação'!$A$14<5,"Slot ainda não liberado (nível 5). ","")&IF(ISERROR(MATCH($Q$29,'Dados'!$C$126:$C$233,0)),"Bênção fora do catálogo dos capítulos 07 a 15. ",IF(INDEX('Dados'!$A$126:$A$233,MATCH($Q$29,'Dados'!$C$126:$C$233,0))<>'Criação'!$Q$33,"Bênção de outro Caminho ("&INDEX('Dados'!$A$126:$A$233,MATCH($Q$29,'Dados'!$C$126:$C$233,0))&"). ",IF(INDEX('Dados'!$E$126:$E$233,MATCH($Q$29,'Dados'!$C$126:$C$233,0))>5,"Tier "&INDEX('Dados'!$D$126:$D$233,MATCH($Q$29,'Dados'!$C$126:$C$233,0))&" exige slot de nível "&INDEX('Dados'!$E$126:$E$233,MATCH($Q$29,'Dados'!$C$126:$C$233,0))&" ou mais. ","")))&IF(COUNTIF($Q$27:$Q$36,$Q$29)>1,"Bênção repetida.",""))) | N29: =IF('Criação'!$Q$33="","",IFERROR(INDEX('Dados'!$C$126:$C$233,MATCH('Criação'!$Q$33,'Dados'!$A$126:$A$233,0)+2),"")) | Q29: =IF(ISERROR($C$29),"",IF(ISBLANK($C$29),"",$C$29)) | T29: =ISERROR($C$29)*1
A30: Slot 4 | B30: 7 | D30: =IF($Q$30="","",IFERROR(INDEX('Dados'!$D$126:$D$233,MATCH($Q$30,'Dados'!$C$126:$C$233,0)),"—")) | E30: =IF($Q$30="","",IFERROR(INDEX('Dados'!$E$126:$E$233,MATCH($Q$30,'Dados'!$C$126:$C$233,0)),"")) | F30: =IF('Criação'!$A$14>=7,"Sim","Não (nível 7)") | G30: =IF($Q$30="","",IFERROR(INDEX('Dados'!$F$126:$F$233,MATCH($Q$30,'Dados'!$C$126:$C$233,0)),"Fora do catálogo dos capítulos 07 a 15")) | H30: =IF($Q$30="","",IFERROR(INDEX('Dados'!$G$126:$G$233,MATCH($Q$30,'Dados'!$C$126:$C$233,0)),"")) | I30: =IF(AND($Q$30<>"",'Criação'!$A$14>=7),$Q$30,"") | K30: =IF(T30>0,"O Google leu como fórmula: escolha de novo na lista.",IF($Q$30="","",IF('Criação'!$A$14<7,"Slot ainda não liberado (nível 7). ","")&IF(ISERROR(MATCH($Q$30,'Dados'!$C$126:$C$233,0)),"Bênção fora do catálogo dos capítulos 07 a 15. ",IF(INDEX('Dados'!$A$126:$A$233,MATCH($Q$30,'Dados'!$C$126:$C$233,0))<>'Criação'!$Q$33,"Bênção de outro Caminho ("&INDEX('Dados'!$A$126:$A$233,MATCH($Q$30,'Dados'!$C$126:$C$233,0))&"). ",IF(INDEX('Dados'!$E$126:$E$233,MATCH($Q$30,'Dados'!$C$126:$C$233,0))>7,"Tier "&INDEX('Dados'!$D$126:$D$233,MATCH($Q$30,'Dados'!$C$126:$C$233,0))&" exige slot de nível "&INDEX('Dados'!$E$126:$E$233,MATCH($Q$30,'Dados'!$C$126:$C$233,0))&" ou mais. ","")))&IF(COUNTIF($Q$27:$Q$36,$Q$30)>1,"Bênção repetida.",""))) | N30: =IF('Criação'!$Q$33="","",IFERROR(INDEX('Dados'!$C$126:$C$233,MATCH('Criação'!$Q$33,'Dados'!$A$126:$A$233,0)+3),"")) | Q30: =IF(ISERROR($C$30),"",IF(ISBLANK($C$30),"",$C$30)) | T30: =ISERROR($C$30)*1
A31: Slot 5 | B31: 9 | D31: =IF($Q$31="","",IFERROR(INDEX('Dados'!$D$126:$D$233,MATCH($Q$31,'Dados'!$C$126:$C$233,0)),"—")) | E31: =IF($Q$31="","",IFERROR(INDEX('Dados'!$E$126:$E$233,MATCH($Q$31,'Dados'!$C$126:$C$233,0)),"")) | F31: =IF('Criação'!$A$14>=9,"Sim","Não (nível 9)") | G31: =IF($Q$31="","",IFERROR(INDEX('Dados'!$F$126:$F$233,MATCH($Q$31,'Dados'!$C$126:$C$233,0)),"Fora do catálogo dos capítulos 07 a 15")) | H31: =IF($Q$31="","",IFERROR(INDEX('Dados'!$G$126:$G$233,MATCH($Q$31,'Dados'!$C$126:$C$233,0)),"")) | I31: =IF(AND($Q$31<>"",'Criação'!$A$14>=9),$Q$31,"") | K31: =IF(T31>0,"O Google leu como fórmula: escolha de novo na lista.",IF($Q$31="","",IF('Criação'!$A$14<9,"Slot ainda não liberado (nível 9). ","")&IF(ISERROR(MATCH($Q$31,'Dados'!$C$126:$C$233,0)),"Bênção fora do catálogo dos capítulos 07 a 15. ",IF(INDEX('Dados'!$A$126:$A$233,MATCH($Q$31,'Dados'!$C$126:$C$233,0))<>'Criação'!$Q$33,"Bênção de outro Caminho ("&INDEX('Dados'!$A$126:$A$233,MATCH($Q$31,'Dados'!$C$126:$C$233,0))&"). ",IF(INDEX('Dados'!$E$126:$E$233,MATCH($Q$31,'Dados'!$C$126:$C$233,0))>9,"Tier "&INDEX('Dados'!$D$126:$D$233,MATCH($Q$31,'Dados'!$C$126:$C$233,0))&" exige slot de nível "&INDEX('Dados'!$E$126:$E$233,MATCH($Q$31,'Dados'!$C$126:$C$233,0))&" ou mais. ","")))&IF(COUNTIF($Q$27:$Q$36,$Q$31)>1,"Bênção repetida.",""))) | N31: =IF('Criação'!$Q$33="","",IFERROR(INDEX('Dados'!$C$126:$C$233,MATCH('Criação'!$Q$33,'Dados'!$A$126:$A$233,0)+4),"")) | Q31: =IF(ISERROR($C$31),"",IF(ISBLANK($C$31),"",$C$31)) | T31: =ISERROR($C$31)*1
A32: Slot 6 | B32: 11 | D32: =IF($Q$32="","",IFERROR(INDEX('Dados'!$D$126:$D$233,MATCH($Q$32,'Dados'!$C$126:$C$233,0)),"—")) | E32: =IF($Q$32="","",IFERROR(INDEX('Dados'!$E$126:$E$233,MATCH($Q$32,'Dados'!$C$126:$C$233,0)),"")) | F32: =IF('Criação'!$A$14>=11,"Sim","Não (nível 11)") | G32: =IF($Q$32="","",IFERROR(INDEX('Dados'!$F$126:$F$233,MATCH($Q$32,'Dados'!$C$126:$C$233,0)),"Fora do catálogo dos capítulos 07 a 15")) | H32: =IF($Q$32="","",IFERROR(INDEX('Dados'!$G$126:$G$233,MATCH($Q$32,'Dados'!$C$126:$C$233,0)),"")) | I32: =IF(AND($Q$32<>"",'Criação'!$A$14>=11),$Q$32,"") | K32: =IF(T32>0,"O Google leu como fórmula: escolha de novo na lista.",IF($Q$32="","",IF('Criação'!$A$14<11,"Slot ainda não liberado (nível 11). ","")&IF(ISERROR(MATCH($Q$32,'Dados'!$C$126:$C$233,0)),"Bênção fora do catálogo dos capítulos 07 a 15. ",IF(INDEX('Dados'!$A$126:$A$233,MATCH($Q$32,'Dados'!$C$126:$C$233,0))<>'Criação'!$Q$33,"Bênção de outro Caminho ("&INDEX('Dados'!$A$126:$A$233,MATCH($Q$32,'Dados'!$C$126:$C$233,0))&"). ",IF(INDEX('Dados'!$E$126:$E$233,MATCH($Q$32,'Dados'!$C$126:$C$233,0))>11,"Tier "&INDEX('Dados'!$D$126:$D$233,MATCH($Q$32,'Dados'!$C$126:$C$233,0))&" exige slot de nível "&INDEX('Dados'!$E$126:$E$233,MATCH($Q$32,'Dados'!$C$126:$C$233,0))&" ou mais. ","")))&IF(COUNTIF($Q$27:$Q$36,$Q$32)>1,"Bênção repetida.",""))) | N32: =IF('Criação'!$Q$33="","",IFERROR(INDEX('Dados'!$C$126:$C$233,MATCH('Criação'!$Q$33,'Dados'!$A$126:$A$233,0)+5),"")) | Q32: =IF(ISERROR($C$32),"",IF(ISBLANK($C$32),"",$C$32)) | T32: =ISERROR($C$32)*1
A33: Slot 7 | B33: 13 | D33: =IF($Q$33="","",IFERROR(INDEX('Dados'!$D$126:$D$233,MATCH($Q$33,'Dados'!$C$126:$C$233,0)),"—")) | E33: =IF($Q$33="","",IFERROR(INDEX('Dados'!$E$126:$E$233,MATCH($Q$33,'Dados'!$C$126:$C$233,0)),"")) | F33: =IF('Criação'!$A$14>=13,"Sim","Não (nível 13)") | G33: =IF($Q$33="","",IFERROR(INDEX('Dados'!$F$126:$F$233,MATCH($Q$33,'Dados'!$C$126:$C$233,0)),"Fora do catálogo dos capítulos 07 a 15")) | H33: =IF($Q$33="","",IFERROR(INDEX('Dados'!$G$126:$G$233,MATCH($Q$33,'Dados'!$C$126:$C$233,0)),"")) | I33: =IF(AND($Q$33<>"",'Criação'!$A$14>=13),$Q$33,"") | K33: =IF(T33>0,"O Google leu como fórmula: escolha de novo na lista.",IF($Q$33="","",IF('Criação'!$A$14<13,"Slot ainda não liberado (nível 13). ","")&IF(ISERROR(MATCH($Q$33,'Dados'!$C$126:$C$233,0)),"Bênção fora do catálogo dos capítulos 07 a 15. ",IF(INDEX('Dados'!$A$126:$A$233,MATCH($Q$33,'Dados'!$C$126:$C$233,0))<>'Criação'!$Q$33,"Bênção de outro Caminho ("&INDEX('Dados'!$A$126:$A$233,MATCH($Q$33,'Dados'!$C$126:$C$233,0))&"). ",IF(INDEX('Dados'!$E$126:$E$233,MATCH($Q$33,'Dados'!$C$126:$C$233,0))>13,"Tier "&INDEX('Dados'!$D$126:$D$233,MATCH($Q$33,'Dados'!$C$126:$C$233,0))&" exige slot de nível "&INDEX('Dados'!$E$126:$E$233,MATCH($Q$33,'Dados'!$C$126:$C$233,0))&" ou mais. ","")))&IF(COUNTIF($Q$27:$Q$36,$Q$33)>1,"Bênção repetida.",""))) | N33: =IF('Criação'!$Q$33="","",IFERROR(INDEX('Dados'!$C$126:$C$233,MATCH('Criação'!$Q$33,'Dados'!$A$126:$A$233,0)+6),"")) | Q33: =IF(ISERROR($C$33),"",IF(ISBLANK($C$33),"",$C$33)) | T33: =ISERROR($C$33)*1
A34: Slot 8 | B34: 15 | D34: =IF($Q$34="","",IFERROR(INDEX('Dados'!$D$126:$D$233,MATCH($Q$34,'Dados'!$C$126:$C$233,0)),"—")) | E34: =IF($Q$34="","",IFERROR(INDEX('Dados'!$E$126:$E$233,MATCH($Q$34,'Dados'!$C$126:$C$233,0)),"")) | F34: =IF('Criação'!$A$14>=15,"Sim","Não (nível 15)") | G34: =IF($Q$34="","",IFERROR(INDEX('Dados'!$F$126:$F$233,MATCH($Q$34,'Dados'!$C$126:$C$233,0)),"Fora do catálogo dos capítulos 07 a 15")) | H34: =IF($Q$34="","",IFERROR(INDEX('Dados'!$G$126:$G$233,MATCH($Q$34,'Dados'!$C$126:$C$233,0)),"")) | I34: =IF(AND($Q$34<>"",'Criação'!$A$14>=15),$Q$34,"") | K34: =IF(T34>0,"O Google leu como fórmula: escolha de novo na lista.",IF($Q$34="","",IF('Criação'!$A$14<15,"Slot ainda não liberado (nível 15). ","")&IF(ISERROR(MATCH($Q$34,'Dados'!$C$126:$C$233,0)),"Bênção fora do catálogo dos capítulos 07 a 15. ",IF(INDEX('Dados'!$A$126:$A$233,MATCH($Q$34,'Dados'!$C$126:$C$233,0))<>'Criação'!$Q$33,"Bênção de outro Caminho ("&INDEX('Dados'!$A$126:$A$233,MATCH($Q$34,'Dados'!$C$126:$C$233,0))&"). ",IF(INDEX('Dados'!$E$126:$E$233,MATCH($Q$34,'Dados'!$C$126:$C$233,0))>15,"Tier "&INDEX('Dados'!$D$126:$D$233,MATCH($Q$34,'Dados'!$C$126:$C$233,0))&" exige slot de nível "&INDEX('Dados'!$E$126:$E$233,MATCH($Q$34,'Dados'!$C$126:$C$233,0))&" ou mais. ","")))&IF(COUNTIF($Q$27:$Q$36,$Q$34)>1,"Bênção repetida.",""))) | N34: =IF('Criação'!$Q$33="","",IFERROR(INDEX('Dados'!$C$126:$C$233,MATCH('Criação'!$Q$33,'Dados'!$A$126:$A$233,0)+7),"")) | Q34: =IF(ISERROR($C$34),"",IF(ISBLANK($C$34),"",$C$34)) | T34: =ISERROR($C$34)*1
A35: Slot 9 | B35: 17 | D35: =IF($Q$35="","",IFERROR(INDEX('Dados'!$D$126:$D$233,MATCH($Q$35,'Dados'!$C$126:$C$233,0)),"—")) | E35: =IF($Q$35="","",IFERROR(INDEX('Dados'!$E$126:$E$233,MATCH($Q$35,'Dados'!$C$126:$C$233,0)),"")) | F35: =IF('Criação'!$A$14>=17,"Sim","Não (nível 17)") | G35: =IF($Q$35="","",IFERROR(INDEX('Dados'!$F$126:$F$233,MATCH($Q$35,'Dados'!$C$126:$C$233,0)),"Fora do catálogo dos capítulos 07 a 15")) | H35: =IF($Q$35="","",IFERROR(INDEX('Dados'!$G$126:$G$233,MATCH($Q$35,'Dados'!$C$126:$C$233,0)),"")) | I35: =IF(AND($Q$35<>"",'Criação'!$A$14>=17),$Q$35,"") | K35: =IF(T35>0,"O Google leu como fórmula: escolha de novo na lista.",IF($Q$35="","",IF('Criação'!$A$14<17,"Slot ainda não liberado (nível 17). ","")&IF(ISERROR(MATCH($Q$35,'Dados'!$C$126:$C$233,0)),"Bênção fora do catálogo dos capítulos 07 a 15. ",IF(INDEX('Dados'!$A$126:$A$233,MATCH($Q$35,'Dados'!$C$126:$C$233,0))<>'Criação'!$Q$33,"Bênção de outro Caminho ("&INDEX('Dados'!$A$126:$A$233,MATCH($Q$35,'Dados'!$C$126:$C$233,0))&"). ",IF(INDEX('Dados'!$E$126:$E$233,MATCH($Q$35,'Dados'!$C$126:$C$233,0))>17,"Tier "&INDEX('Dados'!$D$126:$D$233,MATCH($Q$35,'Dados'!$C$126:$C$233,0))&" exige slot de nível "&INDEX('Dados'!$E$126:$E$233,MATCH($Q$35,'Dados'!$C$126:$C$233,0))&" ou mais. ","")))&IF(COUNTIF($Q$27:$Q$36,$Q$35)>1,"Bênção repetida.",""))) | N35: =IF('Criação'!$Q$33="","",IFERROR(INDEX('Dados'!$C$126:$C$233,MATCH('Criação'!$Q$33,'Dados'!$A$126:$A$233,0)+8),"")) | Q35: =IF(ISERROR($C$35),"",IF(ISBLANK($C$35),"",$C$35)) | T35: =ISERROR($C$35)*1
A36: Slot 10 | B36: 19 | D36: =IF($Q$36="","",IFERROR(INDEX('Dados'!$D$126:$D$233,MATCH($Q$36,'Dados'!$C$126:$C$233,0)),"—")) | E36: =IF($Q$36="","",IFERROR(INDEX('Dados'!$E$126:$E$233,MATCH($Q$36,'Dados'!$C$126:$C$233,0)),"")) | F36: =IF('Criação'!$A$14>=19,"Sim","Não (nível 19)") | G36: =IF($Q$36="","",IFERROR(INDEX('Dados'!$F$126:$F$233,MATCH($Q$36,'Dados'!$C$126:$C$233,0)),"Fora do catálogo dos capítulos 07 a 15")) | H36: =IF($Q$36="","",IFERROR(INDEX('Dados'!$G$126:$G$233,MATCH($Q$36,'Dados'!$C$126:$C$233,0)),"")) | I36: =IF(AND($Q$36<>"",'Criação'!$A$14>=19),$Q$36,"") | K36: =IF(T36>0,"O Google leu como fórmula: escolha de novo na lista.",IF($Q$36="","",IF('Criação'!$A$14<19,"Slot ainda não liberado (nível 19). ","")&IF(ISERROR(MATCH($Q$36,'Dados'!$C$126:$C$233,0)),"Bênção fora do catálogo dos capítulos 07 a 15. ",IF(INDEX('Dados'!$A$126:$A$233,MATCH($Q$36,'Dados'!$C$126:$C$233,0))<>'Criação'!$Q$33,"Bênção de outro Caminho ("&INDEX('Dados'!$A$126:$A$233,MATCH($Q$36,'Dados'!$C$126:$C$233,0))&"). ",IF(INDEX('Dados'!$E$126:$E$233,MATCH($Q$36,'Dados'!$C$126:$C$233,0))>19,"Tier "&INDEX('Dados'!$D$126:$D$233,MATCH($Q$36,'Dados'!$C$126:$C$233,0))&" exige slot de nível "&INDEX('Dados'!$E$126:$E$233,MATCH($Q$36,'Dados'!$C$126:$C$233,0))&" ou mais. ","")))&IF(COUNTIF($Q$27:$Q$36,$Q$36)>1,"Bênção repetida.",""))) | N36: =IF('Criação'!$Q$33="","",IFERROR(INDEX('Dados'!$C$126:$C$233,MATCH('Criação'!$Q$33,'Dados'!$A$126:$A$233,0)+9),"")) | Q36: =IF(ISERROR($C$36),"",IF(ISBLANK($C$36),"",$C$36)) | T36: =ISERROR($C$36)*1
N37: =IF('Criação'!$Q$33="","",IFERROR(INDEX('Dados'!$C$126:$C$233,MATCH('Criação'!$Q$33,'Dados'!$A$126:$A$233,0)+10),""))
A38: Catálogo das 12 Bênçãos do seu Caminho | N38: =IF('Criação'!$Q$33="","",IFERROR(INDEX('Dados'!$C$126:$C$233,MATCH('Criação'!$Q$33,'Dados'!$A$126:$A$233,0)+11),""))
A39: Nº | C39: Bênção | D39: Tier | E39: Requisito (nível) | F39: Pode escolher agora? | G39: Em uma linha | H39: Frequência
A40: 1 | C40: =$N$27 | D40: =IF($N$27="","",IFERROR(INDEX('Dados'!$D$126:$D$233,MATCH($N$27,'Dados'!$C$126:$C$233,0)),"")) | E40: =IF($N$27="","",IFERROR(INDEX('Dados'!$E$126:$E$233,MATCH($N$27,'Dados'!$C$126:$C$233,0)),"")) | F40: =IF($N$27="","",IF(COUNTIF($Q$27:$Q$36,$N$27)>0,"Já escolhida",IF('Criação'!$A$14>=$E$40,"Sim","A partir do nível "&$E$40))) | G40: =IF($N$27="","",IFERROR(INDEX('Dados'!$F$126:$F$233,MATCH($N$27,'Dados'!$C$126:$C$233,0)),"")) | H40: =IF($N$27="","",IFERROR(INDEX('Dados'!$G$126:$G$233,MATCH($N$27,'Dados'!$C$126:$C$233,0)),""))
A41: 2 | C41: =$N$28 | D41: =IF($N$28="","",IFERROR(INDEX('Dados'!$D$126:$D$233,MATCH($N$28,'Dados'!$C$126:$C$233,0)),"")) | E41: =IF($N$28="","",IFERROR(INDEX('Dados'!$E$126:$E$233,MATCH($N$28,'Dados'!$C$126:$C$233,0)),"")) | F41: =IF($N$28="","",IF(COUNTIF($Q$27:$Q$36,$N$28)>0,"Já escolhida",IF('Criação'!$A$14>=$E$41,"Sim","A partir do nível "&$E$41))) | G41: =IF($N$28="","",IFERROR(INDEX('Dados'!$F$126:$F$233,MATCH($N$28,'Dados'!$C$126:$C$233,0)),"")) | H41: =IF($N$28="","",IFERROR(INDEX('Dados'!$G$126:$G$233,MATCH($N$28,'Dados'!$C$126:$C$233,0)),""))
A42: 3 | C42: =$N$29 | D42: =IF($N$29="","",IFERROR(INDEX('Dados'!$D$126:$D$233,MATCH($N$29,'Dados'!$C$126:$C$233,0)),"")) | E42: =IF($N$29="","",IFERROR(INDEX('Dados'!$E$126:$E$233,MATCH($N$29,'Dados'!$C$126:$C$233,0)),"")) | F42: =IF($N$29="","",IF(COUNTIF($Q$27:$Q$36,$N$29)>0,"Já escolhida",IF('Criação'!$A$14>=$E$42,"Sim","A partir do nível "&$E$42))) | G42: =IF($N$29="","",IFERROR(INDEX('Dados'!$F$126:$F$233,MATCH($N$29,'Dados'!$C$126:$C$233,0)),"")) | H42: =IF($N$29="","",IFERROR(INDEX('Dados'!$G$126:$G$233,MATCH($N$29,'Dados'!$C$126:$C$233,0)),""))
A43: 4 | C43: =$N$30 | D43: =IF($N$30="","",IFERROR(INDEX('Dados'!$D$126:$D$233,MATCH($N$30,'Dados'!$C$126:$C$233,0)),"")) | E43: =IF($N$30="","",IFERROR(INDEX('Dados'!$E$126:$E$233,MATCH($N$30,'Dados'!$C$126:$C$233,0)),"")) | F43: =IF($N$30="","",IF(COUNTIF($Q$27:$Q$36,$N$30)>0,"Já escolhida",IF('Criação'!$A$14>=$E$43,"Sim","A partir do nível "&$E$43))) | G43: =IF($N$30="","",IFERROR(INDEX('Dados'!$F$126:$F$233,MATCH($N$30,'Dados'!$C$126:$C$233,0)),"")) | H43: =IF($N$30="","",IFERROR(INDEX('Dados'!$G$126:$G$233,MATCH($N$30,'Dados'!$C$126:$C$233,0)),""))
A44: 5 | C44: =$N$31 | D44: =IF($N$31="","",IFERROR(INDEX('Dados'!$D$126:$D$233,MATCH($N$31,'Dados'!$C$126:$C$233,0)),"")) | E44: =IF($N$31="","",IFERROR(INDEX('Dados'!$E$126:$E$233,MATCH($N$31,'Dados'!$C$126:$C$233,0)),"")) | F44: =IF($N$31="","",IF(COUNTIF($Q$27:$Q$36,$N$31)>0,"Já escolhida",IF('Criação'!$A$14>=$E$44,"Sim","A partir do nível "&$E$44))) | G44: =IF($N$31="","",IFERROR(INDEX('Dados'!$F$126:$F$233,MATCH($N$31,'Dados'!$C$126:$C$233,0)),"")) | H44: =IF($N$31="","",IFERROR(INDEX('Dados'!$G$126:$G$233,MATCH($N$31,'Dados'!$C$126:$C$233,0)),""))
A45: 6 | C45: =$N$32 | D45: =IF($N$32="","",IFERROR(INDEX('Dados'!$D$126:$D$233,MATCH($N$32,'Dados'!$C$126:$C$233,0)),"")) | E45: =IF($N$32="","",IFERROR(INDEX('Dados'!$E$126:$E$233,MATCH($N$32,'Dados'!$C$126:$C$233,0)),"")) | F45: =IF($N$32="","",IF(COUNTIF($Q$27:$Q$36,$N$32)>0,"Já escolhida",IF('Criação'!$A$14>=$E$45,"Sim","A partir do nível "&$E$45))) | G45: =IF($N$32="","",IFERROR(INDEX('Dados'!$F$126:$F$233,MATCH($N$32,'Dados'!$C$126:$C$233,0)),"")) | H45: =IF($N$32="","",IFERROR(INDEX('Dados'!$G$126:$G$233,MATCH($N$32,'Dados'!$C$126:$C$233,0)),""))
A46: 7 | C46: =$N$33 | D46: =IF($N$33="","",IFERROR(INDEX('Dados'!$D$126:$D$233,MATCH($N$33,'Dados'!$C$126:$C$233,0)),"")) | E46: =IF($N$33="","",IFERROR(INDEX('Dados'!$E$126:$E$233,MATCH($N$33,'Dados'!$C$126:$C$233,0)),"")) | F46: =IF($N$33="","",IF(COUNTIF($Q$27:$Q$36,$N$33)>0,"Já escolhida",IF('Criação'!$A$14>=$E$46,"Sim","A partir do nível "&$E$46))) | G46: =IF($N$33="","",IFERROR(INDEX('Dados'!$F$126:$F$233,MATCH($N$33,'Dados'!$C$126:$C$233,0)),"")) | H46: =IF($N$33="","",IFERROR(INDEX('Dados'!$G$126:$G$233,MATCH($N$33,'Dados'!$C$126:$C$233,0)),""))
A47: 8 | C47: =$N$34 | D47: =IF($N$34="","",IFERROR(INDEX('Dados'!$D$126:$D$233,MATCH($N$34,'Dados'!$C$126:$C$233,0)),"")) | E47: =IF($N$34="","",IFERROR(INDEX('Dados'!$E$126:$E$233,MATCH($N$34,'Dados'!$C$126:$C$233,0)),"")) | F47: =IF($N$34="","",IF(COUNTIF($Q$27:$Q$36,$N$34)>0,"Já escolhida",IF('Criação'!$A$14>=$E$47,"Sim","A partir do nível "&$E$47))) | G47: =IF($N$34="","",IFERROR(INDEX('Dados'!$F$126:$F$233,MATCH($N$34,'Dados'!$C$126:$C$233,0)),"")) | H47: =IF($N$34="","",IFERROR(INDEX('Dados'!$G$126:$G$233,MATCH($N$34,'Dados'!$C$126:$C$233,0)),""))
A48: 9 | C48: =$N$35 | D48: =IF($N$35="","",IFERROR(INDEX('Dados'!$D$126:$D$233,MATCH($N$35,'Dados'!$C$126:$C$233,0)),"")) | E48: =IF($N$35="","",IFERROR(INDEX('Dados'!$E$126:$E$233,MATCH($N$35,'Dados'!$C$126:$C$233,0)),"")) | F48: =IF($N$35="","",IF(COUNTIF($Q$27:$Q$36,$N$35)>0,"Já escolhida",IF('Criação'!$A$14>=$E$48,"Sim","A partir do nível "&$E$48))) | G48: =IF($N$35="","",IFERROR(INDEX('Dados'!$F$126:$F$233,MATCH($N$35,'Dados'!$C$126:$C$233,0)),"")) | H48: =IF($N$35="","",IFERROR(INDEX('Dados'!$G$126:$G$233,MATCH($N$35,'Dados'!$C$126:$C$233,0)),""))
A49: 10 | C49: =$N$36 | D49: =IF($N$36="","",IFERROR(INDEX('Dados'!$D$126:$D$233,MATCH($N$36,'Dados'!$C$126:$C$233,0)),"")) | E49: =IF($N$36="","",IFERROR(INDEX('Dados'!$E$126:$E$233,MATCH($N$36,'Dados'!$C$126:$C$233,0)),"")) | F49: =IF($N$36="","",IF(COUNTIF($Q$27:$Q$36,$N$36)>0,"Já escolhida",IF('Criação'!$A$14>=$E$49,"Sim","A partir do nível "&$E$49))) | G49: =IF($N$36="","",IFERROR(INDEX('Dados'!$F$126:$F$233,MATCH($N$36,'Dados'!$C$126:$C$233,0)),"")) | H49: =IF($N$36="","",IFERROR(INDEX('Dados'!$G$126:$G$233,MATCH($N$36,'Dados'!$C$126:$C$233,0)),""))
A50: 11 | C50: =$N$37 | D50: =IF($N$37="","",IFERROR(INDEX('Dados'!$D$126:$D$233,MATCH($N$37,'Dados'!$C$126:$C$233,0)),"")) | E50: =IF($N$37="","",IFERROR(INDEX('Dados'!$E$126:$E$233,MATCH($N$37,'Dados'!$C$126:$C$233,0)),"")) | F50: =IF($N$37="","",IF(COUNTIF($Q$27:$Q$36,$N$37)>0,"Já escolhida",IF('Criação'!$A$14>=$E$50,"Sim","A partir do nível "&$E$50))) | G50: =IF($N$37="","",IFERROR(INDEX('Dados'!$F$126:$F$233,MATCH($N$37,'Dados'!$C$126:$C$233,0)),"")) | H50: =IF($N$37="","",IFERROR(INDEX('Dados'!$G$126:$G$233,MATCH($N$37,'Dados'!$C$126:$C$233,0)),""))
A51: 12 | C51: =$N$38 | D51: =IF($N$38="","",IFERROR(INDEX('Dados'!$D$126:$D$233,MATCH($N$38,'Dados'!$C$126:$C$233,0)),"")) | E51: =IF($N$38="","",IFERROR(INDEX('Dados'!$E$126:$E$233,MATCH($N$38,'Dados'!$C$126:$C$233,0)),"")) | F51: =IF($N$38="","",IF(COUNTIF($Q$27:$Q$36,$N$38)>0,"Já escolhida",IF('Criação'!$A$14>=$E$51,"Sim","A partir do nível "&$E$51))) | G51: =IF($N$38="","",IFERROR(INDEX('Dados'!$F$126:$F$233,MATCH($N$38,'Dados'!$C$126:$C$233,0)),"")) | H51: =IF($N$38="","",IFERROR(INDEX('Dados'!$G$126:$G$233,MATCH($N$38,'Dados'!$C$126:$C$233,0)),""))
A53: =IF('Criação'!$Q$33="A Recordação","Memoespírito — 11.3 a 11.5","Memoespírito — só para A Recordação")
A54: Só para A Recordação? | B54: =IF('Criação'!$Q$33="A Recordação","Sim","Não") | D54: Fora da Recordação o bloco fica cinza e as contas ficam vazias. | K54: =IF(AND(NOT(($B$54="Sim")),(LEN($P$55)+LEN($P$56)+LEN($P$57)+LEN($P$58)+LEN($P$60)+LEN($P$61)+LEN($P$62)+LEN($P$63)+LEN($P$64)+LEN($P$65)+LEN($P$67)+LEN($P$69)+LEN($P$70)+LEN($P$71)+LEN($P$72)+LEN($S$72)+LEN($P$73)+LEN($S$73)+LEN($Q$75)+LEN($Q$76)+LEN($Q$77)+LEN($P$78))>0),"Memoespírito só na Recordação: estes campos não contam","")
A55: Nome do Memoespírito | K55: =IF(T55>0,"O Google leu como fórmula: digite de novo com ' na frente.","") | P55: =IF(ISERROR($B$55),"",IF(ISBLANK($B$55),"",$B$55)) | T55: =ISERROR($B$55)*1
A56: Conceito (11.3 Passo 2) | D56: =IF(OR(NOT(($B$54="Sim")),$P$56=""),"",IFERROR(VLOOKUP($P$56,'Dados'!$A$550:$B$554,2,FALSE),"")) | K56: =IF(T56>0,"O Google leu como fórmula: escolha de novo na lista.","") | P56: =IF(ISERROR($B$56),"",IF(ISBLANK($B$56),"",$B$56)) | T56: =ISERROR($B$56)*1
A57: Função (11.3 Passo 3) | D57: =IF(OR(NOT(($B$54="Sim")),$P$57=""),"",IFERROR(VLOOKUP($P$57,'Dados'!$A$558:$B$561,2,FALSE),"")) | K57: =IF(T57>0,"O Google leu como fórmula: escolha de novo na lista.","") | P57: =IF(ISERROR($B$57),"",IF(ISBLANK($B$57),"",$B$57)) | T57: =ISERROR($B$57)*1
A58: Elemento dele | K58: =IF(T58>0,"O Google leu como fórmula: escolha de novo na lista.","") | P58: =IF(ISERROR($B$58),"",IF(ISBLANK($B$58),"",$B$58)) | T58: =ISERROR($B$58)*1
A59: Atributo | B59: Pontos (preencha, máx. 5) | C59: Pontos usados | D59: Teste de Resistência dele | K59: Aviso
A60: Poder | C60: =IF(ISNUMBER($P$60),MAX(0,MIN(5,INT($P$60))),0) | D60: =IF(($B$54="Sim"),"d20"&IF(($C$60+'Criação'!$C$14)>=0,"+","")&($C$60+'Criação'!$C$14),"") | K60: =IF(T60>0,"O Google leu como fórmula: digite de novo com ' na frente.",IF($P$60="","",IF(ISNUMBER($P$60),IF($P$60>5,"Máximo 5 pontos por Atributo","")&IF($P$60<0,"Pontos não podem ser negativos",""),"Precisa ser um número"))) | P60: =IF(ISERROR($B$60),"",IF(ISBLANK($B$60),"",$B$60)) | T60: =ISERROR($B$60)*1
A61: Agilidade | C61: =IF(ISNUMBER($P$61),MAX(0,MIN(5,INT($P$61))),0) | D61: =IF(($B$54="Sim"),"d20"&IF(($C$61+'Criação'!$C$14)>=0,"+","")&($C$61+'Criação'!$C$14),"") | K61: =IF(T61>0,"O Google leu como fórmula: digite de novo com ' na frente.",IF($P$61="","",IF(ISNUMBER($P$61),IF($P$61>5,"Máximo 5 pontos por Atributo","")&IF($P$61<0,"Pontos não podem ser negativos",""),"Precisa ser um número"))) | P61: =IF(ISERROR($B$61),"",IF(ISBLANK($B$61),"",$B$61)) | T61: =ISERROR($B$61)*1
A62: Vigor | C62: =IF(ISNUMBER($P$62),MAX(0,MIN(5,INT($P$62))),0) | D62: =IF(($B$54="Sim"),"d20"&IF(($C$62+'Criação'!$C$14)>=0,"+","")&($C$62+'Criação'!$C$14),"") | K62: =IF(T62>0,"O Google leu como fórmula: digite de novo com ' na frente.",IF($P$62="","",IF(ISNUMBER($P$62),IF($P$62>5,"Máximo 5 pontos por Atributo","")&IF($P$62<0,"Pontos não podem ser negativos",""),"Precisa ser um número"))) | P62: =IF(ISERROR($B$62),"",IF(ISBLANK($B$62),"",$B$62)) | T62: =ISERROR($B$62)*1
A63: Sincronia | C63: =IF(ISNUMBER($P$63),MAX(0,MIN(5,INT($P$63))),0) | D63: =IF(($B$54="Sim"),"d20"&IF(($C$63+'Criação'!$C$14)>=0,"+","")&($C$63+'Criação'!$C$14),"") | K63: =IF(T63>0,"O Google leu como fórmula: digite de novo com ' na frente.",IF($P$63="","",IF(ISNUMBER($P$63),IF($P$63>5,"Máximo 5 pontos por Atributo","")&IF($P$63<0,"Pontos não podem ser negativos",""),"Precisa ser um número"))) | P63: =IF(ISERROR($B$63),"",IF(ISBLANK($B$63),"",$B$63)) | T63: =ISERROR($B$63)*1
A64: Discernimento | C64: =IF(ISNUMBER($P$64),MAX(0,MIN(5,INT($P$64))),0) | D64: =IF(($B$54="Sim"),"d20"&IF(($C$64+'Criação'!$C$14)>=0,"+","")&($C$64+'Criação'!$C$14),"") | K64: =IF(T64>0,"O Google leu como fórmula: digite de novo com ' na frente.",IF($P$64="","",IF(ISNUMBER($P$64),IF($P$64>5,"Máximo 5 pontos por Atributo","")&IF($P$64<0,"Pontos não podem ser negativos",""),"Precisa ser um número"))) | P64: =IF(ISERROR($B$64),"",IF(ISBLANK($B$64),"",$B$64)) | T64: =ISERROR($B$64)*1
A65: Presença | C65: =IF(ISNUMBER($P$65),MAX(0,MIN(5,INT($P$65))),0) | D65: =IF(($B$54="Sim"),"d20"&IF(($C$65+'Criação'!$C$14)>=0,"+","")&($C$65+'Criação'!$C$14),"") | K65: =IF(T65>0,"O Google leu como fórmula: digite de novo com ' na frente.",IF($P$65="","",IF(ISNUMBER($P$65),IF($P$65>5,"Máximo 5 pontos por Atributo","")&IF($P$65<0,"Pontos não podem ser negativos",""),"Precisa ser um número"))) | P65: =IF(ISERROR($B$65),"",IF(ISBLANK($B$65),"",$B$65)) | T65: =ISERROR($B$65)*1
A66: Pontos totais (12 + metade do nível) / gastos | B66: =IF(($B$54="Sim"),'Criação'!$K$16,"") | C66: =SUM($P$60:$P$65) | K66: =IF(AND(($B$54="Sim"),$C$66>'Criação'!$K$16),"Pontos acima do total ("&'Criação'!$K$16&")","")
A67: Atributo de ataque dele (vazio = Poder) | D67: =IF($P$67="","Poder",$P$67) | K67: =IF(T67>0,"O Google leu como fórmula: escolha de novo na lista.","") | P67: =IF(ISERROR($B$67),"",IF(ISBLANK($B$67),"",$B$67)) | T67: =ISERROR($B$67)*1
A68: Bônus menor (11.3 Passo 4) | B68: Escolha (preencha) | D68: Efeito
A69: Bônus menor 1 | D69: =IF($P$69="","",IFERROR(VLOOKUP($P$69,'Dados'!$A$565:$B$570,2,FALSE),"")) | K69: =IF(T69>0,"O Google leu como fórmula: escolha de novo na lista.",IF($P$69="","",IF(COUNTIF($P$69:$P$71,$P$69)>1,"Bônus menor repetido: escolha 3 diferentes",IF(COUNTIF('Dados'!$AE$6:$AE$11,$P$69)=0,"Fora da lista de 11.3","")))) | P69: =IF(ISERROR($B$69),"",IF(ISBLANK($B$69),"",$B$69)) | T69: =ISERROR($B$69)*1
A70: Bônus menor 2 | D70: =IF($P$70="","",IFERROR(VLOOKUP($P$70,'Dados'!$A$565:$B$570,2,FALSE),"")) | K70: =IF(T70>0,"O Google leu como fórmula: escolha de novo na lista.",IF($P$70="","",IF(COUNTIF($P$69:$P$71,$P$70)>1,"Bônus menor repetido: escolha 3 diferentes",IF(COUNTIF('Dados'!$AE$6:$AE$11,$P$70)=0,"Fora da lista de 11.3","")))) | P70: =IF(ISERROR($B$70),"",IF(ISBLANK($B$70),"",$B$70)) | T70: =ISERROR($B$70)*1
A71: Bônus menor 3 | D71: =IF($P$71="","",IFERROR(VLOOKUP($P$71,'Dados'!$A$565:$B$570,2,FALSE),"")) | K71: =IF(T71>0,"O Google leu como fórmula: escolha de novo na lista.",IF($P$71="","",IF(COUNTIF($P$69:$P$71,$P$71)>1,"Bônus menor repetido: escolha 3 diferentes",IF(COUNTIF('Dados'!$AE$6:$AE$11,$P$71)=0,"Fora da lista de 11.3","")))) | P71: =IF(ISERROR($B$71),"",IF(ISBLANK($B$71),"",$B$71)) | T71: =ISERROR($B$71)*1
A72: Técnica Principal: nome | D72: o que faz | K72: =IF(T72>0,"O Google leu como fórmula: digite de novo com ' na frente.","") | P72: =IF(ISERROR($B$72),"",IF(ISBLANK($B$72),"",$B$72)) | S72: =IF(ISERROR($E$72),"",IF(ISBLANK($E$72),"",$E$72)) | T72: =ISERROR($B$72)*1+ISERROR($E$72)*1
A73: Técnica Auxiliar: nome | D73: o que faz | K73: =IF(T73>0,"O Google leu como fórmula: digite de novo com ' na frente.","") | P73: =IF(ISERROR($B$73),"",IF(ISBLANK($B$73),"",$B$73)) | S73: =IF(ISERROR($E$73),"",IF(ISBLANK($E$73),"",$E$73)) | T73: =ISERROR($B$73)*1+ISERROR($E$73)*1
A74: Evolução (11.3) | B74: Nível | C74: Escolha (preencha) | D74: Efeito
A75: Evolução 1 | B75: 8 | D75: =IF($Q$75="","",IFERROR(VLOOKUP($Q$75,'Dados'!$A$588:$B$590,2,FALSE),"")) | K75: =IF(T75>0,"O Google leu como fórmula: escolha de novo na lista.",IF($Q$75="","",IF('Criação'!$A$14<8,"Só a partir do nível 8. ","")&IF(COUNTIF($Q$75:$Q$77,$Q$75)>1,"Evolução repetida: cada uma só uma vez.",""))) | Q75: =IF(ISERROR($C$75),"",IF(ISBLANK($C$75),"",$C$75)) | T75: =ISERROR($C$75)*1
A76: Evolução 2 | B76: 14 | D76: =IF($Q$76="","",IFERROR(VLOOKUP($Q$76,'Dados'!$A$588:$B$590,2,FALSE),"")) | K76: =IF(T76>0,"O Google leu como fórmula: escolha de novo na lista.",IF($Q$76="","",IF('Criação'!$A$14<14,"Só a partir do nível 14. ","")&IF(COUNTIF($Q$75:$Q$77,$Q$76)>1,"Evolução repetida: cada uma só uma vez.",""))) | Q76: =IF(ISERROR($C$76),"",IF(ISBLANK($C$76),"",$C$76)) | T76: =ISERROR($C$76)*1
A77: Evolução 3 | B77: 20 | D77: =IF($Q$77="","",IFERROR(VLOOKUP($Q$77,'Dados'!$A$588:$B$590,2,FALSE),"")) | K77: =IF(T77>0,"O Google leu como fórmula: escolha de novo na lista.",IF($Q$77="","",IF('Criação'!$A$14<20,"Só a partir do nível 20. ","")&IF(COUNTIF($Q$75:$Q$77,$Q$77)>1,"Evolução repetida: cada uma só uma vez.",""))) | Q77: =IF(ISERROR($C$77),"",IF(ISBLANK($C$77),"",$C$77)) | T77: =ISERROR($C$77)*1
A78: Memória Desperta: +2 em | K78: =IF(T78>0,"O Google leu como fórmula: escolha de novo na lista.","") | P78: =IF(ISERROR($B$78),"",IF(ISBLANK($B$78),"",$B$78)) | T78: =ISERROR($B$78)*1
