Workbook

Sheet Início
A1: Início — Explorando Galáxias v1.2 | AA1: =SUMPRODUCT((LEN($K$16:$K$16)>0)*1) | AB1: =IFERROR(INDEX($K$16:$K$16,MATCH("?*",$K$16:$K$16,0))&"","") | AC1: =IF(LEN(AB1)>0,AB1,"")
A2: Legenda: | B2: Entrada (preencha) | C2: Calculada (automático) | D2: Aviso (texto em vermelho) | E2: Título de bloco | F2: Cabeçalho de coluna | G2: Rótulo da linha | H2: Linha alternada (outro tom) | I2: Não se aplica
A3: Comece por aqui: semente da campanha, índice das abas e como a planilha se organiza. | AA3: =SUMPRODUCT((LEN('Campanha'!$K$7:$K$13)>0)*1) | AB3: =IFERROR(INDEX('Campanha'!$K$7:$K$13,MATCH("?*",'Campanha'!$K$7:$K$13,0))&"","") | AC3: =IF(LEN(AB3)>0,AB3,AC4)
AA4: =SUMPRODUCT((LEN('Campanha'!$K$38:$K$38)>0)*1) | AB4: =IFERROR(INDEX('Campanha'!$K$38:$K$38,MATCH("?*",'Campanha'!$K$38:$K$38,0))&"","") | AC4: =IF(LEN(AB4)>0,AB4,AC5)
A5: Comece por aqui | AA5: =SUMPRODUCT((LEN('Campanha'!$K$47:$K$58)>0)*1) | AB5: =IFERROR(INDEX('Campanha'!$K$47:$K$58,MATCH("?*",'Campanha'!$K$47:$K$58,0))&"","") | AC5: =IF(LEN(AB5)>0,AB5,AC6)
A6: 1. Abra no Google Planilhas (Arquivo → Importar) e trabalhe numa cópia por campanha. | AA6: =SUMPRODUCT((LEN('Campanha'!$K$62:$K$71)>0)*1) | AB6: =IFERROR(INDEX('Campanha'!$K$62:$K$71,MATCH("?*",'Campanha'!$K$62:$K$71,0))&"","") | AC6: =IF(LEN(AB6)>0,AB6,AC7)
A7: 2. Aba Campanha: nível do grupo e nº de jogadores (uma vez; todas as abas leem daqui). Faça a Sessão Zero. | AA7: =SUMPRODUCT((LEN('Campanha'!$K$76:$K$85)>0)*1) | AB7: =IFERROR(INDEX('Campanha'!$K$76:$K$85,MATCH("?*",'Campanha'!$K$76:$K$85,0))&"","") | AC7: =IF(LEN(AB7)>0,AB7,AC8)
A8: 3. Aba Grupo: copie da ficha de cada jogador os números de combate e os testes. | AA8: =SUMPRODUCT((LEN('Campanha'!$K$87:$K$96)>0)*1) | AB8: =IFERROR(INDEX('Campanha'!$K$87:$K$96,MATCH("?*",'Campanha'!$K$87:$K$96,0))&"","") | AC8: =IF(LEN(AB8)>0,AB8,AC9)
A9: 4. Prepare: Encontros (com Inimigos e Bestiário), NPCs, Aventuras, Mundos; a sessão na aba Sessões. | AA9: =SUMPRODUCT((LEN('Campanha'!$K$98:$K$107)>0)*1) | AB9: =IFERROR(INDEX('Campanha'!$K$98:$K$107,MATCH("?*",'Campanha'!$K$98:$K$107,0))&"","") | AC9: =IF(LEN(AB9)>0,AB9,AC10)
A10: 5. Jogue com Combate e Improviso; o Escudo do Mestre impresso fica na mesa. | AA10: =SUMPRODUCT((LEN('Campanha'!$K$122:$K$131)>0)*1) | AB10: =IFERROR(INDEX('Campanha'!$K$122:$K$131,MATCH("?*",'Campanha'!$K$122:$K$131,0))&"","") | AC10: =IF(LEN(AB10)>0,AB10,AC11)
A11: 6. Depois: diário (Sessões), Missões, Recompensas, relógios e linha do tempo (Campanha). | AA11: =SUMPRODUCT((LEN('Campanha'!$K$134:$K$143)>0)*1) | AB11: =IFERROR(INDEX('Campanha'!$K$134:$K$143,MATCH("?*",'Campanha'!$K$134:$K$143,0))&"","") | AC11: =IF(LEN(AB11)>0,AB11,AC12)
A12: Amarelo = você preenche; azul = automático; vermelho = aviso; 'Sugestão da planilha' = não é regra do livro. | AA12: =SUMPRODUCT((LEN('Campanha'!$K$146:$K$153)>0)*1) | AB12: =IFERROR(INDEX('Campanha'!$K$146:$K$153,MATCH("?*",'Campanha'!$K$146:$K$153,0))&"","") | AC12: =IF(LEN(AB12)>0,AB12,AC13)
A13: Não comece um texto com +, - ou =: o Google entende como fórmula. Se precisar, digite um apóstrofo (') antes. | AA13: =SUMPRODUCT((LEN('Campanha'!$K$156:$K$165)>0)*1) | AB13: =IFERROR(INDEX('Campanha'!$K$156:$K$165,MATCH("?*",'Campanha'!$K$156:$K$165,0))&"","") | AC13: =IF(LEN(AB13)>0,AB13,AC14)
AA14: =SUMPRODUCT((LEN('Campanha'!$K$169:$K$181)>0)*1) | AB14: =IFERROR(INDEX('Campanha'!$K$169:$K$181,MATCH("?*",'Campanha'!$K$169:$K$181,0))&"","") | AC14: =IF(LEN(AB14)>0,AB14,AC15)
A15: Semente da campanha (geradores determinísticos, sem sorteio escondido) | AA15: =SUMPRODUCT((LEN('Campanha'!$K$183:$K$185)>0)*1) | AB15: =IFERROR(INDEX('Campanha'!$K$183:$K$185,MATCH("?*",'Campanha'!$K$183:$K$185,0))&"","") | AC15: =IF(LEN(AB15)>0,AB15,AC16)
A16: Semente da campanha | D16: Semente efetiva | E16: =IF(ISNUMBER($P$16),IF(AND($P$16>=1,$P$16<=2147483646,INT($P$16)=$P$16),$P$16,12345),12345) | G16: Vazia = 12345. | K16: =IF(Q16>0,"O Google leu como fórmula: digite de novo com ' na frente.",IF(LEN($P$16)=0,"",IF(ISNUMBER($P$16),IF(AND($P$16>=1,$P$16<=2147483646,INT($P$16)=$P$16),"","Semente fora de 1 a 2.147.483.646: usando 12345"),"Semente fora de 1 a 2.147.483.646: usando 12345"))) | P16: =IF(ISERROR($B$16),"",IF(ISBLANK($B$16),"",$B$16)) | Q16: =ISERROR($B$16)*1 | AA16: =SUMPRODUCT((LEN('Campanha'!$K$188:$K$192)>0)*1) | AB16: =IFERROR(INDEX('Campanha'!$K$188:$K$192,MATCH("?*",'Campanha'!$K$188:$K$192,0))&"","") | AC16: =IF(LEN(AB16)>0,AB16,"")
A17: Mesma semente e mesma 'Rolagem nº' dão sempre o mesmo resultado; editar outra célula não muda o sorteio. Para rolar de novo, some 1 na 'Rolagem nº' do gerador; para outra campanha, troque a semente.
AA18: =SUMPRODUCT((LEN('Grupo'!$K$7:$K$12)>0)*1) | AB18: =IFERROR(INDEX('Grupo'!$K$7:$K$12,MATCH("?*",'Grupo'!$K$7:$K$12,0))&"","") | AC18: =IF(LEN(AB18)>0,AB18,AC19)
A19: Painel da campanha (automático) | AA19: =SUMPRODUCT((LEN('Grupo'!$K$16:$K$21)>0)*1) | AB19: =IFERROR(INDEX('Grupo'!$K$16:$K$21,MATCH("?*",'Grupo'!$K$16:$K$21,0))&"","") | AC19: =IF(LEN(AB19)>0,AB19,AC20)
A20: Campo | B20: Agora | G20: De onde vem | AA20: =SUMPRODUCT((LEN('Grupo'!$K$25:$K$30)>0)*1) | AB20: =IFERROR(INDEX('Grupo'!$K$25:$K$30,MATCH("?*",'Grupo'!$K$25:$K$30,0))&"","") | AC20: =IF(LEN(AB20)>0,AB20,AC21)
A21: Campanha | B21: =IF(LEN('Campanha'!$AD$7)>0,'Campanha'!$AD$7,"(sem nome: aba Campanha)") | G21: Aba Campanha, Mesa. | AA21: =SUMPRODUCT((LEN('Grupo'!$K$34:$K$39)>0)*1) | AB21: =IFERROR(INDEX('Grupo'!$K$34:$K$39,MATCH("?*",'Grupo'!$K$34:$K$39,0))&"","") | AC21: =IF(LEN(AB21)>0,AB21,AC22)
A22: Sessão atual | B22: =IF(ISNUMBER('Campanha'!$AD$10),'Campanha'!$AD$10,"(vazia)")&" · dia de campanha "&'Campanha'!$B$41 | G22: Aba Campanha, Mesa. | AA22: =SUMPRODUCT((LEN('Grupo'!$K$43:$K$48)>0)*1) | AB22: =IFERROR(INDEX('Grupo'!$K$43:$K$48,MATCH("?*",'Grupo'!$K$43:$K$48,0))&"","") | AC22: =IF(LEN(AB22)>0,AB22,AC23)
A23: Nível e faixa | B23: ="Nível "&'Campanha'!$B$17&", faixa "&'Campanha'!$B$19&" · Eficiência +"&'Campanha'!$B$20 | G23: 26.1, 26.2, 26.3. | AA23: =SUMPRODUCT((LEN('Grupo'!$K$52:$K$57)>0)*1) | AB23: =IFERROR(INDEX('Grupo'!$K$52:$K$57,MATCH("?*",'Grupo'!$K$52:$K$57,0))&"","") | AC23: =IF(LEN(AB23)>0,AB23,AC24)
A24: PH do grupo | B24: ="Máximo "&'Campanha'!$B$24&" · início do combate "&'Campanha'!$B$25&" ("&'Campanha'!$B$21&" jogadores)" | G24: 16.2. | AA24: =SUMPRODUCT((LEN('Grupo'!$K$61:$K$66)>0)*1) | AB24: =IFERROR(INDEX('Grupo'!$K$61:$K$66,MATCH("?*",'Grupo'!$K$61:$K$66,0))&"","") | AC24: =IF(LEN(AB24)>0,AB24,AC25)
A25: Missões ativas | B25: ='Missões'!$C$54&" ativa(s) · "&'Missões'!$B$54&" oferecida(s) · "&'Missões'!$D$54&" concluída(s)" | G25: Aba Missões. | AA25: =SUMPRODUCT((LEN('Grupo'!$K$70:$K$75)>0)*1) | AB25: =IFERROR(INDEX('Grupo'!$K$70:$K$75,MATCH("?*",'Grupo'!$K$70:$K$75,0))&"","") | AC25: =IF(LEN(AB25)>0,AB25,AC26)
A26: Relógios a 1 de encher | B26: =COUNTIF('Campanha'!$G$62:$G$71,"Falta 1") | G26: Aba Campanha, relógios (Sugestão da planilha, H16). | AA26: =SUMPRODUCT((LEN('Grupo'!$C$79:$C$79)>0)*1) | AB26: =IFERROR(INDEX('Grupo'!$C$79:$C$79,MATCH("?*",'Grupo'!$C$79:$C$79,0))&"","") | AC26: =IF(LEN(AB26)>0,AB26,"")
A27: Próxima Ressonância | B27: ='Campanha'!$B$39 | G27: 26.7; sempre marco de história.
A28: Sessões no nível atual | B28: =IF(ISNUMBER('Campanha'!$AD$38),'Campanha'!$AD$38&IF('Campanha'!$AD$38=1," sessão"," sessões")&" no nível · ","")&'Campanha'!$E$38 | G28: 26.1. | AA28: =SUMPRODUCT((LEN('Sessões'!$K$7:$K$10)>0)*1) | AB28: =IFERROR(INDEX('Sessões'!$K$7:$K$10,MATCH("?*",'Sessões'!$K$7:$K$10,0))&"","") | AC28: =IF(LEN(AB28)>0,AB28,AC29)
A29: Próxima sessão preparada | B29: =IF(LEN('Sessões'!$R$9)>0,IF(ISNUMBER('Sessões'!$R$7),"Sessão "&'Sessões'!$R$7&": ","")&'Sessões'!$R$9,"(nenhuma: aba Sessões)") | G29: Aba Sessões. | AA29: =SUMPRODUCT((LEN('Sessões'!$K$14:$K$18)>0)*1) | AB29: =IFERROR(INDEX('Sessões'!$K$14:$K$18,MATCH("?*",'Sessões'!$K$14:$K$18,0))&"","") | AC29: =IF(LEN(AB29)>0,AB29,AC30)
AA30: =SUMPRODUCT((LEN('Sessões'!$K$28:$K$37)>0)*1) | AB30: =IFERROR(INDEX('Sessões'!$K$28:$K$37,MATCH("?*",'Sessões'!$K$28:$K$37,0))&"","") | AC30: =IF(LEN(AB30)>0,AB30,AC31)
A31: Índice das abas | AA31: =SUMPRODUCT((LEN('Sessões'!$K$41:$K$41)>0)*1) | AB31: =IFERROR(INDEX('Sessões'!$K$41:$K$41,MATCH("?*",'Sessões'!$K$41:$K$41,0))&"","") | AC31: =IF(LEN(AB31)>0,AB31,AC32)
A32: Aba | B32: Para que serve | H32: Quando usar | AA32: =SUMPRODUCT((LEN('Sessões'!$K$46:$K$51)>0)*1) | AB32: =IFERROR(INDEX('Sessões'!$K$46:$K$51,MATCH("?*",'Sessões'!$K$46:$K$51,0))&"","") | AC32: =IF(LEN(AB32)>0,AB32,AC33)
A33: Início | B33: Semente da campanha, painel, índice e avisos. | H33: Na primeira vez e no começo de cada sessão. | AA33: =SUMPRODUCT((LEN('Sessões'!$K$55:$K$59)>0)*1) | AB33: =IFERROR(INDEX('Sessões'!$K$55:$K$59,MATCH("?*",'Sessões'!$K$55:$K$59,0))&"","") | AC33: =IF(LEN(AB33)>0,AB33,AC34)
A34: Campanha | B34: Mesa, marcos, facções, relógios, linha do tempo, Ficha de Decisões e Sessão Zero. | H34: Ao começar e entre sessões. | AA34: =SUMPRODUCT((LEN('Sessões'!$K$64:$K$73)>0)*1) | AB34: =IFERROR(INDEX('Sessões'!$K$64:$K$73,MATCH("?*",'Sessões'!$K$64:$K$73,0))&"","") | AC34: =IF(LEN(AB34)>0,AB34,AC35)
A35: Grupo | B35: Os PJs copiados da ficha de cada jogador, com os testes que o Mestre pede. | H35: Ao começar e quando a ficha muda. | AA35: =SUMPRODUCT((LEN('Sessões'!$K$75:$K$84)>0)*1) | AB35: =IFERROR(INDEX('Sessões'!$K$75:$K$84,MATCH("?*",'Sessões'!$K$75:$K$84,0))&"","") | AC35: =IF(LEN(AB35)>0,AB35,AC36)
A36: Sessões | B36: Preparar a próxima sessão (cenas, pistas, ganchos, checklist) e o diário. | H36: Entre sessões. | AA36: =SUMPRODUCT((LEN('Sessões'!$K$86:$K$95)>0)*1) | AB36: =IFERROR(INDEX('Sessões'!$K$86:$K$95,MATCH("?*",'Sessões'!$K$86:$K$95,0))&"","") | AC36: =IF(LEN(AB36)>0,AB36,AC37)
A37: Missões | B37: Missões oferecidas, ativas e concluídas. | H37: Entre sessões. | AA37: =SUMPRODUCT((LEN('Sessões'!$K$98:$K$107)>0)*1) | AB37: =IFERROR(INDEX('Sessões'!$K$98:$K$107,MATCH("?*",'Sessões'!$K$98:$K$107,0))&"","") | AC37: =IF(LEN(AB37)>0,AB37,AC38)
A38: NPCs | B38: Gerador de NPCs, elenco e cartões. | H38: Preparando a história. | AA38: =SUMPRODUCT((LEN('Sessões'!$K$109:$K$118)>0)*1) | AB38: =IFERROR(INDEX('Sessões'!$K$109:$K$118,MATCH("?*",'Sessões'!$K$109:$K$118,0))&"","") | AC38: =IF(LEN(AB38)>0,AB38,AC39)
A39: Inimigos | B39: Criador de Inimigos: a ficha de 28.1 pronta. | H39: Preparando o combate. | AA39: =SUMPRODUCT((LEN('Sessões'!$K$120:$K$129)>0)*1) | AB39: =IFERROR(INDEX('Sessões'!$K$120:$K$129,MATCH("?*",'Sessões'!$K$120:$K$129,0))&"","") | AC39: =IF(LEN(AB39)>0,AB39,"")
A40: Bestiário | B40: As 32 fichas do capítulo 28 com filtro. | H40: Preparando o combate.
A41: Encontros | B41: Orçamento, encontros salvos, contrato da Fraqueza, encontro aleatório. | H41: Preparando o combate. | AA41: =SUMPRODUCT((LEN('Missões'!$K$8:$K$17)>0)*1) | AB41: =IFERROR(INDEX('Missões'!$K$8:$K$17,MATCH("?*",'Missões'!$K$8:$K$17,0))&"","") | AC41: =IF(LEN(AB41)>0,AB41,AC42)
A42: Aba | B42: Para que serve | H42: Quando usar | AA42: =SUMPRODUCT((LEN('Missões'!$K$19:$K$28)>0)*1) | AB42: =IFERROR(INDEX('Missões'!$K$19:$K$28,MATCH("?*",'Missões'!$K$19:$K$28,0))&"","") | AC42: =IF(LEN(AB42)>0,AB42,AC43)
A43: Combate | B43: Fila de Ação, PV, Tenacidade e Quebra, condições, Morrendo. | H43: Na mesa, durante a luta. | AA43: =SUMPRODUCT((LEN('Missões'!$K$31:$K$40)>0)*1) | AB43: =IFERROR(INDEX('Missões'!$K$31:$K$40,MATCH("?*",'Missões'!$K$31:$K$40,0))&"","") | AC43: =IF(LEN(AB43)>0,AB43,AC44)
A44: Aventuras | B44: Gerador de aventuras com 5 cenas. | H44: Preparando a história. | AA44: =SUMPRODUCT((LEN('Missões'!$K$42:$K$51)>0)*1) | AB44: =IFERROR(INDEX('Missões'!$K$42:$K$51,MATCH("?*",'Missões'!$K$42:$K$51,0))&"","") | AC44: =IF(LEN(AB44)>0,AB44,AC45)
A45: Recompensas | B45: Entrega de marco, achados, Cone e Conjunto, tesouro. | H45: Depois de um encontro ou marco. | AA45: =SUMPRODUCT((LEN('Missões'!$A$55:$A$55)>0)*1) | AB45: =IFERROR(INDEX('Missões'!$A$55:$A$55,MATCH("?*",'Missões'!$A$55:$A$55,0))&"","") | AC45: =IF(LEN(AB45)>0,AB45,"")
A46: Mundos | B46: Planetas, estações, naves, facções, organizações e nomes. | H46: Preparando a história.
A47: Improviso | B47: Rumores, eventos, loja, bugigangas, oráculo, rolador e DT rápida. | H47: Na mesa, quando precisar. | AA47: =SUMPRODUCT((LEN('NPCs'!$K$7:$K$7)>0)*1) | AB47: =IFERROR(INDEX('NPCs'!$K$7:$K$7,MATCH("?*",'NPCs'!$K$7:$K$7,0))&"","") | AC47: =IF(LEN(AB47)>0,AB47,AC48)
A48: Escudo do Mestre | B48: Referência de mesa para imprimir (A4 paisagem). | H48: Antes da sessão. | AA48: =SUMPRODUCT((LEN('NPCs'!$K$12:$K$12)>0)*1) | AB48: =IFERROR(INDEX('NPCs'!$K$12:$K$12,MATCH("?*",'NPCs'!$K$12:$K$12,0))&"","") | AC48: =IF(LEN(AB48)>0,AB48,AC49)
A49: Minhas Tabelas | B49: Dez tabelas do próprio Mestre, com sorteio. | H49: Quando quiser. | AA49: =SUMPRODUCT((LEN('NPCs'!$K$15:$K$22)>0)*1) | AB49: =IFERROR(INDEX('NPCs'!$K$15:$K$22,MATCH("?*",'NPCs'!$K$15:$K$22,0))&"","") | AC49: =IF(LEN(AB49)>0,AB49,AC50)
A50: Tabelas | B50: Listas dos geradores, editáveis (100 vagas). | H50: Para mudar o que os geradores sorteiam. | AA50: =SUMPRODUCT((LEN('NPCs'!$K$46:$K$55)>0)*1) | AB50: =IFERROR(INDEX('NPCs'!$K$46:$K$55,MATCH("?*",'NPCs'!$K$46:$K$55,0))&"","") | AC50: =IF(LEN(AB50)>0,AB50,AC51)
A51: Dados | B51: Tabelas do livro usadas pelas fórmulas. Não edite. | H51: Nunca: o gerador reescreve. | AA51: =SUMPRODUCT((LEN('NPCs'!$K$57:$K$66)>0)*1) | AB51: =IFERROR(INDEX('NPCs'!$K$57:$K$66,MATCH("?*",'NPCs'!$K$57:$K$66,0))&"","") | AC51: =IF(LEN(AB51)>0,AB51,AC52)
AA52: =SUMPRODUCT((LEN('NPCs'!$K$68:$K$77)>0)*1) | AB52: =IFERROR(INDEX('NPCs'!$K$68:$K$77,MATCH("?*",'NPCs'!$K$68:$K$77,0))&"","") | AC52: =IF(LEN(AB52)>0,AB52,AC53)
A53: Avisos por aba (automático): quantos estão acesos e o primeiro deles | AA53: =SUMPRODUCT((LEN('NPCs'!$K$80:$K$89)>0)*1) | AB53: =IFERROR(INDEX('NPCs'!$K$80:$K$89,MATCH("?*",'NPCs'!$K$80:$K$89,0))&"","") | AC53: =IF(LEN(AB53)>0,AB53,AC54)
A54: Aba | B54: Avisos acesos | C54: Primeiro aviso aceso | AA54: =SUMPRODUCT((LEN('NPCs'!$K$91:$K$100)>0)*1) | AB54: =IFERROR(INDEX('NPCs'!$K$91:$K$100,MATCH("?*",'NPCs'!$K$91:$K$100,0))&"","") | AC54: =IF(LEN(AB54)>0,AB54,AC55)
A55: Início | B55: =SUM($AA$1:$AA$1) | C55: =AC1 | AA55: =SUMPRODUCT((LEN('NPCs'!$K$102:$K$111)>0)*1) | AB55: =IFERROR(INDEX('NPCs'!$K$102:$K$111,MATCH("?*",'NPCs'!$K$102:$K$111,0))&"","") | AC55: =IF(LEN(AB55)>0,AB55,AC56)
A56: Campanha | B56: =SUM($AA$3:$AA$16) | C56: =AC3 | AA56: =SUMPRODUCT((LEN('NPCs'!$K$114:$K$123)>0)*1) | AB56: =IFERROR(INDEX('NPCs'!$K$114:$K$123,MATCH("?*",'NPCs'!$K$114:$K$123,0))&"","") | AC56: =IF(LEN(AB56)>0,AB56,AC57)
A57: Grupo | B57: =SUM($AA$18:$AA$26) | C57: =AC18 | AA57: =SUMPRODUCT((LEN('NPCs'!$K$125:$K$134)>0)*1) | AB57: =IFERROR(INDEX('NPCs'!$K$125:$K$134,MATCH("?*",'NPCs'!$K$125:$K$134,0))&"","") | AC57: =IF(LEN(AB57)>0,AB57,AC58)
A58: Sessões | B58: =SUM($AA$28:$AA$39) | C58: =AC28 | AA58: =SUMPRODUCT((LEN('NPCs'!$K$136:$K$145)>0)*1) | AB58: =IFERROR(INDEX('NPCs'!$K$136:$K$145,MATCH("?*",'NPCs'!$K$136:$K$145,0))&"","") | AC58: =IF(LEN(AB58)>0,AB58,AC59)
A59: Missões | B59: =SUM($AA$41:$AA$45) | C59: =AC41 | AA59: =SUMPRODUCT((LEN('NPCs'!$K$148:$K$157)>0)*1) | AB59: =IFERROR(INDEX('NPCs'!$K$148:$K$157,MATCH("?*",'NPCs'!$K$148:$K$157,0))&"","") | AC59: =IF(LEN(AB59)>0,AB59,AC60)
A60: NPCs | B60: =SUM($AA$47:$AA$66) | C60: =AC47 | AA60: =SUMPRODUCT((LEN('NPCs'!$K$159:$K$168)>0)*1) | AB60: =IFERROR(INDEX('NPCs'!$K$159:$K$168,MATCH("?*",'NPCs'!$K$159:$K$168,0))&"","") | AC60: =IF(LEN(AB60)>0,AB60,AC61)
A61: Inimigos | B61: =SUM($AA$68:$AA$80) | C61: =AC68 | AA61: =SUMPRODUCT((LEN('NPCs'!$K$170:$K$179)>0)*1) | AB61: =IFERROR(INDEX('NPCs'!$K$170:$K$179,MATCH("?*",'NPCs'!$K$170:$K$179,0))&"","") | AC61: =IF(LEN(AB61)>0,AB61,AC62)
A62: Bestiário | B62: =SUM($AA$82:$AA$84) | C62: =AC82 | AA62: =SUMPRODUCT((LEN('NPCs'!$K$182:$K$191)>0)*1) | AB62: =IFERROR(INDEX('NPCs'!$K$182:$K$191,MATCH("?*",'NPCs'!$K$182:$K$191,0))&"","") | AC62: =IF(LEN(AB62)>0,AB62,AC63)
A63: Encontros | B63: =SUM($AA$86:$AA$103) | C63: =AC86 | AA63: =SUMPRODUCT((LEN('NPCs'!$K$193:$K$202)>0)*1) | AB63: =IFERROR(INDEX('NPCs'!$K$193:$K$202,MATCH("?*",'NPCs'!$K$193:$K$202,0))&"","") | AC63: =IF(LEN(AB63)>0,AB63,AC64)
A64: Aba | B64: Avisos acesos | C64: Primeiro aviso aceso | AA64: =SUMPRODUCT((LEN('NPCs'!$K$204:$K$213)>0)*1) | AB64: =IFERROR(INDEX('NPCs'!$K$204:$K$213,MATCH("?*",'NPCs'!$K$204:$K$213,0))&"","") | AC64: =IF(LEN(AB64)>0,AB64,AC65)
A65: Combate | B65: =SUM($AA$105:$AA$126) | C65: =AC105 | AA65: =SUMPRODUCT((LEN('NPCs'!$K$216:$K$216)>0)*1) | AB65: =IFERROR(INDEX('NPCs'!$K$216:$K$216,MATCH("?*",'NPCs'!$K$216:$K$216,0))&"","") | AC65: =IF(LEN(AB65)>0,AB65,AC66)
A66: Aventuras | B66: =SUM($AA$128:$AA$131) | C66: =AC128 | AA66: =SUMPRODUCT((LEN('NPCs'!$K$225:$K$225)>0)*1) | AB66: =IFERROR(INDEX('NPCs'!$K$225:$K$225,MATCH("?*",'NPCs'!$K$225:$K$225,0))&"","") | AC66: =IF(LEN(AB66)>0,AB66,"")
A67: Recompensas | B67: =SUM($AA$133:$AA$145) | C67: =AC133
A68: Mundos | B68: =SUM($AA$147:$AA$158) | C68: =AC147 | AA68: =SUMPRODUCT((LEN('Inimigos'!$K$7:$K$7)>0)*1) | AB68: =IFERROR(INDEX('Inimigos'!$K$7:$K$7,MATCH("?*",'Inimigos'!$K$7:$K$7,0))&"","") | AC68: =IF(LEN(AB68)>0,AB68,AC69)
A69: Improviso | B69: =SUM($AA$160:$AA$170) | C69: =AC160 | AA69: =SUMPRODUCT((LEN('Inimigos'!$K$11:$K$22)>0)*1) | AB69: =IFERROR(INDEX('Inimigos'!$K$11:$K$22,MATCH("?*",'Inimigos'!$K$11:$K$22,0))&"","") | AC69: =IF(LEN(AB69)>0,AB69,AC70)
A70: Escudo do Mestre | B70: =0 | C70: ="" | AA70: =SUMPRODUCT((LEN('Inimigos'!$K$26:$K$37)>0)*1) | AB70: =IFERROR(INDEX('Inimigos'!$K$26:$K$37,MATCH("?*",'Inimigos'!$K$26:$K$37,0))&"","") | AC70: =IF(LEN(AB70)>0,AB70,AC71)
A71: Minhas Tabelas | B71: =SUM($AA$172:$AA$204) | C71: =AC172 | AA71: =SUMPRODUCT((LEN('Inimigos'!$K$42:$K$53)>0)*1) | AB71: =IFERROR(INDEX('Inimigos'!$K$42:$K$53,MATCH("?*",'Inimigos'!$K$42:$K$53,0))&"","") | AC71: =IF(LEN(AB71)>0,AB71,AC72)
A72: Tabelas | B72: =SUM($AA$206:$AA$371) | C72: =AC206 | AA72: =SUMPRODUCT((LEN('Inimigos'!$K$72:$K$83)>0)*1) | AB72: =IFERROR(INDEX('Inimigos'!$K$72:$K$83,MATCH("?*",'Inimigos'!$K$72:$K$83,0))&"","") | AC72: =IF(LEN(AB72)>0,AB72,AC73)
A73: Dados | B73: =0 | C73: ="" | AA73: =SUMPRODUCT((LEN('Inimigos'!$K$88:$K$99)>0)*1) | AB73: =IFERROR(INDEX('Inimigos'!$K$88:$K$99,MATCH("?*",'Inimigos'!$K$88:$K$99,0))&"","") | AC73: =IF(LEN(AB73)>0,AB73,AC74)
AA74: =SUMPRODUCT((LEN('Inimigos'!$K$101:$K$112)>0)*1) | AB74: =IFERROR(INDEX('Inimigos'!$K$101:$K$112,MATCH("?*",'Inimigos'!$K$101:$K$112,0))&"","") | AC74: =IF(LEN(AB74)>0,AB74,AC75)
A75: Células com erro na planilha (o Google leu como fórmula um texto digitado) | AA75: =SUMPRODUCT((LEN('Inimigos'!$K$116:$K$127)>0)*1) | AB75: =IFERROR(INDEX('Inimigos'!$K$116:$K$127,MATCH("?*",'Inimigos'!$K$116:$K$127,0))&"","") | AC75: =IF(LEN(AB75)>0,AB75,AC76)
A76: Células com erro na planilha | B76: =$B$77+$D$77+$F$77+$H$77+$J$77+$B$78+$D$78+$F$78+$H$78+$J$78+$B$79+$D$79+$F$79+$H$79+$J$79+$B$80+$D$80+$F$80 | C76: =IF($B$76=0,"Nenhuma célula com erro.","O Google leu como fórmula um texto que começa com +, - ou =. Veja abaixo a aba com erro: o aviso da linha diz o que fazer. Apague e escreva de novo com um apóstrofo (') na frente, ou escolha de novo na lista.") | AA76: =SUMPRODUCT((LEN('Inimigos'!$K$129:$K$140)>0)*1) | AB76: =IFERROR(INDEX('Inimigos'!$K$129:$K$140,MATCH("?*",'Inimigos'!$K$129:$K$140,0))&"","") | AC76: =IF(LEN(AB76)>0,AB76,AC77)
A77: Início | B77: =SUMPRODUCT(ISERROR($A$1:$Q$75)*1) | C77: Campanha | D77: =SUMPRODUCT(ISERROR('Campanha'!$A$1:$AM$192)*1) | E77: Grupo | F77: =SUMPRODUCT(ISERROR('Grupo'!$A$1:$Z$85)*1) | G77: Sessões | H77: =SUMPRODUCT(ISERROR('Sessões'!$A$1:$AA$131)*1) | I77: Missões | J77: =SUMPRODUCT(ISERROR('Missões'!$A$1:$AL$104)*1) | AA77: =SUMPRODUCT((LEN('Inimigos'!$K$142:$K$153)>0)*1) | AB77: =IFERROR(INDEX('Inimigos'!$K$142:$K$153,MATCH("?*",'Inimigos'!$K$142:$K$153,0))&"","") | AC77: =IF(LEN(AB77)>0,AB77,AC78)
A78: NPCs | B78: =SUMPRODUCT(ISERROR('NPCs'!$A$1:$BF$232)*1) | C78: Inimigos | D78: =SUMPRODUCT(ISERROR('Inimigos'!$A$1:$EA$219)*1) | E78: Bestiário | F78: =SUMPRODUCT(ISERROR('Bestiário'!$A$1:$S$121)*1) | G78: Encontros | H78: =SUMPRODUCT(ISERROR('Encontros'!$A$1:$BN$122)*1) | I78: Combate | J78: =SUMPRODUCT(ISERROR('Combate'!$A$1:$CJ$311)*1) | AA78: =SUMPRODUCT((LEN('Inimigos'!$K$157:$K$168)>0)*1) | AB78: =IFERROR(INDEX('Inimigos'!$K$157:$K$168,MATCH("?*",'Inimigos'!$K$157:$K$168,0))&"","") | AC78: =IF(LEN(AB78)>0,AB78,AC79)
A79: Aventuras | B79: =SUMPRODUCT(ISERROR('Aventuras'!$A$1:$AU$116)*1) | C79: Recompensas | D79: =SUMPRODUCT(ISERROR('Recompensas'!$A$1:$AK$159)*1) | E79: Mundos | F79: =SUMPRODUCT(ISERROR('Mundos'!$A$1:$AF$106)*1) | G79: Improviso | H79: =SUMPRODUCT(ISERROR('Improviso'!$A$1:$AJ$121)*1) | I79: Escudo do Mestre | J79: =SUMPRODUCT(ISERROR('Escudo do Mestre'!$A$1:$N$173)*1) | AA79: =SUMPRODUCT((LEN('Inimigos'!$K$170:$K$181)>0)*1) | AB79: =IFERROR(INDEX('Inimigos'!$K$170:$K$181,MATCH("?*",'Inimigos'!$K$170:$K$181,0))&"","") | AC79: =IF(LEN(AB79)>0,AB79,AC80)
A80: Minhas Tabelas | B80: =SUMPRODUCT(ISERROR('Minhas Tabelas'!$A$1:$BF$470)*1) | C80: Tabelas | D80: =SUMPRODUCT(ISERROR('Tabelas'!$A$1:$AG$1268)*1) | E80: Dados | F80: =SUMPRODUCT(ISERROR('Dados'!$A$1:$CG$919)*1) | AA80: =SUMPRODUCT((LEN('Inimigos'!$K$183:$K$194)>0)*1) | AB80: =IFERROR(INDEX('Inimigos'!$K$183:$K$194,MATCH("?*",'Inimigos'!$K$183:$K$194,0))&"","") | AC80: =IF(LEN(AB80)>0,AB80,"")
AA82: =SUMPRODUCT((LEN('Bestiário'!$K$7:$K$9)>0)*1) | AB82: =IFERROR(INDEX('Bestiário'!$K$7:$K$9,MATCH("?*",'Bestiário'!$K$7:$K$9,0))&"","") | AC82: =IF(LEN(AB82)>0,AB82,AC83)
AA83: =SUMPRODUCT((LEN('Bestiário'!$K$11:$K$12)>0)*1) | AB83: =IFERROR(INDEX('Bestiário'!$K$11:$K$12,MATCH("?*",'Bestiário'!$K$11:$K$12,0))&"","") | AC83: =IF(LEN(AB83)>0,AB83,AC84)
AA84: =SUMPRODUCT((LEN('Bestiário'!$K$97:$K$97)>0)*1) | AB84: =IFERROR(INDEX('Bestiário'!$K$97:$K$97,MATCH("?*",'Bestiário'!$K$97:$K$97,0))&"","") | AC84: =IF(LEN(AB84)>0,AB84,"")
AA86: =SUMPRODUCT((LEN('Encontros'!$K$7:$K$8)>0)*1) | AB86: =IFERROR(INDEX('Encontros'!$K$7:$K$8,MATCH("?*",'Encontros'!$K$7:$K$8,0))&"","") | AC86: =IF(LEN(AB86)>0,AB86,AC87)
AA87: =SUMPRODUCT((LEN('Encontros'!$K$19:$K$19)>0)*1) | AB87: =IFERROR(INDEX('Encontros'!$K$19:$K$19,MATCH("?*",'Encontros'!$K$19:$K$19,0))&"","") | AC87: =IF(LEN(AB87)>0,AB87,AC88)
AA88: =SUMPRODUCT((LEN('Encontros'!$K$21:$K$28)>0)*1) | AB88: =IFERROR(INDEX('Encontros'!$K$21:$K$28,MATCH("?*",'Encontros'!$K$21:$K$28,0))&"","") | AC88: =IF(LEN(AB88)>0,AB88,AC89)
AA89: =SUMPRODUCT((LEN('Encontros'!$K$30:$K$37)>0)*1) | AB89: =IFERROR(INDEX('Encontros'!$K$30:$K$37,MATCH("?*",'Encontros'!$K$30:$K$37,0))&"","") | AC89: =IF(LEN(AB89)>0,AB89,AC90)
AA90: =SUMPRODUCT((LEN('Encontros'!$K$41:$K$41)>0)*1) | AB90: =IFERROR(INDEX('Encontros'!$K$41:$K$41,MATCH("?*",'Encontros'!$K$41:$K$41,0))&"","") | AC90: =IF(LEN(AB90)>0,AB90,AC91)
AA91: =SUMPRODUCT((LEN('Encontros'!$B$44:$B$44)>0)*1) | AB91: =IFERROR(INDEX('Encontros'!$B$44:$B$44,MATCH("?*",'Encontros'!$B$44:$B$44,0))&"","") | AC91: =IF(LEN(AB91)>0,AB91,AC92)
AA92: =SUMPRODUCT((LEN('Encontros'!$K$47:$K$47)>0)*1) | AB92: =IFERROR(INDEX('Encontros'!$K$47:$K$47,MATCH("?*",'Encontros'!$K$47:$K$47,0))&"","") | AC92: =IF(LEN(AB92)>0,AB92,AC93)
AA93: =SUMPRODUCT((LEN('Encontros'!$K$49:$K$56)>0)*1) | AB93: =IFERROR(INDEX('Encontros'!$K$49:$K$56,MATCH("?*",'Encontros'!$K$49:$K$56,0))&"","") | AC93: =IF(LEN(AB93)>0,AB93,AC94)
AA94: =SUMPRODUCT((LEN('Encontros'!$K$58:$K$65)>0)*1) | AB94: =IFERROR(INDEX('Encontros'!$K$58:$K$65,MATCH("?*",'Encontros'!$K$58:$K$65,0))&"","") | AC94: =IF(LEN(AB94)>0,AB94,AC95)
AA95: =SUMPRODUCT((LEN('Encontros'!$K$69:$K$69)>0)*1) | AB95: =IFERROR(INDEX('Encontros'!$K$69:$K$69,MATCH("?*",'Encontros'!$K$69:$K$69,0))&"","") | AC95: =IF(LEN(AB95)>0,AB95,AC96)
AA96: =SUMPRODUCT((LEN('Encontros'!$B$72:$B$72)>0)*1) | AB96: =IFERROR(INDEX('Encontros'!$B$72:$B$72,MATCH("?*",'Encontros'!$B$72:$B$72,0))&"","") | AC96: =IF(LEN(AB96)>0,AB96,AC97)
AA97: =SUMPRODUCT((LEN('Encontros'!$K$75:$K$75)>0)*1) | AB97: =IFERROR(INDEX('Encontros'!$K$75:$K$75,MATCH("?*",'Encontros'!$K$75:$K$75,0))&"","") | AC97: =IF(LEN(AB97)>0,AB97,AC98)
AA98: =SUMPRODUCT((LEN('Encontros'!$K$77:$K$84)>0)*1) | AB98: =IFERROR(INDEX('Encontros'!$K$77:$K$84,MATCH("?*",'Encontros'!$K$77:$K$84,0))&"","") | AC98: =IF(LEN(AB98)>0,AB98,AC99)
AA99: =SUMPRODUCT((LEN('Encontros'!$K$86:$K$93)>0)*1) | AB99: =IFERROR(INDEX('Encontros'!$K$86:$K$93,MATCH("?*",'Encontros'!$K$86:$K$93,0))&"","") | AC99: =IF(LEN(AB99)>0,AB99,AC100)
AA100: =SUMPRODUCT((LEN('Encontros'!$K$97:$K$97)>0)*1) | AB100: =IFERROR(INDEX('Encontros'!$K$97:$K$97,MATCH("?*",'Encontros'!$K$97:$K$97,0))&"","") | AC100: =IF(LEN(AB100)>0,AB100,AC101)
AA101: =SUMPRODUCT((LEN('Encontros'!$B$100:$B$100)>0)*1) | AB101: =IFERROR(INDEX('Encontros'!$B$100:$B$100,MATCH("?*",'Encontros'!$B$100:$B$100,0))&"","") | AC101: =IF(LEN(AB101)>0,AB101,AC102)
AA102: =SUMPRODUCT((LEN('Encontros'!$K$105:$K$105)>0)*1) | AB102: =IFERROR(INDEX('Encontros'!$K$105:$K$105,MATCH("?*",'Encontros'!$K$105:$K$105,0))&"","") | AC102: =IF(LEN(AB102)>0,AB102,AC103)
...

Sheet Campanha
A1: Campanha — Explorando Galáxias v1.2
A2: Legenda: | B2: Entrada (preencha) | C2: Calculada (automático) | D2: Aviso (texto em vermelho) | E2: Título de bloco | F2: Cabeçalho de coluna | G2: Rótulo da linha | H2: Linha alternada (outro tom) | I2: Não se aplica
A3: A mesa, os marcos, as facções e a reputação, os relógios, a linha do tempo, a Ficha de Decisões e a Sessão Zero.
A5: Mesa (preencha uma vez: todas as abas leem daqui — D9) | AA5: ='Tabelas'!$X$12&""
A6: Campo | B6: Valor (preencha) | E6: O que a planilha usa (automático) | K6: Aviso | AA6: ='Tabelas'!$X$13&""
A7: Nome da campanha | E7: ="A campanha aparece no título das abas de jogo." | K7: =IF(AM7>0,"O Google leu como fórmula: digite de novo com ' na frente.","") | AA7: ='Tabelas'!$X$14&"" | AD7: =IF(ISERROR($B$7),"",IF(ISBLANK($B$7),"",$B$7)) | AM7: =ISERROR($B$7)*1
A8: Nº de jogadores | E8: =IF(ISNUMBER($AD$8),"Jogadores na mesa: "&$B$21&".","Vazio: usando o nº de PJs da aba Grupo ("&$B$21&").") | K8: =IF(AM8>0,"O Google leu como fórmula: digite de novo com ' na frente.",IF(LEN($AD$8)=0,"",IF(NOT(ISNUMBER($AD$8)),"Nº de jogadores não é número: usando o nº de PJs do Grupo",IF(OR($AD$8<1,$AD$8>6,INT($AD$8)<>$AD$8),"Nº de jogadores fora de 1 a 6: usando o limite",IF(OR($AD$8<3,$AD$8>6),"Fora da tabela de 16.2 (3 a 6): PH calculado com o limite 3 a 6",""))))) | AA8: ='Tabelas'!$X$15&"" | AD8: =IF(ISERROR($B$8),"",IF(ISBLANK($B$8),"",$B$8)) | AM8: =ISERROR($B$8)*1
A9: Nível do grupo | E9: =IF(ISNUMBER($AD$9),"Nível "&$B$17&", faixa "&$B$19&".","Vazio: as abas calculam com o nível 1 (faixa 1-4).") | K9: =IF(AM9>0,"O Google leu como fórmula: digite de novo com ' na frente.",IF(LEN($AD$9)=0,"",IF(NOT(ISNUMBER($AD$9)),"Nível não é número: usando 1",IF(OR($AD$9<1,$AD$9>20,INT($AD$9)<>$AD$9),"Nível fora de 1 a 20: usando o limite","")))) | AA9: ='Tabelas'!$X$16&"" | AD9: =IF(ISERROR($B$9),"",IF(ISBLANK($B$9),"",$B$9)) | AM9: =ISERROR($B$9)*1
A10: Sessão atual | E10: ="Lida pela aba Sessões (preparação e diário) e pela Início." | K10: =IF(AM10>0,"O Google leu como fórmula: digite de novo com ' na frente.","") | AA10: ='Tabelas'!$X$17&"" | AD10: =IF(ISERROR($B$10),"",IF(ISBLANK($B$10),"",$B$10)) | AM10: =ISERROR($B$10)*1
A11: Dia de campanha | E11: ="Usado pela linha do tempo (nesta aba, mais abaixo)." | K11: =IF(AM11>0,"O Google leu como fórmula: digite de novo com ' na frente.","") | AA11: ='Tabelas'!$X$18&"" | AD11: =IF(ISERROR($B$11),"",IF(ISBLANK($B$11),"",$B$11)) | AM11: =ISERROR($B$11)*1
A12: Método de atributos | E12: ="Lembrete da Sessão Zero (capítulo 03)." | K12: =IF(AM12>0,"O Google leu como fórmula: escolha de novo na lista.","") | AA12: ='Tabelas'!$X$19&"" | AD12: =IF(ISERROR($B$12),"",IF(ISBLANK($B$12),"",$B$12)) | AM12: =ISERROR($B$12)*1
A13: Variantes da mesa | E13: ="Texto livre: média impressa, PV rolado, outra variante (06.4, 28.3)." | K13: =IF(AM13>0,"O Google leu como fórmula: digite de novo com ' na frente.","") | AA13: ='Tabelas'!$X$20&"" | AD13: =IF(ISERROR($B$13),"",IF(ISBLANK($B$13),"",$B$13)) | AM13: =ISERROR($B$13)*1
AA14: ='Tabelas'!$X$21&""
A15: Números do grupo (automático) | AA15: ='Tabelas'!$X$22&""
A16: Campo | B16: Valor | D16: Fonte no livro | G16: Observação | AA16: ='Tabelas'!$X$23&""
A17: Nível efetivo | B17: =IF(ISNUMBER($AD$9),MIN(20,MAX(1,INT($AD$9))),1) | D17: 26.1 | G17: Vazio = 1. | AA17: ='Tabelas'!$X$24&""
A18: Índice da faixa | B18: =INT(($B$17-1)/4)+1 | D18: 26.3 | G18: 1 a 5. | AA18: ='Tabelas'!$X$26&""
A19: Faixa do grupo | B19: =INDEX('Dados'!$B$7:$B$11,$B$18) | D19: 26.3 | G19: A faixa do inimigo é a faixa do grupo (28.4 passo 1). | AA19: ='Tabelas'!$X$27&""
A20: Eficiência | B20: =INDEX('Dados'!$B$15:$B$34,$B$17) | D20: 26.2 (02.3) | G20: Usada no Dano de Quebra e nas condições. | AA20: ='Tabelas'!$X$28&""
A21: Nº de jogadores efetivo | B21: =IF(ISNUMBER($AD$8),MIN(6,MAX(1,INT($AD$8))),MAX(1,'Grupo'!$B$79)) | D21: 16.2 | G21: Vazio = nº de PJs da aba Grupo (mínimo 1). | AA21: ='Tabelas'!$X$29&""
A22: Jogadores para o PH | B22: =MIN(6,MAX(3,$B$21)) | D22: 16.2 | G22: A tabela de 16.2 vai de 3 a 6 jogadores. | AA22: ='Tabelas'!$X$30&""
A23: Degrau de PH | B23: =IF($B$17<=8,1,IF($B$17<=16,2,3)) | D23: 16.2 | G23: 1 = níveis 1-8; 2 = 9-16; 3 = 17-20. | AA23: ='Tabelas'!$X$31&""
A24: PH máximo do grupo | B24: =IF($B$23=1,INDEX('Dados'!$B$343:$B$346,MATCH($B$22,'Dados'!$A$343:$A$346,0)),IF($B$23=2,INDEX('Dados'!$C$343:$C$346,MATCH($B$22,'Dados'!$A$343:$A$346,0)),INDEX('Dados'!$D$343:$D$346,MATCH($B$22,'Dados'!$A$343:$A$346,0)))) | D24: 16.2 | G24: Degraus 1-8, 9-16 e 17-20. | AA24: ='Tabelas'!$X$32&""
A25: PH no início do combate | B25: =IF($B$23=1,INDEX('Dados'!$E$343:$E$346,MATCH($B$22,'Dados'!$A$343:$A$346,0)),IF($B$23=2,INDEX('Dados'!$F$343:$F$346,MATCH($B$22,'Dados'!$A$343:$A$346,0)),INDEX('Dados'!$G$343:$G$346,MATCH($B$22,'Dados'!$A$343:$A$346,0)))) | D25: 16.2 | G25: Começa cada combate com o máximo menos 2. | AA25: ='Tabelas'!$X$33&""
A26: Campo | B26: Valor | D26: Fonte no livro | G26: Observação | AA26: ='Tabelas'!$X$34&""
A27: DT Média da faixa | B27: =IF($B$18=1,INDEX('Dados'!$B$284:$B$289,3),IF($B$18=2,INDEX('Dados'!$C$284:$C$289,3),IF($B$18=3,INDEX('Dados'!$D$284:$D$289,3),IF($B$18=4,INDEX('Dados'!$E$284:$E$289,3),INDEX('Dados'!$F$284:$F$289,3))))) | D27: 27.2 | G27: Regra 1: a faixa é a do desafio, não a do personagem. | AA27: ='Tabelas'!$X$35&""
A28: DT Difícil da faixa | B28: =IF($B$18=1,INDEX('Dados'!$B$284:$B$289,4),IF($B$18=2,INDEX('Dados'!$C$284:$C$289,4),IF($B$18=3,INDEX('Dados'!$D$284:$D$289,4),IF($B$18=4,INDEX('Dados'!$E$284:$E$289,4),INDEX('Dados'!$F$284:$F$289,4))))) | D28: 27.2 | AA28: ='Tabelas'!$X$36&""
A29: DT para descobrir Fraqueza | B29: =IFERROR(INDEX('Dados'!$B$293:$B$297,MATCH($B$19,'Dados'!$A$293:$A$297,0)),"") | D29: 20.2 | G29: Pela faixa do inimigo mais forte da cena. | AA29: ='Tabelas'!$X$37&""
A30: Cone de Luz máximo | B30: =IFERROR(INDEX('Dados'!$B$380:$B$384,MATCH($B$19,'Dados'!$A$380:$A$384,0)),"") | D30: 25.1 | AA30: ='Tabelas'!$X$38&""
A31: Relíquias | B31: =IFERROR(INDEX('Dados'!$C$380:$C$384,MATCH($B$19,'Dados'!$A$380:$A$384,0)),"") | D31: 25.1 | AA31: ='Tabelas'!$X$40&""
A32: Verba de marco (Cr) | B32: =IFERROR(INDEX('Dados'!$B$372:$B$376,MATCH($B$19,'Dados'!$A$372:$A$376,0)),"") | D32: 24.5 | G32: Por marco, para o grupo. | AA32: ='Tabelas'!$X$41&""
AA33: ='Tabelas'!$X$42&""
A34: Não existe experiência por inimigo derrotado: a progressão é por marco narrativo (26.1). | AA34: ='Tabelas'!$X$43&""
AA35: ='Tabelas'!$X$44&""
A36: Marcos e progressão (26.1): o grupo sobe de nível junto, por marco narrativo | AA36: ='Tabelas'!$X$45&""
A37: Campo | B37: Valor | E37: O que a planilha usa (automático) | K37: Aviso | AA37: ='Tabelas'!$X$46&""
A38: Sessões jogadas no nível atual | E38: ="Ritmo sugerido: "&IF($B$17<='Dados'!$B$724,'Dados'!$E$724,'Dados'!$E$725)&" (26.1)." | K38: =IF(AM38>0,"O Google leu como fórmula: digite de novo com ' na frente.",IF(LEN($AD$38)=0,"",IF(NOT(ISNUMBER($AD$38)),"Sessões não é número",IF(OR($AD$38<0,$AD$38>99,INT($AD$38)<>$AD$38),"Sessões fora de 0 a 99",IF($AD$38>IF($B$17<='Dados'!$B$724,'Dados'!$D$724,'Dados'!$D$725),"Ritmo acima do sugerido (26.1): mais de "&IF($B$17<='Dados'!$B$724,'Dados'!$D$724,'Dados'!$D$725)&" sessões no nível",""))))) | AA38: ='Tabelas'!$X$47&"" | AD38: =IF(ISERROR($B$38),"",IF(ISBLANK($B$38),"",$B$38)) | AM38: =ISERROR($B$38)*1
A39: Próxima Ressonância | B39: =IF((COUNTIF('Dados'!$B$490:$B$493,"<="&$B$17)+1)>4,"Todas (nível 20)","Ressonância "&INDEX('Dados'!$A$490:$A$493,MIN(4,(COUNTIF('Dados'!$B$490:$B$493,"<="&$B$17)+1)))&" no nível "&INDEX('Dados'!$B$490:$B$493,MIN(4,(COUNTIF('Dados'!$B$490:$B$493,"<="&$B$17)+1)))) | E39: Sempre um marco de história, escolhida com o Mestre na hora (26.1, 26.7). É o lugar natural para fechar um capítulo do Propósito de Vida de alguém. | AA39: ='Tabelas'!$X$48&""
A40: Marcos concluídos | B40: =COUNTIFS('Missões'!$AK$8:$AK$28,"Concluída",'Missões'!$AD$31:$AD$51,"Sim") | E40: Missões concluídas que eram marco de nível (aba Missões). | AA40: ='Tabelas'!$X$49&""
A41: Dia de campanha efetivo | B41: =IF(ISNUMBER($AD$11),MAX(1,INT($AD$11)),1) | E41: Vazio = dia 1. A linha do tempo mostra os próximos eventos a partir deste dia. | AA41: ='Tabelas'!$X$50&""
A42: ='Dados'!$C$806 | AA42: ='Tabelas'!$X$51&""
A43: Na virada de nível entram o Tier de Relíquia, o Cone de Luz e a verba de marco (26.1): veja a entrega de marco na aba Recompensas. | AA43: ='Tabelas'!$X$52&""
AA44: ='Tabelas'!$X$54&""
A45: Facções e reputação (12 linhas): atitude com o grupo de −3 a +3 | K45: Sugestão da planilha — não é regra do livro (H17) | AA45: ='Tabelas'!$X$55&""
A46: Facção (preencha) | B46: Atitude (−3 a +3) | C46: Leitura (automático) | E46: Relógio ligado | G46: Notas | J46: Último contato (sessão) | K46: Aviso | AA46: ='Tabelas'!$X$56&""
C47: =IF(LEN($AD$47)=0,"",IF(ISNUMBER($AD$47),IFERROR(INDEX('Dados'!$B$913:$B$919,MATCH($AD$47,'Dados'!$A$913:$A$919,0)),""),"")) | K47: =IF(AM47>0,"O Google leu como fórmula: escolha de novo ou digite com ' na frente.",IF(LEN($AC$47)=0,IF(LEN($AD$47&$AG$47&$AI$47&$AL$47)>0,"Linha sem facção: preencha a facção",""),IF(COUNTIF($AC$47:$AC$58,$AC$47)>1,"Facção repetida: use uma linha por facção (H17)",IF(AND(LEN($AD$47)>0,LEN($C$47)=0),"Atitude fora de −3 a +3 (H17)","")))) | AA47: ='Tabelas'!$X$57&"" | AC47: =IF(ISERROR($A$47),"",IF(ISBLANK($A$47),"",$A$47)) | AD47: =IF(ISERROR($B$47),"",IF(ISBLANK($B$47),"",$B$47)) | AG47: =IF(ISERROR($E$47),"",IF(ISBLANK($E$47),"",$E$47)) | AI47: =IF(ISERROR($G$47),"",IF(ISBLANK($G$47),"",$G$47)) | AL47: =IF(ISERROR($J$47),"",IF(ISBLANK($J$47),"",$J$47)) | AM47: =ISERROR($A$47)*1+ISERROR($B$47)*1+ISERROR($E$47)*1+ISERROR($G$47)*1+ISERROR($J$47)*1
C48: =IF(LEN($AD$48)=0,"",IF(ISNUMBER($AD$48),IFERROR(INDEX('Dados'!$B$913:$B$919,MATCH($AD$48,'Dados'!$A$913:$A$919,0)),""),"")) | K48: =IF(AM48>0,"O Google leu como fórmula: escolha de novo ou digite com ' na frente.",IF(LEN($AC$48)=0,IF(LEN($AD$48&$AG$48&$AI$48&$AL$48)>0,"Linha sem facção: preencha a facção",""),IF(COUNTIF($AC$47:$AC$58,$AC$48)>1,"Facção repetida: use uma linha por facção (H17)",IF(AND(LEN($AD$48)>0,LEN($C$48)=0),"Atitude fora de −3 a +3 (H17)","")))) | AA48: ='Tabelas'!$X$58&"" | AC48: =IF(ISERROR($A$48),"",IF(ISBLANK($A$48),"",$A$48)) | AD48: =IF(ISERROR($B$48),"",IF(ISBLANK($B$48),"",$B$48)) | AG48: =IF(ISERROR($E$48),"",IF(ISBLANK($E$48),"",$E$48)) | AI48: =IF(ISERROR($G$48),"",IF(ISBLANK($G$48),"",$G$48)) | AL48: =IF(ISERROR($J$48),"",IF(ISBLANK($J$48),"",$J$48)) | AM48: =ISERROR($A$48)*1+ISERROR($B$48)*1+ISERROR($E$48)*1+ISERROR($G$48)*1+ISERROR($J$48)*1
C49: =IF(LEN($AD$49)=0,"",IF(ISNUMBER($AD$49),IFERROR(INDEX('Dados'!$B$913:$B$919,MATCH($AD$49,'Dados'!$A$913:$A$919,0)),""),"")) | K49: =IF(AM49>0,"O Google leu como fórmula: escolha de novo ou digite com ' na frente.",IF(LEN($AC$49)=0,IF(LEN($AD$49&$AG$49&$AI$49&$AL$49)>0,"Linha sem facção: preencha a facção",""),IF(COUNTIF($AC$47:$AC$58,$AC$49)>1,"Facção repetida: use uma linha por facção (H17)",IF(AND(LEN($AD$49)>0,LEN($C$49)=0),"Atitude fora de −3 a +3 (H17)","")))) | AA49: ='Tabelas'!$X$59&"" | AC49: =IF(ISERROR($A$49),"",IF(ISBLANK($A$49),"",$A$49)) | AD49: =IF(ISERROR($B$49),"",IF(ISBLANK($B$49),"",$B$49)) | AG49: =IF(ISERROR($E$49),"",IF(ISBLANK($E$49),"",$E$49)) | AI49: =IF(ISERROR($G$49),"",IF(ISBLANK($G$49),"",$G$49)) | AL49: =IF(ISERROR($J$49),"",IF(ISBLANK($J$49),"",$J$49)) | AM49: =ISERROR($A$49)*1+ISERROR($B$49)*1+ISERROR($E$49)*1+ISERROR($G$49)*1+ISERROR($J$49)*1
C50: =IF(LEN($AD$50)=0,"",IF(ISNUMBER($AD$50),IFERROR(INDEX('Dados'!$B$913:$B$919,MATCH($AD$50,'Dados'!$A$913:$A$919,0)),""),"")) | K50: =IF(AM50>0,"O Google leu como fórmula: escolha de novo ou digite com ' na frente.",IF(LEN($AC$50)=0,IF(LEN($AD$50&$AG$50&$AI$50&$AL$50)>0,"Linha sem facção: preencha a facção",""),IF(COUNTIF($AC$47:$AC$58,$AC$50)>1,"Facção repetida: use uma linha por facção (H17)",IF(AND(LEN($AD$50)>0,LEN($C$50)=0),"Atitude fora de −3 a +3 (H17)","")))) | AA50: ='Tabelas'!$X$60&"" | AC50: =IF(ISERROR($A$50),"",IF(ISBLANK($A$50),"",$A$50)) | AD50: =IF(ISERROR($B$50),"",IF(ISBLANK($B$50),"",$B$50)) | AG50: =IF(ISERROR($E$50),"",IF(ISBLANK($E$50),"",$E$50)) | AI50: =IF(ISERROR($G$50),"",IF(ISBLANK($G$50),"",$G$50)) | AL50: =IF(ISERROR($J$50),"",IF(ISBLANK($J$50),"",$J$50)) | AM50: =ISERROR($A$50)*1+ISERROR($B$50)*1+ISERROR($E$50)*1+ISERROR($G$50)*1+ISERROR($J$50)*1
C51: =IF(LEN($AD$51)=0,"",IF(ISNUMBER($AD$51),IFERROR(INDEX('Dados'!$B$913:$B$919,MATCH($AD$51,'Dados'!$A$913:$A$919,0)),""),"")) | K51: =IF(AM51>0,"O Google leu como fórmula: escolha de novo ou digite com ' na frente.",IF(LEN($AC$51)=0,IF(LEN($AD$51&$AG$51&$AI$51&$AL$51)>0,"Linha sem facção: preencha a facção",""),IF(COUNTIF($AC$47:$AC$58,$AC$51)>1,"Facção repetida: use uma linha por facção (H17)",IF(AND(LEN($AD$51)>0,LEN($C$51)=0),"Atitude fora de −3 a +3 (H17)","")))) | AA51: ='Tabelas'!$X$61&"" | AC51: =IF(ISERROR($A$51),"",IF(ISBLANK($A$51),"",$A$51)) | AD51: =IF(ISERROR($B$51),"",IF(ISBLANK($B$51),"",$B$51)) | AG51: =IF(ISERROR($E$51),"",IF(ISBLANK($E$51),"",$E$51)) | AI51: =IF(ISERROR($G$51),"",IF(ISBLANK($G$51),"",$G$51)) | AL51: =IF(ISERROR($J$51),"",IF(ISBLANK($J$51),"",$J$51)) | AM51: =ISERROR($A$51)*1+ISERROR($B$51)*1+ISERROR($E$51)*1+ISERROR($G$51)*1+ISERROR($J$51)*1
C52: =IF(LEN($AD$52)=0,"",IF(ISNUMBER($AD$52),IFERROR(INDEX('Dados'!$B$913:$B$919,MATCH($AD$52,'Dados'!$A$913:$A$919,0)),""),"")) | K52: =IF(AM52>0,"O Google leu como fórmula: escolha de novo ou digite com ' na frente.",IF(LEN($AC$52)=0,IF(LEN($AD$52&$AG$52&$AI$52&$AL$52)>0,"Linha sem facção: preencha a facção",""),IF(COUNTIF($AC$47:$AC$58,$AC$52)>1,"Facção repetida: use uma linha por facção (H17)",IF(AND(LEN($AD$52)>0,LEN($C$52)=0),"Atitude fora de −3 a +3 (H17)","")))) | AA52: ='Tabelas'!$X$62&"" | AC52: =IF(ISERROR($A$52),"",IF(ISBLANK($A$52),"",$A$52)) | AD52: =IF(ISERROR($B$52),"",IF(ISBLANK($B$52),"",$B$52)) | AG52: =IF(ISERROR($E$52),"",IF(ISBLANK($E$52),"",$E$52)) | AI52: =IF(ISERROR($G$52),"",IF(ISBLANK($G$52),"",$G$52)) | AL52: =IF(ISERROR($J$52),"",IF(ISBLANK($J$52),"",$J$52)) | AM52: =ISERROR($A$52)*1+ISERROR($B$52)*1+ISERROR($E$52)*1+ISERROR($G$52)*1+ISERROR($J$52)*1
C53: =IF(LEN($AD$53)=0,"",IF(ISNUMBER($AD$53),IFERROR(INDEX('Dados'!$B$913:$B$919,MATCH($AD$53,'Dados'!$A$913:$A$919,0)),""),"")) | K53: =IF(AM53>0,"O Google leu como fórmula: escolha de novo ou digite com ' na frente.",IF(LEN($AC$53)=0,IF(LEN($AD$53&$AG$53&$AI$53&$AL$53)>0,"Linha sem facção: preencha a facção",""),IF(COUNTIF($AC$47:$AC$58,$AC$53)>1,"Facção repetida: use uma linha por facção (H17)",IF(AND(LEN($AD$53)>0,LEN($C$53)=0),"Atitude fora de −3 a +3 (H17)","")))) | AA53: ='Tabelas'!$X$63&"" | AC53: =IF(ISERROR($A$53),"",IF(ISBLANK($A$53),"",$A$53)) | AD53: =IF(ISERROR($B$53),"",IF(ISBLANK($B$53),"",$B$53)) | AG53: =IF(ISERROR($E$53),"",IF(ISBLANK($E$53),"",$E$53)) | AI53: =IF(ISERROR($G$53),"",IF(ISBLANK($G$53),"",$G$53)) | AL53: =IF(ISERROR($J$53),"",IF(ISBLANK($J$53),"",$J$53)) | AM53: =ISERROR($A$53)*1+ISERROR($B$53)*1+ISERROR($E$53)*1+ISERROR($G$53)*1+ISERROR($J$53)*1
C54: =IF(LEN($AD$54)=0,"",IF(ISNUMBER($AD$54),IFERROR(INDEX('Dados'!$B$913:$B$919,MATCH($AD$54,'Dados'!$A$913:$A$919,0)),""),"")) | K54: =IF(AM54>0,"O Google leu como fórmula: escolha de novo ou digite com ' na frente.",IF(LEN($AC$54)=0,IF(LEN($AD$54&$AG$54&$AI$54&$AL$54)>0,"Linha sem facção: preencha a facção",""),IF(COUNTIF($AC$47:$AC$58,$AC$54)>1,"Facção repetida: use uma linha por facção (H17)",IF(AND(LEN($AD$54)>0,LEN($C$54)=0),"Atitude fora de −3 a +3 (H17)","")))) | AA54: ='Tabelas'!$X$64&"" | AC54: =IF(ISERROR($A$54),"",IF(ISBLANK($A$54),"",$A$54)) | AD54: =IF(ISERROR($B$54),"",IF(ISBLANK($B$54),"",$B$54)) | AG54: =IF(ISERROR($E$54),"",IF(ISBLANK($E$54),"",$E$54)) | AI54: =IF(ISERROR($G$54),"",IF(ISBLANK($G$54),"",$G$54)) | AL54: =IF(ISERROR($J$54),"",IF(ISBLANK($J$54),"",$J$54)) | AM54: =ISERROR($A$54)*1+ISERROR($B$54)*1+ISERROR($E$54)*1+ISERROR($G$54)*1+ISERROR($J$54)*1
C55: =IF(LEN($AD$55)=0,"",IF(ISNUMBER($AD$55),IFERROR(INDEX('Dados'!$B$913:$B$919,MATCH($AD$55,'Dados'!$A$913:$A$919,0)),""),"")) | K55: =IF(AM55>0,"O Google leu como fórmula: escolha de novo ou digite com ' na frente.",IF(LEN($AC$55)=0,IF(LEN($AD$55&$AG$55&$AI$55&$AL$55)>0,"Linha sem facção: preencha a facção",""),IF(COUNTIF($AC$47:$AC$58,$AC$55)>1,"Facção repetida: use uma linha por facção (H17)",IF(AND(LEN($AD$55)>0,LEN($C$55)=0),"Atitude fora de −3 a +3 (H17)","")))) | AA55: ='Tabelas'!$X$65&"" | AC55: =IF(ISERROR($A$55),"",IF(ISBLANK($A$55),"",$A$55)) | AD55: =IF(ISERROR($B$55),"",IF(ISBLANK($B$55),"",$B$55)) | AG55: =IF(ISERROR($E$55),"",IF(ISBLANK($E$55),"",$E$55)) | AI55: =IF(ISERROR($G$55),"",IF(ISBLANK($G$55),"",$G$55)) | AL55: =IF(ISERROR($J$55),"",IF(ISBLANK($J$55),"",$J$55)) | AM55: =ISERROR($A$55)*1+ISERROR($B$55)*1+ISERROR($E$55)*1+ISERROR($G$55)*1+ISERROR($J$55)*1
C56: =IF(LEN($AD$56)=0,"",IF(ISNUMBER($AD$56),IFERROR(INDEX('Dados'!$B$913:$B$919,MATCH($AD$56,'Dados'!$A$913:$A$919,0)),""),"")) | K56: =IF(AM56>0,"O Google leu como fórmula: escolha de novo ou digite com ' na frente.",IF(LEN($AC$56)=0,IF(LEN($AD$56&$AG$56&$AI$56&$AL$56)>0,"Linha sem facção: preencha a facção",""),IF(COUNTIF($AC$47:$AC$58,$AC$56)>1,"Facção repetida: use uma linha por facção (H17)",IF(AND(LEN($AD$56)>0,LEN($C$56)=0),"Atitude fora de −3 a +3 (H17)","")))) | AA56: ='Tabelas'!$X$66&"" | AC56: =IF(ISERROR($A$56),"",IF(ISBLANK($A$56),"",$A$56)) | AD56: =IF(ISERROR($B$56),"",IF(ISBLANK($B$56),"",$B$56)) | AG56: =IF(ISERROR($E$56),"",IF(ISBLANK($E$56),"",$E$56)) | AI56: =IF(ISERROR($G$56),"",IF(ISBLANK($G$56),"",$G$56)) | AL56: =IF(ISERROR($J$56),"",IF(ISBLANK($J$56),"",$J$56)) | AM56: =ISERROR($A$56)*1+ISERROR($B$56)*1+ISERROR($E$56)*1+ISERROR($G$56)*1+ISERROR($J$56)*1
C57: =IF(LEN($AD$57)=0,"",IF(ISNUMBER($AD$57),IFERROR(INDEX('Dados'!$B$913:$B$919,MATCH($AD$57,'Dados'!$A$913:$A$919,0)),""),"")) | K57: =IF(AM57>0,"O Google leu como fórmula: escolha de novo ou digite com ' na frente.",IF(LEN($AC$57)=0,IF(LEN($AD$57&$AG$57&$AI$57&$AL$57)>0,"Linha sem facção: preencha a facção",""),IF(COUNTIF($AC$47:$AC$58,$AC$57)>1,"Facção repetida: use uma linha por facção (H17)",IF(AND(LEN($AD$57)>0,LEN($C$57)=0),"Atitude fora de −3 a +3 (H17)","")))) | AA57: ='Tabelas'!$X$68&"" | AC57: =IF(ISERROR($A$57),"",IF(ISBLANK($A$57),"",$A$57)) | AD57: =IF(ISERROR($B$57),"",IF(ISBLANK($B$57),"",$B$57)) | AG57: =IF(ISERROR($E$57),"",IF(ISBLANK($E$57),"",$E$57)) | AI57: =IF(ISERROR($G$57),"",IF(ISBLANK($G$57),"",$G$57)) | AL57: =IF(ISERROR($J$57),"",IF(ISBLANK($J$57),"",$J$57)) | AM57: =ISERROR($A$57)*1+ISERROR($B$57)*1+ISERROR($E$57)*1+ISERROR($G$57)*1+ISERROR($J$57)*1
C58: =IF(LEN($AD$58)=0,"",IF(ISNUMBER($AD$58),IFERROR(INDEX('Dados'!$B$913:$B$919,MATCH($AD$58,'Dados'!$A$913:$A$919,0)),""),"")) | K58: =IF(AM58>0,"O Google leu como fórmula: escolha de novo ou digite com ' na frente.",IF(LEN($AC$58)=0,IF(LEN($AD$58&$AG$58&$AI$58&$AL$58)>0,"Linha sem facção: preencha a facção",""),IF(COUNTIF($AC$47:$AC$58,$AC$58)>1,"Facção repetida: use uma linha por facção (H17)",IF(AND(LEN($AD$58)>0,LEN($C$58)=0),"Atitude fora de −3 a +3 (H17)","")))) | AA58: ='Tabelas'!$X$69&"" | AC58: =IF(ISERROR($A$58),"",IF(ISBLANK($A$58),"",$A$58)) | AD58: =IF(ISERROR($B$58),"",IF(ISBLANK($B$58),"",$B$58)) | AG58: =IF(ISERROR($E$58),"",IF(ISBLANK($E$58),"",$E$58)) | AI58: =IF(ISERROR($G$58),"",IF(ISBLANK($G$58),"",$G$58)) | AL58: =IF(ISERROR($J$58),"",IF(ISBLANK($J$58),"",$J$58)) | AM58: =ISERROR($A$58)*1+ISERROR($B$58)*1+ISERROR($E$58)*1+ISERROR($G$58)*1+ISERROR($J$58)*1
AA59: ='Tabelas'!$X$70&""
A60: Relógios de progresso (10 linhas): 4, 6, 8, 10 ou 12 segmentos | K60: Sugestão da planilha — não é regra do livro (H16) | AA60: ='Tabelas'!$X$71&""
A61: Relógio (preencha) | B61: Segmentos | C61: Preenchidos | D61: Barra (automático) | G61: Situação (automático) | I61: O que acontece ao encher | K61: Aviso | AA61: ='Tabelas'!$X$72&""
D62: =IF($P$62=1,REPT("●",$O$62)&REPT("○",$AD$62-$O$62)&" "&$O$62&"/"&$AD$62,"") | G62: =IF($P$62=1,IF($O$62=$AD$62,"Cheio — aconteceu",IF($O$62=$AD$62-1,"Falta 1","")),"") | K62: =IF(AM62>0,"O Google leu como fórmula: escolha de novo ou digite com ' na frente.",IF(LEN($AC$62&$AD$62&$AE$62)=0,"",IF($N$62=0,IF(LEN($AD$62)=0,"Escolha os segmentos: 4, 6, 8, 10 ou 12 (H16)","Segmentos fora de 4, 6, 8, 10 ou 12 (H16)"),IF(NOT(ISNUMBER($O$62)),"Preenchidos não é número (H16)",IF(OR($O$62<0,INT($O$62)<>$O$62),"Preenchidos fora de 0 a "&$AD$62&" (H16)",IF($O$62>$AD$62,"Preenchidos acima dos segmentos: confira (H16)","")))))) | N62: =IF(ISNUMBER($AD$62),IF(OR($AD$62=4,$AD$62=6,$AD$62=8,$AD$62=10,$AD$62=12),1,0),0) | O62: =IF(LEN($AE$62)=0,0,$AE$62) | P62: =IF($N$62=1,IF(ISNUMBER($O$62),IF(AND($O$62>=0,INT($O$62)=$O$62,$O$62<=$AD$62),1,0),0),0) | AA62: ='Tabelas'!$X$73&"" | AC62: =IF(ISERROR($A$62),"",IF(ISBLANK($A$62),"",$A$62)) | AD62: =IF(ISERROR($B$62),"",IF(ISBLANK($B$62),"",$B$62)) | AE62: =IF(ISERROR($C$62),"",IF(ISBLANK($C$62),"",$C$62)) | AM62: =ISERROR($A$62)*1+ISERROR($B$62)*1+ISERROR($C$62)*1+ISERROR($I$62)*1
D63: =IF($P$63=1,REPT("●",$O$63)&REPT("○",$AD$63-$O$63)&" "&$O$63&"/"&$AD$63,"") | G63: =IF($P$63=1,IF($O$63=$AD$63,"Cheio — aconteceu",IF($O$63=$AD$63-1,"Falta 1","")),"") | K63: =IF(AM63>0,"O Google leu como fórmula: escolha de novo ou digite com ' na frente.",IF(LEN($AC$63&$AD$63&$AE$63)=0,"",IF($N$63=0,IF(LEN($AD$63)=0,"Escolha os segmentos: 4, 6, 8, 10 ou 12 (H16)","Segmentos fora de 4, 6, 8, 10 ou 12 (H16)"),IF(NOT(ISNUMBER($O$63)),"Preenchidos não é número (H16)",IF(OR($O$63<0,INT($O$63)<>$O$63),"Preenchidos fora de 0 a "&$AD$63&" (H16)",IF($O$63>$AD$63,"Preenchidos acima dos segmentos: confira (H16)","")))))) | N63: =IF(ISNUMBER($AD$63),IF(OR($AD$63=4,$AD$63=6,$AD$63=8,$AD$63=10,$AD$63=12),1,0),0) | O63: =IF(LEN($AE$63)=0,0,$AE$63) | P63: =IF($N$63=1,IF(ISNUMBER($O$63),IF(AND($O$63>=0,INT($O$63)=$O$63,$O$63<=$AD$63),1,0),0),0) | AA63: ='Tabelas'!$X$74&"" | AC63: =IF(ISERROR($A$63),"",IF(ISBLANK($A$63),"",$A$63)) | AD63: =IF(ISERROR($B$63),"",IF(ISBLANK($B$63),"",$B$63)) | AE63: =IF(ISERROR($C$63),"",IF(ISBLANK($C$63),"",$C$63)) | AM63: =ISERROR($A$63)*1+ISERROR($B$63)*1+ISERROR($C$63)*1+ISERROR($I$63)*1
D64: =IF($P$64=1,REPT("●",$O$64)&REPT("○",$AD$64-$O$64)&" "&$O$64&"/"&$AD$64,"") | G64: =IF($P$64=1,IF($O$64=$AD$64,"Cheio — aconteceu",IF($O$64=$AD$64-1,"Falta 1","")),"") | K64: =IF(AM64>0,"O Google leu como fórmula: escolha de novo ou digite com ' na frente.",IF(LEN($AC$64&$AD$64&$AE$64)=0,"",IF($N$64=0,IF(LEN($AD$64)=0,"Escolha os segmentos: 4, 6, 8, 10 ou 12 (H16)","Segmentos fora de 4, 6, 8, 10 ou 12 (H16)"),IF(NOT(ISNUMBER($O$64)),"Preenchidos não é número (H16)",IF(OR($O$64<0,INT($O$64)<>$O$64),"Preenchidos fora de 0 a "&$AD$64&" (H16)",IF($O$64>$AD$64,"Preenchidos acima dos segmentos: confira (H16)","")))))) | N64: =IF(ISNUMBER($AD$64),IF(OR($AD$64=4,$AD$64=6,$AD$64=8,$AD$64=10,$AD$64=12),1,0),0) | O64: =IF(LEN($AE$64)=0,0,$AE$64) | P64: =IF($N$64=1,IF(ISNUMBER($O$64),IF(AND($O$64>=0,INT($O$64)=$O$64,$O$64<=$AD$64),1,0),0),0) | AA64: ='Tabelas'!$X$75&"" | AC64: =IF(ISERROR($A$64),"",IF(ISBLANK($A$64),"",$A$64)) | AD64: =IF(ISERROR($B$64),"",IF(ISBLANK($B$64),"",$B$64)) | AE64: =IF(ISERROR($C$64),"",IF(ISBLANK($C$64),"",$C$64)) | AM64: =ISERROR($A$64)*1+ISERROR($B$64)*1+ISERROR($C$64)*1+ISERROR($I$64)*1
D65: =IF($P$65=1,REPT("●",$O$65)&REPT("○",$AD$65-$O$65)&" "&$O$65&"/"&$AD$65,"") | G65: =IF($P$65=1,IF($O$65=$AD$65,"Cheio — aconteceu",IF($O$65=$AD$65-1,"Falta 1","")),"") | K65: =IF(AM65>0,"O Google leu como fórmula: escolha de novo ou digite com ' na frente.",IF(LEN($AC$65&$AD$65&$AE$65)=0,"",IF($N$65=0,IF(LEN($AD$65)=0,"Escolha os segmentos: 4, 6, 8, 10 ou 12 (H16)","Segmentos fora de 4, 6, 8, 10 ou 12 (H16)"),IF(NOT(ISNUMBER($O$65)),"Preenchidos não é número (H16)",IF(OR($O$65<0,INT($O$65)<>$O$65),"Preenchidos fora de 0 a "&$AD$65&" (H16)",IF($O$65>$AD$65,"Preenchidos acima dos segmentos: confira (H16)","")))))) | N65: =IF(ISNUMBER($AD$65),IF(OR($AD$65=4,$AD$65=6,$AD$65=8,$AD$65=10,$AD$65=12),1,0),0) | O65: =IF(LEN($AE$65)=0,0,$AE$65) | P65: =IF($N$65=1,IF(ISNUMBER($O$65),IF(AND($O$65>=0,INT($O$65)=$O$65,$O$65<=$AD$65),1,0),0),0) | AA65: ='Tabelas'!$X$76&"" | AC65: =IF(ISERROR($A$65),"",IF(ISBLANK($A$65),"",$A$65)) | AD65: =IF(ISERROR($B$65),"",IF(ISBLANK($B$65),"",$B$65)) | AE65: =IF(ISERROR($C$65),"",IF(ISBLANK($C$65),"",$C$65)) | AM65: =ISERROR($A$65)*1+ISERROR($B$65)*1+ISERROR($C$65)*1+ISERROR($I$65)*1
D66: =IF($P$66=1,REPT("●",$O$66)&REPT("○",$AD$66-$O$66)&" "&$O$66&"/"&$AD$66,"") | G66: =IF($P$66=1,IF($O$66=$AD$66,"Cheio — aconteceu",IF($O$66=$AD$66-1,"Falta 1","")),"") | K66: =IF(AM66>0,"O Google leu como fórmula: escolha de novo ou digite com ' na frente.",IF(LEN($AC$66&$AD$66&$AE$66)=0,"",IF($N$66=0,IF(LEN($AD$66)=0,"Escolha os segmentos: 4, 6, 8, 10 ou 12 (H16)","Segmentos fora de 4, 6, 8, 10 ou 12 (H16)"),IF(NOT(ISNUMBER($O$66)),"Preenchidos não é número (H16)",IF(OR($O$66<0,INT($O$66)<>$O$66),"Preenchidos fora de 0 a "&$AD$66&" (H16)",IF($O$66>$AD$66,"Preenchidos acima dos segmentos: confira (H16)","")))))) | N66: =IF(ISNUMBER($AD$66),IF(OR($AD$66=4,$AD$66=6,$AD$66=8,$AD$66=10,$AD$66=12),1,0),0) | O66: =IF(LEN($AE$66)=0,0,$AE$66) | P66: =IF($N$66=1,IF(ISNUMBER($O$66),IF(AND($O$66>=0,INT($O$66)=$O$66,$O$66<=$AD$66),1,0),0),0) | AA66: ='Tabelas'!$X$77&"" | AC66: =IF(ISERROR($A$66),"",IF(ISBLANK($A$66),"",$A$66)) | AD66: =IF(ISERROR($B$66),"",IF(ISBLANK($B$66),"",$B$66)) | AE66: =IF(ISERROR($C$66),"",IF(ISBLANK($C$66),"",$C$66)) | AM66: =ISERROR($A$66)*1+ISERROR($B$66)*1+ISERROR($C$66)*1+ISERROR($I$66)*1
D67: =IF($P$67=1,REPT("●",$O$67)&REPT("○",$AD$67-$O$67)&" "&$O$67&"/"&$AD$67,"") | G67: =IF($P$67=1,IF($O$67=$AD$67,"Cheio — aconteceu",IF($O$67=$AD$67-1,"Falta 1","")),"") | K67: =IF(AM67>0,"O Google leu como fórmula: escolha de novo ou digite com ' na frente.",IF(LEN($AC$67&$AD$67&$AE$67)=0,"",IF($N$67=0,IF(LEN($AD$67)=0,"Escolha os segmentos: 4, 6, 8, 10 ou 12 (H16)","Segmentos fora de 4, 6, 8, 10 ou 12 (H16)"),IF(NOT(ISNUMBER($O$67)),"Preenchidos não é número (H16)",IF(OR($O$67<0,INT($O$67)<>$O$67),"Preenchidos fora de 0 a "&$AD$67&" (H16)",IF($O$67>$AD$67,"Preenchidos acima dos segmentos: confira (H16)","")))))) | N67: =IF(ISNUMBER($AD$67),IF(OR($AD$67=4,$AD$67=6,$AD$67=8,$AD$67=10,$AD$67=12),1,0),0) | O67: =IF(LEN($AE$67)=0,0,$AE$67) | P67: =IF($N$67=1,IF(ISNUMBER($O$67),IF(AND($O$67>=0,INT($O$67)=$O$67,$O$67<=$AD$67),1,0),0),0) | AA67: ='Tabelas'!$X$78&"" | AC67: =IF(ISERROR($A$67),"",IF(ISBLANK($A$67),"",$A$67)) | AD67: =IF(ISERROR($B$67),"",IF(ISBLANK($B$67),"",$B$67)) | AE67: =IF(ISERROR($C$67),"",IF(ISBLANK($C$67),"",$C$67)) | AM67: =ISERROR($A$67)*1+ISERROR($B$67)*1+ISERROR($C$67)*1+ISERROR($I$67)*1
D68: =IF($P$68=1,REPT("●",$O$68)&REPT("○",$AD$68-$O$68)&" "&$O$68&"/"&$AD$68,"") | G68: =IF($P$68=1,IF($O$68=$AD$68,"Cheio — aconteceu",IF($O$68=$AD$68-1,"Falta 1","")),"") | K68: =IF(AM68>0,"O Google leu como fórmula: escolha de novo ou digite com ' na frente.",IF(LEN($AC$68&$AD$68&$AE$68)=0,"",IF($N$68=0,IF(LEN($AD$68)=0,"Escolha os segmentos: 4, 6, 8, 10 ou 12 (H16)","Segmentos fora de 4, 6, 8, 10 ou 12 (H16)"),IF(NOT(ISNUMBER($O$68)),"Preenchidos não é número (H16)",IF(OR($O$68<0,INT($O$68)<>$O$68),"Preenchidos fora de 0 a "&$AD$68&" (H16)",IF($O$68>$AD$68,"Preenchidos acima dos segmentos: confira (H16)","")))))) | N68: =IF(ISNUMBER($AD$68),IF(OR($AD$68=4,$AD$68=6,$AD$68=8,$AD$68=10,$AD$68=12),1,0),0) | O68: =IF(LEN($AE$68)=0,0,$AE$68) | P68: =IF($N$68=1,IF(ISNUMBER($O$68),IF(AND($O$68>=0,INT($O$68)=$O$68,$O$68<=$AD$68),1,0),0),0) | AA68: ='Tabelas'!$X$79&"" | AC68: =IF(ISERROR($A$68),"",IF(ISBLANK($A$68),"",$A$68)) | AD68: =IF(ISERROR($B$68),"",IF(ISBLANK($B$68),"",$B$68)) | AE68: =IF(ISERROR($C$68),"",IF(ISBLANK($C$68),"",$C$68)) | AM68: =ISERROR($A$68)*1+ISERROR($B$68)*1+ISERROR($C$68)*1+ISERROR($I$68)*1
D69: =IF($P$69=1,REPT("●",$O$69)&REPT("○",$AD$69-$O$69)&" "&$O$69&"/"&$AD$69,"") | G69: =IF($P$69=1,IF($O$69=$AD$69,"Cheio — aconteceu",IF($O$69=$AD$69-1,"Falta 1","")),"") | K69: =IF(AM69>0,"O Google leu como fórmula: escolha de novo ou digite com ' na frente.",IF(LEN($AC$69&$AD$69&$AE$69)=0,"",IF($N$69=0,IF(LEN($AD$69)=0,"Escolha os segmentos: 4, 6, 8, 10 ou 12 (H16)","Segmentos fora de 4, 6, 8, 10 ou 12 (H16)"),IF(NOT(ISNUMBER($O$69)),"Preenchidos não é número (H16)",IF(OR($O$69<0,INT($O$69)<>$O$69),"Preenchidos fora de 0 a "&$AD$69&" (H16)",IF($O$69>$AD$69,"Preenchidos acima dos segmentos: confira (H16)","")))))) | N69: =IF(ISNUMBER($AD$69),IF(OR($AD$69=4,$AD$69=6,$AD$69=8,$AD$69=10,$AD$69=12),1,0),0) | O69: =IF(LEN($AE$69)=0,0,$AE$69) | P69: =IF($N$69=1,IF(ISNUMBER($O$69),IF(AND($O$69>=0,INT($O$69)=$O$69,$O$69<=$AD$69),1,0),0),0) | AA69: ='Tabelas'!$X$80&"" | AC69: =IF(ISERROR($A$69),"",IF(ISBLANK($A$69),"",$A$69)) | AD69: =IF(ISERROR($B$69),"",IF(ISBLANK($B$69),"",$B$69)) | AE69: =IF(ISERROR($C$69),"",IF(ISBLANK($C$69),"",$C$69)) | AM69: =ISERROR($A$69)*1+ISERROR($B$69)*1+ISERROR($C$69)*1+ISERROR($I$69)*1
D70: =IF($P$70=1,REPT("●",$O$70)&REPT("○",$AD$70-$O$70)&" "&$O$70&"/"&$AD$70,"") | G70: =IF($P$70=1,IF($O$70=$AD$70,"Cheio — aconteceu",IF($O$70=$AD$70-1,"Falta 1","")),"") | K70: =IF(AM70>0,"O Google leu como fórmula: escolha de novo ou digite com ' na frente.",IF(LEN($AC$70&$AD$70&$AE$70)=0,"",IF($N$70=0,IF(LEN($AD$70)=0,"Escolha os segmentos: 4, 6, 8, 10 ou 12 (H16)","Segmentos fora de 4, 6, 8, 10 ou 12 (H16)"),IF(NOT(ISNUMBER($O$70)),"Preenchidos não é número (H16)",IF(OR($O$70<0,INT($O$70)<>$O$70),"Preenchidos fora de 0 a "&$AD$70&" (H16)",IF($O$70>$AD$70,"Preenchidos acima dos segmentos: confira (H16)","")))))) | N70: =IF(ISNUMBER($AD$70),IF(OR($AD$70=4,$AD$70=6,$AD$70=8,$AD$70=10,$AD$70=12),1,0),0) | O70: =IF(LEN($AE$70)=0,0,$AE$70) | P70: =IF($N$70=1,IF(ISNUMBER($O$70),IF(AND($O$70>=0,INT($O$70)=$O$70,$O$70<=$AD$70),1,0),0),0) | AA70: ='Tabelas'!$X$82&"" | AC70: =IF(ISERROR($A$70),"",IF(ISBLANK($A$70),"",$A$70)) | AD70: =IF(ISERROR($B$70),"",IF(ISBLANK($B$70),"",$B$70)) | AE70: =IF(ISERROR($C$70),"",IF(ISBLANK($C$70),"",$C$70)) | AM70: =ISERROR($A$70)*1+ISERROR($B$70)*1+ISERROR($C$70)*1+ISERROR($I$70)*1
D71: =IF($P$71=1,REPT("●",$O$71)&REPT("○",$AD$71-$O$71)&" "&$O$71&"/"&$AD$71,"") | G71: =IF($P$71=1,IF($O$71=$AD$71,"Cheio — aconteceu",IF($O$71=$AD$71-1,"Falta 1","")),"") | K71: =IF(AM71>0,"O Google leu como fórmula: escolha de novo ou digite com ' na frente.",IF(LEN($AC$71&$AD$71&$AE$71)=0,"",IF($N$71=0,IF(LEN($AD$71)=0,"Escolha os segmentos: 4, 6, 8, 10 ou 12 (H16)","Segmentos fora de 4, 6, 8, 10 ou 12 (H16)"),IF(NOT(ISNUMBER($O$71)),"Preenchidos não é número (H16)",IF(OR($O$71<0,INT($O$71)<>$O$71),"Preenchidos fora de 0 a "&$AD$71&" (H16)",IF($O$71>$AD$71,"Preenchidos acima dos segmentos: confira (H16)","")))))) | N71: =IF(ISNUMBER($AD$71),IF(OR($AD$71=4,$AD$71=6,$AD$71=8,$AD$71=10,$AD$71=12),1,0),0) | O71: =IF(LEN($AE$71)=0,0,$AE$71) | P71: =IF($N$71=1,IF(ISNUMBER($O$71),IF(AND($O$71>=0,INT($O$71)=$O$71,$O$71<=$AD$71),1,0),0),0) | AA71: ='Tabelas'!$X$83&"" | AC71: =IF(ISERROR($A$71),"",IF(ISBLANK($A$71),"",$A$71)) | AD71: =IF(ISERROR($B$71),"",IF(ISBLANK($B$71),"",$B$71)) | AE71: =IF(ISERROR($C$71),"",IF(ISBLANK($C$71),"",$C$71)) | AM71: =ISERROR($A$71)*1+ISERROR($B$71)*1+ISERROR($C$71)*1+ISERROR($I$71)*1
A72: ="Relógios a 1 segmento de encher: "&COUNTIF($G$62:$G$71,"Falta 1")&" · cheios: "&COUNTIF($G$62:$G$71,"Cheio — aconteceu")&". O livro pede relógio na ficção para o Descanso Longo (27.7): a nave parte ao amanhecer, o lacre não aguenta mais um dia." | AA72: ='Tabelas'!$X$84&""
AA73: ='Tabelas'!$X$85&""
A74: Linha do tempo (30 eventos): a ordem e os próximos eventos são automáticos | AA74: ='Tabelas'!$X$86&""
A75: Dia de campanha (preencha) | B75: Nº na ordem (automático) | C75: Sessão | D75: Evento | G75: Quem (facção ou NPC) | H75: Consequência | J75: Público? | K75: Aviso | AA75: ='Tabelas'!$X$87&""
B76: =IF(ISNUMBER($Q$76),COUNTIF($Q$76:$Q$107,"<"&$Q$76)+1,"") | K76: =IF(AM76>0,"O Google leu como fórmula: escolha de novo ou digite com ' na frente.",IF(LEN($AC$76)=0,IF(LEN($AF$76&$AI$76&$AJ$76&$AE$76)>0,"Sem dia: o evento fica fora da ordem",""),IF(ISNUMBER($Q$76),"","Dia fora de 1 a 9.999 (inteiro)"))) | Q76: =IF(ISNUMBER($AC$76),IF(AND($AC$76>=1,$AC$76<=9999,INT($AC$76)=$AC$76),$AC$76+1/100,""),"") | R76: =IF(ISNUMBER($Q$76),IF(INT($Q$76)>=$B$41,$Q$76,""),"") | AA76: ='Tabelas'!$X$88&"" | AC76: =IF(ISERROR($A$76),"",IF(ISBLANK($A$76),"",$A$76)) | AE76: =IF(ISERROR($C$76),"",IF(ISBLANK($C$76),"",$C$76)) | AF76: =IF(ISERROR($D$76),"",IF(ISBLANK($D$76),"",$D$76)) | AI76: =IF(ISERROR($G$76),"",IF(ISBLANK($G$76),"",$G$76)) | AJ76: =IF(ISERROR($H$76),"",IF(ISBLANK($H$76),"",$H$76)) | AL76: =IF(ISERROR($J$76),"",IF(ISBLANK($J$76),"",$J$76)) | AM76: =ISERROR($A$76)*1+ISERROR($C$76)*1+ISERROR($D$76)*1+ISERROR($G$76)*1+ISERROR($H$76)*1+ISERROR($J$76)*1
B77: =IF(ISNUMBER($Q$77),COUNTIF($Q$76:$Q$107,"<"&$Q$77)+1,"") | K77: =IF(AM77>0,"O Google leu como fórmula: escolha de novo ou digite com ' na frente.",IF(LEN($AC$77)=0,IF(LEN($AF$77&$AI$77&$AJ$77&$AE$77)>0,"Sem dia: o evento fica fora da ordem",""),IF(ISNUMBER($Q$77),"","Dia fora de 1 a 9.999 (inteiro)"))) | Q77: =IF(ISNUMBER($AC$77),IF(AND($AC$77>=1,$AC$77<=9999,INT($AC$77)=$AC$77),$AC$77+2/100,""),"") | R77: =IF(ISNUMBER($Q$77),IF(INT($Q$77)>=$B$41,$Q$77,""),"") | AA77: ='Tabelas'!$X$89&"" | AC77: =IF(ISERROR($A$77),"",IF(ISBLANK($A$77),"",$A$77)) | AE77: =IF(ISERROR($C$77),"",IF(ISBLANK($C$77),"",$C$77)) | AF77: =IF(ISERROR($D$77),"",IF(ISBLANK($D$77),"",$D$77)) | AI77: =IF(ISERROR($G$77),"",IF(ISBLANK($G$77),"",$G$77)) | AJ77: =IF(ISERROR($H$77),"",IF(ISBLANK($H$77),"",$H$77)) | AL77: =IF(ISERROR($J$77),"",IF(ISBLANK($J$77),"",$J$77)) | AM77: =ISERROR($A$77)*1+ISERROR($C$77)*1+ISERROR($D$77)*1+ISERROR($G$77)*1+ISERROR($H$77)*1+ISERROR($J$77)*1
B78: =IF(ISNUMBER($Q$78),COUNTIF($Q$76:$Q$107,"<"&$Q$78)+1,"") | K78: =IF(AM78>0,"O Google leu como fórmula: escolha de novo ou digite com ' na frente.",IF(LEN($AC$78)=0,IF(LEN($AF$78&$AI$78&$AJ$78&$AE$78)>0,"Sem dia: o evento fica fora da ordem",""),IF(ISNUMBER($Q$78),"","Dia fora de 1 a 9.999 (inteiro)"))) | Q78: =IF(ISNUMBER($AC$78),IF(AND($AC$78>=1,$AC$78<=9999,INT($AC$78)=$AC$78),$AC$78+3/100,""),"") | R78: =IF(ISNUMBER($Q$78),IF(INT($Q$78)>=$B$41,$Q$78,""),"") | AA78: ='Tabelas'!$X$90&"" | AC78: =IF(ISERROR($A$78),"",IF(ISBLANK($A$78),"",$A$78)) | AE78: =IF(ISERROR($C$78),"",IF(ISBLANK($C$78),"",$C$78)) | AF78: =IF(ISERROR($D$78),"",IF(ISBLANK($D$78),"",$D$78)) | AI78: =IF(ISERROR($G$78),"",IF(ISBLANK($G$78),"",$G$78)) | AJ78: =IF(ISERROR($H$78),"",IF(ISBLANK($H$78),"",$H$78)) | AL78: =IF(ISERROR($J$78),"",IF(ISBLANK($J$78),"",$J$78)) | AM78: =ISERROR($A$78)*1+ISERROR($C$78)*1+ISERROR($D$78)*1+ISERROR($G$78)*1+ISERROR($H$78)*1+ISERROR($J$78)*1
B79: =IF(ISNUMBER($Q$79),COUNTIF($Q$76:$Q$107,"<"&$Q$79)+1,"") | K79: =IF(AM79>0,"O Google leu como fórmula: escolha de novo ou digite com ' na frente.",IF(LEN($AC$79)=0,IF(LEN($AF$79&$AI$79&$AJ$79&$AE$79)>0,"Sem dia: o evento fica fora da ordem",""),IF(ISNUMBER($Q$79),"","Dia fora de 1 a 9.999 (inteiro)"))) | Q79: =IF(ISNUMBER($AC$79),IF(AND($AC$79>=1,$AC$79<=9999,INT($AC$79)=$AC$79),$AC$79+4/100,""),"") | R79: =IF(ISNUMBER($Q$79),IF(INT($Q$79)>=$B$41,$Q$79,""),"") | AA79: ='Tabelas'!$X$91&"" | AC79: =IF(ISERROR($A$79),"",IF(ISBLANK($A$79),"",$A$79)) | AE79: =IF(ISERROR($C$79),"",IF(ISBLANK($C$79),"",$C$79)) | AF79: =IF(ISERROR($D$79),"",IF(ISBLANK($D$79),"",$D$79)) | AI79: =IF(ISERROR($G$79),"",IF(ISBLANK($G$79),"",$G$79)) | AJ79: =IF(ISERROR($H$79),"",IF(ISBLANK($H$79),"",$H$79)) | AL79: =IF(ISERROR($J$79),"",IF(ISBLANK($J$79),"",$J$79)) | AM79: =ISERROR($A$79)*1+ISERROR($C$79)*1+ISERROR($D$79)*1+ISERROR($G$79)*1+ISERROR($H$79)*1+ISERROR($J$79)*1
B80: =IF(ISNUMBER($Q$80),COUNTIF($Q$76:$Q$107,"<"&$Q$80)+1,"") | K80: =IF(AM80>0,"O Google leu como fórmula: escolha de novo ou digite com ' na frente.",IF(LEN($AC$80)=0,IF(LEN($AF$80&$AI$80&$AJ$80&$AE$80)>0,"Sem dia: o evento fica fora da ordem",""),IF(ISNUMBER($Q$80),"","Dia fora de 1 a 9.999 (inteiro)"))) | Q80: =IF(ISNUMBER($AC$80),IF(AND($AC$80>=1,$AC$80<=9999,INT($AC$80)=$AC$80),$AC$80+5/100,""),"") | R80: =IF(ISNUMBER($Q$80),IF(INT($Q$80)>=$B$41,$Q$80,""),"") | AA80: ='Tabelas'!$X$92&"" | AC80: =IF(ISERROR($A$80),"",IF(ISBLANK($A$80),"",$A$80)) | AE80: =IF(ISERROR($C$80),"",IF(ISBLANK($C$80),"",$C$80)) | AF80: =IF(ISERROR($D$80),"",IF(ISBLANK($D$80),"",$D$80)) | AI80: =IF(ISERROR($G$80),"",IF(ISBLANK($G$80),"",$G$80)) | AJ80: =IF(ISERROR($H$80),"",IF(ISBLANK($H$80),"",$H$80)) | AL80: =IF(ISERROR($J$80),"",IF(ISBLANK($J$80),"",$J$80)) | AM80: =ISERROR($A$80)*1+ISERROR($C$80)*1+ISERROR($D$80)*1+ISERROR($G$80)*1+ISERROR($H$80)*1+ISERROR($J$80)*1
B81: =IF(ISNUMBER($Q$81),COUNTIF($Q$76:$Q$107,"<"&$Q$81)+1,"") | K81: =IF(AM81>0,"O Google leu como fórmula: escolha de novo ou digite com ' na frente.",IF(LEN($AC$81)=0,IF(LEN($AF$81&$AI$81&$AJ$81&$AE$81)>0,"Sem dia: o evento fica fora da ordem",""),IF(ISNUMBER($Q$81),"","Dia fora de 1 a 9.999 (inteiro)"))) | Q81: =IF(ISNUMBER($AC$81),IF(AND($AC$81>=1,$AC$81<=9999,INT($AC$81)=$AC$81),$AC$81+6/100,""),"") | R81: =IF(ISNUMBER($Q$81),IF(INT($Q$81)>=$B$41,$Q$81,""),"") | AA81: ='Tabelas'!$X$93&"" | AC81: =IF(ISERROR($A$81),"",IF(ISBLANK($A$81),"",$A$81)) | AE81: =IF(ISERROR($C$81),"",IF(ISBLANK($C$81),"",$C$81)) | AF81: =IF(ISERROR($D$81),"",IF(ISBLANK($D$81),"",$D$81)) | AI81: =IF(ISERROR($G$81),"",IF(ISBLANK($G$81),"",$G$81)) | AJ81: =IF(ISERROR($H$81),"",IF(ISBLANK($H$81),"",$H$81)) | AL81: =IF(ISERROR($J$81),"",IF(ISBLANK($J$81),"",$J$81)) | AM81: =ISERROR($A$81)*1+ISERROR($C$81)*1+ISERROR($D$81)*1+ISERROR($G$81)*1+ISERROR($H$81)*1+ISERROR($J$81)*1
B82: =IF(ISNUMBER($Q$82),COUNTIF($Q$76:$Q$107,"<"&$Q$82)+1,"") | K82: =IF(AM82>0,"O Google leu como fórmula: escolha de novo ou digite com ' na frente.",IF(LEN($AC$82)=0,IF(LEN($AF$82&$AI$82&$AJ$82&$AE$82)>0,"Sem dia: o evento fica fora da ordem",""),IF(ISNUMBER($Q$82),"","Dia fora de 1 a 9.999 (inteiro)"))) | Q82: =IF(ISNUMBER($AC$82),IF(AND($AC$82>=1,$AC$82<=9999,INT($AC$82)=$AC$82),$AC$82+7/100,""),"") | R82: =IF(ISNUMBER($Q$82),IF(INT($Q$82)>=$B$41,$Q$82,""),"") | AA82: ='Tabelas'!$X$94&"" | AC82: =IF(ISERROR($A$82),"",IF(ISBLANK($A$82),"",$A$82)) | AE82: =IF(ISERROR($C$82),"",IF(ISBLANK($C$82),"",$C$82)) | AF82: =IF(ISERROR($D$82),"",IF(ISBLANK($D$82),"",$D$82)) | AI82: =IF(ISERROR($G$82),"",IF(ISBLANK($G$82),"",$G$82)) | AJ82: =IF(ISERROR($H$82),"",IF(ISBLANK($H$82),"",$H$82)) | AL82: =IF(ISERROR($J$82),"",IF(ISBLANK($J$82),"",$J$82)) | AM82: =ISERROR($A$82)*1+ISERROR($C$82)*1+ISERROR($D$82)*1+ISERROR($G$82)*1+ISERROR($H$82)*1+ISERROR($J$82)*1
B83: =IF(ISNUMBER($Q$83),COUNTIF($Q$76:$Q$107,"<"&$Q$83)+1,"") | K83: =IF(AM83>0,"O Google leu como fórmula: escolha de novo ou digite com ' na frente.",IF(LEN($AC$83)=0,IF(LEN($AF$83&$AI$83&$AJ$83&$AE$83)>0,"Sem dia: o evento fica fora da ordem",""),IF(ISNUMBER($Q$83),"","Dia fora de 1 a 9.999 (inteiro)"))) | Q83: =IF(ISNUMBER($AC$83),IF(AND($AC$83>=1,$AC$83<=9999,INT($AC$83)=$AC$83),$AC$83+8/100,""),"") | R83: =IF(ISNUMBER($Q$83),IF(INT($Q$83)>=$B$41,$Q$83,""),"") | AA83: ='Tabelas'!$X$96&"" | AC83: =IF(ISERROR($A$83),"",IF(ISBLANK($A$83),"",$A$83)) | AE83: =IF(ISERROR($C$83),"",IF(ISBLANK($C$83),"",$C$83)) | AF83: =IF(ISERROR($D$83),"",IF(ISBLANK($D$83),"",$D$83)) | AI83: =IF(ISERROR($G$83),"",IF(ISBLANK($G$83),"",$G$83)) | AJ83: =IF(ISERROR($H$83),"",IF(ISBLANK($H$83),"",$H$83)) | AL83: =IF(ISERROR($J$83),"",IF(ISBLANK($J$83),"",$J$83)) | AM83: =ISERROR($A$83)*1+ISERROR($C$83)*1+ISERROR($D$83)*1+ISERROR($G$83)*1+ISERROR($H$83)*1+ISERROR($J$83)*1
B84: =IF(ISNUMBER($Q$84),COUNTIF($Q$76:$Q$107,"<"&$Q$84)+1,"") | K84: =IF(AM84>0,"O Google leu como fórmula: escolha de novo ou digite com ' na frente.",IF(LEN($AC$84)=0,IF(LEN($AF$84&$AI$84&$AJ$84&$AE$84)>0,"Sem dia: o evento fica fora da ordem",""),IF(ISNUMBER($Q$84),"","Dia fora de 1 a 9.999 (inteiro)"))) | Q84: =IF(ISNUMBER($AC$84),IF(AND($AC$84>=1,$AC$84<=9999,INT($AC$84)=$AC$84),$AC$84+9/100,""),"") | R84: =IF(ISNUMBER($Q$84),IF(INT($Q$84)>=$B$41,$Q$84,""),"") | AA84: ='Tabelas'!$X$97&"" | AC84: =IF(ISERROR($A$84),"",IF(ISBLANK($A$84),"",$A$84)) | AE84: =IF(ISERROR($C$84),"",IF(ISBLANK($C$84),"",$C$84)) | AF84: =IF(ISERROR($D$84),"",IF(ISBLANK($D$84),"",$D$84)) | AI84: =IF(ISERROR($G$84),"",IF(ISBLANK($G$84),"",$G$84)) | AJ84: =IF(ISERROR($H$84),"",IF(ISBLANK($H$84),"",$H$84)) | AL84: =IF(ISERROR($J$84),"",IF(ISBLANK($J$84),"",$J$84)) | AM84: =ISERROR($A$84)*1+ISERROR($C$84)*1+ISERROR($D$84)*1+ISERROR($G$84)*1+ISERROR($H$84)*1+ISERROR($J$84)*1
B85: =IF(ISNUMBER($Q$85),COUNTIF($Q$76:$Q$107,"<"&$Q$85)+1,"") | K85: =IF(AM85>0,"O Google leu como fórmula: escolha de novo ou digite com ' na frente.",IF(LEN($AC$85)=0,IF(LEN($AF$85&$AI$85&$AJ$85&$AE$85)>0,"Sem dia: o evento fica fora da ordem",""),IF(ISNUMBER($Q$85),"","Dia fora de 1 a 9.999 (inteiro)"))) | Q85: =IF(ISNUMBER($AC$85),IF(AND($AC$85>=1,$AC$85<=9999,INT($AC$85)=$AC$85),$AC$85+10/100,""),"") | R85: =IF(ISNUMBER($Q$85),IF(INT($Q$85)>=$B$41,$Q$85,""),"") | AA85: ='Tabelas'!$X$98&"" | AC85: =IF(ISERROR($A$85),"",IF(ISBLANK($A$85),"",$A$85)) | AE85: =IF(ISERROR($C$85),"",IF(ISBLANK($C$85),"",$C$85)) | AF85: =IF(ISERROR($D$85),"",IF(ISBLANK($D$85),"",$D$85)) | AI85: =IF(ISERROR($G$85),"",IF(ISBLANK($G$85),"",$G$85)) | AJ85: =IF(ISERROR($H$85),"",IF(ISBLANK($H$85),"",$H$85)) | AL85: =IF(ISERROR($J$85),"",IF(ISBLANK($J$85),"",$J$85)) | AM85: =ISERROR($A$85)*1+ISERROR($C$85)*1+ISERROR($D$85)*1+ISERROR($G$85)*1+ISERROR($H$85)*1+ISERROR($J$85)*1
A86: Dia de campanha (preencha) | B86: Nº na ordem (automático) | C86: Sessão | D86: Evento | G86: Quem (facção ou NPC) | H86: Consequência | J86: Público? | K86: Aviso | AA86: ='Tabelas'!$X$99&"" | AC86: =IF(ISERROR($A$86),"",IF(ISBLANK($A$86),"",$A$86)) | AE86: =IF(ISERROR($C$86),"",IF(ISBLANK($C$86),"",$C$86)) | AF86: =IF(ISERROR($D$86),"",IF(ISBLANK($D$86),"",$D$86)) | AI86: =IF(ISERROR($G$86),"",IF(ISBLANK($G$86),"",$G$86)) | AJ86: =IF(ISERROR($H$86),"",IF(ISBLANK($H$86),"",$H$86)) | AL86: =IF(ISERROR($J$86),"",IF(ISBLANK($J$86),"",$J$86))
B87: =IF(ISNUMBER($Q$87),COUNTIF($Q$76:$Q$107,"<"&$Q$87)+1,"") | K87: =IF(AM87>0,"O Google leu como fórmula: escolha de novo ou digite com ' na frente.",IF(LEN($AC$87)=0,IF(LEN($AF$87&$AI$87&$AJ$87&$AE$87)>0,"Sem dia: o evento fica fora da ordem",""),IF(ISNUMBER($Q$87),"","Dia fora de 1 a 9.999 (inteiro)"))) | Q87: =IF(ISNUMBER($AC$87),IF(AND($AC$87>=1,$AC$87<=9999,INT($AC$87)=$AC$87),$AC$87+11/100,""),"") | R87: =IF(ISNUMBER($Q$87),IF(INT($Q$87)>=$B$41,$Q$87,""),"") | AA87: ='Tabelas'!$X$100&"" | AC87: =IF(ISERROR($A$87),"",IF(ISBLANK($A$87),"",$A$87)) | AE87: =IF(ISERROR($C$87),"",IF(ISBLANK($C$87),"",$C$87)) | AF87: =IF(ISERROR($D$87),"",IF(ISBLANK($D$87),"",$D$87)) | AI87: =IF(ISERROR($G$87),"",IF(ISBLANK($G$87),"",$G$87)) | AJ87: =IF(ISERROR($H$87),"",IF(ISBLANK($H$87),"",$H$87)) | AL87: =IF(ISERROR($J$87),"",IF(ISBLANK($J$87),"",$J$87)) | AM87: =ISERROR($A$87)*1+ISERROR($C$87)*1+ISERROR($D$87)*1+ISERROR($G$87)*1+ISERROR($H$87)*1+ISERROR($J$87)*1
B88: =IF(ISNUMBER($Q$88),COUNTIF($Q$76:$Q$107,"<"&$Q$88)+1,"") | K88: =IF(AM88>0,"O Google leu como fórmula: escolha de novo ou digite com ' na frente.",IF(LEN($AC$88)=0,IF(LEN($AF$88&$AI$88&$AJ$88&$AE$88)>0,"Sem dia: o evento fica fora da ordem",""),IF(ISNUMBER($Q$88),"","Dia fora de 1 a 9.999 (inteiro)"))) | Q88: =IF(ISNUMBER($AC$88),IF(AND($AC$88>=1,$AC$88<=9999,INT($AC$88)=$AC$88),$AC$88+12/100,""),"") | R88: =IF(ISNUMBER($Q$88),IF(INT($Q$88)>=$B$41,$Q$88,""),"") | AA88: ='Tabelas'!$X$101&"" | AC88: =IF(ISERROR($A$88),"",IF(ISBLANK($A$88),"",$A$88)) | AE88: =IF(ISERROR($C$88),"",IF(ISBLANK($C$88),"",$C$88)) | AF88: =IF(ISERROR($D$88),"",IF(ISBLANK($D$88),"",$D$88)) | AI88: =IF(ISERROR($G$88),"",IF(ISBLANK($G$88),"",$G$88)) | AJ88: =IF(ISERROR($H$88),"",IF(ISBLANK($H$88),"",$H$88)) | AL88: =IF(ISERROR($J$88),"",IF(ISBLANK($J$88),"",$J$88)) | AM88: =ISERROR($A$88)*1+ISERROR($C$88)*1+ISERROR($D$88)*1+ISERROR($G$88)*1+ISERROR($H$88)*1+ISERROR($J$88)*1
B89: =IF(ISNUMBER($Q$89),COUNTIF($Q$76:$Q$107,"<"&$Q$89)+1,"") | K89: =IF(AM89>0,"O Google leu como fórmula: escolha de novo ou digite com ' na frente.",IF(LEN($AC$89)=0,IF(LEN($AF$89&$AI$89&$AJ$89&$AE$89)>0,"Sem dia: o evento fica fora da ordem",""),IF(ISNUMBER($Q$89),"","Dia fora de 1 a 9.999 (inteiro)"))) | Q89: =IF(ISNUMBER($AC$89),IF(AND($AC$89>=1,$AC$89<=9999,INT($AC$89)=$AC$89),$AC$89+13/100,""),"") | R89: =IF(ISNUMBER($Q$89),IF(INT($Q$89)>=$B$41,$Q$89,""),"") | AA89: ='Tabelas'!$X$102&"" | AC89: =IF(ISERROR($A$89),"",IF(ISBLANK($A$89),"",$A$89)) | AE89: =IF(ISERROR($C$89),"",IF(ISBLANK($C$89),"",$C$89)) | AF89: =IF(ISERROR($D$89),"",IF(ISBLANK($D$89),"",$D$89)) | AI89: =IF(ISERROR($G$89),"",IF(ISBLANK($G$89),"",$G$89)) | AJ89: =IF(ISERROR($H$89),"",IF(ISBLANK($H$89),"",$H$89)) | AL89: =IF(ISERROR($J$89),"",IF(ISBLANK($J$89),"",$J$89)) | AM89: =ISERROR($A$89)*1+ISERROR($C$89)*1+ISERROR($D$89)*1+ISERROR($G$89)*1+ISERROR($H$89)*1+ISERROR($J$89)*1
B90: =IF(ISNUMBER($Q$90),COUNTIF($Q$76:$Q$107,"<"&$Q$90)+1,"") | K90: =IF(AM90>0,"O Google leu como fórmula: escolha de novo ou digite com ' na frente.",IF(LEN($AC$90)=0,IF(LEN($AF$90&$AI$90&$AJ$90&$AE$90)>0,"Sem dia: o evento fica fora da ordem",""),IF(ISNUMBER($Q$90),"","Dia fora de 1 a 9.999 (inteiro)"))) | Q90: =IF(ISNUMBER($AC$90),IF(AND($AC$90>=1,$AC$90<=9999,INT($AC$90)=$AC$90),$AC$90+14/100,""),"") | R90: =IF(ISNUMBER($Q$90),IF(INT($Q$90)>=$B$41,$Q$90,""),"") | AA90: ='Tabelas'!$X$103&"" | AC90: =IF(ISERROR($A$90),"",IF(ISBLANK($A$90),"",$A$90)) | AE90: =IF(ISERROR($C$90),"",IF(ISBLANK($C$90),"",$C$90)) | AF90: =IF(ISERROR($D$90),"",IF(ISBLANK($D$90),"",$D$90)) | AI90: =IF(ISERROR($G$90),"",IF(ISBLANK($G$90),"",$G$90)) | AJ90: =IF(ISERROR($H$90),"",IF(ISBLANK($H$90),"",$H$90)) | AL90: =IF(ISERROR($J$90),"",IF(ISBLANK($J$90),"",$J$90)) | AM90: =ISERROR($A$90)*1+ISERROR($C$90)*1+ISERROR($D$90)*1+ISERROR($G$90)*1+ISERROR($H$90)*1+ISERROR($J$90)*1
B91: =IF(ISNUMBER($Q$91),COUNTIF($Q$76:$Q$107,"<"&$Q$91)+1,"") | K91: =IF(AM91>0,"O Google leu como fórmula: escolha de novo ou digite com ' na frente.",IF(LEN($AC$91)=0,IF(LEN($AF$91&$AI$91&$AJ$91&$AE$91)>0,"Sem dia: o evento fica fora da ordem",""),IF(ISNUMBER($Q$91),"","Dia fora de 1 a 9.999 (inteiro)"))) | Q91: =IF(ISNUMBER($AC$91),IF(AND($AC$91>=1,$AC$91<=9999,INT($AC$91)=$AC$91),$AC$91+15/100,""),"") | R91: =IF(ISNUMBER($Q$91),IF(INT($Q$91)>=$B$41,$Q$91,""),"") | AA91: ='Tabelas'!$X$104&"" | AC91: =IF(ISERROR($A$91),"",IF(ISBLANK($A$91),"",$A$91)) | AE91: =IF(ISERROR($C$91),"",IF(ISBLANK($C$91),"",$C$91)) | AF91: =IF(ISERROR($D$91),"",IF(ISBLANK($D$91),"",$D$91)) | AI91: =IF(ISERROR($G$91),"",IF(ISBLANK($G$91),"",$G$91)) | AJ91: =IF(ISERROR($H$91),"",IF(ISBLANK($H$91),"",$H$91)) | AL91: =IF(ISERROR($J$91),"",IF(ISBLANK($J$91),"",$J$91)) | AM91: =ISERROR($A$91)*1+ISERROR($C$91)*1+ISERROR($D$91)*1+ISERROR($G$91)*1+ISERROR($H$91)*1+ISERROR($J$91)*1
B92: =IF(ISNUMBER($Q$92),COUNTIF($Q$76:$Q$107,"<"&$Q$92)+1,"") | K92: =IF(AM92>0,"O Google leu como fórmula: escolha de novo ou digite com ' na frente.",IF(LEN($AC$92)=0,IF(LEN($AF$92&$AI$92&$AJ$92&$AE$92)>0,"Sem dia: o evento fica fora da ordem",""),IF(ISNUMBER($Q$92),"","Dia fora de 1 a 9.999 (inteiro)"))) | Q92: =IF(ISNUMBER($AC$92),IF(AND($AC$92>=1,$AC$92<=9999,INT($AC$92)=$AC$92),$AC$92+16/100,""),"") | R92: =IF(ISNUMBER($Q$92),IF(INT($Q$92)>=$B$41,$Q$92,""),"") | AA92: ='Tabelas'!$X$105&"" | AC92: =IF(ISERROR($A$92),"",IF(ISBLANK($A$92),"",$A$92)) | AE92: =IF(ISERROR($C$92),"",IF(ISBLANK($C$92),"",$C$92)) | AF92: =IF(ISERROR($D$92),"",IF(ISBLANK($D$92),"",$D$92)) | AI92: =IF(ISERROR($G$92),"",IF(ISBLANK($G$92),"",$G$92)) | AJ92: =IF(ISERROR($H$92),"",IF(ISBLANK($H$92),"",$H$92)) | AL92: =IF(ISERROR($J$92),"",IF(ISBLANK($J$92),"",$J$92)) | AM92: =ISERROR($A$92)*1+ISERROR($C$92)*1+ISERROR($D$92)*1+ISERROR($G$92)*1+ISERROR($H$92)*1+ISERROR($J$92)*1
B93: =IF(ISNUMBER($Q$93),COUNTIF($Q$76:$Q$107,"<"&$Q$93)+1,"") | K93: =IF(AM93>0,"O Google leu como fórmula: escolha de novo ou digite com ' na frente.",IF(LEN($AC$93)=0,IF(LEN($AF$93&$AI$93&$AJ$93&$AE$93)>0,"Sem dia: o evento fica fora da ordem",""),IF(ISNUMBER($Q$93),"","Dia fora de 1 a 9.999 (inteiro)"))) | Q93: =IF(ISNUMBER($AC$93),IF(AND($AC$93>=1,$AC$93<=9999,INT($AC$93)=$AC$93),$AC$93+17/100,""),"") | R93: =IF(ISNUMBER($Q$93),IF(INT($Q$93)>=$B$41,$Q$93,""),"") | AA93: ='Tabelas'!$X$106&"" | AC93: =IF(ISERROR($A$93),"",IF(ISBLANK($A$93),"",$A$93)) | AE93: =IF(ISERROR($C$93),"",IF(ISBLANK($C$93),"",$C$93)) | AF93: =IF(ISERROR($D$93),"",IF(ISBLANK($D$93),"",$D$93)) | AI93: =IF(ISERROR($G$93),"",IF(ISBLANK($G$93),"",$G$93)) | AJ93: =IF(ISERROR($H$93),"",IF(ISBLANK($H$93),"",$H$93)) | AL93: =IF(ISERROR($J$93),"",IF(ISBLANK($J$93),"",$J$93)) | AM93: =ISERROR($A$93)*1+ISERROR($C$93)*1+ISERROR($D$93)*1+ISERROR($G$93)*1+ISERROR($H$93)*1+ISERROR($J$93)*1
B94: =IF(ISNUMBER($Q$94),COUNTIF($Q$76:$Q$107,"<"&$Q$94)+1,"") | K94: =IF(AM94>0,"O Google leu como fórmula: escolha de novo ou digite com ' na frente.",IF(LEN($AC$94)=0,IF(LEN($AF$94&$AI$94&$AJ$94&$AE$94)>0,"Sem dia: o evento fica fora da ordem",""),IF(ISNUMBER($Q$94),"","Dia fora de 1 a 9.999 (inteiro)"))) | Q94: =IF(ISNUMBER($AC$94),IF(AND($AC$94>=1,$AC$94<=9999,INT($AC$94)=$AC$94),$AC$94+18/100,""),"") | R94: =IF(ISNUMBER($Q$94),IF(INT($Q$94)>=$B$41,$Q$94,""),"") | AA94: ='Tabelas'!$X$107&"" | AC94: =IF(ISERROR($A$94),"",IF(ISBLANK($A$94),"",$A$94)) | AE94: =IF(ISERROR($C$94),"",IF(ISBLANK($C$94),"",$C$94)) | AF94: =IF(ISERROR($D$94),"",IF(ISBLANK($D$94),"",$D$94)) | AI94: =IF(ISERROR($G$94),"",IF(ISBLANK($G$94),"",$G$94)) | AJ94: =IF(ISERROR($H$94),"",IF(ISBLANK($H$94),"",$H$94)) | AL94: =IF(ISERROR($J$94),"",IF(ISBLANK($J$94),"",$J$94)) | AM94: =ISERROR($A$94)*1+ISERROR($C$94)*1+ISERROR($D$94)*1+ISERROR($G$94)*1+ISERROR($H$94)*1+ISERROR($J$94)*1
B95: =IF(ISNUMBER($Q$95),COUNTIF($Q$76:$Q$107,"<"&$Q$95)+1,"") | K95: =IF(AM95>0,"O Google leu como fórmula: escolha de novo ou digite com ' na frente.",IF(LEN($AC$95)=0,IF(LEN($AF$95&$AI$95&$AJ$95&$AE$95)>0,"Sem dia: o evento fica fora da ordem",""),IF(ISNUMBER($Q$95),"","Dia fora de 1 a 9.999 (inteiro)"))) | Q95: =IF(ISNUMBER($AC$95),IF(AND($AC$95>=1,$AC$95<=9999,INT($AC$95)=$AC$95),$AC$95+19/100,""),"") | R95: =IF(ISNUMBER($Q$95),IF(INT($Q$95)>=$B$41,$Q$95,""),"") | AA95: ='Tabelas'!$X$108&"" | AC95: =IF(ISERROR($A$95),"",IF(ISBLANK($A$95),"",$A$95)) | AE95: =IF(ISERROR($C$95),"",IF(ISBLANK($C$95),"",$C$95)) | AF95: =IF(ISERROR($D$95),"",IF(ISBLANK($D$95),"",$D$95)) | AI95: =IF(ISERROR($G$95),"",IF(ISBLANK($G$95),"",$G$95)) | AJ95: =IF(ISERROR($H$95),"",IF(ISBLANK($H$95),"",$H$95)) | AL95: =IF(ISERROR($J$95),"",IF(ISBLANK($J$95),"",$J$95)) | AM95: =ISERROR($A$95)*1+ISERROR($C$95)*1+ISERROR($D$95)*1+ISERROR($G$95)*1+ISERROR($H$95)*1+ISERROR($J$95)*1
B96: =IF(ISNUMBER($Q$96),COUNTIF($Q$76:$Q$107,"<"&$Q$96)+1,"") | K96: =IF(AM96>0,"O Google leu como fórmula: escolha de novo ou digite com ' na frente.",IF(LEN($AC$96)=0,IF(LEN($AF$96&$AI$96&$AJ$96&$AE$96)>0,"Sem dia: o evento fica fora da ordem",""),IF(ISNUMBER($Q$96),"","Dia fora de 1 a 9.999 (inteiro)"))) | Q96: =IF(ISNUMBER($AC$96),IF(AND($AC$96>=1,$AC$96<=9999,INT($AC$96)=$AC$96),$AC$96+20/100,""),"") | R96: =IF(ISNUMBER($Q$96),IF(INT($Q$96)>=$B$41,$Q$96,""),"") | AA96: ='Tabelas'!$X$110&"" | AC96: =IF(ISERROR($A$96),"",IF(ISBLANK($A$96),"",$A$96)) | AE96: =IF(ISERROR($C$96),"",IF(ISBLANK($C$96),"",$C$96)) | AF96: =IF(ISERROR($D$96),"",IF(ISBLANK($D$96),"",$D$96)) | AI96: =IF(ISERROR($G$96),"",IF(ISBLANK($G$96),"",$G$96)) | AJ96: =IF(ISERROR($H$96),"",IF(ISBLANK($H$96),"",$H$96)) | AL96: =IF(ISERROR($J$96),"",IF(ISBLANK($J$96),"",$J$96)) | AM96: =ISERROR($A$96)*1+ISERROR($C$96)*1+ISERROR($D$96)*1+ISERROR($G$96)*1+ISERROR($H$96)*1+ISERROR($J$96)*1
A97: Dia de campanha (preencha) | B97: Nº na ordem (automático) | C97: Sessão | D97: Evento | G97: Quem (facção ou NPC) | H97: Consequência | J97: Público? | K97: Aviso | AA97: ='Tabelas'!$X$111&"" | AC97: =IF(ISERROR($A$97),"",IF(ISBLANK($A$97),"",$A$97)) | AE97: =IF(ISERROR($C$97),"",IF(ISBLANK($C$97),"",$C$97)) | AF97: =IF(ISERROR($D$97),"",IF(ISBLANK($D$97),"",$D$97)) | AI97: =IF(ISERROR($G$97),"",IF(ISBLANK($G$97),"",$G$97)) | AJ97: =IF(ISERROR($H$97),"",IF(ISBLANK($H$97),"",$H$97)) | AL97: =IF(ISERROR($J$97),"",IF(ISBLANK($J$97),"",$J$97))
B98: =IF(ISNUMBER($Q$98),COUNTIF($Q$76:$Q$107,"<"&$Q$98)+1,"") | K98: =IF(AM98>0,"O Google leu como fórmula: escolha de novo ou digite com ' na frente.",IF(LEN($AC$98)=0,IF(LEN($AF$98&$AI$98&$AJ$98&$AE$98)>0,"Sem dia: o evento fica fora da ordem",""),IF(ISNUMBER($Q$98),"","Dia fora de 1 a 9.999 (inteiro)"))) | Q98: =IF(ISNUMBER($AC$98),IF(AND($AC$98>=1,$AC$98<=9999,INT($AC$98)=$AC$98),$AC$98+21/100,""),"") | R98: =IF(ISNUMBER($Q$98),IF(INT($Q$98)>=$B$41,$Q$98,""),"") | AA98: ='Tabelas'!$X$112&"" | AC98: =IF(ISERROR($A$98),"",IF(ISBLANK($A$98),"",$A$98)) | AE98: =IF(ISERROR($C$98),"",IF(ISBLANK($C$98),"",$C$98)) | AF98: =IF(ISERROR($D$98),"",IF(ISBLANK($D$98),"",$D$98)) | AI98: =IF(ISERROR($G$98),"",IF(ISBLANK($G$98),"",$G$98)) | AJ98: =IF(ISERROR($H$98),"",IF(ISBLANK($H$98),"",$H$98)) | AL98: =IF(ISERROR($J$98),"",IF(ISBLANK($J$98),"",$J$98)) | AM98: =ISERROR($A$98)*1+ISERROR($C$98)*1+ISERROR($D$98)*1+ISERROR($G$98)*1+ISERROR($H$98)*1+ISERROR($J$98)*1
B99: =IF(ISNUMBER($Q$99),COUNTIF($Q$76:$Q$107,"<"&$Q$99)+1,"") | K99: =IF(AM99>0,"O Google leu como fórmula: escolha de novo ou digite com ' na frente.",IF(LEN($AC$99)=0,IF(LEN($AF$99&$AI$99&$AJ$99&$AE$99)>0,"Sem dia: o evento fica fora da ordem",""),IF(ISNUMBER($Q$99),"","Dia fora de 1 a 9.999 (inteiro)"))) | Q99: =IF(ISNUMBER($AC$99),IF(AND($AC$99>=1,$AC$99<=9999,INT($AC$99)=$AC$99),$AC$99+22/100,""),"") | R99: =IF(ISNUMBER($Q$99),IF(INT($Q$99)>=$B$41,$Q$99,""),"") | AA99: ='Tabelas'!$X$113&"" | AC99: =IF(ISERROR($A$99),"",IF(ISBLANK($A$99),"",$A$99)) | AE99: =IF(ISERROR($C$99),"",IF(ISBLANK($C$99),"",$C$99)) | AF99: =IF(ISERROR($D$99),"",IF(ISBLANK($D$99),"",$D$99)) | AI99: =IF(ISERROR($G$99),"",IF(ISBLANK($G$99),"",$G$99)) | AJ99: =IF(ISERROR($H$99),"",IF(ISBLANK($H$99),"",$H$99)) | AL99: =IF(ISERROR($J$99),"",IF(ISBLANK($J$99),"",$J$99)) | AM99: =ISERROR($A$99)*1+ISERROR($C$99)*1+ISERROR($D$99)*1+ISERROR($G$99)*1+ISERROR($H$99)*1+ISERROR($J$99)*1
B100: =IF(ISNUMBER($Q$100),COUNTIF($Q$76:$Q$107,"<"&$Q$100)+1,"") | K100: =IF(AM100>0,"O Google leu como fórmula: escolha de novo ou digite com ' na frente.",IF(LEN($AC$100)=0,IF(LEN($AF$100&$AI$100&$AJ$100&$AE$100)>0,"Sem dia: o evento fica fora da ordem",""),IF(ISNUMBER($Q$100),"","Dia fora de 1 a 9.999 (inteiro)"))) | Q100: =IF(ISNUMBER($AC$100),IF(AND($AC$100>=1,$AC$100<=9999,INT($AC$100)=$AC$100),$AC$100+23/100,""),"") | R100: =IF(ISNUMBER($Q$100),IF(INT($Q$100)>=$B$41,$Q$100,""),"") | AA100: ='Tabelas'!$X$114&"" | AC100: =IF(ISERROR($A$100),"",IF(ISBLANK($A$100),"",$A$100)) | AE100: =IF(ISERROR($C$100),"",IF(ISBLANK($C$100),"",$C$100)) | AF100: =IF(ISERROR($D$100),"",IF(ISBLANK($D$100),"",$D$100)) | AI100: =IF(ISERROR($G$100),"",IF(ISBLANK($G$100),"",$G$100)) | AJ100: =IF(ISERROR($H$100),"",IF(ISBLANK($H$100),"",$H$100)) | AL100: =IF(ISERROR($J$100),"",IF(ISBLANK($J$100),"",$J$100)) | AM100: =ISERROR($A$100)*1+ISERROR($C$100)*1+ISERROR($D$100)*1+ISERROR($G$100)*1+ISERROR($H$100)*1+ISERROR($J$100)*1
B101: =IF(ISNUMBER($Q$101),COUNTIF($Q$76:$Q$107,"<"&$Q$101)+1,"") | K101: =IF(AM101>0,"O Google leu como fórmula: escolha de novo ou digite com ' na frente.",IF(LEN($AC$101)=0,IF(LEN($AF$101&$AI$101&$AJ$101&$AE$101)>0,"Sem dia: o evento fica fora da ordem",""),IF(ISNUMBER($Q$101),"","Dia fora de 1 a 9.999 (inteiro)"))) | Q101: =IF(ISNUMBER($AC$101),IF(AND($AC$101>=1,$AC$101<=9999,INT($AC$101)=$AC$101),$AC$101+24/100,""),"") | R101: =IF(ISNUMBER($Q$101),IF(INT($Q$101)>=$B$41,$Q$101,""),"") | AA101: ='Tabelas'!$X$115&"" | AC101: =IF(ISERROR($A$101),"",IF(ISBLANK($A$101),"",$A$101)) | AE101: =IF(ISERROR($C$101),"",IF(ISBLANK($C$101),"",$C$101)) | AF101: =IF(ISERROR($D$101),"",IF(ISBLANK($D$101),"",$D$101)) | AI101: =IF(ISERROR($G$101),"",IF(ISBLANK($G$101),"",$G$101)) | AJ101: =IF(ISERROR($H$101),"",IF(ISBLANK($H$101),"",$H$101)) | AL101: =IF(ISERROR($J$101),"",IF(ISBLANK($J$101),"",$J$101)) | AM101: =ISERROR($A$101)*1+ISERROR($C$101)*1+ISERROR($D$101)*1+ISERROR($G$101)*1+ISERROR($H$101)*1+ISERROR($J$101)*1
...

Sheet Grupo
A1: Grupo — Explorando Galáxias v1.2
A2: Legenda: | B2: Entrada (preencha) | C2: Calculada (automático) | D2: Aviso (texto em vermelho) | E2: Título de bloco | F2: Cabeçalho de coluna | G2: Rótulo da linha | H2: Linha alternada (outro tom) | I2: Não se aplica
A3: Os personagens jogadores, copiados da ficha de cada jogador (uma linha por PJ).
A5: G1 · Quem é (preencha, da ficha de cada jogador)
A6: Nome do PJ | B6: Jogador | C6: Raça | D6: Caminho | E6: Elemento | F6: Propósito de Vida | I6: Crença do Esforço (Humano) | K6: Aviso
K7: =IF(Z7>0,"O Google leu como fórmula: escolha de novo ou digite com ' na frente.",IF(AND(LEN($R$7)>0,COUNTIF('Dados'!$A$350:$A$356,$R$7)=0),"Raça fora da lista do capítulo 05",IF(AND(LEN($T$7)>0,COUNTIF($T$7:$T$12,$T$7)>1),"Elemento repetido no grupo: cuidado com a Resistência (regra irmã, 27.5)",IF(AND(LEN($P$7)=0,LEN($R$7&$T$7&$S$7)>0),"Linha sem nome: o PJ não entra na contagem","")))) | P7: =IF(ISERROR($A$7),"",IF(ISBLANK($A$7),"",$A$7)) | R7: =IF(ISERROR($C$7),"",IF(ISBLANK($C$7),"",$C$7)) | S7: =IF(ISERROR($D$7),"",IF(ISBLANK($D$7),"",$D$7)) | T7: =IF(ISERROR($E$7),"",IF(ISBLANK($E$7),"",$E$7)) | U7: =IF(ISERROR($F$7),"",IF(ISBLANK($F$7),"",$F$7)) | Z7: =ISERROR($A$7)*1+ISERROR($B$7)*1+ISERROR($C$7)*1+ISERROR($D$7)*1+ISERROR($E$7)*1+ISERROR($F$7)*1+ISERROR($I$7)*1
K8: =IF(Z8>0,"O Google leu como fórmula: escolha de novo ou digite com ' na frente.",IF(AND(LEN($R$8)>0,COUNTIF('Dados'!$A$350:$A$356,$R$8)=0),"Raça fora da lista do capítulo 05",IF(AND(LEN($T$8)>0,COUNTIF($T$7:$T$12,$T$8)>1),"Elemento repetido no grupo: cuidado com a Resistência (regra irmã, 27.5)",IF(AND(LEN($P$8)=0,LEN($R$8&$T$8&$S$8)>0),"Linha sem nome: o PJ não entra na contagem","")))) | P8: =IF(ISERROR($A$8),"",IF(ISBLANK($A$8),"",$A$8)) | R8: =IF(ISERROR($C$8),"",IF(ISBLANK($C$8),"",$C$8)) | S8: =IF(ISERROR($D$8),"",IF(ISBLANK($D$8),"",$D$8)) | T8: =IF(ISERROR($E$8),"",IF(ISBLANK($E$8),"",$E$8)) | U8: =IF(ISERROR($F$8),"",IF(ISBLANK($F$8),"",$F$8)) | Z8: =ISERROR($A$8)*1+ISERROR($B$8)*1+ISERROR($C$8)*1+ISERROR($D$8)*1+ISERROR($E$8)*1+ISERROR($F$8)*1+ISERROR($I$8)*1
K9: =IF(Z9>0,"O Google leu como fórmula: escolha de novo ou digite com ' na frente.",IF(AND(LEN($R$9)>0,COUNTIF('Dados'!$A$350:$A$356,$R$9)=0),"Raça fora da lista do capítulo 05",IF(AND(LEN($T$9)>0,COUNTIF($T$7:$T$12,$T$9)>1),"Elemento repetido no grupo: cuidado com a Resistência (regra irmã, 27.5)",IF(AND(LEN($P$9)=0,LEN($R$9&$T$9&$S$9)>0),"Linha sem nome: o PJ não entra na contagem","")))) | P9: =IF(ISERROR($A$9),"",IF(ISBLANK($A$9),"",$A$9)) | R9: =IF(ISERROR($C$9),"",IF(ISBLANK($C$9),"",$C$9)) | S9: =IF(ISERROR($D$9),"",IF(ISBLANK($D$9),"",$D$9)) | T9: =IF(ISERROR($E$9),"",IF(ISBLANK($E$9),"",$E$9)) | U9: =IF(ISERROR($F$9),"",IF(ISBLANK($F$9),"",$F$9)) | Z9: =ISERROR($A$9)*1+ISERROR($B$9)*1+ISERROR($C$9)*1+ISERROR($D$9)*1+ISERROR($E$9)*1+ISERROR($F$9)*1+ISERROR($I$9)*1
K10: =IF(Z10>0,"O Google leu como fórmula: escolha de novo ou digite com ' na frente.",IF(AND(LEN($R$10)>0,COUNTIF('Dados'!$A$350:$A$356,$R$10)=0),"Raça fora da lista do capítulo 05",IF(AND(LEN($T$10)>0,COUNTIF($T$7:$T$12,$T$10)>1),"Elemento repetido no grupo: cuidado com a Resistência (regra irmã, 27.5)",IF(AND(LEN($P$10)=0,LEN($R$10&$T$10&$S$10)>0),"Linha sem nome: o PJ não entra na contagem","")))) | P10: =IF(ISERROR($A$10),"",IF(ISBLANK($A$10),"",$A$10)) | R10: =IF(ISERROR($C$10),"",IF(ISBLANK($C$10),"",$C$10)) | S10: =IF(ISERROR($D$10),"",IF(ISBLANK($D$10),"",$D$10)) | T10: =IF(ISERROR($E$10),"",IF(ISBLANK($E$10),"",$E$10)) | U10: =IF(ISERROR($F$10),"",IF(ISBLANK($F$10),"",$F$10)) | Z10: =ISERROR($A$10)*1+ISERROR($B$10)*1+ISERROR($C$10)*1+ISERROR($D$10)*1+ISERROR($E$10)*1+ISERROR($F$10)*1+ISERROR($I$10)*1
K11: =IF(Z11>0,"O Google leu como fórmula: escolha de novo ou digite com ' na frente.",IF(AND(LEN($R$11)>0,COUNTIF('Dados'!$A$350:$A$356,$R$11)=0),"Raça fora da lista do capítulo 05",IF(AND(LEN($T$11)>0,COUNTIF($T$7:$T$12,$T$11)>1),"Elemento repetido no grupo: cuidado com a Resistência (regra irmã, 27.5)",IF(AND(LEN($P$11)=0,LEN($R$11&$T$11&$S$11)>0),"Linha sem nome: o PJ não entra na contagem","")))) | P11: =IF(ISERROR($A$11),"",IF(ISBLANK($A$11),"",$A$11)) | R11: =IF(ISERROR($C$11),"",IF(ISBLANK($C$11),"",$C$11)) | S11: =IF(ISERROR($D$11),"",IF(ISBLANK($D$11),"",$D$11)) | T11: =IF(ISERROR($E$11),"",IF(ISBLANK($E$11),"",$E$11)) | U11: =IF(ISERROR($F$11),"",IF(ISBLANK($F$11),"",$F$11)) | Z11: =ISERROR($A$11)*1+ISERROR($B$11)*1+ISERROR($C$11)*1+ISERROR($D$11)*1+ISERROR($E$11)*1+ISERROR($F$11)*1+ISERROR($I$11)*1
K12: =IF(Z12>0,"O Google leu como fórmula: escolha de novo ou digite com ' na frente.",IF(AND(LEN($R$12)>0,COUNTIF('Dados'!$A$350:$A$356,$R$12)=0),"Raça fora da lista do capítulo 05",IF(AND(LEN($T$12)>0,COUNTIF($T$7:$T$12,$T$12)>1),"Elemento repetido no grupo: cuidado com a Resistência (regra irmã, 27.5)",IF(AND(LEN($P$12)=0,LEN($R$12&$T$12&$S$12)>0),"Linha sem nome: o PJ não entra na contagem","")))) | P12: =IF(ISERROR($A$12),"",IF(ISBLANK($A$12),"",$A$12)) | R12: =IF(ISERROR($C$12),"",IF(ISBLANK($C$12),"",$C$12)) | S12: =IF(ISERROR($D$12),"",IF(ISBLANK($D$12),"",$D$12)) | T12: =IF(ISERROR($E$12),"",IF(ISBLANK($E$12),"",$E$12)) | U12: =IF(ISERROR($F$12),"",IF(ISBLANK($F$12),"",$F$12)) | Z12: =ISERROR($A$12)*1+ISERROR($B$12)*1+ISERROR($C$12)*1+ISERROR($D$12)*1+ISERROR($E$12)*1+ISERROR($F$12)*1+ISERROR($I$12)*1
A14: G2 · Números de combate (preencha, da aba Em Jogo da ficha)
A15: PJ | B15: PV máx. | C15: Defesa | D15: Esquiva | E15: RD | F15: VEL | G15: Bônus de Agilidade | H15: Bônus de Discernimento | I15: Bônus de Presença | J15: DT das Habilidades | K15: Aviso
A16: =IF(LEN($P$7)>0,$P$7,"PJ 1") | K16: =IF(Z16>0,"O Google leu como fórmula: digite de novo com ' na frente.",IF(AND(ISNUMBER($U$16),OR($U$16<7,$U$16>25)),"VEL fora dos extremos 7 a 25 da fórmula: confira na ficha (19.1)",IF(OR(AND(ISNUMBER($V$16),OR($V$16<-1,$V$16>5)),AND(ISNUMBER($W$16),OR($W$16<-1,$W$16>5)),AND(ISNUMBER($X$16),OR($X$16<-1,$X$16>5))),"Bônus de Atributo fora de -1 a +5: confira na ficha",IF(AND(ISNUMBER($Q$16),OR($Q$16<1,$Q$16>999)),"PV fora de 1 a 999: confira na ficha","")))) | Q16: =IF(ISERROR($B$16),"",IF(ISBLANK($B$16),"",$B$16)) | U16: =IF(ISERROR($F$16),"",IF(ISBLANK($F$16),"",$F$16)) | V16: =IF(ISERROR($G$16),"",IF(ISBLANK($G$16),"",$G$16)) | W16: =IF(ISERROR($H$16),"",IF(ISBLANK($H$16),"",$H$16)) | X16: =IF(ISERROR($I$16),"",IF(ISBLANK($I$16),"",$I$16)) | Z16: =ISERROR($B$16)*1+ISERROR($C$16)*1+ISERROR($D$16)*1+ISERROR($E$16)*1+ISERROR($F$16)*1+ISERROR($G$16)*1+ISERROR($H$16)*1+ISERROR($I$16)*1+ISERROR($J$16)*1
A17: =IF(LEN($P$8)>0,$P$8,"PJ 2") | K17: =IF(Z17>0,"O Google leu como fórmula: digite de novo com ' na frente.",IF(AND(ISNUMBER($U$17),OR($U$17<7,$U$17>25)),"VEL fora dos extremos 7 a 25 da fórmula: confira na ficha (19.1)",IF(OR(AND(ISNUMBER($V$17),OR($V$17<-1,$V$17>5)),AND(ISNUMBER($W$17),OR($W$17<-1,$W$17>5)),AND(ISNUMBER($X$17),OR($X$17<-1,$X$17>5))),"Bônus de Atributo fora de -1 a +5: confira na ficha",IF(AND(ISNUMBER($Q$17),OR($Q$17<1,$Q$17>999)),"PV fora de 1 a 999: confira na ficha","")))) | Q17: =IF(ISERROR($B$17),"",IF(ISBLANK($B$17),"",$B$17)) | U17: =IF(ISERROR($F$17),"",IF(ISBLANK($F$17),"",$F$17)) | V17: =IF(ISERROR($G$17),"",IF(ISBLANK($G$17),"",$G$17)) | W17: =IF(ISERROR($H$17),"",IF(ISBLANK($H$17),"",$H$17)) | X17: =IF(ISERROR($I$17),"",IF(ISBLANK($I$17),"",$I$17)) | Z17: =ISERROR($B$17)*1+ISERROR($C$17)*1+ISERROR($D$17)*1+ISERROR($E$17)*1+ISERROR($F$17)*1+ISERROR($G$17)*1+ISERROR($H$17)*1+ISERROR($I$17)*1+ISERROR($J$17)*1
A18: =IF(LEN($P$9)>0,$P$9,"PJ 3") | K18: =IF(Z18>0,"O Google leu como fórmula: digite de novo com ' na frente.",IF(AND(ISNUMBER($U$18),OR($U$18<7,$U$18>25)),"VEL fora dos extremos 7 a 25 da fórmula: confira na ficha (19.1)",IF(OR(AND(ISNUMBER($V$18),OR($V$18<-1,$V$18>5)),AND(ISNUMBER($W$18),OR($W$18<-1,$W$18>5)),AND(ISNUMBER($X$18),OR($X$18<-1,$X$18>5))),"Bônus de Atributo fora de -1 a +5: confira na ficha",IF(AND(ISNUMBER($Q$18),OR($Q$18<1,$Q$18>999)),"PV fora de 1 a 999: confira na ficha","")))) | Q18: =IF(ISERROR($B$18),"",IF(ISBLANK($B$18),"",$B$18)) | U18: =IF(ISERROR($F$18),"",IF(ISBLANK($F$18),"",$F$18)) | V18: =IF(ISERROR($G$18),"",IF(ISBLANK($G$18),"",$G$18)) | W18: =IF(ISERROR($H$18),"",IF(ISBLANK($H$18),"",$H$18)) | X18: =IF(ISERROR($I$18),"",IF(ISBLANK($I$18),"",$I$18)) | Z18: =ISERROR($B$18)*1+ISERROR($C$18)*1+ISERROR($D$18)*1+ISERROR($E$18)*1+ISERROR($F$18)*1+ISERROR($G$18)*1+ISERROR($H$18)*1+ISERROR($I$18)*1+ISERROR($J$18)*1
A19: =IF(LEN($P$10)>0,$P$10,"PJ 4") | K19: =IF(Z19>0,"O Google leu como fórmula: digite de novo com ' na frente.",IF(AND(ISNUMBER($U$19),OR($U$19<7,$U$19>25)),"VEL fora dos extremos 7 a 25 da fórmula: confira na ficha (19.1)",IF(OR(AND(ISNUMBER($V$19),OR($V$19<-1,$V$19>5)),AND(ISNUMBER($W$19),OR($W$19<-1,$W$19>5)),AND(ISNUMBER($X$19),OR($X$19<-1,$X$19>5))),"Bônus de Atributo fora de -1 a +5: confira na ficha",IF(AND(ISNUMBER($Q$19),OR($Q$19<1,$Q$19>999)),"PV fora de 1 a 999: confira na ficha","")))) | Q19: =IF(ISERROR($B$19),"",IF(ISBLANK($B$19),"",$B$19)) | U19: =IF(ISERROR($F$19),"",IF(ISBLANK($F$19),"",$F$19)) | V19: =IF(ISERROR($G$19),"",IF(ISBLANK($G$19),"",$G$19)) | W19: =IF(ISERROR($H$19),"",IF(ISBLANK($H$19),"",$H$19)) | X19: =IF(ISERROR($I$19),"",IF(ISBLANK($I$19),"",$I$19)) | Z19: =ISERROR($B$19)*1+ISERROR($C$19)*1+ISERROR($D$19)*1+ISERROR($E$19)*1+ISERROR($F$19)*1+ISERROR($G$19)*1+ISERROR($H$19)*1+ISERROR($I$19)*1+ISERROR($J$19)*1
A20: =IF(LEN($P$11)>0,$P$11,"PJ 5") | K20: =IF(Z20>0,"O Google leu como fórmula: digite de novo com ' na frente.",IF(AND(ISNUMBER($U$20),OR($U$20<7,$U$20>25)),"VEL fora dos extremos 7 a 25 da fórmula: confira na ficha (19.1)",IF(OR(AND(ISNUMBER($V$20),OR($V$20<-1,$V$20>5)),AND(ISNUMBER($W$20),OR($W$20<-1,$W$20>5)),AND(ISNUMBER($X$20),OR($X$20<-1,$X$20>5))),"Bônus de Atributo fora de -1 a +5: confira na ficha",IF(AND(ISNUMBER($Q$20),OR($Q$20<1,$Q$20>999)),"PV fora de 1 a 999: confira na ficha","")))) | Q20: =IF(ISERROR($B$20),"",IF(ISBLANK($B$20),"",$B$20)) | U20: =IF(ISERROR($F$20),"",IF(ISBLANK($F$20),"",$F$20)) | V20: =IF(ISERROR($G$20),"",IF(ISBLANK($G$20),"",$G$20)) | W20: =IF(ISERROR($H$20),"",IF(ISBLANK($H$20),"",$H$20)) | X20: =IF(ISERROR($I$20),"",IF(ISBLANK($I$20),"",$I$20)) | Z20: =ISERROR($B$20)*1+ISERROR($C$20)*1+ISERROR($D$20)*1+ISERROR($E$20)*1+ISERROR($F$20)*1+ISERROR($G$20)*1+ISERROR($H$20)*1+ISERROR($I$20)*1+ISERROR($J$20)*1
A21: =IF(LEN($P$12)>0,$P$12,"PJ 6") | K21: =IF(Z21>0,"O Google leu como fórmula: digite de novo com ' na frente.",IF(AND(ISNUMBER($U$21),OR($U$21<7,$U$21>25)),"VEL fora dos extremos 7 a 25 da fórmula: confira na ficha (19.1)",IF(OR(AND(ISNUMBER($V$21),OR($V$21<-1,$V$21>5)),AND(ISNUMBER($W$21),OR($W$21<-1,$W$21>5)),AND(ISNUMBER($X$21),OR($X$21<-1,$X$21>5))),"Bônus de Atributo fora de -1 a +5: confira na ficha",IF(AND(ISNUMBER($Q$21),OR($Q$21<1,$Q$21>999)),"PV fora de 1 a 999: confira na ficha","")))) | Q21: =IF(ISERROR($B$21),"",IF(ISBLANK($B$21),"",$B$21)) | U21: =IF(ISERROR($F$21),"",IF(ISBLANK($F$21),"",$F$21)) | V21: =IF(ISERROR($G$21),"",IF(ISBLANK($G$21),"",$G$21)) | W21: =IF(ISERROR($H$21),"",IF(ISBLANK($H$21),"",$H$21)) | X21: =IF(ISERROR($I$21),"",IF(ISBLANK($I$21),"",$I$21)) | Z21: =ISERROR($B$21)*1+ISERROR($C$21)*1+ISERROR($D$21)*1+ISERROR($E$21)*1+ISERROR($F$21)*1+ISERROR($G$21)*1+ISERROR($H$21)*1+ISERROR($I$21)*1+ISERROR($J$21)*1
A23: G3 · Equipamento de faixa (preencha)
A24: PJ | B24: Nível do Cone | C24: Tier de Relíquias | D24: Slots de Relíquia | E24: Sobreposições nesta faixa | F24: Total no Cone | G24: Ressonâncias escolhidas | K24: Aviso
A25: =IF(LEN($P$7)>0,$P$7,"PJ 1") | K25: =IF(Z25>0,"O Google leu como fórmula: digite de novo com ' na frente.",IF(AND(ISNUMBER($Q$25),$Q$25>'Campanha'!$B$18),"Cone acima do máximo da faixa (25.1)",IF(AND(ISNUMBER($T$25),$T$25>1),"Mais de 1 Sobreposição nesta faixa (25.2)",IF(AND(ISNUMBER($Q$25),$Q$25>=1,$Q$25<=5),IF(MAX(IF(ISNUMBER($U$25),$U$25,0),IF(ISNUMBER($T$25),$T$25,0))>INDEX('Dados'!$H$468:$H$472,INT($Q$25)),"Acima do teto do Cone (25.2): o Nível "&INT($Q$25)&" aceita até "&INDEX('Dados'!$H$468:$H$472,INT($Q$25)),IF(AND(ISNUMBER($U$25),ISNUMBER($T$25),$U$25<$T$25),"Total no Cone menor que as desta faixa","")),IF(AND(ISNUMBER($U$25),ISNUMBER($T$25),$U$25<$T$25),"Total no Cone menor que as desta faixa",""))))) | Q25: =IF(ISERROR($B$25),"",IF(ISBLANK($B$25),"",$B$25)) | R25: =IF(ISERROR($C$25),"",IF(ISBLANK($C$25),"",$C$25)) | T25: =IF(ISERROR($E$25),"",IF(ISBLANK($E$25),"",$E$25)) | U25: =IF(ISERROR($F$25),"",IF(ISBLANK($F$25),"",$F$25)) | Z25: =ISERROR($B$25)*1+ISERROR($C$25)*1+ISERROR($D$25)*1+ISERROR($E$25)*1+ISERROR($F$25)*1+ISERROR($G$25)*1
A26: =IF(LEN($P$8)>0,$P$8,"PJ 2") | K26: =IF(Z26>0,"O Google leu como fórmula: digite de novo com ' na frente.",IF(AND(ISNUMBER($Q$26),$Q$26>'Campanha'!$B$18),"Cone acima do máximo da faixa (25.1)",IF(AND(ISNUMBER($T$26),$T$26>1),"Mais de 1 Sobreposição nesta faixa (25.2)",IF(AND(ISNUMBER($Q$26),$Q$26>=1,$Q$26<=5),IF(MAX(IF(ISNUMBER($U$26),$U$26,0),IF(ISNUMBER($T$26),$T$26,0))>INDEX('Dados'!$H$468:$H$472,INT($Q$26)),"Acima do teto do Cone (25.2): o Nível "&INT($Q$26)&" aceita até "&INDEX('Dados'!$H$468:$H$472,INT($Q$26)),IF(AND(ISNUMBER($U$26),ISNUMBER($T$26),$U$26<$T$26),"Total no Cone menor que as desta faixa","")),IF(AND(ISNUMBER($U$26),ISNUMBER($T$26),$U$26<$T$26),"Total no Cone menor que as desta faixa",""))))) | Q26: =IF(ISERROR($B$26),"",IF(ISBLANK($B$26),"",$B$26)) | R26: =IF(ISERROR($C$26),"",IF(ISBLANK($C$26),"",$C$26)) | T26: =IF(ISERROR($E$26),"",IF(ISBLANK($E$26),"",$E$26)) | U26: =IF(ISERROR($F$26),"",IF(ISBLANK($F$26),"",$F$26)) | Z26: =ISERROR($B$26)*1+ISERROR($C$26)*1+ISERROR($D$26)*1+ISERROR($E$26)*1+ISERROR($F$26)*1+ISERROR($G$26)*1
A27: =IF(LEN($P$9)>0,$P$9,"PJ 3") | K27: =IF(Z27>0,"O Google leu como fórmula: digite de novo com ' na frente.",IF(AND(ISNUMBER($Q$27),$Q$27>'Campanha'!$B$18),"Cone acima do máximo da faixa (25.1)",IF(AND(ISNUMBER($T$27),$T$27>1),"Mais de 1 Sobreposição nesta faixa (25.2)",IF(AND(ISNUMBER($Q$27),$Q$27>=1,$Q$27<=5),IF(MAX(IF(ISNUMBER($U$27),$U$27,0),IF(ISNUMBER($T$27),$T$27,0))>INDEX('Dados'!$H$468:$H$472,INT($Q$27)),"Acima do teto do Cone (25.2): o Nível "&INT($Q$27)&" aceita até "&INDEX('Dados'!$H$468:$H$472,INT($Q$27)),IF(AND(ISNUMBER($U$27),ISNUMBER($T$27),$U$27<$T$27),"Total no Cone menor que as desta faixa","")),IF(AND(ISNUMBER($U$27),ISNUMBER($T$27),$U$27<$T$27),"Total no Cone menor que as desta faixa",""))))) | Q27: =IF(ISERROR($B$27),"",IF(ISBLANK($B$27),"",$B$27)) | R27: =IF(ISERROR($C$27),"",IF(ISBLANK($C$27),"",$C$27)) | T27: =IF(ISERROR($E$27),"",IF(ISBLANK($E$27),"",$E$27)) | U27: =IF(ISERROR($F$27),"",IF(ISBLANK($F$27),"",$F$27)) | Z27: =ISERROR($B$27)*1+ISERROR($C$27)*1+ISERROR($D$27)*1+ISERROR($E$27)*1+ISERROR($F$27)*1+ISERROR($G$27)*1
A28: =IF(LEN($P$10)>0,$P$10,"PJ 4") | K28: =IF(Z28>0,"O Google leu como fórmula: digite de novo com ' na frente.",IF(AND(ISNUMBER($Q$28),$Q$28>'Campanha'!$B$18),"Cone acima do máximo da faixa (25.1)",IF(AND(ISNUMBER($T$28),$T$28>1),"Mais de 1 Sobreposição nesta faixa (25.2)",IF(AND(ISNUMBER($Q$28),$Q$28>=1,$Q$28<=5),IF(MAX(IF(ISNUMBER($U$28),$U$28,0),IF(ISNUMBER($T$28),$T$28,0))>INDEX('Dados'!$H$468:$H$472,INT($Q$28)),"Acima do teto do Cone (25.2): o Nível "&INT($Q$28)&" aceita até "&INDEX('Dados'!$H$468:$H$472,INT($Q$28)),IF(AND(ISNUMBER($U$28),ISNUMBER($T$28),$U$28<$T$28),"Total no Cone menor que as desta faixa","")),IF(AND(ISNUMBER($U$28),ISNUMBER($T$28),$U$28<$T$28),"Total no Cone menor que as desta faixa",""))))) | Q28: =IF(ISERROR($B$28),"",IF(ISBLANK($B$28),"",$B$28)) | R28: =IF(ISERROR($C$28),"",IF(ISBLANK($C$28),"",$C$28)) | T28: =IF(ISERROR($E$28),"",IF(ISBLANK($E$28),"",$E$28)) | U28: =IF(ISERROR($F$28),"",IF(ISBLANK($F$28),"",$F$28)) | Z28: =ISERROR($B$28)*1+ISERROR($C$28)*1+ISERROR($D$28)*1+ISERROR($E$28)*1+ISERROR($F$28)*1+ISERROR($G$28)*1
A29: =IF(LEN($P$11)>0,$P$11,"PJ 5") | K29: =IF(Z29>0,"O Google leu como fórmula: digite de novo com ' na frente.",IF(AND(ISNUMBER($Q$29),$Q$29>'Campanha'!$B$18),"Cone acima do máximo da faixa (25.1)",IF(AND(ISNUMBER($T$29),$T$29>1),"Mais de 1 Sobreposição nesta faixa (25.2)",IF(AND(ISNUMBER($Q$29),$Q$29>=1,$Q$29<=5),IF(MAX(IF(ISNUMBER($U$29),$U$29,0),IF(ISNUMBER($T$29),$T$29,0))>INDEX('Dados'!$H$468:$H$472,INT($Q$29)),"Acima do teto do Cone (25.2): o Nível "&INT($Q$29)&" aceita até "&INDEX('Dados'!$H$468:$H$472,INT($Q$29)),IF(AND(ISNUMBER($U$29),ISNUMBER($T$29),$U$29<$T$29),"Total no Cone menor que as desta faixa","")),IF(AND(ISNUMBER($U$29),ISNUMBER($T$29),$U$29<$T$29),"Total no Cone menor que as desta faixa",""))))) | Q29: =IF(ISERROR($B$29),"",IF(ISBLANK($B$29),"",$B$29)) | R29: =IF(ISERROR($C$29),"",IF(ISBLANK($C$29),"",$C$29)) | T29: =IF(ISERROR($E$29),"",IF(ISBLANK($E$29),"",$E$29)) | U29: =IF(ISERROR($F$29),"",IF(ISBLANK($F$29),"",$F$29)) | Z29: =ISERROR($B$29)*1+ISERROR($C$29)*1+ISERROR($D$29)*1+ISERROR($E$29)*1+ISERROR($F$29)*1+ISERROR($G$29)*1
A30: =IF(LEN($P$12)>0,$P$12,"PJ 6") | K30: =IF(Z30>0,"O Google leu como fórmula: digite de novo com ' na frente.",IF(AND(ISNUMBER($Q$30),$Q$30>'Campanha'!$B$18),"Cone acima do máximo da faixa (25.1)",IF(AND(ISNUMBER($T$30),$T$30>1),"Mais de 1 Sobreposição nesta faixa (25.2)",IF(AND(ISNUMBER($Q$30),$Q$30>=1,$Q$30<=5),IF(MAX(IF(ISNUMBER($U$30),$U$30,0),IF(ISNUMBER($T$30),$T$30,0))>INDEX('Dados'!$H$468:$H$472,INT($Q$30)),"Acima do teto do Cone (25.2): o Nível "&INT($Q$30)&" aceita até "&INDEX('Dados'!$H$468:$H$472,INT($Q$30)),IF(AND(ISNUMBER($U$30),ISNUMBER($T$30),$U$30<$T$30),"Total no Cone menor que as desta faixa","")),IF(AND(ISNUMBER($U$30),ISNUMBER($T$30),$U$30<$T$30),"Total no Cone menor que as desta faixa",""))))) | Q30: =IF(ISERROR($B$30),"",IF(ISBLANK($B$30),"",$B$30)) | R30: =IF(ISERROR($C$30),"",IF(ISBLANK($C$30),"",$C$30)) | T30: =IF(ISERROR($E$30),"",IF(ISBLANK($E$30),"",$E$30)) | U30: =IF(ISERROR($F$30),"",IF(ISBLANK($F$30),"",$F$30)) | Z30: =ISERROR($B$30)*1+ISERROR($C$30)*1+ISERROR($D$30)*1+ISERROR($E$30)*1+ISERROR($F$30)*1+ISERROR($G$30)*1
A32: G4 · O que a Raça muda no combate (automático)
A33: PJ | B33: Morrendo com Vantagem? | C33: Pode ser Executado? | D33: Esforço? | E33: Descobre Fraqueza | G33: Lembrete da Raça | K33: Aviso
A34: =IF(LEN($P$7)>0,$P$7,"PJ 1") | B34: =IFERROR(INDEX('Dados'!$B$350:$B$356,MATCH($R$7,'Dados'!$A$350:$A$356,0)),"") | C34: =IFERROR(INDEX('Dados'!$C$350:$C$356,MATCH($R$7,'Dados'!$A$350:$A$356,0)),"") | D34: =IFERROR(INDEX('Dados'!$D$350:$D$356,MATCH($R$7,'Dados'!$A$350:$A$356,0)),"") | E34: =IFERROR(INDEX('Dados'!$E$350:$E$356,MATCH($R$7,'Dados'!$A$350:$A$356,0)),"") | G34: =IF($R$7="Vulpes","Raposa Astuta: segunda chance contra a Surpresa (DT 10, 19.3 e 27.3)",IF($R$7="Haloviano","To na sua mente: DT 13 de ativação; a falha gasta o uso (05, 27.3)",IF($R$7="Xianzhouíta","Não pode ser Executado (05, 23.5)",IF($R$7="Intellitron","Descobre Fraqueza com Vantagem e 2 por sucesso (20.2)",IF($R$7="Vidyadhara","Maré que Volta: 1 por Descanso Curto, nível + Vigor PV em si (05)",IF($R$7="Avginiano","Não Foi a Primeira Vez: 1 por combate, metade da duração na falha (05)",IF($R$7="Humano","Esforço: no máximo 1 ponto (05)",""))))))) | K34: =IF(AND(ISNUMBER($Q$25),$Q$25<'Campanha'!$B$18),"Cone abaixo do esperado: encontros ficam mais duros (27.8)",IF(AND(ISNUMBER($R$25),$R$25<IF('Campanha'!$B$17<=6,1,IF('Campanha'!$B$17<=12,2,IF('Campanha'!$B$17<=17,3,4)))),"Tier abaixo do esperado: encontros ficam mais duros (27.8)",IF(AND(ISNUMBER($R$25),$R$25>IF('Campanha'!$B$17<=6,1,IF('Campanha'!$B$17<=12,2,IF('Campanha'!$B$17<=17,3,4)))),"Tier acima do Tier do nível do grupo (25.1, 25.3)","")))
A35: =IF(LEN($P$8)>0,$P$8,"PJ 2") | B35: =IFERROR(INDEX('Dados'!$B$350:$B$356,MATCH($R$8,'Dados'!$A$350:$A$356,0)),"") | C35: =IFERROR(INDEX('Dados'!$C$350:$C$356,MATCH($R$8,'Dados'!$A$350:$A$356,0)),"") | D35: =IFERROR(INDEX('Dados'!$D$350:$D$356,MATCH($R$8,'Dados'!$A$350:$A$356,0)),"") | E35: =IFERROR(INDEX('Dados'!$E$350:$E$356,MATCH($R$8,'Dados'!$A$350:$A$356,0)),"") | G35: =IF($R$8="Vulpes","Raposa Astuta: segunda chance contra a Surpresa (DT 10, 19.3 e 27.3)",IF($R$8="Haloviano","To na sua mente: DT 13 de ativação; a falha gasta o uso (05, 27.3)",IF($R$8="Xianzhouíta","Não pode ser Executado (05, 23.5)",IF($R$8="Intellitron","Descobre Fraqueza com Vantagem e 2 por sucesso (20.2)",IF($R$8="Vidyadhara","Maré que Volta: 1 por Descanso Curto, nível + Vigor PV em si (05)",IF($R$8="Avginiano","Não Foi a Primeira Vez: 1 por combate, metade da duração na falha (05)",IF($R$8="Humano","Esforço: no máximo 1 ponto (05)",""))))))) | K35: =IF(AND(ISNUMBER($Q$26),$Q$26<'Campanha'!$B$18),"Cone abaixo do esperado: encontros ficam mais duros (27.8)",IF(AND(ISNUMBER($R$26),$R$26<IF('Campanha'!$B$17<=6,1,IF('Campanha'!$B$17<=12,2,IF('Campanha'!$B$17<=17,3,4)))),"Tier abaixo do esperado: encontros ficam mais duros (27.8)",IF(AND(ISNUMBER($R$26),$R$26>IF('Campanha'!$B$17<=6,1,IF('Campanha'!$B$17<=12,2,IF('Campanha'!$B$17<=17,3,4)))),"Tier acima do Tier do nível do grupo (25.1, 25.3)","")))
A36: =IF(LEN($P$9)>0,$P$9,"PJ 3") | B36: =IFERROR(INDEX('Dados'!$B$350:$B$356,MATCH($R$9,'Dados'!$A$350:$A$356,0)),"") | C36: =IFERROR(INDEX('Dados'!$C$350:$C$356,MATCH($R$9,'Dados'!$A$350:$A$356,0)),"") | D36: =IFERROR(INDEX('Dados'!$D$350:$D$356,MATCH($R$9,'Dados'!$A$350:$A$356,0)),"") | E36: =IFERROR(INDEX('Dados'!$E$350:$E$356,MATCH($R$9,'Dados'!$A$350:$A$356,0)),"") | G36: =IF($R$9="Vulpes","Raposa Astuta: segunda chance contra a Surpresa (DT 10, 19.3 e 27.3)",IF($R$9="Haloviano","To na sua mente: DT 13 de ativação; a falha gasta o uso (05, 27.3)",IF($R$9="Xianzhouíta","Não pode ser Executado (05, 23.5)",IF($R$9="Intellitron","Descobre Fraqueza com Vantagem e 2 por sucesso (20.2)",IF($R$9="Vidyadhara","Maré que Volta: 1 por Descanso Curto, nível + Vigor PV em si (05)",IF($R$9="Avginiano","Não Foi a Primeira Vez: 1 por combate, metade da duração na falha (05)",IF($R$9="Humano","Esforço: no máximo 1 ponto (05)",""))))))) | K36: =IF(AND(ISNUMBER($Q$27),$Q$27<'Campanha'!$B$18),"Cone abaixo do esperado: encontros ficam mais duros (27.8)",IF(AND(ISNUMBER($R$27),$R$27<IF('Campanha'!$B$17<=6,1,IF('Campanha'!$B$17<=12,2,IF('Campanha'!$B$17<=17,3,4)))),"Tier abaixo do esperado: encontros ficam mais duros (27.8)",IF(AND(ISNUMBER($R$27),$R$27>IF('Campanha'!$B$17<=6,1,IF('Campanha'!$B$17<=12,2,IF('Campanha'!$B$17<=17,3,4)))),"Tier acima do Tier do nível do grupo (25.1, 25.3)","")))
A37: =IF(LEN($P$10)>0,$P$10,"PJ 4") | B37: =IFERROR(INDEX('Dados'!$B$350:$B$356,MATCH($R$10,'Dados'!$A$350:$A$356,0)),"") | C37: =IFERROR(INDEX('Dados'!$C$350:$C$356,MATCH($R$10,'Dados'!$A$350:$A$356,0)),"") | D37: =IFERROR(INDEX('Dados'!$D$350:$D$356,MATCH($R$10,'Dados'!$A$350:$A$356,0)),"") | E37: =IFERROR(INDEX('Dados'!$E$350:$E$356,MATCH($R$10,'Dados'!$A$350:$A$356,0)),"") | G37: =IF($R$10="Vulpes","Raposa Astuta: segunda chance contra a Surpresa (DT 10, 19.3 e 27.3)",IF($R$10="Haloviano","To na sua mente: DT 13 de ativação; a falha gasta o uso (05, 27.3)",IF($R$10="Xianzhouíta","Não pode ser Executado (05, 23.5)",IF($R$10="Intellitron","Descobre Fraqueza com Vantagem e 2 por sucesso (20.2)",IF($R$10="Vidyadhara","Maré que Volta: 1 por Descanso Curto, nível + Vigor PV em si (05)",IF($R$10="Avginiano","Não Foi a Primeira Vez: 1 por combate, metade da duração na falha (05)",IF($R$10="Humano","Esforço: no máximo 1 ponto (05)",""))))))) | K37: =IF(AND(ISNUMBER($Q$28),$Q$28<'Campanha'!$B$18),"Cone abaixo do esperado: encontros ficam mais duros (27.8)",IF(AND(ISNUMBER($R$28),$R$28<IF('Campanha'!$B$17<=6,1,IF('Campanha'!$B$17<=12,2,IF('Campanha'!$B$17<=17,3,4)))),"Tier abaixo do esperado: encontros ficam mais duros (27.8)",IF(AND(ISNUMBER($R$28),$R$28>IF('Campanha'!$B$17<=6,1,IF('Campanha'!$B$17<=12,2,IF('Campanha'!$B$17<=17,3,4)))),"Tier acima do Tier do nível do grupo (25.1, 25.3)","")))
A38: =IF(LEN($P$11)>0,$P$11,"PJ 5") | B38: =IFERROR(INDEX('Dados'!$B$350:$B$356,MATCH($R$11,'Dados'!$A$350:$A$356,0)),"") | C38: =IFERROR(INDEX('Dados'!$C$350:$C$356,MATCH($R$11,'Dados'!$A$350:$A$356,0)),"") | D38: =IFERROR(INDEX('Dados'!$D$350:$D$356,MATCH($R$11,'Dados'!$A$350:$A$356,0)),"") | E38: =IFERROR(INDEX('Dados'!$E$350:$E$356,MATCH($R$11,'Dados'!$A$350:$A$356,0)),"") | G38: =IF($R$11="Vulpes","Raposa Astuta: segunda chance contra a Surpresa (DT 10, 19.3 e 27.3)",IF($R$11="Haloviano","To na sua mente: DT 13 de ativação; a falha gasta o uso (05, 27.3)",IF($R$11="Xianzhouíta","Não pode ser Executado (05, 23.5)",IF($R$11="Intellitron","Descobre Fraqueza com Vantagem e 2 por sucesso (20.2)",IF($R$11="Vidyadhara","Maré que Volta: 1 por Descanso Curto, nível + Vigor PV em si (05)",IF($R$11="Avginiano","Não Foi a Primeira Vez: 1 por combate, metade da duração na falha (05)",IF($R$11="Humano","Esforço: no máximo 1 ponto (05)",""))))))) | K38: =IF(AND(ISNUMBER($Q$29),$Q$29<'Campanha'!$B$18),"Cone abaixo do esperado: encontros ficam mais duros (27.8)",IF(AND(ISNUMBER($R$29),$R$29<IF('Campanha'!$B$17<=6,1,IF('Campanha'!$B$17<=12,2,IF('Campanha'!$B$17<=17,3,4)))),"Tier abaixo do esperado: encontros ficam mais duros (27.8)",IF(AND(ISNUMBER($R$29),$R$29>IF('Campanha'!$B$17<=6,1,IF('Campanha'!$B$17<=12,2,IF('Campanha'!$B$17<=17,3,4)))),"Tier acima do Tier do nível do grupo (25.1, 25.3)","")))
A39: =IF(LEN($P$12)>0,$P$12,"PJ 6") | B39: =IFERROR(INDEX('Dados'!$B$350:$B$356,MATCH($R$12,'Dados'!$A$350:$A$356,0)),"") | C39: =IFERROR(INDEX('Dados'!$C$350:$C$356,MATCH($R$12,'Dados'!$A$350:$A$356,0)),"") | D39: =IFERROR(INDEX('Dados'!$D$350:$D$356,MATCH($R$12,'Dados'!$A$350:$A$356,0)),"") | E39: =IFERROR(INDEX('Dados'!$E$350:$E$356,MATCH($R$12,'Dados'!$A$350:$A$356,0)),"") | G39: =IF($R$12="Vulpes","Raposa Astuta: segunda chance contra a Surpresa (DT 10, 19.3 e 27.3)",IF($R$12="Haloviano","To na sua mente: DT 13 de ativação; a falha gasta o uso (05, 27.3)",IF($R$12="Xianzhouíta","Não pode ser Executado (05, 23.5)",IF($R$12="Intellitron","Descobre Fraqueza com Vantagem e 2 por sucesso (20.2)",IF($R$12="Vidyadhara","Maré que Volta: 1 por Descanso Curto, nível + Vigor PV em si (05)",IF($R$12="Avginiano","Não Foi a Primeira Vez: 1 por combate, metade da duração na falha (05)",IF($R$12="Humano","Esforço: no máximo 1 ponto (05)",""))))))) | K39: =IF(AND(ISNUMBER($Q$30),$Q$30<'Campanha'!$B$18),"Cone abaixo do esperado: encontros ficam mais duros (27.8)",IF(AND(ISNUMBER($R$30),$R$30<IF('Campanha'!$B$17<=6,1,IF('Campanha'!$B$17<=12,2,IF('Campanha'!$B$17<=17,3,4)))),"Tier abaixo do esperado: encontros ficam mais duros (27.8)",IF(AND(ISNUMBER($R$30),$R$30>IF('Campanha'!$B$17<=6,1,IF('Campanha'!$B$17<=12,2,IF('Campanha'!$B$17<=17,3,4)))),"Tier acima do Tier do nível do grupo (25.1, 25.3)","")))
A41: G5 · Testes de Resistência e Perícias de mesa (preencha o total da ficha: o que soma ao d20)
A42: PJ | B42: Potência Física | C42: Reflexos | D42: Resistência Física | E42: Resistência Mental | F42: Percepção Mental | G42: Força de Vontade | H42: Percepção | I42: Intuição | J42: Furtividade | K42: Aviso
A43: =IF(LEN($P$7)>0,$P$7,"PJ 1") | K43: =IF(Z43>0,"O Google leu como fórmula: digite de novo com ' na frente.",IF(OR(AND(ISNUMBER($Q$43),OR($Q$43<-5,$Q$43>40)),AND(ISNUMBER($R$43),OR($R$43<-5,$R$43>40)),AND(ISNUMBER($S$43),OR($S$43<-5,$S$43>40)),AND(ISNUMBER($T$43),OR($T$43<-5,$T$43>40)),AND(ISNUMBER($U$43),OR($U$43<-5,$U$43>40)),AND(ISNUMBER($V$43),OR($V$43<-5,$V$43>40)),AND(ISNUMBER($W$43),OR($W$43<-5,$W$43>40)),AND(ISNUMBER($X$43),OR($X$43<-5,$X$43>40)),AND(ISNUMBER($Y$43),OR($Y$43<-5,$Y$43>40))),"Total fora de −5 a +40: confira na ficha","")) | Q43: =IF(ISERROR($B$43),"",IF(ISBLANK($B$43),"",$B$43)) | R43: =IF(ISERROR($C$43),"",IF(ISBLANK($C$43),"",$C$43)) | S43: =IF(ISERROR($D$43),"",IF(ISBLANK($D$43),"",$D$43)) | T43: =IF(ISERROR($E$43),"",IF(ISBLANK($E$43),"",$E$43)) | U43: =IF(ISERROR($F$43),"",IF(ISBLANK($F$43),"",$F$43)) | V43: =IF(ISERROR($G$43),"",IF(ISBLANK($G$43),"",$G$43)) | W43: =IF(ISERROR($H$43),"",IF(ISBLANK($H$43),"",$H$43)) | X43: =IF(ISERROR($I$43),"",IF(ISBLANK($I$43),"",$I$43)) | Y43: =IF(ISERROR($J$43),"",IF(ISBLANK($J$43),"",$J$43)) | Z43: =ISERROR($B$43)*1+ISERROR($C$43)*1+ISERROR($D$43)*1+ISERROR($E$43)*1+ISERROR($F$43)*1+ISERROR($G$43)*1+ISERROR($H$43)*1+ISERROR($I$43)*1+ISERROR($J$43)*1
A44: =IF(LEN($P$8)>0,$P$8,"PJ 2") | K44: =IF(Z44>0,"O Google leu como fórmula: digite de novo com ' na frente.",IF(OR(AND(ISNUMBER($Q$44),OR($Q$44<-5,$Q$44>40)),AND(ISNUMBER($R$44),OR($R$44<-5,$R$44>40)),AND(ISNUMBER($S$44),OR($S$44<-5,$S$44>40)),AND(ISNUMBER($T$44),OR($T$44<-5,$T$44>40)),AND(ISNUMBER($U$44),OR($U$44<-5,$U$44>40)),AND(ISNUMBER($V$44),OR($V$44<-5,$V$44>40)),AND(ISNUMBER($W$44),OR($W$44<-5,$W$44>40)),AND(ISNUMBER($X$44),OR($X$44<-5,$X$44>40)),AND(ISNUMBER($Y$44),OR($Y$44<-5,$Y$44>40))),"Total fora de −5 a +40: confira na ficha","")) | Q44: =IF(ISERROR($B$44),"",IF(ISBLANK($B$44),"",$B$44)) | R44: =IF(ISERROR($C$44),"",IF(ISBLANK($C$44),"",$C$44)) | S44: =IF(ISERROR($D$44),"",IF(ISBLANK($D$44),"",$D$44)) | T44: =IF(ISERROR($E$44),"",IF(ISBLANK($E$44),"",$E$44)) | U44: =IF(ISERROR($F$44),"",IF(ISBLANK($F$44),"",$F$44)) | V44: =IF(ISERROR($G$44),"",IF(ISBLANK($G$44),"",$G$44)) | W44: =IF(ISERROR($H$44),"",IF(ISBLANK($H$44),"",$H$44)) | X44: =IF(ISERROR($I$44),"",IF(ISBLANK($I$44),"",$I$44)) | Y44: =IF(ISERROR($J$44),"",IF(ISBLANK($J$44),"",$J$44)) | Z44: =ISERROR($B$44)*1+ISERROR($C$44)*1+ISERROR($D$44)*1+ISERROR($E$44)*1+ISERROR($F$44)*1+ISERROR($G$44)*1+ISERROR($H$44)*1+ISERROR($I$44)*1+ISERROR($J$44)*1
A45: =IF(LEN($P$9)>0,$P$9,"PJ 3") | K45: =IF(Z45>0,"O Google leu como fórmula: digite de novo com ' na frente.",IF(OR(AND(ISNUMBER($Q$45),OR($Q$45<-5,$Q$45>40)),AND(ISNUMBER($R$45),OR($R$45<-5,$R$45>40)),AND(ISNUMBER($S$45),OR($S$45<-5,$S$45>40)),AND(ISNUMBER($T$45),OR($T$45<-5,$T$45>40)),AND(ISNUMBER($U$45),OR($U$45<-5,$U$45>40)),AND(ISNUMBER($V$45),OR($V$45<-5,$V$45>40)),AND(ISNUMBER($W$45),OR($W$45<-5,$W$45>40)),AND(ISNUMBER($X$45),OR($X$45<-5,$X$45>40)),AND(ISNUMBER($Y$45),OR($Y$45<-5,$Y$45>40))),"Total fora de −5 a +40: confira na ficha","")) | Q45: =IF(ISERROR($B$45),"",IF(ISBLANK($B$45),"",$B$45)) | R45: =IF(ISERROR($C$45),"",IF(ISBLANK($C$45),"",$C$45)) | S45: =IF(ISERROR($D$45),"",IF(ISBLANK($D$45),"",$D$45)) | T45: =IF(ISERROR($E$45),"",IF(ISBLANK($E$45),"",$E$45)) | U45: =IF(ISERROR($F$45),"",IF(ISBLANK($F$45),"",$F$45)) | V45: =IF(ISERROR($G$45),"",IF(ISBLANK($G$45),"",$G$45)) | W45: =IF(ISERROR($H$45),"",IF(ISBLANK($H$45),"",$H$45)) | X45: =IF(ISERROR($I$45),"",IF(ISBLANK($I$45),"",$I$45)) | Y45: =IF(ISERROR($J$45),"",IF(ISBLANK($J$45),"",$J$45)) | Z45: =ISERROR($B$45)*1+ISERROR($C$45)*1+ISERROR($D$45)*1+ISERROR($E$45)*1+ISERROR($F$45)*1+ISERROR($G$45)*1+ISERROR($H$45)*1+ISERROR($I$45)*1+ISERROR($J$45)*1
A46: =IF(LEN($P$10)>0,$P$10,"PJ 4") | K46: =IF(Z46>0,"O Google leu como fórmula: digite de novo com ' na frente.",IF(OR(AND(ISNUMBER($Q$46),OR($Q$46<-5,$Q$46>40)),AND(ISNUMBER($R$46),OR($R$46<-5,$R$46>40)),AND(ISNUMBER($S$46),OR($S$46<-5,$S$46>40)),AND(ISNUMBER($T$46),OR($T$46<-5,$T$46>40)),AND(ISNUMBER($U$46),OR($U$46<-5,$U$46>40)),AND(ISNUMBER($V$46),OR($V$46<-5,$V$46>40)),AND(ISNUMBER($W$46),OR($W$46<-5,$W$46>40)),AND(ISNUMBER($X$46),OR($X$46<-5,$X$46>40)),AND(ISNUMBER($Y$46),OR($Y$46<-5,$Y$46>40))),"Total fora de −5 a +40: confira na ficha","")) | Q46: =IF(ISERROR($B$46),"",IF(ISBLANK($B$46),"",$B$46)) | R46: =IF(ISERROR($C$46),"",IF(ISBLANK($C$46),"",$C$46)) | S46: =IF(ISERROR($D$46),"",IF(ISBLANK($D$46),"",$D$46)) | T46: =IF(ISERROR($E$46),"",IF(ISBLANK($E$46),"",$E$46)) | U46: =IF(ISERROR($F$46),"",IF(ISBLANK($F$46),"",$F$46)) | V46: =IF(ISERROR($G$46),"",IF(ISBLANK($G$46),"",$G$46)) | W46: =IF(ISERROR($H$46),"",IF(ISBLANK($H$46),"",$H$46)) | X46: =IF(ISERROR($I$46),"",IF(ISBLANK($I$46),"",$I$46)) | Y46: =IF(ISERROR($J$46),"",IF(ISBLANK($J$46),"",$J$46)) | Z46: =ISERROR($B$46)*1+ISERROR($C$46)*1+ISERROR($D$46)*1+ISERROR($E$46)*1+ISERROR($F$46)*1+ISERROR($G$46)*1+ISERROR($H$46)*1+ISERROR($I$46)*1+ISERROR($J$46)*1
A47: =IF(LEN($P$11)>0,$P$11,"PJ 5") | K47: =IF(Z47>0,"O Google leu como fórmula: digite de novo com ' na frente.",IF(OR(AND(ISNUMBER($Q$47),OR($Q$47<-5,$Q$47>40)),AND(ISNUMBER($R$47),OR($R$47<-5,$R$47>40)),AND(ISNUMBER($S$47),OR($S$47<-5,$S$47>40)),AND(ISNUMBER($T$47),OR($T$47<-5,$T$47>40)),AND(ISNUMBER($U$47),OR($U$47<-5,$U$47>40)),AND(ISNUMBER($V$47),OR($V$47<-5,$V$47>40)),AND(ISNUMBER($W$47),OR($W$47<-5,$W$47>40)),AND(ISNUMBER($X$47),OR($X$47<-5,$X$47>40)),AND(ISNUMBER($Y$47),OR($Y$47<-5,$Y$47>40))),"Total fora de −5 a +40: confira na ficha","")) | Q47: =IF(ISERROR($B$47),"",IF(ISBLANK($B$47),"",$B$47)) | R47: =IF(ISERROR($C$47),"",IF(ISBLANK($C$47),"",$C$47)) | S47: =IF(ISERROR($D$47),"",IF(ISBLANK($D$47),"",$D$47)) | T47: =IF(ISERROR($E$47),"",IF(ISBLANK($E$47),"",$E$47)) | U47: =IF(ISERROR($F$47),"",IF(ISBLANK($F$47),"",$F$47)) | V47: =IF(ISERROR($G$47),"",IF(ISBLANK($G$47),"",$G$47)) | W47: =IF(ISERROR($H$47),"",IF(ISBLANK($H$47),"",$H$47)) | X47: =IF(ISERROR($I$47),"",IF(ISBLANK($I$47),"",$I$47)) | Y47: =IF(ISERROR($J$47),"",IF(ISBLANK($J$47),"",$J$47)) | Z47: =ISERROR($B$47)*1+ISERROR($C$47)*1+ISERROR($D$47)*1+ISERROR($E$47)*1+ISERROR($F$47)*1+ISERROR($G$47)*1+ISERROR($H$47)*1+ISERROR($I$47)*1+ISERROR($J$47)*1
A48: =IF(LEN($P$12)>0,$P$12,"PJ 6") | K48: =IF(Z48>0,"O Google leu como fórmula: digite de novo com ' na frente.",IF(OR(AND(ISNUMBER($Q$48),OR($Q$48<-5,$Q$48>40)),AND(ISNUMBER($R$48),OR($R$48<-5,$R$48>40)),AND(ISNUMBER($S$48),OR($S$48<-5,$S$48>40)),AND(ISNUMBER($T$48),OR($T$48<-5,$T$48>40)),AND(ISNUMBER($U$48),OR($U$48<-5,$U$48>40)),AND(ISNUMBER($V$48),OR($V$48<-5,$V$48>40)),AND(ISNUMBER($W$48),OR($W$48<-5,$W$48>40)),AND(ISNUMBER($X$48),OR($X$48<-5,$X$48>40)),AND(ISNUMBER($Y$48),OR($Y$48<-5,$Y$48>40))),"Total fora de −5 a +40: confira na ficha","")) | Q48: =IF(ISERROR($B$48),"",IF(ISBLANK($B$48),"",$B$48)) | R48: =IF(ISERROR($C$48),"",IF(ISBLANK($C$48),"",$C$48)) | S48: =IF(ISERROR($D$48),"",IF(ISBLANK($D$48),"",$D$48)) | T48: =IF(ISERROR($E$48),"",IF(ISBLANK($E$48),"",$E$48)) | U48: =IF(ISERROR($F$48),"",IF(ISBLANK($F$48),"",$F$48)) | V48: =IF(ISERROR($G$48),"",IF(ISBLANK($G$48),"",$G$48)) | W48: =IF(ISERROR($H$48),"",IF(ISBLANK($H$48),"",$H$48)) | X48: =IF(ISERROR($I$48),"",IF(ISBLANK($I$48),"",$I$48)) | Y48: =IF(ISERROR($J$48),"",IF(ISBLANK($J$48),"",$J$48)) | Z48: =ISERROR($B$48)*1+ISERROR($C$48)*1+ISERROR($D$48)*1+ISERROR($E$48)*1+ISERROR($F$48)*1+ISERROR($G$48)*1+ISERROR($H$48)*1+ISERROR($I$48)*1+ISERROR($J$48)*1
A50: G6 · Descobrir Fraqueza (20.2), conversar e o que o Mestre lembra (preencha)
A51: PJ | B51: Pesquisa | C51: Ciência | D51: Sintonia | E51: Persuasão | F51: Traços e passivas que o Mestre lembra | K51: Aviso
A52: =IF(LEN($P$7)>0,$P$7,"PJ 1") | K52: =IF(Z52>0,"O Google leu como fórmula: digite de novo com ' na frente.",IF(OR(AND(ISNUMBER($Q$52),OR($Q$52<-5,$Q$52>40)),AND(ISNUMBER($R$52),OR($R$52<-5,$R$52>40)),AND(ISNUMBER($S$52),OR($S$52<-5,$S$52>40)),AND(ISNUMBER($T$52),OR($T$52<-5,$T$52>40))),"Total fora de −5 a +40: confira na ficha","")) | N52: =IF(SUMPRODUCT(ISNUMBER($Q$52:$S$52)*1)=0,"",MAX($Q$52:$S$52)) | Q52: =IF(ISERROR($B$52),"",IF(ISBLANK($B$52),"",$B$52)) | R52: =IF(ISERROR($C$52),"",IF(ISBLANK($C$52),"",$C$52)) | S52: =IF(ISERROR($D$52),"",IF(ISBLANK($D$52),"",$D$52)) | T52: =IF(ISERROR($E$52),"",IF(ISBLANK($E$52),"",$E$52)) | Z52: =ISERROR($B$52)*1+ISERROR($C$52)*1+ISERROR($D$52)*1+ISERROR($E$52)*1+ISERROR($F$52)*1
A53: =IF(LEN($P$8)>0,$P$8,"PJ 2") | K53: =IF(Z53>0,"O Google leu como fórmula: digite de novo com ' na frente.",IF(OR(AND(ISNUMBER($Q$53),OR($Q$53<-5,$Q$53>40)),AND(ISNUMBER($R$53),OR($R$53<-5,$R$53>40)),AND(ISNUMBER($S$53),OR($S$53<-5,$S$53>40)),AND(ISNUMBER($T$53),OR($T$53<-5,$T$53>40))),"Total fora de −5 a +40: confira na ficha","")) | N53: =IF(SUMPRODUCT(ISNUMBER($Q$53:$S$53)*1)=0,"",MAX($Q$53:$S$53)) | Q53: =IF(ISERROR($B$53),"",IF(ISBLANK($B$53),"",$B$53)) | R53: =IF(ISERROR($C$53),"",IF(ISBLANK($C$53),"",$C$53)) | S53: =IF(ISERROR($D$53),"",IF(ISBLANK($D$53),"",$D$53)) | T53: =IF(ISERROR($E$53),"",IF(ISBLANK($E$53),"",$E$53)) | Z53: =ISERROR($B$53)*1+ISERROR($C$53)*1+ISERROR($D$53)*1+ISERROR($E$53)*1+ISERROR($F$53)*1
A54: =IF(LEN($P$9)>0,$P$9,"PJ 3") | K54: =IF(Z54>0,"O Google leu como fórmula: digite de novo com ' na frente.",IF(OR(AND(ISNUMBER($Q$54),OR($Q$54<-5,$Q$54>40)),AND(ISNUMBER($R$54),OR($R$54<-5,$R$54>40)),AND(ISNUMBER($S$54),OR($S$54<-5,$S$54>40)),AND(ISNUMBER($T$54),OR($T$54<-5,$T$54>40))),"Total fora de −5 a +40: confira na ficha","")) | N54: =IF(SUMPRODUCT(ISNUMBER($Q$54:$S$54)*1)=0,"",MAX($Q$54:$S$54)) | Q54: =IF(ISERROR($B$54),"",IF(ISBLANK($B$54),"",$B$54)) | R54: =IF(ISERROR($C$54),"",IF(ISBLANK($C$54),"",$C$54)) | S54: =IF(ISERROR($D$54),"",IF(ISBLANK($D$54),"",$D$54)) | T54: =IF(ISERROR($E$54),"",IF(ISBLANK($E$54),"",$E$54)) | Z54: =ISERROR($B$54)*1+ISERROR($C$54)*1+ISERROR($D$54)*1+ISERROR($E$54)*1+ISERROR($F$54)*1
A55: =IF(LEN($P$10)>0,$P$10,"PJ 4") | K55: =IF(Z55>0,"O Google leu como fórmula: digite de novo com ' na frente.",IF(OR(AND(ISNUMBER($Q$55),OR($Q$55<-5,$Q$55>40)),AND(ISNUMBER($R$55),OR($R$55<-5,$R$55>40)),AND(ISNUMBER($S$55),OR($S$55<-5,$S$55>40)),AND(ISNUMBER($T$55),OR($T$55<-5,$T$55>40))),"Total fora de −5 a +40: confira na ficha","")) | N55: =IF(SUMPRODUCT(ISNUMBER($Q$55:$S$55)*1)=0,"",MAX($Q$55:$S$55)) | Q55: =IF(ISERROR($B$55),"",IF(ISBLANK($B$55),"",$B$55)) | R55: =IF(ISERROR($C$55),"",IF(ISBLANK($C$55),"",$C$55)) | S55: =IF(ISERROR($D$55),"",IF(ISBLANK($D$55),"",$D$55)) | T55: =IF(ISERROR($E$55),"",IF(ISBLANK($E$55),"",$E$55)) | Z55: =ISERROR($B$55)*1+ISERROR($C$55)*1+ISERROR($D$55)*1+ISERROR($E$55)*1+ISERROR($F$55)*1
A56: =IF(LEN($P$11)>0,$P$11,"PJ 5") | K56: =IF(Z56>0,"O Google leu como fórmula: digite de novo com ' na frente.",IF(OR(AND(ISNUMBER($Q$56),OR($Q$56<-5,$Q$56>40)),AND(ISNUMBER($R$56),OR($R$56<-5,$R$56>40)),AND(ISNUMBER($S$56),OR($S$56<-5,$S$56>40)),AND(ISNUMBER($T$56),OR($T$56<-5,$T$56>40))),"Total fora de −5 a +40: confira na ficha","")) | N56: =IF(SUMPRODUCT(ISNUMBER($Q$56:$S$56)*1)=0,"",MAX($Q$56:$S$56)) | Q56: =IF(ISERROR($B$56),"",IF(ISBLANK($B$56),"",$B$56)) | R56: =IF(ISERROR($C$56),"",IF(ISBLANK($C$56),"",$C$56)) | S56: =IF(ISERROR($D$56),"",IF(ISBLANK($D$56),"",$D$56)) | T56: =IF(ISERROR($E$56),"",IF(ISBLANK($E$56),"",$E$56)) | Z56: =ISERROR($B$56)*1+ISERROR($C$56)*1+ISERROR($D$56)*1+ISERROR($E$56)*1+ISERROR($F$56)*1
A57: =IF(LEN($P$12)>0,$P$12,"PJ 6") | K57: =IF(Z57>0,"O Google leu como fórmula: digite de novo com ' na frente.",IF(OR(AND(ISNUMBER($Q$57),OR($Q$57<-5,$Q$57>40)),AND(ISNUMBER($R$57),OR($R$57<-5,$R$57>40)),AND(ISNUMBER($S$57),OR($S$57<-5,$S$57>40)),AND(ISNUMBER($T$57),OR($T$57<-5,$T$57>40))),"Total fora de −5 a +40: confira na ficha","")) | N57: =IF(SUMPRODUCT(ISNUMBER($Q$57:$S$57)*1)=0,"",MAX($Q$57:$S$57)) | Q57: =IF(ISERROR($B$57),"",IF(ISBLANK($B$57),"",$B$57)) | R57: =IF(ISERROR($C$57),"",IF(ISBLANK($C$57),"",$C$57)) | S57: =IF(ISERROR($D$57),"",IF(ISBLANK($D$57),"",$D$57)) | T57: =IF(ISERROR($E$57),"",IF(ISBLANK($E$57),"",$E$57)) | Z57: =ISERROR($B$57)*1+ISERROR($C$57)*1+ISERROR($D$57)*1+ISERROR($E$57)*1+ISERROR($F$57)*1
A59: G7 · Memoespírito ligado a cada PJ (Recordação, capítulo 11; preencha, da ficha do jogador, 29.9)
A60: PJ dono | B60: Tem? (Sim/Não) | C60: Nome dele | D60: PV máx. | E60: Defesa | F60: VEL | G60: RD | H60: Pontos em Discernimento | I60: Pontos em Agilidade | J60: Pontos em Vigor | K60: Aviso
A61: =IF(LEN($P$7)>0,$P$7,"PJ 1") | K61: =IF(Z61>0,"O Google leu como fórmula: escolha de novo ou digite com ' na frente.",IF($Q$61="Sim",IF(LEN($P$7)=0,"PJ sem nome em G1: o Memoespírito não entra no Combate",IF(AND(LEN($S$7)>0,$S$7<>"A Recordação"),"O Memoespírito é da Recordação (11.1); este PJ é de outro Caminho",IF(AND(ISNUMBER($U$61),$U$61<10+IF(ISNUMBER($X$61),$X$61,0)+1),"VEL abaixo de 10 + Agilidade + 1 (11.4): confira na ficha",IF(AND(ISNUMBER($T$61),$T$61<10+IF(ISNUMBER($X$61),$X$61,0)+'Campanha'!$B$20),"Defesa abaixo de 10 + Agilidade + Eficiência (11.4): confira na ficha",IF(AND(ISNUMBER($S$61),$S$61<8*'Campanha'!$B$17+3*IF(ISNUMBER($Y$61),$Y$61,0)),"PV abaixo de 8 × nível + 3 × Vigor (11.4): confira na ficha",IF(IF(ISNUMBER($X$61),$X$61,0)+IF(ISNUMBER($W$61),$W$61,0)+IF(ISNUMBER($Y$61),$Y$61,0)>12+INT('Campanha'!$B$17/2),"Pontos acima de 12 + 1 a cada 2 níveis (11.3)","")))))),IF(LEN($R$61&$S$61&$T$61&$U$61&$V$61&$X$61&$W$61&$Y$61)>0,"Marque Sim em Tem? para o Memoespírito aparecer no Combate",""))) | Q61: =IF(ISERROR($B$61),"",IF(ISBLANK($B$61),"",$B$61)) | R61: =IF(ISERROR($C$61),"",IF(ISBLANK($C$61),"",$C$61)) | S61: =IF(ISERROR($D$61),"",IF(ISBLANK($D$61),"",$D$61)) | T61: =IF(ISERROR($E$61),"",IF(ISBLANK($E$61),"",$E$61)) | U61: =IF(ISERROR($F$61),"",IF(ISBLANK($F$61),"",$F$61)) | V61: =IF(ISERROR($G$61),"",IF(ISBLANK($G$61),"",$G$61)) | W61: =IF(ISERROR($H$61),"",IF(ISBLANK($H$61),"",$H$61)) | X61: =IF(ISERROR($I$61),"",IF(ISBLANK($I$61),"",$I$61)) | Y61: =IF(ISERROR($J$61),"",IF(ISBLANK($J$61),"",$J$61)) | Z61: =ISERROR($B$61)*1+ISERROR($C$61)*1+ISERROR($D$61)*1+ISERROR($E$61)*1+ISERROR($F$61)*1+ISERROR($G$61)*1+ISERROR($H$61)*1+ISERROR($I$61)*1+ISERROR($J$61)*1
A62: =IF(LEN($P$8)>0,$P$8,"PJ 2") | K62: =IF(Z62>0,"O Google leu como fórmula: escolha de novo ou digite com ' na frente.",IF($Q$62="Sim",IF(LEN($P$8)=0,"PJ sem nome em G1: o Memoespírito não entra no Combate",IF(AND(LEN($S$8)>0,$S$8<>"A Recordação"),"O Memoespírito é da Recordação (11.1); este PJ é de outro Caminho",IF(AND(ISNUMBER($U$62),$U$62<10+IF(ISNUMBER($X$62),$X$62,0)+1),"VEL abaixo de 10 + Agilidade + 1 (11.4): confira na ficha",IF(AND(ISNUMBER($T$62),$T$62<10+IF(ISNUMBER($X$62),$X$62,0)+'Campanha'!$B$20),"Defesa abaixo de 10 + Agilidade + Eficiência (11.4): confira na ficha",IF(AND(ISNUMBER($S$62),$S$62<8*'Campanha'!$B$17+3*IF(ISNUMBER($Y$62),$Y$62,0)),"PV abaixo de 8 × nível + 3 × Vigor (11.4): confira na ficha",IF(IF(ISNUMBER($X$62),$X$62,0)+IF(ISNUMBER($W$62),$W$62,0)+IF(ISNUMBER($Y$62),$Y$62,0)>12+INT('Campanha'!$B$17/2),"Pontos acima de 12 + 1 a cada 2 níveis (11.3)","")))))),IF(LEN($R$62&$S$62&$T$62&$U$62&$V$62&$X$62&$W$62&$Y$62)>0,"Marque Sim em Tem? para o Memoespírito aparecer no Combate",""))) | Q62: =IF(ISERROR($B$62),"",IF(ISBLANK($B$62),"",$B$62)) | R62: =IF(ISERROR($C$62),"",IF(ISBLANK($C$62),"",$C$62)) | S62: =IF(ISERROR($D$62),"",IF(ISBLANK($D$62),"",$D$62)) | T62: =IF(ISERROR($E$62),"",IF(ISBLANK($E$62),"",$E$62)) | U62: =IF(ISERROR($F$62),"",IF(ISBLANK($F$62),"",$F$62)) | V62: =IF(ISERROR($G$62),"",IF(ISBLANK($G$62),"",$G$62)) | W62: =IF(ISERROR($H$62),"",IF(ISBLANK($H$62),"",$H$62)) | X62: =IF(ISERROR($I$62),"",IF(ISBLANK($I$62),"",$I$62)) | Y62: =IF(ISERROR($J$62),"",IF(ISBLANK($J$62),"",$J$62)) | Z62: =ISERROR($B$62)*1+ISERROR($C$62)*1+ISERROR($D$62)*1+ISERROR($E$62)*1+ISERROR($F$62)*1+ISERROR($G$62)*1+ISERROR($H$62)*1+ISERROR($I$62)*1+ISERROR($J$62)*1
A63: =IF(LEN($P$9)>0,$P$9,"PJ 3") | K63: =IF(Z63>0,"O Google leu como fórmula: escolha de novo ou digite com ' na frente.",IF($Q$63="Sim",IF(LEN($P$9)=0,"PJ sem nome em G1: o Memoespírito não entra no Combate",IF(AND(LEN($S$9)>0,$S$9<>"A Recordação"),"O Memoespírito é da Recordação (11.1); este PJ é de outro Caminho",IF(AND(ISNUMBER($U$63),$U$63<10+IF(ISNUMBER($X$63),$X$63,0)+1),"VEL abaixo de 10 + Agilidade + 1 (11.4): confira na ficha",IF(AND(ISNUMBER($T$63),$T$63<10+IF(ISNUMBER($X$63),$X$63,0)+'Campanha'!$B$20),"Defesa abaixo de 10 + Agilidade + Eficiência (11.4): confira na ficha",IF(AND(ISNUMBER($S$63),$S$63<8*'Campanha'!$B$17+3*IF(ISNUMBER($Y$63),$Y$63,0)),"PV abaixo de 8 × nível + 3 × Vigor (11.4): confira na ficha",IF(IF(ISNUMBER($X$63),$X$63,0)+IF(ISNUMBER($W$63),$W$63,0)+IF(ISNUMBER($Y$63),$Y$63,0)>12+INT('Campanha'!$B$17/2),"Pontos acima de 12 + 1 a cada 2 níveis (11.3)","")))))),IF(LEN($R$63&$S$63&$T$63&$U$63&$V$63&$X$63&$W$63&$Y$63)>0,"Marque Sim em Tem? para o Memoespírito aparecer no Combate",""))) | Q63: =IF(ISERROR($B$63),"",IF(ISBLANK($B$63),"",$B$63)) | R63: =IF(ISERROR($C$63),"",IF(ISBLANK($C$63),"",$C$63)) | S63: =IF(ISERROR($D$63),"",IF(ISBLANK($D$63),"",$D$63)) | T63: =IF(ISERROR($E$63),"",IF(ISBLANK($E$63),"",$E$63)) | U63: =IF(ISERROR($F$63),"",IF(ISBLANK($F$63),"",$F$63)) | V63: =IF(ISERROR($G$63),"",IF(ISBLANK($G$63),"",$G$63)) | W63: =IF(ISERROR($H$63),"",IF(ISBLANK($H$63),"",$H$63)) | X63: =IF(ISERROR($I$63),"",IF(ISBLANK($I$63),"",$I$63)) | Y63: =IF(ISERROR($J$63),"",IF(ISBLANK($J$63),"",$J$63)) | Z63: =ISERROR($B$63)*1+ISERROR($C$63)*1+ISERROR($D$63)*1+ISERROR($E$63)*1+ISERROR($F$63)*1+ISERROR($G$63)*1+ISERROR($H$63)*1+ISERROR($I$63)*1+ISERROR($J$63)*1
A64: =IF(LEN($P$10)>0,$P$10,"PJ 4") | K64: =IF(Z64>0,"O Google leu como fórmula: escolha de novo ou digite com ' na frente.",IF($Q$64="Sim",IF(LEN($P$10)=0,"PJ sem nome em G1: o Memoespírito não entra no Combate",IF(AND(LEN($S$10)>0,$S$10<>"A Recordação"),"O Memoespírito é da Recordação (11.1); este PJ é de outro Caminho",IF(AND(ISNUMBER($U$64),$U$64<10+IF(ISNUMBER($X$64),$X$64,0)+1),"VEL abaixo de 10 + Agilidade + 1 (11.4): confira na ficha",IF(AND(ISNUMBER($T$64),$T$64<10+IF(ISNUMBER($X$64),$X$64,0)+'Campanha'!$B$20),"Defesa abaixo de 10 + Agilidade + Eficiência (11.4): confira na ficha",IF(AND(ISNUMBER($S$64),$S$64<8*'Campanha'!$B$17+3*IF(ISNUMBER($Y$64),$Y$64,0)),"PV abaixo de 8 × nível + 3 × Vigor (11.4): confira na ficha",IF(IF(ISNUMBER($X$64),$X$64,0)+IF(ISNUMBER($W$64),$W$64,0)+IF(ISNUMBER($Y$64),$Y$64,0)>12+INT('Campanha'!$B$17/2),"Pontos acima de 12 + 1 a cada 2 níveis (11.3)","")))))),IF(LEN($R$64&$S$64&$T$64&$U$64&$V$64&$X$64&$W$64&$Y$64)>0,"Marque Sim em Tem? para o Memoespírito aparecer no Combate",""))) | Q64: =IF(ISERROR($B$64),"",IF(ISBLANK($B$64),"",$B$64)) | R64: =IF(ISERROR($C$64),"",IF(ISBLANK($C$64),"",$C$64)) | S64: =IF(ISERROR($D$64),"",IF(ISBLANK($D$64),"",$D$64)) | T64: =IF(ISERROR($E$64),"",IF(ISBLANK($E$64),"",$E$64)) | U64: =IF(ISERROR($F$64),"",IF(ISBLANK($F$64),"",$F$64)) | V64: =IF(ISERROR($G$64),"",IF(ISBLANK($G$64),"",$G$64)) | W64: =IF(ISERROR($H$64),"",IF(ISBLANK($H$64),"",$H$64)) | X64: =IF(ISERROR($I$64),"",IF(ISBLANK($I$64),"",$I$64)) | Y64: =IF(ISERROR($J$64),"",IF(ISBLANK($J$64),"",$J$64)) | Z64: =ISERROR($B$64)*1+ISERROR($C$64)*1+ISERROR($D$64)*1+ISERROR($E$64)*1+ISERROR($F$64)*1+ISERROR($G$64)*1+ISERROR($H$64)*1+ISERROR($I$64)*1+ISERROR($J$64)*1
A65: =IF(LEN($P$11)>0,$P$11,"PJ 5") | K65: =IF(Z65>0,"O Google leu como fórmula: escolha de novo ou digite com ' na frente.",IF($Q$65="Sim",IF(LEN($P$11)=0,"PJ sem nome em G1: o Memoespírito não entra no Combate",IF(AND(LEN($S$11)>0,$S$11<>"A Recordação"),"O Memoespírito é da Recordação (11.1); este PJ é de outro Caminho",IF(AND(ISNUMBER($U$65),$U$65<10+IF(ISNUMBER($X$65),$X$65,0)+1),"VEL abaixo de 10 + Agilidade + 1 (11.4): confira na ficha",IF(AND(ISNUMBER($T$65),$T$65<10+IF(ISNUMBER($X$65),$X$65,0)+'Campanha'!$B$20),"Defesa abaixo de 10 + Agilidade + Eficiência (11.4): confira na ficha",IF(AND(ISNUMBER($S$65),$S$65<8*'Campanha'!$B$17+3*IF(ISNUMBER($Y$65),$Y$65,0)),"PV abaixo de 8 × nível + 3 × Vigor (11.4): confira na ficha",IF(IF(ISNUMBER($X$65),$X$65,0)+IF(ISNUMBER($W$65),$W$65,0)+IF(ISNUMBER($Y$65),$Y$65,0)>12+INT('Campanha'!$B$17/2),"Pontos acima de 12 + 1 a cada 2 níveis (11.3)","")))))),IF(LEN($R$65&$S$65&$T$65&$U$65&$V$65&$X$65&$W$65&$Y$65)>0,"Marque Sim em Tem? para o Memoespírito aparecer no Combate",""))) | Q65: =IF(ISERROR($B$65),"",IF(ISBLANK($B$65),"",$B$65)) | R65: =IF(ISERROR($C$65),"",IF(ISBLANK($C$65),"",$C$65)) | S65: =IF(ISERROR($D$65),"",IF(ISBLANK($D$65),"",$D$65)) | T65: =IF(ISERROR($E$65),"",IF(ISBLANK($E$65),"",$E$65)) | U65: =IF(ISERROR($F$65),"",IF(ISBLANK($F$65),"",$F$65)) | V65: =IF(ISERROR($G$65),"",IF(ISBLANK($G$65),"",$G$65)) | W65: =IF(ISERROR($H$65),"",IF(ISBLANK($H$65),"",$H$65)) | X65: =IF(ISERROR($I$65),"",IF(ISBLANK($I$65),"",$I$65)) | Y65: =IF(ISERROR($J$65),"",IF(ISBLANK($J$65),"",$J$65)) | Z65: =ISERROR($B$65)*1+ISERROR($C$65)*1+ISERROR($D$65)*1+ISERROR($E$65)*1+ISERROR($F$65)*1+ISERROR($G$65)*1+ISERROR($H$65)*1+ISERROR($I$65)*1+ISERROR($J$65)*1
A66: =IF(LEN($P$12)>0,$P$12,"PJ 6") | K66: =IF(Z66>0,"O Google leu como fórmula: escolha de novo ou digite com ' na frente.",IF($Q$66="Sim",IF(LEN($P$12)=0,"PJ sem nome em G1: o Memoespírito não entra no Combate",IF(AND(LEN($S$12)>0,$S$12<>"A Recordação"),"O Memoespírito é da Recordação (11.1); este PJ é de outro Caminho",IF(AND(ISNUMBER($U$66),$U$66<10+IF(ISNUMBER($X$66),$X$66,0)+1),"VEL abaixo de 10 + Agilidade + 1 (11.4): confira na ficha",IF(AND(ISNUMBER($T$66),$T$66<10+IF(ISNUMBER($X$66),$X$66,0)+'Campanha'!$B$20),"Defesa abaixo de 10 + Agilidade + Eficiência (11.4): confira na ficha",IF(AND(ISNUMBER($S$66),$S$66<8*'Campanha'!$B$17+3*IF(ISNUMBER($Y$66),$Y$66,0)),"PV abaixo de 8 × nível + 3 × Vigor (11.4): confira na ficha",IF(IF(ISNUMBER($X$66),$X$66,0)+IF(ISNUMBER($W$66),$W$66,0)+IF(ISNUMBER($Y$66),$Y$66,0)>12+INT('Campanha'!$B$17/2),"Pontos acima de 12 + 1 a cada 2 níveis (11.3)","")))))),IF(LEN($R$66&$S$66&$T$66&$U$66&$V$66&$X$66&$W$66&$Y$66)>0,"Marque Sim em Tem? para o Memoespírito aparecer no Combate",""))) | Q66: =IF(ISERROR($B$66),"",IF(ISBLANK($B$66),"",$B$66)) | R66: =IF(ISERROR($C$66),"",IF(ISBLANK($C$66),"",$C$66)) | S66: =IF(ISERROR($D$66),"",IF(ISBLANK($D$66),"",$D$66)) | T66: =IF(ISERROR($E$66),"",IF(ISBLANK($E$66),"",$E$66)) | U66: =IF(ISERROR($F$66),"",IF(ISBLANK($F$66),"",$F$66)) | V66: =IF(ISERROR($G$66),"",IF(ISBLANK($G$66),"",$G$66)) | W66: =IF(ISERROR($H$66),"",IF(ISBLANK($H$66),"",$H$66)) | X66: =IF(ISERROR($I$66),"",IF(ISBLANK($I$66),"",$I$66)) | Y66: =IF(ISERROR($J$66),"",IF(ISBLANK($J$66),"",$J$66)) | Z66: =ISERROR($B$66)*1+ISERROR($C$66)*1+ISERROR($D$66)*1+ISERROR($E$66)*1+ISERROR($F$66)*1+ISERROR($G$66)*1+ISERROR($H$66)*1+ISERROR($I$66)*1+ISERROR($J$66)*1
A68: G8 · Memoespírito: os números que o Combate usa (automático; vazio em G7 = 11.4 sem Bênção)
A69: PJ dono | B69: Memoespírito | D69: PV máx. | E69: Defesa | F69: VEL | G69: RD | H69: Dano do ataque (11.4) | J69: Redução de Tenacidade | K69: Aviso
A70: =IF(LEN($P$7)>0,$P$7,"PJ 1") | B70: =IF($Q$61="Sim",IF(LEN($R$61)>0,$R$61,"(sem nome)"),"—") | D70: =IF($Q$61="Sim",IF(ISNUMBER($S$61),$S$61,8*'Campanha'!$B$17+3*IF(ISNUMBER($Y$61),$Y$61,0)),"") | E70: =IF($Q$61="Sim",IF(ISNUMBER($T$61),$T$61,10+IF(ISNUMBER($X$61),$X$61,0)+'Campanha'!$B$20),"") | F70: =IF($Q$61="Sim",IF(ISNUMBER($U$61),$U$61,10+IF(ISNUMBER($X$61),$X$61,0)+1),"") | G70: =IF($Q$61="Sim",IF(ISNUMBER($V$61),$V$61,0),"") | H70: =IF($Q$61="Sim",'Campanha'!$B$18&"d6 + pontos no Atributo de ataque ("&('Campanha'!$B$18+1)&"d6 se a arma do dono for de Energia)","") | J70: =IF($Q$61="Sim",IF('Campanha'!$B$17>=11,2,1),"") | K70: =IF(AND($Q$61="Sim",OR(NOT(ISNUMBER($S$61)),NOT(ISNUMBER($T$61)),NOT(ISNUMBER($U$61)))),"Campo vazio em G7: usando 11.4 sem Bênção nem Bônus menor; digite o da ficha","")
A71: =IF(LEN($P$8)>0,$P$8,"PJ 2") | B71: =IF($Q$62="Sim",IF(LEN($R$62)>0,$R$62,"(sem nome)"),"—") | D71: =IF($Q$62="Sim",IF(ISNUMBER($S$62),$S$62,8*'Campanha'!$B$17+3*IF(ISNUMBER($Y$62),$Y$62,0)),"") | E71: =IF($Q$62="Sim",IF(ISNUMBER($T$62),$T$62,10+IF(ISNUMBER($X$62),$X$62,0)+'Campanha'!$B$20),"") | F71: =IF($Q$62="Sim",IF(ISNUMBER($U$62),$U$62,10+IF(ISNUMBER($X$62),$X$62,0)+1),"") | G71: =IF($Q$62="Sim",IF(ISNUMBER($V$62),$V$62,0),"") | H71: =IF($Q$62="Sim",'Campanha'!$B$18&"d6 + pontos no Atributo de ataque ("&('Campanha'!$B$18+1)&"d6 se a arma do dono for de Energia)","") | J71: =IF($Q$62="Sim",IF('Campanha'!$B$17>=11,2,1),"") | K71: =IF(AND($Q$62="Sim",OR(NOT(ISNUMBER($S$62)),NOT(ISNUMBER($T$62)),NOT(ISNUMBER($U$62)))),"Campo vazio em G7: usando 11.4 sem Bênção nem Bônus menor; digite o da ficha","")
A72: =IF(LEN($P$9)>0,$P$9,"PJ 3") | B72: =IF($Q$63="Sim",IF(LEN($R$63)>0,$R$63,"(sem nome)"),"—") | D72: =IF($Q$63="Sim",IF(ISNUMBER($S$63),$S$63,8*'Campanha'!$B$17+3*IF(ISNUMBER($Y$63),$Y$63,0)),"") | E72: =IF($Q$63="Sim",IF(ISNUMBER($T$63),$T$63,10+IF(ISNUMBER($X$63),$X$63,0)+'Campanha'!$B$20),"") | F72: =IF($Q$63="Sim",IF(ISNUMBER($U$63),$U$63,10+IF(ISNUMBER($X$63),$X$63,0)+1),"") | G72: =IF($Q$63="Sim",IF(ISNUMBER($V$63),$V$63,0),"") | H72: =IF($Q$63="Sim",'Campanha'!$B$18&"d6 + pontos no Atributo de ataque ("&('Campanha'!$B$18+1)&"d6 se a arma do dono for de Energia)","") | J72: =IF($Q$63="Sim",IF('Campanha'!$B$17>=11,2,1),"") | K72: =IF(AND($Q$63="Sim",OR(NOT(ISNUMBER($S$63)),NOT(ISNUMBER($T$63)),NOT(ISNUMBER($U$63)))),"Campo vazio em G7: usando 11.4 sem Bênção nem Bônus menor; digite o da ficha","")
A73: =IF(LEN($P$10)>0,$P$10,"PJ 4") | B73: =IF($Q$64="Sim",IF(LEN($R$64)>0,$R$64,"(sem nome)"),"—") | D73: =IF($Q$64="Sim",IF(ISNUMBER($S$64),$S$64,8*'Campanha'!$B$17+3*IF(ISNUMBER($Y$64),$Y$64,0)),"") | E73: =IF($Q$64="Sim",IF(ISNUMBER($T$64),$T$64,10+IF(ISNUMBER($X$64),$X$64,0)+'Campanha'!$B$20),"") | F73: =IF($Q$64="Sim",IF(ISNUMBER($U$64),$U$64,10+IF(ISNUMBER($X$64),$X$64,0)+1),"") | G73: =IF($Q$64="Sim",IF(ISNUMBER($V$64),$V$64,0),"") | H73: =IF($Q$64="Sim",'Campanha'!$B$18&"d6 + pontos no Atributo de ataque ("&('Campanha'!$B$18+1)&"d6 se a arma do dono for de Energia)","") | J73: =IF($Q$64="Sim",IF('Campanha'!$B$17>=11,2,1),"") | K73: =IF(AND($Q$64="Sim",OR(NOT(ISNUMBER($S$64)),NOT(ISNUMBER($T$64)),NOT(ISNUMBER($U$64)))),"Campo vazio em G7: usando 11.4 sem Bênção nem Bônus menor; digite o da ficha","")
A74: =IF(LEN($P$11)>0,$P$11,"PJ 5") | B74: =IF($Q$65="Sim",IF(LEN($R$65)>0,$R$65,"(sem nome)"),"—") | D74: =IF($Q$65="Sim",IF(ISNUMBER($S$65),$S$65,8*'Campanha'!$B$17+3*IF(ISNUMBER($Y$65),$Y$65,0)),"") | E74: =IF($Q$65="Sim",IF(ISNUMBER($T$65),$T$65,10+IF(ISNUMBER($X$65),$X$65,0)+'Campanha'!$B$20),"") | F74: =IF($Q$65="Sim",IF(ISNUMBER($U$65),$U$65,10+IF(ISNUMBER($X$65),$X$65,0)+1),"") | G74: =IF($Q$65="Sim",IF(ISNUMBER($V$65),$V$65,0),"") | H74: =IF($Q$65="Sim",'Campanha'!$B$18&"d6 + pontos no Atributo de ataque ("&('Campanha'!$B$18+1)&"d6 se a arma do dono for de Energia)","") | J74: =IF($Q$65="Sim",IF('Campanha'!$B$17>=11,2,1),"") | K74: =IF(AND($Q$65="Sim",OR(NOT(ISNUMBER($S$65)),NOT(ISNUMBER($T$65)),NOT(ISNUMBER($U$65)))),"Campo vazio em G7: usando 11.4 sem Bênção nem Bônus menor; digite o da ficha","")
A75: =IF(LEN($P$12)>0,$P$12,"PJ 6") | B75: =IF($Q$66="Sim",IF(LEN($R$66)>0,$R$66,"(sem nome)"),"—") | D75: =IF($Q$66="Sim",IF(ISNUMBER($S$66),$S$66,8*'Campanha'!$B$17+3*IF(ISNUMBER($Y$66),$Y$66,0)),"") | E75: =IF($Q$66="Sim",IF(ISNUMBER($T$66),$T$66,10+IF(ISNUMBER($X$66),$X$66,0)+'Campanha'!$B$20),"") | F75: =IF($Q$66="Sim",IF(ISNUMBER($U$66),$U$66,10+IF(ISNUMBER($X$66),$X$66,0)+1),"") | G75: =IF($Q$66="Sim",IF(ISNUMBER($V$66),$V$66,0),"") | H75: =IF($Q$66="Sim",'Campanha'!$B$18&"d6 + pontos no Atributo de ataque ("&('Campanha'!$B$18+1)&"d6 se a arma do dono for de Energia)","") | J75: =IF($Q$66="Sim",IF('Campanha'!$B$17>=11,2,1),"") | K75: =IF(AND($Q$66="Sim",OR(NOT(ISNUMBER($S$66)),NOT(ISNUMBER($T$66)),NOT(ISNUMBER($U$66)))),"Campo vazio em G7: usando 11.4 sem Bênção nem Bônus menor; digite o da ficha","")
A76: Na mesa (11.5): invocar custa a Ação Complementar do dono e 1 PH; ele tem casa própria na Fila pela VEL dele e faz 1 ação por turno (Ataque Básico, uma das 2 Habilidades dele ou Movimento) mais 1 Reação; gera metade da Energia para o dono (17); fica até o dono dispensá-lo ou ele cair a 0 PV, e então só volta depois do próximo Descanso Curto (23.6). Não tem Tenacidade nem fica Quebrado (20.1).
A78: Resumo do grupo (automático)
A79: Nº de PJs | B79: =SUMPRODUCT((LEN($P$7:$P$12)>0)*1) | C79: =IF(AND(ISNUMBER('Campanha'!$AD$8),$B$79>0,$B$79<>'Campanha'!$AD$8),"Nº de PJs diferente do nº de jogadores da aba Campanha","")
A80: Elemento | B80: Físico | C80: Fogo | D80: Gelo | E80: Raio | F80: Vento | G80: Quântico | H80: Imaginário | I80: Distintos | J80: Em dobro
A81: No grupo? | B81: =IF(COUNTIF($T$7:$T$12,"Físico")>0,"Sim","Não") | C81: =IF(COUNTIF($T$7:$T$12,"Fogo")>0,"Sim","Não") | D81: =IF(COUNTIF($T$7:$T$12,"Gelo")>0,"Sim","Não") | E81: =IF(COUNTIF($T$7:$T$12,"Raio")>0,"Sim","Não") | F81: =IF(COUNTIF($T$7:$T$12,"Vento")>0,"Sim","Não") | G81: =IF(COUNTIF($T$7:$T$12,"Quântico")>0,"Sim","Não") | H81: =IF(COUNTIF($T$7:$T$12,"Imaginário")>0,"Sim","Não") | I81: =IF($B$81="Sim",1,0)+IF($C$81="Sim",1,0)+IF($D$81="Sim",1,0)+IF($E$81="Sim",1,0)+IF($F$81="Sim",1,0)+IF($G$81="Sim",1,0)+IF($H$81="Sim",1,0) | J81: =IF(COUNTIF($T$7:$T$12,"Físico")>1,1,0)+IF(COUNTIF($T$7:$T$12,"Fogo")>1,1,0)+IF(COUNTIF($T$7:$T$12,"Gelo")>1,1,0)+IF(COUNTIF($T$7:$T$12,"Raio")>1,1,0)+IF(COUNTIF($T$7:$T$12,"Vento")>1,1,0)+IF(COUNTIF($T$7:$T$12,"Quântico")>1,1,0)+IF(COUNTIF($T$7:$T$12,"Imaginário")>1,1,0)
A82: Presenças | B82: =IF(COUNTIF($R$7:$R$12,"Intellitron")>0,"Intellitron no grupo: descobre Fraqueza com Vantagem e 2 por sucesso (20.2). ","")&IF(COUNTIF($R$7:$R$12,"Humano")>0,"Humano no grupo: Esforço (05). ","")&IF(COUNTIF($S$7:$S$12,"A Preservação")+COUNTIF($S$7:$S$12,"A Abundância")>0,"Há Caminho de sustentação (27.7).","Sem Preservação nem Abundância: cuidado com o dia de jogo (27.7).")
A83: Surpresa | B83: =IF(SUMPRODUCT(ISNUMBER($U$43:$U$48)*1)=0,"Preencha a Percepção Mental na G5.","Menor Percepção Mental do grupo: "&MIN($U$43:$U$48)&" ("&INDEX($P$7:$P$12,MATCH(MIN($U$43:$U$48),$U$43:$U$48,0))&"). Surpresa: Teste de Percepção Mental contra DT 13, fixa em todas as faixas (19.3, 27.3).")
A84: Descobrir Fraqueza | B84: =IF(SUMPRODUCT(ISNUMBER($N$52:$N$57)*1)=0,"Preencha Pesquisa, Ciência ou Sintonia na G6.","Melhor total de Pesquisa, Ciência ou Sintonia: "&MAX($N$52:$N$57)&" ("&INDEX($P$7:$P$12,MATCH(MAX($N$52:$N$57),$N$52:$N$57,0))&"), contra DT "&'Campanha'!$B$29&" na faixa do grupo (20.2)"&IF(COUNTIF($R$7:$R$12,"Intellitron")>0,"; o Intellitron rola com Vantagem e descobre duas por sucesso (20.2).","."))
A85: VEL esperada | B85: Faixa esperada de VEL (19.1): 10 a 19 no nível 1; 12 a 21 no nível 10; 13 a 24 no nível 20 com equipamento. Extremos absolutos da fórmula: 7 e 25.

Sheet Sessões
A1: Sessões — Explorando Galáxias v1.2
A2: Legenda: | B2: Entrada (preencha) | C2: Calculada (automático) | D2: Aviso (texto em vermelho) | E2: Título de bloco | F2: Cabeçalho de coluna | G2: Rótulo da linha | H2: Linha alternada (outro tom) | I2: Não se aplica
A3: Preparar a próxima sessão (cenas, pistas, ganchos, checklist) e o diário de campanha.
A5: Preparar a próxima sessão (preencha)
A6: Campo | B6: Valor (preencha) | K6: Aviso
A7: Sessão nº | C7: ="Sessão atual na Mesa: "&IF(ISNUMBER('Campanha'!$AD$10),'Campanha'!$AD$10,"(vazia)")&"." | K7: =IF(AA7>0,"O Google leu como fórmula: digite de novo com ' na frente.",IF(AND(ISNUMBER($R$7),ISNUMBER('Campanha'!$AD$10)),IF($R$7<'Campanha'!$AD$10,"Sessão preparada anterior à sessão atual da Mesa",""),"")) | R7: =IF(ISERROR($B$7),"",IF(ISBLANK($B$7),"",$B$7)) | AA7: =ISERROR($B$7)*1
A8: Data real | K8: =IF(AA8>0,"O Google leu como fórmula: digite de novo com ' na frente.","") | AA8: =ISERROR($B$8)*1
A9: Título | K9: =IF(AA9>0,"O Google leu como fórmula: digite de novo com ' na frente.","") | R9: =IF(ISERROR($B$9),"",IF(ISBLANK($B$9),"",$B$9)) | AA9: =ISERROR($B$9)*1
A10: Objetivo da sessão | K10: =IF(AA10>0,"O Google leu como fórmula: digite de novo com ' na frente.","") | AA10: =ISERROR($B$10)*1
A12: 5 cenas planejadas (a DT usa a faixa do desafio, não a do grupo: 27.2 regra 1)
A13: Cena | B13: Tipo | C13: Descrição | F13: NPCs presentes | H13: Encontro ligado | I13: Dificuldade | J13: Faixa do desafio | K13: Aviso
A14: Cena 1 | K14: =IF(AA14>0,"O Google leu como fórmula: escolha de novo ou digite com ' na frente.",IF(AND(LEN($Y$14)>0,COUNTIF('Dados'!$A$284:$A$289,$Y$14)=0),"Dificuldade fora da lista (27.2)",IF(AND(LEN($Z$14)>0,COUNTIF('Dados'!$AP$6:$AP$10,$Z$14)=0),"Faixa fora da lista: usando a do grupo",IF(AND(LEN($X$14)>0,$X$14<>"Nenhum",$X$14<>"A",$X$14<>"B",$X$14<>"C"),"Encontro fora da lista (A, B ou C)","")))) | R14: =IF(ISERROR($B$14),"",IF(ISBLANK($B$14),"",$B$14)) | X14: =IF(ISERROR($H$14),"",IF(ISBLANK($H$14),"",$H$14)) | Y14: =IF(ISERROR($I$14),"",IF(ISBLANK($I$14),"",$I$14)) | Z14: =IF(ISERROR($J$14),"",IF(ISBLANK($J$14),"",$J$14)) | AA14: =ISERROR($B$14)*1+ISERROR($C$14)*1+ISERROR($F$14)*1+ISERROR($H$14)*1+ISERROR($I$14)*1+ISERROR($J$14)*1
A15: Cena 2 | K15: =IF(AA15>0,"O Google leu como fórmula: escolha de novo ou digite com ' na frente.",IF(AND(LEN($Y$15)>0,COUNTIF('Dados'!$A$284:$A$289,$Y$15)=0),"Dificuldade fora da lista (27.2)",IF(AND(LEN($Z$15)>0,COUNTIF('Dados'!$AP$6:$AP$10,$Z$15)=0),"Faixa fora da lista: usando a do grupo",IF(AND(LEN($X$15)>0,$X$15<>"Nenhum",$X$15<>"A",$X$15<>"B",$X$15<>"C"),"Encontro fora da lista (A, B ou C)","")))) | R15: =IF(ISERROR($B$15),"",IF(ISBLANK($B$15),"",$B$15)) | X15: =IF(ISERROR($H$15),"",IF(ISBLANK($H$15),"",$H$15)) | Y15: =IF(ISERROR($I$15),"",IF(ISBLANK($I$15),"",$I$15)) | Z15: =IF(ISERROR($J$15),"",IF(ISBLANK($J$15),"",$J$15)) | AA15: =ISERROR($B$15)*1+ISERROR($C$15)*1+ISERROR($F$15)*1+ISERROR($H$15)*1+ISERROR($I$15)*1+ISERROR($J$15)*1
A16: Cena 3 | K16: =IF(AA16>0,"O Google leu como fórmula: escolha de novo ou digite com ' na frente.",IF(AND(LEN($Y$16)>0,COUNTIF('Dados'!$A$284:$A$289,$Y$16)=0),"Dificuldade fora da lista (27.2)",IF(AND(LEN($Z$16)>0,COUNTIF('Dados'!$AP$6:$AP$10,$Z$16)=0),"Faixa fora da lista: usando a do grupo",IF(AND(LEN($X$16)>0,$X$16<>"Nenhum",$X$16<>"A",$X$16<>"B",$X$16<>"C"),"Encontro fora da lista (A, B ou C)","")))) | R16: =IF(ISERROR($B$16),"",IF(ISBLANK($B$16),"",$B$16)) | X16: =IF(ISERROR($H$16),"",IF(ISBLANK($H$16),"",$H$16)) | Y16: =IF(ISERROR($I$16),"",IF(ISBLANK($I$16),"",$I$16)) | Z16: =IF(ISERROR($J$16),"",IF(ISBLANK($J$16),"",$J$16)) | AA16: =ISERROR($B$16)*1+ISERROR($C$16)*1+ISERROR($F$16)*1+ISERROR($H$16)*1+ISERROR($I$16)*1+ISERROR($J$16)*1
A17: Cena 4 | K17: =IF(AA17>0,"O Google leu como fórmula: escolha de novo ou digite com ' na frente.",IF(AND(LEN($Y$17)>0,COUNTIF('Dados'!$A$284:$A$289,$Y$17)=0),"Dificuldade fora da lista (27.2)",IF(AND(LEN($Z$17)>0,COUNTIF('Dados'!$AP$6:$AP$10,$Z$17)=0),"Faixa fora da lista: usando a do grupo",IF(AND(LEN($X$17)>0,$X$17<>"Nenhum",$X$17<>"A",$X$17<>"B",$X$17<>"C"),"Encontro fora da lista (A, B ou C)","")))) | R17: =IF(ISERROR($B$17),"",IF(ISBLANK($B$17),"",$B$17)) | X17: =IF(ISERROR($H$17),"",IF(ISBLANK($H$17),"",$H$17)) | Y17: =IF(ISERROR($I$17),"",IF(ISBLANK($I$17),"",$I$17)) | Z17: =IF(ISERROR($J$17),"",IF(ISBLANK($J$17),"",$J$17)) | AA17: =ISERROR($B$17)*1+ISERROR($C$17)*1+ISERROR($F$17)*1+ISERROR($H$17)*1+ISERROR($I$17)*1+ISERROR($J$17)*1
A18: Cena 5 | K18: =IF(AA18>0,"O Google leu como fórmula: escolha de novo ou digite com ' na frente.",IF(AND(LEN($Y$18)>0,COUNTIF('Dados'!$A$284:$A$289,$Y$18)=0),"Dificuldade fora da lista (27.2)",IF(AND(LEN($Z$18)>0,COUNTIF('Dados'!$AP$6:$AP$10,$Z$18)=0),"Faixa fora da lista: usando a do grupo",IF(AND(LEN($X$18)>0,$X$18<>"Nenhum",$X$18<>"A",$X$18<>"B",$X$18<>"C"),"Encontro fora da lista (A, B ou C)","")))) | R18: =IF(ISERROR($B$18),"",IF(ISBLANK($B$18),"",$B$18)) | X18: =IF(ISERROR($H$18),"",IF(ISBLANK($H$18),"",$H$18)) | Y18: =IF(ISERROR($I$18),"",IF(ISBLANK($I$18),"",$I$18)) | Z18: =IF(ISERROR($J$18),"",IF(ISBLANK($J$18),"",$J$18)) | AA18: =ISERROR($B$18)*1+ISERROR($C$18)*1+ISERROR($F$18)*1+ISERROR($H$18)*1+ISERROR($I$18)*1+ISERROR($J$18)*1
A19: Cena | B19: DT (automático) | C19: Encontro ligado (aba Encontros) | G19: Contrato da Fraqueza (27.5) | K19: Aviso
A20: Cena 1 | B20: =IF(LEN($Y$14)=0,"",IFERROR(IF(IF(LEN($Z$14)=0,'Campanha'!$B$18,IFERROR(MATCH($Z$14,'Dados'!$AP$6:$AP$10,0),'Campanha'!$B$18))=1,INDEX('Dados'!$B$284:$B$289,MATCH($Y$14,'Dados'!$A$284:$A$289,0)),IF(IF(LEN($Z$14)=0,'Campanha'!$B$18,IFERROR(MATCH($Z$14,'Dados'!$AP$6:$AP$10,0),'Campanha'!$B$18))=2,INDEX('Dados'!$C$284:$C$289,MATCH($Y$14,'Dados'!$A$284:$A$289,0)),IF(IF(LEN($Z$14)=0,'Campanha'!$B$18,IFERROR(MATCH($Z$14,'Dados'!$AP$6:$AP$10,0),'Campanha'!$B$18))=3,INDEX('Dados'!$D$284:$D$289,MATCH($Y$14,'Dados'!$A$284:$A$289,0)),IF(IF(LEN($Z$14)=0,'Campanha'!$B$18,IFERROR(MATCH($Z$14,'Dados'!$AP$6:$AP$10,0),'Campanha'!$B$18))=4,INDEX('Dados'!$E$284:$E$289,MATCH($Y$14,'Dados'!$A$284:$A$289,0)),INDEX('Dados'!$F$284:$F$289,MATCH($Y$14,'Dados'!$A$284:$A$289,0)))))),"")) | C20: =IF($X$14="A",IF(LEN('Encontros'!$BH$19&"")>0,'Encontros'!$BH$19&": ","Encontro A: ")&"custo "&'Encontros'!$B$38&" · "&'Encontros'!$G$38,IF($X$14="B",IF(LEN('Encontros'!$BH$47&"")>0,'Encontros'!$BH$47&": ","Encontro B: ")&"custo "&'Encontros'!$B$66&" · "&'Encontros'!$G$66,IF($X$14="C",IF(LEN('Encontros'!$BH$75&"")>0,'Encontros'!$BH$75&": ","Encontro C: ")&"custo "&'Encontros'!$B$94&" · "&'Encontros'!$G$94,""))) | G20: =IF($X$14="A",'Encontros'!$J$41,IF($X$14="B",'Encontros'!$J$69,IF($X$14="C",'Encontros'!$J$97,"")))
A21: Cena 2 | B21: =IF(LEN($Y$15)=0,"",IFERROR(IF(IF(LEN($Z$15)=0,'Campanha'!$B$18,IFERROR(MATCH($Z$15,'Dados'!$AP$6:$AP$10,0),'Campanha'!$B$18))=1,INDEX('Dados'!$B$284:$B$289,MATCH($Y$15,'Dados'!$A$284:$A$289,0)),IF(IF(LEN($Z$15)=0,'Campanha'!$B$18,IFERROR(MATCH($Z$15,'Dados'!$AP$6:$AP$10,0),'Campanha'!$B$18))=2,INDEX('Dados'!$C$284:$C$289,MATCH($Y$15,'Dados'!$A$284:$A$289,0)),IF(IF(LEN($Z$15)=0,'Campanha'!$B$18,IFERROR(MATCH($Z$15,'Dados'!$AP$6:$AP$10,0),'Campanha'!$B$18))=3,INDEX('Dados'!$D$284:$D$289,MATCH($Y$15,'Dados'!$A$284:$A$289,0)),IF(IF(LEN($Z$15)=0,'Campanha'!$B$18,IFERROR(MATCH($Z$15,'Dados'!$AP$6:$AP$10,0),'Campanha'!$B$18))=4,INDEX('Dados'!$E$284:$E$289,MATCH($Y$15,'Dados'!$A$284:$A$289,0)),INDEX('Dados'!$F$284:$F$289,MATCH($Y$15,'Dados'!$A$284:$A$289,0)))))),"")) | C21: =IF($X$15="A",IF(LEN('Encontros'!$BH$19&"")>0,'Encontros'!$BH$19&": ","Encontro A: ")&"custo "&'Encontros'!$B$38&" · "&'Encontros'!$G$38,IF($X$15="B",IF(LEN('Encontros'!$BH$47&"")>0,'Encontros'!$BH$47&": ","Encontro B: ")&"custo "&'Encontros'!$B$66&" · "&'Encontros'!$G$66,IF($X$15="C",IF(LEN('Encontros'!$BH$75&"")>0,'Encontros'!$BH$75&": ","Encontro C: ")&"custo "&'Encontros'!$B$94&" · "&'Encontros'!$G$94,""))) | G21: =IF($X$15="A",'Encontros'!$J$41,IF($X$15="B",'Encontros'!$J$69,IF($X$15="C",'Encontros'!$J$97,"")))
A22: Cena 3 | B22: =IF(LEN($Y$16)=0,"",IFERROR(IF(IF(LEN($Z$16)=0,'Campanha'!$B$18,IFERROR(MATCH($Z$16,'Dados'!$AP$6:$AP$10,0),'Campanha'!$B$18))=1,INDEX('Dados'!$B$284:$B$289,MATCH($Y$16,'Dados'!$A$284:$A$289,0)),IF(IF(LEN($Z$16)=0,'Campanha'!$B$18,IFERROR(MATCH($Z$16,'Dados'!$AP$6:$AP$10,0),'Campanha'!$B$18))=2,INDEX('Dados'!$C$284:$C$289,MATCH($Y$16,'Dados'!$A$284:$A$289,0)),IF(IF(LEN($Z$16)=0,'Campanha'!$B$18,IFERROR(MATCH($Z$16,'Dados'!$AP$6:$AP$10,0),'Campanha'!$B$18))=3,INDEX('Dados'!$D$284:$D$289,MATCH($Y$16,'Dados'!$A$284:$A$289,0)),IF(IF(LEN($Z$16)=0,'Campanha'!$B$18,IFERROR(MATCH($Z$16,'Dados'!$AP$6:$AP$10,0),'Campanha'!$B$18))=4,INDEX('Dados'!$E$284:$E$289,MATCH($Y$16,'Dados'!$A$284:$A$289,0)),INDEX('Dados'!$F$284:$F$289,MATCH($Y$16,'Dados'!$A$284:$A$289,0)))))),"")) | C22: =IF($X$16="A",IF(LEN('Encontros'!$BH$19&"")>0,'Encontros'!$BH$19&": ","Encontro A: ")&"custo "&'Encontros'!$B$38&" · "&'Encontros'!$G$38,IF($X$16="B",IF(LEN('Encontros'!$BH$47&"")>0,'Encontros'!$BH$47&": ","Encontro B: ")&"custo "&'Encontros'!$B$66&" · "&'Encontros'!$G$66,IF($X$16="C",IF(LEN('Encontros'!$BH$75&"")>0,'Encontros'!$BH$75&": ","Encontro C: ")&"custo "&'Encontros'!$B$94&" · "&'Encontros'!$G$94,""))) | G22: =IF($X$16="A",'Encontros'!$J$41,IF($X$16="B",'Encontros'!$J$69,IF($X$16="C",'Encontros'!$J$97,"")))
A23: Cena 4 | B23: =IF(LEN($Y$17)=0,"",IFERROR(IF(IF(LEN($Z$17)=0,'Campanha'!$B$18,IFERROR(MATCH($Z$17,'Dados'!$AP$6:$AP$10,0),'Campanha'!$B$18))=1,INDEX('Dados'!$B$284:$B$289,MATCH($Y$17,'Dados'!$A$284:$A$289,0)),IF(IF(LEN($Z$17)=0,'Campanha'!$B$18,IFERROR(MATCH($Z$17,'Dados'!$AP$6:$AP$10,0),'Campanha'!$B$18))=2,INDEX('Dados'!$C$284:$C$289,MATCH($Y$17,'Dados'!$A$284:$A$289,0)),IF(IF(LEN($Z$17)=0,'Campanha'!$B$18,IFERROR(MATCH($Z$17,'Dados'!$AP$6:$AP$10,0),'Campanha'!$B$18))=3,INDEX('Dados'!$D$284:$D$289,MATCH($Y$17,'Dados'!$A$284:$A$289,0)),IF(IF(LEN($Z$17)=0,'Campanha'!$B$18,IFERROR(MATCH($Z$17,'Dados'!$AP$6:$AP$10,0),'Campanha'!$B$18))=4,INDEX('Dados'!$E$284:$E$289,MATCH($Y$17,'Dados'!$A$284:$A$289,0)),INDEX('Dados'!$F$284:$F$289,MATCH($Y$17,'Dados'!$A$284:$A$289,0)))))),"")) | C23: =IF($X$17="A",IF(LEN('Encontros'!$BH$19&"")>0,'Encontros'!$BH$19&": ","Encontro A: ")&"custo "&'Encontros'!$B$38&" · "&'Encontros'!$G$38,IF($X$17="B",IF(LEN('Encontros'!$BH$47&"")>0,'Encontros'!$BH$47&": ","Encontro B: ")&"custo "&'Encontros'!$B$66&" · "&'Encontros'!$G$66,IF($X$17="C",IF(LEN('Encontros'!$BH$75&"")>0,'Encontros'!$BH$75&": ","Encontro C: ")&"custo "&'Encontros'!$B$94&" · "&'Encontros'!$G$94,""))) | G23: =IF($X$17="A",'Encontros'!$J$41,IF($X$17="B",'Encontros'!$J$69,IF($X$17="C",'Encontros'!$J$97,"")))
A24: Cena 5 | B24: =IF(LEN($Y$18)=0,"",IFERROR(IF(IF(LEN($Z$18)=0,'Campanha'!$B$18,IFERROR(MATCH($Z$18,'Dados'!$AP$6:$AP$10,0),'Campanha'!$B$18))=1,INDEX('Dados'!$B$284:$B$289,MATCH($Y$18,'Dados'!$A$284:$A$289,0)),IF(IF(LEN($Z$18)=0,'Campanha'!$B$18,IFERROR(MATCH($Z$18,'Dados'!$AP$6:$AP$10,0),'Campanha'!$B$18))=2,INDEX('Dados'!$C$284:$C$289,MATCH($Y$18,'Dados'!$A$284:$A$289,0)),IF(IF(LEN($Z$18)=0,'Campanha'!$B$18,IFERROR(MATCH($Z$18,'Dados'!$AP$6:$AP$10,0),'Campanha'!$B$18))=3,INDEX('Dados'!$D$284:$D$289,MATCH($Y$18,'Dados'!$A$284:$A$289,0)),IF(IF(LEN($Z$18)=0,'Campanha'!$B$18,IFERROR(MATCH($Z$18,'Dados'!$AP$6:$AP$10,0),'Campanha'!$B$18))=4,INDEX('Dados'!$E$284:$E$289,MATCH($Y$18,'Dados'!$A$284:$A$289,0)),INDEX('Dados'!$F$284:$F$289,MATCH($Y$18,'Dados'!$A$284:$A$289,0)))))),"")) | C24: =IF($X$18="A",IF(LEN('Encontros'!$BH$19&"")>0,'Encontros'!$BH$19&": ","Encontro A: ")&"custo "&'Encontros'!$B$38&" · "&'Encontros'!$G$38,IF($X$18="B",IF(LEN('Encontros'!$BH$47&"")>0,'Encontros'!$BH$47&": ","Encontro B: ")&"custo "&'Encontros'!$B$66&" · "&'Encontros'!$G$66,IF($X$18="C",IF(LEN('Encontros'!$BH$75&"")>0,'Encontros'!$BH$75&": ","Encontro C: ")&"custo "&'Encontros'!$B$94&" · "&'Encontros'!$G$94,""))) | G24: =IF($X$18="A",'Encontros'!$J$41,IF($X$18="B",'Encontros'!$J$69,IF($X$18="C",'Encontros'!$J$97,"")))
A26: Segredos e pistas (10 linhas)
A27: Pista | B27: Segredo ou pista | J27: Revelada? | K27: Aviso
A28: Pista 1 | K28: =IF(AA28>0,"O Google leu como fórmula: escolha de novo ou digite com ' na frente.","") | R28: =IF(ISERROR($B$28),"",IF(ISBLANK($B$28),"",$B$28)) | Z28: =IF(ISERROR($J$28),"",IF(ISBLANK($J$28),"",$J$28)) | AA28: =ISERROR($B$28)*1+ISERROR($J$28)*1
A29: Pista 2 | K29: =IF(AA29>0,"O Google leu como fórmula: escolha de novo ou digite com ' na frente.","") | R29: =IF(ISERROR($B$29),"",IF(ISBLANK($B$29),"",$B$29)) | Z29: =IF(ISERROR($J$29),"",IF(ISBLANK($J$29),"",$J$29)) | AA29: =ISERROR($B$29)*1+ISERROR($J$29)*1
A30: Pista 3 | K30: =IF(AA30>0,"O Google leu como fórmula: escolha de novo ou digite com ' na frente.","") | R30: =IF(ISERROR($B$30),"",IF(ISBLANK($B$30),"",$B$30)) | Z30: =IF(ISERROR($J$30),"",IF(ISBLANK($J$30),"",$J$30)) | AA30: =ISERROR($B$30)*1+ISERROR($J$30)*1
A31: Pista 4 | K31: =IF(AA31>0,"O Google leu como fórmula: escolha de novo ou digite com ' na frente.","") | R31: =IF(ISERROR($B$31),"",IF(ISBLANK($B$31),"",$B$31)) | Z31: =IF(ISERROR($J$31),"",IF(ISBLANK($J$31),"",$J$31)) | AA31: =ISERROR($B$31)*1+ISERROR($J$31)*1
A32: Pista 5 | K32: =IF(AA32>0,"O Google leu como fórmula: escolha de novo ou digite com ' na frente.","") | R32: =IF(ISERROR($B$32),"",IF(ISBLANK($B$32),"",$B$32)) | Z32: =IF(ISERROR($J$32),"",IF(ISBLANK($J$32),"",$J$32)) | AA32: =ISERROR($B$32)*1+ISERROR($J$32)*1
A33: Pista 6 | K33: =IF(AA33>0,"O Google leu como fórmula: escolha de novo ou digite com ' na frente.","") | R33: =IF(ISERROR($B$33),"",IF(ISBLANK($B$33),"",$B$33)) | Z33: =IF(ISERROR($J$33),"",IF(ISBLANK($J$33),"",$J$33)) | AA33: =ISERROR($B$33)*1+ISERROR($J$33)*1
A34: Pista 7 | K34: =IF(AA34>0,"O Google leu como fórmula: escolha de novo ou digite com ' na frente.","") | R34: =IF(ISERROR($B$34),"",IF(ISBLANK($B$34),"",$B$34)) | Z34: =IF(ISERROR($J$34),"",IF(ISBLANK($J$34),"",$J$34)) | AA34: =ISERROR($B$34)*1+ISERROR($J$34)*1
A35: Pista 8 | K35: =IF(AA35>0,"O Google leu como fórmula: escolha de novo ou digite com ' na frente.","") | R35: =IF(ISERROR($B$35),"",IF(ISBLANK($B$35),"",$B$35)) | Z35: =IF(ISERROR($J$35),"",IF(ISBLANK($J$35),"",$J$35)) | AA35: =ISERROR($B$35)*1+ISERROR($J$35)*1
A36: Pista 9 | K36: =IF(AA36>0,"O Google leu como fórmula: escolha de novo ou digite com ' na frente.","") | R36: =IF(ISERROR($B$36),"",IF(ISBLANK($B$36),"",$B$36)) | Z36: =IF(ISERROR($J$36),"",IF(ISBLANK($J$36),"",$J$36)) | AA36: =ISERROR($B$36)*1+ISERROR($J$36)*1
A37: Pista 10 | K37: =IF(AA37>0,"O Google leu como fórmula: escolha de novo ou digite com ' na frente.","") | R37: =IF(ISERROR($B$37),"",IF(ISBLANK($B$37),"",$B$37)) | Z37: =IF(ISERROR($J$37),"",IF(ISBLANK($J$37),"",$J$37)) | AA37: =ISERROR($B$37)*1+ISERROR($J$37)*1
A38: ="Pistas: "&SUMPRODUCT((LEN($R$28:$R$37)>0)*1)&" · reveladas: "&COUNTIF($Z$28:$Z$37,"Sim")
A40: Recompensas planejadas
A41: Recompensas | K41: =IF(AA41>0,"O Google leu como fórmula: digite de novo com ' na frente.","") | AA41: =ISERROR($B$41)*1
A42: A entrega de marco (verba, Cone, Tier, Ressonância) e os achados de encontro estão na aba Recompensas. Amarre cada entrega ao Propósito de Vida de alguém (27.8).
A44: Ganchos de Propósito de Vida (um por PJ; o gancho com nome de personagem inicia um arco, 27.18)
A45: PJ (aba Grupo) | B45: Propósito de Vida (aba Grupo) | F45: Gancho desta sessão (preencha) | K45: Aviso
A46: =IF(LEN('Grupo'!$P$7)>0,'Grupo'!$P$7,"PJ 1") | B46: =IF(LEN('Grupo'!$U$7)>0,'Grupo'!$U$7,"") | K46: =IF(AA46>0,"O Google leu como fórmula: digite de novo com ' na frente.",IF(AND(LEN($V$46)>0,LEN('Grupo'!$P$7)=0),"PJ 1 sem nome na aba Grupo","")) | V46: =IF(ISERROR($F$46),"",IF(ISBLANK($F$46),"",$F$46)) | AA46: =ISERROR($F$46)*1
A47: =IF(LEN('Grupo'!$P$8)>0,'Grupo'!$P$8,"PJ 2") | B47: =IF(LEN('Grupo'!$U$8)>0,'Grupo'!$U$8,"") | K47: =IF(AA47>0,"O Google leu como fórmula: digite de novo com ' na frente.",IF(AND(LEN($V$47)>0,LEN('Grupo'!$P$8)=0),"PJ 2 sem nome na aba Grupo","")) | V47: =IF(ISERROR($F$47),"",IF(ISBLANK($F$47),"",$F$47)) | AA47: =ISERROR($F$47)*1
A48: =IF(LEN('Grupo'!$P$9)>0,'Grupo'!$P$9,"PJ 3") | B48: =IF(LEN('Grupo'!$U$9)>0,'Grupo'!$U$9,"") | K48: =IF(AA48>0,"O Google leu como fórmula: digite de novo com ' na frente.",IF(AND(LEN($V$48)>0,LEN('Grupo'!$P$9)=0),"PJ 3 sem nome na aba Grupo","")) | V48: =IF(ISERROR($F$48),"",IF(ISBLANK($F$48),"",$F$48)) | AA48: =ISERROR($F$48)*1
A49: =IF(LEN('Grupo'!$P$10)>0,'Grupo'!$P$10,"PJ 4") | B49: =IF(LEN('Grupo'!$U$10)>0,'Grupo'!$U$10,"") | K49: =IF(AA49>0,"O Google leu como fórmula: digite de novo com ' na frente.",IF(AND(LEN($V$49)>0,LEN('Grupo'!$P$10)=0),"PJ 4 sem nome na aba Grupo","")) | V49: =IF(ISERROR($F$49),"",IF(ISBLANK($F$49),"",$F$49)) | AA49: =ISERROR($F$49)*1
A50: =IF(LEN('Grupo'!$P$11)>0,'Grupo'!$P$11,"PJ 5") | B50: =IF(LEN('Grupo'!$U$11)>0,'Grupo'!$U$11,"") | K50: =IF(AA50>0,"O Google leu como fórmula: digite de novo com ' na frente.",IF(AND(LEN($V$50)>0,LEN('Grupo'!$P$11)=0),"PJ 5 sem nome na aba Grupo","")) | V50: =IF(ISERROR($F$50),"",IF(ISBLANK($F$50),"",$F$50)) | AA50: =ISERROR($F$50)*1
A51: =IF(LEN('Grupo'!$P$12)>0,'Grupo'!$P$12,"PJ 6") | B51: =IF(LEN('Grupo'!$U$12)>0,'Grupo'!$U$12,"") | K51: =IF(AA51>0,"O Google leu como fórmula: digite de novo com ' na frente.",IF(AND(LEN($V$51)>0,LEN('Grupo'!$P$12)=0),"PJ 6 sem nome na aba Grupo","")) | V51: =IF(ISERROR($F$51),"",IF(ISBLANK($F$51),"",$F$51)) | AA51: =ISERROR($F$51)*1
A53: Checklist de preparo
A54: Item | B54: O que conferir | G54: Feito? | H54: Automático | K54: Aviso
A55: Orçamento | B55: O encontro gasta o orçamento da faixa (27.4); metade dele é cena de passagem. | H55: ="Orçamento da faixa para o grupo: "&'Encontros'!$B$11&" PV (aba Encontros)." | K55: =IF(AA55>0,"O Google leu como fórmula: escolha de novo na lista.","") | AA55: =ISERROR($G$55)*1
A56: Contrato da Fraqueza | B56: Pelo menos 3 dos Elementos do grupo como Fraqueza na cena (27.5). | H56: =IF(COUNTIF($X$14:$X$18,"A")>0,"A: "&'Encontros'!$J$41&". ","")&IF(COUNTIF($X$14:$X$18,"B")>0,"B: "&'Encontros'!$J$69&". ","")&IF(COUNTIF($X$14:$X$18,"C")>0,"C: "&'Encontros'!$J$97&". ","")&IF(COUNTIF($X$14:$X$18,"A")+COUNTIF($X$14:$X$18,"B")+COUNTIF($X$14:$X$18,"C")=0,"Nenhum encontro ligado às cenas.","") | K56: =IF(AA56>0,"O Google leu como fórmula: escolha de novo na lista.","") | AA56: =ISERROR($G$56)*1
A57: Relógio na ficção | B57: Um prazo na história para o Descanso Longo não ser um botão (27.7). | H57: ="Relógios a 1 de encher: "&COUNTIF('Campanha'!$G$62:$G$71,"Falta 1")&" (aba Campanha)." | K57: =IF(AA57>0,"O Google leu como fórmula: escolha de novo na lista.","") | AA57: =ISERROR($G$57)*1
A58: Combates do dia | B58: Dois combates por dia é um dia tranquilo; três é um dia de verdade; quatro é uma emergência (27.7). Vazio = os combates das cenas. | H58: =IF($N$58<=0,"Nenhum combate previsto",$N$58&" combate(s): "&IF($N$58<=2,"dia tranquilo",IF($N$58=3,"dia de verdade","emergência, e o grupo deve sentir que é"))&" (27.7)") | K58: =IF(AA58>0,"O Google leu como fórmula: digite de novo com ' na frente.",IF(IF(ISNUMBER($W$58),OR($W$58<0,$W$58>9,INT($W$58)<>$W$58),FALSE),"Combates fora de 0 a 9",IF($N$58>=4,"Quatro combates ou mais no dia é emergência (27.7)",""))) | N58: =IF(ISNUMBER($W$58),$W$58,COUNTIF($R$14:$R$18,"Combate")) | W58: =IF(ISERROR($G$58),"",IF(ISBLANK($G$58),"",$G$58)) | AA58: =ISERROR($G$58)*1
A59: Equipamento de faixa | B59: Se houve virada de faixa ou de Tier, o Cone e o Tier novos entram (25.1, 27.8). | H59: =IF(OR('Campanha'!$B$17=1,'Campanha'!$B$17=5,'Campanha'!$B$17=9,'Campanha'!$B$17=13,'Campanha'!$B$17=17),"Nível "&'Campanha'!$B$17&": faixa nova (Cone e Tier)",IF(OR('Campanha'!$B$17=7,'Campanha'!$B$17=18),"Nível "&'Campanha'!$B$17&": Tier novo","Nível "&'Campanha'!$B$17&": sem virada")) | K59: =IF(AA59>0,"O Google leu como fórmula: escolha de novo na lista.","") | AA59: =ISERROR($G$59)*1
A61: Diário de campanha (30 sessões; uma linha por sessão jogada, na ordem)
A62: D1 · A sessão
A63: Sessão nº (preencha) | B63: Data real | C63: Dia de campanha | D63: Marco atingido? | E63: Resumo (até 300 caracteres) | K63: Aviso
K64: =IF(AA64>0,"O Google leu como fórmula: escolha de novo ou digite com ' na frente.",IF(AND(LEN($T$64)>0,$T$64<>"Sim",$T$64<>"Não"),"Marco: escolha Sim ou Não","")) | N64: =0+IF(LEN($Q$64&$U$64&$R$64&$S$64&$T$64)>0,1,0) | O64: =IF($T$64="Sim",0,0+IF($T$64="Não",1,0)) | Q64: =IF(ISERROR($A$64),"",IF(ISBLANK($A$64),"",$A$64)) | R64: =IF(ISERROR($B$64),"",IF(ISBLANK($B$64),"",$B$64)) | S64: =IF(ISERROR($C$64),"",IF(ISBLANK($C$64),"",$C$64)) | T64: =IF(ISERROR($D$64),"",IF(ISBLANK($D$64),"",$D$64)) | U64: =IF(ISERROR($E$64),"",IF(ISBLANK($E$64),"",$E$64)) | AA64: =ISERROR($A$64)*1+ISERROR($B$64)*1+ISERROR($C$64)*1+ISERROR($D$64)*1+ISERROR($E$64)*1
K65: =IF(AA65>0,"O Google leu como fórmula: escolha de novo ou digite com ' na frente.",IF(AND(LEN($T$65)>0,$T$65<>"Sim",$T$65<>"Não"),"Marco: escolha Sim ou Não","")) | N65: =$N$64+IF(LEN($Q$65&$U$65&$R$65&$S$65&$T$65)>0,1,0) | O65: =IF($T$65="Sim",0,$O$64+IF($T$65="Não",1,0)) | Q65: =IF(ISERROR($A$65),"",IF(ISBLANK($A$65),"",$A$65)) | R65: =IF(ISERROR($B$65),"",IF(ISBLANK($B$65),"",$B$65)) | S65: =IF(ISERROR($C$65),"",IF(ISBLANK($C$65),"",$C$65)) | T65: =IF(ISERROR($D$65),"",IF(ISBLANK($D$65),"",$D$65)) | U65: =IF(ISERROR($E$65),"",IF(ISBLANK($E$65),"",$E$65)) | AA65: =ISERROR($A$65)*1+ISERROR($B$65)*1+ISERROR($C$65)*1+ISERROR($D$65)*1+ISERROR($E$65)*1
K66: =IF(AA66>0,"O Google leu como fórmula: escolha de novo ou digite com ' na frente.",IF(AND(LEN($T$66)>0,$T$66<>"Sim",$T$66<>"Não"),"Marco: escolha Sim ou Não","")) | N66: =$N$65+IF(LEN($Q$66&$U$66&$R$66&$S$66&$T$66)>0,1,0) | O66: =IF($T$66="Sim",0,$O$65+IF($T$66="Não",1,0)) | Q66: =IF(ISERROR($A$66),"",IF(ISBLANK($A$66),"",$A$66)) | R66: =IF(ISERROR($B$66),"",IF(ISBLANK($B$66),"",$B$66)) | S66: =IF(ISERROR($C$66),"",IF(ISBLANK($C$66),"",$C$66)) | T66: =IF(ISERROR($D$66),"",IF(ISBLANK($D$66),"",$D$66)) | U66: =IF(ISERROR($E$66),"",IF(ISBLANK($E$66),"",$E$66)) | AA66: =ISERROR($A$66)*1+ISERROR($B$66)*1+ISERROR($C$66)*1+ISERROR($D$66)*1+ISERROR($E$66)*1
K67: =IF(AA67>0,"O Google leu como fórmula: escolha de novo ou digite com ' na frente.",IF(AND(LEN($T$67)>0,$T$67<>"Sim",$T$67<>"Não"),"Marco: escolha Sim ou Não","")) | N67: =$N$66+IF(LEN($Q$67&$U$67&$R$67&$S$67&$T$67)>0,1,0) | O67: =IF($T$67="Sim",0,$O$66+IF($T$67="Não",1,0)) | Q67: =IF(ISERROR($A$67),"",IF(ISBLANK($A$67),"",$A$67)) | R67: =IF(ISERROR($B$67),"",IF(ISBLANK($B$67),"",$B$67)) | S67: =IF(ISERROR($C$67),"",IF(ISBLANK($C$67),"",$C$67)) | T67: =IF(ISERROR($D$67),"",IF(ISBLANK($D$67),"",$D$67)) | U67: =IF(ISERROR($E$67),"",IF(ISBLANK($E$67),"",$E$67)) | AA67: =ISERROR($A$67)*1+ISERROR($B$67)*1+ISERROR($C$67)*1+ISERROR($D$67)*1+ISERROR($E$67)*1
K68: =IF(AA68>0,"O Google leu como fórmula: escolha de novo ou digite com ' na frente.",IF(AND(LEN($T$68)>0,$T$68<>"Sim",$T$68<>"Não"),"Marco: escolha Sim ou Não","")) | N68: =$N$67+IF(LEN($Q$68&$U$68&$R$68&$S$68&$T$68)>0,1,0) | O68: =IF($T$68="Sim",0,$O$67+IF($T$68="Não",1,0)) | Q68: =IF(ISERROR($A$68),"",IF(ISBLANK($A$68),"",$A$68)) | R68: =IF(ISERROR($B$68),"",IF(ISBLANK($B$68),"",$B$68)) | S68: =IF(ISERROR($C$68),"",IF(ISBLANK($C$68),"",$C$68)) | T68: =IF(ISERROR($D$68),"",IF(ISBLANK($D$68),"",$D$68)) | U68: =IF(ISERROR($E$68),"",IF(ISBLANK($E$68),"",$E$68)) | AA68: =ISERROR($A$68)*1+ISERROR($B$68)*1+ISERROR($C$68)*1+ISERROR($D$68)*1+ISERROR($E$68)*1
K69: =IF(AA69>0,"O Google leu como fórmula: escolha de novo ou digite com ' na frente.",IF(AND(LEN($T$69)>0,$T$69<>"Sim",$T$69<>"Não"),"Marco: escolha Sim ou Não","")) | N69: =$N$68+IF(LEN($Q$69&$U$69&$R$69&$S$69&$T$69)>0,1,0) | O69: =IF($T$69="Sim",0,$O$68+IF($T$69="Não",1,0)) | Q69: =IF(ISERROR($A$69),"",IF(ISBLANK($A$69),"",$A$69)) | R69: =IF(ISERROR($B$69),"",IF(ISBLANK($B$69),"",$B$69)) | S69: =IF(ISERROR($C$69),"",IF(ISBLANK($C$69),"",$C$69)) | T69: =IF(ISERROR($D$69),"",IF(ISBLANK($D$69),"",$D$69)) | U69: =IF(ISERROR($E$69),"",IF(ISBLANK($E$69),"",$E$69)) | AA69: =ISERROR($A$69)*1+ISERROR($B$69)*1+ISERROR($C$69)*1+ISERROR($D$69)*1+ISERROR($E$69)*1
K70: =IF(AA70>0,"O Google leu como fórmula: escolha de novo ou digite com ' na frente.",IF(AND(LEN($T$70)>0,$T$70<>"Sim",$T$70<>"Não"),"Marco: escolha Sim ou Não","")) | N70: =$N$69+IF(LEN($Q$70&$U$70&$R$70&$S$70&$T$70)>0,1,0) | O70: =IF($T$70="Sim",0,$O$69+IF($T$70="Não",1,0)) | Q70: =IF(ISERROR($A$70),"",IF(ISBLANK($A$70),"",$A$70)) | R70: =IF(ISERROR($B$70),"",IF(ISBLANK($B$70),"",$B$70)) | S70: =IF(ISERROR($C$70),"",IF(ISBLANK($C$70),"",$C$70)) | T70: =IF(ISERROR($D$70),"",IF(ISBLANK($D$70),"",$D$70)) | U70: =IF(ISERROR($E$70),"",IF(ISBLANK($E$70),"",$E$70)) | AA70: =ISERROR($A$70)*1+ISERROR($B$70)*1+ISERROR($C$70)*1+ISERROR($D$70)*1+ISERROR($E$70)*1
K71: =IF(AA71>0,"O Google leu como fórmula: escolha de novo ou digite com ' na frente.",IF(AND(LEN($T$71)>0,$T$71<>"Sim",$T$71<>"Não"),"Marco: escolha Sim ou Não","")) | N71: =$N$70+IF(LEN($Q$71&$U$71&$R$71&$S$71&$T$71)>0,1,0) | O71: =IF($T$71="Sim",0,$O$70+IF($T$71="Não",1,0)) | Q71: =IF(ISERROR($A$71),"",IF(ISBLANK($A$71),"",$A$71)) | R71: =IF(ISERROR($B$71),"",IF(ISBLANK($B$71),"",$B$71)) | S71: =IF(ISERROR($C$71),"",IF(ISBLANK($C$71),"",$C$71)) | T71: =IF(ISERROR($D$71),"",IF(ISBLANK($D$71),"",$D$71)) | U71: =IF(ISERROR($E$71),"",IF(ISBLANK($E$71),"",$E$71)) | AA71: =ISERROR($A$71)*1+ISERROR($B$71)*1+ISERROR($C$71)*1+ISERROR($D$71)*1+ISERROR($E$71)*1
K72: =IF(AA72>0,"O Google leu como fórmula: escolha de novo ou digite com ' na frente.",IF(AND(LEN($T$72)>0,$T$72<>"Sim",$T$72<>"Não"),"Marco: escolha Sim ou Não","")) | N72: =$N$71+IF(LEN($Q$72&$U$72&$R$72&$S$72&$T$72)>0,1,0) | O72: =IF($T$72="Sim",0,$O$71+IF($T$72="Não",1,0)) | Q72: =IF(ISERROR($A$72),"",IF(ISBLANK($A$72),"",$A$72)) | R72: =IF(ISERROR($B$72),"",IF(ISBLANK($B$72),"",$B$72)) | S72: =IF(ISERROR($C$72),"",IF(ISBLANK($C$72),"",$C$72)) | T72: =IF(ISERROR($D$72),"",IF(ISBLANK($D$72),"",$D$72)) | U72: =IF(ISERROR($E$72),"",IF(ISBLANK($E$72),"",$E$72)) | AA72: =ISERROR($A$72)*1+ISERROR($B$72)*1+ISERROR($C$72)*1+ISERROR($D$72)*1+ISERROR($E$72)*1
K73: =IF(AA73>0,"O Google leu como fórmula: escolha de novo ou digite com ' na frente.",IF(AND(LEN($T$73)>0,$T$73<>"Sim",$T$73<>"Não"),"Marco: escolha Sim ou Não","")) | N73: =$N$72+IF(LEN($Q$73&$U$73&$R$73&$S$73&$T$73)>0,1,0) | O73: =IF($T$73="Sim",0,$O$72+IF($T$73="Não",1,0)) | Q73: =IF(ISERROR($A$73),"",IF(ISBLANK($A$73),"",$A$73)) | R73: =IF(ISERROR($B$73),"",IF(ISBLANK($B$73),"",$B$73)) | S73: =IF(ISERROR($C$73),"",IF(ISBLANK($C$73),"",$C$73)) | T73: =IF(ISERROR($D$73),"",IF(ISBLANK($D$73),"",$D$73)) | U73: =IF(ISERROR($E$73),"",IF(ISBLANK($E$73),"",$E$73)) | AA73: =ISERROR($A$73)*1+ISERROR($B$73)*1+ISERROR($C$73)*1+ISERROR($D$73)*1+ISERROR($E$73)*1
A74: Sessão nº (preencha) | B74: Data real | C74: Dia de campanha | D74: Marco atingido? | E74: Resumo (até 300 caracteres) | K74: Aviso
K75: =IF(AA75>0,"O Google leu como fórmula: escolha de novo ou digite com ' na frente.",IF(AND(LEN($T$75)>0,$T$75<>"Sim",$T$75<>"Não"),"Marco: escolha Sim ou Não","")) | N75: =$N$73+IF(LEN($Q$75&$U$75&$R$75&$S$75&$T$75)>0,1,0) | O75: =IF($T$75="Sim",0,$O$73+IF($T$75="Não",1,0)) | Q75: =IF(ISERROR($A$75),"",IF(ISBLANK($A$75),"",$A$75)) | R75: =IF(ISERROR($B$75),"",IF(ISBLANK($B$75),"",$B$75)) | S75: =IF(ISERROR($C$75),"",IF(ISBLANK($C$75),"",$C$75)) | T75: =IF(ISERROR($D$75),"",IF(ISBLANK($D$75),"",$D$75)) | U75: =IF(ISERROR($E$75),"",IF(ISBLANK($E$75),"",$E$75)) | AA75: =ISERROR($A$75)*1+ISERROR($B$75)*1+ISERROR($C$75)*1+ISERROR($D$75)*1+ISERROR($E$75)*1
K76: =IF(AA76>0,"O Google leu como fórmula: escolha de novo ou digite com ' na frente.",IF(AND(LEN($T$76)>0,$T$76<>"Sim",$T$76<>"Não"),"Marco: escolha Sim ou Não","")) | N76: =$N$75+IF(LEN($Q$76&$U$76&$R$76&$S$76&$T$76)>0,1,0) | O76: =IF($T$76="Sim",0,$O$75+IF($T$76="Não",1,0)) | Q76: =IF(ISERROR($A$76),"",IF(ISBLANK($A$76),"",$A$76)) | R76: =IF(ISERROR($B$76),"",IF(ISBLANK($B$76),"",$B$76)) | S76: =IF(ISERROR($C$76),"",IF(ISBLANK($C$76),"",$C$76)) | T76: =IF(ISERROR($D$76),"",IF(ISBLANK($D$76),"",$D$76)) | U76: =IF(ISERROR($E$76),"",IF(ISBLANK($E$76),"",$E$76)) | AA76: =ISERROR($A$76)*1+ISERROR($B$76)*1+ISERROR($C$76)*1+ISERROR($D$76)*1+ISERROR($E$76)*1
K77: =IF(AA77>0,"O Google leu como fórmula: escolha de novo ou digite com ' na frente.",IF(AND(LEN($T$77)>0,$T$77<>"Sim",$T$77<>"Não"),"Marco: escolha Sim ou Não","")) | N77: =$N$76+IF(LEN($Q$77&$U$77&$R$77&$S$77&$T$77)>0,1,0) | O77: =IF($T$77="Sim",0,$O$76+IF($T$77="Não",1,0)) | Q77: =IF(ISERROR($A$77),"",IF(ISBLANK($A$77),"",$A$77)) | R77: =IF(ISERROR($B$77),"",IF(ISBLANK($B$77),"",$B$77)) | S77: =IF(ISERROR($C$77),"",IF(ISBLANK($C$77),"",$C$77)) | T77: =IF(ISERROR($D$77),"",IF(ISBLANK($D$77),"",$D$77)) | U77: =IF(ISERROR($E$77),"",IF(ISBLANK($E$77),"",$E$77)) | AA77: =ISERROR($A$77)*1+ISERROR($B$77)*1+ISERROR($C$77)*1+ISERROR($D$77)*1+ISERROR($E$77)*1
K78: =IF(AA78>0,"O Google leu como fórmula: escolha de novo ou digite com ' na frente.",IF(AND(LEN($T$78)>0,$T$78<>"Sim",$T$78<>"Não"),"Marco: escolha Sim ou Não","")) | N78: =$N$77+IF(LEN($Q$78&$U$78&$R$78&$S$78&$T$78)>0,1,0) | O78: =IF($T$78="Sim",0,$O$77+IF($T$78="Não",1,0)) | Q78: =IF(ISERROR($A$78),"",IF(ISBLANK($A$78),"",$A$78)) | R78: =IF(ISERROR($B$78),"",IF(ISBLANK($B$78),"",$B$78)) | S78: =IF(ISERROR($C$78),"",IF(ISBLANK($C$78),"",$C$78)) | T78: =IF(ISERROR($D$78),"",IF(ISBLANK($D$78),"",$D$78)) | U78: =IF(ISERROR($E$78),"",IF(ISBLANK($E$78),"",$E$78)) | AA78: =ISERROR($A$78)*1+ISERROR($B$78)*1+ISERROR($C$78)*1+ISERROR($D$78)*1+ISERROR($E$78)*1
K79: =IF(AA79>0,"O Google leu como fórmula: escolha de novo ou digite com ' na frente.",IF(AND(LEN($T$79)>0,$T$79<>"Sim",$T$79<>"Não"),"Marco: escolha Sim ou Não","")) | N79: =$N$78+IF(LEN($Q$79&$U$79&$R$79&$S$79&$T$79)>0,1,0) | O79: =IF($T$79="Sim",0,$O$78+IF($T$79="Não",1,0)) | Q79: =IF(ISERROR($A$79),"",IF(ISBLANK($A$79),"",$A$79)) | R79: =IF(ISERROR($B$79),"",IF(ISBLANK($B$79),"",$B$79)) | S79: =IF(ISERROR($C$79),"",IF(ISBLANK($C$79),"",$C$79)) | T79: =IF(ISERROR($D$79),"",IF(ISBLANK($D$79),"",$D$79)) | U79: =IF(ISERROR($E$79),"",IF(ISBLANK($E$79),"",$E$79)) | AA79: =ISERROR($A$79)*1+ISERROR($B$79)*1+ISERROR($C$79)*1+ISERROR($D$79)*1+ISERROR($E$79)*1
K80: =IF(AA80>0,"O Google leu como fórmula: escolha de novo ou digite com ' na frente.",IF(AND(LEN($T$80)>0,$T$80<>"Sim",$T$80<>"Não"),"Marco: escolha Sim ou Não","")) | N80: =$N$79+IF(LEN($Q$80&$U$80&$R$80&$S$80&$T$80)>0,1,0) | O80: =IF($T$80="Sim",0,$O$79+IF($T$80="Não",1,0)) | Q80: =IF(ISERROR($A$80),"",IF(ISBLANK($A$80),"",$A$80)) | R80: =IF(ISERROR($B$80),"",IF(ISBLANK($B$80),"",$B$80)) | S80: =IF(ISERROR($C$80),"",IF(ISBLANK($C$80),"",$C$80)) | T80: =IF(ISERROR($D$80),"",IF(ISBLANK($D$80),"",$D$80)) | U80: =IF(ISERROR($E$80),"",IF(ISBLANK($E$80),"",$E$80)) | AA80: =ISERROR($A$80)*1+ISERROR($B$80)*1+ISERROR($C$80)*1+ISERROR($D$80)*1+ISERROR($E$80)*1
K81: =IF(AA81>0,"O Google leu como fórmula: escolha de novo ou digite com ' na frente.",IF(AND(LEN($T$81)>0,$T$81<>"Sim",$T$81<>"Não"),"Marco: escolha Sim ou Não","")) | N81: =$N$80+IF(LEN($Q$81&$U$81&$R$81&$S$81&$T$81)>0,1,0) | O81: =IF($T$81="Sim",0,$O$80+IF($T$81="Não",1,0)) | Q81: =IF(ISERROR($A$81),"",IF(ISBLANK($A$81),"",$A$81)) | R81: =IF(ISERROR($B$81),"",IF(ISBLANK($B$81),"",$B$81)) | S81: =IF(ISERROR($C$81),"",IF(ISBLANK($C$81),"",$C$81)) | T81: =IF(ISERROR($D$81),"",IF(ISBLANK($D$81),"",$D$81)) | U81: =IF(ISERROR($E$81),"",IF(ISBLANK($E$81),"",$E$81)) | AA81: =ISERROR($A$81)*1+ISERROR($B$81)*1+ISERROR($C$81)*1+ISERROR($D$81)*1+ISERROR($E$81)*1
K82: =IF(AA82>0,"O Google leu como fórmula: escolha de novo ou digite com ' na frente.",IF(AND(LEN($T$82)>0,$T$82<>"Sim",$T$82<>"Não"),"Marco: escolha Sim ou Não","")) | N82: =$N$81+IF(LEN($Q$82&$U$82&$R$82&$S$82&$T$82)>0,1,0) | O82: =IF($T$82="Sim",0,$O$81+IF($T$82="Não",1,0)) | Q82: =IF(ISERROR($A$82),"",IF(ISBLANK($A$82),"",$A$82)) | R82: =IF(ISERROR($B$82),"",IF(ISBLANK($B$82),"",$B$82)) | S82: =IF(ISERROR($C$82),"",IF(ISBLANK($C$82),"",$C$82)) | T82: =IF(ISERROR($D$82),"",IF(ISBLANK($D$82),"",$D$82)) | U82: =IF(ISERROR($E$82),"",IF(ISBLANK($E$82),"",$E$82)) | AA82: =ISERROR($A$82)*1+ISERROR($B$82)*1+ISERROR($C$82)*1+ISERROR($D$82)*1+ISERROR($E$82)*1
K83: =IF(AA83>0,"O Google leu como fórmula: escolha de novo ou digite com ' na frente.",IF(AND(LEN($T$83)>0,$T$83<>"Sim",$T$83<>"Não"),"Marco: escolha Sim ou Não","")) | N83: =$N$82+IF(LEN($Q$83&$U$83&$R$83&$S$83&$T$83)>0,1,0) | O83: =IF($T$83="Sim",0,$O$82+IF($T$83="Não",1,0)) | Q83: =IF(ISERROR($A$83),"",IF(ISBLANK($A$83),"",$A$83)) | R83: =IF(ISERROR($B$83),"",IF(ISBLANK($B$83),"",$B$83)) | S83: =IF(ISERROR($C$83),"",IF(ISBLANK($C$83),"",$C$83)) | T83: =IF(ISERROR($D$83),"",IF(ISBLANK($D$83),"",$D$83)) | U83: =IF(ISERROR($E$83),"",IF(ISBLANK($E$83),"",$E$83)) | AA83: =ISERROR($A$83)*1+ISERROR($B$83)*1+ISERROR($C$83)*1+ISERROR($D$83)*1+ISERROR($E$83)*1
K84: =IF(AA84>0,"O Google leu como fórmula: escolha de novo ou digite com ' na frente.",IF(AND(LEN($T$84)>0,$T$84<>"Sim",$T$84<>"Não"),"Marco: escolha Sim ou Não","")) | N84: =$N$83+IF(LEN($Q$84&$U$84&$R$84&$S$84&$T$84)>0,1,0) | O84: =IF($T$84="Sim",0,$O$83+IF($T$84="Não",1,0)) | Q84: =IF(ISERROR($A$84),"",IF(ISBLANK($A$84),"",$A$84)) | R84: =IF(ISERROR($B$84),"",IF(ISBLANK($B$84),"",$B$84)) | S84: =IF(ISERROR($C$84),"",IF(ISBLANK($C$84),"",$C$84)) | T84: =IF(ISERROR($D$84),"",IF(ISBLANK($D$84),"",$D$84)) | U84: =IF(ISERROR($E$84),"",IF(ISBLANK($E$84),"",$E$84)) | AA84: =ISERROR($A$84)*1+ISERROR($B$84)*1+ISERROR($C$84)*1+ISERROR($D$84)*1+ISERROR($E$84)*1
A85: Sessão nº (preencha) | B85: Data real | C85: Dia de campanha | D85: Marco atingido? | E85: Resumo (até 300 caracteres) | K85: Aviso
K86: =IF(AA86>0,"O Google leu como fórmula: escolha de novo ou digite com ' na frente.",IF(AND(LEN($T$86)>0,$T$86<>"Sim",$T$86<>"Não"),"Marco: escolha Sim ou Não","")) | N86: =$N$84+IF(LEN($Q$86&$U$86&$R$86&$S$86&$T$86)>0,1,0) | O86: =IF($T$86="Sim",0,$O$84+IF($T$86="Não",1,0)) | Q86: =IF(ISERROR($A$86),"",IF(ISBLANK($A$86),"",$A$86)) | R86: =IF(ISERROR($B$86),"",IF(ISBLANK($B$86),"",$B$86)) | S86: =IF(ISERROR($C$86),"",IF(ISBLANK($C$86),"",$C$86)) | T86: =IF(ISERROR($D$86),"",IF(ISBLANK($D$86),"",$D$86)) | U86: =IF(ISERROR($E$86),"",IF(ISBLANK($E$86),"",$E$86)) | AA86: =ISERROR($A$86)*1+ISERROR($B$86)*1+ISERROR($C$86)*1+ISERROR($D$86)*1+ISERROR($E$86)*1
K87: =IF(AA87>0,"O Google leu como fórmula: escolha de novo ou digite com ' na frente.",IF(AND(LEN($T$87)>0,$T$87<>"Sim",$T$87<>"Não"),"Marco: escolha Sim ou Não","")) | N87: =$N$86+IF(LEN($Q$87&$U$87&$R$87&$S$87&$T$87)>0,1,0) | O87: =IF($T$87="Sim",0,$O$86+IF($T$87="Não",1,0)) | Q87: =IF(ISERROR($A$87),"",IF(ISBLANK($A$87),"",$A$87)) | R87: =IF(ISERROR($B$87),"",IF(ISBLANK($B$87),"",$B$87)) | S87: =IF(ISERROR($C$87),"",IF(ISBLANK($C$87),"",$C$87)) | T87: =IF(ISERROR($D$87),"",IF(ISBLANK($D$87),"",$D$87)) | U87: =IF(ISERROR($E$87),"",IF(ISBLANK($E$87),"",$E$87)) | AA87: =ISERROR($A$87)*1+ISERROR($B$87)*1+ISERROR($C$87)*1+ISERROR($D$87)*1+ISERROR($E$87)*1
K88: =IF(AA88>0,"O Google leu como fórmula: escolha de novo ou digite com ' na frente.",IF(AND(LEN($T$88)>0,$T$88<>"Sim",$T$88<>"Não"),"Marco: escolha Sim ou Não","")) | N88: =$N$87+IF(LEN($Q$88&$U$88&$R$88&$S$88&$T$88)>0,1,0) | O88: =IF($T$88="Sim",0,$O$87+IF($T$88="Não",1,0)) | Q88: =IF(ISERROR($A$88),"",IF(ISBLANK($A$88),"",$A$88)) | R88: =IF(ISERROR($B$88),"",IF(ISBLANK($B$88),"",$B$88)) | S88: =IF(ISERROR($C$88),"",IF(ISBLANK($C$88),"",$C$88)) | T88: =IF(ISERROR($D$88),"",IF(ISBLANK($D$88),"",$D$88)) | U88: =IF(ISERROR($E$88),"",IF(ISBLANK($E$88),"",$E$88)) | AA88: =ISERROR($A$88)*1+ISERROR($B$88)*1+ISERROR($C$88)*1+ISERROR($D$88)*1+ISERROR($E$88)*1
K89: =IF(AA89>0,"O Google leu como fórmula: escolha de novo ou digite com ' na frente.",IF(AND(LEN($T$89)>0,$T$89<>"Sim",$T$89<>"Não"),"Marco: escolha Sim ou Não","")) | N89: =$N$88+IF(LEN($Q$89&$U$89&$R$89&$S$89&$T$89)>0,1,0) | O89: =IF($T$89="Sim",0,$O$88+IF($T$89="Não",1,0)) | Q89: =IF(ISERROR($A$89),"",IF(ISBLANK($A$89),"",$A$89)) | R89: =IF(ISERROR($B$89),"",IF(ISBLANK($B$89),"",$B$89)) | S89: =IF(ISERROR($C$89),"",IF(ISBLANK($C$89),"",$C$89)) | T89: =IF(ISERROR($D$89),"",IF(ISBLANK($D$89),"",$D$89)) | U89: =IF(ISERROR($E$89),"",IF(ISBLANK($E$89),"",$E$89)) | AA89: =ISERROR($A$89)*1+ISERROR($B$89)*1+ISERROR($C$89)*1+ISERROR($D$89)*1+ISERROR($E$89)*1
K90: =IF(AA90>0,"O Google leu como fórmula: escolha de novo ou digite com ' na frente.",IF(AND(LEN($T$90)>0,$T$90<>"Sim",$T$90<>"Não"),"Marco: escolha Sim ou Não","")) | N90: =$N$89+IF(LEN($Q$90&$U$90&$R$90&$S$90&$T$90)>0,1,0) | O90: =IF($T$90="Sim",0,$O$89+IF($T$90="Não",1,0)) | Q90: =IF(ISERROR($A$90),"",IF(ISBLANK($A$90),"",$A$90)) | R90: =IF(ISERROR($B$90),"",IF(ISBLANK($B$90),"",$B$90)) | S90: =IF(ISERROR($C$90),"",IF(ISBLANK($C$90),"",$C$90)) | T90: =IF(ISERROR($D$90),"",IF(ISBLANK($D$90),"",$D$90)) | U90: =IF(ISERROR($E$90),"",IF(ISBLANK($E$90),"",$E$90)) | AA90: =ISERROR($A$90)*1+ISERROR($B$90)*1+ISERROR($C$90)*1+ISERROR($D$90)*1+ISERROR($E$90)*1
K91: =IF(AA91>0,"O Google leu como fórmula: escolha de novo ou digite com ' na frente.",IF(AND(LEN($T$91)>0,$T$91<>"Sim",$T$91<>"Não"),"Marco: escolha Sim ou Não","")) | N91: =$N$90+IF(LEN($Q$91&$U$91&$R$91&$S$91&$T$91)>0,1,0) | O91: =IF($T$91="Sim",0,$O$90+IF($T$91="Não",1,0)) | Q91: =IF(ISERROR($A$91),"",IF(ISBLANK($A$91),"",$A$91)) | R91: =IF(ISERROR($B$91),"",IF(ISBLANK($B$91),"",$B$91)) | S91: =IF(ISERROR($C$91),"",IF(ISBLANK($C$91),"",$C$91)) | T91: =IF(ISERROR($D$91),"",IF(ISBLANK($D$91),"",$D$91)) | U91: =IF(ISERROR($E$91),"",IF(ISBLANK($E$91),"",$E$91)) | AA91: =ISERROR($A$91)*1+ISERROR($B$91)*1+ISERROR($C$91)*1+ISERROR($D$91)*1+ISERROR($E$91)*1
K92: =IF(AA92>0,"O Google leu como fórmula: escolha de novo ou digite com ' na frente.",IF(AND(LEN($T$92)>0,$T$92<>"Sim",$T$92<>"Não"),"Marco: escolha Sim ou Não","")) | N92: =$N$91+IF(LEN($Q$92&$U$92&$R$92&$S$92&$T$92)>0,1,0) | O92: =IF($T$92="Sim",0,$O$91+IF($T$92="Não",1,0)) | Q92: =IF(ISERROR($A$92),"",IF(ISBLANK($A$92),"",$A$92)) | R92: =IF(ISERROR($B$92),"",IF(ISBLANK($B$92),"",$B$92)) | S92: =IF(ISERROR($C$92),"",IF(ISBLANK($C$92),"",$C$92)) | T92: =IF(ISERROR($D$92),"",IF(ISBLANK($D$92),"",$D$92)) | U92: =IF(ISERROR($E$92),"",IF(ISBLANK($E$92),"",$E$92)) | AA92: =ISERROR($A$92)*1+ISERROR($B$92)*1+ISERROR($C$92)*1+ISERROR($D$92)*1+ISERROR($E$92)*1
K93: =IF(AA93>0,"O Google leu como fórmula: escolha de novo ou digite com ' na frente.",IF(AND(LEN($T$93)>0,$T$93<>"Sim",$T$93<>"Não"),"Marco: escolha Sim ou Não","")) | N93: =$N$92+IF(LEN($Q$93&$U$93&$R$93&$S$93&$T$93)>0,1,0) | O93: =IF($T$93="Sim",0,$O$92+IF($T$93="Não",1,0)) | Q93: =IF(ISERROR($A$93),"",IF(ISBLANK($A$93),"",$A$93)) | R93: =IF(ISERROR($B$93),"",IF(ISBLANK($B$93),"",$B$93)) | S93: =IF(ISERROR($C$93),"",IF(ISBLANK($C$93),"",$C$93)) | T93: =IF(ISERROR($D$93),"",IF(ISBLANK($D$93),"",$D$93)) | U93: =IF(ISERROR($E$93),"",IF(ISBLANK($E$93),"",$E$93)) | AA93: =ISERROR($A$93)*1+ISERROR($B$93)*1+ISERROR($C$93)*1+ISERROR($D$93)*1+ISERROR($E$93)*1
K94: =IF(AA94>0,"O Google leu como fórmula: escolha de novo ou digite com ' na frente.",IF(AND(LEN($T$94)>0,$T$94<>"Sim",$T$94<>"Não"),"Marco: escolha Sim ou Não","")) | N94: =$N$93+IF(LEN($Q$94&$U$94&$R$94&$S$94&$T$94)>0,1,0) | O94: =IF($T$94="Sim",0,$O$93+IF($T$94="Não",1,0)) | Q94: =IF(ISERROR($A$94),"",IF(ISBLANK($A$94),"",$A$94)) | R94: =IF(ISERROR($B$94),"",IF(ISBLANK($B$94),"",$B$94)) | S94: =IF(ISERROR($C$94),"",IF(ISBLANK($C$94),"",$C$94)) | T94: =IF(ISERROR($D$94),"",IF(ISBLANK($D$94),"",$D$94)) | U94: =IF(ISERROR($E$94),"",IF(ISBLANK($E$94),"",$E$94)) | AA94: =ISERROR($A$94)*1+ISERROR($B$94)*1+ISERROR($C$94)*1+ISERROR($D$94)*1+ISERROR($E$94)*1
K95: =IF(AA95>0,"O Google leu como fórmula: escolha de novo ou digite com ' na frente.",IF(AND(LEN($T$95)>0,$T$95<>"Sim",$T$95<>"Não"),"Marco: escolha Sim ou Não","")) | N95: =$N$94+IF(LEN($Q$95&$U$95&$R$95&$S$95&$T$95)>0,1,0) | O95: =IF($T$95="Sim",0,$O$94+IF($T$95="Não",1,0)) | Q95: =IF(ISERROR($A$95),"",IF(ISBLANK($A$95),"",$A$95)) | R95: =IF(ISERROR($B$95),"",IF(ISBLANK($B$95),"",$B$95)) | S95: =IF(ISERROR($C$95),"",IF(ISBLANK($C$95),"",$C$95)) | T95: =IF(ISERROR($D$95),"",IF(ISBLANK($D$95),"",$D$95)) | U95: =IF(ISERROR($E$95),"",IF(ISBLANK($E$95),"",$E$95)) | AA95: =ISERROR($A$95)*1+ISERROR($B$95)*1+ISERROR($C$95)*1+ISERROR($D$95)*1+ISERROR($E$95)*1
A96: D2 · O que ficou
A97: Sessão | B97: Decisões importantes | E97: Ganchos abertos | H97: NPCs que apareceram | K97: Aviso
A98: =IF(ISNUMBER($Q$64),"Sessão "&$Q$64,"Linha 1") | K98: =IF(AA98>0,"O Google leu como fórmula: digite de novo com ' na frente.","") | AA98: =ISERROR($B$98)*1+ISERROR($E$98)*1+ISERROR($H$98)*1
A99: =IF(ISNUMBER($Q$65),"Sessão "&$Q$65,"Linha 2") | K99: =IF(AA99>0,"O Google leu como fórmula: digite de novo com ' na frente.","") | AA99: =ISERROR($B$99)*1+ISERROR($E$99)*1+ISERROR($H$99)*1
A100: =IF(ISNUMBER($Q$66),"Sessão "&$Q$66,"Linha 3") | K100: =IF(AA100>0,"O Google leu como fórmula: digite de novo com ' na frente.","") | AA100: =ISERROR($B$100)*1+ISERROR($E$100)*1+ISERROR($H$100)*1
A101: =IF(ISNUMBER($Q$67),"Sessão "&$Q$67,"Linha 4") | K101: =IF(AA101>0,"O Google leu como fórmula: digite de novo com ' na frente.","") | AA101: =ISERROR($B$101)*1+ISERROR($E$101)*1+ISERROR($H$101)*1
A102: =IF(ISNUMBER($Q$68),"Sessão "&$Q$68,"Linha 5") | K102: =IF(AA102>0,"O Google leu como fórmula: digite de novo com ' na frente.","") | AA102: =ISERROR($B$102)*1+ISERROR($E$102)*1+ISERROR($H$102)*1
A103: =IF(ISNUMBER($Q$69),"Sessão "&$Q$69,"Linha 6") | K103: =IF(AA103>0,"O Google leu como fórmula: digite de novo com ' na frente.","") | AA103: =ISERROR($B$103)*1+ISERROR($E$103)*1+ISERROR($H$103)*1
A104: =IF(ISNUMBER($Q$70),"Sessão "&$Q$70,"Linha 7") | K104: =IF(AA104>0,"O Google leu como fórmula: digite de novo com ' na frente.","") | AA104: =ISERROR($B$104)*1+ISERROR($E$104)*1+ISERROR($H$104)*1
A105: =IF(ISNUMBER($Q$71),"Sessão "&$Q$71,"Linha 8") | K105: =IF(AA105>0,"O Google leu como fórmula: digite de novo com ' na frente.","") | AA105: =ISERROR($B$105)*1+ISERROR($E$105)*1+ISERROR($H$105)*1
A106: =IF(ISNUMBER($Q$72),"Sessão "&$Q$72,"Linha 9") | K106: =IF(AA106>0,"O Google leu como fórmula: digite de novo com ' na frente.","") | AA106: =ISERROR($B$106)*1+ISERROR($E$106)*1+ISERROR($H$106)*1
A107: =IF(ISNUMBER($Q$73),"Sessão "&$Q$73,"Linha 10") | K107: =IF(AA107>0,"O Google leu como fórmula: digite de novo com ' na frente.","") | AA107: =ISERROR($B$107)*1+ISERROR($E$107)*1+ISERROR($H$107)*1
...

Sheet Missões
A1: Missões — Explorando Galáxias v1.2
A2: Legenda: | B2: Entrada (preencha) | C2: Calculada (automático) | D2: Aviso (texto em vermelho) | F2: Título de bloco | G2: Cabeçalho de coluna | H2: Rótulo da linha | I2: Linha alternada (outro tom) | J2: Não se aplica
A3: As missões oferecidas, ativas e concluídas (cole a linha de saída da aba Aventuras).
A5: Missões (20 linhas): cole a linha de saída da aba Aventuras em A:J da M1 (Colar especial → Somente valores) | AA5: ='Tabelas'!$AB$472&""
A6: M1 · A missão (mesma ordem de colunas da linha de saída da aba Aventuras, D6) | AA6: ='Tabelas'!$AB$473&""
A7: Missão (preencha) | B7: Tipo | C7: Contratante | E7: Objetivo | G7: Local | H7: Prazo | I7: Estado | J7: Recompensa combinada | K7: Aviso | AA7: ='Tabelas'!$AB$474&""
K8: =IF(AL8>0,"O Google leu como fórmula: escolha de novo ou digite com ' na frente.",IF(AND(LEN($AK$8)>0,COUNTIF('Dados'!$BV$6:$BV$10,$AK$8)=0),"Estado fora da lista",IF(AND(LEN($AC$8)=0,LEN($AK$8&$AG$8)>0),"Linha sem o nome da missão",""))) | AA8: ='Tabelas'!$AB$475&"" | AC8: =IF(ISERROR($A$8),"",IF(ISBLANK($A$8),"",$A$8)) | AG8: =IF(ISERROR($E$8),"",IF(ISBLANK($E$8),"",$E$8)) | AK8: =IF(ISERROR($I$8),"",IF(ISBLANK($I$8),"",$I$8)) | AL8: =ISERROR($A$8)*1+ISERROR($B$8)*1+ISERROR($C$8)*1+ISERROR($E$8)*1+ISERROR($G$8)*1+ISERROR($H$8)*1+ISERROR($I$8)*1+ISERROR($J$8)*1
K9: =IF(AL9>0,"O Google leu como fórmula: escolha de novo ou digite com ' na frente.",IF(AND(LEN($AK$9)>0,COUNTIF('Dados'!$BV$6:$BV$10,$AK$9)=0),"Estado fora da lista",IF(AND(LEN($AC$9)=0,LEN($AK$9&$AG$9)>0),"Linha sem o nome da missão",""))) | AA9: ='Tabelas'!$AB$476&"" | AC9: =IF(ISERROR($A$9),"",IF(ISBLANK($A$9),"",$A$9)) | AG9: =IF(ISERROR($E$9),"",IF(ISBLANK($E$9),"",$E$9)) | AK9: =IF(ISERROR($I$9),"",IF(ISBLANK($I$9),"",$I$9)) | AL9: =ISERROR($A$9)*1+ISERROR($B$9)*1+ISERROR($C$9)*1+ISERROR($E$9)*1+ISERROR($G$9)*1+ISERROR($H$9)*1+ISERROR($I$9)*1+ISERROR($J$9)*1
K10: =IF(AL10>0,"O Google leu como fórmula: escolha de novo ou digite com ' na frente.",IF(AND(LEN($AK$10)>0,COUNTIF('Dados'!$BV$6:$BV$10,$AK$10)=0),"Estado fora da lista",IF(AND(LEN($AC$10)=0,LEN($AK$10&$AG$10)>0),"Linha sem o nome da missão",""))) | AA10: ='Tabelas'!$AB$477&"" | AC10: =IF(ISERROR($A$10),"",IF(ISBLANK($A$10),"",$A$10)) | AG10: =IF(ISERROR($E$10),"",IF(ISBLANK($E$10),"",$E$10)) | AK10: =IF(ISERROR($I$10),"",IF(ISBLANK($I$10),"",$I$10)) | AL10: =ISERROR($A$10)*1+ISERROR($B$10)*1+ISERROR($C$10)*1+ISERROR($E$10)*1+ISERROR($G$10)*1+ISERROR($H$10)*1+ISERROR($I$10)*1+ISERROR($J$10)*1
K11: =IF(AL11>0,"O Google leu como fórmula: escolha de novo ou digite com ' na frente.",IF(AND(LEN($AK$11)>0,COUNTIF('Dados'!$BV$6:$BV$10,$AK$11)=0),"Estado fora da lista",IF(AND(LEN($AC$11)=0,LEN($AK$11&$AG$11)>0),"Linha sem o nome da missão",""))) | AA11: ='Tabelas'!$AB$478&"" | AC11: =IF(ISERROR($A$11),"",IF(ISBLANK($A$11),"",$A$11)) | AG11: =IF(ISERROR($E$11),"",IF(ISBLANK($E$11),"",$E$11)) | AK11: =IF(ISERROR($I$11),"",IF(ISBLANK($I$11),"",$I$11)) | AL11: =ISERROR($A$11)*1+ISERROR($B$11)*1+ISERROR($C$11)*1+ISERROR($E$11)*1+ISERROR($G$11)*1+ISERROR($H$11)*1+ISERROR($I$11)*1+ISERROR($J$11)*1
K12: =IF(AL12>0,"O Google leu como fórmula: escolha de novo ou digite com ' na frente.",IF(AND(LEN($AK$12)>0,COUNTIF('Dados'!$BV$6:$BV$10,$AK$12)=0),"Estado fora da lista",IF(AND(LEN($AC$12)=0,LEN($AK$12&$AG$12)>0),"Linha sem o nome da missão",""))) | AA12: ='Tabelas'!$AB$479&"" | AC12: =IF(ISERROR($A$12),"",IF(ISBLANK($A$12),"",$A$12)) | AG12: =IF(ISERROR($E$12),"",IF(ISBLANK($E$12),"",$E$12)) | AK12: =IF(ISERROR($I$12),"",IF(ISBLANK($I$12),"",$I$12)) | AL12: =ISERROR($A$12)*1+ISERROR($B$12)*1+ISERROR($C$12)*1+ISERROR($E$12)*1+ISERROR($G$12)*1+ISERROR($H$12)*1+ISERROR($I$12)*1+ISERROR($J$12)*1
K13: =IF(AL13>0,"O Google leu como fórmula: escolha de novo ou digite com ' na frente.",IF(AND(LEN($AK$13)>0,COUNTIF('Dados'!$BV$6:$BV$10,$AK$13)=0),"Estado fora da lista",IF(AND(LEN($AC$13)=0,LEN($AK$13&$AG$13)>0),"Linha sem o nome da missão",""))) | AA13: ='Tabelas'!$AB$480&"" | AC13: =IF(ISERROR($A$13),"",IF(ISBLANK($A$13),"",$A$13)) | AG13: =IF(ISERROR($E$13),"",IF(ISBLANK($E$13),"",$E$13)) | AK13: =IF(ISERROR($I$13),"",IF(ISBLANK($I$13),"",$I$13)) | AL13: =ISERROR($A$13)*1+ISERROR($B$13)*1+ISERROR($C$13)*1+ISERROR($E$13)*1+ISERROR($G$13)*1+ISERROR($H$13)*1+ISERROR($I$13)*1+ISERROR($J$13)*1
K14: =IF(AL14>0,"O Google leu como fórmula: escolha de novo ou digite com ' na frente.",IF(AND(LEN($AK$14)>0,COUNTIF('Dados'!$BV$6:$BV$10,$AK$14)=0),"Estado fora da lista",IF(AND(LEN($AC$14)=0,LEN($AK$14&$AG$14)>0),"Linha sem o nome da missão",""))) | AA14: ='Tabelas'!$AB$481&"" | AC14: =IF(ISERROR($A$14),"",IF(ISBLANK($A$14),"",$A$14)) | AG14: =IF(ISERROR($E$14),"",IF(ISBLANK($E$14),"",$E$14)) | AK14: =IF(ISERROR($I$14),"",IF(ISBLANK($I$14),"",$I$14)) | AL14: =ISERROR($A$14)*1+ISERROR($B$14)*1+ISERROR($C$14)*1+ISERROR($E$14)*1+ISERROR($G$14)*1+ISERROR($H$14)*1+ISERROR($I$14)*1+ISERROR($J$14)*1
K15: =IF(AL15>0,"O Google leu como fórmula: escolha de novo ou digite com ' na frente.",IF(AND(LEN($AK$15)>0,COUNTIF('Dados'!$BV$6:$BV$10,$AK$15)=0),"Estado fora da lista",IF(AND(LEN($AC$15)=0,LEN($AK$15&$AG$15)>0),"Linha sem o nome da missão",""))) | AA15: ='Tabelas'!$AB$482&"" | AC15: =IF(ISERROR($A$15),"",IF(ISBLANK($A$15),"",$A$15)) | AG15: =IF(ISERROR($E$15),"",IF(ISBLANK($E$15),"",$E$15)) | AK15: =IF(ISERROR($I$15),"",IF(ISBLANK($I$15),"",$I$15)) | AL15: =ISERROR($A$15)*1+ISERROR($B$15)*1+ISERROR($C$15)*1+ISERROR($E$15)*1+ISERROR($G$15)*1+ISERROR($H$15)*1+ISERROR($I$15)*1+ISERROR($J$15)*1
K16: =IF(AL16>0,"O Google leu como fórmula: escolha de novo ou digite com ' na frente.",IF(AND(LEN($AK$16)>0,COUNTIF('Dados'!$BV$6:$BV$10,$AK$16)=0),"Estado fora da lista",IF(AND(LEN($AC$16)=0,LEN($AK$16&$AG$16)>0),"Linha sem o nome da missão",""))) | AA16: ='Tabelas'!$AB$483&"" | AC16: =IF(ISERROR($A$16),"",IF(ISBLANK($A$16),"",$A$16)) | AG16: =IF(ISERROR($E$16),"",IF(ISBLANK($E$16),"",$E$16)) | AK16: =IF(ISERROR($I$16),"",IF(ISBLANK($I$16),"",$I$16)) | AL16: =ISERROR($A$16)*1+ISERROR($B$16)*1+ISERROR($C$16)*1+ISERROR($E$16)*1+ISERROR($G$16)*1+ISERROR($H$16)*1+ISERROR($I$16)*1+ISERROR($J$16)*1
K17: =IF(AL17>0,"O Google leu como fórmula: escolha de novo ou digite com ' na frente.",IF(AND(LEN($AK$17)>0,COUNTIF('Dados'!$BV$6:$BV$10,$AK$17)=0),"Estado fora da lista",IF(AND(LEN($AC$17)=0,LEN($AK$17&$AG$17)>0),"Linha sem o nome da missão",""))) | AA17: ='Tabelas'!$AB$484&"" | AC17: =IF(ISERROR($A$17),"",IF(ISBLANK($A$17),"",$A$17)) | AG17: =IF(ISERROR($E$17),"",IF(ISBLANK($E$17),"",$E$17)) | AK17: =IF(ISERROR($I$17),"",IF(ISBLANK($I$17),"",$I$17)) | AL17: =ISERROR($A$17)*1+ISERROR($B$17)*1+ISERROR($C$17)*1+ISERROR($E$17)*1+ISERROR($G$17)*1+ISERROR($H$17)*1+ISERROR($I$17)*1+ISERROR($J$17)*1
A18: Missão (preencha) | B18: Tipo | C18: Contratante | E18: Objetivo | G18: Local | H18: Prazo | I18: Estado | J18: Recompensa combinada | K18: Aviso | AA18: ='Tabelas'!$AB$486&"" | AK18: =IF(ISERROR($I$18),"",IF(ISBLANK($I$18),"",$I$18))
K19: =IF(AL19>0,"O Google leu como fórmula: escolha de novo ou digite com ' na frente.",IF(AND(LEN($AK$19)>0,COUNTIF('Dados'!$BV$6:$BV$10,$AK$19)=0),"Estado fora da lista",IF(AND(LEN($AC$19)=0,LEN($AK$19&$AG$19)>0),"Linha sem o nome da missão",""))) | AA19: ='Tabelas'!$AB$487&"" | AC19: =IF(ISERROR($A$19),"",IF(ISBLANK($A$19),"",$A$19)) | AG19: =IF(ISERROR($E$19),"",IF(ISBLANK($E$19),"",$E$19)) | AK19: =IF(ISERROR($I$19),"",IF(ISBLANK($I$19),"",$I$19)) | AL19: =ISERROR($A$19)*1+ISERROR($B$19)*1+ISERROR($C$19)*1+ISERROR($E$19)*1+ISERROR($G$19)*1+ISERROR($H$19)*1+ISERROR($I$19)*1+ISERROR($J$19)*1
K20: =IF(AL20>0,"O Google leu como fórmula: escolha de novo ou digite com ' na frente.",IF(AND(LEN($AK$20)>0,COUNTIF('Dados'!$BV$6:$BV$10,$AK$20)=0),"Estado fora da lista",IF(AND(LEN($AC$20)=0,LEN($AK$20&$AG$20)>0),"Linha sem o nome da missão",""))) | AA20: ='Tabelas'!$AB$488&"" | AC20: =IF(ISERROR($A$20),"",IF(ISBLANK($A$20),"",$A$20)) | AG20: =IF(ISERROR($E$20),"",IF(ISBLANK($E$20),"",$E$20)) | AK20: =IF(ISERROR($I$20),"",IF(ISBLANK($I$20),"",$I$20)) | AL20: =ISERROR($A$20)*1+ISERROR($B$20)*1+ISERROR($C$20)*1+ISERROR($E$20)*1+ISERROR($G$20)*1+ISERROR($H$20)*1+ISERROR($I$20)*1+ISERROR($J$20)*1
K21: =IF(AL21>0,"O Google leu como fórmula: escolha de novo ou digite com ' na frente.",IF(AND(LEN($AK$21)>0,COUNTIF('Dados'!$BV$6:$BV$10,$AK$21)=0),"Estado fora da lista",IF(AND(LEN($AC$21)=0,LEN($AK$21&$AG$21)>0),"Linha sem o nome da missão",""))) | AA21: ='Tabelas'!$AB$489&"" | AC21: =IF(ISERROR($A$21),"",IF(ISBLANK($A$21),"",$A$21)) | AG21: =IF(ISERROR($E$21),"",IF(ISBLANK($E$21),"",$E$21)) | AK21: =IF(ISERROR($I$21),"",IF(ISBLANK($I$21),"",$I$21)) | AL21: =ISERROR($A$21)*1+ISERROR($B$21)*1+ISERROR($C$21)*1+ISERROR($E$21)*1+ISERROR($G$21)*1+ISERROR($H$21)*1+ISERROR($I$21)*1+ISERROR($J$21)*1
K22: =IF(AL22>0,"O Google leu como fórmula: escolha de novo ou digite com ' na frente.",IF(AND(LEN($AK$22)>0,COUNTIF('Dados'!$BV$6:$BV$10,$AK$22)=0),"Estado fora da lista",IF(AND(LEN($AC$22)=0,LEN($AK$22&$AG$22)>0),"Linha sem o nome da missão",""))) | AA22: ='Tabelas'!$AB$490&"" | AC22: =IF(ISERROR($A$22),"",IF(ISBLANK($A$22),"",$A$22)) | AG22: =IF(ISERROR($E$22),"",IF(ISBLANK($E$22),"",$E$22)) | AK22: =IF(ISERROR($I$22),"",IF(ISBLANK($I$22),"",$I$22)) | AL22: =ISERROR($A$22)*1+ISERROR($B$22)*1+ISERROR($C$22)*1+ISERROR($E$22)*1+ISERROR($G$22)*1+ISERROR($H$22)*1+ISERROR($I$22)*1+ISERROR($J$22)*1
K23: =IF(AL23>0,"O Google leu como fórmula: escolha de novo ou digite com ' na frente.",IF(AND(LEN($AK$23)>0,COUNTIF('Dados'!$BV$6:$BV$10,$AK$23)=0),"Estado fora da lista",IF(AND(LEN($AC$23)=0,LEN($AK$23&$AG$23)>0),"Linha sem o nome da missão",""))) | AA23: ='Tabelas'!$AB$491&"" | AC23: =IF(ISERROR($A$23),"",IF(ISBLANK($A$23),"",$A$23)) | AG23: =IF(ISERROR($E$23),"",IF(ISBLANK($E$23),"",$E$23)) | AK23: =IF(ISERROR($I$23),"",IF(ISBLANK($I$23),"",$I$23)) | AL23: =ISERROR($A$23)*1+ISERROR($B$23)*1+ISERROR($C$23)*1+ISERROR($E$23)*1+ISERROR($G$23)*1+ISERROR($H$23)*1+ISERROR($I$23)*1+ISERROR($J$23)*1
K24: =IF(AL24>0,"O Google leu como fórmula: escolha de novo ou digite com ' na frente.",IF(AND(LEN($AK$24)>0,COUNTIF('Dados'!$BV$6:$BV$10,$AK$24)=0),"Estado fora da lista",IF(AND(LEN($AC$24)=0,LEN($AK$24&$AG$24)>0),"Linha sem o nome da missão",""))) | AA24: ='Tabelas'!$AB$492&"" | AC24: =IF(ISERROR($A$24),"",IF(ISBLANK($A$24),"",$A$24)) | AG24: =IF(ISERROR($E$24),"",IF(ISBLANK($E$24),"",$E$24)) | AK24: =IF(ISERROR($I$24),"",IF(ISBLANK($I$24),"",$I$24)) | AL24: =ISERROR($A$24)*1+ISERROR($B$24)*1+ISERROR($C$24)*1+ISERROR($E$24)*1+ISERROR($G$24)*1+ISERROR($H$24)*1+ISERROR($I$24)*1+ISERROR($J$24)*1
K25: =IF(AL25>0,"O Google leu como fórmula: escolha de novo ou digite com ' na frente.",IF(AND(LEN($AK$25)>0,COUNTIF('Dados'!$BV$6:$BV$10,$AK$25)=0),"Estado fora da lista",IF(AND(LEN($AC$25)=0,LEN($AK$25&$AG$25)>0),"Linha sem o nome da missão",""))) | AA25: ='Tabelas'!$AB$493&"" | AC25: =IF(ISERROR($A$25),"",IF(ISBLANK($A$25),"",$A$25)) | AG25: =IF(ISERROR($E$25),"",IF(ISBLANK($E$25),"",$E$25)) | AK25: =IF(ISERROR($I$25),"",IF(ISBLANK($I$25),"",$I$25)) | AL25: =ISERROR($A$25)*1+ISERROR($B$25)*1+ISERROR($C$25)*1+ISERROR($E$25)*1+ISERROR($G$25)*1+ISERROR($H$25)*1+ISERROR($I$25)*1+ISERROR($J$25)*1
K26: =IF(AL26>0,"O Google leu como fórmula: escolha de novo ou digite com ' na frente.",IF(AND(LEN($AK$26)>0,COUNTIF('Dados'!$BV$6:$BV$10,$AK$26)=0),"Estado fora da lista",IF(AND(LEN($AC$26)=0,LEN($AK$26&$AG$26)>0),"Linha sem o nome da missão",""))) | AA26: ='Tabelas'!$AB$494&"" | AC26: =IF(ISERROR($A$26),"",IF(ISBLANK($A$26),"",$A$26)) | AG26: =IF(ISERROR($E$26),"",IF(ISBLANK($E$26),"",$E$26)) | AK26: =IF(ISERROR($I$26),"",IF(ISBLANK($I$26),"",$I$26)) | AL26: =ISERROR($A$26)*1+ISERROR($B$26)*1+ISERROR($C$26)*1+ISERROR($E$26)*1+ISERROR($G$26)*1+ISERROR($H$26)*1+ISERROR($I$26)*1+ISERROR($J$26)*1
K27: =IF(AL27>0,"O Google leu como fórmula: escolha de novo ou digite com ' na frente.",IF(AND(LEN($AK$27)>0,COUNTIF('Dados'!$BV$6:$BV$10,$AK$27)=0),"Estado fora da lista",IF(AND(LEN($AC$27)=0,LEN($AK$27&$AG$27)>0),"Linha sem o nome da missão",""))) | AA27: ='Tabelas'!$AB$495&"" | AC27: =IF(ISERROR($A$27),"",IF(ISBLANK($A$27),"",$A$27)) | AG27: =IF(ISERROR($E$27),"",IF(ISBLANK($E$27),"",$E$27)) | AK27: =IF(ISERROR($I$27),"",IF(ISBLANK($I$27),"",$I$27)) | AL27: =ISERROR($A$27)*1+ISERROR($B$27)*1+ISERROR($C$27)*1+ISERROR($E$27)*1+ISERROR($G$27)*1+ISERROR($H$27)*1+ISERROR($I$27)*1+ISERROR($J$27)*1
K28: =IF(AL28>0,"O Google leu como fórmula: escolha de novo ou digite com ' na frente.",IF(AND(LEN($AK$28)>0,COUNTIF('Dados'!$BV$6:$BV$10,$AK$28)=0),"Estado fora da lista",IF(AND(LEN($AC$28)=0,LEN($AK$28&$AG$28)>0),"Linha sem o nome da missão",""))) | AA28: ='Tabelas'!$AB$496&"" | AC28: =IF(ISERROR($A$28),"",IF(ISBLANK($A$28),"",$A$28)) | AG28: =IF(ISERROR($E$28),"",IF(ISBLANK($E$28),"",$E$28)) | AK28: =IF(ISERROR($I$28),"",IF(ISBLANK($I$28),"",$I$28)) | AL28: =ISERROR($A$28)*1+ISERROR($B$28)*1+ISERROR($C$28)*1+ISERROR($E$28)*1+ISERROR($G$28)*1+ISERROR($H$28)*1+ISERROR($I$28)*1+ISERROR($J$28)*1
A29: M2 · O registro (preencha) | AA29: ='Tabelas'!$AB$497&""
A30: Missão | B30: É marco de nível? | C30: Sessão de início | D30: Sessão de fim | E30: Notas | K30: Aviso | AA30: ='Tabelas'!$AB$498&""
A31: =IF(LEN($AC$8)>0,$AC$8,"Missão 1") | K31: =IF(AL31>0,"O Google leu como fórmula: escolha de novo ou digite com ' na frente.",IF(AND($AK$8="Concluída",LEN($AF$31)=0),"Concluída sem sessão de fim",IF(AND(ISNUMBER($AE$31),ISNUMBER($AF$31)),IF($AF$31<$AE$31,"Sessão de fim antes da de início",""),""))) | AA31: ='Tabelas'!$AB$500&"" | AD31: =IF(ISERROR($B$31),"",IF(ISBLANK($B$31),"",$B$31)) | AE31: =IF(ISERROR($C$31),"",IF(ISBLANK($C$31),"",$C$31)) | AF31: =IF(ISERROR($D$31),"",IF(ISBLANK($D$31),"",$D$31)) | AL31: =ISERROR($B$31)*1+ISERROR($C$31)*1+ISERROR($D$31)*1+ISERROR($E$31)*1
A32: =IF(LEN($AC$9)>0,$AC$9,"Missão 2") | K32: =IF(AL32>0,"O Google leu como fórmula: escolha de novo ou digite com ' na frente.",IF(AND($AK$9="Concluída",LEN($AF$32)=0),"Concluída sem sessão de fim",IF(AND(ISNUMBER($AE$32),ISNUMBER($AF$32)),IF($AF$32<$AE$32,"Sessão de fim antes da de início",""),""))) | AA32: ='Tabelas'!$AB$501&"" | AD32: =IF(ISERROR($B$32),"",IF(ISBLANK($B$32),"",$B$32)) | AE32: =IF(ISERROR($C$32),"",IF(ISBLANK($C$32),"",$C$32)) | AF32: =IF(ISERROR($D$32),"",IF(ISBLANK($D$32),"",$D$32)) | AL32: =ISERROR($B$32)*1+ISERROR($C$32)*1+ISERROR($D$32)*1+ISERROR($E$32)*1
A33: =IF(LEN($AC$10)>0,$AC$10,"Missão 3") | K33: =IF(AL33>0,"O Google leu como fórmula: escolha de novo ou digite com ' na frente.",IF(AND($AK$10="Concluída",LEN($AF$33)=0),"Concluída sem sessão de fim",IF(AND(ISNUMBER($AE$33),ISNUMBER($AF$33)),IF($AF$33<$AE$33,"Sessão de fim antes da de início",""),""))) | AA33: ='Tabelas'!$AB$502&"" | AD33: =IF(ISERROR($B$33),"",IF(ISBLANK($B$33),"",$B$33)) | AE33: =IF(ISERROR($C$33),"",IF(ISBLANK($C$33),"",$C$33)) | AF33: =IF(ISERROR($D$33),"",IF(ISBLANK($D$33),"",$D$33)) | AL33: =ISERROR($B$33)*1+ISERROR($C$33)*1+ISERROR($D$33)*1+ISERROR($E$33)*1
A34: =IF(LEN($AC$11)>0,$AC$11,"Missão 4") | K34: =IF(AL34>0,"O Google leu como fórmula: escolha de novo ou digite com ' na frente.",IF(AND($AK$11="Concluída",LEN($AF$34)=0),"Concluída sem sessão de fim",IF(AND(ISNUMBER($AE$34),ISNUMBER($AF$34)),IF($AF$34<$AE$34,"Sessão de fim antes da de início",""),""))) | AA34: ='Tabelas'!$AB$503&"" | AD34: =IF(ISERROR($B$34),"",IF(ISBLANK($B$34),"",$B$34)) | AE34: =IF(ISERROR($C$34),"",IF(ISBLANK($C$34),"",$C$34)) | AF34: =IF(ISERROR($D$34),"",IF(ISBLANK($D$34),"",$D$34)) | AL34: =ISERROR($B$34)*1+ISERROR($C$34)*1+ISERROR($D$34)*1+ISERROR($E$34)*1
A35: =IF(LEN($AC$12)>0,$AC$12,"Missão 5") | K35: =IF(AL35>0,"O Google leu como fórmula: escolha de novo ou digite com ' na frente.",IF(AND($AK$12="Concluída",LEN($AF$35)=0),"Concluída sem sessão de fim",IF(AND(ISNUMBER($AE$35),ISNUMBER($AF$35)),IF($AF$35<$AE$35,"Sessão de fim antes da de início",""),""))) | AA35: ='Tabelas'!$AB$504&"" | AD35: =IF(ISERROR($B$35),"",IF(ISBLANK($B$35),"",$B$35)) | AE35: =IF(ISERROR($C$35),"",IF(ISBLANK($C$35),"",$C$35)) | AF35: =IF(ISERROR($D$35),"",IF(ISBLANK($D$35),"",$D$35)) | AL35: =ISERROR($B$35)*1+ISERROR($C$35)*1+ISERROR($D$35)*1+ISERROR($E$35)*1
A36: =IF(LEN($AC$13)>0,$AC$13,"Missão 6") | K36: =IF(AL36>0,"O Google leu como fórmula: escolha de novo ou digite com ' na frente.",IF(AND($AK$13="Concluída",LEN($AF$36)=0),"Concluída sem sessão de fim",IF(AND(ISNUMBER($AE$36),ISNUMBER($AF$36)),IF($AF$36<$AE$36,"Sessão de fim antes da de início",""),""))) | AA36: ='Tabelas'!$AB$505&"" | AD36: =IF(ISERROR($B$36),"",IF(ISBLANK($B$36),"",$B$36)) | AE36: =IF(ISERROR($C$36),"",IF(ISBLANK($C$36),"",$C$36)) | AF36: =IF(ISERROR($D$36),"",IF(ISBLANK($D$36),"",$D$36)) | AL36: =ISERROR($B$36)*1+ISERROR($C$36)*1+ISERROR($D$36)*1+ISERROR($E$36)*1
A37: =IF(LEN($AC$14)>0,$AC$14,"Missão 7") | K37: =IF(AL37>0,"O Google leu como fórmula: escolha de novo ou digite com ' na frente.",IF(AND($AK$14="Concluída",LEN($AF$37)=0),"Concluída sem sessão de fim",IF(AND(ISNUMBER($AE$37),ISNUMBER($AF$37)),IF($AF$37<$AE$37,"Sessão de fim antes da de início",""),""))) | AA37: ='Tabelas'!$AB$506&"" | AD37: =IF(ISERROR($B$37),"",IF(ISBLANK($B$37),"",$B$37)) | AE37: =IF(ISERROR($C$37),"",IF(ISBLANK($C$37),"",$C$37)) | AF37: =IF(ISERROR($D$37),"",IF(ISBLANK($D$37),"",$D$37)) | AL37: =ISERROR($B$37)*1+ISERROR($C$37)*1+ISERROR($D$37)*1+ISERROR($E$37)*1
A38: =IF(LEN($AC$15)>0,$AC$15,"Missão 8") | K38: =IF(AL38>0,"O Google leu como fórmula: escolha de novo ou digite com ' na frente.",IF(AND($AK$15="Concluída",LEN($AF$38)=0),"Concluída sem sessão de fim",IF(AND(ISNUMBER($AE$38),ISNUMBER($AF$38)),IF($AF$38<$AE$38,"Sessão de fim antes da de início",""),""))) | AA38: ='Tabelas'!$AB$507&"" | AD38: =IF(ISERROR($B$38),"",IF(ISBLANK($B$38),"",$B$38)) | AE38: =IF(ISERROR($C$38),"",IF(ISBLANK($C$38),"",$C$38)) | AF38: =IF(ISERROR($D$38),"",IF(ISBLANK($D$38),"",$D$38)) | AL38: =ISERROR($B$38)*1+ISERROR($C$38)*1+ISERROR($D$38)*1+ISERROR($E$38)*1
A39: =IF(LEN($AC$16)>0,$AC$16,"Missão 9") | K39: =IF(AL39>0,"O Google leu como fórmula: escolha de novo ou digite com ' na frente.",IF(AND($AK$16="Concluída",LEN($AF$39)=0),"Concluída sem sessão de fim",IF(AND(ISNUMBER($AE$39),ISNUMBER($AF$39)),IF($AF$39<$AE$39,"Sessão de fim antes da de início",""),""))) | AA39: ='Tabelas'!$AB$508&"" | AD39: =IF(ISERROR($B$39),"",IF(ISBLANK($B$39),"",$B$39)) | AE39: =IF(ISERROR($C$39),"",IF(ISBLANK($C$39),"",$C$39)) | AF39: =IF(ISERROR($D$39),"",IF(ISBLANK($D$39),"",$D$39)) | AL39: =ISERROR($B$39)*1+ISERROR($C$39)*1+ISERROR($D$39)*1+ISERROR($E$39)*1
