Workbook

Sheet Início
A1: Início — Explorando Galáxias v1.1
A2: Legenda: | B2: Entrada (preencha) | C2: Calculada (automático) | D2: Aviso (texto em vermelho) | E2: Título de bloco | F2: Cabeçalho de coluna | G2: Rótulo da linha | H2: Linha alternada (outro tom) | I2: Não se aplica
A3: Comece por aqui: semente da campanha, índice das abas e como a planilha se organiza.
A5: Comece por aqui
A6: 1. Abra no Google Planilhas (Arquivo → Importar) e trabalhe numa cópia por campanha.
A7: 2. Aba Campanha: nível do grupo e nº de jogadores (uma vez; todas as abas leem daqui).
A8: 3. Aba Grupo: copie da ficha de cada jogador os números de combate.
A9: 4. Prepare o combate: Inimigos (criar), Bestiário (consultar) e Encontros (montar e conferir o contrato).
A10: 5. Jogue com a aba Combate: carregue o encontro, siga a Fila e registre o estado (sem macro: tudo é digitado).
A11: Amarelo = você preenche; azul = automático; vermelho = aviso; 'Sugestão da planilha' = não é regra do livro.
A12: Não comece um texto com +, - ou =: o Google entende como fórmula. Se precisar, digite um apóstrofo (') antes.
A14: Semente da campanha (geradores determinísticos, sem sorteio escondido)
A15: Semente da campanha | D15: Semente efetiva | E15: =IF(ISNUMBER($P$15),IF(AND($P$15>=1,$P$15<=2147483646,INT($P$15)=$P$15),$P$15,12345),12345) | G15: Vazia = 12345. | K15: =IF(Q15>0,"O Google leu como fórmula: digite de novo com ' na frente.",IF(LEN($P$15)=0,"",IF(ISNUMBER($P$15),IF(AND($P$15>=1,$P$15<=2147483646,INT($P$15)=$P$15),"","Semente fora de 1 a 2.147.483.646: usando 12345"),"Semente fora de 1 a 2.147.483.646: usando 12345"))) | P15: =IF(ISERROR($B$15),"",IF(ISBLANK($B$15),"",$B$15)) | Q15: =ISERROR($B$15)*1
A16: Mesma semente e mesma 'Rolagem nº' dão sempre o mesmo resultado; editar outra célula não muda o sorteio. Para rolar de novo, some 1 na 'Rolagem nº' do gerador; para outra campanha, troque a semente.
A18: Índice das abas
A19: Aba | B19: Para que serve | G19: Quando usar | K19: Situação
A20: Início | B20: Semente da campanha e índice. | G20: Na primeira vez e para trocar a semente. | K20: Pronta
A21: Campanha | B21: Nível do grupo, nº de jogadores e os números que saem deles. | G21: Ao começar e a cada marco. | K21: Pronta (Mesa)
A22: Grupo | B22: Os PJs copiados da ficha de cada jogador. | G22: Ao começar e quando a ficha muda. | K22: Pronta
A23: Sessões | B23: Preparar a próxima sessão e o diário. | G23: Entre sessões. | K23: Em construção
A24: Missões | B24: Missões oferecidas, ativas e concluídas. | G24: Entre sessões. | K24: Em construção
A25: NPCs | B25: Gerador de NPCs, elenco e cartões. | G25: Preparando a história. | K25: Pronta
A26: Inimigos | B26: Criador de Inimigos: a ficha de 28.1 pronta. | G26: Preparando o combate. | K26: Pronta
A27: Bestiário | B27: As 32 fichas do capítulo 28 com filtro. | G27: Preparando o combate. | K27: Pronta
A28: Encontros | B28: Orçamento, encontros salvos, contrato da Fraqueza, encontro aleatório. | G28: Preparando o combate. | K28: Pronta
A29: Aba | B29: Para que serve | G29: Quando usar | K29: Situação
A30: Combate | B30: Fila de Ação, PV, Tenacidade e Quebra, condições, Morrendo. | G30: Na mesa, durante a luta. | K30: Pronta
... A38: Dados | B38: Tabelas do livro usadas pelas fórmulas. Não edite. | G38: Nunca: o gerador reescreve. | K38: Pronta
A40: Células com erro na planilha (o Google leu como fórmula um texto digitado)
A41: Células com erro na planilha | B41: =$B$42+$D$42+$F$42+$H$42+$J$42+$B$43+$D$43+$F$43+$H$43+$J$43+$B$44+$D$44+$F$44+$H$44+$J$44+$B$45+$D$45+$F$45 | C41: =IF($B$41=0,"Nenhuma célula com erro.","O Google leu como fórmula um texto que começa com +, - ou =. Veja abaixo a aba com erro: o aviso da linha diz o que fazer. Apague e escreva de novo com um apóstrofo (') na frente, ou escolha de novo na lista.")
A42: Início | B42: =SUMPRODUCT(ISERROR($A$1:$Q$40)*1) | C42: Campanha | D42: =SUMPRODUCT(ISERROR('Campanha'!$A$1:$Q$34)*1) | E42: Grupo | F42: =SUMPRODUCT(ISERROR('Grupo'!$A$1:$Y$45)*1) | G42: Sessões | H42: =SUMPRODUCT(ISERROR('Sessões'!$A$1:$L$5)*1) | I42: Missões | J42: =SUMPRODUCT(ISERROR('Missões'!$A$1:$L$5)*1)
A43: NPCs | B43: =SUMPRODUCT(ISERROR('NPCs'!$A$1:$BF$232)*1) | C43: Inimigos | D43: =SUMPRODUCT(ISERROR('Inimigos'!$A$1:$EA$219)*1) | E43: Bestiário | F43: =SUMPRODUCT(ISERROR('Bestiário'!$A$1:$S$121)*1) | G43: Encontros | H43: =SUMPRODUCT(ISERROR('Encontros'!$A$1:$BN$122)*1) | I43: Combate | J43: =SUMPRODUCT(ISERROR('Combate'!$A$1:$CK$216)*1)
A44: Aventuras | B44: =SUMPRODUCT(ISERROR('Aventuras'!$A$1:$AU$116)*1) | C44: Recompensas | D44: =SUMPRODUCT(ISERROR('Recompensas'!$A$1:$AK$159)*1) | E44: Mundos | F44: =SUMPRODUCT(ISERROR('Mundos'!$A$1:$L$5)*1) | G44: Improviso | H44: =SUMPRODUCT(ISERROR('Improviso'!$A$1:$L$5)*1) | I44: Escudo do Mestre | J44: =SUMPRODUCT(ISERROR('Escudo do Mestre'!$A$1:$L$5)*1)
A45: Minhas Tabelas | B45: =SUMPRODUCT(ISERROR('Minhas Tabelas'!$A$1:$L$5)*1) | C45: Tabelas | D45: =SUMPRODUCT(ISERROR('Tabelas'!$A$1:$AG$808)*1) | E45: Dados | F45: =SUMPRODUCT(ISERROR('Dados'!$A$1:$BU$588)*1)

Sheet Campanha
A1: Campanha — Explorando Galáxias v1.1
A2: Legenda: | B2: Entrada (preencha) | C2: Calculada (automático) | D2: Aviso (texto em vermelho) | E2: Título de bloco | F2: Cabeçalho de coluna | G2: Rótulo da linha | H2: Linha alternada (outro tom) | I2: Não se aplica
A3: A mesa: nível do grupo, número de jogadores e os números que saem deles.
A5: Mesa (preencha uma vez: todas as abas leem daqui — D9)
A6: Campo | B6: Valor (preencha) | E6: O que a planilha usa (automático) | K6: Aviso
A7: Nome da campanha | E7: ="A campanha aparece no título das abas de jogo." | K7: =IF(Q7>0,"O Google leu como fórmula: digite de novo com ' na frente.","") | Q7: =ISERROR($B$7)*1
A8: Nº de jogadores | E8: =IF(ISNUMBER($P$8),"Jogadores na mesa: "&$B$21&".","Vazio: usando o nº de PJs da aba Grupo ("&$B$21&").") | K8: =IF(Q8>0,"O Google leu como fórmula: digite de novo com ' na frente.",IF(LEN($P$8)=0,"",IF(NOT(ISNUMBER($P$8)),"Nº de jogadores não é número: usando o nº de PJs do Grupo",IF(OR($P$8<1,$P$8>6,INT($P$8)<>$P$8),"Nº de jogadores fora de 1 a 6: usando o limite",IF(OR($P$8<3,$P$8>6),"Fora da tabela de 16.2 (3 a 6): PH calculado com o limite 3 a 6",""))))) | P8: =IF(ISERROR($B$8),"",IF(ISBLANK($B$8),"",$B$8)) | Q8: =ISERROR($B$8)*1
A9: Nível do grupo | E9: =IF(ISNUMBER($P$9),"Nível "&$B$17&", faixa "&$B$19&".","Vazio: as abas calculam com o nível 1 (faixa 1-4).") | K9: =IF(Q9>0,"O Google leu como fórmula: digite de novo com ' na frente.",IF(LEN($P$9)=0,"",IF(NOT(ISNUMBER($P$9)),"Nível não é número: usando 1",IF(OR($P$9<1,$P$9>20,INT($P$9)<>$P$9),"Nível fora de 1 a 20: usando o limite","")))) | P9: =IF(ISERROR($B$9),"",IF(ISBLANK($B$9),"",$B$9)) | Q9: =ISERROR($B$9)*1
A10: Sessão atual | E10: ="Sessões e diário: aba Sessões (próxima fase)." | K10: =IF(Q10>0,"O Google leu como fórmula: digite de novo com ' na frente.","") | P10: =IF(ISERROR($B$10),"",IF(ISBLANK($B$10),"",$B$10)) | Q10: =ISERROR($B$10)*1
A11: Dia de campanha | E11: ="Usado pela linha do tempo (próxima fase)." | K11: =IF(Q11>0,"O Google leu como fórmula: digite de novo com ' na frente.","") | Q11: =ISERROR($B$11)*1
A12: Método de atributos | E12: ="Lembrete da Sessão Zero (capítulo 03)." | K12: =IF(Q12>0,"O Google leu como fórmula: escolha de novo na lista.","") | Q12: =ISERROR($B$12)*1
A13: Variantes da mesa | E13: ="Texto livre: média impressa, PV rolado, outra variante (06.4, 28.3)." | K13: =IF(Q13>0,"O Google leu como fórmula: digite de novo com ' na frente.","") | Q13: =ISERROR($B$13)*1
A15: Números do grupo (automático)
A16: Campo | B16: Valor | D16: Fonte no livro | G16: Observação
A17: Nível efetivo | B17: =IF(ISNUMBER($P$9),MIN(20,MAX(1,INT($P$9))),1) | D17: 26.1 | G17: Vazio = 1.
A18: Índice da faixa | B18: =INT(($B$17-1)/4)+1 | D18: 26.3 | G18: 1 a 5.
A19: Faixa do grupo | B19: =INDEX('Dados'!$B$7:$B$11,$B$18) | D19: 26.3 | G19: A faixa do inimigo é a faixa do grupo (28.4 passo 1).
A20: Eficiência | B20: =INDEX('Dados'!$B$15:$B$34,$B$17) | D20: 26.2 (02.3) | G20: Usada no Dano de Quebra e nas condições.
A21: Nº de jogadores efetivo | B21: =IF(ISNUMBER($P$8),MIN(6,MAX(1,INT($P$8))),MAX(1,'Grupo'!$B$42)) | D21: 16.2 | G21: Vazio = nº de PJs da aba Grupo (mínimo 1).
A22: Jogadores para o PH | B22: =MIN(6,MAX(3,$B$21)) | D22: 16.2 | G22: A tabela de 16.2 vai de 3 a 6 jogadores.
A23: Degrau de PH | B23: =IF($B$17<=8,1,IF($B$17<=16,2,3)) | D23: 16.2 | G23: 1 = níveis 1-8; 2 = 9-16; 3 = 17-20.
A24: PH máximo do grupo | B24: =IF($B$23=1,INDEX('Dados'!$B$343:$B$346,MATCH($B$22,'Dados'!$A$343:$A$346,0)),IF($B$23=2,INDEX('Dados'!$C$343:$C$346,MATCH($B$22,'Dados'!$A$343:$A$346,0)),INDEX('Dados'!$D$343:$D$346,MATCH($B$22,'Dados'!$A$343:$A$346,0)))) | D24: 16.2 | G24: Degraus 1-8, 9-16 e 17-20.
A25: PH no início do combate | B25: =IF($B$23=1,INDEX('Dados'!$E$343:$E$346,MATCH($B$22,'Dados'!$A$343:$A$346,0)),IF($B$23=2,INDEX('Dados'!$F$343:$F$346,MATCH($B$22,'Dados'!$A$343:$A$346,0)),INDEX('Dados'!$G$343:$G$346,MATCH($B$22,'Dados'!$A$343:$A$346,0)))) | D25: 16.2 | G25: Começa cada combate com o máximo menos 2.
A26: Campo | B26: Valor | D26: Fonte no livro | G26: Observação
A27: DT Média da faixa | B27: =IF($B$18=1,INDEX('Dados'!$B$284:$B$289,3),IF($B$18=2,INDEX('Dados'!$C$284:$C$289,3),IF($B$18=3,INDEX('Dados'!$D$284:$D$289,3),IF($B$18=4,INDEX('Dados'!$E$284:$E$289,3),INDEX('Dados'!$F$284:$F$289,3))))) | D27: 27.2 | G27: Regra 1: a faixa é a do desafio, não a do personagem.
A28: DT Difícil da faixa | B28: =IF($B$18=1,INDEX('Dados'!$B$284:$B$289,4),IF($B$18=2,INDEX('Dados'!$C$284:$C$289,4),IF($B$18=3,INDEX('Dados'!$D$284:$D$289,4),IF($B$18=4,INDEX('Dados'!$E$284:$E$289,4),INDEX('Dados'!$F$284:$F$289,4))))) | D28: 27.2
A29: DT para descobrir Fraqueza | B29: =IFERROR(INDEX('Dados'!$B$293:$B$297,MATCH($B$19,'Dados'!$A$293:$A$297,0)),"") | D29: 20.2 | G29: Pela faixa do inimigo mais forte da cena.
A30: Cone de Luz máximo | B30: =IFERROR(INDEX('Dados'!$B$380:$B$384,MATCH($B$19,'Dados'!$A$380:$A$384,0)),"") | D30: 25.1
A31: Relíquias | B31: =IFERROR(INDEX('Dados'!$C$380:$C$384,MATCH($B$19,'Dados'!$A$380:$A$384,0)),"") | D31: 25.1
A32: Verba de marco (Cr) | B32: =IFERROR(INDEX('Dados'!$B$372:$B$376,MATCH($B$19,'Dados'!$A$372:$A$376,0)),"") | D32: 24.5 | G32: Por marco, para o grupo.
A34: Não existe experiência por inimigo derrotado: a progressão é por marco narrativo (26.1).

Sheet Grupo
A1: Grupo — Explorando Galáxias v1.1
A2: Legenda: | B2: Entrada (preencha) | C2: Calculada (automático) | D2: Aviso (texto em vermelho) | E2: Título de bloco | F2: Cabeçalho de coluna | G2: Rótulo da linha | H2: Linha alternada (outro tom) | I2: Não se aplica
A3: Os personagens jogadores, copiados da ficha de cada jogador (uma linha por PJ).
A5: G1 · Quem é (preencha, da ficha de cada jogador)
A6: Nome do PJ | B6: Jogador | C6: Raça | D6: Caminho | E6: Elemento | F6: Propósito de Vida | I6: Crença do Esforço (Humano) | K6: Aviso
K7: =IF(Y7>0,"O Google leu como fórmula: escolha de novo ou digite com ' na frente.",IF(AND(LEN($R$7)>0,COUNTIF('Dados'!$A$350:$A$356,$R$7)=0),"Raça fora da lista do capítulo 05",IF(AND(LEN($T$7)>0,COUNTIF($T$7:$T$12,$T$7)>1),"Elemento repetido no grupo: cuidado com a Resistência (regra irmã, 27.5)",IF(AND(LEN($P$7)=0,LEN($R$7&$T$7&$S$7)>0),"Linha sem nome: o PJ não entra na contagem","")))) | P7: =IF(ISERROR($A$7),"",IF(ISBLANK($A$7),"",$A$7)) | R7: =IF(ISERROR($C$7),"",IF(ISBLANK($C$7),"",$C$7)) | S7: =IF(ISERROR($D$7),"",IF(ISBLANK($D$7),"",$D$7)) | T7: =IF(ISERROR($E$7),"",IF(ISBLANK($E$7),"",$E$7)) | Y7: =ISERROR($A$7)*1+ISERROR($B$7)*1+ISERROR($C$7)*1+ISERROR($D$7)*1+ISERROR($E$7)*1+ISERROR($F$7)*1+ISERROR($I$7)*1
K8: =IF(Y8>0,"O Google leu como fórmula: escolha de novo ou digite com ' na frente.",IF(AND(LEN($R$8)>0,COUNTIF('Dados'!$A$350:$A$356,$R$8)=0),"Raça fora da lista do capítulo 05",IF(AND(LEN($T$8)>0,COUNTIF($T$7:$T$12,$T$8)>1),"Elemento repetido no grupo: cuidado com a Resistência (regra irmã, 27.5)",IF(AND(LEN($P$8)=0,LEN($R$8&$T$8&$S$8)>0),"Linha sem nome: o PJ não entra na contagem","")))) | P8: =IF(ISERROR($A$8),"",IF(ISBLANK($A$8),"",$A$8)) | R8: =IF(ISERROR($C$8),"",IF(ISBLANK($C$8),"",$C$8)) | S8: =IF(ISERROR($D$8),"",IF(ISBLANK($D$8),"",$D$8)) | T8: =IF(ISERROR($E$8),"",IF(ISBLANK($E$8),"",$E$8)) | Y8: =ISERROR($A$8)*1+ISERROR($B$8)*1+ISERROR($C$8)*1+ISERROR($D$8)*1+ISERROR($E$8)*1+ISERROR($F$8)*1+ISERROR($I$8)*1
K9: =IF(Y9>0,"O Google leu como fórmula: escolha de novo ou digite com ' na frente.",IF(AND(LEN($R$9)>0,COUNTIF('Dados'!$A$350:$A$356,$R$9)=0),"Raça fora da lista do capítulo 05",IF(AND(LEN($T$9)>0,COUNTIF($T$7:$T$12,$T$9)>1),"Elemento repetido no grupo: cuidado com a Resistência (regra irmã, 27.5)",IF(AND(LEN($P$9)=0,LEN($R$9&$T$9&$S$9)>0),"Linha sem nome: o PJ não entra na contagem","")))) | P9: =IF(ISERROR($A$9),"",IF(ISBLANK($A$9),"",$A$9)) | R9: =IF(ISERROR($C$9),"",IF(ISBLANK($C$9),"",$C$9)) | S9: =IF(ISERROR($D$9),"",IF(ISBLANK($D$9),"",$D$9)) | T9: =IF(ISERROR($E$9),"",IF(ISBLANK($E$9),"",$E$9)) | Y9: =ISERROR($A$9)*1+ISERROR($B$9)*1+ISERROR($C$9)*1+ISERROR($D$9)*1+ISERROR($E$9)*1+ISERROR($F$9)*1+ISERROR($I$9)*1
K10: =IF(Y10>0,"O Google leu como fórmula: escolha de novo ou digite com ' na frente.",IF(AND(LEN($R$10)>0,COUNTIF('Dados'!$A$350:$A$356,$R$10)=0),"Raça fora da lista do capítulo 05",IF(AND(LEN($T$10)>0,COUNTIF($T$7:$T$12,$T$10)>1),"Elemento repetido no grupo: cuidado com a Resistência (regra irmã, 27.5)",IF(AND(LEN($P$10)=0,LEN($R$10&$T$10&$S$10)>0),"Linha sem nome: o PJ não entra na contagem","")))) | P10: =IF(ISERROR($A$10),"",IF(ISBLANK($A$10),"",$A$10)) | R10: =IF(ISERROR($C$10),"",IF(ISBLANK($C$10),"",$C$10)) | S10: =IF(ISERROR($D$10),"",IF(ISBLANK($D$10),"",$D$10)) | T10: =IF(ISERROR($E$10),"",IF(ISBLANK($E$10),"",$E$10)) | Y10: =ISERROR($A$10)*1+ISERROR($B$10)*1+ISERROR($C$10)*1+ISERROR($D$10)*1+ISERROR($E$10)*1+ISERROR($F$10)*1+ISERROR($I$10)*1
K11: =IF(Y11>0,"O Google leu como fórmula: escolha de novo ou digite com ' na frente.",IF(AND(LEN($R$11)>0,COUNTIF('Dados'!$A$350:$A$356,$R$11)=0),"Raça fora da lista do capítulo 05",IF(AND(LEN($T$11)>0,COUNTIF($T$7:$T$12,$T$11)>1),"Elemento repetido no grupo: cuidado com a Resistência (regra irmã, 27.5)",IF(AND(LEN($P$11)=0,LEN($R$11&$T$11&$S$11)>0),"Linha sem nome: o PJ não entra na contagem","")))) | P11: =IF(ISERROR($A$11),"",IF(ISBLANK($A$11),"",$A$11)) | R11: =IF(ISERROR($C$11),"",IF(ISBLANK($C$11),"",$C$11)) | S11: =IF(ISERROR($D$11),"",IF(ISBLANK($D$11),"",$D$11)) | T11: =IF(ISERROR($E$11),"",IF(ISBLANK($E$11),"",$E$11)) | Y11: =ISERROR($A$11)*1+ISERROR($B$11)*1+ISERROR($C$11)*1+ISERROR($D$11)*1+ISERROR($E$11)*1+ISERROR($F$11)*1+ISERROR($I$11)*1
K12: =IF(Y12>0,"O Google leu como fórmula: escolha de novo ou digite com ' na frente.",IF(AND(LEN($R$12)>0,COUNTIF('Dados'!$A$350:$A$356,$R$12)=0),"Raça fora da lista do capítulo 05",IF(AND(LEN($T$12)>0,COUNTIF($T$7:$T$12,$T$12)>1),"Elemento repetido no grupo: cuidado com a Resistência (regra irmã, 27.5)",IF(AND(LEN($P$12)=0,LEN($R$12&$T$12&$S$12)>0),"Linha sem nome: o PJ não entra na contagem","")))) | P12: =IF(ISERROR($A$12),"",IF(ISBLANK($A$12),"",$A$12)) | R12: =IF(ISERROR($C$12),"",IF(ISBLANK($C$12),"",$C$12)) | S12: =IF(ISERROR($D$12),"",IF(ISBLANK($D$12),"",$D$12)) | T12: =IF(ISERROR($E$12),"",IF(ISBLANK($E$12),"",$E$12)) | Y12: =ISERROR($A$12)*1+ISERROR($B$12)*1+ISERROR($C$12)*1+ISERROR($D$12)*1+ISERROR($E$12)*1+ISERROR($F$12)*1+ISERROR($I$12)*1
A14: G2 · Números de combate (preencha, da aba Em Jogo da ficha)
A15: PJ | B15: PV máx. | C15: Defesa | D15: Esquiva | E15: RD | F15: VEL | G15: Bônus de Agilidade | H15: Bônus de Discernimento | I15: Bônus de Presença | J15: DT das Habilidades | K15: Aviso
A16: =IF(LEN($P$7)>0,$P$7,"PJ 1") | K16: =IF(Y16>0,"O Google leu como fórmula: digite de novo com ' na frente.",IF(AND(ISNUMBER($U$16),OR($U$16<7,$U$16>25)),"VEL fora dos extremos 7 a 25 da fórmula: confira na ficha (19.1)",IF(OR(AND(ISNUMBER($V$16),OR($V$16<-1,$V$16>5)),AND(ISNUMBER($W$16),OR($W$16<-1,$W$16>5)),AND(ISNUMBER($X$16),OR($X$16<-1,$X$16>5))),"Bônus de Atributo fora de -1 a +5: confira na ficha",IF(AND(ISNUMBER($Q$16),OR($Q$16<1,$Q$16>999)),"PV fora de 1 a 999: confira na ficha","")))) | Q16: =IF(ISERROR($B$16),"",IF(ISBLANK($B$16),"",$B$16)) | U16: =IF(ISERROR($F$16),"",IF(ISBLANK($F$16),"",$F$16)) | V16: =IF(ISERROR($G$16),"",IF(ISBLANK($G$16),"",$G$16)) | W16: =IF(ISERROR($H$16),"",IF(ISBLANK($H$16),"",$H$16)) | X16: =IF(ISERROR($I$16),"",IF(ISBLANK($I$16),"",$I$16)) | Y16: =ISERROR($B$16)*1+ISERROR($C$16)*1+ISERROR($D$16)*1+ISERROR($E$16)*1+ISERROR($F$16)*1+ISERROR($G$16)*1+ISERROR($H$16)*1+ISERROR($I$16)*1+ISERROR($J$16)*1
A17: =IF(LEN($P$8)>0,$P$8,"PJ 2") | K17: =IF(Y17>0,"O Google leu como fórmula: digite de novo com ' na frente.",IF(AND(ISNUMBER($U$17),OR($U$17<7,$U$17>25)),"VEL fora dos extremos 7 a 25 da fórmula: confira na ficha (19.1)",IF(OR(AND(ISNUMBER($V$17),OR($V$17<-1,$V$17>5)),AND(ISNUMBER($W$17),OR($W$17<-1,$W$17>5)),AND(ISNUMBER($X$17),OR($X$17<-1,$X$17>5))),"Bônus de Atributo fora de -1 a +5: confira na ficha",IF(AND(ISNUMBER($Q$17),OR($Q$17<1,$Q$17>999)),"PV fora de 1 a 999: confira na ficha","")))) | Q17: =IF(ISERROR($B$17),"",IF(ISBLANK($B$17),"",$B$17)) | U17: =IF(ISERROR($F$17),"",IF(ISBLANK($F$17),"",$F$17)) | V17: =IF(ISERROR($G$17),"",IF(ISBLANK($G$17),"",$G$17)) | W17: =IF(ISERROR($H$17),"",IF(ISBLANK($H$17),"",$H$17)) | X17: =IF(ISERROR($I$17),"",IF(ISBLANK($I$17),"",$I$17)) | Y17: =ISERROR($B$17)*1+ISERROR($C$17)*1+ISERROR($D$17)*1+ISERROR($E$17)*1+ISERROR($F$17)*1+ISERROR($G$17)*1+ISERROR($H$17)*1+ISERROR($I$17)*1+ISERROR($J$17)*1
A18: =IF(LEN($P$9)>0,$P$9,"PJ 3") | K18: =IF(Y18>0,"O Google leu como fórmula: digite de novo com ' na frente.",IF(AND(ISNUMBER($U$18),OR($U$18<7,$U$18>25)),"VEL fora dos extremos 7 a 25 da fórmula: confira na ficha (19.1)",IF(OR(AND(ISNUMBER($V$18),OR($V$18<-1,$V$18>5)),AND(ISNUMBER($W$18),OR($W$18<-1,$W$18>5)),AND(ISNUMBER($X$18),OR($X$18<-1,$X$18>5))),"Bônus de Atributo fora de -1 a +5: confira na ficha",IF(AND(ISNUMBER($Q$18),OR($Q$18<1,$Q$18>999)),"PV fora de 1 a 999: confira na ficha","")))) | Q18: =IF(ISERROR($B$18),"",IF(ISBLANK($B$18),"",$B$18)) | U18: =IF(ISERROR($F$18),"",IF(ISBLANK($F$18),"",$F$18)) | V18: =IF(ISERROR($G$18),"",IF(ISBLANK($G$18),"",$G$18)) | W18: =IF(ISERROR($H$18),"",IF(ISBLANK($H$18),"",$H$18)) | X18: =IF(ISERROR($I$18),"",IF(ISBLANK($I$18),"",$I$18)) | Y18: =ISERROR($B$18)*1+ISERROR($C$18)*1+ISERROR($D$18)*1+ISERROR($E$18)*1+ISERROR($F$18)*1+ISERROR($G$18)*1+ISERROR($H$18)*1+ISERROR($I$18)*1+ISERROR($J$18)*1
A19: =IF(LEN($P$10)>0,$P$10,"PJ 4") | K19: =IF(Y19>0,"O Google leu como fórmula: digite de novo com ' na frente.",IF(AND(ISNUMBER($U$19),OR($U$19<7,$U$19>25)),"VEL fora dos extremos 7 a 25 da fórmula: confira na ficha (19.1)",IF(OR(AND(ISNUMBER($V$19),OR($V$19<-1,$V$19>5)),AND(ISNUMBER($W$19),OR($W$19<-1,$W$19>5)),AND(ISNUMBER($X$19),OR($X$19<-1,$X$19>5))),"Bônus de Atributo fora de -1 a +5: confira na ficha",IF(AND(ISNUMBER($Q$19),OR($Q$19<1,$Q$19>999)),"PV fora de 1 a 999: confira na ficha","")))) | Q19: =IF(ISERROR($B$19),"",IF(ISBLANK($B$19),"",$B$19)) | U19: =IF(ISERROR($F$19),"",IF(ISBLANK($F$19),"",$F$19)) | V19: =IF(ISERROR($G$19),"",IF(ISBLANK($G$19),"",$G$19)) | W19: =IF(ISERROR($H$19),"",IF(ISBLANK($H$19),"",$H$19)) | X19: =IF(ISERROR($I$19),"",IF(ISBLANK($I$19),"",$I$19)) | Y19: =ISERROR($B$19)*1+ISERROR($C$19)*1+ISERROR($D$19)*1+ISERROR($E$19)*1+ISERROR($F$19)*1+ISERROR($G$19)*1+ISERROR($H$19)*1+ISERROR($I$19)*1+ISERROR($J$19)*1
A20: =IF(LEN($P$11)>0,$P$11,"PJ 5") | K20: =IF(Y20>0,"O Google leu como fórmula: digite de novo com ' na frente.",IF(AND(ISNUMBER($U$20),OR($U$20<7,$U$20>25)),"VEL fora dos extremos 7 a 25 da fórmula: confira na ficha (19.1)",IF(OR(AND(ISNUMBER($V$20),OR($V$20<-1,$V$20>5)),AND(ISNUMBER($W$20),OR($W$20<-1,$W$20>5)),AND(ISNUMBER($X$20),OR($X$20<-1,$X$20>5))),"Bônus de Atributo fora de -1 a +5: confira na ficha",IF(AND(ISNUMBER($Q$20),OR($Q$20<1,$Q$20>999)),"PV fora de 1 a 999: confira na ficha","")))) | Q20: =IF(ISERROR($B$20),"",IF(ISBLANK($B$20),"",$B$20)) | U20: =IF(ISERROR($F$20),"",IF(ISBLANK($F$20),"",$F$20)) | V20: =IF(ISERROR($G$20),"",IF(ISBLANK($G$20),"",$G$20)) | W20: =IF(ISERROR($H$20),"",IF(ISBLANK($H$20),"",$H$20)) | X20: =IF(ISERROR($I$20),"",IF(ISBLANK($I$20),"",$I$20)) | Y20: =ISERROR($B$20)*1+ISERROR($C$20)*1+ISERROR($D$20)*1+ISERROR($E$20)*1+ISERROR($F$20)*1+ISERROR($G$20)*1+ISERROR($H$20)*1+ISERROR($I$20)*1+ISERROR($J$20)*1
A21: =IF(LEN($P$12)>0,$P$12,"PJ 6") | K21: =IF(Y21>0,"O Google leu como fórmula: digite de novo com ' na frente.",IF(AND(ISNUMBER($U$21),OR($U$21<7,$U$21>25)),"VEL fora dos extremos 7 a 25 da fórmula: confira na ficha (19.1)",IF(OR(AND(ISNUMBER($V$21),OR($V$21<-1,$V$21>5)),AND(ISNUMBER($W$21),OR($W$21<-1,$W$21>5)),AND(ISNUMBER($X$21),OR($X$21<-1,$X$21>5))),"Bônus de Atributo fora de -1 a +5: confira na ficha",IF(AND(ISNUMBER($Q$21),OR($Q$21<1,$Q$21>999)),"PV fora de 1 a 999: confira na ficha","")))) | Q21: =IF(ISERROR($B$21),"",IF(ISBLANK($B$21),"",$B$21)) | U21: =IF(ISERROR($F$21),"",IF(ISBLANK($F$21),"",$F$21)) | V21: =IF(ISERROR($G$21),"",IF(ISBLANK($G$21),"",$G$21)) | W21: =IF(ISERROR($H$21),"",IF(ISBLANK($H$21),"",$H$21)) | X21: =IF(ISERROR($I$21),"",IF(ISBLANK($I$21),"",$I$21)) | Y21: =ISERROR($B$21)*1+ISERROR($C$21)*1+ISERROR($D$21)*1+ISERROR($E$21)*1+ISERROR($F$21)*1+ISERROR($G$21)*1+ISERROR($H$21)*1+ISERROR($I$21)*1+ISERROR($J$21)*1
A23: G3 · Equipamento de faixa (preencha)
A24: PJ | B24: Nível do Cone | C24: Tier de Relíquias | D24: Slots de Relíquia | E24: Sobreposições nesta faixa | F24: Ressonâncias escolhidas | K24: Aviso
A25: =IF(LEN($P$7)>0,$P$7,"PJ 1") | K25: =IF(Y25>0,"O Google leu como fórmula: digite de novo com ' na frente.",IF(AND(ISNUMBER($Q$25),$Q$25>'Campanha'!$B$18),"Cone acima do máximo da faixa (25.1)",IF(AND(ISNUMBER($T$25),$T$25>1),"Mais de 1 Sobreposição nesta faixa (25.2)",""))) | Q25: =IF(ISERROR($B$25),"",IF(ISBLANK($B$25),"",$B$25)) | T25: =IF(ISERROR($E$25),"",IF(ISBLANK($E$25),"",$E$25)) | Y25: =ISERROR($B$25)*1+ISERROR($C$25)*1+ISERROR($D$25)*1+ISERROR($E$25)*1+ISERROR($F$25)*1
A26: =IF(LEN($P$8)>0,$P$8,"PJ 2") | K26: =IF(Y26>0,"O Google leu como fórmula: digite de novo com ' na frente.",IF(AND(ISNUMBER($Q$26),$Q$26>'Campanha'!$B$18),"Cone acima do máximo da faixa (25.1)",IF(AND(ISNUMBER($T$26),$T$26>1),"Mais de 1 Sobreposição nesta faixa (25.2)",""))) | Q26: =IF(ISERROR($B$26),"",IF(ISBLANK($B$26),"",$B$26)) | T26: =IF(ISERROR($E$26),"",IF(ISBLANK($E$26),"",$E$26)) | Y26: =ISERROR($B$26)*1+ISERROR($C$26)*1+ISERROR($D$26)*1+ISERROR($E$26)*1+ISERROR($F$26)*1
A27: =IF(LEN($P$9)>0,$P$9,"PJ 3") | K27: =IF(Y27>0,"O Google leu como fórmula: digite de novo com ' na frente.",IF(AND(ISNUMBER($Q$27),$Q$27>'Campanha'!$B$18),"Cone acima do máximo da faixa (25.1)",IF(AND(ISNUMBER($T$27),$T$27>1),"Mais de 1 Sobreposição nesta faixa (25.2)",""))) | Q27: =IF(ISERROR($B$27),"",IF(ISBLANK($B$27),"",$B$27)) | T27: =IF(ISERROR($E$27),"",IF(ISBLANK($E$27),"",$E$27)) | Y27: =ISERROR($B$27)*1+ISERROR($C$27)*1+ISERROR($D$27)*1+ISERROR($E$27)*1+ISERROR($F$27)*1
A28: =IF(LEN($P$10)>0,$P$10,"PJ 4") | K28: =IF(Y28>0,"O Google leu como fórmula: digite de novo com ' na frente.",IF(AND(ISNUMBER($Q$28),$Q$28>'Campanha'!$B$18),"Cone acima do máximo da faixa (25.1)",IF(AND(ISNUMBER($T$28),$T$28>1),"Mais de 1 Sobreposição nesta faixa (25.2)",""))) | Q28: =IF(ISERROR($B$28),"",IF(ISBLANK($B$28),"",$B$28)) | T28: =IF(ISERROR($E$28),"",IF(ISBLANK($E$28),"",$E$28)) | Y28: =ISERROR($B$28)*1+ISERROR($C$28)*1+ISERROR($D$28)*1+ISERROR($E$28)*1+ISERROR($F$28)*1
A29: =IF(LEN($P$11)>0,$P$11,"PJ 5") | K29: =IF(Y29>0,"O Google leu como fórmula: digite de novo com ' na frente.",IF(AND(ISNUMBER($Q$29),$Q$29>'Campanha'!$B$18),"Cone acima do máximo da faixa (25.1)",IF(AND(ISNUMBER($T$29),$T$29>1),"Mais de 1 Sobreposição nesta faixa (25.2)",""))) | Q29: =IF(ISERROR($B$29),"",IF(ISBLANK($B$29),"",$B$29)) | T29: =IF(ISERROR($E$29),"",IF(ISBLANK($E$29),"",$E$29)) | Y29: =ISERROR($B$29)*1+ISERROR($C$29)*1+ISERROR($D$29)*1+ISERROR($E$29)*1+ISERROR($F$29)*1
A30: =IF(LEN($P$12)>0,$P$12,"PJ 6") | K30: =IF(Y30>0,"O Google leu como fórmula: digite de novo com ' na frente.",IF(AND(ISNUMBER($Q$30),$Q$30>'Campanha'!$B$18),"Cone acima do máximo da faixa (25.1)",IF(AND(ISNUMBER($T$30),$T$30>1),"Mais de 1 Sobreposição nesta faixa (25.2)",""))) | Q30: =IF(ISERROR($B$30),"",IF(ISBLANK($B$30),"",$B$30)) | T30: =IF(ISERROR($E$30),"",IF(ISBLANK($E$30),"",$E$30)) | Y30: =ISERROR($B$30)*1+ISERROR($C$30)*1+ISERROR($D$30)*1+ISERROR($E$30)*1+ISERROR($F$30)*1
A32: G4 · O que a Raça muda no combate (automático)
A33: PJ | B33: Morrendo com Vantagem? | C33: Pode ser Executado? | D33: Esforço? | E33: Descobre Fraqueza | G33: Lembrete da Raça | K33: Aviso
A34: =IF(LEN($P$7)>0,$P$7,"PJ 1") | B34: =IFERROR(INDEX('Dados'!$B$350:$B$356,MATCH($R$7,'Dados'!$A$350:$A$356,0)),"") | C34: =IFERROR(INDEX('Dados'!$C$350:$C$356,MATCH($R$7,'Dados'!$A$350:$A$356,0)),"") | D34: =IFERROR(INDEX('Dados'!$D$350:$D$356,MATCH($R$7,'Dados'!$A$350:$A$356,0)),"") | E34: =IFERROR(INDEX('Dados'!$E$350:$E$356,MATCH($R$7,'Dados'!$A$350:$A$356,0)),"") | G34: =IF($R$7="Vulpes","Raposa Astuta: segunda chance contra a Surpresa (DT 10, 19.3 e 27.3)",IF($R$7="Haloviano","To na sua mente: DT 13 de ativação (27.3)",IF($R$7="Xianzhouíta","Não pode ser Executado (05, 23.5)",IF($R$7="Intellitron","Descobre Fraqueza com Vantagem e 2 por sucesso (20.2)",IF($R$7="Humano","Esforço: no máximo 1 ponto (05)",""))))) | K34: =IF(AND(ISNUMBER($Q$25),$Q$25<'Campanha'!$B$18),"Cone abaixo do esperado: encontros ficam mais duros (27.8)","")
A35: =IF(LEN($P$8)>0,$P$8,"PJ 2") | B35: =IFERROR(INDEX('Dados'!$B$350:$B$356,MATCH($R$8,'Dados'!$A$350:$A$356,0)),"") | C35: =IFERROR(INDEX('Dados'!$C$350:$C$356,MATCH($R$8,'Dados'!$A$350:$A$356,0)),"") | D35: =IFERROR(INDEX('Dados'!$D$350:$D$356,MATCH($R$8,'Dados'!$A$350:$A$356,0)),"") | E35: =IFERROR(INDEX('Dados'!$E$350:$E$356,MATCH($R$8,'Dados'!$A$350:$A$356,0)),"") | G35: =IF($R$8="Vulpes","Raposa Astuta: segunda chance contra a Surpresa (DT 10, 19.3 e 27.3)",IF($R$8="Haloviano","To na sua mente: DT 13 de ativação (27.3)",IF($R$8="Xianzhouíta","Não pode ser Executado (05, 23.5)",IF($R$8="Intellitron","Descobre Fraqueza com Vantagem e 2 por sucesso (20.2)",IF($R$8="Humano","Esforço: no máximo 1 ponto (05)",""))))) | K35: =IF(AND(ISNUMBER($Q$26),$Q$26<'Campanha'!$B$18),"Cone abaixo do esperado: encontros ficam mais duros (27.8)","")
A36: =IF(LEN($P$9)>0,$P$9,"PJ 3") | B36: =IFERROR(INDEX('Dados'!$B$350:$B$356,MATCH($R$9,'Dados'!$A$350:$A$356,0)),"") | C36: =IFERROR(INDEX('Dados'!$C$350:$C$356,MATCH($R$9,'Dados'!$A$350:$A$356,0)),"") | D36: =IFERROR(INDEX('Dados'!$D$350:$D$356,MATCH($R$9,'Dados'!$A$350:$A$356,0)),"") | E36: =IFERROR(INDEX('Dados'!$E$350:$E$356,MATCH($R$9,'Dados'!$A$350:$A$356,0)),"") | G36: =IF($R$9="Vulpes","Raposa Astuta: segunda chance contra a Surpresa (DT 10, 19.3 e 27.3)",IF($R$9="Haloviano","To na sua mente: DT 13 de ativação (27.3)",IF($R$9="Xianzhouíta","Não pode ser Executado (05, 23.5)",IF($R$9="Intellitron","Descobre Fraqueza com Vantagem e 2 por sucesso (20.2)",IF($R$9="Humano","Esforço: no máximo 1 ponto (05)",""))))) | K36: =IF(AND(ISNUMBER($Q$27),$Q$27<'Campanha'!$B$18),"Cone abaixo do esperado: encontros ficam mais duros (27.8)","")
A37: =IF(LEN($P$10)>0,$P$10,"PJ 4") | B37: =IFERROR(INDEX('Dados'!$B$350:$B$356,MATCH($R$10,'Dados'!$A$350:$A$356,0)),"") | C37: =IFERROR(INDEX('Dados'!$C$350:$C$356,MATCH($R$10,'Dados'!$A$350:$A$356,0)),"") | D37: =IFERROR(INDEX('Dados'!$D$350:$D$356,MATCH($R$10,'Dados'!$A$350:$A$356,0)),"") | E37: =IFERROR(INDEX('Dados'!$E$350:$E$356,MATCH($R$10,'Dados'!$A$350:$A$356,0)),"") | G37: =IF($R$10="Vulpes","Raposa Astuta: segunda chance contra a Surpresa (DT 10, 19.3 e 27.3)",IF($R$10="Haloviano","To na sua mente: DT 13 de ativação (27.3)",IF($R$10="Xianzhouíta","Não pode ser Executado (05, 23.5)",IF($R$10="Intellitron","Descobre Fraqueza com Vantagem e 2 por sucesso (20.2)",IF($R$10="Humano","Esforço: no máximo 1 ponto (05)",""))))) | K37: =IF(AND(ISNUMBER($Q$28),$Q$28<'Campanha'!$B$18),"Cone abaixo do esperado: encontros ficam mais duros (27.8)","")
A38: =IF(LEN($P$11)>0,$P$11,"PJ 5") | B38: =IFERROR(INDEX('Dados'!$B$350:$B$356,MATCH($R$11,'Dados'!$A$350:$A$356,0)),"") | C38: =IFERROR(INDEX('Dados'!$C$350:$C$356,MATCH($R$11,'Dados'!$A$350:$A$356,0)),"") | D38: =IFERROR(INDEX('Dados'!$D$350:$D$356,MATCH($R$11,'Dados'!$A$350:$A$356,0)),"") | E38: =IFERROR(INDEX('Dados'!$E$350:$E$356,MATCH($R$11,'Dados'!$A$350:$A$356,0)),"") | G38: =IF($R$11="Vulpes","Raposa Astuta: segunda chance contra a Surpresa (DT 10, 19.3 e 27.3)",IF($R$11="Haloviano","To na sua mente: DT 13 de ativação (27.3)",IF($R$11="Xianzhouíta","Não pode ser Executado (05, 23.5)",IF($R$11="Intellitron","Descobre Fraqueza com Vantagem e 2 por sucesso (20.2)",IF($R$11="Humano","Esforço: no máximo 1 ponto (05)",""))))) | K38: =IF(AND(ISNUMBER($Q$29),$Q$29<'Campanha'!$B$18),"Cone abaixo do esperado: encontros ficam mais duros (27.8)","")
A39: =IF(LEN($P$12)>0,$P$12,"PJ 6") | B39: =IFERROR(INDEX('Dados'!$B$350:$B$356,MATCH($R$12,'Dados'!$A$350:$A$356,0)),"") | C39: =IFERROR(INDEX('Dados'!$C$350:$C$356,MATCH($R$12,'Dados'!$A$350:$A$356,0)),"") | D39: =IFERROR(INDEX('Dados'!$D$350:$D$356,MATCH($R$12,'Dados'!$A$350:$A$356,0)),"") | E39: =IFERROR(INDEX('Dados'!$E$350:$E$356,MATCH($R$12,'Dados'!$A$350:$A$356,0)),"") | G39: =IF($R$12="Vulpes","Raposa Astuta: segunda chance contra a Surpresa (DT 10, 19.3 e 27.3)",IF($R$12="Haloviano","To na sua mente: DT 13 de ativação (27.3)",IF($R$12="Xianzhouíta","Não pode ser Executado (05, 23.5)",IF($R$12="Intellitron","Descobre Fraqueza com Vantagem e 2 por sucesso (20.2)",IF($R$12="Humano","Esforço: no máximo 1 ponto (05)",""))))) | K39: =IF(AND(ISNUMBER($Q$30),$Q$30<'Campanha'!$B$18),"Cone abaixo do esperado: encontros ficam mais duros (27.8)","")
A41: Resumo do grupo (automático)
A42: Nº de PJs | B42: =SUMPRODUCT((LEN($P$7:$P$12)>0)*1) | C42: =IF(AND(ISNUMBER('Campanha'!$P$8),$B$42>0,$B$42<>'Campanha'!$P$8),"Nº de PJs diferente do nº de jogadores da aba Campanha","")
A43: Elemento | B43: Físico | C43: Fogo | D43: Gelo | E43: Raio | F43: Vento | G43: Quântico | H43: Imaginário | I43: Distintos | J43: Em dobro
A44: No grupo? | B44: =IF(COUNTIF($T$7:$T$12,"Físico")>0,"Sim","Não") | C44: =IF(COUNTIF($T$7:$T$12,"Fogo")>0,"Sim","Não") | D44: =IF(COUNTIF($T$7:$T$12,"Gelo")>0,"Sim","Não") | E44: =IF(COUNTIF($T$7:$T$12,"Raio")>0,"Sim","Não") | F44: =IF(COUNTIF($T$7:$T$12,"Vento")>0,"Sim","Não") | G44: =IF(COUNTIF($T$7:$T$12,"Quântico")>0,"Sim","Não") | H44: =IF(COUNTIF($T$7:$T$12,"Imaginário")>0,"Sim","Não") | I44: =IF($B$44="Sim",1,0)+IF($C$44="Sim",1,0)+IF($D$44="Sim",1,0)+IF($E$44="Sim",1,0)+IF($F$44="Sim",1,0)+IF($G$44="Sim",1,0)+IF($H$44="Sim",1,0) | J44: =IF(COUNTIF($T$7:$T$12,"Físico")>1,1,0)+IF(COUNTIF($T$7:$T$12,"Fogo")>1,1,0)+IF(COUNTIF($T$7:$T$12,"Gelo")>1,1,0)+IF(COUNTIF($T$7:$T$12,"Raio")>1,1,0)+IF(COUNTIF($T$7:$T$12,"Vento")>1,1,0)+IF(COUNTIF($T$7:$T$12,"Quântico")>1,1,0)+IF(COUNTIF($T$7:$T$12,"Imaginário")>1,1,0)
A45: Presenças | B45: =IF(COUNTIF($R$7:$R$12,"Intellitron")>0,"Intellitron no grupo: descobre Fraqueza com Vantagem e 2 por sucesso (20.2). ","")&IF(COUNTIF($R$7:$R$12,"Humano")>0,"Humano no grupo: Esforço (05). ","")&IF(COUNTIF($S$7:$S$12,"A Preservação")+COUNTIF($S$7:$S$12,"A Abundância")>0,"Há Caminho de sustentação (27.7).","Sem Preservação nem Abundância: cuidado com o dia de jogo (27.7).")

Sheet Sessões
A1: Sessões — Explorando Galáxias v1.1
A2: Legenda: | B2: Entrada (preencha) | C2: Calculada (automático) | D2: Aviso (texto em vermelho) | E2: Título de bloco | F2: Cabeçalho de coluna | G2: Rótulo da linha | H2: Linha alternada (outro tom) | I2: Não se aplica
A3: Preparar a próxima sessão e o diário de campanha.
A5: Em construção: esta aba chega numa próxima fase da Planilha do Mestre.

Sheet Missões
A1: Missões — Explorando Galáxias v1.1
A2: Legenda: | B2: Entrada (preencha) | C2: Calculada (automático) | D2: Aviso (texto em vermelho) | E2: Título de bloco | F2: Cabeçalho de coluna | G2: Rótulo da linha | H2: Linha alternada (outro tom) | I2: Não se aplica
A3: As missões oferecidas, ativas e concluídas.
A5: Em construção: esta aba chega numa próxima fase da Planilha do Mestre.

Sheet NPCs
A1: NPCs — Explorando Galáxias v1.1
A2: Legenda: | B2: Entrada (preencha) | C2: Calculada (automático) | D2: Aviso (texto em vermelho) | E2: Título de bloco | F2: Cabeçalho de coluna | G2: Rótulo da linha | H2: Linha alternada (outro tom) | I2: Não se aplica
A3: Gerador de NPCs (nome por cultura, Raça, Caminho, ocupação, voz, segredo, gancho), elenco e cartões.
A5: Gerador de NPCs (G = 200): vazio = Sortear; a semente é a da aba Início
A6: Rolagem nº | B6: Raça | D6: Caminho | F6: Papel na história | H6: Bloco de combate | J6: Tipo do bloco | K6: Aviso
K7: =IF(BF7>0,"O Google leu como fórmula: escolha de novo ou digite com ' na frente.",IF(LEN(IF(LEN($AV$7)=0,"",IF(ISNUMBER($AV$7),IF(AND($AV$7>=1,$AV$7<=1000000,INT($AV$7)=$AV$7),"","Rolagem nº fora de 1 a 1.000.000: usando 1"),"Rolagem nº fora de 1 a 1.000.000: usando 1")))>0,IF(LEN($AV$7)=0,"",IF(ISNUMBER($AV$7),IF(AND($AV$7>=1,$AV$7<=1000000,INT($AV$7)=$AV$7),"","Rolagem nº fora de 1 a 1.000.000: usando 1"),"Rolagem nº fora de 1 a 1.000.000: usando 1")),IF(AND(LEN($AW$7)>0,$AW$7<>"Sortear",COUNTIF('Dados'!$A$350:$A$356,$AW$7)=0),"Raça fora da lista do capítulo 05: sorteando",IF(AND(LEN($AY$7)>0,$AY$7<>"Sortear",$AY$7<>"Nenhum",COUNTIF('Dados'!$A$360:$A$368,$AY$7)=0),"Caminho fora da lista: sorteando",IF(AND(LEN($BA$7)>0,$BA$7<>"Sortear",COUNTIF('Dados'!$A$398:$A$404,$BA$7)=0),"Papel fora da lista: sorteando",IF(AND(LEN($BC$7)>0,$BC$7<>"Nenhum",$BC$7<>"Do grupo",LEN(IFERROR(INDEX('Dados'!$B$7:$B$11,MATCH($BC$7,'Dados'!$AP$6:$AP$10,0)),""))=0),"Bloco de combate fora da lista: sem bloco",IF(AND(LEN($BE$7)>0,$BE$7<>"Comum",$BE$7<>"Elite"),"Tipo do bloco fora da lista: usando Comum",""))))))) | AV7: =IF(ISERROR($A$7),"",IF(ISBLANK($A$7),"",$A$7)) | AW7: =IF(ISERROR($B$7),"",IF(ISBLANK($B$7),"",$B$7)) | AY7: =IF(ISERROR($D$7),"",IF(ISBLANK($D$7),"",$D$7)) | BA7: =IF(ISERROR($F$7),"",IF(ISBLANK($F$7),"",$F$7)) | BC7: =IF(ISERROR($H$7),"",IF(ISBLANK($H$7),"",$H$7)) | BE7: =IF(ISERROR($J$7),"",IF(ISBLANK($J$7),"",$J$7)) | BF7: =ISERROR($A$7)*1+ISERROR($B$7)*1+ISERROR($D$7)*1+ISERROR($F$7)*1+ISERROR($H$7)*1+ISERROR($J$7)*1
A8: Rolagem efetiva | B8: =IF(ISNUMBER($AV$7),IF(AND($AV$7>=1,$AV$7<=1000000,INT($AV$7)=$AV$7),$AV$7,1),1) | C8: Mesma semente e mesma Rolagem nº dão o mesmo NPC; para outro, some 1 na Rolagem nº. Bloco de combate vazio = Nenhum; tipo vazio = Comum.
A10: NPC sorteado (automático) | N10: =IF(COUNTIF('Dados'!$A$350:$A$356,$AW$7)>0,$AW$7,INDEX('Dados'!$A$350:$A$356,INT($AC$10*7/2147483647)+1)) | AA10: =MOD(MOD(MOD((MOD('Início'!$E$15+104729*$B$8+2883509,2147483646)+1)*16807,2147483647)*16807,2147483647)*16807,2147483647) | AB10: =MOD(MOD(MOD((MOD(MOD(INT($AA$10/65536)*$AA$10,2147483647)*65536+MOD($AA$10,65536)*$AA$10,2147483647))*16807,2147483647)*16807,2147483647)*16807,2147483647) | AC10: =MOD(MOD(MOD((MOD($AB$10+INT($AB$10/65536)*MOD($AB$10,65536),2147483646)+1)*16807,2147483647)*16807,2147483647)*16807,2147483647) | AE10: =0+IF(AND(LEN($N$15)>0,INDEX('Tabelas'!$X$472:$X$578,1)&""=$N$15,LEN(INDEX('Tabelas'!$Y$472:$Y$578,1)&"")>0),1,0) | AG10: =$AV$46&"" | AH10: =$AW$46&"" | AI10: =$AY$46&"" | AJ10: =$BC$46&"" | AK10: =$AW$80&"" | AL10: =$AW$148&"" | AM10: =$AW$114&"" | AN10: =$BA$114&"" | AO10: =$AZ$148&"" | AP10: =$BA$46&"" | AT10: ='Tabelas'!$AE$357&""
A11: Campo | B11: Sorteado | I11: De onde vem | K11: Aviso | N11: =IFERROR(MATCH($N$10,'Dados'!$A$388:$A$394,0),1) | AA11: =MOD(MOD(MOD((MOD('Início'!$E$15+104729*$B$8+4183218,2147483646)+1)*16807,2147483647)*16807,2147483647)*16807,2147483647) | AB11: =MOD(MOD(MOD((MOD(MOD(INT($AA$11/65536)*$AA$11,2147483647)*65536+MOD($AA$11,65536)*$AA$11,2147483647))*16807,2147483647)*16807,2147483647)*16807,2147483647) | AC11: =MOD(MOD(MOD((MOD($AB$11+INT($AB$11/65536)*MOD($AB$11,65536),2147483646)+1)*16807,2147483647)*16807,2147483647)*16807,2147483647) | AE11: =$AE$10+IF(AND(LEN($N$15)>0,INDEX('Tabelas'!$X$472:$X$578,2)&""=$N$15,LEN(INDEX('Tabelas'!$Y$472:$Y$578,2)&"")>0),1,0) | AG11: =$AV$47&"" | AH11: =$AW$47&"" | AI11: =$AY$47&"" | AJ11: =$BC$47&"" | AK11: =$AW$81&"" | AL11: =$AW$149&"" | AM11: =$AW$115&"" | AN11: =$BA$115&"" | AO11: =$AZ$149&"" | AP11: =$BA$47&"" | AT11: ='Tabelas'!$AE$358&""
A12: Nome completo | B12: =$N$14 | I12: ="Tabelas: nome e sobrenome da cultura "&$N$10&" (estilo de 05)" | K12: =IF($N$11=1,IF('Tabelas'!$B$124+'Tabelas'!$B$239<=0,"Listas de nome da cultura Humano vazias (aba Tabelas)",""),IF($N$11=2,IF('Tabelas'!$C$124+'Tabelas'!$C$239<=0,"Listas de nome da cultura Xianzhouíta vazias (aba Tabelas)",""),IF($N$11=3,IF('Tabelas'!$D$124+'Tabelas'!$D$239<=0,"Listas de nome da cultura Vidyadhara vazias (aba Tabelas)",""),IF($N$11=4,IF('Tabelas'!$E$124+'Tabelas'!$E$239<=0,"Listas de nome da cultura Vulpes vazias (aba Tabelas)",""),IF($N$11=5,IF('Tabelas'!$F$124+'Tabelas'!$F$239<=0,"Listas de nome da cultura Haloviano vazias (aba Tabelas)",""),IF($N$11=6,IF('Tabelas'!$G$124+'Tabelas'!$G$239<=0,"Listas de nome da cultura Avginiano vazias (aba Tabelas)",""),IF('Tabelas'!$H$124+'Tabelas'!$H$239<=0,"Listas de nome da cultura Intellitron vazias (aba Tabelas)",""))))))) | N12: =IF($N$11=1,IF('Tabelas'!$B$124<=0,"",IFERROR(INDEX('Tabelas'!$X$127:$X$233,MATCH(IF('Tabelas'!$B$124<=0,0,INT($AC$11*'Tabelas'!$B$124/2147483647)+1),'Tabelas'!$N$127:$N$233,0))&"","")),IF($N$11=2,IF('Tabelas'!$C$124<=0,"",IFERROR(INDEX('Tabelas'!$Y$127:$Y$233,MATCH(IF('Tabelas'!$C$124<=0,0,INT($AC$11*'Tabelas'!$C$124/2147483647)+1),'Tabelas'!$O$127:$O$233,0))&"","")),IF($N$11=3,IF('Tabelas'!$D$124<=0,"",IFERROR(INDEX('Tabelas'!$Z$127:$Z$233,MATCH(IF('Tabelas'!$D$124<=0,0,INT($AC$11*'Tabelas'!$D$124/2147483647)+1),'Tabelas'!$P$127:$P$233,0))&"","")),IF($N$11=4,IF('Tabelas'!$E$124<=0,"",IFERROR(INDEX('Tabelas'!$AA$127:$AA$233,MATCH(IF('Tabelas'!$E$124<=0,0,INT($AC$11*'Tabelas'!$E$124/2147483647)+1),'Tabelas'!$Q$127:$Q$233,0))&"","")),IF($N$11=5,IF('Tabelas'!$F$124<=0,"",IFERROR(INDEX('Tabelas'!$AB$127:$AB$233,MATCH(IF('Tabelas'!$F$124<=0,0,INT($AC$11*'Tabelas'!$F$124/2147483647)+1),'Tabelas'!$R$127:$R$233,0))&"","")),IF($N$11=6,IF('Tabelas'!$G$124<=0,"",IFERROR(INDEX('Tabelas'!$AC$127:$AC$233,MATCH(IF('Tabelas'!$G$124<=0,0,INT($AC$11*'Tabelas'!$G$124/2147483647)+1),'Tabelas'!$S$127:$S$233,0))&"","")),IF('Tabelas'!$H$124<=0,"",IFERROR(INDEX('Tabelas'!$AD$127:$AD$233,MATCH(IF('Tabelas'!$H$124<=0,0,INT($AC$11*'Tabelas'!$H$124/2147483647)+1),'Tabelas'!$T$127:$T$233,0))&"","")))))))) | AA12: =MOD(MOD(MOD((MOD('Início'!$E$15+104729*$B$8+5482927,2147483646)+1)*16807,2147483647)*16807,2147483647)*16807,2147483647) | AB12: =MOD(MOD(MOD((MOD(MOD(INT($AA$12/65536)*$AA$12,2147483647)*65536+MOD($AA$12,65536)*$AA$12,2147483647))*16807,2147483647)*16807,2147483647)*16807,2147483647) | AC12: =MOD(MOD(MOD((MOD($AB$12+INT($AB$12/65536)*MOD($AB$12,65536),2147483646)+1)*16807,2147483647)*16807,2147483647)*16807,2147483647) | AE12: =$AE$11+IF(AND(LEN($N$15)>0,INDEX('Tabelas'!$X$472:$X$578,3)&""=$N$15,LEN(INDEX('Tabelas'!$Y$472:$Y$578,3)&"")>0),1,0) | AG12: =$AV$48&"" | AH12: =$AW$48&"" | AI12: =$AY$48&"" | AJ12: =$BC$48&"" | AK12: =$AW$82&"" | AL12: =$AW$150&"" | AM12: =$AW$116&"" | AN12: =$BA$116&"" | AO12: =$AZ$150&"" | AP12: =$BA$48&"" | AT12: ='Tabelas'!$AE$359&""
A13: Raça | B13: =$N$10 | I13: =IF(COUNTIF('Dados'!$A$350:$A$356,$AW$7)>0,"Escolhida","Sorteada entre as 7 Raças de 05") | N13: =IF($N$11=1,IF('Tabelas'!$B$239<=0,"",IFERROR(INDEX('Tabelas'!$X$242:$X$348,MATCH(IF('Tabelas'!$B$239<=0,0,INT($AC$12*'Tabelas'!$B$239/2147483647)+1),'Tabelas'!$N$242:$N$348,0))&"","")),IF($N$11=2,IF('Tabelas'!$C$239<=0,"",IFERROR(INDEX('Tabelas'!$Y$242:$Y$348,MATCH(IF('Tabelas'!$C$239<=0,0,INT($AC$12*'Tabelas'!$C$239/2147483647)+1),'Tabelas'!$O$242:$O$348,0))&"","")),IF($N$11=3,IF('Tabelas'!$D$239<=0,"",IFERROR(INDEX('Tabelas'!$Z$242:$Z$348,MATCH(IF('Tabelas'!$D$239<=0,0,INT($AC$12*'Tabelas'!$D$239/2147483647)+1),'Tabelas'!$P$242:$P$348,0))&"","")),IF($N$11=4,IF('Tabelas'!$E$239<=0,"",IFERROR(INDEX('Tabelas'!$AA$242:$AA$348,MATCH(IF('Tabelas'!$E$239<=0,0,INT($AC$12*'Tabelas'!$E$239/2147483647)+1),'Tabelas'!$Q$242:$Q$348,0))&"","")),IF($N$11=5,IF('Tabelas'!$F$239<=0,"",IFERROR(INDEX('Tabelas'!$AB$242:$AB$348,MATCH(IF('Tabelas'!$F$239<=0,0,INT($AC$12*'Tabelas'!$F$239/2147483647)+1),'Tabelas'!$R$242:$R$348,0))&"","")),IF($N$11=6,IF('Tabelas'!$G$239<=0,"",IFERROR(INDEX('Tabelas'!$AC$242:$AC$348,MATCH(IF('Tabelas'!$G$239<=0,0,INT($AC$12*'Tabelas'!$G$239/2147483647)+1),'Tabelas'!$S$242:$S$348,0))&"","")),IF('Tabelas'!$H$239<=0,"",IFERROR(INDEX('Tabelas'!$AD$242:$AD$348,MATCH(IF('Tabelas'!$H$239<=0,0,INT($AC$12*'Tabelas'!$H$239/2147483647)+1),'Tabelas'!$T$242:$T$348,0))&"","")))))))) | AA13: =MOD(MOD(MOD((MOD('Início'!$E$15+104729*$B$8+6782636,2147483646)+1)*16807,2147483647)*16807,2147483647)*16807,2147483647) | AB13: =MOD(MOD(MOD((MOD(MOD(INT($AA$13/65536)*$AA$13,2147483647)*65536+MOD($AA$13,65536)*$AA$13,2147483647))*16807,2147483647)*16807,2147483647)*16807,2147483647) | AC13: =MOD(MOD(MOD((MOD($AB$13+INT($AB$13/65536)*MOD($AB$13,65536),2147483646)+1)*16807,2147483647)*16807,2147483647)*16807,2147483647) | AE13: =$AE$12+IF(AND(LEN($N$15)>0,INDEX('Tabelas'!$X$472:$X$578,4)&""=$N$15,LEN(INDEX('Tabelas'!$Y$472:$Y$578,4)&"")>0),1,0) | AG13: =$AV$49&"" | AH13: =$AW$49&"" | AI13: =$AY$49&"" | AJ13: =$BC$49&"" | AK13: =$AW$83&"" | AL13: =$AW$151&"" | AM13: =$AW$117&"" | AN13: =$BA$117&"" | AO13: =$AZ$151&"" | AP13: =$BA$49&"" | AT13: ='Tabelas'!$AE$360&""
A14: Caminho | B14: =$N$15 | I14: =IF(OR($AY$7="Nenhum",COUNTIF('Dados'!$A$360:$A$368,$AY$7)>0),"Escolhido","Tabelas: Caminho do NPC (06.3; Nenhum ×3, 27.12) · Sugestão da planilha — não é regra do livro (H11)") | N14: =IF(LEN($N$13)=0,$N$12,IF(LEN($N$12)=0,$N$13,IF(INDEX('Dados'!$B$388:$B$394,$N$11)=2,$N$13&INDEX('Dados'!$C$388:$C$394,$N$11)&$N$12,$N$12&INDEX('Dados'!$C$388:$C$394,$N$11)&$N$13))) | AA14: =MOD(MOD(MOD((MOD('Início'!$E$15+104729*$B$8+8082345,2147483646)+1)*16807,2147483647)*16807,2147483647)*16807,2147483647) | AB14: =MOD(MOD(MOD((MOD(MOD(INT($AA$14/65536)*$AA$14,2147483647)*65536+MOD($AA$14,65536)*$AA$14,2147483647))*16807,2147483647)*16807,2147483647)*16807,2147483647) | AC14: =MOD(MOD(MOD((MOD($AB$14+INT($AB$14/65536)*MOD($AB$14,65536),2147483646)+1)*16807,2147483647)*16807,2147483647)*16807,2147483647) | AE14: =$AE$13+IF(AND(LEN($N$15)>0,INDEX('Tabelas'!$X$472:$X$578,5)&""=$N$15,LEN(INDEX('Tabelas'!$Y$472:$Y$578,5)&"")>0),1,0) | AG14: =$AV$50&"" | AH14: =$AW$50&"" | AI14: =$AY$50&"" | AJ14: =$BC$50&"" | AK14: =$AW$84&"" | AL14: =$AW$152&"" | AM14: =$AW$118&"" | AN14: =$BA$118&"" | AO14: =$AZ$152&"" | AP14: =$BA$50&"" | AT14: ='Tabelas'!$AE$361&""
A15: Ocupação | B15: =$N$16 | I15: ="Tabelas: Ocupação (NPC)" | K15: =IF('Tabelas'!$B$354<=0,"Lista 'Ocupação (NPC)' está vazia (aba Tabelas)","") | N15: =IF(OR($AY$7="Nenhum",COUNTIF('Dados'!$A$360:$A$368,$AY$7)>0),$AY$7,IF('Tabelas'!$H$354<=0,"",IFERROR(INDEX('Tabelas'!$AD$357:$AD$463,MATCH(IF('Tabelas'!$H$354<=0,0,INT($AC$13*'Tabelas'!$H$354/2147483647)+1),'Tabelas'!$T$357:$T$463,0))&"",""))) | AA15: =MOD(MOD(MOD((MOD('Início'!$E$15+104729*$B$8+9382054,2147483646)+1)*16807,2147483647)*16807,2147483647)*16807,2147483647) | AB15: =MOD(MOD(MOD((MOD(MOD(INT($AA$15/65536)*$AA$15,2147483647)*65536+MOD($AA$15,65536)*$AA$15,2147483647))*16807,2147483647)*16807,2147483647)*16807,2147483647) | AC15: =MOD(MOD(MOD((MOD($AB$15+INT($AB$15/65536)*MOD($AB$15,65536),2147483646)+1)*16807,2147483647)*16807,2147483647)*16807,2147483647) | AE15: =$AE$14+IF(AND(LEN($N$15)>0,INDEX('Tabelas'!$X$472:$X$578,6)&""=$N$15,LEN(INDEX('Tabelas'!$Y$472:$Y$578,6)&"")>0),1,0) | AG15: =$AV$51&"" | AH15: =$AW$51&"" | AI15: =$AY$51&"" | AJ15: =$BC$51&"" | AK15: =$AW$85&"" | AL15: =$AW$153&"" | AM15: =$AW$119&"" | AN15: =$BA$119&"" | AO15: =$AZ$153&"" | AP15: =$BA$51&"" | AT15: ='Tabelas'!$AE$362&""
A16: Aparência | B16: =$N$20 | I16: Sugestão da planilha — não é regra do livro (H25): 2 traços | K16: =IF('Tabelas'!$C$354<=0,"Lista 'Traço de aparência' está vazia (aba Tabelas)","") | N16: =IF('Tabelas'!$B$354<=0,"",IFERROR(INDEX('Tabelas'!$X$357:$X$463,MATCH(IF('Tabelas'!$B$354<=0,0,INT($AC$14*'Tabelas'!$B$354/2147483647)+1),'Tabelas'!$N$357:$N$463,0))&"","")) | AA16: =MOD(MOD(MOD((MOD('Início'!$E$15+104729*$B$8+10681763,2147483646)+1)*16807,2147483647)*16807,2147483647)*16807,2147483647) | AB16: =MOD(MOD(MOD((MOD(MOD(INT($AA$16/65536)*$AA$16,2147483647)*65536+MOD($AA$16,65536)*$AA$16,2147483647))*16807,2147483647)*16807,2147483647)*16807,2147483647) | AC16: =MOD(MOD(MOD((MOD($AB$16+INT($AB$16/65536)*MOD($AB$16,65536),2147483646)+1)*16807,2147483647)*16807,2147483647)*16807,2147483647) | AE16: =$AE$15+IF(AND(LEN($N$15)>0,INDEX('Tabelas'!$X$472:$X$578,7)&""=$N$15,LEN(INDEX('Tabelas'!$Y$472:$Y$578,7)&"")>0),1,0) | AG16: =$AV$52&"" | AH16: =$AW$52&"" | AI16: =$AY$52&"" | AJ16: =$BC$52&"" | AK16: =$AW$86&"" | AL16: =$AW$154&"" | AM16: =$AW$120&"" | AN16: =$BA$120&"" | AO16: =$AZ$154&"" | AP16: =$BA$52&"" | AT16: ='Tabelas'!$AE$363&""
A17: Personalidade | B17: =$N$21 | I17: ="Tabelas: Personalidade" | K17: =IF('Tabelas'!$D$354<=0,"Lista 'Personalidade' está vazia (aba Tabelas)","") | N17: =IF('Tabelas'!$C$354<=0,0,INT($AC$15*'Tabelas'!$C$354/2147483647)+1) | AA17: =MOD(MOD(MOD((MOD('Início'!$E$15+104729*$B$8+11981472,2147483646)+1)*16807,2147483647)*16807,2147483647)*16807,2147483647) | AB17: =MOD(MOD(MOD((MOD(MOD(INT($AA$17/65536)*$AA$17,2147483647)*65536+MOD($AA$17,65536)*$AA$17,2147483647))*16807,2147483647)*16807,2147483647)*16807,2147483647) | AC17: =MOD(MOD(MOD((MOD($AB$17+INT($AB$17/65536)*MOD($AB$17,65536),2147483646)+1)*16807,2147483647)*16807,2147483647)*16807,2147483647) | AE17: =$AE$16+IF(AND(LEN($N$15)>0,INDEX('Tabelas'!$X$472:$X$578,8)&""=$N$15,LEN(INDEX('Tabelas'!$Y$472:$Y$578,8)&"")>0),1,0) | AG17: =$AV$53&"" | AH17: =$AW$53&"" | AI17: =$AY$53&"" | AJ17: =$BC$53&"" | AK17: =$AW$87&"" | AL17: =$AW$155&"" | AM17: =$AW$121&"" | AN17: =$BA$121&"" | AO17: =$AZ$155&"" | AP17: =$BA$53&"" | AT17: ='Tabelas'!$AE$364&""
A18: Motivação | B18: =$N$23 | I18: =IF(OR($N$15="Nenhum",LEN($N$15)=0,$N$22=0),"Tabelas: Motivação (sem Caminho)","Tabelas: Motivação por Caminho (27.12)") | K18: =IF(AND($N$22=0,'Tabelas'!$E$354<=0),"Listas de motivação vazias (aba Tabelas)","") | N18: =IF('Tabelas'!$C$354<=0,"",IFERROR(INDEX('Tabelas'!$Y$357:$Y$463,MATCH($N$17,'Tabelas'!$O$357:$O$463,0))&"","")) | AA18: =MOD(MOD(MOD((MOD('Início'!$E$15+104729*$B$8+13281181,2147483646)+1)*16807,2147483647)*16807,2147483647)*16807,2147483647) | AB18: =MOD(MOD(MOD((MOD(MOD(INT($AA$18/65536)*$AA$18,2147483647)*65536+MOD($AA$18,65536)*$AA$18,2147483647))*16807,2147483647)*16807,2147483647)*16807,2147483647) | AC18: =MOD(MOD(MOD((MOD($AB$18+INT($AB$18/65536)*MOD($AB$18,65536),2147483646)+1)*16807,2147483647)*16807,2147483647)*16807,2147483647) | AE18: =$AE$17+IF(AND(LEN($N$15)>0,INDEX('Tabelas'!$X$472:$X$578,9)&""=$N$15,LEN(INDEX('Tabelas'!$Y$472:$Y$578,9)&"")>0),1,0) | AG18: =$AV$54&"" | AH18: =$AW$54&"" | AI18: =$AY$54&"" | AJ18: =$BC$54&"" | AK18: =$AW$88&"" | AL18: =$AW$156&"" | AM18: =$AW$122&"" | AN18: =$BA$122&"" | AO18: =$AZ$156&"" | AP18: =$BA$54&"" | AT18: ='Tabelas'!$AE$365&""
A19: Segredo | B19: =$N$24 | I19: ="Tabelas: Segredo" | K19: =IF('Tabelas'!$F$354<=0,"Lista 'Segredo' está vazia (aba Tabelas)","") | N19: =IF('Tabelas'!$C$354<=0,"",IFERROR(INDEX('Tabelas'!$Y$357:$Y$463,MATCH(IF('Tabelas'!$C$354<=1,$N$17,MOD($N$17-1+1+INT($AC$16*('Tabelas'!$C$354-1)/2147483647),'Tabelas'!$C$354)+1),'Tabelas'!$O$357:$O$463,0))&"","")) | AA19: =MOD(MOD(MOD((MOD('Início'!$E$15+104729*$B$8+14580890,2147483646)+1)*16807,2147483647)*16807,2147483647)*16807,2147483647) | AB19: =MOD(MOD(MOD((MOD(MOD(INT($AA$19/65536)*$AA$19,2147483647)*65536+MOD($AA$19,65536)*$AA$19,2147483647))*16807,2147483647)*16807,2147483647)*16807,2147483647) | AC19: =MOD(MOD(MOD((MOD($AB$19+INT($AB$19/65536)*MOD($AB$19,65536),2147483646)+1)*16807,2147483647)*16807,2147483647)*16807,2147483647) | AE19: =$AE$18+IF(AND(LEN($N$15)>0,INDEX('Tabelas'!$X$472:$X$578,10)&""=$N$15,LEN(INDEX('Tabelas'!$Y$472:$Y$578,10)&"")>0),1,0) | AG19: =$AV$55&"" | AH19: =$AW$55&"" | AI19: =$AY$55&"" | AJ19: =$BC$55&"" | AK19: =$AW$89&"" | AL19: =$AW$157&"" | AM19: =$AW$123&"" | AN19: =$BA$123&"" | AO19: =$AZ$157&"" | AP19: =$BA$55&"" | AT19: ='Tabelas'!$AE$366&""
A20: Maneirismo e voz | B20: =$N$25 | I20: ="Tabelas: Maneirismo e voz" | K20: =IF('Tabelas'!$G$354<=0,"Lista 'Maneirismo e voz' está vazia (aba Tabelas)","") | N20: =IF(LEN($N$18)=0,"",IF(OR($N$19=$N$18,LEN($N$19)=0),$N$18,$N$18&"; "&$N$19)) | AA20: =MOD(MOD(MOD((MOD('Início'!$E$15+104729*$B$8+15880599,2147483646)+1)*16807,2147483647)*16807,2147483647)*16807,2147483647) | AB20: =MOD(MOD(MOD((MOD(MOD(INT($AA$20/65536)*$AA$20,2147483647)*65536+MOD($AA$20,65536)*$AA$20,2147483647))*16807,2147483647)*16807,2147483647)*16807,2147483647) | AC20: =MOD(MOD(MOD((MOD($AB$20+INT($AB$20/65536)*MOD($AB$20,65536),2147483646)+1)*16807,2147483647)*16807,2147483647)*16807,2147483647) | AE20: =$AE$19+IF(AND(LEN($N$15)>0,INDEX('Tabelas'!$X$472:$X$578,11)&""=$N$15,LEN(INDEX('Tabelas'!$Y$472:$Y$578,11)&"")>0),1,0) | AG20: =$AV$57&"" | AH20: =$AW$57&"" | AI20: =$AY$57&"" | AJ20: =$BC$57&"" | AK20: =$AW$91&"" | AL20: =$AW$159&"" | AM20: =$AW$125&"" | AN20: =$BA$125&"" | AO20: =$AZ$159&"" | AP20: =$BA$57&"" | AT20: ='Tabelas'!$AE$367&""
A21: Atitude com o grupo | B21: =$N$26 | I21: ="Tabelas: Atitude com o grupo · Sugestão da planilha — não é regra do livro (H11)" | K21: =IF('Tabelas'!$I$354<=0,"Lista 'Atitude com o grupo' está vazia (aba Tabelas)","") | N21: =IF('Tabelas'!$D$354<=0,"",IFERROR(INDEX('Tabelas'!$Z$357:$Z$463,MATCH(IF('Tabelas'!$D$354<=0,0,INT($AC$17*'Tabelas'!$D$354/2147483647)+1),'Tabelas'!$P$357:$P$463,0))&"","")) | AA21: =MOD(MOD(MOD((MOD('Início'!$E$15+104729*$B$8+17180308,2147483646)+1)*16807,2147483647)*16807,2147483647)*16807,2147483647) | AB21: =MOD(MOD(MOD((MOD(MOD(INT($AA$21/65536)*$AA$21,2147483647)*65536+MOD($AA$21,65536)*$AA$21,2147483647))*16807,2147483647)*16807,2147483647)*16807,2147483647) | AC21: =MOD(MOD(MOD((MOD($AB$21+INT($AB$21/65536)*MOD($AB$21,65536),2147483646)+1)*16807,2147483647)*16807,2147483647)*16807,2147483647) | AE21: =$AE$20+IF(AND(LEN($N$15)>0,INDEX('Tabelas'!$X$472:$X$578,12)&""=$N$15,LEN(INDEX('Tabelas'!$Y$472:$Y$578,12)&"")>0),1,0) | AG21: =$AV$58&"" | AH21: =$AW$58&"" | AI21: =$AY$58&"" | AJ21: =$BC$58&"" | AK21: =$AW$92&"" | AL21: =$AW$160&"" | AM21: =$AW$126&"" | AN21: =$BA$126&"" | AO21: =$AZ$160&"" | AP21: =$BA$58&"" | AT21: ='Tabelas'!$AE$368&""
A22: Gancho | B22: =$N$30 | I22: =IF($N$27=1,"27.18, faixa "&'Campanha'!$B$19,"Tabelas: Gancho do NPC")&" · Sugestão da planilha — não é regra do livro (H20)" | K22: =IF(LEN($N$30)=0,"Listas de gancho vazias (aba Tabelas)","") | N22: =$AE$116 | AA22: =MOD(MOD(MOD((MOD('Início'!$E$15+104729*$B$8+18480017,2147483646)+1)*16807,2147483647)*16807,2147483647)*16807,2147483647) | AB22: =MOD(MOD(MOD((MOD(MOD(INT($AA$22/65536)*$AA$22,2147483647)*65536+MOD($AA$22,65536)*$AA$22,2147483647))*16807,2147483647)*16807,2147483647)*16807,2147483647) | AC22: =MOD(MOD(MOD((MOD($AB$22+INT($AB$22/65536)*MOD($AB$22,65536),2147483646)+1)*16807,2147483647)*16807,2147483647)*16807,2147483647) | AE22: =$AE$21+IF(AND(LEN($N$15)>0,INDEX('Tabelas'!$X$472:$X$578,13)&""=$N$15,LEN(INDEX('Tabelas'!$Y$472:$Y$578,13)&"")>0),1,0) | AG22: =$AV$59&"" | AH22: =$AW$59&"" | AI22: =$AY$59&"" | AJ22: =$BC$59&"" | AK22: =$AW$93&"" | AL22: =$AW$161&"" | AM22: =$AW$127&"" | AN22: =$BA$127&"" | AO22: =$AZ$161&"" | AP22: =$BA$59&"" | AT22: ='Tabelas'!$AE$369&""
A23: Papel na história | B23: =$N$31 | I23: =IF(COUNTIF('Dados'!$A$398:$A$404,$BA$7)>0,"Escolhido","Sorteado entre os 7 papéis") | N23: =IF(OR($N$15="Nenhum",LEN($N$15)=0,$N$22=0),IF('Tabelas'!$E$354<=0,"",IFERROR(INDEX('Tabelas'!$AA$357:$AA$463,MATCH(IF('Tabelas'!$E$354<=0,0,INT($AC$18*'Tabelas'!$E$354/2147483647)+1),'Tabelas'!$Q$357:$Q$463,0))&"","")),IFERROR(INDEX('Tabelas'!$Y$472:$Y$578,MATCH(INT($AC$18*$N$22/2147483647)+1,$AE$10:$AE$116,0))&"","")) | AA23: =MOD(MOD(MOD((MOD('Início'!$E$15+104729*$B$8+19779726,2147483646)+1)*16807,2147483647)*16807,2147483647)*16807,2147483647) | AB23: =MOD(MOD(MOD((MOD(MOD(INT($AA$23/65536)*$AA$23,2147483647)*65536+MOD($AA$23,65536)*$AA$23,2147483647))*16807,2147483647)*16807,2147483647)*16807,2147483647) | AC23: =MOD(MOD(MOD((MOD($AB$23+INT($AB$23/65536)*MOD($AB$23,65536),2147483646)+1)*16807,2147483647)*16807,2147483647)*16807,2147483647) | AE23: =$AE$22 | AG23: =$AV$60&"" | AH23: =$AW$60&"" | AI23: =$AY$60&"" | AJ23: =$BC$60&"" | AK23: =$AW$94&"" | AL23: =$AW$162&"" | AM23: =$AW$128&"" | AN23: =$BA$128&"" | AO23: =$AZ$162&"" | AP23: =$BA$60&"" | AT23: ='Tabelas'!$AE$371&""
N24: =IF('Tabelas'!$F$354<=0,"",IFERROR(INDEX('Tabelas'!$AB$357:$AB$463,MATCH(IF('Tabelas'!$F$354<=0,0,INT($AC$19*'Tabelas'!$F$354/2147483647)+1),'Tabelas'!$R$357:$R$463,0))&"","")) | AA24: =MOD(MOD(MOD((MOD('Início'!$E$15+104729*$B$8+21079435,2147483646)+1)*16807,2147483647)*16807,2147483647)*16807,2147483647) | AB24: =MOD(MOD(MOD((MOD(MOD(INT($AA$24/65536)*$AA$24,2147483647)*65536+MOD($AA$24,65536)*$AA$24,2147483647))*16807,2147483647)*16807,2147483647)*16807,2147483647) | AC24: =MOD(MOD(MOD((MOD($AB$24+INT($AB$24/65536)*MOD($AB$24,65536),2147483646)+1)*16807,2147483647)*16807,2147483647)*16807,2147483647) | AE24: =$AE$23+IF(AND(LEN($N$15)>0,INDEX('Tabelas'!$X$472:$X$578,15)&""=$N$15,LEN(INDEX('Tabelas'!$Y$472:$Y$578,15)&"")>0),1,0) | AG24: =$AV$61&"" | AH24: =$AW$61&"" | AI24: =$AY$61&"" | AJ24: =$BC$61&"" | AK24: =$AW$95&"" | AL24: =$AW$163&"" | AM24: =$AW$129&"" | AN24: =$BA$129&"" | AO24: =$AZ$163&"" | AP24: =$BA$61&"" | AT24: ='Tabelas'!$AE$372&""
A25: Bloco de combate (âncoras de 28.3; o mesmo número do Criador de Inimigos no modo Faixa do livro) | N25: =IF('Tabelas'!$G$354<=0,"",IFERROR(INDEX('Tabelas'!$AC$357:$AC$463,MATCH(IF('Tabelas'!$G$354<=0,0,INT($AC$20*'Tabelas'!$G$354/2147483647)+1),'Tabelas'!$S$357:$S$463,0))&"","")) | AE25: =$AE$24+IF(AND(LEN($N$15)>0,INDEX('Tabelas'!$X$472:$X$578,16)&""=$N$15,LEN(INDEX('Tabelas'!$Y$472:$Y$578,16)&"")>0),1,0) | AG25: =$AV$62&"" | AH25: =$AW$62&"" | AI25: =$AY$62&"" | AJ25: =$BC$62&"" | AK25: =$AW$96&"" | AL25: =$AW$164&"" | AM25: =$AW$130&"" | AN25: =$BA$130&"" | AO25: =$AZ$164&"" | AP25: =$BA$62&"" | AT25: ='Tabelas'!$AE$373&""
A26: Faixa · tipo | B26: PV | C26: Defesa | D26: RD | E26: Tenacidade | F26: VEL | G26: Ataque | H26: DT dos efeitos | I26: Teste de Resistência | J26: Nº de Fraquezas | K26: Aviso | N26: =IF('Tabelas'!$I$354<=0,"",IFERROR(INDEX('Tabelas'!$AE$357:$AE$463,MATCH(IF('Tabelas'!$I$354<=0,0,INT($AC$21*'Tabelas'!$I$354/2147483647)+1),'Tabelas'!$U$357:$U$463,0))&"","")) | AE26: =$AE$25+IF(AND(LEN($N$15)>0,INDEX('Tabelas'!$X$472:$X$578,17)&""=$N$15,LEN(INDEX('Tabelas'!$Y$472:$Y$578,17)&"")>0),1,0) | AG26: =$AV$63&"" | AH26: =$AW$63&"" | AI26: =$AY$63&"" | AJ26: =$BC$63&"" | AK26: =$AW$97&"" | AL26: =$AW$165&"" | AM26: =$AW$131&"" | AN26: =$BA$131&"" | AO26: =$AZ$165&"" | AP26: =$BA$63&"" | AT26: ='Tabelas'!$AE$374&""
A27: =IF(LEN($N$35)=0,"Sem bloco",$N$33&" · "&$N$34) | B27: =IF(LEN($N$35)=0,"",IFERROR(INDEX('Dados'!$D$38:$D$52,MATCH($N$35,'Dados'!$A$38:$A$52,0)),"")) | C27: =IF(LEN($N$35)=0,"",IFERROR(INDEX('Dados'!$E$38:$E$52,MATCH($N$35,'Dados'!$A$38:$A$52,0)),"")) | D27: =IF(LEN($N$35)=0,"",IFERROR(INDEX('Dados'!$F$38:$F$52,MATCH($N$35,'Dados'!$A$38:$A$52,0)),"")) | E27: =IF(LEN($N$35)=0,"",IFERROR(INDEX('Dados'!$G$38:$G$52,MATCH($N$35,'Dados'!$A$38:$A$52,0)),"")) | F27: =IF(LEN($N$35)=0,"",IFERROR(INDEX('Dados'!$H$38:$H$52,MATCH($N$35,'Dados'!$A$38:$A$52,0)),"")) | G27: =IF(LEN($N$35)=0,"","+"&IFERROR(INDEX('Dados'!$I$38:$I$52,MATCH($N$35,'Dados'!$A$38:$A$52,0)),"")) | H27: =IF(LEN($N$35)=0,"",IFERROR(INDEX('Dados'!$L$38:$L$52,MATCH($N$35,'Dados'!$A$38:$A$52,0)),"")) | I27: =IF(LEN($N$35)=0,"","+"&IFERROR(INDEX('Dados'!$M$38:$M$52,MATCH($N$35,'Dados'!$A$38:$A$52,0)),"")) | J27: =IF(LEN($N$35)=0,"",IFERROR(INDEX('Dados'!$N$38:$N$52,MATCH($N$35,'Dados'!$A$38:$A$52,0)),"")) | N27: =(1+INT($AC$23*((2)-(1)+1)/2147483647)) | AE27: =$AE$26+IF(AND(LEN($N$15)>0,INDEX('Tabelas'!$X$472:$X$578,18)&""=$N$15,LEN(INDEX('Tabelas'!$Y$472:$Y$578,18)&"")>0),1,0) | AG27: =$AV$64&"" | AH27: =$AW$64&"" | AI27: =$AY$64&"" | AJ27: =$BC$64&"" | AK27: =$AW$98&"" | AL27: =$AW$166&"" | AM27: =$AW$132&"" | AN27: =$BA$132&"" | AO27: =$AZ$166&"" | AP27: =$BA$64&"" | AT27: ='Tabelas'!$AE$375&""
A28: Dano por acerto | B28: =IF(LEN($N$35)=0,"",IFERROR(INDEX('Dados'!$J$38:$J$52,MATCH($N$35,'Dados'!$A$38:$A$52,0)),"")&" · média "&IFERROR(INDEX('Dados'!$K$38:$K$52,MATCH($N$35,'Dados'!$A$38:$A$52,0)),"")) | F28: Na Fila | G28: =IF(LEN($N$35)=0,"","VEL "&IFERROR(INDEX('Dados'!$H$38:$H$52,MATCH($N$35,'Dados'!$A$38:$A$52,0)),"")&", "&IFERROR(INDEX('Dados'!$P$38:$P$52,MATCH($N$35,'Dados'!$A$38:$A$52,0)),"")) | N28: =IF('Campanha'!$B$18=1,IF('Tabelas'!$D$9<=0,"",IFERROR(INDEX('Tabelas'!$Z$12:$Z$118,MATCH(IF('Tabelas'!$D$9<=0,0,INT($AC$22*'Tabelas'!$D$9/2147483647)+1),'Tabelas'!$P$12:$P$118,0))&"","")),IF('Campanha'!$B$18=2,IF('Tabelas'!$E$9<=0,"",IFERROR(INDEX('Tabelas'!$AA$12:$AA$118,MATCH(IF('Tabelas'!$E$9<=0,0,INT($AC$22*'Tabelas'!$E$9/2147483647)+1),'Tabelas'!$Q$12:$Q$118,0))&"","")),IF('Campanha'!$B$18=3,IF('Tabelas'!$F$9<=0,"",IFERROR(INDEX('Tabelas'!$AB$12:$AB$118,MATCH(IF('Tabelas'!$F$9<=0,0,INT($AC$22*'Tabelas'!$F$9/2147483647)+1),'Tabelas'!$R$12:$R$118,0))&"","")),IF('Campanha'!$B$18=4,IF('Tabelas'!$G$9<=0,"",IFERROR(INDEX('Tabelas'!$AC$12:$AC$118,MATCH(IF('Tabelas'!$G$9<=0,0,INT($AC$22*'Tabelas'!$G$9/2147483647)+1),'Tabelas'!$S$12:$S$118,0))&"","")),IF('Tabelas'!$H$9<=0,"",IFERROR(INDEX('Tabelas'!$AD$12:$AD$118,MATCH(IF('Tabelas'!$H$9<=0,0,INT($AC$22*'Tabelas'!$H$9/2147483647)+1),'Tabelas'!$T$12:$T$118,0))&"","")))))) | AE28: =$AE$27+IF(AND(LEN($N$15)>0,INDEX('Tabelas'!$X$472:$X$578,19)&""=$N$15,LEN(INDEX('Tabelas'!$Y$472:$Y$578,19)&"")>0),1,0) | AG28: =$AV$65&"" | AH28: =$AW$65&"" | AI28: =$AY$65&"" | AJ28: =$BC$65&"" | AK28: =$AW$99&"" | AL28: =$AW$167&"" | AM28: =$AW$133&"" | AN28: =$BA$133&"" | AO28: =$AZ$167&"" | AP28: =$BA$65&"" | AT28: ='Tabelas'!$AE$376&""
A29: =IF(LEN($N$35)=0,"Escolha a faixa do bloco (ou Do grupo) para ver os números.","NPC aliado também usa as âncoras de 28.3 (sem Esquiva, PH, Energia nem Ultimate, 28.2); Execução: ser racional pode Executar (23.5).") | N29: =IF('Tabelas'!$J$354<=0,"",IFERROR(INDEX('Tabelas'!$AF$357:$AF$463,MATCH(IF('Tabelas'!$J$354<=0,0,INT($AC$22*'Tabelas'!$J$354/2147483647)+1),'Tabelas'!$V$357:$V$463,0))&"","")) | AE29: =$AE$28+IF(AND(LEN($N$15)>0,INDEX('Tabelas'!$X$472:$X$578,20)&""=$N$15,LEN(INDEX('Tabelas'!$Y$472:$Y$578,20)&"")>0),1,0) | AG29: =$AV$66&"" | AH29: =$AW$66&"" | AI29: =$AY$66&"" | AJ29: =$BC$66&"" | AK29: =$AW$100&"" | AL29: =$AW$168&"" | AM29: =$AW$134&"" | AN29: =$BA$134&"" | AO29: =$AZ$168&"" | AP29: =$BA$66&"" | AT29: ='Tabelas'!$AE$377&""
A30: =IF(LEN($N$35)=0,"","Para levar ao combate: na aba Inimigos, crie uma linha com o nome "&$N$14&", tipo "&$N$34&" e faixa "&$N$33&" (modo Faixa do livro); ele entra nas listas de Encontros e Combate.") | N30: =IF($N$27=1,IF(LEN($N$28)>0,$N$28,$N$29),IF(LEN($N$29)>0,$N$29,$N$28)) | AE30: =$AE$29+IF(AND(LEN($N$15)>0,INDEX('Tabelas'!$X$472:$X$578,21)&""=$N$15,LEN(INDEX('Tabelas'!$Y$472:$Y$578,21)&"")>0),1,0) | AG30: =$AV$68&"" | AH30: =$AW$68&"" | AI30: =$AY$68&"" | AJ30: =$BC$68&"" | AK30: =$AW$102&"" | AL30: =$AW$170&"" | AM30: =$AW$136&"" | AN30: =$BA$136&"" | AO30: =$AZ$170&"" | AP30: =$BA$68&"" | AT30: ='Tabelas'!$AE$378&""
N31: =IF(COUNTIF('Dados'!$A$398:$A$404,$BA$7)>0,$BA$7,INDEX('Dados'!$A$398:$A$404,INT($AC$24*7/2147483647)+1)) | AE31: =$AE$30+IF(AND(LEN($N$15)>0,INDEX('Tabelas'!$X$472:$X$578,22)&""=$N$15,LEN(INDEX('Tabelas'!$Y$472:$Y$578,22)&"")>0),1,0) | AG31: =$AV$69&"" | AH31: =$AW$69&"" | AI31: =$AY$69&"" | AJ31: =$BC$69&"" | AK31: =$AW$103&"" | AL31: =$AW$171&"" | AM31: =$AW$137&"" | AN31: =$BA$137&"" | AO31: =$AZ$171&"" | AP31: =$BA$69&"" | AT31: ='Tabelas'!$AE$379&""
A32: Linha de saída: copie e cole como valores no Elenco (Colar especial → Somente valores) | AE32: =$AE$31+IF(AND(LEN($N$15)>0,INDEX('Tabelas'!$X$472:$X$578,23)&""=$N$15,LEN(INDEX('Tabelas'!$Y$472:$Y$578,23)&"")>0),1,0) | AG32: =$AV$70&"" | AH32: =$AW$70&"" | AI32: =$AY$70&"" | AJ32: =$BC$70&"" | AK32: =$AW$104&"" | AL32: =$AW$172&"" | AM32: =$AW$138&"" | AN32: =$BA$138&"" | AO32: =$AZ$172&"" | AP32: =$BA$70&"" | AT32: ='Tabelas'!$AE$380&""
A33: Nome completo | B33: Raça | D33: Caminho | F33: Papel | H33: Ocupação | N33: =IF($BC$7="Do grupo",'Campanha'!$B$19,IFERROR(INDEX('Dados'!$B$7:$B$11,MATCH($BC$7,'Dados'!$AP$6:$AP$10,0)),"")) | AE33: =$AE$32+IF(AND(LEN($N$15)>0,INDEX('Tabelas'!$X$472:$X$578,24)&""=$N$15,LEN(INDEX('Tabelas'!$Y$472:$Y$578,24)&"")>0),1,0) | AG33: =$AV$71&"" | AH33: =$AW$71&"" | AI33: =$AY$71&"" | AJ33: =$BC$71&"" | AK33: =$AW$105&"" | AL33: =$AW$173&"" | AM33: =$AW$139&"" | AN33: =$BA$139&"" | AO33: =$AZ$173&"" | AP33: =$BA$71&"" | AT33: ='Tabelas'!$AE$381&""
A34: =$N$14 | B34: =$N$10 | D34: =$N$15 | F34: =$N$31 | H34: =$N$16 | N34: =IF($BE$7="Elite","Elite","Comum") | AE34: =$AE$33+IF(AND(LEN($N$15)>0,INDEX('Tabelas'!$X$472:$X$578,25)&""=$N$15,LEN(INDEX('Tabelas'!$Y$472:$Y$578,25)&"")>0),1,0) | AG34: =$AV$72&"" | AH34: =$AW$72&"" | AI34: =$AY$72&"" | AJ34: =$BC$72&"" | AK34: =$AW$106&"" | AL34: =$AW$174&"" | AM34: =$AW$140&"" | AN34: =$BA$140&"" | AO34: =$AZ$174&"" | AP34: =$BA$72&"" | AT34: ='Tabelas'!$AE$382&""
A35: Parte 2 | B35: Aparência | F35: Personalidade | N35: =IF(LEN($N$33)=0,"",$N$33&"|"&$N$34) | AE35: =$AE$34+IF(AND(LEN($N$15)>0,INDEX('Tabelas'!$X$472:$X$578,26)&""=$N$15,LEN(INDEX('Tabelas'!$Y$472:$Y$578,26)&"")>0),1,0) | AG35: =$AV$73&"" | AH35: =$AW$73&"" | AI35: =$AY$73&"" | AJ35: =$BC$73&"" | AK35: =$AW$107&"" | AL35: =$AW$175&"" | AM35: =$AW$141&"" | AN35: =$BA$141&"" | AO35: =$AZ$175&"" | AP35: =$BA$73&"" | AT35: ='Tabelas'!$AE$383&""
A36: ="Parte 2 de 4" | B36: =$N$20 | F36: =$N$21 | AE36: =$AE$35+IF(AND(LEN($N$15)>0,INDEX('Tabelas'!$X$472:$X$578,27)&""=$N$15,LEN(INDEX('Tabelas'!$Y$472:$Y$578,27)&"")>0),1,0) | AG36: =$AV$74&"" | AH36: =$AW$74&"" | AI36: =$AY$74&"" | AJ36: =$BC$74&"" | AK36: =$AW$108&"" | AL36: =$AW$176&"" | AM36: =$AW$142&"" | AN36: =$BA$142&"" | AO36: =$AZ$176&"" | AP36: =$BA$74&"" | AT36: ='Tabelas'!$AE$385&""
A37: Parte 3 | B37: Motivação | F37: Segredo | AE37: =$AE$36 | AG37: =$AV$75&"" | AH37: =$AW$75&"" | AI37: =$AY$75&"" | AJ37: =$BC$75&"" | AK37: =$AW$109&"" | AL37: =$AW$177&"" | AM37: =$AW$143&"" | AN37: =$BA$143&"" | AO37: =$AZ$177&"" | AP37: =$BA$75&"" | AT37: ='Tabelas'!$AE$386&""
A38: ="Parte 3 de 4" | B38: =$N$23 | F38: =$N$24 | AE38: =$AE$37+IF(AND(LEN($N$15)>0,INDEX('Tabelas'!$X$472:$X$578,29)&""=$N$15,LEN(INDEX('Tabelas'!$Y$472:$Y$578,29)&"")>0),1,0) | AG38: =$AV$76&"" | AH38: =$AW$76&"" | AI38: =$AY$76&"" | AJ38: =$BC$76&"" | AK38: =$AW$110&"" | AL38: =$AW$178&"" | AM38: =$AW$144&"" | AN38: =$BA$144&"" | AO38: =$AZ$178&"" | AP38: =$BA$76&"" | AT38: ='Tabelas'!$AE$387&""
A39: Parte 4 | B39: Maneirismo e voz | E39: Atitude | G39: Gancho | AE39: =$AE$38+IF(AND(LEN($N$15)>0,INDEX('Tabelas'!$X$472:$X$578,30)&""=$N$15,LEN(INDEX('Tabelas'!$Y$472:$Y$578,30)&"")>0),1,0) | AG39: =$AV$77&"" | AH39: =$AW$77&"" | AI39: =$AY$77&"" | AJ39: =$BC$77&"" | AK39: =$AW$111&"" | AL39: =$AW$179&"" | AM39: =$AW$145&"" | AN39: =$BA$145&"" | AO39: =$AZ$179&"" | AP39: =$BA$77&"" | AT39: ='Tabelas'!$AE$388&""
A40: ="Parte 4 de 4" | B40: =$N$25 | E40: =$N$26 | G40: =$N$30 | AE40: =$AE$39+IF(AND(LEN($N$15)>0,INDEX('Tabelas'!$X$472:$X$578,31)&""=$N$15,LEN(INDEX('Tabelas'!$Y$472:$Y$578,31)&"")>0),1,0) | AT40: ='Tabelas'!$AE$389&""
A41: Parte 1: copie A:J e cole em A:J da linha do Elenco E1. Partes 2 a 4: B:J em E2, E3 e E4 (a mesma ordem de colunas, D6). Depois, preencha a relação e o registro (E5). | AE41: =$AE$40+IF(AND(LEN($N$15)>0,INDEX('Tabelas'!$X$472:$X$578,32)&""=$N$15,LEN(INDEX('Tabelas'!$Y$472:$Y$578,32)&"")>0),1,0) | AT41: ='Tabelas'!$AE$390&""
AE42: =$AE$41+IF(AND(LEN($N$15)>0,INDEX('Tabelas'!$X$472:$X$578,33)&""=$N$15,LEN(INDEX('Tabelas'!$Y$472:$Y$578,33)&"")>0),1,0) | AT42: ='Tabelas'!$AE$391&""
A43: Elenco da campanha (30 NPCs; preencha ou cole a linha de saída) | AE43: =$AE$42+IF(AND(LEN($N$15)>0,INDEX('Tabelas'!$X$472:$X$578,34)&""=$N$15,LEN(INDEX('Tabelas'!$Y$472:$Y$578,34)&"")>0),1,0) | AT43: ='Tabelas'!$AE$392&""
A44: E1 · Quem é | AE44: =$AE$43+IF(AND(LEN($N$15)>0,INDEX('Tabelas'!$X$472:$X$578,35)&""=$N$15,LEN(INDEX('Tabelas'!$Y$472:$Y$578,35)&"")>0),1,0) | AT44: ='Tabelas'!$AE$393&""
A45: Nome completo | B45: Raça | D45: Caminho | F45: Papel | H45: Ocupação | K45: Aviso | AE45: =$AE$44+IF(AND(LEN($N$15)>0,INDEX('Tabelas'!$X$472:$X$578,36)&""=$N$15,LEN(INDEX('Tabelas'!$Y$472:$Y$578,36)&"")>0),1,0) | AT45: ='Tabelas'!$AE$394&""
K46: =IF(BF46>0,"O Google leu como fórmula: escolha de novo ou digite com ' na frente.",IF(LEN($AV$46)=0,"",IF(COUNTIF($AG$10:$AG$39,$AV$46)>1,"Nome repetido no elenco",IF(COUNTIF('Dados'!$B$92:$B$123,$AV$46)>0,"Nome igual a uma criatura do Bestiário","")))) | AE46: =$AE$45+IF(AND(LEN($N$15)>0,INDEX('Tabelas'!$X$472:$X$578,37)&""=$N$15,LEN(INDEX('Tabelas'!$Y$472:$Y$578,37)&"")>0),1,0) | AT46: ='Tabelas'!$AE$395&"" | AV46: =IF(ISERROR($A$46),"",IF(ISBLANK($A$46),"",$A$46)) | AW46: =IF(ISERROR($B$46),"",IF(ISBLANK($B$46),"",$B$46)) | AY46: =IF(ISERROR($D$46),"",IF(ISBLANK($D$46),"",$D$46)) | BA46: =IF(ISERROR($F$46),"",IF(ISBLANK($F$46),"",$F$46)) | BC46: =IF(ISERROR($H$46),"",IF(ISBLANK($H$46),"",$H$46)) | BF46: =ISERROR($A$46)*1+ISERROR($B$46)*1+ISERROR($D$46)*1+ISERROR($F$46)*1+ISERROR($H$46)*1
K47: =IF(BF47>0,"O Google leu como fórmula: escolha de novo ou digite com ' na frente.",IF(LEN($AV$47)=0,"",IF(COUNTIF($AG$10:$AG$39,$AV$47)>1,"Nome repetido no elenco",IF(COUNTIF('Dados'!$B$92:$B$123,$AV$47)>0,"Nome igual a uma criatura do Bestiário","")))) | AE47: =$AE$46+IF(AND(LEN($N$15)>0,INDEX('Tabelas'!$X$472:$X$578,38)&""=$N$15,LEN(INDEX('Tabelas'!$Y$472:$Y$578,38)&"")>0),1,0) | AT47: ='Tabelas'!$AE$396&"" | AV47: =IF(ISERROR($A$47),"",IF(ISBLANK($A$47),"",$A$47)) | AW47: =IF(ISERROR($B$47),"",IF(ISBLANK($B$47),"",$B$47)) | AY47: =IF(ISERROR($D$47),"",IF(ISBLANK($D$47),"",$D$47)) | BA47: =IF(ISERROR($F$47),"",IF(ISBLANK($F$47),"",$F$47)) | BC47: =IF(ISERROR($H$47),"",IF(ISBLANK($H$47),"",$H$47)) | BF47: =ISERROR($A$47)*1+ISERROR($B$47)*1+ISERROR($D$47)*1+ISERROR($F$47)*1+ISERROR($H$47)*1
K48: =IF(BF48>0,"O Google leu como fórmula: escolha de novo ou digite com ' na frente.",IF(LEN($AV$48)=0,"",IF(COUNTIF($AG$10:$AG$39,$AV$48)>1,"Nome repetido no elenco",IF(COUNTIF('Dados'!$B$92:$B$123,$AV$48)>0,"Nome igual a uma criatura do Bestiário","")))) | AE48: =$AE$47+IF(AND(LEN($N$15)>0,INDEX('Tabelas'!$X$472:$X$578,39)&""=$N$15,LEN(INDEX('Tabelas'!$Y$472:$Y$578,39)&"")>0),1,0) | AT48: ='Tabelas'!$AE$397&"" | AV48: =IF(ISERROR($A$48),"",IF(ISBLANK($A$48),"",$A$48)) | AW48: =IF(ISERROR($B$48),"",IF(ISBLANK($B$48),"",$B$48)) | AY48: =IF(ISERROR($D$48),"",IF(ISBLANK($D$48),"",$D$48)) | BA48: =IF(ISERROR($F$48),"",IF(ISBLANK($F$48),"",$F$48)) | BC48: =IF(ISERROR($H$48),"",IF(ISBLANK($H$48),"",$H$48)) | BF48: =ISERROR($A$48)*1+ISERROR($B$48)*1+ISERROR($D$48)*1+ISERROR($F$48)*1+ISERROR($H$48)*1
K49: =IF(BF49>0,"O Google leu como fórmula: escolha de novo ou digite com ' na frente.",IF(LEN($AV$49)=0,"",IF(COUNTIF($AG$10:$AG$39,$AV$49)>1,"Nome repetido no elenco",IF(COUNTIF('Dados'!$B$92:$B$123,$AV$49)>0,"Nome igual a uma criatura do Bestiário","")))) | AE49: =$AE$48+IF(AND(LEN($N$15)>0,INDEX('Tabelas'!$X$472:$X$578,40)&""=$N$15,LEN(INDEX('Tabelas'!$Y$472:$Y$578,40)&"")>0),1,0) | AT49: ='Tabelas'!$AE$399&"" | AV49: =IF(ISERROR($A$49),"",IF(ISBLANK($A$49),"",$A$49)) | AW49: =IF(ISERROR($B$49),"",IF(ISBLANK($B$49),"",$B$49)) | AY49: =IF(ISERROR($D$49),"",IF(ISBLANK($D$49),"",$D$49)) | BA49: =IF(ISERROR($F$49),"",IF(ISBLANK($F$49),"",$F$49)) | BC49: =IF(ISERROR($H$49),"",IF(ISBLANK($H$49),"",$H$49)) | BF49: =ISERROR($A$49)*1+ISERROR($B$49)*1+ISERROR($D$49)*1+ISERROR($F$49)*1+ISERROR($H$49)*1
K50: =IF(BF50>0,"O Google leu como fórmula: escolha de novo ou digite com ' na frente.",IF(LEN($AV$50)=0,"",IF(COUNTIF($AG$10:$AG$39,$AV$50)>1,"Nome repetido no elenco",IF(COUNTIF('Dados'!$B$92:$B$123,$AV$50)>0,"Nome igual a uma criatura do Bestiário","")))) | AE50: =$AE$49+IF(AND(LEN($N$15)>0,INDEX('Tabelas'!$X$472:$X$578,41)&""=$N$15,LEN(INDEX('Tabelas'!$Y$472:$Y$578,41)&"")>0),1,0) | AT50: ='Tabelas'!$AE$400&"" | AV50: =IF(ISERROR($A$50),"",IF(ISBLANK($A$50),"",$A$50)) | AW50: =IF(ISERROR($B$50),"",IF(ISBLANK($B$50),"",$B$50)) | AY50: =IF(ISERROR($D$50),"",IF(ISBLANK($D$50),"",$D$50)) | BA50: =IF(ISERROR($F$50),"",IF(ISBLANK($F$50),"",$F$50)) | BC50: =IF(ISERROR($H$50),"",IF(ISBLANK($H$50),"",$H$50)) | BF50: =ISERROR($A$50)*1+ISERROR($B$50)*1+ISERROR($D$50)*1+ISERROR($F$50)*1+ISERROR($H$50)*1
K51: =IF(BF51>0,"O Google leu como fórmula: escolha de novo ou digite com ' na frente.",IF(LEN($AV$51)=0,"",IF(COUNTIF($AG$10:$AG$39,$AV$51)>1,"Nome repetido no elenco",IF(COUNTIF('Dados'!$B$92:$B$123,$AV$51)>0,"Nome igual a uma criatura do Bestiário","")))) | AE51: =$AE$50 | AT51: ='Tabelas'!$AE$401&"" | AV51: =IF(ISERROR($A$51),"",IF(ISBLANK($A$51),"",$A$51)) | AW51: =IF(ISERROR($B$51),"",IF(ISBLANK($B$51),"",$B$51)) | AY51: =IF(ISERROR($D$51),"",IF(ISBLANK($D$51),"",$D$51)) | BA51: =IF(ISERROR($F$51),"",IF(ISBLANK($F$51),"",$F$51)) | BC51: =IF(ISERROR($H$51),"",IF(ISBLANK($H$51),"",$H$51)) | BF51: =ISERROR($A$51)*1+ISERROR($B$51)*1+ISERROR($D$51)*1+ISERROR($F$51)*1+ISERROR($H$51)*1
K52: =IF(BF52>0,"O Google leu como fórmula: escolha de novo ou digite com ' na frente.",IF(LEN($AV$52)=0,"",IF(COUNTIF($AG$10:$AG$39,$AV$52)>1,"Nome repetido no elenco",IF(COUNTIF('Dados'!$B$92:$B$123,$AV$52)>0,"Nome igual a uma criatura do Bestiário","")))) | AE52: =$AE$51+IF(AND(LEN($N$15)>0,INDEX('Tabelas'!$X$472:$X$578,43)&""=$N$15,LEN(INDEX('Tabelas'!$Y$472:$Y$578,43)&"")>0),1,0) | AT52: ='Tabelas'!$AE$402&"" | AV52: =IF(ISERROR($A$52),"",IF(ISBLANK($A$52),"",$A$52)) | AW52: =IF(ISERROR($B$52),"",IF(ISBLANK($B$52),"",$B$52)) | AY52: =IF(ISERROR($D$52),"",IF(ISBLANK($D$52),"",$D$52)) | BA52: =IF(ISERROR($F$52),"",IF(ISBLANK($F$52),"",$F$52)) | BC52: =IF(ISERROR($H$52),"",IF(ISBLANK($H$52),"",$H$52)) | BF52: =ISERROR($A$52)*1+ISERROR($B$52)*1+ISERROR($D$52)*1+ISERROR($F$52)*1+ISERROR($H$52)*1
K53: =IF(BF53>0,"O Google leu como fórmula: escolha de novo ou digite com ' na frente.",IF(LEN($AV$53)=0,"",IF(COUNTIF($AG$10:$AG$39,$AV$53)>1,"Nome repetido no elenco",IF(COUNTIF('Dados'!$B$92:$B$123,$AV$53)>0,"Nome igual a uma criatura do Bestiário","")))) | AE53: =$AE$52+IF(AND(LEN($N$15)>0,INDEX('Tabelas'!$X$472:$X$578,44)&""=$N$15,LEN(INDEX('Tabelas'!$Y$472:$Y$578,44)&"")>0),1,0) | AT53: ='Tabelas'!$AE$403&"" | AV53: =IF(ISERROR($A$53),"",IF(ISBLANK($A$53),"",$A$53)) | AW53: =IF(ISERROR($B$53),"",IF(ISBLANK($B$53),"",$B$53)) | AY53: =IF(ISERROR($D$53),"",IF(ISBLANK($D$53),"",$D$53)) | BA53: =IF(ISERROR($F$53),"",IF(ISBLANK($F$53),"",$F$53)) | BC53: =IF(ISERROR($H$53),"",IF(ISBLANK($H$53),"",$H$53)) | BF53: =ISERROR($A$53)*1+ISERROR($B$53)*1+ISERROR($D$53)*1+ISERROR($F$53)*1+ISERROR($H$53)*1
K54: =IF(BF54>0,"O Google leu como fórmula: escolha de novo ou digite com ' na frente.",IF(LEN($AV$54)=0,"",IF(COUNTIF($AG$10:$AG$39,$AV$54)>1,"Nome repetido no elenco",IF(COUNTIF('Dados'!$B$92:$B$123,$AV$54)>0,"Nome igual a uma criatura do Bestiário","")))) | AE54: =$AE$53+IF(AND(LEN($N$15)>0,INDEX('Tabelas'!$X$472:$X$578,45)&""=$N$15,LEN(INDEX('Tabelas'!$Y$472:$Y$578,45)&"")>0),1,0) | AT54: ='Tabelas'!$AE$404&"" | AV54: =IF(ISERROR($A$54),"",IF(ISBLANK($A$54),"",$A$54)) | AW54: =IF(ISERROR($B$54),"",IF(ISBLANK($B$54),"",$B$54)) | AY54: =IF(ISERROR($D$54),"",IF(ISBLANK($D$54),"",$D$54)) | BA54: =IF(ISERROR($F$54),"",IF(ISBLANK($F$54),"",$F$54)) | BC54: =IF(ISERROR($H$54),"",IF(ISBLANK($H$54),"",$H$54)) | BF54: =ISERROR($A$54)*1+ISERROR($B$54)*1+ISERROR($D$54)*1+ISERROR($F$54)*1+ISERROR($H$54)*1
K55: =IF(BF55>0,"O Google leu como fórmula: escolha de novo ou digite com ' na frente.",IF(LEN($AV$55)=0,"",IF(COUNTIF($AG$10:$AG$39,$AV$55)>1,"Nome repetido no elenco",IF(COUNTIF('Dados'!$B$92:$B$123,$AV$55)>0,"Nome igual a uma criatura do Bestiário","")))) | AE55: =$AE$54+IF(AND(LEN($N$15)>0,INDEX('Tabelas'!$X$472:$X$578,46)&""=$N$15,LEN(INDEX('Tabelas'!$Y$472:$Y$578,46)&"")>0),1,0) | AT55: ='Tabelas'!$AE$405&"" | AV55: =IF(ISERROR($A$55),"",IF(ISBLANK($A$55),"",$A$55)) | AW55: =IF(ISERROR($B$55),"",IF(ISBLANK($B$55),"",$B$55)) | AY55: =IF(ISERROR($D$55),"",IF(ISBLANK($D$55),"",$D$55)) | BA55: =IF(ISERROR($F$55),"",IF(ISBLANK($F$55),"",$F$55)) | BC55: =IF(ISERROR($H$55),"",IF(ISBLANK($H$55),"",$H$55)) | BF55: =ISERROR($A$55)*1+ISERROR($B$55)*1+ISERROR($D$55)*1+ISERROR($F$55)*1+ISERROR($H$55)*1
A56: Nome completo | B56: Raça | D56: Caminho | F56: Papel | H56: Ocupação | K56: Aviso | AE56: =$AE$55+IF(AND(LEN($N$15)>0,INDEX('Tabelas'!$X$472:$X$578,47)&""=$N$15,LEN(INDEX('Tabelas'!$Y$472:$Y$578,47)&"")>0),1,0) | AT56: ='Tabelas'!$AE$406&""
K57: =IF(BF57>0,"O Google leu como fórmula: escolha de novo ou digite com ' na frente.",IF(LEN($AV$57)=0,"",IF(COUNTIF($AG$10:$AG$39,$AV$57)>1,"Nome repetido no elenco",IF(COUNTIF('Dados'!$B$92:$B$123,$AV$57)>0,"Nome igual a uma criatura do Bestiário","")))) | AE57: =$AE$56+IF(AND(LEN($N$15)>0,INDEX('Tabelas'!$X$472:$X$578,48)&""=$N$15,LEN(INDEX('Tabelas'!$Y$472:$Y$578,48)&"")>0),1,0) | AT57: ='Tabelas'!$AE$407&"" | AV57: =IF(ISERROR($A$57),"",IF(ISBLANK($A$57),"",$A$57)) | AW57: =IF(ISERROR($B$57),"",IF(ISBLANK($B$57),"",$B$57)) | AY57: =IF(ISERROR($D$57),"",IF(ISBLANK($D$57),"",$D$57)) | BA57: =IF(ISERROR($F$57),"",IF(ISBLANK($F$57),"",$F$57)) | BC57: =IF(ISERROR($H$57),"",IF(ISBLANK($H$57),"",$H$57)) | BF57: =ISERROR($A$57)*1+ISERROR($B$57)*1+ISERROR($D$57)*1+ISERROR($F$57)*1+ISERROR($H$57)*1
K58: =IF(BF58>0,"O Google leu como fórmula: escolha de novo ou digite com ' na frente.",IF(LEN($AV$58)=0,"",IF(COUNTIF($AG$10:$AG$39,$AV$58)>1,"Nome repetido no elenco",IF(COUNTIF('Dados'!$B$92:$B$123,$AV$58)>0,"Nome igual a uma criatura do Bestiário","")))) | AE58: =$AE$57+IF(AND(LEN($N$15)>0,INDEX('Tabelas'!$X$472:$X$578,49)&""=$N$15,LEN(INDEX('Tabelas'!$Y$472:$Y$578,49)&"")>0),1,0) | AT58: ='Tabelas'!$AE$408&"" | AV58: =IF(ISERROR($A$58),"",IF(ISBLANK($A$58),"",$A$58)) | AW58: =IF(ISERROR($B$58),"",IF(ISBLANK($B$58),"",$B$58)) | AY58: =IF(ISERROR($D$58),"",IF(ISBLANK($D$58),"",$D$58)) | BA58: =IF(ISERROR($F$58),"",IF(ISBLANK($F$58),"",$F$58)) | BC58: =IF(ISERROR($H$58),"",IF(ISBLANK($H$58),"",$H$58)) | BF58: =ISERROR($A$58)*1+ISERROR($B$58)*1+ISERROR($D$58)*1+ISERROR($F$58)*1+ISERROR($H$58)*1
K59: =IF(BF59>0,"O Google leu como fórmula: escolha de novo ou digite com ' na frente.",IF(LEN($AV$59)=0,"",IF(COUNTIF($AG$10:$AG$39,$AV$59)>1,"Nome repetido no elenco",IF(COUNTIF('Dados'!$B$92:$B$123,$AV$59)>0,"Nome igual a uma criatura do Bestiário","")))) | AE59: =$AE$58+IF(AND(LEN($N$15)>0,INDEX('Tabelas'!$X$472:$X$578,50)&""=$N$15,LEN(INDEX('Tabelas'!$Y$472:$Y$578,50)&"")>0),1,0) | AT59: ='Tabelas'!$AE$409&"" | AV59: =IF(ISERROR($A$59),"",IF(ISBLANK($A$59),"",$A$59)) | AW59: =IF(ISERROR($B$59),"",IF(ISBLANK($B$59),"",$B$59)) | AY59: =IF(ISERROR($D$59),"",IF(ISBLANK($D$59),"",$D$59)) | BA59: =IF(ISERROR($F$59),"",IF(ISBLANK($F$59),"",$F$59)) | BC59: =IF(ISERROR($H$59),"",IF(ISBLANK($H$59),"",$H$59)) | BF59: =ISERROR($A$59)*1+ISERROR($B$59)*1+ISERROR($D$59)*1+ISERROR($F$59)*1+ISERROR($H$59)*1
K60: =IF(BF60>0,"O Google leu como fórmula: escolha de novo ou digite com ' na frente.",IF(LEN($AV$60)=0,"",IF(COUNTIF($AG$10:$AG$39,$AV$60)>1,"Nome repetido no elenco",IF(COUNTIF('Dados'!$B$92:$B$123,$AV$60)>0,"Nome igual a uma criatura do Bestiário","")))) | AE60: =$AE$59+IF(AND(LEN($N$15)>0,INDEX('Tabelas'!$X$472:$X$578,51)&""=$N$15,LEN(INDEX('Tabelas'!$Y$472:$Y$578,51)&"")>0),1,0) | AT60: ='Tabelas'!$AE$410&"" | AV60: =IF(ISERROR($A$60),"",IF(ISBLANK($A$60),"",$A$60)) | AW60: =IF(ISERROR($B$60),"",IF(ISBLANK($B$60),"",$B$60)) | AY60: =IF(ISERROR($D$60),"",IF(ISBLANK($D$60),"",$D$60)) | BA60: =IF(ISERROR($F$60),"",IF(ISBLANK($F$60),"",$F$60)) | BC60: =IF(ISERROR($H$60),"",IF(ISBLANK($H$60),"",$H$60)) | BF60: =ISERROR($A$60)*1+ISERROR($B$60)*1+ISERROR($D$60)*1+ISERROR($F$60)*1+ISERROR($H$60)*1
K61: =IF(BF61>0,"O Google leu como fórmula: escolha de novo ou digite com ' na frente.",IF(LEN($AV$61)=0,"",IF(COUNTIF($AG$10:$AG$39,$AV$61)>1,"Nome repetido no elenco",IF(COUNTIF('Dados'!$B$92:$B$123,$AV$61)>0,"Nome igual a uma criatura do Bestiário","")))) | AE61: =$AE$60+IF(AND(LEN($N$15)>0,INDEX('Tabelas'!$X$472:$X$578,52)&""=$N$15,LEN(INDEX('Tabelas'!$Y$472:$Y$578,52)&"")>0),1,0) | AT61: ='Tabelas'!$AE$411&"" | AV61: =IF(ISERROR($A$61),"",IF(ISBLANK($A$61),"",$A$61)) | AW61: =IF(ISERROR($B$61),"",IF(ISBLANK($B$61),"",$B$61)) | AY61: =IF(ISERROR($D$61),"",IF(ISBLANK($D$61),"",$D$61)) | BA61: =IF(ISERROR($F$61),"",IF(ISBLANK($F$61),"",$F$61)) | BC61: =IF(ISERROR($H$61),"",IF(ISBLANK($H$61),"",$H$61)) | BF61: =ISERROR($A$61)*1+ISERROR($B$61)*1+ISERROR($D$61)*1+ISERROR($F$61)*1+ISERROR($H$61)*1
K62: =IF(BF62>0,"O Google leu como fórmula: escolha de novo ou digite com ' na frente.",IF(LEN($AV$62)=0,"",IF(COUNTIF($AG$10:$AG$39,$AV$62)>1,"Nome repetido no elenco",IF(COUNTIF('Dados'!$B$92:$B$123,$AV$62)>0,"Nome igual a uma criatura do Bestiário","")))) | AE62: =$AE$61+IF(AND(LEN($N$15)>0,INDEX('Tabelas'!$X$472:$X$578,53)&""=$N$15,LEN(INDEX('Tabelas'!$Y$472:$Y$578,53)&"")>0),1,0) | AT62: ='Tabelas'!$AE$413&"" | AV62: =IF(ISERROR($A$62),"",IF(ISBLANK($A$62),"",$A$62)) | AW62: =IF(ISERROR($B$62),"",IF(ISBLANK($B$62),"",$B$62)) | AY62: =IF(ISERROR($D$62),"",IF(ISBLANK($D$62),"",$D$62)) | BA62: =IF(ISERROR($F$62),"",IF(ISBLANK($F$62),"",$F$62)) | BC62: =IF(ISERROR($H$62),"",IF(ISBLANK($H$62),"",$H$62)) | BF62: =ISERROR($A$62)*1+ISERROR($B$62)*1+ISERROR($D$62)*1+ISERROR($F$62)*1+ISERROR($H$62)*1
K63: =IF(BF63>0,"O Google leu como fórmula: escolha de novo ou digite com ' na frente.",IF(LEN($AV$63)=0,"",IF(COUNTIF($AG$10:$AG$39,$AV$63)>1,"Nome repetido no elenco",IF(COUNTIF('Dados'!$B$92:$B$123,$AV$63)>0,"Nome igual a uma criatura do Bestiário","")))) | AE63: =$AE$62+IF(AND(LEN($N$15)>0,INDEX('Tabelas'!$X$472:$X$578,54)&""=$N$15,LEN(INDEX('Tabelas'!$Y$472:$Y$578,54)&"")>0),1,0) | AT63: ='Tabelas'!$AE$414&"" | AV63: =IF(ISERROR($A$63),"",IF(ISBLANK($A$63),"",$A$63)) | AW63: =IF(ISERROR($B$63),"",IF(ISBLANK($B$63),"",$B$63)) | AY63: =IF(ISERROR($D$63),"",IF(ISBLANK($D$63),"",$D$63)) | BA63: =IF(ISERROR($F$63),"",IF(ISBLANK($F$63),"",$F$63)) | BC63: =IF(ISERROR($H$63),"",IF(ISBLANK($H$63),"",$H$63)) | BF63: =ISERROR($A$63)*1+ISERROR($B$63)*1+ISERROR($D$63)*1+ISERROR($F$63)*1+ISERROR($H$63)*1
K64: =IF(BF64>0,"O Google leu como fórmula: escolha de novo ou digite com ' na frente.",IF(LEN($AV$64)=0,"",IF(COUNTIF($AG$10:$AG$39,$AV$64)>1,"Nome repetido no elenco",IF(COUNTIF('Dados'!$B$92:$B$123,$AV$64)>0,"Nome igual a uma criatura do Bestiário","")))) | AE64: =$AE$63+IF(AND(LEN($N$15)>0,INDEX('Tabelas'!$X$472:$X$578,55)&""=$N$15,LEN(INDEX('Tabelas'!$Y$472:$Y$578,55)&"")>0),1,0) | AT64: ='Tabelas'!$AE$415&"" | AV64: =IF(ISERROR($A$64),"",IF(ISBLANK($A$64),"",$A$64)) | AW64: =IF(ISERROR($B$64),"",IF(ISBLANK($B$64),"",$B$64)) | AY64: =IF(ISERROR($D$64),"",IF(ISBLANK($D$64),"",$D$64)) | BA64: =IF(ISERROR($F$64),"",IF(ISBLANK($F$64),"",$F$64)) | BC64: =IF(ISERROR($H$64),"",IF(ISBLANK($H$64),"",$H$64)) | BF64: =ISERROR($A$64)*1+ISERROR($B$64)*1+ISERROR($D$64)*1+ISERROR($F$64)*1+ISERROR($H$64)*1
K65: =IF(BF65>0,"O Google leu como fórmula: escolha de novo ou digite com ' na frente.",IF(LEN($AV$65)=0,"",IF(COUNTIF($AG$10:$AG$39,$AV$65)>1,"Nome repetido no elenco",IF(COUNTIF('Dados'!$B$92:$B$123,$AV$65)>0,"Nome igual a uma criatura do Bestiário","")))) | AE65: =$AE$64 | AT65: ='Tabelas'!$AE$416&"" | AV65: =IF(ISERROR($A$65),"",IF(ISBLANK($A$65),"",$A$65)) | AW65: =IF(ISERROR($B$65),"",IF(ISBLANK($B$65),"",$B$65)) | AY65: =IF(ISERROR($D$65),"",IF(ISBLANK($D$65),"",$D$65)) | BA65: =IF(ISERROR($F$65),"",IF(ISBLANK($F$65),"",$F$65)) | BC65: =IF(ISERROR($H$65),"",IF(ISBLANK($H$65),"",$H$65)) | BF65: =ISERROR($A$65)*1+ISERROR($B$65)*1+ISERROR($D$65)*1+ISERROR($F$65)*1+ISERROR($H$65)*1
K66: =IF(BF66>0,"O Google leu como fórmula: escolha de novo ou digite com ' na frente.",IF(LEN($AV$66)=0,"",IF(COUNTIF($AG$10:$AG$39,$AV$66)>1,"Nome repetido no elenco",IF(COUNTIF('Dados'!$B$92:$B$123,$AV$66)>0,"Nome igual a uma criatura do Bestiário","")))) | AE66: =$AE$65+IF(AND(LEN($N$15)>0,INDEX('Tabelas'!$X$472:$X$578,57)&""=$N$15,LEN(INDEX('Tabelas'!$Y$472:$Y$578,57)&"")>0),1,0) | AT66: ='Tabelas'!$AE$417&"" | AV66: =IF(ISERROR($A$66),"",IF(ISBLANK($A$66),"",$A$66)) | AW66: =IF(ISERROR($B$66),"",IF(ISBLANK($B$66),"",$B$66)) | AY66: =IF(ISERROR($D$66),"",IF(ISBLANK($D$66),"",$D$66)) | BA66: =IF(ISERROR($F$66),"",IF(ISBLANK($F$66),"",$F$66)) | BC66: =IF(ISERROR($H$66),"",IF(ISBLANK($H$66),"",$H$66)) | BF66: =ISERROR($A$66)*1+ISERROR($B$66)*1+ISERROR($D$66)*1+ISERROR($F$66)*1+ISERROR($H$66)*1
A67: Nome completo | B67: Raça | D67: Caminho | F67: Papel | H67: Ocupação | K67: Aviso | AE67: =$AE$66+IF(AND(LEN($N$15)>0,INDEX('Tabelas'!$X$472:$X$578,58)&""=$N$15,LEN(INDEX('Tabelas'!$Y$472:$Y$578,58)&"")>0),1,0) | AT67: ='Tabelas'!$AE$418&""
K68: =IF(BF68>0,"O Google leu como fórmula: escolha de novo ou digite com ' na frente.",IF(LEN($AV$68)=0,"",IF(COUNTIF($AG$10:$AG$39,$AV$68)>1,"Nome repetido no elenco",IF(COUNTIF('Dados'!$B$92:$B$123,$AV$68)>0,"Nome igual a uma criatura do Bestiário","")))) | AE68: =$AE$67+IF(AND(LEN($N$15)>0,INDEX('Tabelas'!$X$472:$X$578,59)&""=$N$15,LEN(INDEX('Tabelas'!$Y$472:$Y$578,59)&"")>0),1,0) | AT68: ='Tabelas'!$AE$419&"" | AV68: =IF(ISERROR($A$68),"",IF(ISBLANK($A$68),"",$A$68)) | AW68: =IF(ISERROR($B$68),"",IF(ISBLANK($B$68),"",$B$68)) | AY68: =IF(ISERROR($D$68),"",IF(ISBLANK($D$68),"",$D$68)) | BA68: =IF(ISERROR($F$68),"",IF(ISBLANK($F$68),"",$F$68)) | BC68: =IF(ISERROR($H$68),"",IF(ISBLANK($H$68),"",$H$68)) | BF68: =ISERROR($A$68)*1+ISERROR($B$68)*1+ISERROR($D$68)*1+ISERROR($F$68)*1+ISERROR($H$68)*1
K69: =IF(BF69>0,"O Google leu como fórmula: escolha de novo ou digite com ' na frente.",IF(LEN($AV$69)=0,"",IF(COUNTIF($AG$10:$AG$39,$AV$69)>1,"Nome repetido no elenco",IF(COUNTIF('Dados'!$B$92:$B$123,$AV$69)>0,"Nome igual a uma criatura do Bestiário","")))) | AE69: =$AE$68+IF(AND(LEN($N$15)>0,INDEX('Tabelas'!$X$472:$X$578,60)&""=$N$15,LEN(INDEX('Tabelas'!$Y$472:$Y$578,60)&"")>0),1,0) | AT69: ='Tabelas'!$AE$420&"" | AV69: =IF(ISERROR($A$69),"",IF(ISBLANK($A$69),"",$A$69)) | AW69: =IF(ISERROR($B$69),"",IF(ISBLANK($B$69),"",$B$69)) | AY69: =IF(ISERROR($D$69),"",IF(ISBLANK($D$69),"",$D$69)) | BA69: =IF(ISERROR($F$69),"",IF(ISBLANK($F$69),"",$F$69)) | BC69: =IF(ISERROR($H$69),"",IF(ISBLANK($H$69),"",$H$69)) | BF69: =ISERROR($A$69)*1+ISERROR($B$69)*1+ISERROR($D$69)*1+ISERROR($F$69)*1+ISERROR($H$69)*1
K70: =IF(BF70>0,"O Google leu como fórmula: escolha de novo ou digite com ' na frente.",IF(LEN($AV$70)=0,"",IF(COUNTIF($AG$10:$AG$39,$AV$70)>1,"Nome repetido no elenco",IF(COUNTIF('Dados'!$B$92:$B$123,$AV$70)>0,"Nome igual a uma criatura do Bestiário","")))) | AE70: =$AE$69+IF(AND(LEN($N$15)>0,INDEX('Tabelas'!$X$472:$X$578,61)&""=$N$15,LEN(INDEX('Tabelas'!$Y$472:$Y$578,61)&"")>0),1,0) | AT70: ='Tabelas'!$AE$421&"" | AV70: =IF(ISERROR($A$70),"",IF(ISBLANK($A$70),"",$A$70)) | AW70: =IF(ISERROR($B$70),"",IF(ISBLANK($B$70),"",$B$70)) | AY70: =IF(ISERROR($D$70),"",IF(ISBLANK($D$70),"",$D$70)) | BA70: =IF(ISERROR($F$70),"",IF(ISBLANK($F$70),"",$F$70)) | BC70: =IF(ISERROR($H$70),"",IF(ISBLANK($H$70),"",$H$70)) | BF70: =ISERROR($A$70)*1+ISERROR($B$70)*1+ISERROR($D$70)*1+ISERROR($F$70)*1+ISERROR($H$70)*1
K71: =IF(BF71>0,"O Google leu como fórmula: escolha de novo ou digite com ' na frente.",IF(LEN($AV$71)=0,"",IF(COUNTIF($AG$10:$AG$39,$AV$71)>1,"Nome repetido no elenco",IF(COUNTIF('Dados'!$B$92:$B$123,$AV$71)>0,"Nome igual a uma criatura do Bestiário","")))) | AE71: =$AE$70+IF(AND(LEN($N$15)>0,INDEX('Tabelas'!$X$472:$X$578,62)&""=$N$15,LEN(INDEX('Tabelas'!$Y$472:$Y$578,62)&"")>0),1,0) | AT71: ='Tabelas'!$AE$422&"" | AV71: =IF(ISERROR($A$71),"",IF(ISBLANK($A$71),"",$A$71)) | AW71: =IF(ISERROR($B$71),"",IF(ISBLANK($B$71),"",$B$71)) | AY71: =IF(ISERROR($D$71),"",IF(ISBLANK($D$71),"",$D$71)) | BA71: =IF(ISERROR($F$71),"",IF(ISBLANK($F$71),"",$F$71)) | BC71: =IF(ISERROR($H$71),"",IF(ISBLANK($H$71),"",$H$71)) | BF71: =ISERROR($A$71)*1+ISERROR($B$71)*1+ISERROR($D$71)*1+ISERROR($F$71)*1+ISERROR($H$71)*1
K72: =IF(BF72>0,"O Google leu como fórmula: escolha de novo ou digite com ' na frente.",IF(LEN($AV$72)=0,"",IF(COUNTIF($AG$10:$AG$39,$AV$72)>1,"Nome repetido no elenco",IF(COUNTIF('Dados'!$B$92:$B$123,$AV$72)>0,"Nome igual a uma criatura do Bestiário","")))) | AE72: =$AE$71+IF(AND(LEN($N$15)>0,INDEX('Tabelas'!$X$472:$X$578,63)&""=$N$15,LEN(INDEX('Tabelas'!$Y$472:$Y$578,63)&"")>0),1,0) | AT72: ='Tabelas'!$AE$423&"" | AV72: =IF(ISERROR($A$72),"",IF(ISBLANK($A$72),"",$A$72)) | AW72: =IF(ISERROR($B$72),"",IF(ISBLANK($B$72),"",$B$72)) | AY72: =IF(ISERROR($D$72),"",IF(ISBLANK($D$72),"",$D$72)) | BA72: =IF(ISERROR($F$72),"",IF(ISBLANK($F$72),"",$F$72)) | BC72: =IF(ISERROR($H$72),"",IF(ISBLANK($H$72),"",$H$72)) | BF72: =ISERROR($A$72)*1+ISERROR($B$72)*1+ISERROR($D$72)*1+ISERROR($F$72)*1+ISERROR($H$72)*1
K73: =IF(BF73>0,"O Google leu como fórmula: escolha de novo ou digite com ' na frente.",IF(LEN($AV$73)=0,"",IF(COUNTIF($AG$10:$AG$39,$AV$73)>1,"Nome repetido no elenco",IF(COUNTIF('Dados'!$B$92:$B$123,$AV$73)>0,"Nome igual a uma criatura do Bestiário","")))) | AE73: =$AE$72+IF(AND(LEN($N$15)>0,INDEX('Tabelas'!$X$472:$X$578,64)&""=$N$15,LEN(INDEX('Tabelas'!$Y$472:$Y$578,64)&"")>0),1,0) | AT73: ='Tabelas'!$AE$424&"" | AV73: =IF(ISERROR($A$73),"",IF(ISBLANK($A$73),"",$A$73)) | AW73: =IF(ISERROR($B$73),"",IF(ISBLANK($B$73),"",$B$73)) | AY73: =IF(ISERROR($D$73),"",IF(ISBLANK($D$73),"",$D$73)) | BA73: =IF(ISERROR($F$73),"",IF(ISBLANK($F$73),"",$F$73)) | BC73: =IF(ISERROR($H$73),"",IF(ISBLANK($H$73),"",$H$73)) | BF73: =ISERROR($A$73)*1+ISERROR($B$73)*1+ISERROR($D$73)*1+ISERROR($F$73)*1+ISERROR($H$73)*1
K74: =IF(BF74>0,"O Google leu como fórmula: escolha de novo ou digite com ' na frente.",IF(LEN($AV$74)=0,"",IF(COUNTIF($AG$10:$AG$39,$AV$74)>1,"Nome repetido no elenco",IF(COUNTIF('Dados'!$B$92:$B$123,$AV$74)>0,"Nome igual a uma criatura do Bestiário","")))) | AE74: =$AE$73+IF(AND(LEN($N$15)>0,INDEX('Tabelas'!$X$472:$X$578,65)&""=$N$15,LEN(INDEX('Tabelas'!$Y$472:$Y$578,65)&"")>0),1,0) | AT74: ='Tabelas'!$AE$425&"" | AV74: =IF(ISERROR($A$74),"",IF(ISBLANK($A$74),"",$A$74)) | AW74: =IF(ISERROR($B$74),"",IF(ISBLANK($B$74),"",$B$74)) | AY74: =IF(ISERROR($D$74),"",IF(ISBLANK($D$74),"",$D$74)) | BA74: =IF(ISERROR($F$74),"",IF(ISBLANK($F$74),"",$F$74)) | BC74: =IF(ISERROR($H$74),"",IF(ISBLANK($H$74),"",$H$74)) | BF74: =ISERROR($A$74)*1+ISERROR($B$74)*1+ISERROR($D$74)*1+ISERROR($F$74)*1+ISERROR($H$74)*1
K75: =IF(BF75>0,"O Google leu como fórmula: escolha de novo ou digite com ' na frente.",IF(LEN($AV$75)=0,"",IF(COUNTIF($AG$10:$AG$39,$AV$75)>1,"Nome repetido no elenco",IF(COUNTIF('Dados'!$B$92:$B$123,$AV$75)>0,"Nome igual a uma criatura do Bestiário","")))) | AE75: =$AE$74+IF(AND(LEN($N$15)>0,INDEX('Tabelas'!$X$472:$X$578,66)&""=$N$15,LEN(INDEX('Tabelas'!$Y$472:$Y$578,66)&"")>0),1,0) | AT75: ='Tabelas'!$AE$427&"" | AV75: =IF(ISERROR($A$75),"",IF(ISBLANK($A$75),"",$A$75)) | AW75: =IF(ISERROR($B$75),"",IF(ISBLANK($B$75),"",$B$75)) | AY75: =IF(ISERROR($D$75),"",IF(ISBLANK($D$75),"",$D$75)) | BA75: =IF(ISERROR($F$75),"",IF(ISBLANK($F$75),"",$F$75)) | BC75: =IF(ISERROR($H$75),"",IF(ISBLANK($H$75),"",$H$75)) | BF75: =ISERROR($A$75)*1+ISERROR($B$75)*1+ISERROR($D$75)*1+ISERROR($F$75)*1+ISERROR($H$75)*1
K76: =IF(BF76>0,"O Google leu como fórmula: escolha de novo ou digite com ' na frente.",IF(LEN($AV$76)=0,"",IF(COUNTIF($AG$10:$AG$39,$AV$76)>1,"Nome repetido no elenco",IF(COUNTIF('Dados'!$B$92:$B$123,$AV$76)>0,"Nome igual a uma criatura do Bestiário","")))) | AE76: =$AE$75+IF(AND(LEN($N$15)>0,INDEX('Tabelas'!$X$472:$X$578,67)&""=$N$15,LEN(INDEX('Tabelas'!$Y$472:$Y$578,67)&"")>0),1,0) | AT76: ='Tabelas'!$AE$428&"" | AV76: =IF(ISERROR($A$76),"",IF(ISBLANK($A$76),"",$A$76)) | AW76: =IF(ISERROR($B$76),"",IF(ISBLANK($B$76),"",$B$76)) | AY76: =IF(ISERROR($D$76),"",IF(ISBLANK($D$76),"",$D$76)) | BA76: =IF(ISERROR($F$76),"",IF(ISBLANK($F$76),"",$F$76)) | BC76: =IF(ISERROR($H$76),"",IF(ISBLANK($H$76),"",$H$76)) | BF76: =ISERROR($A$76)*1+ISERROR($B$76)*1+ISERROR($D$76)*1+ISERROR($F$76)*1+ISERROR($H$76)*1
K77: =IF(BF77>0,"O Google leu como fórmula: escolha de novo ou digite com ' na frente.",IF(LEN($AV$77)=0,"",IF(COUNTIF($AG$10:$AG$39,$AV$77)>1,"Nome repetido no elenco",IF(COUNTIF('Dados'!$B$92:$B$123,$AV$77)>0,"Nome igual a uma criatura do Bestiário","")))) | AE77: =$AE$76+IF(AND(LEN($N$15)>0,INDEX('Tabelas'!$X$472:$X$578,68)&""=$N$15,LEN(INDEX('Tabelas'!$Y$472:$Y$578,68)&"")>0),1,0) | AT77: ='Tabelas'!$AE$429&"" | AV77: =IF(ISERROR($A$77),"",IF(ISBLANK($A$77),"",$A$77)) | AW77: =IF(ISERROR($B$77),"",IF(ISBLANK($B$77),"",$B$77)) | AY77: =IF(ISERROR($D$77),"",IF(ISBLANK($D$77),"",$D$77)) | BA77: =IF(ISERROR($F$77),"",IF(ISBLANK($F$77),"",$F$77)) | BC77: =IF(ISERROR($H$77),"",IF(ISBLANK($H$77),"",$H$77)) | BF77: =ISERROR($A$77)*1+ISERROR($B$77)*1+ISERROR($D$77)*1+ISERROR($F$77)*1+ISERROR($H$77)*1
A78: E2 · Como é | AE78: =$AE$77+IF(AND(LEN($N$15)>0,INDEX('Tabelas'!$X$472:$X$578,69)&""=$N$15,LEN(INDEX('Tabelas'!$Y$472:$Y$578,69)&"")>0),1,0) | AT78: ='Tabelas'!$AE$430&""
A79: NPC | B79: Aparência | F79: Personalidade | K79: Aviso | AE79: =$AE$78 | AT79: ='Tabelas'!$AE$431&""
A80: =IF(LEN($AV$46)>0,$AV$46,"NPC 1") | K80: =IF(BF80>0,"O Google leu como fórmula: digite de novo com ' na frente.","") | AE80: =$AE$79+IF(AND(LEN($N$15)>0,INDEX('Tabelas'!$X$472:$X$578,71)&""=$N$15,LEN(INDEX('Tabelas'!$Y$472:$Y$578,71)&"")>0),1,0) | AT80: ='Tabelas'!$AE$432&"" | AW80: =IF(ISERROR($B$80),"",IF(ISBLANK($B$80),"",$B$80)) | BF80: =ISERROR($B$80)*1+ISERROR($F$80)*1
A81: =IF(LEN($AV$47)>0,$AV$47,"NPC 2") | K81: =IF(BF81>0,"O Google leu como fórmula: digite de novo com ' na frente.","") | AE81: =$AE$80+IF(AND(LEN($N$15)>0,INDEX('Tabelas'!$X$472:$X$578,72)&""=$N$15,LEN(INDEX('Tabelas'!$Y$472:$Y$578,72)&"")>0),1,0) | AT81: ='Tabelas'!$AE$433&"" | AW81: =IF(ISERROR($B$81),"",IF(ISBLANK($B$81),"",$B$81)) | BF81: =ISERROR($B$81)*1+ISERROR($F$81)*1
A82: =IF(LEN($AV$48)>0,$AV$48,"NPC 3") | K82: =IF(BF82>0,"O Google leu como fórmula: digite de novo com ' na frente.","") | AE82: =$AE$81+IF(AND(LEN($N$15)>0,INDEX('Tabelas'!$X$472:$X$578,73)&""=$N$15,LEN(INDEX('Tabelas'!$Y$472:$Y$578,73)&"")>0),1,0) | AT82: ='Tabelas'!$AE$434&"" | AW82: =IF(ISERROR($B$82),"",IF(ISBLANK($B$82),"",$B$82)) | BF82: =ISERROR($B$82)*1+ISERROR($F$82)*1
A83: =IF(LEN($AV$49)>0,$AV$49,"NPC 4") | K83: =IF(BF83>0,"O Google leu como fórmula: digite de novo com ' na frente.","") | AE83: =$AE$82+IF(AND(LEN($N$15)>0,INDEX('Tabelas'!$X$472:$X$578,74)&""=$N$15,LEN(INDEX('Tabelas'!$Y$472:$Y$578,74)&"")>0),1,0) | AT83: ='Tabelas'!$AE$435&"" | AW83: =IF(ISERROR($B$83),"",IF(ISBLANK($B$83),"",$B$83)) | BF83: =ISERROR($B$83)*1+ISERROR($F$83)*1
A84: =IF(LEN($AV$50)>0,$AV$50,"NPC 5") | K84: =IF(BF84>0,"O Google leu como fórmula: digite de novo com ' na frente.","") | AE84: =$AE$83+IF(AND(LEN($N$15)>0,INDEX('Tabelas'!$X$472:$X$578,75)&""=$N$15,LEN(INDEX('Tabelas'!$Y$472:$Y$578,75)&"")>0),1,0) | AT84: ='Tabelas'!$AE$436&"" | AW84: =IF(ISERROR($B$84),"",IF(ISBLANK($B$84),"",$B$84)) | BF84: =ISERROR($B$84)*1+ISERROR($F$84)*1
A85: =IF(LEN($AV$51)>0,$AV$51,"NPC 6") | K85: =IF(BF85>0,"O Google leu como fórmula: digite de novo com ' na frente.","") | AE85: =$AE$84+IF(AND(LEN($N$15)>0,INDEX('Tabelas'!$X$472:$X$578,76)&""=$N$15,LEN(INDEX('Tabelas'!$Y$472:$Y$578,76)&"")>0),1,0) | AT85: ='Tabelas'!$AE$437&"" | AW85: =IF(ISERROR($B$85),"",IF(ISBLANK($B$85),"",$B$85)) | BF85: =ISERROR($B$85)*1+ISERROR($F$85)*1
A86: =IF(LEN($AV$52)>0,$AV$52,"NPC 7") | K86: =IF(BF86>0,"O Google leu como fórmula: digite de novo com ' na frente.","") | AE86: =$AE$85+IF(AND(LEN($N$15)>0,INDEX('Tabelas'!$X$472:$X$578,77)&""=$N$15,LEN(INDEX('Tabelas'!$Y$472:$Y$578,77)&"")>0),1,0) | AT86: ='Tabelas'!$AE$438&"" | AW86: =IF(ISERROR($B$86),"",IF(ISBLANK($B$86),"",$B$86)) | BF86: =ISERROR($B$86)*1+ISERROR($F$86)*1
A87: =IF(LEN($AV$53)>0,$AV$53,"NPC 8") | K87: =IF(BF87>0,"O Google leu como fórmula: digite de novo com ' na frente.","") | AE87: =$AE$86+IF(AND(LEN($N$15)>0,INDEX('Tabelas'!$X$472:$X$578,78)&""=$N$15,LEN(INDEX('Tabelas'!$Y$472:$Y$578,78)&"")>0),1,0) | AT87: ='Tabelas'!$AE$439&"" | AW87: =IF(ISERROR($B$87),"",IF(ISBLANK($B$87),"",$B$87)) | BF87: =ISERROR($B$87)*1+ISERROR($F$87)*1
A88: =IF(LEN($AV$54)>0,$AV$54,"NPC 9") | K88: =IF(BF88>0,"O Google leu como fórmula: digite de novo com ' na frente.","") | AE88: =$AE$87+IF(AND(LEN($N$15)>0,INDEX('Tabelas'!$X$472:$X$578,79)&""=$N$15,LEN(INDEX('Tabelas'!$Y$472:$Y$578,79)&"")>0),1,0) | AT88: ='Tabelas'!$AE$441&"" | AW88: =IF(ISERROR($B$88),"",IF(ISBLANK($B$88),"",$B$88)) | BF88: =ISERROR($B$88)*1+ISERROR($F$88)*1
A89: =IF(LEN($AV$55)>0,$AV$55,"NPC 10") | K89: =IF(BF89>0,"O Google leu como fórmula: digite de novo com ' na frente.","") | AE89: =$AE$88+IF(AND(LEN($N$15)>0,INDEX('Tabelas'!$X$472:$X$578,80)&""=$N$15,LEN(INDEX('Tabelas'!$Y$472:$Y$578,80)&"")>0),1,0) | AT89: ='Tabelas'!$AE$442&"" | AW89: =IF(ISERROR($B$89),"",IF(ISBLANK($B$89),"",$B$89)) | BF89: =ISERROR($B$89)*1+ISERROR($F$89)*1
A90: NPC | B90: Aparência | F90: Personalidade | K90: Aviso | AE90: =$AE$89+IF(AND(LEN($N$15)>0,INDEX('Tabelas'!$X$472:$X$578,81)&""=$N$15,LEN(INDEX('Tabelas'!$Y$472:$Y$578,81)&"")>0),1,0) | AT90: ='Tabelas'!$AE$443&""
A91: =IF(LEN($AV$57)>0,$AV$57,"NPC 11") | K91: =IF(BF91>0,"O Google leu como fórmula: digite de novo com ' na frente.","") | AE91: =$AE$90+IF(AND(LEN($N$15)>0,INDEX('Tabelas'!$X$472:$X$578,82)&""=$N$15,LEN(INDEX('Tabelas'!$Y$472:$Y$578,82)&"")>0),1,0) | AT91: ='Tabelas'!$AE$444&"" | AW91: =IF(ISERROR($B$91),"",IF(ISBLANK($B$91),"",$B$91)) | BF91: =ISERROR($B$91)*1+ISERROR($F$91)*1
A92: =IF(LEN($AV$58)>0,$AV$58,"NPC 12") | K92: =IF(BF92>0,"O Google leu como fórmula: digite de novo com ' na frente.","") | AE92: =$AE$91+IF(AND(LEN($N$15)>0,INDEX('Tabelas'!$X$472:$X$578,83)&""=$N$15,LEN(INDEX('Tabelas'!$Y$472:$Y$578,83)&"")>0),1,0) | AT92: ='Tabelas'!$AE$445&"" | AW92: =IF(ISERROR($B$92),"",IF(ISBLANK($B$92),"",$B$92)) | BF92: =ISERROR($B$92)*1+ISERROR($F$92)*1
A93: =IF(LEN($AV$59)>0,$AV$59,"NPC 13") | K93: =IF(BF93>0,"O Google leu como fórmula: digite de novo com ' na frente.","") | AE93: =$AE$92 | AT93: ='Tabelas'!$AE$446&"" | AW93: =IF(ISERROR($B$93),"",IF(ISBLANK($B$93),"",$B$93)) | BF93: =ISERROR($B$93)*1+ISERROR($F$93)*1
A94: =IF(LEN($AV$60)>0,$AV$60,"NPC 14") | K94: =IF(BF94>0,"O Google leu como fórmula: digite de novo com ' na frente.","") | AE94: =$AE$93+IF(AND(LEN($N$15)>0,INDEX('Tabelas'!$X$472:$X$578,85)&""=$N$15,LEN(INDEX('Tabelas'!$Y$472:$Y$578,85)&"")>0),1,0) | AT94: ='Tabelas'!$AE$447&"" | AW94: =IF(ISERROR($B$94),"",IF(ISBLANK($B$94),"",$B$94)) | BF94: =ISERROR($B$94)*1+ISERROR($F$94)*1
A95: =IF(LEN($AV$61)>0,$AV$61,"NPC 15") | K95: =IF(BF95>0,"O Google leu como fórmula: digite de novo com ' na frente.","") | AE95: =$AE$94+IF(AND(LEN($N$15)>0,INDEX('Tabelas'!$X$472:$X$578,86)&""=$N$15,LEN(INDEX('Tabelas'!$Y$472:$Y$578,86)&"")>0),1,0) | AT95: ='Tabelas'!$AE$448&"" | AW95: =IF(ISERROR($B$95),"",IF(ISBLANK($B$95),"",$B$95)) | BF95: =ISERROR($B$95)*1+ISERROR($F$95)*1
A96: =IF(LEN($AV$62)>0,$AV$62,"NPC 16") | K96: =IF(BF96>0,"O Google leu como fórmula: digite de novo com ' na frente.","") | AE96: =$AE$95+IF(AND(LEN($N$15)>0,INDEX('Tabelas'!$X$472:$X$578,87)&""=$N$15,LEN(INDEX('Tabelas'!$Y$472:$Y$578,87)&"")>0),1,0) | AT96: ='Tabelas'!$AE$449&"" | AW96: =IF(ISERROR($B$96),"",IF(ISBLANK($B$96),"",$B$96)) | BF96: =ISERROR($B$96)*1+ISERROR($F$96)*1
A97: =IF(LEN($AV$63)>0,$AV$63,"NPC 17") | K97: =IF(BF97>0,"O Google leu como fórmula: digite de novo com ' na frente.","") | AE97: =$AE$96+IF(AND(LEN($N$15)>0,INDEX('Tabelas'!$X$472:$X$578,88)&""=$N$15,LEN(INDEX('Tabelas'!$Y$472:$Y$578,88)&"")>0),1,0) | AT97: ='Tabelas'!$AE$450&"" | AW97: =IF(ISERROR($B$97),"",IF(ISBLANK($B$97),"",$B$97)) | BF97: =ISERROR($B$97)*1+ISERROR($F$97)*1
A98: =IF(LEN($AV$64)>0,$AV$64,"NPC 18") | K98: =IF(BF98>0,"O Google leu como fórmula: digite de novo com ' na frente.","") | AE98: =$AE$97+IF(AND(LEN($N$15)>0,INDEX('Tabelas'!$X$472:$X$578,89)&""=$N$15,LEN(INDEX('Tabelas'!$Y$472:$Y$578,89)&"")>0),1,0) | AT98: ='Tabelas'!$AE$451&"" | AW98: =IF(ISERROR($B$98),"",IF(ISBLANK($B$98),"",$B$98)) | BF98: =ISERROR($B$98)*1+ISERROR($F$98)*1
A99: =IF(LEN($AV$65)>0,$AV$65,"NPC 19") | K99: =IF(BF99>0,"O Google leu como fórmula: digite de novo com ' na frente.","") | AE99: =$AE$98+IF(AND(LEN($N$15)>0,INDEX('Tabelas'!$X$472:$X$578,90)&""=$N$15,LEN(INDEX('Tabelas'!$Y$472:$Y$578,90)&"")>0),1,0) | AT99: ='Tabelas'!$AE$452&"" | AW99: =IF(ISERROR($B$99),"",IF(ISBLANK($B$99),"",$B$99)) | BF99: =ISERROR($B$99)*1+ISERROR($F$99)*1
A100: =IF(LEN($AV$66)>0,$AV$66,"NPC 20") | K100: =IF(BF100>0,"O Google leu como fórmula: digite de novo com ' na frente.","") | AE100: =$AE$99+IF(AND(LEN($N$15)>0,INDEX('Tabelas'!$X$472:$X$578,91)&""=$N$15,LEN(INDEX('Tabelas'!$Y$472:$Y$578,91)&"")>0),1,0) | AT100: ='Tabelas'!$AE$453&"" | AW100: =IF(ISERROR($B$100),"",IF(ISBLANK($B$100),"",$B$100)) | BF100: =ISERROR($B$100)*1+ISERROR($F$100)*1
A101: NPC | B101: Aparência | F101: Personalidade | K101: Aviso | AE101: =$AE$100+IF(AND(LEN($N$15)>0,INDEX('Tabelas'!$X$472:$X$578,92)&""=$N$15,LEN(INDEX('Tabelas'!$Y$472:$Y$578,92)&"")>0),1,0) | AT101: ='Tabelas'!$AE$455&""
A102: =IF(LEN($AV$68)>0,$AV$68,"NPC 21") | K102: =IF(BF102>0,"O Google leu como fórmula: digite de novo com ' na frente.","") | AE102: =$AE$101+IF(AND(LEN($N$15)>0,INDEX('Tabelas'!$X$472:$X$578,93)&""=$N$15,LEN(INDEX('Tabelas'!$Y$472:$Y$578,93)&"")>0),1,0) | AT102: ='Tabelas'!$AE$456&"" | AW102: =IF(ISERROR($B$102),"",IF(ISBLANK($B$102),"",$B$102)) | BF102: =ISERROR($B$102)*1+ISERROR($F$102)*1
...

Sheet Inimigos
A1: Inimigos — Explorando Galáxias v1.1
A2: Legenda: | B2: Entrada (preencha) | C2: Calculada (automático) | D2: Aviso (texto em vermelho) | E2: Título de bloco | F2: Cabeçalho de coluna | G2: Rótulo da linha | H2: Linha alternada (outro tom) | I2: Não se aplica
A3: Criador de Inimigos: uma linha por inimigo da campanha, com a ficha de 28.1 pronta.
A5: Criador de Inimigos — uma linha por inimigo da campanha (28.1, 28.3, 28.4)
A6: Modo vazio = Faixa do livro; Faixa vazia = faixa do grupo; Tipo vazio = Comum (no modo Ajustar, o da base). A tabela já alimenta as listas de Encontros e Combate: não precisa copiar nada.
A7: Rolagem nº (Fraquezas sugeridas) | C7: =IF(ISNUMBER($DR$7),IF(AND($DR$7>=1,$DR$7<=1000000,INT($DR$7)=$DR$7),$DR$7,1),1) | D7: Some 1 para sortear outra ordem de Fraquezas sugeridas. | K7: =IF(EA7>0,"O Google leu como fórmula: digite de novo com ' na frente.",IF(LEN($DR$7)=0,"",IF(ISNUMBER($DR$7),IF(AND($DR$7>=1,$DR$7<=1000000,INT($DR$7)=$DR$7),"","Rolagem nº fora de 1 a 1.000.000: usando 1"),"Rolagem nº fora de 1 a 1.000.000: usando 1"))) | DR7: =IF(ISERROR($B$7),"",IF(ISBLANK($B$7),"",$B$7)) | EA7: =ISERROR($B$7)*1
A9: I1 · Conceito (preencha)
A10: Nome | B10: Modo | D10: Base do bestiário (modo Ajustar) | G10: Faixa | H10: Nível (modo Por nível) | I10: Tipo | J10: Fases (Boss, 1 a 3) | K10: Aviso
K11: =IF(EA11>0,"O Google leu como fórmula: escolha de novo ou digite com ' na frente.",IF(LEN($DQ$11)=0,IF(LEN($DR$11&$DT$11&$DY$11)>0,"Linha sem nome: o inimigo não entra nas listas",""),IF(COUNTIF($DQ$11:$DQ$22,$DQ$11)>1,"Nome repetido na tabela",IF(COUNTIF('Dados'!$B$92:$B$123,$DQ$11)>0,"Nome igual a uma criatura do bestiário: dê outro nome",IF(AND($BK$11="Ajustar do bestiário",$BL$11=0),"Modo Ajustar sem base do bestiário válida",IF(AND(LEN($DZ$11)>0,$BN$11<>"Boss"),"Fases só valem para Boss (28.5)",IF(AND(ISNUMBER($DX$11),OR($DX$11<1,$DX$11>20)),"Nível fora de 1 a 20: usando o limite",IF(AND(LEN($DY$11)>0,COUNTIF('Dados'!$AO$6:$AO$8,$DY$11)=0),"Tipo fora da lista: usando Comum","")))))))) | N11: =IF(LEN($DQ$11)=0,"",$DQ$11) | O11: =IF(LEN($DQ$11)=0,"",$BN$11) | P11: =IF(LEN($DQ$11)=0,"",$BQ$11) | Q11: =IF(LEN($DQ$11)=0,"",$BU$11) | R11: =IF(LEN($DQ$11)=0,"",IFERROR(INDEX('Dados'!$E$38:$E$52,MATCH($BS$11,'Dados'!$A$38:$A$52,0)),"")) | S11: =IF(LEN($DQ$11)=0,"",IFERROR(INDEX('Dados'!$F$38:$F$52,MATCH($BS$11,'Dados'!$A$38:$A$52,0)),"")) | T11: =IF(LEN($DQ$11)=0,"",IFERROR(INDEX('Dados'!$G$38:$G$52,MATCH($BS$11,'Dados'!$A$38:$A$52,0)),"")) | U11: =IF(LEN($DQ$11)=0,"",IFERROR(INDEX('Dados'!$H$38:$H$52,MATCH($BS$11,'Dados'!$A$38:$A$52,0)),"")) | V11: =IF(LEN($DQ$11)=0,"",IFERROR(INDEX('Dados'!$I$38:$I$52,MATCH($BS$11,'Dados'!$A$38:$A$52,0)),"")) | W11: =IF(LEN($DQ$11)=0,"",IFERROR(INDEX('Dados'!$J$38:$J$52,MATCH($BS$11,'Dados'!$A$38:$A$52,0)),"")) | X11: =IF(LEN($DQ$11)=0,"",IFERROR(INDEX('Dados'!$K$38:$K$52,MATCH($BS$11,'Dados'!$A$38:$A$52,0)),"")) | Y11: =IF(LEN($DQ$11)=0,"",IFERROR(INDEX('Dados'!$L$38:$L$52,MATCH($BS$11,'Dados'!$A$38:$A$52,0)),"")) | Z11: =IF(LEN($DQ$11)=0,"",IFERROR(INDEX('Dados'!$M$38:$M$52,MATCH($BS$11,'Dados'!$A$38:$A$52,0)),"")) | AA11: =IF(LEN($DQ$11)=0,"",$BY$11) | AB11: =IF(LEN($DQ$11)=0,"",$BZ$11) | AC11: =IF(LEN($DQ$11)=0,"",$CA$11) | AD11: =IF(LEN($DQ$11)=0,"",$CB$11) | AE11: =IF(LEN($DQ$11)=0,"",$CC$11) | AF11: =IF(LEN($DQ$11)=0,"",IF($DV$26="Sim","Pode",IF($DV$26="Não","Não",IF($BL$11=1,IFERROR(INDEX('Dados'!$V$92:$V$123,$BM$11)&"",""),"Não declarado")))) | AG11: =IF(LEN($DQ$11)=0,"",$BV$11) | AH11: =IF(LEN($DQ$11)=0,"",IFERROR(INDEX('Dados'!$Q$38:$Q$52,MATCH($BS$11,'Dados'!$A$38:$A$52,0)),"")) | AI11: =IF(LEN($DQ$11)=0,"",IF(AND($BL$11=1,$DT$11="Escória de Stellaron"),1.5,1)*$BU$11) | AJ11: =IF(LEN($DQ$11)=0,"",IFERROR(INDEX('Dados'!$P$38:$P$52,MATCH($BS$11,'Dados'!$A$38:$A$52,0)),"")) | AK11: =IF(LEN($DQ$11)=0,"",IF($BV$11=2,INT($BU$11/2),IF($BV$11=3,INT(2*$BU$11/3),""))) | AL11: =IF(LEN($DQ$11)=0,"",IF($BV$11=3,INT($BU$11/3),"")) | AM11: =IF(OR(LEN($DQ$11)=0,$BV$11<2),"",IFERROR(INDEX($DT$88:$DT$112,MATCH($DQ$11&"|2",$N$88:$N$112,0))&"",IF($BL$11=1,IFERROR(INDEX('Dados'!$G$127:$G$138,MATCH($DT$11&"|2",'Dados'!$A$127:$A$138,0)),""),""))) | AN11: =IF(OR(LEN($DQ$11)=0,$BV$11<2),"",IFERROR(INDEX($DU$88:$DU$112,MATCH($DQ$11&"|2",$N$88:$N$112,0))&"",IF($BL$11=1,IFERROR(INDEX('Dados'!$H$127:$H$138,MATCH($DT$11&"|2",'Dados'!$A$127:$A$138,0)),""),""))) | AO11: =IF(OR(LEN($DQ$11)=0,$BV$11<2),"",IFERROR(INDEX($DV$88:$DV$112,MATCH($DQ$11&"|2",$N$88:$N$112,0))&"",IF($BL$11=1,IFERROR(INDEX('Dados'!$I$127:$I$138,MATCH($DT$11&"|2",'Dados'!$A$127:$A$138,0)),""),""))) | AP11: =IF(OR(LEN($DQ$11)=0,$BV$11<2),"",IFERROR(INDEX($DW$88:$DW$112,MATCH($DQ$11&"|2",$N$88:$N$112,0))&"",IF($BL$11=1,IFERROR(INDEX('Dados'!$J$127:$J$138,MATCH($DT$11&"|2",'Dados'!$A$127:$A$138,0)),""),""))) | AQ11: =IF(OR(LEN($DQ$11)=0,$BV$11<2),"",IF(ISNUMBER(MATCH($DQ$11&"|2",$N$88:$N$112,0)),IF(ISNUMBER(INDEX($DX$88:$DX$112,MATCH($DQ$11&"|2",$N$88:$N$112,0))),MIN(IFERROR(INDEX('Dados'!$G$38:$G$52,MATCH($BS$11,'Dados'!$A$38:$A$52,0)),""),INDEX($DX$88:$DX$112,MATCH($DQ$11&"|2",$N$88:$N$112,0))),IFERROR(INDEX('Dados'!$G$38:$G$52,MATCH($BS$11,'Dados'!$A$38:$A$52,0)),"")),IF($BL$11=1,IFERROR(MIN(IFERROR(INDEX('Dados'!$G$38:$G$52,MATCH($BS$11,'Dados'!$A$38:$A$52,0)),""),INT(INDEX('Dados'!$K$127:$K$138,MATCH($DT$11&"|2",'Dados'!$A$127:$A$138,0))*IFERROR(INDEX('Dados'!$G$38:$G$52,MATCH($BS$11,'Dados'!$A$38:$A$52,0)),"")/$CH$11)),IFERROR(INDEX('Dados'!$G$38:$G$52,MATCH($BS$11,'Dados'!$A$38:$A$52,0)),"")),IFERROR(INDEX('Dados'!$G$38:$G$52,MATCH($BS$11,'Dados'!$A$38:$A$52,0)),"")))) | AR11: =IF(OR(LEN($DQ$11)=0,$BV$11<3),"",IFERROR(INDEX($DT$88:$DT$112,MATCH($DQ$11&"|3",$N$88:$N$112,0))&"",IF($BL$11=1,IFERROR(INDEX('Dados'!$G$127:$G$138,MATCH($DT$11&"|3",'Dados'!$A$127:$A$138,0)),""),""))) | AS11: =IF(OR(LEN($DQ$11)=0,$BV$11<3),"",IFERROR(INDEX($DU$88:$DU$112,MATCH($DQ$11&"|3",$N$88:$N$112,0))&"",IF($BL$11=1,IFERROR(INDEX('Dados'!$H$127:$H$138,MATCH($DT$11&"|3",'Dados'!$A$127:$A$138,0)),""),""))) | AT11: =IF(OR(LEN($DQ$11)=0,$BV$11<3),"",IFERROR(INDEX($DV$88:$DV$112,MATCH($DQ$11&"|3",$N$88:$N$112,0))&"",IF($BL$11=1,IFERROR(INDEX('Dados'!$I$127:$I$138,MATCH($DT$11&"|3",'Dados'!$A$127:$A$138,0)),""),""))) | AU11: =IF(OR(LEN($DQ$11)=0,$BV$11<3),"",IFERROR(INDEX($DW$88:$DW$112,MATCH($DQ$11&"|3",$N$88:$N$112,0))&"",IF($BL$11=1,IFERROR(INDEX('Dados'!$J$127:$J$138,MATCH($DT$11&"|3",'Dados'!$A$127:$A$138,0)),""),""))) | AV11: =IF(OR(LEN($DQ$11)=0,$BV$11<3),"",IF(ISNUMBER(MATCH($DQ$11&"|3",$N$88:$N$112,0)),IF(ISNUMBER(INDEX($DX$88:$DX$112,MATCH($DQ$11&"|3",$N$88:$N$112,0))),MIN(IFERROR(INDEX('Dados'!$G$38:$G$52,MATCH($BS$11,'Dados'!$A$38:$A$52,0)),""),INDEX($DX$88:$DX$112,MATCH($DQ$11&"|3",$N$88:$N$112,0))),IFERROR(INDEX('Dados'!$G$38:$G$52,MATCH($BS$11,'Dados'!$A$38:$A$52,0)),"")),IF($BL$11=1,IFERROR(MIN(IFERROR(INDEX('Dados'!$G$38:$G$52,MATCH($BS$11,'Dados'!$A$38:$A$52,0)),""),INT(INDEX('Dados'!$K$127:$K$138,MATCH($DT$11&"|3",'Dados'!$A$127:$A$138,0))*IFERROR(INDEX('Dados'!$G$38:$G$52,MATCH($BS$11,'Dados'!$A$38:$A$52,0)),"")/$CH$11)),IFERROR(INDEX('Dados'!$G$38:$G$52,MATCH($BS$11,'Dados'!$A$38:$A$52,0)),"")),IFERROR(INDEX('Dados'!$G$38:$G$52,MATCH($BS$11,'Dados'!$A$38:$A$52,0)),"")))) | AW11: =IF(LEN($DQ$11)=0,"",IF($BL$11=1,IFERROR(INDEX('Dados'!$AF$92:$AF$123,$BM$11)&"",""),IFERROR(INDEX($DU$116:$DU$153,MATCH($DQ$11&"|1",$Q$116:$Q$153,0))&"",""))) | AX11: =IF(LEN($DQ$11)=0,"",IF($BL$11=1,IF(ISNUMBER(IFERROR(INDEX('Dados'!$AG$92:$AG$123,$BM$11),"")),IF(IFERROR(INDEX('Dados'!$AG$92:$AG$123,$BM$11),"")>0,IFERROR(INDEX('Dados'!$AG$92:$AG$123,$BM$11),""),""),""),IFERROR(INDEX($DY$116:$DY$153,MATCH($DQ$11&"|1",$Q$116:$Q$153,0))+0,""))) | AY11: =IF(LEN($DQ$11)=0,"",IF($BL$11=1,IFERROR(INDEX('Dados'!$AH$92:$AH$123,$BM$11)&"",""),IFERROR(INDEX($DU$116:$DU$153,MATCH($DQ$11&"|2",$Q$116:$Q$153,0))&"",""))) | AZ11: =IF(LEN($DQ$11)=0,"",IF($BL$11=1,IF(ISNUMBER(IFERROR(INDEX('Dados'!$AI$92:$AI$123,$BM$11),"")),IF(IFERROR(INDEX('Dados'!$AI$92:$AI$123,$BM$11),"")>0,IFERROR(INDEX('Dados'!$AI$92:$AI$123,$BM$11),""),""),""),IFERROR(INDEX($DY$116:$DY$153,MATCH($DQ$11&"|2",$Q$116:$Q$153,0))+0,""))) | BA11: =IF(LEN($DQ$11)=0,"",IF($BL$11=1,IFERROR(INDEX('Dados'!$AJ$92:$AJ$123,$BM$11)&"",""),IFERROR(INDEX($DU$116:$DU$153,MATCH($DQ$11&"|3",$Q$116:$Q$153,0))&"",""))) | BB11: =IF(LEN($DQ$11)=0,"",IF($BL$11=1,IF(ISNUMBER(IFERROR(INDEX('Dados'!$AK$92:$AK$123,$BM$11),"")),IF(IFERROR(INDEX('Dados'!$AK$92:$AK$123,$BM$11),"")>0,IFERROR(INDEX('Dados'!$AK$92:$AK$123,$BM$11),""),""),""),IFERROR(INDEX($DY$116:$DY$153,MATCH($DQ$11&"|3",$Q$116:$Q$153,0))+0,""))) | BC11: =IF(LEN($DQ$11)=0,"",IF(LEN($DR$26)>0,$DR$26,IF($BL$11=1,IFERROR(INDEX('Dados'!$E$92:$E$123,$BM$11)&"",""),""))) | BD11: =IF(AND(LEN($DR$26)=0,$BL$11=1),IFERROR(INDEX('Dados'!$AD$92:$AD$123,$BM$11)&"",""),"") | BE11: =IF(LEN($DQ$11)=0,"",INDEX('Dados'!$F$7:$F$11,$BR$11)) | BF11: =IF(LEN($DQ$11)=0,"",$BR$11) | BG11: =$G$42 | BH11: ="Campanha" | BK11: =IF(COUNTIF('Dados'!$AQ$6:$AQ$8,$DR$11)>0,$DR$11,"Faixa do livro") | BL11: =IF(AND($BK$11="Ajustar do bestiário",ISNUMBER($BM$11)),1,0) | BM11: =IFERROR(MATCH($DT$11,'Dados'!$B$92:$B$123,0),"") | BN11: =IF(COUNTIF('Dados'!$AO$6:$AO$8,$DY$11)>0,$DY$11,IF($BL$11=1,IFERROR(INDEX('Dados'!$C$92:$C$123,$BM$11),""),"Comum")) | BO11: =MATCH($BN$11,'Dados'!$AO$6:$AO$8,0) | BP11: =IF(ISNUMBER($DX$11),MIN(20,MAX(1,INT($DX$11))),'Campanha'!$B$17) | BQ11: =IF($BK$11="Por nível — Sugestão",INDEX('Dados'!$B$7:$B$11,INT(($BP$11-1)/4)+1),IF(LEN(IFERROR(INDEX('Dados'!$B$7:$B$11,MATCH($DW$11,'Dados'!$AP$6:$AP$10,0)),""))>0,IFERROR(INDEX('Dados'!$B$7:$B$11,MATCH($DW$11,'Dados'!$AP$6:$AP$10,0)),""),'Campanha'!$B$19)) | BR11: =MATCH($BQ$11,'Dados'!$B$7:$B$11,0) | BS11: =$BQ$11&"|"&$BN$11 | BT11: =MIN(4,MAX(1,INT(($BP$11-3)/4)+1)) | BU11: =IF($BK$11="Por nível — Sugestão",INT(IF($BP$11<=3,INDEX('Dados'!$D$38:$D$52,$BO$11),IF($BP$11>=19,INDEX('Dados'!$D$38:$D$52,12+$BO$11),INDEX('Dados'!$D$38:$D$52,($BT$11-1)*3+$BO$11)+(INDEX('Dados'!$D$38:$D$52,$BT$11*3+$BO$11)-INDEX('Dados'!$D$38:$D$52,($BT$11-1)*3+$BO$11))*($BP$11-(4*$BT$11-1))/4))),IFERROR(INDEX('Dados'!$D$38:$D$52,MATCH($BS$11,'Dados'!$A$38:$A$52,0)),"")) | BV11: =IF($BN$11<>"Boss",1,IF(AND(ISNUMBER($DZ$11),$DZ$11>=1,$DZ$11<=3),INT($DZ$11),IF($BL$11=1,MAX(1,IFERROR(INDEX('Dados'!$F$92:$F$123,$BM$11),"")),1))) | BW11: =IFERROR(INDEX('Dados'!$O$38:$O$52,MATCH($BS$11,'Dados'!$A$38:$A$52,0)),"") | BX11: =IF(AND(LEN($DR$42)=0,LEN($DS$42)=0,LEN($DT$42)=0,LEN($DU$42)=0),1,0) | BY11: =IF(LEN($DQ$11)=0,"",IF($BX$11=0,$DR$42&"",IF($BL$11=1,IFERROR(INDEX('Dados'!$Q$92:$Q$123,$BM$11)&"",""),IF(1<=$BW$11,$CD$11,"")))) | BZ11: =IF(LEN($DQ$11)=0,"",IF($BX$11=0,$DS$42&"",IF($BL$11=1,IFERROR(INDEX('Dados'!$R$92:$R$123,$BM$11)&"",""),IF(2<=$BW$11,$CE$11,"")))) | CA11: =IF(LEN($DQ$11)=0,"",IF($BX$11=0,$DT$42&"",IF($BL$11=1,IFERROR(INDEX('Dados'!$S$92:$S$123,$BM$11)&"",""),IF(3<=$BW$11,$CF$11,"")))) | CB11: =IF(LEN($DQ$11)=0,"",IF($BX$11=0,$DU$42&"",IF($BL$11=1,IFERROR(INDEX('Dados'!$T$92:$T$123,$BM$11)&"",""),IF(4<=$BW$11,$CG$11,"")))) | CC11: =IF(LEN($DV$42)>0,$DV$42,IF($BL$11=1,IFERROR(INDEX('Dados'!$U$92:$U$123,$BM$11)&"",""),"")) | CD11: =INDEX('Dados'!$A$301:$A$307,MATCH(SMALL($DI$11:$DO$11,1),$DI$11:$DO$11,0)) | CE11: =INDEX('Dados'!$A$301:$A$307,MATCH(SMALL($DI$11:$DO$11,2),$DI$11:$DO$11,0)) | CF11: =INDEX('Dados'!$A$301:$A$307,MATCH(SMALL($DI$11:$DO$11,3),$DI$11:$DO$11,0)) | CG11: =INDEX('Dados'!$A$301:$A$307,MATCH(SMALL($DI$11:$DO$11,4),$DI$11:$DO$11,0)) | CH11: =IF($BL$11=1,IFERROR(INDEX('Dados'!$J$92:$J$123,$BM$11),""),"") | CI11: =IF($BL$11=1,IFERROR(INDEX('Dados'!$G$92:$G$123,$BM$11),""),"") | CJ11: =IFERROR(INDEX('Dados'!$S$38:$S$52,MATCH($BS$11,'Dados'!$A$38:$A$52,0)),"") | CK11: =IFERROR(INDEX('Dados'!$T$38:$T$52,MATCH($BS$11,'Dados'!$A$38:$A$52,0)),"") | CL11: =IFERROR(INDEX('Dados'!$J$38:$J$52,MATCH($BQ$11&"|Comum",'Dados'!$A$38:$A$52,0)),"") | CM11: =IFERROR(INDEX('Dados'!$K$38:$K$52,MATCH($BQ$11&"|Comum",'Dados'!$A$38:$A$52,0)),"") | CN11: =MOD(MOD(MOD((MOD('Início'!$E$15+104729*$C$7+15167889,2147483646)+1)*16807,2147483647)*16807,2147483647)*16807,2147483647) | CO11: =MOD(MOD(MOD((MOD(MOD(INT($CN$11/65536)*$CN$11,2147483647)*65536+MOD($CN$11,65536)*$CN$11,2147483647))*16807,2147483647)*16807,2147483647)*16807,2147483647) | CP11: =MOD(MOD(MOD((MOD($CO$11+INT($CO$11/65536)*MOD($CO$11,65536),2147483646)+1)*16807,2147483647)*16807,2147483647)*16807,2147483647) | CQ11: =MOD(MOD(MOD((MOD('Início'!$E$15+104729*$C$7+16467598,2147483646)+1)*16807,2147483647)*16807,2147483647)*16807,2147483647) | CR11: =MOD(MOD(MOD((MOD(MOD(INT($CQ$11/65536)*$CQ$11,2147483647)*65536+MOD($CQ$11,65536)*$CQ$11,2147483647))*16807,2147483647)*16807,2147483647)*16807,2147483647) | CS11: =MOD(MOD(MOD((MOD($CR$11+INT($CR$11/65536)*MOD($CR$11,65536),2147483646)+1)*16807,2147483647)*16807,2147483647)*16807,2147483647) | CT11: =MOD(MOD(MOD((MOD('Início'!$E$15+104729*$C$7+17767307,2147483646)+1)*16807,2147483647)*16807,2147483647)*16807,2147483647) | CU11: =MOD(MOD(MOD((MOD(MOD(INT($CT$11/65536)*$CT$11,2147483647)*65536+MOD($CT$11,65536)*$CT$11,2147483647))*16807,2147483647)*16807,2147483647)*16807,2147483647) | CV11: =MOD(MOD(MOD((MOD($CU$11+INT($CU$11/65536)*MOD($CU$11,65536),2147483646)+1)*16807,2147483647)*16807,2147483647)*16807,2147483647) | CW11: =MOD(MOD(MOD((MOD('Início'!$E$15+104729*$C$7+19067016,2147483646)+1)*16807,2147483647)*16807,2147483647)*16807,2147483647) | CX11: =MOD(MOD(MOD((MOD(MOD(INT($CW$11/65536)*$CW$11,2147483647)*65536+MOD($CW$11,65536)*$CW$11,2147483647))*16807,2147483647)*16807,2147483647)*16807,2147483647) | CY11: =MOD(MOD(MOD((MOD($CX$11+INT($CX$11/65536)*MOD($CX$11,65536),2147483646)+1)*16807,2147483647)*16807,2147483647)*16807,2147483647) | CZ11: =MOD(MOD(MOD((MOD('Início'!$E$15+104729*$C$7+20366725,2147483646)+1)*16807,2147483647)*16807,2147483647)*16807,2147483647) | DA11: =MOD(MOD(MOD((MOD(MOD(INT($CZ$11/65536)*$CZ$11,2147483647)*65536+MOD($CZ$11,65536)*$CZ$11,2147483647))*16807,2147483647)*16807,2147483647)*16807,2147483647) | DB11: =MOD(MOD(MOD((MOD($DA$11+INT($DA$11/65536)*MOD($DA$11,65536),2147483646)+1)*16807,2147483647)*16807,2147483647)*16807,2147483647) | DC11: =MOD(MOD(MOD((MOD('Início'!$E$15+104729*$C$7+21666434,2147483646)+1)*16807,2147483647)*16807,2147483647)*16807,2147483647) | DD11: =MOD(MOD(MOD((MOD(MOD(INT($DC$11/65536)*$DC$11,2147483647)*65536+MOD($DC$11,65536)*$DC$11,2147483647))*16807,2147483647)*16807,2147483647)*16807,2147483647) | DE11: =MOD(MOD(MOD((MOD($DD$11+INT($DD$11/65536)*MOD($DD$11,65536),2147483646)+1)*16807,2147483647)*16807,2147483647)*16807,2147483647) | DF11: =MOD(MOD(MOD((MOD('Início'!$E$15+104729*$C$7+22966143,2147483646)+1)*16807,2147483647)*16807,2147483647)*16807,2147483647) | DG11: =MOD(MOD(MOD((MOD(MOD(INT($DF$11/65536)*$DF$11,2147483647)*65536+MOD($DF$11,65536)*$DF$11,2147483647))*16807,2147483647)*16807,2147483647)*16807,2147483647) | DH11: =MOD(MOD(MOD((MOD($DG$11+INT($DG$11/65536)*MOD($DG$11,65536),2147483646)+1)*16807,2147483647)*16807,2147483647)*16807,2147483647) | DI11: =IF($CC$11="Físico",9000000000,IF(AND('Grupo'!$B$44="Sim",0=0),0,2147483647))+$CP$11+1/10 | DJ11: =IF($CC$11="Fogo",9000000000,IF(AND('Grupo'!$C$44="Sim",0=0),0,2147483647))+$CS$11+2/10 | DK11: =IF($CC$11="Gelo",9000000000,IF(AND('Grupo'!$D$44="Sim",0=0),0,2147483647))+$CV$11+3/10 | DL11: =IF($CC$11="Raio",9000000000,IF(AND('Grupo'!$E$44="Sim",0=0),0,2147483647))+$CY$11+4/10 | DM11: =IF($CC$11="Vento",9000000000,IF(AND('Grupo'!$F$44="Sim",0=0),0,2147483647))+$DB$11+5/10 | DN11: =IF($CC$11="Quântico",9000000000,IF(AND('Grupo'!$G$44="Sim",0=0),0,2147483647))+$DE$11+6/10 | DO11: =IF($CC$11="Imaginário",9000000000,IF(AND('Grupo'!$H$44="Sim",0=0),0,2147483647))+$DH$11+7/10 | DQ11: =IF(ISERROR($A$11),"",IF(ISBLANK($A$11),"",$A$11)) | DR11: =IF(ISERROR($B$11),"",IF(ISBLANK($B$11),"",$B$11)) | DT11: =IF(ISERROR($D$11),"",IF(ISBLANK($D$11),"",$D$11)) | DW11: =IF(ISERROR($G$11),"",IF(ISBLANK($G$11),"",$G$11)) | DX11: =IF(ISERROR($H$11),"",IF(ISBLANK($H$11),"",$H$11)) | DY11: =IF(ISERROR($I$11),"",IF(ISBLANK($I$11),"",$I$11)) | DZ11: =IF(ISERROR($J$11),"",IF(ISBLANK($J$11),"",$J$11)) | EA11: =ISERROR($A$11)*1+ISERROR($B$11)*1+ISERROR($D$11)*1+ISERROR($G$11)*1+ISERROR($H$11)*1+ISERROR($I$11)*1+ISERROR($J$11)*1
K12: =IF(EA12>0,"O Google leu como fórmula: escolha de novo ou digite com ' na frente.",IF(LEN($DQ$12)=0,IF(LEN($DR$12&$DT$12&$DY$12)>0,"Linha sem nome: o inimigo não entra nas listas",""),IF(COUNTIF($DQ$11:$DQ$22,$DQ$12)>1,"Nome repetido na tabela",IF(COUNTIF('Dados'!$B$92:$B$123,$DQ$12)>0,"Nome igual a uma criatura do bestiário: dê outro nome",IF(AND($BK$12="Ajustar do bestiário",$BL$12=0),"Modo Ajustar sem base do bestiário válida",IF(AND(LEN($DZ$12)>0,$BN$12<>"Boss"),"Fases só valem para Boss (28.5)",IF(AND(ISNUMBER($DX$12),OR($DX$12<1,$DX$12>20)),"Nível fora de 1 a 20: usando o limite",IF(AND(LEN($DY$12)>0,COUNTIF('Dados'!$AO$6:$AO$8,$DY$12)=0),"Tipo fora da lista: usando Comum","")))))))) | N12: =IF(LEN($DQ$12)=0,"",$DQ$12) | O12: =IF(LEN($DQ$12)=0,"",$BN$12) | P12: =IF(LEN($DQ$12)=0,"",$BQ$12) | Q12: =IF(LEN($DQ$12)=0,"",$BU$12) | R12: =IF(LEN($DQ$12)=0,"",IFERROR(INDEX('Dados'!$E$38:$E$52,MATCH($BS$12,'Dados'!$A$38:$A$52,0)),"")) | S12: =IF(LEN($DQ$12)=0,"",IFERROR(INDEX('Dados'!$F$38:$F$52,MATCH($BS$12,'Dados'!$A$38:$A$52,0)),"")) | T12: =IF(LEN($DQ$12)=0,"",IFERROR(INDEX('Dados'!$G$38:$G$52,MATCH($BS$12,'Dados'!$A$38:$A$52,0)),"")) | U12: =IF(LEN($DQ$12)=0,"",IFERROR(INDEX('Dados'!$H$38:$H$52,MATCH($BS$12,'Dados'!$A$38:$A$52,0)),"")) | V12: =IF(LEN($DQ$12)=0,"",IFERROR(INDEX('Dados'!$I$38:$I$52,MATCH($BS$12,'Dados'!$A$38:$A$52,0)),"")) | W12: =IF(LEN($DQ$12)=0,"",IFERROR(INDEX('Dados'!$J$38:$J$52,MATCH($BS$12,'Dados'!$A$38:$A$52,0)),"")) | X12: =IF(LEN($DQ$12)=0,"",IFERROR(INDEX('Dados'!$K$38:$K$52,MATCH($BS$12,'Dados'!$A$38:$A$52,0)),"")) | Y12: =IF(LEN($DQ$12)=0,"",IFERROR(INDEX('Dados'!$L$38:$L$52,MATCH($BS$12,'Dados'!$A$38:$A$52,0)),"")) | Z12: =IF(LEN($DQ$12)=0,"",IFERROR(INDEX('Dados'!$M$38:$M$52,MATCH($BS$12,'Dados'!$A$38:$A$52,0)),"")) | AA12: =IF(LEN($DQ$12)=0,"",$BY$12) | AB12: =IF(LEN($DQ$12)=0,"",$BZ$12) | AC12: =IF(LEN($DQ$12)=0,"",$CA$12) | AD12: =IF(LEN($DQ$12)=0,"",$CB$12) | AE12: =IF(LEN($DQ$12)=0,"",$CC$12) | AF12: =IF(LEN($DQ$12)=0,"",IF($DV$27="Sim","Pode",IF($DV$27="Não","Não",IF($BL$12=1,IFERROR(INDEX('Dados'!$V$92:$V$123,$BM$12)&"",""),"Não declarado")))) | AG12: =IF(LEN($DQ$12)=0,"",$BV$12) | AH12: =IF(LEN($DQ$12)=0,"",IFERROR(INDEX('Dados'!$Q$38:$Q$52,MATCH($BS$12,'Dados'!$A$38:$A$52,0)),"")) | AI12: =IF(LEN($DQ$12)=0,"",IF(AND($BL$12=1,$DT$12="Escória de Stellaron"),1.5,1)*$BU$12) | AJ12: =IF(LEN($DQ$12)=0,"",IFERROR(INDEX('Dados'!$P$38:$P$52,MATCH($BS$12,'Dados'!$A$38:$A$52,0)),"")) | AK12: =IF(LEN($DQ$12)=0,"",IF($BV$12=2,INT($BU$12/2),IF($BV$12=3,INT(2*$BU$12/3),""))) | AL12: =IF(LEN($DQ$12)=0,"",IF($BV$12=3,INT($BU$12/3),"")) | AM12: =IF(OR(LEN($DQ$12)=0,$BV$12<2),"",IFERROR(INDEX($DT$88:$DT$112,MATCH($DQ$12&"|2",$N$88:$N$112,0))&"",IF($BL$12=1,IFERROR(INDEX('Dados'!$G$127:$G$138,MATCH($DT$12&"|2",'Dados'!$A$127:$A$138,0)),""),""))) | AN12: =IF(OR(LEN($DQ$12)=0,$BV$12<2),"",IFERROR(INDEX($DU$88:$DU$112,MATCH($DQ$12&"|2",$N$88:$N$112,0))&"",IF($BL$12=1,IFERROR(INDEX('Dados'!$H$127:$H$138,MATCH($DT$12&"|2",'Dados'!$A$127:$A$138,0)),""),""))) | AO12: =IF(OR(LEN($DQ$12)=0,$BV$12<2),"",IFERROR(INDEX($DV$88:$DV$112,MATCH($DQ$12&"|2",$N$88:$N$112,0))&"",IF($BL$12=1,IFERROR(INDEX('Dados'!$I$127:$I$138,MATCH($DT$12&"|2",'Dados'!$A$127:$A$138,0)),""),""))) | AP12: =IF(OR(LEN($DQ$12)=0,$BV$12<2),"",IFERROR(INDEX($DW$88:$DW$112,MATCH($DQ$12&"|2",$N$88:$N$112,0))&"",IF($BL$12=1,IFERROR(INDEX('Dados'!$J$127:$J$138,MATCH($DT$12&"|2",'Dados'!$A$127:$A$138,0)),""),""))) | AQ12: =IF(OR(LEN($DQ$12)=0,$BV$12<2),"",IF(ISNUMBER(MATCH($DQ$12&"|2",$N$88:$N$112,0)),IF(ISNUMBER(INDEX($DX$88:$DX$112,MATCH($DQ$12&"|2",$N$88:$N$112,0))),MIN(IFERROR(INDEX('Dados'!$G$38:$G$52,MATCH($BS$12,'Dados'!$A$38:$A$52,0)),""),INDEX($DX$88:$DX$112,MATCH($DQ$12&"|2",$N$88:$N$112,0))),IFERROR(INDEX('Dados'!$G$38:$G$52,MATCH($BS$12,'Dados'!$A$38:$A$52,0)),"")),IF($BL$12=1,IFERROR(MIN(IFERROR(INDEX('Dados'!$G$38:$G$52,MATCH($BS$12,'Dados'!$A$38:$A$52,0)),""),INT(INDEX('Dados'!$K$127:$K$138,MATCH($DT$12&"|2",'Dados'!$A$127:$A$138,0))*IFERROR(INDEX('Dados'!$G$38:$G$52,MATCH($BS$12,'Dados'!$A$38:$A$52,0)),"")/$CH$12)),IFERROR(INDEX('Dados'!$G$38:$G$52,MATCH($BS$12,'Dados'!$A$38:$A$52,0)),"")),IFERROR(INDEX('Dados'!$G$38:$G$52,MATCH($BS$12,'Dados'!$A$38:$A$52,0)),"")))) | AR12: =IF(OR(LEN($DQ$12)=0,$BV$12<3),"",IFERROR(INDEX($DT$88:$DT$112,MATCH($DQ$12&"|3",$N$88:$N$112,0))&"",IF($BL$12=1,IFERROR(INDEX('Dados'!$G$127:$G$138,MATCH($DT$12&"|3",'Dados'!$A$127:$A$138,0)),""),""))) | AS12: =IF(OR(LEN($DQ$12)=0,$BV$12<3),"",IFERROR(INDEX($DU$88:$DU$112,MATCH($DQ$12&"|3",$N$88:$N$112,0))&"",IF($BL$12=1,IFERROR(INDEX('Dados'!$H$127:$H$138,MATCH($DT$12&"|3",'Dados'!$A$127:$A$138,0)),""),""))) | AT12: =IF(OR(LEN($DQ$12)=0,$BV$12<3),"",IFERROR(INDEX($DV$88:$DV$112,MATCH($DQ$12&"|3",$N$88:$N$112,0))&"",IF($BL$12=1,IFERROR(INDEX('Dados'!$I$127:$I$138,MATCH($DT$12&"|3",'Dados'!$A$127:$A$138,0)),""),""))) | AU12: =IF(OR(LEN($DQ$12)=0,$BV$12<3),"",IFERROR(INDEX($DW$88:$DW$112,MATCH($DQ$12&"|3",$N$88:$N$112,0))&"",IF($BL$12=1,IFERROR(INDEX('Dados'!$J$127:$J$138,MATCH($DT$12&"|3",'Dados'!$A$127:$A$138,0)),""),""))) | AV12: =IF(OR(LEN($DQ$12)=0,$BV$12<3),"",IF(ISNUMBER(MATCH($DQ$12&"|3",$N$88:$N$112,0)),IF(ISNUMBER(INDEX($DX$88:$DX$112,MATCH($DQ$12&"|3",$N$88:$N$112,0))),MIN(IFERROR(INDEX('Dados'!$G$38:$G$52,MATCH($BS$12,'Dados'!$A$38:$A$52,0)),""),INDEX($DX$88:$DX$112,MATCH($DQ$12&"|3",$N$88:$N$112,0))),IFERROR(INDEX('Dados'!$G$38:$G$52,MATCH($BS$12,'Dados'!$A$38:$A$52,0)),"")),IF($BL$12=1,IFERROR(MIN(IFERROR(INDEX('Dados'!$G$38:$G$52,MATCH($BS$12,'Dados'!$A$38:$A$52,0)),""),INT(INDEX('Dados'!$K$127:$K$138,MATCH($DT$12&"|3",'Dados'!$A$127:$A$138,0))*IFERROR(INDEX('Dados'!$G$38:$G$52,MATCH($BS$12,'Dados'!$A$38:$A$52,0)),"")/$CH$12)),IFERROR(INDEX('Dados'!$G$38:$G$52,MATCH($BS$12,'Dados'!$A$38:$A$52,0)),"")),IFERROR(INDEX('Dados'!$G$38:$G$52,MATCH($BS$12,'Dados'!$A$38:$A$52,0)),"")))) | AW12: =IF(LEN($DQ$12)=0,"",IF($BL$12=1,IFERROR(INDEX('Dados'!$AF$92:$AF$123,$BM$12)&"",""),IFERROR(INDEX($DU$116:$DU$153,MATCH($DQ$12&"|1",$Q$116:$Q$153,0))&"",""))) | AX12: =IF(LEN($DQ$12)=0,"",IF($BL$12=1,IF(ISNUMBER(IFERROR(INDEX('Dados'!$AG$92:$AG$123,$BM$12),"")),IF(IFERROR(INDEX('Dados'!$AG$92:$AG$123,$BM$12),"")>0,IFERROR(INDEX('Dados'!$AG$92:$AG$123,$BM$12),""),""),""),IFERROR(INDEX($DY$116:$DY$153,MATCH($DQ$12&"|1",$Q$116:$Q$153,0))+0,""))) | AY12: =IF(LEN($DQ$12)=0,"",IF($BL$12=1,IFERROR(INDEX('Dados'!$AH$92:$AH$123,$BM$12)&"",""),IFERROR(INDEX($DU$116:$DU$153,MATCH($DQ$12&"|2",$Q$116:$Q$153,0))&"",""))) | AZ12: =IF(LEN($DQ$12)=0,"",IF($BL$12=1,IF(ISNUMBER(IFERROR(INDEX('Dados'!$AI$92:$AI$123,$BM$12),"")),IF(IFERROR(INDEX('Dados'!$AI$92:$AI$123,$BM$12),"")>0,IFERROR(INDEX('Dados'!$AI$92:$AI$123,$BM$12),""),""),""),IFERROR(INDEX($DY$116:$DY$153,MATCH($DQ$12&"|2",$Q$116:$Q$153,0))+0,""))) | BA12: =IF(LEN($DQ$12)=0,"",IF($BL$12=1,IFERROR(INDEX('Dados'!$AJ$92:$AJ$123,$BM$12)&"",""),IFERROR(INDEX($DU$116:$DU$153,MATCH($DQ$12&"|3",$Q$116:$Q$153,0))&"",""))) | BB12: =IF(LEN($DQ$12)=0,"",IF($BL$12=1,IF(ISNUMBER(IFERROR(INDEX('Dados'!$AK$92:$AK$123,$BM$12),"")),IF(IFERROR(INDEX('Dados'!$AK$92:$AK$123,$BM$12),"")>0,IFERROR(INDEX('Dados'!$AK$92:$AK$123,$BM$12),""),""),""),IFERROR(INDEX($DY$116:$DY$153,MATCH($DQ$12&"|3",$Q$116:$Q$153,0))+0,""))) | BC12: =IF(LEN($DQ$12)=0,"",IF(LEN($DR$27)>0,$DR$27,IF($BL$12=1,IFERROR(INDEX('Dados'!$E$92:$E$123,$BM$12)&"",""),""))) | BD12: =IF(AND(LEN($DR$27)=0,$BL$12=1),IFERROR(INDEX('Dados'!$AD$92:$AD$123,$BM$12)&"",""),"") | BE12: =IF(LEN($DQ$12)=0,"",INDEX('Dados'!$F$7:$F$11,$BR$12)) | BF12: =IF(LEN($DQ$12)=0,"",$BR$12) | BG12: =$G$43 | BH12: ="Campanha" | BK12: =IF(COUNTIF('Dados'!$AQ$6:$AQ$8,$DR$12)>0,$DR$12,"Faixa do livro") | BL12: =IF(AND($BK$12="Ajustar do bestiário",ISNUMBER($BM$12)),1,0) | BM12: =IFERROR(MATCH($DT$12,'Dados'!$B$92:$B$123,0),"") | BN12: =IF(COUNTIF('Dados'!$AO$6:$AO$8,$DY$12)>0,$DY$12,IF($BL$12=1,IFERROR(INDEX('Dados'!$C$92:$C$123,$BM$12),""),"Comum")) | BO12: =MATCH($BN$12,'Dados'!$AO$6:$AO$8,0) | BP12: =IF(ISNUMBER($DX$12),MIN(20,MAX(1,INT($DX$12))),'Campanha'!$B$17) | BQ12: =IF($BK$12="Por nível — Sugestão",INDEX('Dados'!$B$7:$B$11,INT(($BP$12-1)/4)+1),IF(LEN(IFERROR(INDEX('Dados'!$B$7:$B$11,MATCH($DW$12,'Dados'!$AP$6:$AP$10,0)),""))>0,IFERROR(INDEX('Dados'!$B$7:$B$11,MATCH($DW$12,'Dados'!$AP$6:$AP$10,0)),""),'Campanha'!$B$19)) | BR12: =MATCH($BQ$12,'Dados'!$B$7:$B$11,0) | BS12: =$BQ$12&"|"&$BN$12 | BT12: =MIN(4,MAX(1,INT(($BP$12-3)/4)+1)) | BU12: =IF($BK$12="Por nível — Sugestão",INT(IF($BP$12<=3,INDEX('Dados'!$D$38:$D$52,$BO$12),IF($BP$12>=19,INDEX('Dados'!$D$38:$D$52,12+$BO$12),INDEX('Dados'!$D$38:$D$52,($BT$12-1)*3+$BO$12)+(INDEX('Dados'!$D$38:$D$52,$BT$12*3+$BO$12)-INDEX('Dados'!$D$38:$D$52,($BT$12-1)*3+$BO$12))*($BP$12-(4*$BT$12-1))/4))),IFERROR(INDEX('Dados'!$D$38:$D$52,MATCH($BS$12,'Dados'!$A$38:$A$52,0)),"")) | BV12: =IF($BN$12<>"Boss",1,IF(AND(ISNUMBER($DZ$12),$DZ$12>=1,$DZ$12<=3),INT($DZ$12),IF($BL$12=1,MAX(1,IFERROR(INDEX('Dados'!$F$92:$F$123,$BM$12),"")),1))) | BW12: =IFERROR(INDEX('Dados'!$O$38:$O$52,MATCH($BS$12,'Dados'!$A$38:$A$52,0)),"") | BX12: =IF(AND(LEN($DR$43)=0,LEN($DS$43)=0,LEN($DT$43)=0,LEN($DU$43)=0),1,0) | BY12: =IF(LEN($DQ$12)=0,"",IF($BX$12=0,$DR$43&"",IF($BL$12=1,IFERROR(INDEX('Dados'!$Q$92:$Q$123,$BM$12)&"",""),IF(1<=$BW$12,$CD$12,"")))) | BZ12: =IF(LEN($DQ$12)=0,"",IF($BX$12=0,$DS$43&"",IF($BL$12=1,IFERROR(INDEX('Dados'!$R$92:$R$123,$BM$12)&"",""),IF(2<=$BW$12,$CE$12,"")))) | CA12: =IF(LEN($DQ$12)=0,"",IF($BX$12=0,$DT$43&"",IF($BL$12=1,IFERROR(INDEX('Dados'!$S$92:$S$123,$BM$12)&"",""),IF(3<=$BW$12,$CF$12,"")))) | CB12: =IF(LEN($DQ$12)=0,"",IF($BX$12=0,$DU$43&"",IF($BL$12=1,IFERROR(INDEX('Dados'!$T$92:$T$123,$BM$12)&"",""),IF(4<=$BW$12,$CG$12,"")))) | CC12: =IF(LEN($DV$43)>0,$DV$43,IF($BL$12=1,IFERROR(INDEX('Dados'!$U$92:$U$123,$BM$12)&"",""),"")) | CD12: =INDEX('Dados'!$A$301:$A$307,MATCH(SMALL($DI$12:$DO$12,1),$DI$12:$DO$12,0)) | CE12: =INDEX('Dados'!$A$301:$A$307,MATCH(SMALL($DI$12:$DO$12,2),$DI$12:$DO$12,0)) | CF12: =INDEX('Dados'!$A$301:$A$307,MATCH(SMALL($DI$12:$DO$12,3),$DI$12:$DO$12,0)) | CG12: =INDEX('Dados'!$A$301:$A$307,MATCH(SMALL($DI$12:$DO$12,4),$DI$12:$DO$12,0)) | CH12: =IF($BL$12=1,IFERROR(INDEX('Dados'!$J$92:$J$123,$BM$12),""),"") | CI12: =IF($BL$12=1,IFERROR(INDEX('Dados'!$G$92:$G$123,$BM$12),""),"") | CJ12: =IFERROR(INDEX('Dados'!$S$38:$S$52,MATCH($BS$12,'Dados'!$A$38:$A$52,0)),"") | CK12: =IFERROR(INDEX('Dados'!$T$38:$T$52,MATCH($BS$12,'Dados'!$A$38:$A$52,0)),"") | CL12: =IFERROR(INDEX('Dados'!$J$38:$J$52,MATCH($BQ$12&"|Comum",'Dados'!$A$38:$A$52,0)),"") | CM12: =IFERROR(INDEX('Dados'!$K$38:$K$52,MATCH($BQ$12&"|Comum",'Dados'!$A$38:$A$52,0)),"") | CN12: =MOD(MOD(MOD((MOD('Início'!$E$15+104729*$C$7+28164979,2147483646)+1)*16807,2147483647)*16807,2147483647)*16807,2147483647) | CO12: =MOD(MOD(MOD((MOD(MOD(INT($CN$12/65536)*$CN$12,2147483647)*65536+MOD($CN$12,65536)*$CN$12,2147483647))*16807,2147483647)*16807,2147483647)*16807,2147483647) | CP12: =MOD(MOD(MOD((MOD($CO$12+INT($CO$12/65536)*MOD($CO$12,65536),2147483646)+1)*16807,2147483647)*16807,2147483647)*16807,2147483647) | CQ12: =MOD(MOD(MOD((MOD('Início'!$E$15+104729*$C$7+29464688,2147483646)+1)*16807,2147483647)*16807,2147483647)*16807,2147483647) | CR12: =MOD(MOD(MOD((MOD(MOD(INT($CQ$12/65536)*$CQ$12,2147483647)*65536+MOD($CQ$12,65536)*$CQ$12,2147483647))*16807,2147483647)*16807,2147483647)*16807,2147483647) | CS12: =MOD(MOD(MOD((MOD($CR$12+INT($CR$12/65536)*MOD($CR$12,65536),2147483646)+1)*16807,2147483647)*16807,2147483647)*16807,2147483647) | CT12: =MOD(MOD(MOD((MOD('Início'!$E$15+104729*$C$7+30764397,2147483646)+1)*16807,2147483647)*16807,2147483647)*16807,2147483647) | CU12: =MOD(MOD(MOD((MOD(MOD(INT($CT$12/65536)*$CT$12,2147483647)*65536+MOD($CT$12,65536)*$CT$12,2147483647))*16807,2147483647)*16807,2147483647)*16807,2147483647) | CV12: =MOD(MOD(MOD((MOD($CU$12+INT($CU$12/65536)*MOD($CU$12,65536),2147483646)+1)*16807,2147483647)*16807,2147483647)*16807,2147483647) | CW12: =MOD(MOD(MOD((MOD('Início'!$E$15+104729*$C$7+32064106,2147483646)+1)*16807,2147483647)*16807,2147483647)*16807,2147483647) | CX12: =MOD(MOD(MOD((MOD(MOD(INT($CW$12/65536)*$CW$12,2147483647)*65536+MOD($CW$12,65536)*$CW$12,2147483647))*16807,2147483647)*16807,2147483647)*16807,2147483647) | CY12: =MOD(MOD(MOD((MOD($CX$12+INT($CX$12/65536)*MOD($CX$12,65536),2147483646)+1)*16807,2147483647)*16807,2147483647)*16807,2147483647) | CZ12: =MOD(MOD(MOD((MOD('Início'!$E$15+104729*$C$7+33363815,2147483646)+1)*16807,2147483647)*16807,2147483647)*16807,2147483647) | DA12: =MOD(MOD(MOD((MOD(MOD(INT($CZ$12/65536)*$CZ$12,2147483647)*65536+MOD($CZ$12,65536)*$CZ$12,2147483647))*16807,2147483647)*16807,2147483647)*16807,2147483647) | DB12: =MOD(MOD(MOD((MOD($DA$12+INT($DA$12/65536)*MOD($DA$12,65536),2147483646)+1)*16807,2147483647)*16807,2147483647)*16807,2147483647) | DC12: =MOD(MOD(MOD((MOD('Início'!$E$15+104729*$C$7+34663524,2147483646)+1)*16807,2147483647)*16807,2147483647)*16807,2147483647) | DD12: =MOD(MOD(MOD((MOD(MOD(INT($DC$12/65536)*$DC$12,2147483647)*65536+MOD($DC$12,65536)*$DC$12,2147483647))*16807,2147483647)*16807,2147483647)*16807,2147483647) | DE12: =MOD(MOD(MOD((MOD($DD$12+INT($DD$12/65536)*MOD($DD$12,65536),2147483646)+1)*16807,2147483647)*16807,2147483647)*16807,2147483647) | DF12: =MOD(MOD(MOD((MOD('Início'!$E$15+104729*$C$7+35963233,2147483646)+1)*16807,2147483647)*16807,2147483647)*16807,2147483647) | DG12: =MOD(MOD(MOD((MOD(MOD(INT($DF$12/65536)*$DF$12,2147483647)*65536+MOD($DF$12,65536)*$DF$12,2147483647))*16807,2147483647)*16807,2147483647)*16807,2147483647) | DH12: =MOD(MOD(MOD((MOD($DG$12+INT($DG$12/65536)*MOD($DG$12,65536),2147483646)+1)*16807,2147483647)*16807,2147483647)*16807,2147483647) | DI12: =IF($CC$12="Físico",9000000000,IF(AND('Grupo'!$B$44="Sim",COUNTIF($BY$11:$CB$11,"Físico")=0),0,2147483647))+$CP$12+1/10 | DJ12: =IF($CC$12="Fogo",9000000000,IF(AND('Grupo'!$C$44="Sim",COUNTIF($BY$11:$CB$11,"Fogo")=0),0,2147483647))+$CS$12+2/10 | DK12: =IF($CC$12="Gelo",9000000000,IF(AND('Grupo'!$D$44="Sim",COUNTIF($BY$11:$CB$11,"Gelo")=0),0,2147483647))+$CV$12+3/10 | DL12: =IF($CC$12="Raio",9000000000,IF(AND('Grupo'!$E$44="Sim",COUNTIF($BY$11:$CB$11,"Raio")=0),0,2147483647))+$CY$12+4/10 | DM12: =IF($CC$12="Vento",9000000000,IF(AND('Grupo'!$F$44="Sim",COUNTIF($BY$11:$CB$11,"Vento")=0),0,2147483647))+$DB$12+5/10 | DN12: =IF($CC$12="Quântico",9000000000,IF(AND('Grupo'!$G$44="Sim",COUNTIF($BY$11:$CB$11,"Quântico")=0),0,2147483647))+$DE$12+6/10 | DO12: =IF($CC$12="Imaginário",9000000000,IF(AND('Grupo'!$H$44="Sim",COUNTIF($BY$11:$CB$11,"Imaginário")=0),0,2147483647))+$DH$12+7/10 | DQ12: =IF(ISERROR($A$12),"",IF(ISBLANK($A$12),"",$A$12)) | DR12: =IF(ISERROR($B$12),"",IF(ISBLANK($B$12),"",$B$12)) | DT12: =IF(ISERROR($D$12),"",IF(ISBLANK($D$12),"",$D$12)) | DW12: =IF(ISERROR($G$12),"",IF(ISBLANK($G$12),"",$G$12)) | DX12: =IF(ISERROR($H$12),"",IF(ISBLANK($H$12),"",$H$12)) | DY12: =IF(ISERROR($I$12),"",IF(ISBLANK($I$12),"",$I$12)) | DZ12: =IF(ISERROR($J$12),"",IF(ISBLANK($J$12),"",$J$12)) | EA12: =ISERROR($A$12)*1+ISERROR($B$12)*1+ISERROR($D$12)*1+ISERROR($G$12)*1+ISERROR($H$12)*1+ISERROR($I$12)*1+ISERROR($J$12)*1
K13: =IF(EA13>0,"O Google leu como fórmula: escolha de novo ou digite com ' na frente.",IF(LEN($DQ$13)=0,IF(LEN($DR$13&$DT$13&$DY$13)>0,"Linha sem nome: o inimigo não entra nas listas",""),IF(COUNTIF($DQ$11:$DQ$22,$DQ$13)>1,"Nome repetido na tabela",IF(COUNTIF('Dados'!$B$92:$B$123,$DQ$13)>0,"Nome igual a uma criatura do bestiário: dê outro nome",IF(AND($BK$13="Ajustar do bestiário",$BL$13=0),"Modo Ajustar sem base do bestiário válida",IF(AND(LEN($DZ$13)>0,$BN$13<>"Boss"),"Fases só valem para Boss (28.5)",IF(AND(ISNUMBER($DX$13),OR($DX$13<1,$DX$13>20)),"Nível fora de 1 a 20: usando o limite",IF(AND(LEN($DY$13)>0,COUNTIF('Dados'!$AO$6:$AO$8,$DY$13)=0),"Tipo fora da lista: usando Comum","")))))))) | N13: =IF(LEN($DQ$13)=0,"",$DQ$13) | O13: =IF(LEN($DQ$13)=0,"",$BN$13) | P13: =IF(LEN($DQ$13)=0,"",$BQ$13) | Q13: =IF(LEN($DQ$13)=0,"",$BU$13) | R13: =IF(LEN($DQ$13)=0,"",IFERROR(INDEX('Dados'!$E$38:$E$52,MATCH($BS$13,'Dados'!$A$38:$A$52,0)),"")) | S13: =IF(LEN($DQ$13)=0,"",IFERROR(INDEX('Dados'!$F$38:$F$52,MATCH($BS$13,'Dados'!$A$38:$A$52,0)),"")) | T13: =IF(LEN($DQ$13)=0,"",IFERROR(INDEX('Dados'!$G$38:$G$52,MATCH($BS$13,'Dados'!$A$38:$A$52,0)),"")) | U13: =IF(LEN($DQ$13)=0,"",IFERROR(INDEX('Dados'!$H$38:$H$52,MATCH($BS$13,'Dados'!$A$38:$A$52,0)),"")) | V13: =IF(LEN($DQ$13)=0,"",IFERROR(INDEX('Dados'!$I$38:$I$52,MATCH($BS$13,'Dados'!$A$38:$A$52,0)),"")) | W13: =IF(LEN($DQ$13)=0,"",IFERROR(INDEX('Dados'!$J$38:$J$52,MATCH($BS$13,'Dados'!$A$38:$A$52,0)),"")) | X13: =IF(LEN($DQ$13)=0,"",IFERROR(INDEX('Dados'!$K$38:$K$52,MATCH($BS$13,'Dados'!$A$38:$A$52,0)),"")) | Y13: =IF(LEN($DQ$13)=0,"",IFERROR(INDEX('Dados'!$L$38:$L$52,MATCH($BS$13,'Dados'!$A$38:$A$52,0)),"")) | Z13: =IF(LEN($DQ$13)=0,"",IFERROR(INDEX('Dados'!$M$38:$M$52,MATCH($BS$13,'Dados'!$A$38:$A$52,0)),"")) | AA13: =IF(LEN($DQ$13)=0,"",$BY$13) | AB13: =IF(LEN($DQ$13)=0,"",$BZ$13) | AC13: =IF(LEN($DQ$13)=0,"",$CA$13) | AD13: =IF(LEN($DQ$13)=0,"",$CB$13) | AE13: =IF(LEN($DQ$13)=0,"",$CC$13) | AF13: =IF(LEN($DQ$13)=0,"",IF($DV$28="Sim","Pode",IF($DV$28="Não","Não",IF($BL$13=1,IFERROR(INDEX('Dados'!$V$92:$V$123,$BM$13)&"",""),"Não declarado")))) | AG13: =IF(LEN($DQ$13)=0,"",$BV$13) | AH13: =IF(LEN($DQ$13)=0,"",IFERROR(INDEX('Dados'!$Q$38:$Q$52,MATCH($BS$13,'Dados'!$A$38:$A$52,0)),"")) | AI13: =IF(LEN($DQ$13)=0,"",IF(AND($BL$13=1,$DT$13="Escória de Stellaron"),1.5,1)*$BU$13) | AJ13: =IF(LEN($DQ$13)=0,"",IFERROR(INDEX('Dados'!$P$38:$P$52,MATCH($BS$13,'Dados'!$A$38:$A$52,0)),"")) | AK13: =IF(LEN($DQ$13)=0,"",IF($BV$13=2,INT($BU$13/2),IF($BV$13=3,INT(2*$BU$13/3),""))) | AL13: =IF(LEN($DQ$13)=0,"",IF($BV$13=3,INT($BU$13/3),"")) | AM13: =IF(OR(LEN($DQ$13)=0,$BV$13<2),"",IFERROR(INDEX($DT$88:$DT$112,MATCH($DQ$13&"|2",$N$88:$N$112,0))&"",IF($BL$13=1,IFERROR(INDEX('Dados'!$G$127:$G$138,MATCH($DT$13&"|2",'Dados'!$A$127:$A$138,0)),""),""))) | AN13: =IF(OR(LEN($DQ$13)=0,$BV$13<2),"",IFERROR(INDEX($DU$88:$DU$112,MATCH($DQ$13&"|2",$N$88:$N$112,0))&"",IF($BL$13=1,IFERROR(INDEX('Dados'!$H$127:$H$138,MATCH($DT$13&"|2",'Dados'!$A$127:$A$138,0)),""),""))) | AO13: =IF(OR(LEN($DQ$13)=0,$BV$13<2),"",IFERROR(INDEX($DV$88:$DV$112,MATCH($DQ$13&"|2",$N$88:$N$112,0))&"",IF($BL$13=1,IFERROR(INDEX('Dados'!$I$127:$I$138,MATCH($DT$13&"|2",'Dados'!$A$127:$A$138,0)),""),""))) | AP13: =IF(OR(LEN($DQ$13)=0,$BV$13<2),"",IFERROR(INDEX($DW$88:$DW$112,MATCH($DQ$13&"|2",$N$88:$N$112,0))&"",IF($BL$13=1,IFERROR(INDEX('Dados'!$J$127:$J$138,MATCH($DT$13&"|2",'Dados'!$A$127:$A$138,0)),""),""))) | AQ13: =IF(OR(LEN($DQ$13)=0,$BV$13<2),"",IF(ISNUMBER(MATCH($DQ$13&"|2",$N$88:$N$112,0)),IF(ISNUMBER(INDEX($DX$88:$DX$112,MATCH($DQ$13&"|2",$N$88:$N$112,0))),MIN(IFERROR(INDEX('Dados'!$G$38:$G$52,MATCH($BS$13,'Dados'!$A$38:$A$52,0)),""),INDEX($DX$88:$DX$112,MATCH($DQ$13&"|2",$N$88:$N$112,0))),IFERROR(INDEX('Dados'!$G$38:$G$52,MATCH($BS$13,'Dados'!$A$38:$A$52,0)),"")),IF($BL$13=1,IFERROR(MIN(IFERROR(INDEX('Dados'!$G$38:$G$52,MATCH($BS$13,'Dados'!$A$38:$A$52,0)),""),INT(INDEX('Dados'!$K$127:$K$138,MATCH($DT$13&"|2",'Dados'!$A$127:$A$138,0))*IFERROR(INDEX('Dados'!$G$38:$G$52,MATCH($BS$13,'Dados'!$A$38:$A$52,0)),"")/$CH$13)),IFERROR(INDEX('Dados'!$G$38:$G$52,MATCH($BS$13,'Dados'!$A$38:$A$52,0)),"")),IFERROR(INDEX('Dados'!$G$38:$G$52,MATCH($BS$13,'Dados'!$A$38:$A$52,0)),"")))) | AR13: =IF(OR(LEN($DQ$13)=0,$BV$13<3),"",IFERROR(INDEX($DT$88:$DT$112,MATCH($DQ$13&"|3",$N$88:$N$112,0))&"",IF($BL$13=1,IFERROR(INDEX('Dados'!$G$127:$G$138,MATCH($DT$13&"|3",'Dados'!$A$127:$A$138,0)),""),""))) | AS13: =IF(OR(LEN($DQ$13)=0,$BV$13<3),"",IFERROR(INDEX($DU$88:$DU$112,MATCH($DQ$13&"|3",$N$88:$N$112,0))&"",IF($BL$13=1,IFERROR(INDEX('Dados'!$H$127:$H$138,MATCH($DT$13&"|3",'Dados'!$A$127:$A$138,0)),""),""))) | AT13: =IF(OR(LEN($DQ$13)=0,$BV$13<3),"",IFERROR(INDEX($DV$88:$DV$112,MATCH($DQ$13&"|3",$N$88:$N$112,0))&"",IF($BL$13=1,IFERROR(INDEX('Dados'!$I$127:$I$138,MATCH($DT$13&"|3",'Dados'!$A$127:$A$138,0)),""),""))) | AU13: =IF(OR(LEN($DQ$13)=0,$BV$13<3),"",IFERROR(INDEX($DW$88:$DW$112,MATCH($DQ$13&"|3",$N$88:$N$112,0))&"",IF($BL$13=1,IFERROR(INDEX('Dados'!$J$127:$J$138,MATCH($DT$13&"|3",'Dados'!$A$127:$A$138,0)),""),""))) | AV13: =IF(OR(LEN($DQ$13)=0,$BV$13<3),"",IF(ISNUMBER(MATCH($DQ$13&"|3",$N$88:$N$112,0)),IF(ISNUMBER(INDEX($DX$88:$DX$112,MATCH($DQ$13&"|3",$N$88:$N$112,0))),MIN(IFERROR(INDEX('Dados'!$G$38:$G$52,MATCH($BS$13,'Dados'!$A$38:$A$52,0)),""),INDEX($DX$88:$DX$112,MATCH($DQ$13&"|3",$N$88:$N$112,0))),IFERROR(INDEX('Dados'!$G$38:$G$52,MATCH($BS$13,'Dados'!$A$38:$A$52,0)),"")),IF($BL$13=1,IFERROR(MIN(IFERROR(INDEX('Dados'!$G$38:$G$52,MATCH($BS$13,'Dados'!$A$38:$A$52,0)),""),INT(INDEX('Dados'!$K$127:$K$138,MATCH($DT$13&"|3",'Dados'!$A$127:$A$138,0))*IFERROR(INDEX('Dados'!$G$38:$G$52,MATCH($BS$13,'Dados'!$A$38:$A$52,0)),"")/$CH$13)),IFERROR(INDEX('Dados'!$G$38:$G$52,MATCH($BS$13,'Dados'!$A$38:$A$52,0)),"")),IFERROR(INDEX('Dados'!$G$38:$G$52,MATCH($BS$13,'Dados'!$A$38:$A$52,0)),"")))) | AW13: =IF(LEN($DQ$13)=0,"",IF($BL$13=1,IFERROR(INDEX('Dados'!$AF$92:$AF$123,$BM$13)&"",""),IFERROR(INDEX($DU$116:$DU$153,MATCH($DQ$13&"|1",$Q$116:$Q$153,0))&"",""))) | AX13: =IF(LEN($DQ$13)=0,"",IF($BL$13=1,IF(ISNUMBER(IFERROR(INDEX('Dados'!$AG$92:$AG$123,$BM$13),"")),IF(IFERROR(INDEX('Dados'!$AG$92:$AG$123,$BM$13),"")>0,IFERROR(INDEX('Dados'!$AG$92:$AG$123,$BM$13),""),""),""),IFERROR(INDEX($DY$116:$DY$153,MATCH($DQ$13&"|1",$Q$116:$Q$153,0))+0,""))) | AY13: =IF(LEN($DQ$13)=0,"",IF($BL$13=1,IFERROR(INDEX('Dados'!$AH$92:$AH$123,$BM$13)&"",""),IFERROR(INDEX($DU$116:$DU$153,MATCH($DQ$13&"|2",$Q$116:$Q$153,0))&"",""))) | AZ13: =IF(LEN($DQ$13)=0,"",IF($BL$13=1,IF(ISNUMBER(IFERROR(INDEX('Dados'!$AI$92:$AI$123,$BM$13),"")),IF(IFERROR(INDEX('Dados'!$AI$92:$AI$123,$BM$13),"")>0,IFERROR(INDEX('Dados'!$AI$92:$AI$123,$BM$13),""),""),""),IFERROR(INDEX($DY$116:$DY$153,MATCH($DQ$13&"|2",$Q$116:$Q$153,0))+0,""))) | BA13: =IF(LEN($DQ$13)=0,"",IF($BL$13=1,IFERROR(INDEX('Dados'!$AJ$92:$AJ$123,$BM$13)&"",""),IFERROR(INDEX($DU$116:$DU$153,MATCH($DQ$13&"|3",$Q$116:$Q$153,0))&"",""))) | BB13: =IF(LEN($DQ$13)=0,"",IF($BL$13=1,IF(ISNUMBER(IFERROR(INDEX('Dados'!$AK$92:$AK$123,$BM$13),"")),IF(IFERROR(INDEX('Dados'!$AK$92:$AK$123,$BM$13),"")>0,IFERROR(INDEX('Dados'!$AK$92:$AK$123,$BM$13),""),""),""),IFERROR(INDEX($DY$116:$DY$153,MATCH($DQ$13&"|3",$Q$116:$Q$153,0))+0,""))) | BC13: =IF(LEN($DQ$13)=0,"",IF(LEN($DR$28)>0,$DR$28,IF($BL$13=1,IFERROR(INDEX('Dados'!$E$92:$E$123,$BM$13)&"",""),""))) | BD13: =IF(AND(LEN($DR$28)=0,$BL$13=1),IFERROR(INDEX('Dados'!$AD$92:$AD$123,$BM$13)&"",""),"") | BE13: =IF(LEN($DQ$13)=0,"",INDEX('Dados'!$F$7:$F$11,$BR$13)) | BF13: =IF(LEN($DQ$13)=0,"",$BR$13) | BG13: =$G$44 | BH13: ="Campanha" | BK13: =IF(COUNTIF('Dados'!$AQ$6:$AQ$8,$DR$13)>0,$DR$13,"Faixa do livro") | BL13: =IF(AND($BK$13="Ajustar do bestiário",ISNUMBER($BM$13)),1,0) | BM13: =IFERROR(MATCH($DT$13,'Dados'!$B$92:$B$123,0),"") | BN13: =IF(COUNTIF('Dados'!$AO$6:$AO$8,$DY$13)>0,$DY$13,IF($BL$13=1,IFERROR(INDEX('Dados'!$C$92:$C$123,$BM$13),""),"Comum")) | BO13: =MATCH($BN$13,'Dados'!$AO$6:$AO$8,0) | BP13: =IF(ISNUMBER($DX$13),MIN(20,MAX(1,INT($DX$13))),'Campanha'!$B$17) | BQ13: =IF($BK$13="Por nível — Sugestão",INDEX('Dados'!$B$7:$B$11,INT(($BP$13-1)/4)+1),IF(LEN(IFERROR(INDEX('Dados'!$B$7:$B$11,MATCH($DW$13,'Dados'!$AP$6:$AP$10,0)),""))>0,IFERROR(INDEX('Dados'!$B$7:$B$11,MATCH($DW$13,'Dados'!$AP$6:$AP$10,0)),""),'Campanha'!$B$19)) | BR13: =MATCH($BQ$13,'Dados'!$B$7:$B$11,0) | BS13: =$BQ$13&"|"&$BN$13 | BT13: =MIN(4,MAX(1,INT(($BP$13-3)/4)+1)) | BU13: =IF($BK$13="Por nível — Sugestão",INT(IF($BP$13<=3,INDEX('Dados'!$D$38:$D$52,$BO$13),IF($BP$13>=19,INDEX('Dados'!$D$38:$D$52,12+$BO$13),INDEX('Dados'!$D$38:$D$52,($BT$13-1)*3+$BO$13)+(INDEX('Dados'!$D$38:$D$52,$BT$13*3+$BO$13)-INDEX('Dados'!$D$38:$D$52,($BT$13-1)*3+$BO$13))*($BP$13-(4*$BT$13-1))/4))),IFERROR(INDEX('Dados'!$D$38:$D$52,MATCH($BS$13,'Dados'!$A$38:$A$52,0)),"")) | BV13: =IF($BN$13<>"Boss",1,IF(AND(ISNUMBER($DZ$13),$DZ$13>=1,$DZ$13<=3),INT($DZ$13),IF($BL$13=1,MAX(1,IFERROR(INDEX('Dados'!$F$92:$F$123,$BM$13),"")),1))) | BW13: =IFERROR(INDEX('Dados'!$O$38:$O$52,MATCH($BS$13,'Dados'!$A$38:$A$52,0)),"") | BX13: =IF(AND(LEN($DR$44)=0,LEN($DS$44)=0,LEN($DT$44)=0,LEN($DU$44)=0),1,0) | BY13: =IF(LEN($DQ$13)=0,"",IF($BX$13=0,$DR$44&"",IF($BL$13=1,IFERROR(INDEX('Dados'!$Q$92:$Q$123,$BM$13)&"",""),IF(1<=$BW$13,$CD$13,"")))) | BZ13: =IF(LEN($DQ$13)=0,"",IF($BX$13=0,$DS$44&"",IF($BL$13=1,IFERROR(INDEX('Dados'!$R$92:$R$123,$BM$13)&"",""),IF(2<=$BW$13,$CE$13,"")))) | CA13: =IF(LEN($DQ$13)=0,"",IF($BX$13=0,$DT$44&"",IF($BL$13=1,IFERROR(INDEX('Dados'!$S$92:$S$123,$BM$13)&"",""),IF(3<=$BW$13,$CF$13,"")))) | CB13: =IF(LEN($DQ$13)=0,"",IF($BX$13=0,$DU$44&"",IF($BL$13=1,IFERROR(INDEX('Dados'!$T$92:$T$123,$BM$13)&"",""),IF(4<=$BW$13,$CG$13,"")))) | CC13: =IF(LEN($DV$44)>0,$DV$44,IF($BL$13=1,IFERROR(INDEX('Dados'!$U$92:$U$123,$BM$13)&"",""),"")) | CD13: =INDEX('Dados'!$A$301:$A$307,MATCH(SMALL($DI$13:$DO$13,1),$DI$13:$DO$13,0)) | CE13: =INDEX('Dados'!$A$301:$A$307,MATCH(SMALL($DI$13:$DO$13,2),$DI$13:$DO$13,0)) | CF13: =INDEX('Dados'!$A$301:$A$307,MATCH(SMALL($DI$13:$DO$13,3),$DI$13:$DO$13,0)) | CG13: =INDEX('Dados'!$A$301:$A$307,MATCH(SMALL($DI$13:$DO$13,4),$DI$13:$DO$13,0)) | CH13: =IF($BL$13=1,IFERROR(INDEX('Dados'!$J$92:$J$123,$BM$13),""),"") | CI13: =IF($BL$13=1,IFERROR(INDEX('Dados'!$G$92:$G$123,$BM$13),""),"") | CJ13: =IFERROR(INDEX('Dados'!$S$38:$S$52,MATCH($BS$13,'Dados'!$A$38:$A$52,0)),"") | CK13: =IFERROR(INDEX('Dados'!$T$38:$T$52,MATCH($BS$13,'Dados'!$A$38:$A$52,0)),"") | CL13: =IFERROR(INDEX('Dados'!$J$38:$J$52,MATCH($BQ$13&"|Comum",'Dados'!$A$38:$A$52,0)),"") | CM13: =IFERROR(INDEX('Dados'!$K$38:$K$52,MATCH($BQ$13&"|Comum",'Dados'!$A$38:$A$52,0)),"") | CN13: =MOD(MOD(MOD((MOD('Início'!$E$15+104729*$C$7+41162069,2147483646)+1)*16807,2147483647)*16807,2147483647)*16807,2147483647) | CO13: =MOD(MOD(MOD((MOD(MOD(INT($CN$13/65536)*$CN$13,2147483647)*65536+MOD($CN$13,65536)*$CN$13,2147483647))*16807,2147483647)*16807,2147483647)*16807,2147483647) | CP13: =MOD(MOD(MOD((MOD($CO$13+INT($CO$13/65536)*MOD($CO$13,65536),2147483646)+1)*16807,2147483647)*16807,2147483647)*16807,2147483647) | CQ13: =MOD(MOD(MOD((MOD('Início'!$E$15+104729*$C$7+42461778,2147483646)+1)*16807,2147483647)*16807,2147483647)*16807,2147483647) | CR13: =MOD(MOD(MOD((MOD(MOD(INT($CQ$13/65536)*$CQ$13,2147483647)*65536+MOD($CQ$13,65536)*$CQ$13,2147483647))*16807,2147483647)*16807,2147483647)*16807,2147483647) | CS13: =MOD(MOD(MOD((MOD($CR$13+INT($CR$13/65536)*MOD($CR$13,65536),2147483646)+1)*16807,2147483647)*16807,2147483647)*16807,2147483647) | CT13: =MOD(MOD(MOD((MOD('Início'!$E$15+104729*$C$7+43761487,2147483646)+1)*16807,2147483647)*16807,2147483647)*16807,2147483647) | CU13: =MOD(MOD(MOD((MOD(MOD(INT($CT$13/65536)*$CT$13,2147483647)*65536+MOD($CT$13,65536)*$CT$13,2147483647))*16807,2147483647)*16807,2147483647)*16807,2147483647) | CV13: =MOD(MOD(MOD((MOD($CU$13+INT($CU$13/65536)*MOD($CU$13,65536),2147483646)+1)*16807,2147483647)*16807,2147483647)*16807,2147483647) | CW13: =MOD(MOD(MOD((MOD('Início'!$E$15+104729*$C$7+45061196,2147483646)+1)*16807,2147483647)*16807,2147483647)*16807,2147483647) | CX13: =MOD(MOD(MOD((MOD(MOD(INT($CW$13/65536)*$CW$13,2147483647)*65536+MOD($CW$13,65536)*$CW$13,2147483647))*16807,2147483647)*16807,2147483647)*16807,2147483647) | CY13: =MOD(MOD(MOD((MOD($CX$13+INT($CX$13/65536)*MOD($CX$13,65536),2147483646)+1)*16807,2147483647)*16807,2147483647)*16807,2147483647) | CZ13: =MOD(MOD(MOD((MOD('Início'!$E$15+104729*$C$7+46360905,2147483646)+1)*16807,2147483647)*16807,2147483647)*16807,2147483647) | DA13: =MOD(MOD(MOD((MOD(MOD(INT($CZ$13/65536)*$CZ$13,2147483647)*65536+MOD($CZ$13,65536)*$CZ$13,2147483647))*16807,2147483647)*16807,2147483647)*16807,2147483647) | DB13: =MOD(MOD(MOD((MOD($DA$13+INT($DA$13/65536)*MOD($DA$13,65536),2147483646)+1)*16807,2147483647)*16807,2147483647)*16807,2147483647) | DC13: =MOD(MOD(MOD((MOD('Início'!$E$15+104729*$C$7+47660614,2147483646)+1)*16807,2147483647)*16807,2147483647)*16807,2147483647) | DD13: =MOD(MOD(MOD((MOD(MOD(INT($DC$13/65536)*$DC$13,2147483647)*65536+MOD($DC$13,65536)*$DC$13,2147483647))*16807,2147483647)*16807,2147483647)*16807,2147483647) | DE13: =MOD(MOD(MOD((MOD($DD$13+INT($DD$13/65536)*MOD($DD$13,65536),2147483646)+1)*16807,2147483647)*16807,2147483647)*16807,2147483647) | DF13: =MOD(MOD(MOD((MOD('Início'!$E$15+104729*$C$7+48960323,2147483646)+1)*16807,2147483647)*16807,2147483647)*16807,2147483647) | DG13: =MOD(MOD(MOD((MOD(MOD(INT($DF$13/65536)*$DF$13,2147483647)*65536+MOD($DF$13,65536)*$DF$13,2147483647))*16807,2147483647)*16807,2147483647)*16807,2147483647) | DH13: =MOD(MOD(MOD((MOD($DG$13+INT($DG$13/65536)*MOD($DG$13,65536),2147483646)+1)*16807,2147483647)*16807,2147483647)*16807,2147483647) | DI13: =IF($CC$13="Físico",9000000000,IF(AND('Grupo'!$B$44="Sim",COUNTIF($BY$11:$CB$12,"Físico")=0),0,2147483647))+$CP$13+1/10 | DJ13: =IF($CC$13="Fogo",9000000000,IF(AND('Grupo'!$C$44="Sim",COUNTIF($BY$11:$CB$12,"Fogo")=0),0,2147483647))+$CS$13+2/10 | DK13: =IF($CC$13="Gelo",9000000000,IF(AND('Grupo'!$D$44="Sim",COUNTIF($BY$11:$CB$12,"Gelo")=0),0,2147483647))+$CV$13+3/10 | DL13: =IF($CC$13="Raio",9000000000,IF(AND('Grupo'!$E$44="Sim",COUNTIF($BY$11:$CB$12,"Raio")=0),0,2147483647))+$CY$13+4/10 | DM13: =IF($CC$13="Vento",9000000000,IF(AND('Grupo'!$F$44="Sim",COUNTIF($BY$11:$CB$12,"Vento")=0),0,2147483647))+$DB$13+5/10 | DN13: =IF($CC$13="Quântico",9000000000,IF(AND('Grupo'!$G$44="Sim",COUNTIF($BY$11:$CB$12,"Quântico")=0),0,2147483647))+$DE$13+6/10 | DO13: =IF($CC$13="Imaginário",9000000000,IF(AND('Grupo'!$H$44="Sim",COUNTIF($BY$11:$CB$12,"Imaginário")=0),0,2147483647))+$DH$13+7/10 | DQ13: =IF(ISERROR($A$13),"",IF(ISBLANK($A$13),"",$A$13)) | DR13: =IF(ISERROR($B$13),"",IF(ISBLANK($B$13),"",$B$13)) | DT13: =IF(ISERROR($D$13),"",IF(ISBLANK($D$13),"",$D$13)) | DW13: =IF(ISERROR($G$13),"",IF(ISBLANK($G$13),"",$G$13)) | DX13: =IF(ISERROR($H$13),"",IF(ISBLANK($H$13),"",$H$13)) | DY13: =IF(ISERROR($I$13),"",IF(ISBLANK($I$13),"",$I$13)) | DZ13: =IF(ISERROR($J$13),"",IF(ISBLANK($J$13),"",$J$13)) | EA13: =ISERROR($A$13)*1+ISERROR($B$13)*1+ISERROR($D$13)*1+ISERROR($G$13)*1+ISERROR($H$13)*1+ISERROR($I$13)*1+ISERROR($J$13)*1
K14: =IF(EA14>0,"O Google leu como fórmula: escolha de novo ou digite com ' na frente.",IF(LEN($DQ$14)=0,IF(LEN($DR$14&$DT$14&$DY$14)>0,"Linha sem nome: o inimigo não entra nas listas",""),IF(COUNTIF($DQ$11:$DQ$22,$DQ$14)>1,"Nome repetido na tabela",IF(COUNTIF('Dados'!$B$92:$B$123,$DQ$14)>0,"Nome igual a uma criatura do bestiário: dê outro nome",IF(AND($BK$14="Ajustar do bestiário",$BL$14=0),"Modo Ajustar sem base do bestiário válida",IF(AND(LEN($DZ$14)>0,$BN$14<>"Boss"),"Fases só valem para Boss (28.5)",IF(AND(ISNUMBER($DX$14),OR($DX$14<1,$DX$14>20)),"Nível fora de 1 a 20: usando o limite",IF(AND(LEN($DY$14)>0,COUNTIF('Dados'!$AO$6:$AO$8,$DY$14)=0),"Tipo fora da lista: usando Comum","")))))))) | N14: =IF(LEN($DQ$14)=0,"",$DQ$14) | O14: =IF(LEN($DQ$14)=0,"",$BN$14) | P14: =IF(LEN($DQ$14)=0,"",$BQ$14) | Q14: =IF(LEN($DQ$14)=0,"",$BU$14) | R14: =IF(LEN($DQ$14)=0,"",IFERROR(INDEX('Dados'!$E$38:$E$52,MATCH($BS$14,'Dados'!$A$38:$A$52,0)),"")) | S14: =IF(LEN($DQ$14)=0,"",IFERROR(INDEX('Dados'!$F$38:$F$52,MATCH($BS$14,'Dados'!$A$38:$A$52,0)),"")) | T14: =IF(LEN($DQ$14)=0,"",IFERROR(INDEX('Dados'!$G$38:$G$52,MATCH($BS$14,'Dados'!$A$38:$A$52,0)),"")) | U14: =IF(LEN($DQ$14)=0,"",IFERROR(INDEX('Dados'!$H$38:$H$52,MATCH($BS$14,'Dados'!$A$38:$A$52,0)),"")) | V14: =IF(LEN($DQ$14)=0,"",IFERROR(INDEX('Dados'!$I$38:$I$52,MATCH($BS$14,'Dados'!$A$38:$A$52,0)),"")) | W14: =IF(LEN($DQ$14)=0,"",IFERROR(INDEX('Dados'!$J$38:$J$52,MATCH($BS$14,'Dados'!$A$38:$A$52,0)),"")) | X14: =IF(LEN($DQ$14)=0,"",IFERROR(INDEX('Dados'!$K$38:$K$52,MATCH($BS$14,'Dados'!$A$38:$A$52,0)),"")) | Y14: =IF(LEN($DQ$14)=0,"",IFERROR(INDEX('Dados'!$L$38:$L$52,MATCH($BS$14,'Dados'!$A$38:$A$52,0)),"")) | Z14: =IF(LEN($DQ$14)=0,"",IFERROR(INDEX('Dados'!$M$38:$M$52,MATCH($BS$14,'Dados'!$A$38:$A$52,0)),"")) | AA14: =IF(LEN($DQ$14)=0,"",$BY$14) | AB14: =IF(LEN($DQ$14)=0,"",$BZ$14) | AC14: =IF(LEN($DQ$14)=0,"",$CA$14) | AD14: =IF(LEN($DQ$14)=0,"",$CB$14) | AE14: =IF(LEN($DQ$14)=0,"",$CC$14) | AF14: =IF(LEN($DQ$14)=0,"",IF($DV$29="Sim","Pode",IF($DV$29="Não","Não",IF($BL$14=1,IFERROR(INDEX('Dados'!$V$92:$V$123,$BM$14)&"",""),"Não declarado")))) | AG14: =IF(LEN($DQ$14)=0,"",$BV$14) | AH14: =IF(LEN($DQ$14)=0,"",IFERROR(INDEX('Dados'!$Q$38:$Q$52,MATCH($BS$14,'Dados'!$A$38:$A$52,0)),"")) | AI14: =IF(LEN($DQ$14)=0,"",IF(AND($BL$14=1,$DT$14="Escória de Stellaron"),1.5,1)*$BU$14) | AJ14: =IF(LEN($DQ$14)=0,"",IFERROR(INDEX('Dados'!$P$38:$P$52,MATCH($BS$14,'Dados'!$A$38:$A$52,0)),"")) | AK14: =IF(LEN($DQ$14)=0,"",IF($BV$14=2,INT($BU$14/2),IF($BV$14=3,INT(2*$BU$14/3),""))) | AL14: =IF(LEN($DQ$14)=0,"",IF($BV$14=3,INT($BU$14/3),"")) | AM14: =IF(OR(LEN($DQ$14)=0,$BV$14<2),"",IFERROR(INDEX($DT$88:$DT$112,MATCH($DQ$14&"|2",$N$88:$N$112,0))&"",IF($BL$14=1,IFERROR(INDEX('Dados'!$G$127:$G$138,MATCH($DT$14&"|2",'Dados'!$A$127:$A$138,0)),""),""))) | AN14: =IF(OR(LEN($DQ$14)=0,$BV$14<2),"",IFERROR(INDEX($DU$88:$DU$112,MATCH($DQ$14&"|2",$N$88:$N$112,0))&"",IF($BL$14=1,IFERROR(INDEX('Dados'!$H$127:$H$138,MATCH($DT$14&"|2",'Dados'!$A$127:$A$138,0)),""),""))) | AO14: =IF(OR(LEN($DQ$14)=0,$BV$14<2),"",IFERROR(INDEX($DV$88:$DV$112,MATCH($DQ$14&"|2",$N$88:$N$112,0))&"",IF($BL$14=1,IFERROR(INDEX('Dados'!$I$127:$I$138,MATCH($DT$14&"|2",'Dados'!$A$127:$A$138,0)),""),""))) | AP14: =IF(OR(LEN($DQ$14)=0,$BV$14<2),"",IFERROR(INDEX($DW$88:$DW$112,MATCH($DQ$14&"|2",$N$88:$N$112,0))&"",IF($BL$14=1,IFERROR(INDEX('Dados'!$J$127:$J$138,MATCH($DT$14&"|2",'Dados'!$A$127:$A$138,0)),""),""))) | AQ14: =IF(OR(LEN($DQ$14)=0,$BV$14<2),"",IF(ISNUMBER(MATCH($DQ$14&"|2",$N$88:$N$112,0)),IF(ISNUMBER(INDEX($DX$88:$DX$112,MATCH($DQ$14&"|2",$N$88:$N$112,0))),MIN(IFERROR(INDEX('Dados'!$G$38:$G$52,MATCH($BS$14,'Dados'!$A$38:$A$52,0)),""),INDEX($DX$88:$DX$112,MATCH($DQ$14&"|2",$N$88:$N$112,0))),IFERROR(INDEX('Dados'!$G$38:$G$52,MATCH($BS$14,'Dados'!$A$38:$A$52,0)),"")),IF($BL$14=1,IFERROR(MIN(IFERROR(INDEX('Dados'!$G$38:$G$52,MATCH($BS$14,'Dados'!$A$38:$A$52,0)),""),INT(INDEX('Dados'!$K$127:$K$138,MATCH($DT$14&"|2",'Dados'!$A$127:$A$138,0))*IFERROR(INDEX('Dados'!$G$38:$G$52,MATCH($BS$14,'Dados'!$A$38:$A$52,0)),"")/$CH$14)),IFERROR(INDEX('Dados'!$G$38:$G$52,MATCH($BS$14,'Dados'!$A$38:$A$52,0)),"")),IFERROR(INDEX('Dados'!$G$38:$G$52,MATCH($BS$14,'Dados'!$A$38:$A$52,0)),"")))) | AR14: =IF(OR(LEN($DQ$14)=0,$BV$14<3),"",IFERROR(INDEX($DT$88:$DT$112,MATCH($DQ$14&"|3",$N$88:$N$112,0))&"",IF($BL$14=1,IFERROR(INDEX('Dados'!$G$127:$G$138,MATCH($DT$14&"|3",'Dados'!$A$127:$A$138,0)),""),""))) | AS14: =IF(OR(LEN($DQ$14)=0,$BV$14<3),"",IFERROR(INDEX($DU$88:$DU$112,MATCH($DQ$14&"|3",$N$88:$N$112,0))&"",IF($BL$14=1,IFERROR(INDEX('Dados'!$H$127:$H$138,MATCH($DT$14&"|3",'Dados'!$A$127:$A$138,0)),""),""))) | AT14: =IF(OR(LEN($DQ$14)=0,$BV$14<3),"",IFERROR(INDEX($DV$88:$DV$112,MATCH($DQ$14&"|3",$N$88:$N$112,0))&"",IF($BL$14=1,IFERROR(INDEX('Dados'!$I$127:$I$138,MATCH($DT$14&"|3",'Dados'!$A$127:$A$138,0)),""),""))) | AU14: =IF(OR(LEN($DQ$14)=0,$BV$14<3),"",IFERROR(INDEX($DW$88:$DW$112,MATCH($DQ$14&"|3",$N$88:$N$112,0))&"",IF($BL$14=1,IFERROR(INDEX('Dados'!$J$127:$J$138,MATCH($DT$14&"|3",'Dados'!$A$127:$A$138,0)),""),""))) | AV14: =IF(OR(LEN($DQ$14)=0,$BV$14<3),"",IF(ISNUMBER(MATCH($DQ$14&"|3",$N$88:$N$112,0)),IF(ISNUMBER(INDEX($DX$88:$DX$112,MATCH($DQ$14&"|3",$N$88:$N$112,0))),MIN(IFERROR(INDEX('Dados'!$G$38:$G$52,MATCH($BS$14,'Dados'!$A$38:$A$52,0)),""),INDEX($DX$88:$DX$112,MATCH($DQ$14&"|3",$N$88:$N$112,0))),IFERROR(INDEX('Dados'!$G$38:$G$52,MATCH($BS$14,'Dados'!$A$38:$A$52,0)),"")),IF($BL$14=1,IFERROR(MIN(IFERROR(INDEX('Dados'!$G$38:$G$52,MATCH($BS$14,'Dados'!$A$38:$A$52,0)),""),INT(INDEX('Dados'!$K$127:$K$138,MATCH($DT$14&"|3",'Dados'!$A$127:$A$138,0))*IFERROR(INDEX('Dados'!$G$38:$G$52,MATCH($BS$14,'Dados'!$A$38:$A$52,0)),"")/$CH$14)),IFERROR(INDEX('Dados'!$G$38:$G$52,MATCH($BS$14,'Dados'!$A$38:$A$52,0)),"")),IFERROR(INDEX('Dados'!$G$38:$G$52,MATCH($BS$14,'Dados'!$A$38:$A$52,0)),"")))) | AW14: =IF(LEN($DQ$14)=0,"",IF($BL$14=1,IFERROR(INDEX('Dados'!$AF$92:$AF$123,$BM$14)&"",""),IFERROR(INDEX($DU$116:$DU$153,MATCH($DQ$14&"|1",$Q$116:$Q$153,0))&"",""))) | AX14: =IF(LEN($DQ$14)=0,"",IF($BL$14=1,IF(ISNUMBER(IFERROR(INDEX('Dados'!$AG$92:$AG$123,$BM$14),"")),IF(IFERROR(INDEX('Dados'!$AG$92:$AG$123,$BM$14),"")>0,IFERROR(INDEX('Dados'!$AG$92:$AG$123,$BM$14),""),""),""),IFERROR(INDEX($DY$116:$DY$153,MATCH($DQ$14&"|1",$Q$116:$Q$153,0))+0,""))) | AY14: =IF(LEN($DQ$14)=0,"",IF($BL$14=1,IFERROR(INDEX('Dados'!$AH$92:$AH$123,$BM$14)&"",""),IFERROR(INDEX($DU$116:$DU$153,MATCH($DQ$14&"|2",$Q$116:$Q$153,0))&"",""))) | AZ14: =IF(LEN($DQ$14)=0,"",IF($BL$14=1,IF(ISNUMBER(IFERROR(INDEX('Dados'!$AI$92:$AI$123,$BM$14),"")),IF(IFERROR(INDEX('Dados'!$AI$92:$AI$123,$BM$14),"")>0,IFERROR(INDEX('Dados'!$AI$92:$AI$123,$BM$14),""),""),""),IFERROR(INDEX($DY$116:$DY$153,MATCH($DQ$14&"|2",$Q$116:$Q$153,0))+0,""))) | BA14: =IF(LEN($DQ$14)=0,"",IF($BL$14=1,IFERROR(INDEX('Dados'!$AJ$92:$AJ$123,$BM$14)&"",""),IFERROR(INDEX($DU$116:$DU$153,MATCH($DQ$14&"|3",$Q$116:$Q$153,0))&"",""))) | BB14: =IF(LEN($DQ$14)=0,"",IF($BL$14=1,IF(ISNUMBER(IFERROR(INDEX('Dados'!$AK$92:$AK$123,$BM$14),"")),IF(IFERROR(INDEX('Dados'!$AK$92:$AK$123,$BM$14),"")>0,IFERROR(INDEX('Dados'!$AK$92:$AK$123,$BM$14),""),""),""),IFERROR(INDEX($DY$116:$DY$153,MATCH($DQ$14&"|3",$Q$116:$Q$153,0))+0,""))) | BC14: =IF(LEN($DQ$14)=0,"",IF(LEN($DR$29)>0,$DR$29,IF($BL$14=1,IFERROR(INDEX('Dados'!$E$92:$E$123,$BM$14)&"",""),""))) | BD14: =IF(AND(LEN($DR$29)=0,$BL$14=1),IFERROR(INDEX('Dados'!$AD$92:$AD$123,$BM$14)&"",""),"") | BE14: =IF(LEN($DQ$14)=0,"",INDEX('Dados'!$F$7:$F$11,$BR$14)) | BF14: =IF(LEN($DQ$14)=0,"",$BR$14) | BG14: =$G$45 | BH14: ="Campanha" | BK14: =IF(COUNTIF('Dados'!$AQ$6:$AQ$8,$DR$14)>0,$DR$14,"Faixa do livro") | BL14: =IF(AND($BK$14="Ajustar do bestiário",ISNUMBER($BM$14)),1,0) | BM14: =IFERROR(MATCH($DT$14,'Dados'!$B$92:$B$123,0),"") | BN14: =IF(COUNTIF('Dados'!$AO$6:$AO$8,$DY$14)>0,$DY$14,IF($BL$14=1,IFERROR(INDEX('Dados'!$C$92:$C$123,$BM$14),""),"Comum")) | BO14: =MATCH($BN$14,'Dados'!$AO$6:$AO$8,0) | BP14: =IF(ISNUMBER($DX$14),MIN(20,MAX(1,INT($DX$14))),'Campanha'!$B$17) | BQ14: =IF($BK$14="Por nível — Sugestão",INDEX('Dados'!$B$7:$B$11,INT(($BP$14-1)/4)+1),IF(LEN(IFERROR(INDEX('Dados'!$B$7:$B$11,MATCH($DW$14,'Dados'!$AP$6:$AP$10,0)),""))>0,IFERROR(INDEX('Dados'!$B$7:$B$11,MATCH($DW$14,'Dados'!$AP$6:$AP$10,0)),""),'Campanha'!$B$19)) | BR14: =MATCH($BQ$14,'Dados'!$B$7:$B$11,0) | BS14: =$BQ$14&"|"&$BN$14 | BT14: =MIN(4,MAX(1,INT(($BP$14-3)/4)+1)) | BU14: =IF($BK$14="Por nível — Sugestão",INT(IF($BP$14<=3,INDEX('Dados'!$D$38:$D$52,$BO$14),IF($BP$14>=19,INDEX('Dados'!$D$38:$D$52,12+$BO$14),INDEX('Dados'!$D$38:$D$52,($BT$14-1)*3+$BO$14)+(INDEX('Dados'!$D$38:$D$52,$BT$14*3+$BO$14)-INDEX('Dados'!$D$38:$D$52,($BT$14-1)*3+$BO$14))*($BP$14-(4*$BT$14-1))/4))),IFERROR(INDEX('Dados'!$D$38:$D$52,MATCH($BS$14,'Dados'!$A$38:$A$52,0)),"")) | BV14: =IF($BN$14<>"Boss",1,IF(AND(ISNUMBER($DZ$14),$DZ$14>=1,$DZ$14<=3),INT($DZ$14),IF($BL$14=1,MAX(1,IFERROR(INDEX('Dados'!$F$92:$F$123,$BM$14),"")),1))) | BW14: =IFERROR(INDEX('Dados'!$O$38:$O$52,MATCH($BS$14,'Dados'!$A$38:$A$52,0)),"") | BX14: =IF(AND(LEN($DR$45)=0,LEN($DS$45)=0,LEN($DT$45)=0,LEN($DU$45)=0),1,0) | BY14: =IF(LEN($DQ$14)=0,"",IF($BX$14=0,$DR$45&"",IF($BL$14=1,IFERROR(INDEX('Dados'!$Q$92:$Q$123,$BM$14)&"",""),IF(1<=$BW$14,$CD$14,"")))) | BZ14: =IF(LEN($DQ$14)=0,"",IF($BX$14=0,$DS$45&"",IF($BL$14=1,IFERROR(INDEX('Dados'!$R$92:$R$123,$BM$14)&"",""),IF(2<=$BW$14,$CE$14,"")))) | CA14: =IF(LEN($DQ$14)=0,"",IF($BX$14=0,$DT$45&"",IF($BL$14=1,IFERROR(INDEX('Dados'!$S$92:$S$123,$BM$14)&"",""),IF(3<=$BW$14,$CF$14,"")))) | CB14: =IF(LEN($DQ$14)=0,"",IF($BX$14=0,$DU$45&"",IF($BL$14=1,IFERROR(INDEX('Dados'!$T$92:$T$123,$BM$14)&"",""),IF(4<=$BW$14,$CG$14,"")))) | CC14: =IF(LEN($DV$45)>0,$DV$45,IF($BL$14=1,IFERROR(INDEX('Dados'!$U$92:$U$123,$BM$14)&"",""),"")) | CD14: =INDEX('Dados'!$A$301:$A$307,MATCH(SMALL($DI$14:$DO$14,1),$DI$14:$DO$14,0)) | CE14: =INDEX('Dados'!$A$301:$A$307,MATCH(SMALL($DI$14:$DO$14,2),$DI$14:$DO$14,0)) | CF14: =INDEX('Dados'!$A$301:$A$307,MATCH(SMALL($DI$14:$DO$14,3),$DI$14:$DO$14,0)) | CG14: =INDEX('Dados'!$A$301:$A$307,MATCH(SMALL($DI$14:$DO$14,4),$DI$14:$DO$14,0)) | CH14: =IF($BL$14=1,IFERROR(INDEX('Dados'!$J$92:$J$123,$BM$14),""),"") | CI14: =IF($BL$14=1,IFERROR(INDEX('Dados'!$G$92:$G$123,$BM$14),""),"") | CJ14: =IFERROR(INDEX('Dados'!$S$38:$S$52,MATCH($BS$14,'Dados'!$A$38:$A$52,0)),"") | CK14: =IFERROR(INDEX('Dados'!$T$38:$T$52,MATCH($BS$14,'Dados'!$A$38:$A$52,0)),"") | CL14: =IFERROR(INDEX('Dados'!$J$38:$J$52,MATCH($BQ$14&"|Comum",'Dados'!$A$38:$A$52,0)),"") | CM14: =IFERROR(INDEX('Dados'!$K$38:$K$52,MATCH($BQ$14&"|Comum",'Dados'!$A$38:$A$52,0)),"") | CN14: =MOD(MOD(MOD((MOD('Início'!$E$15+104729*$C$7+54159159,2147483646)+1)*16807,2147483647)*16807,2147483647)*16807,2147483647) | CO14: =MOD(MOD(MOD((MOD(MOD(INT($CN$14/65536)*$CN$14,2147483647)*65536+MOD($CN$14,65536)*$CN$14,2147483647))*16807,2147483647)*16807,2147483647)*16807,2147483647) | CP14: =MOD(MOD(MOD((MOD($CO$14+INT($CO$14/65536)*MOD($CO$14,65536),2147483646)+1)*16807,2147483647)*16807,2147483647)*16807,2147483647) | CQ14: =MOD(MOD(MOD((MOD('Início'!$E$15+104729*$C$7+55458868,2147483646)+1)*16807,2147483647)*16807,2147483647)*16807,2147483647) | CR14: =MOD(MOD(MOD((MOD(MOD(INT($CQ$14/65536)*$CQ$14,2147483647)*65536+MOD($CQ$14,65536)*$CQ$14,2147483647))*16807,2147483647)*16807,2147483647)*16807,2147483647) | CS14: =MOD(MOD(MOD((MOD($CR$14+INT($CR$14/65536)*MOD($CR$14,65536),2147483646)+1)*16807,2147483647)*16807,2147483647)*16807,2147483647) | CT14: =MOD(MOD(MOD((MOD('Início'!$E$15+104729*$C$7+56758577,2147483646)+1)*16807,2147483647)*16807,2147483647)*16807,2147483647) | CU14: =MOD(MOD(MOD((MOD(MOD(INT($CT$14/65536)*$CT$14,2147483647)*65536+MOD($CT$14,65536)*$CT$14,2147483647))*16807,2147483647)*16807,2147483647)*16807,2147483647) | CV14: =MOD(MOD(MOD((MOD($CU$14+INT($CU$14/65536)*MOD($CU$14,65536),2147483646)+1)*16807,2147483647)*16807,2147483647)*16807,2147483647) | CW14: =MOD(MOD(MOD((MOD('Início'!$E$15+104729*$C$7+58058286,2147483646)+1)*16807,2147483647)*16807,2147483647)*16807,2147483647) | CX14: =MOD(MOD(MOD((MOD(MOD(INT($CW$14/65536)*$CW$14,2147483647)*65536+MOD($CW$14,65536)*$CW$14,2147483647))*16807,2147483647)*16807,2147483647)*16807,2147483647) | CY14: =MOD(MOD(MOD((MOD($CX$14+INT($CX$14/65536)*MOD($CX$14,65536),2147483646)+1)*16807,2147483647)*16807,2147483647)*16807,2147483647) | CZ14: =MOD(MOD(MOD((MOD('Início'!$E$15+104729*$C$7+59357995,2147483646)+1)*16807,2147483647)*16807,2147483647)*16807,2147483647) | DA14: =MOD(MOD(MOD((MOD(MOD(INT($CZ$14/65536)*$CZ$14,2147483647)*65536+MOD($CZ$14,65536)*$CZ$14,2147483647))*16807,2147483647)*16807,2147483647)*16807,2147483647) | DB14: =MOD(MOD(MOD((MOD($DA$14+INT($DA$14/65536)*MOD($DA$14,65536),2147483646)+1)*16807,2147483647)*16807,2147483647)*16807,2147483647) | DC14: =MOD(MOD(MOD((MOD('Início'!$E$15+104729*$C$7+60657704,2147483646)+1)*16807,2147483647)*16807,2147483647)*16807,2147483647) | DD14: =MOD(MOD(MOD((MOD(MOD(INT($DC$14/65536)*$DC$14,2147483647)*65536+MOD($DC$14,65536)*$DC$14,2147483647))*16807,2147483647)*16807,2147483647)*16807,2147483647) | DE14: =MOD(MOD(MOD((MOD($DD$14+INT($DD$14/65536)*MOD($DD$14,65536),2147483646)+1)*16807,2147483647)*16807,2147483647)*16807,2147483647) | DF14: =MOD(MOD(MOD((MOD('Início'!$E$15+104729*$C$7+61957413,2147483646)+1)*16807,2147483647)*16807,2147483647)*16807,2147483647) | DG14: =MOD(MOD(MOD((MOD(MOD(INT($DF$14/65536)*$DF$14,2147483647)*65536+MOD($DF$14,65536)*$DF$14,2147483647))*16807,2147483647)*16807,2147483647)*16807,2147483647) | DH14: =MOD(MOD(MOD((MOD($DG$14+INT($DG$14/65536)*MOD($DG$14,65536),2147483646)+1)*16807,2147483647)*16807,2147483647)*16807,2147483647) | DI14: =IF($CC$14="Físico",9000000000,IF(AND('Grupo'!$B$44="Sim",COUNTIF($BY$11:$CB$13,"Físico")=0),0,2147483647))+$CP$14+1/10 | DJ14: =IF($CC$14="Fogo",9000000000,IF(AND('Grupo'!$C$44="Sim",COUNTIF($BY$11:$CB$13,"Fogo")=0),0,2147483647))+$CS$14+2/10 | DK14: =IF($CC$14="Gelo",9000000000,IF(AND('Grupo'!$D$44="Sim",COUNTIF($BY$11:$CB$13,"Gelo")=0),0,2147483647))+$CV$14+3/10 | DL14: =IF($CC$14="Raio",9000000000,IF(AND('Grupo'!$E$44="Sim",COUNTIF($BY$11:$CB$13,"Raio")=0),0,2147483647))+$CY$14+4/10 | DM14: =IF($CC$14="Vento",9000000000,IF(AND('Grupo'!$F$44="Sim",COUNTIF($BY$11:$CB$13,"Vento")=0),0,2147483647))+$DB$14+5/10 | DN14: =IF($CC$14="Quântico",9000000000,IF(AND('Grupo'!$G$44="Sim",COUNTIF($BY$11:$CB$13,"Quântico")=0),0,2147483647))+$DE$14+6/10 | DO14: =IF($CC$14="Imaginário",9000000000,IF(AND('Grupo'!$H$44="Sim",COUNTIF($BY$11:$CB$13,"Imaginário")=0),0,2147483647))+$DH$14+7/10 | DQ14: =IF(ISERROR($A$14),"",IF(ISBLANK($A$14),"",$A$14)) | DR14: =IF(ISERROR($B$14),"",IF(ISBLANK($B$14),"",$B$14)) | DT14: =IF(ISERROR($D$14),"",IF(ISBLANK($D$14),"",$D$14)) | DW14: =IF(ISERROR($G$14),"",IF(ISBLANK($G$14),"",$G$14)) | DX14: =IF(ISERROR($H$14),"",IF(ISBLANK($H$14),"",$H$14)) | DY14: =IF(ISERROR($I$14),"",IF(ISBLANK($I$14),"",$I$14)) | DZ14: =IF(ISERROR($J$14),"",IF(ISBLANK($J$14),"",$J$14)) | EA14: =ISERROR($A$14)*1+ISERROR($B$14)*1+ISERROR($D$14)*1+ISERROR($G$14)*1+ISERROR($H$14)*1+ISERROR($I$14)*1+ISERROR($J$14)*1
K15: =IF(EA15>0,"O Google leu como fórmula: escolha de novo ou digite com ' na frente.",IF(LEN($DQ$15)=0,IF(LEN($DR$15&$DT$15&$DY$15)>0,"Linha sem nome: o inimigo não entra nas listas",""),IF(COUNTIF($DQ$11:$DQ$22,$DQ$15)>1,"Nome repetido na tabela",IF(COUNTIF('Dados'!$B$92:$B$123,$DQ$15)>0,"Nome igual a uma criatura do bestiário: dê outro nome",IF(AND($BK$15="Ajustar do bestiário",$BL$15=0),"Modo Ajustar sem base do bestiário válida",IF(AND(LEN($DZ$15)>0,$BN$15<>"Boss"),"Fases só valem para Boss (28.5)",IF(AND(ISNUMBER($DX$15),OR($DX$15<1,$DX$15>20)),"Nível fora de 1 a 20: usando o limite",IF(AND(LEN($DY$15)>0,COUNTIF('Dados'!$AO$6:$AO$8,$DY$15)=0),"Tipo fora da lista: usando Comum","")))))))) | N15: =IF(LEN($DQ$15)=0,"",$DQ$15) | O15: =IF(LEN($DQ$15)=0,"",$BN$15) | P15: =IF(LEN($DQ$15)=0,"",$BQ$15) | Q15: =IF(LEN($DQ$15)=0,"",$BU$15) | R15: =IF(LEN($DQ$15)=0,"",IFERROR(INDEX('Dados'!$E$38:$E$52,MATCH($BS$15,'Dados'!$A$38:$A$52,0)),"")) | S15: =IF(LEN($DQ$15)=0,"",IFERROR(INDEX('Dados'!$F$38:$F$52,MATCH($BS$15,'Dados'!$A$38:$A$52,0)),"")) | T15: =IF(LEN($DQ$15)=0,"",IFERROR(INDEX('Dados'!$G$38:$G$52,MATCH($BS$15,'Dados'!$A$38:$A$52,0)),"")) | U15: =IF(LEN($DQ$15)=0,"",IFERROR(INDEX('Dados'!$H$38:$H$52,MATCH($BS$15,'Dados'!$A$38:$A$52,0)),"")) | V15: =IF(LEN($DQ$15)=0,"",IFERROR(INDEX('Dados'!$I$38:$I$52,MATCH($BS$15,'Dados'!$A$38:$A$52,0)),"")) | W15: =IF(LEN($DQ$15)=0,"",IFERROR(INDEX('Dados'!$J$38:$J$52,MATCH($BS$15,'Dados'!$A$38:$A$52,0)),"")) | X15: =IF(LEN($DQ$15)=0,"",IFERROR(INDEX('Dados'!$K$38:$K$52,MATCH($BS$15,'Dados'!$A$38:$A$52,0)),"")) | Y15: =IF(LEN($DQ$15)=0,"",IFERROR(INDEX('Dados'!$L$38:$L$52,MATCH($BS$15,'Dados'!$A$38:$A$52,0)),"")) | Z15: =IF(LEN($DQ$15)=0,"",IFERROR(INDEX('Dados'!$M$38:$M$52,MATCH($BS$15,'Dados'!$A$38:$A$52,0)),"")) | AA15: =IF(LEN($DQ$15)=0,"",$BY$15) | AB15: =IF(LEN($DQ$15)=0,"",$BZ$15) | AC15: =IF(LEN($DQ$15)=0,"",$CA$15) | AD15: =IF(LEN($DQ$15)=0,"",$CB$15) | AE15: =IF(LEN($DQ$15)=0,"",$CC$15) | AF15: =IF(LEN($DQ$15)=0,"",IF($DV$30="Sim","Pode",IF($DV$30="Não","Não",IF($BL$15=1,IFERROR(INDEX('Dados'!$V$92:$V$123,$BM$15)&"",""),"Não declarado")))) | AG15: =IF(LEN($DQ$15)=0,"",$BV$15) | AH15: =IF(LEN($DQ$15)=0,"",IFERROR(INDEX('Dados'!$Q$38:$Q$52,MATCH($BS$15,'Dados'!$A$38:$A$52,0)),"")) | AI15: =IF(LEN($DQ$15)=0,"",IF(AND($BL$15=1,$DT$15="Escória de Stellaron"),1.5,1)*$BU$15) | AJ15: =IF(LEN($DQ$15)=0,"",IFERROR(INDEX('Dados'!$P$38:$P$52,MATCH($BS$15,'Dados'!$A$38:$A$52,0)),"")) | AK15: =IF(LEN($DQ$15)=0,"",IF($BV$15=2,INT($BU$15/2),IF($BV$15=3,INT(2*$BU$15/3),""))) | AL15: =IF(LEN($DQ$15)=0,"",IF($BV$15=3,INT($BU$15/3),"")) | AM15: =IF(OR(LEN($DQ$15)=0,$BV$15<2),"",IFERROR(INDEX($DT$88:$DT$112,MATCH($DQ$15&"|2",$N$88:$N$112,0))&"",IF($BL$15=1,IFERROR(INDEX('Dados'!$G$127:$G$138,MATCH($DT$15&"|2",'Dados'!$A$127:$A$138,0)),""),""))) | AN15: =IF(OR(LEN($DQ$15)=0,$BV$15<2),"",IFERROR(INDEX($DU$88:$DU$112,MATCH($DQ$15&"|2",$N$88:$N$112,0))&"",IF($BL$15=1,IFERROR(INDEX('Dados'!$H$127:$H$138,MATCH($DT$15&"|2",'Dados'!$A$127:$A$138,0)),""),""))) | AO15: =IF(OR(LEN($DQ$15)=0,$BV$15<2),"",IFERROR(INDEX($DV$88:$DV$112,MATCH($DQ$15&"|2",$N$88:$N$112,0))&"",IF($BL$15=1,IFERROR(INDEX('Dados'!$I$127:$I$138,MATCH($DT$15&"|2",'Dados'!$A$127:$A$138,0)),""),""))) | AP15: =IF(OR(LEN($DQ$15)=0,$BV$15<2),"",IFERROR(INDEX($DW$88:$DW$112,MATCH($DQ$15&"|2",$N$88:$N$112,0))&"",IF($BL$15=1,IFERROR(INDEX('Dados'!$J$127:$J$138,MATCH($DT$15&"|2",'Dados'!$A$127:$A$138,0)),""),""))) | AQ15: =IF(OR(LEN($DQ$15)=0,$BV$15<2),"",IF(ISNUMBER(MATCH($DQ$15&"|2",$N$88:$N$112,0)),IF(ISNUMBER(INDEX($DX$88:$DX$112,MATCH($DQ$15&"|2",$N$88:$N$112,0))),MIN(IFERROR(INDEX('Dados'!$G$38:$G$52,MATCH($BS$15,'Dados'!$A$38:$A$52,0)),""),INDEX($DX$88:$DX$112,MATCH($DQ$15&"|2",$N$88:$N$112,0))),IFERROR(INDEX('Dados'!$G$38:$G$52,MATCH($BS$15,'Dados'!$A$38:$A$52,0)),"")),IF($BL$15=1,IFERROR(MIN(IFERROR(INDEX('Dados'!$G$38:$G$52,MATCH($BS$15,'Dados'!$A$38:$A$52,0)),""),INT(INDEX('Dados'!$K$127:$K$138,MATCH($DT$15&"|2",'Dados'!$A$127:$A$138,0))*IFERROR(INDEX('Dados'!$G$38:$G$52,MATCH($BS$15,'Dados'!$A$38:$A$52,0)),"")/$CH$15)),IFERROR(INDEX('Dados'!$G$38:$G$52,MATCH($BS$15,'Dados'!$A$38:$A$52,0)),"")),IFERROR(INDEX('Dados'!$G$38:$G$52,MATCH($BS$15,'Dados'!$A$38:$A$52,0)),"")))) | AR15: =IF(OR(LEN($DQ$15)=0,$BV$15<3),"",IFERROR(INDEX($DT$88:$DT$112,MATCH($DQ$15&"|3",$N$88:$N$112,0))&"",IF($BL$15=1,IFERROR(INDEX('Dados'!$G$127:$G$138,MATCH($DT$15&"|3",'Dados'!$A$127:$A$138,0)),""),""))) | AS15: =IF(OR(LEN($DQ$15)=0,$BV$15<3),"",IFERROR(INDEX($DU$88:$DU$112,MATCH($DQ$15&"|3",$N$88:$N$112,0))&"",IF($BL$15=1,IFERROR(INDEX('Dados'!$H$127:$H$138,MATCH($DT$15&"|3",'Dados'!$A$127:$A$138,0)),""),""))) | AT15: =IF(OR(LEN($DQ$15)=0,$BV$15<3),"",IFERROR(INDEX($DV$88:$DV$112,MATCH($DQ$15&"|3",$N$88:$N$112,0))&"",IF($BL$15=1,IFERROR(INDEX('Dados'!$I$127:$I$138,MATCH($DT$15&"|3",'Dados'!$A$127:$A$138,0)),""),""))) | AU15: =IF(OR(LEN($DQ$15)=0,$BV$15<3),"",IFERROR(INDEX($DW$88:$DW$112,MATCH($DQ$15&"|3",$N$88:$N$112,0))&"",IF($BL$15=1,IFERROR(INDEX('Dados'!$J$127:$J$138,MATCH($DT$15&"|3",'Dados'!$A$127:$A$138,0)),""),""))) | AV15: =IF(OR(LEN($DQ$15)=0,$BV$15<3),"",IF(ISNUMBER(MATCH($DQ$15&"|3",$N$88:$N$112,0)),IF(ISNUMBER(INDEX($DX$88:$DX$112,MATCH($DQ$15&"|3",$N$88:$N$112,0))),MIN(IFERROR(INDEX('Dados'!$G$38:$G$52,MATCH($BS$15,'Dados'!$A$38:$A$52,0)),""),INDEX($DX$88:$DX$112,MATCH($DQ$15&"|3",$N$88:$N$112,0))),IFERROR(INDEX('Dados'!$G$38:$G$52,MATCH($BS$15,'Dados'!$A$38:$A$52,0)),"")),IF($BL$15=1,IFERROR(MIN(IFERROR(INDEX('Dados'!$G$38:$G$52,MATCH($BS$15,'Dados'!$A$38:$A$52,0)),""),INT(INDEX('Dados'!$K$127:$K$138,MATCH($DT$15&"|3",'Dados'!$A$127:$A$138,0))*IFERROR(INDEX('Dados'!$G$38:$G$52,MATCH($BS$15,'Dados'!$A$38:$A$52,0)),"")/$CH$15)),IFERROR(INDEX('Dados'!$G$38:$G$52,MATCH($BS$15,'Dados'!$A$38:$A$52,0)),"")),IFERROR(INDEX('Dados'!$G$38:$G$52,MATCH($BS$15,'Dados'!$A$38:$A$52,0)),"")))) | AW15: =IF(LEN($DQ$15)=0,"",IF($BL$15=1,IFERROR(INDEX('Dados'!$AF$92:$AF$123,$BM$15)&"",""),IFERROR(INDEX($DU$116:$DU$153,MATCH($DQ$15&"|1",$Q$116:$Q$153,0))&"",""))) | AX15: =IF(LEN($DQ$15)=0,"",IF($BL$15=1,IF(ISNUMBER(IFERROR(INDEX('Dados'!$AG$92:$AG$123,$BM$15),"")),IF(IFERROR(INDEX('Dados'!$AG$92:$AG$123,$BM$15),"")>0,IFERROR(INDEX('Dados'!$AG$92:$AG$123,$BM$15),""),""),""),IFERROR(INDEX($DY$116:$DY$153,MATCH($DQ$15&"|1",$Q$116:$Q$153,0))+0,""))) | AY15: =IF(LEN($DQ$15)=0,"",IF($BL$15=1,IFERROR(INDEX('Dados'!$AH$92:$AH$123,$BM$15)&"",""),IFERROR(INDEX($DU$116:$DU$153,MATCH($DQ$15&"|2",$Q$116:$Q$153,0))&"",""))) | AZ15: =IF(LEN($DQ$15)=0,"",IF($BL$15=1,IF(ISNUMBER(IFERROR(INDEX('Dados'!$AI$92:$AI$123,$BM$15),"")),IF(IFERROR(INDEX('Dados'!$AI$92:$AI$123,$BM$15),"")>0,IFERROR(INDEX('Dados'!$AI$92:$AI$123,$BM$15),""),""),""),IFERROR(INDEX($DY$116:$DY$153,MATCH($DQ$15&"|2",$Q$116:$Q$153,0))+0,""))) | BA15: =IF(LEN($DQ$15)=0,"",IF($BL$15=1,IFERROR(INDEX('Dados'!$AJ$92:$AJ$123,$BM$15)&"",""),IFERROR(INDEX($DU$116:$DU$153,MATCH($DQ$15&"|3",$Q$116:$Q$153,0))&"",""))) | BB15: =IF(LEN($DQ$15)=0,"",IF($BL$15=1,IF(ISNUMBER(IFERROR(INDEX('Dados'!$AK$92:$AK$123,$BM$15),"")),IF(IFERROR(INDEX('Dados'!$AK$92:$AK$123,$BM$15),"")>0,IFERROR(INDEX('Dados'!$AK$92:$AK$123,$BM$15),""),""),""),IFERROR(INDEX($DY$116:$DY$153,MATCH($DQ$15&"|3",$Q$116:$Q$153,0))+0,""))) | BC15: =IF(LEN($DQ$15)=0,"",IF(LEN($DR$30)>0,$DR$30,IF($BL$15=1,IFERROR(INDEX('Dados'!$E$92:$E$123,$BM$15)&"",""),""))) | BD15: =IF(AND(LEN($DR$30)=0,$BL$15=1),IFERROR(INDEX('Dados'!$AD$92:$AD$123,$BM$15)&"",""),"") | BE15: =IF(LEN($DQ$15)=0,"",INDEX('Dados'!$F$7:$F$11,$BR$15)) | BF15: =IF(LEN($DQ$15)=0,"",$BR$15) | BG15: =$G$46 | BH15: ="Campanha" | BK15: =IF(COUNTIF('Dados'!$AQ$6:$AQ$8,$DR$15)>0,$DR$15,"Faixa do livro") | BL15: =IF(AND($BK$15="Ajustar do bestiário",ISNUMBER($BM$15)),1,0) | BM15: =IFERROR(MATCH($DT$15,'Dados'!$B$92:$B$123,0),"") | BN15: =IF(COUNTIF('Dados'!$AO$6:$AO$8,$DY$15)>0,$DY$15,IF($BL$15=1,IFERROR(INDEX('Dados'!$C$92:$C$123,$BM$15),""),"Comum")) | BO15: =MATCH($BN$15,'Dados'!$AO$6:$AO$8,0) | BP15: =IF(ISNUMBER($DX$15),MIN(20,MAX(1,INT($DX$15))),'Campanha'!$B$17) | BQ15: =IF($BK$15="Por nível — Sugestão",INDEX('Dados'!$B$7:$B$11,INT(($BP$15-1)/4)+1),IF(LEN(IFERROR(INDEX('Dados'!$B$7:$B$11,MATCH($DW$15,'Dados'!$AP$6:$AP$10,0)),""))>0,IFERROR(INDEX('Dados'!$B$7:$B$11,MATCH($DW$15,'Dados'!$AP$6:$AP$10,0)),""),'Campanha'!$B$19)) | BR15: =MATCH($BQ$15,'Dados'!$B$7:$B$11,0) | BS15: =$BQ$15&"|"&$BN$15 | BT15: =MIN(4,MAX(1,INT(($BP$15-3)/4)+1)) | BU15: =IF($BK$15="Por nível — Sugestão",INT(IF($BP$15<=3,INDEX('Dados'!$D$38:$D$52,$BO$15),IF($BP$15>=19,INDEX('Dados'!$D$38:$D$52,12+$BO$15),INDEX('Dados'!$D$38:$D$52,($BT$15-1)*3+$BO$15)+(INDEX('Dados'!$D$38:$D$52,$BT$15*3+$BO$15)-INDEX('Dados'!$D$38:$D$52,($BT$15-1)*3+$BO$15))*($BP$15-(4*$BT$15-1))/4))),IFERROR(INDEX('Dados'!$D$38:$D$52,MATCH($BS$15,'Dados'!$A$38:$A$52,0)),"")) | BV15: =IF($BN$15<>"Boss",1,IF(AND(ISNUMBER($DZ$15),$DZ$15>=1,$DZ$15<=3),INT($DZ$15),IF($BL$15=1,MAX(1,IFERROR(INDEX('Dados'!$F$92:$F$123,$BM$15),"")),1))) | BW15: =IFERROR(INDEX('Dados'!$O$38:$O$52,MATCH($BS$15,'Dados'!$A$38:$A$52,0)),"") | BX15: =IF(AND(LEN($DR$46)=0,LEN($DS$46)=0,LEN($DT$46)=0,LEN($DU$46)=0),1,0) | BY15: =IF(LEN($DQ$15)=0,"",IF($BX$15=0,$DR$46&"",IF($BL$15=1,IFERROR(INDEX('Dados'!$Q$92:$Q$123,$BM$15)&"",""),IF(1<=$BW$15,$CD$15,"")))) | BZ15: =IF(LEN($DQ$15)=0,"",IF($BX$15=0,$DS$46&"",IF($BL$15=1,IFERROR(INDEX('Dados'!$R$92:$R$123,$BM$15)&"",""),IF(2<=$BW$15,$CE$15,"")))) | CA15: =IF(LEN($DQ$15)=0,"",IF($BX$15=0,$DT$46&"",IF($BL$15=1,IFERROR(INDEX('Dados'!$S$92:$S$123,$BM$15)&"",""),IF(3<=$BW$15,$CF$15,"")))) | CB15: =IF(LEN($DQ$15)=0,"",IF($BX$15=0,$DU$46&"",IF($BL$15=1,IFERROR(INDEX('Dados'!$T$92:$T$123,$BM$15)&"",""),IF(4<=$BW$15,$CG$15,"")))) | CC15: =IF(LEN($DV$46)>0,$DV$46,IF($BL$15=1,IFERROR(INDEX('Dados'!$U$92:$U$123,$BM$15)&"",""),"")) | CD15: =INDEX('Dados'!$A$301:$A$307,MATCH(SMALL($DI$15:$DO$15,1),$DI$15:$DO$15,0)) | CE15: =INDEX('Dados'!$A$301:$A$307,MATCH(SMALL($DI$15:$DO$15,2),$DI$15:$DO$15,0)) | CF15: =INDEX('Dados'!$A$301:$A$307,MATCH(SMALL($DI$15:$DO$15,3),$DI$15:$DO$15,0)) | CG15: =INDEX('Dados'!$A$301:$A$307,MATCH(SMALL($DI$15:$DO$15,4),$DI$15:$DO$15,0)) | CH15: =IF($BL$15=1,IFERROR(INDEX('Dados'!$J$92:$J$123,$BM$15),""),"") | CI15: =IF($BL$15=1,IFERROR(INDEX('Dados'!$G$92:$G$123,$BM$15),""),"") | CJ15: =IFERROR(INDEX('Dados'!$S$38:$S$52,MATCH($BS$15,'Dados'!$A$38:$A$52,0)),"") | CK15: =IFERROR(INDEX('Dados'!$T$38:$T$52,MATCH($BS$15,'Dados'!$A$38:$A$52,0)),"") | CL15: =IFERROR(INDEX('Dados'!$J$38:$J$52,MATCH($BQ$15&"|Comum",'Dados'!$A$38:$A$52,0)),"") | CM15: =IFERROR(INDEX('Dados'!$K$38:$K$52,MATCH($BQ$15&"|Comum",'Dados'!$A$38:$A$52,0)),"") | CN15: =MOD(MOD(MOD((MOD('Início'!$E$15+104729*$C$7+67156249,2147483646)+1)*16807,2147483647)*16807,2147483647)*16807,2147483647) | CO15: =MOD(MOD(MOD((MOD(MOD(INT($CN$15/65536)*$CN$15,2147483647)*65536+MOD($CN$15,65536)*$CN$15,2147483647))*16807,2147483647)*16807,2147483647)*16807,2147483647) | CP15: =MOD(MOD(MOD((MOD($CO$15+INT($CO$15/65536)*MOD($CO$15,65536),2147483646)+1)*16807,2147483647)*16807,2147483647)*16807,2147483647) | CQ15: =MOD(MOD(MOD((MOD('Início'!$E$15+104729*$C$7+68455958,2147483646)+1)*16807,2147483647)*16807,2147483647)*16807,2147483647) | CR15: =MOD(MOD(MOD((MOD(MOD(INT($CQ$15/65536)*$CQ$15,2147483647)*65536+MOD($CQ$15,65536)*$CQ$15,2147483647))*16807,2147483647)*16807,2147483647)*16807,2147483647) | CS15: =MOD(MOD(MOD((MOD($CR$15+INT($CR$15/65536)*MOD($CR$15,65536),2147483646)+1)*16807,2147483647)*16807,2147483647)*16807,2147483647) | CT15: =MOD(MOD(MOD((MOD('Início'!$E$15+104729*$C$7+69755667,2147483646)+1)*16807,2147483647)*16807,2147483647)*16807,2147483647) | CU15: =MOD(MOD(MOD((MOD(MOD(INT($CT$15/65536)*$CT$15,2147483647)*65536+MOD($CT$15,65536)*$CT$15,2147483647))*16807,2147483647)*16807,2147483647)*16807,2147483647) | CV15: =MOD(MOD(MOD((MOD($CU$15+INT($CU$15/65536)*MOD($CU$15,65536),2147483646)+1)*16807,2147483647)*16807,2147483647)*16807,2147483647) | CW15: =MOD(MOD(MOD((MOD('Início'!$E$15+104729*$C$7+71055376,2147483646)+1)*16807,2147483647)*16807,2147483647)*16807,2147483647) | CX15: =MOD(MOD(MOD((MOD(MOD(INT($CW$15/65536)*$CW$15,2147483647)*65536+MOD($CW$15,65536)*$CW$15,2147483647))*16807,2147483647)*16807,2147483647)*16807,2147483647) | CY15: =MOD(MOD(MOD((MOD($CX$15+INT($CX$15/65536)*MOD($CX$15,65536),2147483646)+1)*16807,2147483647)*16807,2147483647)*16807,2147483647) | CZ15: =MOD(MOD(MOD((MOD('Início'!$E$15+104729*$C$7+72355085,2147483646)+1)*16807,2147483647)*16807,2147483647)*16807,2147483647) | DA15: =MOD(MOD(MOD((MOD(MOD(INT($CZ$15/65536)*$CZ$15,2147483647)*65536+MOD($CZ$15,65536)*$CZ$15,2147483647))*16807,2147483647)*16807,2147483647)*16807,2147483647) | DB15: =MOD(MOD(MOD((MOD($DA$15+INT($DA$15/65536)*MOD($DA$15,65536),2147483646)+1)*16807,2147483647)*16807,2147483647)*16807,2147483647) | DC15: =MOD(MOD(MOD((MOD('Início'!$E$15+104729*$C$7+73654794,2147483646)+1)*16807,2147483647)*16807,2147483647)*16807,2147483647) | DD15: =MOD(MOD(MOD((MOD(MOD(INT($DC$15/65536)*$DC$15,2147483647)*65536+MOD($DC$15,65536)*$DC$15,2147483647))*16807,2147483647)*16807,2147483647)*16807,2147483647) | DE15: =MOD(MOD(MOD((MOD($DD$15+INT($DD$15/65536)*MOD($DD$15,65536),2147483646)+1)*16807,2147483647)*16807,2147483647)*16807,2147483647) | DF15: =MOD(MOD(MOD((MOD('Início'!$E$15+104729*$C$7+74954503,2147483646)+1)*16807,2147483647)*16807,2147483647)*16807,2147483647) | DG15: =MOD(MOD(MOD((MOD(MOD(INT($DF$15/65536)*$DF$15,2147483647)*65536+MOD($DF$15,65536)*$DF$15,2147483647))*16807,2147483647)*16807,2147483647)*16807,2147483647) | DH15: =MOD(MOD(MOD((MOD($DG$15+INT($DG$15/65536)*MOD($DG$15,65536),2147483646)+1)*16807,2147483647)*16807,2147483647)*16807,2147483647) | DI15: =IF($CC$15="Físico",9000000000,IF(AND('Grupo'!$B$44="Sim",COUNTIF($BY$11:$CB$14,"Físico")=0),0,2147483647))+$CP$15+1/10 | DJ15: =IF($CC$15="Fogo",9000000000,IF(AND('Grupo'!$C$44="Sim",COUNTIF($BY$11:$CB$14,"Fogo")=0),0,2147483647))+$CS$15+2/10 | DK15: =IF($CC$15="Gelo",9000000000,IF(AND('Grupo'!$D$44="Sim",COUNTIF($BY$11:$CB$14,"Gelo")=0),0,2147483647))+$CV$15+3/10 | DL15: =IF($CC$15="Raio",9000000000,IF(AND('Grupo'!$E$44="Sim",COUNTIF($BY$11:$CB$14,"Raio")=0),0,2147483647))+$CY$15+4/10 | DM15: =IF($CC$15="Vento",9000000000,IF(AND('Grupo'!$F$44="Sim",COUNTIF($BY$11:$CB$14,"Vento")=0),0,2147483647))+$DB$15+5/10 | DN15: =IF($CC$15="Quântico",9000000000,IF(AND('Grupo'!$G$44="Sim",COUNTIF($BY$11:$CB$14,"Quântico")=0),0,2147483647))+$DE$15+6/10 | DO15: =IF($CC$15="Imaginário",9000000000,IF(AND('Grupo'!$H$44="Sim",COUNTIF($BY$11:$CB$14,"Imaginário")=0),0,2147483647))+$DH$15+7/10 | DQ15: =IF(ISERROR($A$15),"",IF(ISBLANK($A$15),"",$A$15)) | DR15: =IF(ISERROR($B$15),"",IF(ISBLANK($B$15),"",$B$15)) | DT15: =IF(ISERROR($D$15),"",IF(ISBLANK($D$15),"",$D$15)) | DW15: =IF(ISERROR($G$15),"",IF(ISBLANK($G$15),"",$G$15)) | DX15: =IF(ISERROR($H$15),"",IF(ISBLANK($H$15),"",$H$15)) | DY15: =IF(ISERROR($I$15),"",IF(ISBLANK($I$15),"",$I$15)) | DZ15: =IF(ISERROR($J$15),"",IF(ISBLANK($J$15),"",$J$15)) | EA15: =ISERROR($A$15)*1+ISERROR($B$15)*1+ISERROR($D$15)*1+ISERROR($G$15)*1+ISERROR($H$15)*1+ISERROR($I$15)*1+ISERROR($J$15)*1
K16: =IF(EA16>0,"O Google leu como fórmula: escolha de novo ou digite com ' na frente.",IF(LEN($DQ$16)=0,IF(LEN($DR$16&$DT$16&$DY$16)>0,"Linha sem nome: o inimigo não entra nas listas",""),IF(COUNTIF($DQ$11:$DQ$22,$DQ$16)>1,"Nome repetido na tabela",IF(COUNTIF('Dados'!$B$92:$B$123,$DQ$16)>0,"Nome igual a uma criatura do bestiário: dê outro nome",IF(AND($BK$16="Ajustar do bestiário",$BL$16=0),"Modo Ajustar sem base do bestiário válida",IF(AND(LEN($DZ$16)>0,$BN$16<>"Boss"),"Fases só valem para Boss (28.5)",IF(AND(ISNUMBER($DX$16),OR($DX$16<1,$DX$16>20)),"Nível fora de 1 a 20: usando o limite",IF(AND(LEN($DY$16)>0,COUNTIF('Dados'!$AO$6:$AO$8,$DY$16)=0),"Tipo fora da lista: usando Comum","")))))))) | N16: =IF(LEN($DQ$16)=0,"",$DQ$16) | O16: =IF(LEN($DQ$16)=0,"",$BN$16) | P16: =IF(LEN($DQ$16)=0,"",$BQ$16) | Q16: =IF(LEN($DQ$16)=0,"",$BU$16) | R16: =IF(LEN($DQ$16)=0,"",IFERROR(INDEX('Dados'!$E$38:$E$52,MATCH($BS$16,'Dados'!$A$38:$A$52,0)),"")) | S16: =IF(LEN($DQ$16)=0,"",IFERROR(INDEX('Dados'!$F$38:$F$52,MATCH($BS$16,'Dados'!$A$38:$A$52,0)),"")) | T16: =IF(LEN($DQ$16)=0,"",IFERROR(INDEX('Dados'!$G$38:$G$52,MATCH($BS$16,'Dados'!$A$38:$A$52,0)),"")) | U16: =IF(LEN($DQ$16)=0,"",IFERROR(INDEX('Dados'!$H$38:$H$52,MATCH($BS$16,'Dados'!$A$38:$A$52,0)),"")) | V16: =IF(LEN($DQ$16)=0,"",IFERROR(INDEX('Dados'!$I$38:$I$52,MATCH($BS$16,'Dados'!$A$38:$A$52,0)),"")) | W16: =IF(LEN($DQ$16)=0,"",IFERROR(INDEX('Dados'!$J$38:$J$52,MATCH($BS$16,'Dados'!$A$38:$A$52,0)),"")) | X16: =IF(LEN($DQ$16)=0,"",IFERROR(INDEX('Dados'!$K$38:$K$52,MATCH($BS$16,'Dados'!$A$38:$A$52,0)),"")) | Y16: =IF(LEN($DQ$16)=0,"",IFERROR(INDEX('Dados'!$L$38:$L$52,MATCH($BS$16,'Dados'!$A$38:$A$52,0)),"")) | Z16: =IF(LEN($DQ$16)=0,"",IFERROR(INDEX('Dados'!$M$38:$M$52,MATCH($BS$16,'Dados'!$A$38:$A$52,0)),"")) | AA16: =IF(LEN($DQ$16)=0,"",$BY$16) | AB16: =IF(LEN($DQ$16)=0,"",$BZ$16) | AC16: =IF(LEN($DQ$16)=0,"",$CA$16) | AD16: =IF(LEN($DQ$16)=0,"",$CB$16) | AE16: =IF(LEN($DQ$16)=0,"",$CC$16) | AF16: =IF(LEN($DQ$16)=0,"",IF($DV$31="Sim","Pode",IF($DV$31="Não","Não",IF($BL$16=1,IFERROR(INDEX('Dados'!$V$92:$V$123,$BM$16)&"",""),"Não declarado")))) | AG16: =IF(LEN($DQ$16)=0,"",$BV$16) | AH16: =IF(LEN($DQ$16)=0,"",IFERROR(INDEX('Dados'!$Q$38:$Q$52,MATCH($BS$16,'Dados'!$A$38:$A$52,0)),"")) | AI16: =IF(LEN($DQ$16)=0,"",IF(AND($BL$16=1,$DT$16="Escória de Stellaron"),1.5,1)*$BU$16) | AJ16: =IF(LEN($DQ$16)=0,"",IFERROR(INDEX('Dados'!$P$38:$P$52,MATCH($BS$16,'Dados'!$A$38:$A$52,0)),"")) | AK16: =IF(LEN($DQ$16)=0,"",IF($BV$16=2,INT($BU$16/2),IF($BV$16=3,INT(2*$BU$16/3),""))) | AL16: =IF(LEN($DQ$16)=0,"",IF($BV$16=3,INT($BU$16/3),"")) | AM16: =IF(OR(LEN($DQ$16)=0,$BV$16<2),"",IFERROR(INDEX($DT$88:$DT$112,MATCH($DQ$16&"|2",$N$88:$N$112,0))&"",IF($BL$16=1,IFERROR(INDEX('Dados'!$G$127:$G$138,MATCH($DT$16&"|2",'Dados'!$A$127:$A$138,0)),""),""))) | AN16: =IF(OR(LEN($DQ$16)=0,$BV$16<2),"",IFERROR(INDEX($DU$88:$DU$112,MATCH($DQ$16&"|2",$N$88:$N$112,0))&"",IF($BL$16=1,IFERROR(INDEX('Dados'!$H$127:$H$138,MATCH($DT$16&"|2",'Dados'!$A$127:$A$138,0)),""),""))) | AO16: =IF(OR(LEN($DQ$16)=0,$BV$16<2),"",IFERROR(INDEX($DV$88:$DV$112,MATCH($DQ$16&"|2",$N$88:$N$112,0))&"",IF($BL$16=1,IFERROR(INDEX('Dados'!$I$127:$I$138,MATCH($DT$16&"|2",'Dados'!$A$127:$A$138,0)),""),""))) | AP16: =IF(OR(LEN($DQ$16)=0,$BV$16<2),"",IFERROR(INDEX($DW$88:$DW$112,MATCH($DQ$16&"|2",$N$88:$N$112,0))&"",IF($BL$16=1,IFERROR(INDEX('Dados'!$J$127:$J$138,MATCH($DT$16&"|2",'Dados'!$A$127:$A$138,0)),""),""))) | AQ16: =IF(OR(LEN($DQ$16)=0,$BV$16<2),"",IF(ISNUMBER(MATCH($DQ$16&"|2",$N$88:$N$112,0)),IF(ISNUMBER(INDEX($DX$88:$DX$112,MATCH($DQ$16&"|2",$N$88:$N$112,0))),MIN(IFERROR(INDEX('Dados'!$G$38:$G$52,MATCH($BS$16,'Dados'!$A$38:$A$52,0)),""),INDEX($DX$88:$DX$112,MATCH($DQ$16&"|2",$N$88:$N$112,0))),IFERROR(INDEX('Dados'!$G$38:$G$52,MATCH($BS$16,'Dados'!$A$38:$A$52,0)),"")),IF($BL$16=1,IFERROR(MIN(IFERROR(INDEX('Dados'!$G$38:$G$52,MATCH($BS$16,'Dados'!$A$38:$A$52,0)),""),INT(INDEX('Dados'!$K$127:$K$138,MATCH($DT$16&"|2",'Dados'!$A$127:$A$138,0))*IFERROR(INDEX('Dados'!$G$38:$G$52,MATCH($BS$16,'Dados'!$A$38:$A$52,0)),"")/$CH$16)),IFERROR(INDEX('Dados'!$G$38:$G$52,MATCH($BS$16,'Dados'!$A$38:$A$52,0)),"")),IFERROR(INDEX('Dados'!$G$38:$G$52,MATCH($BS$16,'Dados'!$A$38:$A$52,0)),"")))) | AR16: =IF(OR(LEN($DQ$16)=0,$BV$16<3),"",IFERROR(INDEX($DT$88:$DT$112,MATCH($DQ$16&"|3",$N$88:$N$112,0))&"",IF($BL$16=1,IFERROR(INDEX('Dados'!$G$127:$G$138,MATCH($DT$16&"|3",'Dados'!$A$127:$A$138,0)),""),""))) | AS16: =IF(OR(LEN($DQ$16)=0,$BV$16<3),"",IFERROR(INDEX($DU$88:$DU$112,MATCH($DQ$16&"|3",$N$88:$N$112,0))&"",IF($BL$16=1,IFERROR(INDEX('Dados'!$H$127:$H$138,MATCH($DT$16&"|3",'Dados'!$A$127:$A$138,0)),""),""))) | AT16: =IF(OR(LEN($DQ$16)=0,$BV$16<3),"",IFERROR(INDEX($DV$88:$DV$112,MATCH($DQ$16&"|3",$N$88:$N$112,0))&"",IF($BL$16=1,IFERROR(INDEX('Dados'!$I$127:$I$138,MATCH($DT$16&"|3",'Dados'!$A$127:$A$138,0)),""),""))) | AU16: =IF(OR(LEN($DQ$16)=0,$BV$16<3),"",IFERROR(INDEX($DW$88:$DW$112,MATCH($DQ$16&"|3",$N$88:$N$112,0))&"",IF($BL$16=1,IFERROR(INDEX('Dados'!$J$127:$J$138,MATCH($DT$16&"|3",'Dados'!$A$127:$A$138,0)),""),""))) | AV16: =IF(OR(LEN($DQ$16)=0,$BV$16<3),"",IF(ISNUMBER(MATCH($DQ$16&"|3",$N$88:$N$112,0)),IF(ISNUMBER(INDEX($DX$88:$DX$112,MATCH($DQ$16&"|3",$N$88:$N$112,0))),MIN(IFERROR(INDEX('Dados'!$G$38:$G$52,MATCH($BS$16,'Dados'!$A$38:$A$52,0)),""),INDEX($DX$88:$DX$112,MATCH($DQ$16&"|3",$N$88:$N$112,0))),IFERROR(INDEX('Dados'!$G$38:$G$52,MATCH($BS$16,'Dados'!$A$38:$A$52,0)),"")),IF($BL$16=1,IFERROR(MIN(IFERROR(INDEX('Dados'!$G$38:$G$52,MATCH($BS$16,'Dados'!$A$38:$A$52,0)),""),INT(INDEX('Dados'!$K$127:$K$138,MATCH($DT$16&"|3",'Dados'!$A$127:$A$138,0))*IFERROR(INDEX('Dados'!$G$38:$G$52,MATCH($BS$16,'Dados'!$A$38:$A$52,0)),"")/$CH$16)),IFERROR(INDEX('Dados'!$G$38:$G$52,MATCH($BS$16,'Dados'!$A$38:$A$52,0)),"")),IFERROR(INDEX('Dados'!$G$38:$G$52,MATCH($BS$16,'Dados'!$A$38:$A$52,0)),"")))) | AW16: =IF(LEN($DQ$16)=0,"",IF($BL$16=1,IFERROR(INDEX('Dados'!$AF$92:$AF$123,$BM$16)&"",""),IFERROR(INDEX($DU$116:$DU$153,MATCH($DQ$16&"|1",$Q$116:$Q$153,0))&"",""))) | AX16: =IF(LEN($DQ$16)=0,"",IF($BL$16=1,IF(ISNUMBER(IFERROR(INDEX('Dados'!$AG$92:$AG$123,$BM$16),"")),IF(IFERROR(INDEX('Dados'!$AG$92:$AG$123,$BM$16),"")>0,IFERROR(INDEX('Dados'!$AG$92:$AG$123,$BM$16),""),""),""),IFERROR(INDEX($DY$116:$DY$153,MATCH($DQ$16&"|1",$Q$116:$Q$153,0))+0,""))) | AY16: =IF(LEN($DQ$16)=0,"",IF($BL$16=1,IFERROR(INDEX('Dados'!$AH$92:$AH$123,$BM$16)&"",""),IFERROR(INDEX($DU$116:$DU$153,MATCH($DQ$16&"|2",$Q$116:$Q$153,0))&"",""))) | AZ16: =IF(LEN($DQ$16)=0,"",IF($BL$16=1,IF(ISNUMBER(IFERROR(INDEX('Dados'!$AI$92:$AI$123,$BM$16),"")),IF(IFERROR(INDEX('Dados'!$AI$92:$AI$123,$BM$16),"")>0,IFERROR(INDEX('Dados'!$AI$92:$AI$123,$BM$16),""),""),""),IFERROR(INDEX($DY$116:$DY$153,MATCH($DQ$16&"|2",$Q$116:$Q$153,0))+0,""))) | BA16: =IF(LEN($DQ$16)=0,"",IF($BL$16=1,IFERROR(INDEX('Dados'!$AJ$92:$AJ$123,$BM$16)&"",""),IFERROR(INDEX($DU$116:$DU$153,MATCH($DQ$16&"|3",$Q$116:$Q$153,0))&"",""))) | BB16: =IF(LEN($DQ$16)=0,"",IF($BL$16=1,IF(ISNUMBER(IFERROR(INDEX('Dados'!$AK$92:$AK$123,$BM$16),"")),IF(IFERROR(INDEX('Dados'!$AK$92:$AK$123,$BM$16),"")>0,IFERROR(INDEX('Dados'!$AK$92:$AK$123,$BM$16),""),""),""),IFERROR(INDEX($DY$116:$DY$153,MATCH($DQ$16&"|3",$Q$116:$Q$153,0))+0,""))) | BC16: =IF(LEN($DQ$16)=0,"",IF(LEN($DR$31)>0,$DR$31,IF($BL$16=1,IFERROR(INDEX('Dados'!$E$92:$E$123,$BM$16)&"",""),""))) | BD16: =IF(AND(LEN($DR$31)=0,$BL$16=1),IFERROR(INDEX('Dados'!$AD$92:$AD$123,$BM$16)&"",""),"") | BE16: =IF(LEN($DQ$16)=0,"",INDEX('Dados'!$F$7:$F$11,$BR$16)) | BF16: =IF(LEN($DQ$16)=0,"",$BR$16) | BG16: =$G$47 | BH16: ="Campanha" | BK16: =IF(COUNTIF('Dados'!$AQ$6:$AQ$8,$DR$16)>0,$DR$16,"Faixa do livro") | BL16: =IF(AND($BK$16="Ajustar do bestiário",ISNUMBER($BM$16)),1,0) | BM16: =IFERROR(MATCH($DT$16,'Dados'!$B$92:$B$123,0),"") | BN16: =IF(COUNTIF('Dados'!$AO$6:$AO$8,$DY$16)>0,$DY$16,IF($BL$16=1,IFERROR(INDEX('Dados'!$C$92:$C$123,$BM$16),""),"Comum")) | BO16: =MATCH($BN$16,'Dados'!$AO$6:$AO$8,0) | BP16: =IF(ISNUMBER($DX$16),MIN(20,MAX(1,INT($DX$16))),'Campanha'!$B$17) | BQ16: =IF($BK$16="Por nível — Sugestão",INDEX('Dados'!$B$7:$B$11,INT(($BP$16-1)/4)+1),IF(LEN(IFERROR(INDEX('Dados'!$B$7:$B$11,MATCH($DW$16,'Dados'!$AP$6:$AP$10,0)),""))>0,IFERROR(INDEX('Dados'!$B$7:$B$11,MATCH($DW$16,'Dados'!$AP$6:$AP$10,0)),""),'Campanha'!$B$19)) | BR16: =MATCH($BQ$16,'Dados'!$B$7:$B$11,0) | BS16: =$BQ$16&"|"&$BN$16 | BT16: =MIN(4,MAX(1,INT(($BP$16-3)/4)+1)) | BU16: =IF($BK$16="Por nível — Sugestão",INT(IF($BP$16<=3,INDEX('Dados'!$D$38:$D$52,$BO$16),IF($BP$16>=19,INDEX('Dados'!$D$38:$D$52,12+$BO$16),INDEX('Dados'!$D$38:$D$52,($BT$16-1)*3+$BO$16)+(INDEX('Dados'!$D$38:$D$52,$BT$16*3+$BO$16)-INDEX('Dados'!$D$38:$D$52,($BT$16-1)*3+$BO$16))*($BP$16-(4*$BT$16-1))/4))),IFERROR(INDEX('Dados'!$D$38:$D$52,MATCH($BS$16,'Dados'!$A$38:$A$52,0)),"")) | BV16: =IF($BN$16<>"Boss",1,IF(AND(ISNUMBER($DZ$16),$DZ$16>=1,$DZ$16<=3),INT($DZ$16),IF($BL$16=1,MAX(1,IFERROR(INDEX('Dados'!$F$92:$F$123,$BM$16),"")),1))) | BW16: =IFERROR(INDEX('Dados'!$O$38:$O$52,MATCH($BS$16,'Dados'!$A$38:$A$52,0)),"") | BX16: =IF(AND(LEN($DR$47)=0,LEN($DS$47)=0,LEN($DT$47)=0,LEN($DU$47)=0),1,0) | BY16: =IF(LEN($DQ$16)=0,"",IF($BX$16=0,$DR$47&"",IF($BL$16=1,IFERROR(INDEX('Dados'!$Q$92:$Q$123,$BM$16)&"",""),IF(1<=$BW$16,$CD$16,"")))) | BZ16: =IF(LEN($DQ$16)=0,"",IF($BX$16=0,$DS$47&"",IF($BL$16=1,IFERROR(INDEX('Dados'!$R$92:$R$123,$BM$16)&"",""),IF(2<=$BW$16,$CE$16,"")))) | CA16: =IF(LEN($DQ$16)=0,"",IF($BX$16=0,$DT$47&"",IF($BL$16=1,IFERROR(INDEX('Dados'!$S$92:$S$123,$BM$16)&"",""),IF(3<=$BW$16,$CF$16,"")))) | CB16: =IF(LEN($DQ$16)=0,"",IF($BX$16=0,$DU$47&"",IF($BL$16=1,IFERROR(INDEX('Dados'!$T$92:$T$123,$BM$16)&"",""),IF(4<=$BW$16,$CG$16,"")))) | CC16: =IF(LEN($DV$47)>0,$DV$47,IF($BL$16=1,IFERROR(INDEX('Dados'!$U$92:$U$123,$BM$16)&"",""),"")) | CD16: =INDEX('Dados'!$A$301:$A$307,MATCH(SMALL($DI$16:$DO$16,1),$DI$16:$DO$16,0)) | CE16: =INDEX('Dados'!$A$301:$A$307,MATCH(SMALL($DI$16:$DO$16,2),$DI$16:$DO$16,0)) | CF16: =INDEX('Dados'!$A$301:$A$307,MATCH(SMALL($DI$16:$DO$16,3),$DI$16:$DO$16,0)) | CG16: =INDEX('Dados'!$A$301:$A$307,MATCH(SMALL($DI$16:$DO$16,4),$DI$16:$DO$16,0)) | CH16: =IF($BL$16=1,IFERROR(INDEX('Dados'!$J$92:$J$123,$BM$16),""),"") | CI16: =IF($BL$16=1,IFERROR(INDEX('Dados'!$G$92:$G$123,$BM$16),""),"") | CJ16: =IFERROR(INDEX('Dados'!$S$38:$S$52,MATCH($BS$16,'Dados'!$A$38:$A$52,0)),"") | CK16: =IFERROR(INDEX('Dados'!$T$38:$T$52,MATCH($BS$16,'Dados'!$A$38:$A$52,0)),"") | CL16: =IFERROR(INDEX('Dados'!$J$38:$J$52,MATCH($BQ$16&"|Comum",'Dados'!$A$38:$A$52,0)),"") | CM16: =IFERROR(INDEX('Dados'!$K$38:$K$52,MATCH($BQ$16&"|Comum",'Dados'!$A$38:$A$52,0)),"") | CN16: =MOD(MOD(MOD((MOD('Início'!$E$15+104729*$C$7+80153339,2147483646)+1)*16807,2147483647)*16807,2147483647)*16807,2147483647) | CO16: =MOD(MOD(MOD((MOD(MOD(INT($CN$16/65536)*$CN$16,2147483647)*65536+MOD($CN$16,65536)*$CN$16,2147483647))*16807,2147483647)*16807,2147483647)*16807,2147483647) | CP16: =MOD(MOD(MOD((MOD($CO$16+INT($CO$16/65536)*MOD($CO$16,65536),2147483646)+1)*16807,2147483647)*16807,2147483647)*16807,2147483647) | CQ16: =MOD(MOD(MOD((MOD('Início'!$E$15+104729*$C$7+81453048,2147483646)+1)*16807,2147483647)*16807,2147483647)*16807,2147483647) | CR16: =MOD(MOD(MOD((MOD(MOD(INT($CQ$16/65536)*$CQ$16,2147483647)*65536+MOD($CQ$16,65536)*$CQ$16,2147483647))*16807,2147483647)*16807,2147483647)*16807,2147483647) | CS16: =MOD(MOD(MOD((MOD($CR$16+INT($CR$16/65536)*MOD($CR$16,65536),2147483646)+1)*16807,2147483647)*16807,2147483647)*16807,2147483647) | CT16: =MOD(MOD(MOD((MOD('Início'!$E$15+104729*$C$7+82752757,2147483646)+1)*16807,2147483647)*16807,2147483647)*16807,2147483647) | CU16: =MOD(MOD(MOD((MOD(MOD(INT($CT$16/65536)*$CT$16,2147483647)*65536+MOD($CT$16,65536)*$CT$16,2147483647))*16807,2147483647)*16807,2147483647)*16807,2147483647) | CV16: =MOD(MOD(MOD((MOD($CU$16+INT($CU$16/65536)*MOD($CU$16,65536),2147483646)+1)*16807,2147483647)*16807,2147483647)*16807,2147483647) | CW16: =MOD(MOD(MOD((MOD('Início'!$E$15+104729*$C$7+84052466,2147483646)+1)*16807,2147483647)*16807,2147483647)*16807,2147483647) | CX16: =MOD(MOD(MOD((MOD(MOD(INT($CW$16/65536)*$CW$16,2147483647)*65536+MOD($CW$16,65536)*$CW$16,2147483647))*16807,2147483647)*16807,2147483647)*16807,2147483647) | CY16: =MOD(MOD(MOD((MOD($CX$16+INT($CX$16/65536)*MOD($CX$16,65536),2147483646)+1)*16807,2147483647)*16807,2147483647)*16807,2147483647) | CZ16: =MOD(MOD(MOD((MOD('Início'!$E$15+104729*$C$7+85352175,2147483646)+1)*16807,2147483647)*16807,2147483647)*16807,2147483647) | DA16: =MOD(MOD(MOD((MOD(MOD(INT($CZ$16/65536)*$CZ$16,2147483647)*65536+MOD($CZ$16,65536)*$CZ$16,2147483647))*16807,2147483647)*16807,2147483647)*16807,2147483647) | DB16: =MOD(MOD(MOD((MOD($DA$16+INT($DA$16/65536)*MOD($DA$16,65536),2147483646)+1)*16807,2147483647)*16807,2147483647)*16807,2147483647) | DC16: =MOD(MOD(MOD((MOD('Início'!$E$15+104729*$C$7+86651884,2147483646)+1)*16807,2147483647)*16807,2147483647)*16807,2147483647) | DD16: =MOD(MOD(MOD((MOD(MOD(INT($DC$16/65536)*$DC$16,2147483647)*65536+MOD($DC$16,65536)*$DC$16,2147483647))*16807,2147483647)*16807,2147483647)*16807,2147483647) | DE16: =MOD(MOD(MOD((MOD($DD$16+INT($DD$16/65536)*MOD($DD$16,65536),2147483646)+1)*16807,2147483647)*16807,2147483647)*16807,2147483647) | DF16: =MOD(MOD(MOD((MOD('Início'!$E$15+104729*$C$7+87951593,2147483646)+1)*16807,2147483647)*16807,2147483647)*16807,2147483647) | DG16: =MOD(MOD(MOD((MOD(MOD(INT($DF$16/65536)*$DF$16,2147483647)*65536+MOD($DF$16,65536)*$DF$16,2147483647))*16807,2147483647)*16807,2147483647)*16807,2147483647) | DH16: =MOD(MOD(MOD((MOD($DG$16+INT($DG$16/65536)*MOD($DG$16,65536),2147483646)+1)*16807,2147483647)*16807,2147483647)*16807,2147483647) | DI16: =IF($CC$16="Físico",9000000000,IF(AND('Grupo'!$B$44="Sim",COUNTIF($BY$11:$CB$15,"Físico")=0),0,2147483647))+$CP$16+1/10 | DJ16: =IF($CC$16="Fogo",9000000000,IF(AND('Grupo'!$C$44="Sim",COUNTIF($BY$11:$CB$15,"Fogo")=0),0,2147483647))+$CS$16+2/10 | DK16: =IF($CC$16="Gelo",9000000000,IF(AND('Grupo'!$D$44="Sim",COUNTIF($BY$11:$CB$15,"Gelo")=0),0,2147483647))+$CV$16+3/10 | DL16: =IF($CC$16="Raio",9000000000,IF(AND('Grupo'!$E$44="Sim",COUNTIF($BY$11:$CB$15,"Raio")=0),0,2147483647))+$CY$16+4/10 | DM16: =IF($CC$16="Vento",9000000000,IF(AND('Grupo'!$F$44="Sim",COUNTIF($BY$11:$CB$15,"Vento")=0),0,2147483647))+$DB$16+5/10 | DN16: =IF($CC$16="Quântico",9000000000,IF(AND('Grupo'!$G$44="Sim",COUNTIF($BY$11:$CB$15,"Quântico")=0),0,2147483647))+$DE$16+6/10 | DO16: =IF($CC$16="Imaginário",9000000000,IF(AND('Grupo'!$H$44="Sim",COUNTIF($BY$11:$CB$15,"Imaginário")=0),0,2147483647))+$DH$16+7/10 | DQ16: =IF(ISERROR($A$16),"",IF(ISBLANK($A$16),"",$A$16)) | DR16: =IF(ISERROR($B$16),"",IF(ISBLANK($B$16),"",$B$16)) | DT16: =IF(ISERROR($D$16),"",IF(ISBLANK($D$16),"",$D$16)) | DW16: =IF(ISERROR($G$16),"",IF(ISBLANK($G$16),"",$G$16)) | DX16: =IF(ISERROR($H$16),"",IF(ISBLANK($H$16),"",$H$16)) | DY16: =IF(ISERROR($I$16),"",IF(ISBLANK($I$16),"",$I$16)) | DZ16: =IF(ISERROR($J$16),"",IF(ISBLANK($J$16),"",$J$16)) | EA16: =ISERROR($A$16)*1+ISERROR($B$16)*1+ISERROR($D$16)*1+ISERROR($G$16)*1+ISERROR($H$16)*1+ISERROR($I$16)*1+ISERROR($J$16)*1
